Workbook

Sheet Central Dashboard
A1: FY25-26 | B1: B2C Revenue Tracker
A2: FY26-27
A3: Sno. | B3: Venues | C3: April | D3: May | E3: June | F3: July | G3: August | H3: Sept | I3: Oct | J3: Nov | K3: Dec
A4: 1 | B4: RallyGully I Tirang Sports Arena | Dwarka | C4: ='RallyGully I Sector 10 Dwarka'!B26 -> 256879 | D4: ='RallyGully I Sector 10 Dwarka'!C26 -> 428482 | E4: ='RallyGully I Sector 10 Dwarka'!D26 -> 245541 | F4: ='RallyGully I Sector 10 Dwarka'!E26 -> 260770 | G4: ='RallyGully I Sector 10 Dwarka'!F26 -> 264373 | H4: ='RallyGully I Sector 10 Dwarka'!G26 -> 321329
A5: 2 | B5: RallyGully I The Blue Court | Sec 83 | C5: ='RallyGully | KLJ 83'!B26 -> 183913 | D5: ='RallyGully | KLJ 83'!E26 -> 247268 | E5: ='RallyGully | KLJ 83'!H26 -> 199285 | F5: ='RallyGully | KLJ 83'!K26 -> 245199 | G5: ='RallyGully | KLJ 83'!N26 -> 209847 | H5: ='RallyGully | KLJ 83'!Q26 -> 187469
B6: Pickleball | C6: ='RallyGully | KLJ 83'!C26 -> 97738 | D6: ='RallyGully | KLJ 83'!F26 -> 137540 | E6: ='RallyGully | KLJ 83'!I26 -> 107239 | F6: ='RallyGully | KLJ 83'!L26 -> 133437 | G6: ='RallyGully | KLJ 83'!O26 -> 106073 | H6: ='RallyGully | KLJ 83'!R26 -> 102755
B7: Turf | C7: ='RallyGully | KLJ 83'!D26 -> 85218 | D7: ='RallyGully | KLJ 83'!G26 -> 109728 | E7: ='RallyGully | KLJ 83'!J26 -> 68046 | F7: ='RallyGully | KLJ 83'!M26 -> 67309 | G7: ='RallyGully | KLJ 83'!P26 -> 94374 | H7: ='RallyGully | KLJ 83'!S26 -> 84714
A8: 3 | B8: RallyGully I East of Kailash | C8: ='RallyGully | EOK'!B26 -> 301420 | D8: ='RallyGully | EOK'!C26 -> 350844 | E8: ='RallyGully | EOK'!D26 -> 389200 | F8: ='RallyGully | EOK'!E26 -> 193062 | G8: ='RallyGully | EOK'!F26 -> 208166 | H8: ='RallyGully | EOK'!G26 -> 217526
A9: 4 | B9: RallyGully I Drive or Kick | Dwarka | C9: ='RallyGully | DOK Dwarka'!B26 -> 85355 | D9: ='RallyGully | DOK Dwarka'!C26 -> 132322 | E9: ='RallyGully | DOK Dwarka'!D26 -> 110817 | F9: ='RallyGully | DOK Dwarka'!E26 -> 67760 | G9: ='RallyGully | DOK Dwarka'!F26 -> 64231 | H9: ='RallyGully | DOK Dwarka'!G26 -> 52735
A10: 5 | B10: RallyGully | 1011 | DPSG Palam Vihar | C10: ='RallyGully | DPSG'!B26 -> 95190 | D10: ='RallyGully | DPSG'!C26 -> 157033 | E10: ='RallyGully | DPSG'!D26 -> 117732 | F10: ='RallyGully | DPSG'!E26 -> 68206 | G10: ='RallyGully | DPSG'!F26 -> 62615 | H10: ='RallyGully | DPSG'!G26 -> 49069
A11: 6 | B11: RallyGully I Panchsheel Enclave | C11: ='RallyGully | Panchsheel'!B26 -> 126187 | D11: ='RallyGully | Panchsheel'!C26 -> 119195 | E11: ='RallyGully | Panchsheel'!D26 -> 77734 | F11: ='RallyGully | Panchsheel'!E26 -> 65801 | G11: ='RallyGully | Panchsheel'!F26 -> 38408 | H11: ='RallyGully | Panchsheel'!G26 -> 56821
A12: 7 | B12: RallyGully | Law College Road | C12: ='RallyGully | LCR'!B26 -> 342681 | D12: ='RallyGully | LCR'!C26 -> 423322 | E12: ='RallyGully | LCR'!D26 -> 303555 | F12: ='RallyGully | LCR'!E26 -> 204478 | G12: ='RallyGully | LCR'!F26 -> 215489 | H12: ='RallyGully | LCR'!G26 -> 243227
A13: 8 | B13: RallyGully | Powerplay Park | C13: ='RallyGully | Powerplay'!B26 -> 226511 | D13: ='RallyGully | Powerplay'!F26 -> 252927 | E13: ='RallyGully | Powerplay'!J26 -> 217661 | F13: ='RallyGully | Powerplay'!N26 -> 161820 | G13: ='RallyGully | Powerplay'!R26 -> 141427 | H13: ='RallyGully | Powerplay'!V26 -> 160569
B14: Pickleball | C14: ='RallyGully | Powerplay'!C26 -> 53909 | D14: ='RallyGully | Powerplay'!G26 -> 87588 | E14: ='RallyGully | Powerplay'!K26 -> 45308 | F14: ='RallyGully | Powerplay'!O26 -> 15815 | G14: ='RallyGully | Powerplay'!S26 -> 7477 | H14: ='RallyGully | Powerplay'!W26 -> 12270
B15: Padel | C15: ='RallyGully | Powerplay'!E26 -> 118000 | D15: ='RallyGully | Powerplay'!I26 | E15: ='RallyGully | Powerplay'!M26 -> 118000 | F15: ='RallyGully | Powerplay'!Q26 -> 118000 | G15: ='RallyGully | Powerplay'!U26 -> 118000 | H15: ='RallyGully | Powerplay'!Y26 -> 118000
B16: Turf | C16: ='RallyGully | Powerplay'!D26 -> 51089 | D16: ='RallyGully | Powerplay'!H26 | E16: ='RallyGully | Powerplay'!L26 -> 56803 | F16: ='RallyGully | Powerplay'!P26 -> 28005 | G16: ='RallyGully | Powerplay'!T26 -> 15850 | H16: ='RallyGully | Powerplay'!X26 -> 30299
A17: 9 | B17: Commons | RallyGully x Delhi Padel Collective | C17: ='RallyGully | Commons'!B26 -> 335848 | D17: ='RallyGully | Commons'!F26 -> 563241 | E17: ='RallyGully | Commons'!J26 -> 710647 | F17: ='RallyGully | Commons'!N26 -> 614603 | G17: ='RallyGully | Commons'!R26 -> 619059 | H17: ='RallyGully | Commons'!V26 -> 635389
B18: Pickleball | C18: ='RallyGully | Commons'!C26 -> 35407 | D18: ='RallyGully | Commons'!G26 -> 145200 | E18: ='RallyGully | Commons'!K26 -> 168475 | F18: ='RallyGully | Commons'!O26 -> 75602 | G18: ='RallyGully | Commons'!S26 -> 84704 | H18: ='RallyGully | Commons'!W26 -> 93919
B19: Padel | C19: ='RallyGully | Commons'!E26 -> 88513 | D19: ='RallyGully | Commons'!I26 -> 71832 | E19: ='RallyGully | Commons'!M26 -> 63501 | F19: ='RallyGully | Commons'!Q26 -> 81339 | G19: ='RallyGully | Commons'!U26 -> 87157 | H19: ='RallyGully | Commons'!Y26 -> 99482
B20: Turf | C20: ='RallyGully | Commons'!D26 -> 178734 | D20: ='RallyGully | Commons'!H26 -> 346211 | E20: ='RallyGully | Commons'!L26 -> 474406 | F20: ='RallyGully | Commons'!P26 -> 431310 | G20: ='RallyGully | Commons'!T26 -> 363688 | H20: ='RallyGully | Commons'!X26 -> 426515
A21: 10 | B21: RallyGully I Drive or Kick | Sec 83 | C21: 0 | D21: 0 | E21: ='DOK | 83'!D26 -> 49974 | F21: ='DOK | 83'!E26 -> 91850 | G21: ='DOK | 83'!H26 -> 114611 | H21: ='DOK | 83'!I26 -> 47651
B22: Padel | C22: 0 | D22: 0 | E22: 0 | F22: 0 | G22: 0 | H22: 0
B23: Turf | C23: 0 | D23: 0 | E23: ='DOK | 83'!F21 -> 0 | F23: =F21 -> 91850 | G23: =G21 -> 114611 | H23: =H21 -> 47651
A24: 11 | B24: RallyGully I Chandigarh Sec 37 | C24: 0 | D24: 0 | E24: 0 | F24: 0 | G24: 0 | H24: ='RallyGully | Chd'!B26 -> 20398
A25: 12 | B25: RallyGully I Golf Course EXT. | C25: 0 | D25: 0 | E25: 0 | F25: 0 | G25: 0 | H25: 0
B26: RallyGully I Gandhipath | C26: ='RallyGully | Gandipath Jaipur'!B26 -> 46515 | D26: ='RallyGully | Gandipath Jaipur'!C26 -> 31460 | E26: ='RallyGully | Gandipath Jaipur'!D26 -> 36755 | F26: ='RallyGully | Gandipath Jaipur'!E26 -> 49021 | G26: ='RallyGully | Gandipath Jaipur'!F26 -> 40697
B27: RallyGully I Ambala | C27: 0 | D27: 0 | E27: =Ambala!B26 -> 36986 | F27: =Ambala!C26 -> 73258 | G27: =Ambala!D26 -> 23536
B28: RallyGully I Zirakpur | C28: 0 | D28: 0 | E28: =Zirakpur!B26 -> 5734 | F28: =Zirakpur!C26 -> 5142 | G28: =Zirakpur!D26 -> 2242
B29: Total Gross Revenue | C29: =sum(C4,C5,C8,C9,C10,C11,C12,C26,C13,C17) -> 2000499 | D29: =sum(D4,D5,D8,D9,D10,D11,D12,D26,D13,D17) -> 2706094 | E29: =sum(E4,E5,E8,E9,E10,E11,E12,E26,E13,E17,E21,E27,E28) -> 2501621 | F29: =sum(F4,F5,F8,F9,F10,F11,F12,F26,F13,F17,F21,F27,F28) -> 2100970 | G29: =sum(G4,G5,G8,G9,G10,G11,G12,G26,G13,G17,G21,G27,G28) -> 2004701 | H29: =H4+H5+H8+H9+H10+H11+H12+H13+H17+H21+H24 -> 1992183 | I29: =SUM(I4:I17) -> 0 | J29: =SUM(J4:J17) -> 0 | K29: =SUM(K4:K17) -> 0
B30: Net Revenue Post GST | C30: ='RallyGully I Sector 10 Dwarka'!B28+'RallyGully | KLJ 83'!B28+'RallyGully | EOK'!B28+'RallyGully | DOK Dwarka'!B28+'RallyGully | DPSG'!B28+'RallyGully | Panchsheel'!B28+'RallyGully | LCR'!B28+'RallyGully | Gandipath Jaipur'!B28+'RallyGully | Powerplay'!B28+'RallyGully | Commons'!B28 -> 1695338.1 | D30: ='RallyGully I Sector 10 Dwarka'!C28+'RallyGully | KLJ 83'!E28+'RallyGully | EOK'!C28+'RallyGully | DOK Dwarka'!C28+'RallyGully | DPSG'!C28+'RallyGully | Panchsheel'!C28+'RallyGully | LCR'!C28+'RallyGully | Gandipath Jaipur'!C28+'RallyGully | Powerplay'!F28+'RallyGully | Commons'!F28 -> 2293300 | E30: ='RallyGully I Sector 10 Dwarka'!D28+'RallyGully | KLJ 83'!H28+'RallyGully | EOK'!D28+'RallyGully | DOK Dwarka'!D28+'RallyGully | DPSG'!D28+'RallyGully | Panchsheel'!D28+'RallyGully | LCR'!D28+'RallyGully | Gandipath Jaipur'!D28+'RallyGully | Powerplay'!J28+'RallyGully | Commons'!J28+'DOK | 83'!F28+Ambala!B28+Zirakpur!B28 -> 2120170.3 | F30: ='RallyGully I Sector 10 Dwarka'!E28+'RallyGully | KLJ 83'!K28+'RallyGully | EOK'!E28+'RallyGully | DOK Dwarka'!E28+'RallyGully | DPSG'!E28+'RallyGully | Panchsheel'!E28+'RallyGully | LCR'!E28+'RallyGully | Gandipath Jaipur'!E28+'RallyGully | Powerplay'!N28+'RallyGully | Commons'!N28+'DOK | 83'!G28+Ambala!C28+Zirakpur!C28 -> 1780483.1 | G30: ='RallyGully I Sector 10 Dwarka'!F28+'RallyGully | KLJ 83'!N28+'RallyGully | EOK'!F28+'RallyGully | DOK Dwarka'!F28+'RallyGully | DPSG'!F28+'RallyGully | Panchsheel'!F28+'RallyGully | LCR'!F28+'RallyGully | Gandipath Jaipur'!F28+'RallyGully | Powerplay'!R28+'RallyGully | Commons'!R28+'DOK | 83'!H28+Ambala!D28+Zirakpur!D28 -> 1698899.2 | H30: ='RallyGully I Sector 10 Dwarka'!G28+'RallyGully | KLJ 83'!Q28+'RallyGully | EOK'!G28+'RallyGully | DOK Dwarka'!G28+'RallyGully | DPSG'!G28+'RallyGully | Panchsheel'!G28+'RallyGully | LCR'!G28+'RallyGully | Powerplay'!V28+'RallyGully | Commons'!V28+'DOK | 83'!I28+'RallyGully | Chd'!B28 -> 1688290.7
B33: Verticle Vise | C33: April | D33: May | E33: June | F33: July | G33: August | H33: Sept | I33: Oct | J33: Nov | K33: Dec
B34: Pay & Play | C34: =C35+C41 -> 1404213 | D34: =D35+D41 -> 1954301 | E34: =E35+E41 -> 1646292 | F34: =F35+F41 -> 1445541 | G34: =G35+G41 -> 1064083 | H34: =H35+H41 -> 1160572
B35: Online | C35: =sum(C36:C40) -> 801801 | D35: =sum(D36:D40) -> 1321278 | E35: =sum(E36:E40) -> 961428 | F35: =sum(F36:F40) -> 777870 | G35: =sum(G36:G40) -> 675155 | H35: =sum(H36:H40) -> 756313
B36: District | C36: =sum('RallyGully I Sector 10 Dwarka'!B5,'RallyGully | KLJ 83'!B5,'RallyGully | EOK'!B5,'RallyGully | DOK Dwarka'!B5,'RallyGully | DPSG'!B5,'RallyGully | LCR'!B5,'RallyGully | Gandipath Jaipur'!B5,'RallyGully | Panchsheel'!B5,'RallyGully | Powerplay'!B5,'RallyGully | Commons'!B5) -> 258239 | D36: =sum('RallyGully I Sector 10 Dwarka'!C5,'RallyGully | KLJ 83'!E5,'RallyGully | EOK'!C5,'RallyGully | DOK Dwarka'!C5,'RallyGully | DPSG'!C5,'RallyGully | LCR'!C5,'RallyGully | Gandipath Jaipur'!C5,'RallyGully | Panchsheel'!C5,'RallyGully | Powerplay'!F5,'RallyGully | Commons'!F5) -> 996125 | E36: =sum('RallyGully I Sector 10 Dwarka'!D5,'RallyGully | KLJ 83'!H5,'RallyGully | EOK'!D5,'RallyGully | DOK Dwarka'!D5,'RallyGully | DPSG'!D5,'RallyGully | LCR'!D5,'RallyGully | Gandipath Jaipur'!D5,'RallyGully | Panchsheel'!D5,'RallyGully | Powerplay'!J5,'RallyGully | Commons'!J5+'DOK | 83'!D5+Ambala!B5+Zirakpur!B5) -> 814906 | F36: =sum('RallyGully I Sector 10 Dwarka'!E5,'RallyGully | KLJ 83'!K5,'RallyGully | EOK'!E5,'RallyGully | DOK Dwarka'!E5,'RallyGully | DPSG'!E5,'RallyGully | LCR'!E5,'RallyGully | Gandipath Jaipur'!E5,'RallyGully | Panchsheel'!E5,'RallyGully | Powerplay'!N5,'RallyGully | Commons'!N5+'DOK | 83'!E5+Ambala!C5+Zirakpur!C5) -> 708643 | G36: ='RallyGully I Sector 10 Dwarka'!F5+'RallyGully | KLJ 83'!N5+'RallyGully | EOK'!F5+'RallyGully | DOK Dwarka'!F5+'RallyGully | DPSG'!F5+'RallyGully | Panchsheel'!F5+'RallyGully | LCR'!F5+'RallyGully | Gandipath Jaipur'!F5+'RallyGully | Powerplay'!R5+'RallyGully | Commons'!R5+'DOK | 83'!H5+Ambala!D5+Zirakpur!D5 -> 620378 | H36: ='RallyGully I Sector 10 Dwarka'!G5+'RallyGully | KLJ 83'!Q5+'RallyGully | EOK'!G5+'RallyGully | DOK Dwarka'!G5+'RallyGully | DPSG'!G5+'RallyGully | Panchsheel'!G5+'RallyGully | LCR'!G5+'RallyGully | Powerplay'!V5+'RallyGully | Commons'!V5+'DOK | 83'!I5+'RallyGully | Chd'!B5 -> 688435
B37: Hudle | C37: =sum('RallyGully I Sector 10 Dwarka'!B6,'RallyGully | KLJ 83'!B6,'RallyGully | EOK'!B6,'RallyGully | DOK Dwarka'!B6,'RallyGully | DPSG'!B6,'RallyGully | LCR'!B6,'RallyGully | Gandipath Jaipur'!B6,'RallyGully | Panchsheel'!B6,'RallyGully | Powerplay'!B6,'RallyGully | Commons'!B6) -> 351892 | D37: =sum('RallyGully I Sector 10 Dwarka'!C6,'RallyGully | KLJ 83'!E6,'RallyGully | EOK'!C6,'RallyGully | DOK Dwarka'!C6,'RallyGully | DPSG'!C6,'RallyGully | LCR'!C6,'RallyGully | Gandipath Jaipur'!C6,'RallyGully | Panchsheel'!C6,'RallyGully | Powerplay'!F6,'RallyGully | Commons'!F6) -> 166290 | E37: =sum('RallyGully I Sector 10 Dwarka'!D6,'RallyGully | KLJ 83'!H6,'RallyGully | EOK'!D6,'RallyGully | DOK Dwarka'!D6,'RallyGully | DPSG'!D6,'RallyGully | LCR'!D6,'RallyGully | Gandipath Jaipur'!D6,'RallyGully | Panchsheel'!D6,'RallyGully | Powerplay'!J6,'RallyGully | Commons'!J6+'DOK | 83'!D6+Ambala!B6+Zirakpur!B6) -> 19272 | F37: =sum('RallyGully I Sector 10 Dwarka'!E6,'RallyGully | KLJ 83'!K6,'RallyGully | EOK'!E6,'RallyGully | DOK Dwarka'!E6,'RallyGully | DPSG'!E6,'RallyGully | LCR'!E6,'RallyGully | Gandipath Jaipur'!E6,'RallyGully | Panchsheel'!E6,'RallyGully | Powerplay'!N6,'RallyGully | Commons'!N6+'DOK | 83'!E6+Ambala!C6+Zirakpur!C6) -> 26736 | G37: ='RallyGully I Sector 10 Dwarka'!F6+'RallyGully | KLJ 83'!N6+'RallyGully | EOK'!F6+'RallyGully | DOK Dwarka'!F6+'RallyGully | DPSG'!F6+'RallyGully | Panchsheel'!F6+'RallyGully | LCR'!F6+'RallyGully | Gandipath Jaipur'!F6+'RallyGully | Powerplay'!R6+'RallyGully | Commons'!R6+'DOK | 83'!H6+Ambala!D6+Zirakpur!D6 -> 15641 | H37: ='RallyGully I Sector 10 Dwarka'!G6+'RallyGully | KLJ 83'!Q6+'RallyGully | EOK'!G6+'RallyGully | DOK Dwarka'!G6+'RallyGully | DPSG'!G6+'RallyGully | Panchsheel'!G6+'RallyGully | LCR'!G6+'RallyGully | Powerplay'!V6+'RallyGully | Commons'!V6+'DOK | 83'!I6+'RallyGully | Chd'!B6 -> 10070
B38: Playo | C38: =sum('RallyGully I Sector 10 Dwarka'!B7,'RallyGully | KLJ 83'!B7,'RallyGully | EOK'!B7,'RallyGully | DOK Dwarka'!B7,'RallyGully | DPSG'!B7,'RallyGully | LCR'!B7,'RallyGully | Gandipath Jaipur'!B7,'RallyGully | Panchsheel'!B7,'RallyGully | Powerplay'!B7,'RallyGully | Commons'!B7) -> 107876 | D38: =sum('RallyGully I Sector 10 Dwarka'!C7,'RallyGully | KLJ 83'!E7,'RallyGully | EOK'!C7,'RallyGully | DOK Dwarka'!C7,'RallyGully | DPSG'!C7,'RallyGully | LCR'!C7,'RallyGully | Gandipath Jaipur'!C7,'RallyGully | Panchsheel'!C7,'RallyGully | Powerplay'!F7,'RallyGully | Commons'!F7) -> 103594 | E38: =sum('RallyGully I Sector 10 Dwarka'!D7,'RallyGully | KLJ 83'!H7,'RallyGully | EOK'!D7,'RallyGully | DOK Dwarka'!D7,'RallyGully | DPSG'!D7,'RallyGully | LCR'!D7,'RallyGully | Gandipath Jaipur'!D7,'RallyGully | Panchsheel'!D7,'RallyGully | Powerplay'!J7,'RallyGully | Commons'!J7+'DOK | 83'!D7+Ambala!B7+Zirakpur!B7) -> 84875 | F38: =sum('RallyGully I Sector 10 Dwarka'!E7,'RallyGully | KLJ 83'!K7,'RallyGully | EOK'!E7,'RallyGully | DOK Dwarka'!E7,'RallyGully | DPSG'!E7,'RallyGully | LCR'!E7,'RallyGully | Gandipath Jaipur'!E7,'RallyGully | Panchsheel'!E7,'RallyGully | Powerplay'!N7,'RallyGully | Commons'!N7+'DOK | 83'!E7+Ambala!C7+Zirakpur!C7) -> 27753 | G38: ='RallyGully I Sector 10 Dwarka'!F7+'RallyGully | KLJ 83'!N7+'RallyGully | EOK'!F7+'RallyGully | DOK Dwarka'!F7+'RallyGully | DPSG'!F7+'RallyGully | Panchsheel'!F7+'RallyGully | LCR'!F7+'RallyGully | Gandipath Jaipur'!F7+'RallyGully | Powerplay'!R7+'RallyGully | Commons'!R7+'DOK | 83'!H7+Ambala!D7+Zirakpur!D7 -> 26005 | H38: ='RallyGully I Sector 10 Dwarka'!G7+'RallyGully | KLJ 83'!Q7+'RallyGully | EOK'!G7+'RallyGully | DOK Dwarka'!G7+'RallyGully | DPSG'!G7+'RallyGully | Panchsheel'!G7+'RallyGully | LCR'!G7+'RallyGully | Powerplay'!V7+'RallyGully | Commons'!V7+'DOK | 83'!I7+'RallyGully | Chd'!B7 -> 44730
B39: Khelomore | C39: =SUM('RallyGully I Sector 10 Dwarka'!B8,'RallyGully | KLJ 83'!B8,'RallyGully | EOK'!B8,'RallyGully | DOK Dwarka'!B8,'RallyGully | DPSG'!B8,'RallyGully | LCR'!B8,'RallyGully | Gandipath Jaipur'!B8,'RallyGully | Panchsheel'!B8,'RallyGully | Powerplay'!B8,'RallyGully | Commons'!B8) -> 46888 | D39: =SUM('RallyGully I Sector 10 Dwarka'!C8,'RallyGully | KLJ 83'!E8,'RallyGully | EOK'!C8,'RallyGully | DOK Dwarka'!C8,'RallyGully | DPSG'!C8,'RallyGully | LCR'!C8,'RallyGully | Gandipath Jaipur'!C8,'RallyGully | Panchsheel'!C8,'RallyGully | Powerplay'!F8,'RallyGully | Commons'!F8) -> 41275 | E39: =sum('RallyGully I Sector 10 Dwarka'!D8,'RallyGully | KLJ 83'!H8,'RallyGully | EOK'!D8,'RallyGully | DOK Dwarka'!D8,'RallyGully | DPSG'!D8,'RallyGully | LCR'!D8,'RallyGully | Gandipath Jaipur'!D8,'RallyGully | Panchsheel'!D8,'RallyGully | Powerplay'!J8,'RallyGully | Commons'!J8+'DOK | 83'!D8+Ambala!B8+Zirakpur!B8) -> 35177 | F39: =sum('RallyGully I Sector 10 Dwarka'!E8,'RallyGully | KLJ 83'!K8,'RallyGully | EOK'!E8,'RallyGully | DOK Dwarka'!E8,'RallyGully | DPSG'!E8,'RallyGully | LCR'!E8,'RallyGully | Gandipath Jaipur'!E8,'RallyGully | Panchsheel'!E8,'RallyGully | Powerplay'!N8,'RallyGully | Commons'!N8+'DOK | 83'!E8+Ambala!C8+Zirakpur!C8) -> 14154 | G39: ='RallyGully I Sector 10 Dwarka'!F8+'RallyGully | KLJ 83'!N8+'RallyGully | EOK'!F8+'RallyGully | DOK Dwarka'!F8+'RallyGully | DPSG'!F8+'RallyGully | Panchsheel'!F8+'RallyGully | LCR'!F8+'RallyGully | Gandipath Jaipur'!F8+'RallyGully | Powerplay'!R8+'RallyGully | Commons'!R8+'DOK | 83'!H8+Ambala!D8+Zirakpur!D8 -> 11979 | H39: ='RallyGully I Sector 10 Dwarka'!G8+'RallyGully | KLJ 83'!Q8+'RallyGully | EOK'!G8+'RallyGully | DOK Dwarka'!G8+'RallyGully | DPSG'!G8+'RallyGully | Panchsheel'!G8+'RallyGully | LCR'!G8+'RallyGully | Powerplay'!V8+'RallyGully | Commons'!V8+'DOK | 83'!I8+'RallyGully | Chd'!B8 -> 13078
B40: Zplys | C40: ='RallyGully | Gandipath Jaipur'!B9 -> 36906 | D40: ='RallyGully | Gandipath Jaipur'!C9 -> 13994 | E40: =sum('RallyGully I Sector 10 Dwarka'!D9,'RallyGully | KLJ 83'!H9,'RallyGully | EOK'!D9,'RallyGully | DOK Dwarka'!D9,'RallyGully | DPSG'!D9,'RallyGully | LCR'!D9,'RallyGully | Gandipath Jaipur'!D9,'RallyGully | Panchsheel'!D9,'RallyGully | Powerplay'!J9,'RallyGully | Commons'!J9+'DOK | 83'!D9+Ambala!B9+Zirakpur!B9) -> 7198 | F40: =sum('RallyGully I Sector 10 Dwarka'!E9,'RallyGully | KLJ 83'!K9,'RallyGully | EOK'!E9,'RallyGully | DOK Dwarka'!E9,'RallyGully | DPSG'!E9,'RallyGully | LCR'!E9,'RallyGully | Gandipath Jaipur'!E9,'RallyGully | Panchsheel'!E9,'RallyGully | Powerplay'!N9,'RallyGully | Commons'!N9+'DOK | 83'!E9+Ambala!C9+Zirakpur!C9) -> 584 | G40: ='RallyGully I Sector 10 Dwarka'!F9+'RallyGully | KLJ 83'!N9+'RallyGully | EOK'!F9+'RallyGully | DOK Dwarka'!F9+'RallyGully | DPSG'!F9+'RallyGully | Panchsheel'!F9+'RallyGully | LCR'!F9+'RallyGully | Gandipath Jaipur'!F9+'RallyGully | Powerplay'!R9+'RallyGully | Commons'!R9+'DOK | 83'!H9+Ambala!D9+Zirakpur!D9 -> 1152 | H40: ='RallyGully I Sector 10 Dwarka'!G9+'RallyGully | KLJ 83'!O9+'RallyGully | EOK'!G9+'RallyGully | DOK Dwarka'!G9+'RallyGully | DPSG'!G9+'RallyGully | Panchsheel'!G9+'RallyGully | LCR'!G9+'RallyGully | Gandipath Jaipur'!G9+'RallyGully | Powerplay'!S9+'RallyGully | Commons'!V9+'DOK | 83'!I9+'RallyGully | Chd'!C9 -> 0 | Y40: =sum('RallyGully I Sector 10 Dwarka'!X9,'RallyGully | KLJ 83'!AF9,'RallyGully | EOK'!X9,'RallyGully | DOK Dwarka'!X9,'RallyGully | DPSG'!X9,'RallyGully | LCR'!X9,'RallyGully | Gandipath Jaipur'!T9,'RallyGully | Panchsheel'!X9,'RallyGully | Powerplay'!AG9,'RallyGully | Commons'!AH9+'DOK | 83'!AB9+Ambala!L9+Zirakpur!R9) -> 0
B41: Offline | C41: =sum(C42:C43) -> 602412 | D41: =sum(D42:D43) -> 633023 | E41: =sum(E42:E43) -> 684864 | F41: =sum(F42:F43) -> 667671 | G41: =sum(G42:G43) -> 388928 | H41: =sum(H42:H43) -> 404259
B42: Bookings | C42: =sum('RallyGully I Sector 10 Dwarka'!B11,'RallyGully | KLJ 83'!B11,'RallyGully | EOK'!B11,'RallyGully | DOK Dwarka'!B11,'RallyGully | DPSG'!B11,'RallyGully | LCR'!B11,'RallyGully | Gandipath Jaipur'!B11,'RallyGully | Panchsheel'!B11,'RallyGully | Powerplay'!B11,'RallyGully | Commons'!B11) -> 537112 | D42: =sum('RallyGully I Sector 10 Dwarka'!C11,'RallyGully | KLJ 83'!E11,'RallyGully | EOK'!C11,'RallyGully | DOK Dwarka'!C11,'RallyGully | DPSG'!C11,'RallyGully | LCR'!C11,'RallyGully | Gandipath Jaipur'!C11,'RallyGully | Panchsheel'!C11,'RallyGully | Powerplay'!F11,'RallyGully | Commons'!F11) -> 485023 | E42: =sum('RallyGully I Sector 10 Dwarka'!D11,'RallyGully | KLJ 83'!H11,'RallyGully | EOK'!D11,'RallyGully | DOK Dwarka'!D11,'RallyGully | DPSG'!D11,'RallyGully | LCR'!D11,'RallyGully | Gandipath Jaipur'!D11,'RallyGully | Panchsheel'!D11,'RallyGully | Powerplay'!J11,'RallyGully | Commons'!J11+'DOK | 83'!D11+Ambala!B11+Zirakpur!B11) -> 612084 | F42: =sum('RallyGully I Sector 10 Dwarka'!E11,'RallyGully | KLJ 83'!K11,'RallyGully | EOK'!E11,'RallyGully | DOK Dwarka'!E11,'RallyGully | DPSG'!E11,'RallyGully | LCR'!E11,'RallyGully | Gandipath Jaipur'!E11,'RallyGully | Panchsheel'!E11,'RallyGully | Powerplay'!N11,'RallyGully | Commons'!N11+'DOK | 83'!E11+Ambala!C11+Zirakpur!C11) -> 538071 | G42: ='RallyGully I Sector 10 Dwarka'!F11+'RallyGully | KLJ 83'!N11+'RallyGully | EOK'!F11+'RallyGully | DOK Dwarka'!F11+'RallyGully | DPSG'!F11+'RallyGully | Panchsheel'!F11+'RallyGully | LCR'!F11+'RallyGully | Gandipath Jaipur'!F11+'RallyGully | Powerplay'!R11+'RallyGully | Commons'!R11+'DOK | 83'!H11+Ambala!D11+Zirakpur!D11 -> 321328 | H42: ='RallyGully I Sector 10 Dwarka'!G11+'RallyGully | KLJ 83'!Q11+'RallyGully | EOK'!G11+'RallyGully | DOK Dwarka'!G11+'RallyGully | DPSG'!G11+'RallyGully | Panchsheel'!G11+'RallyGully | LCR'!G11+'RallyGully | Powerplay'!V11+'RallyGully | Commons'!V11+'DOK | 83'!I11+'RallyGully | Chd'!B11 -> 275359
B43: Memberships | C43: =sum('RallyGully I Sector 10 Dwarka'!B12,'RallyGully | KLJ 83'!B12,'RallyGully | EOK'!B12,'RallyGully | DOK Dwarka'!B12,'RallyGully | DPSG'!B12,'RallyGully | LCR'!B12,'RallyGully | Gandipath Jaipur'!B12,'RallyGully | Panchsheel'!B12,'RallyGully | Powerplay'!B12,'RallyGully | Commons'!B12) -> 65300 | D43: =sum('RallyGully I Sector 10 Dwarka'!C12,'RallyGully | KLJ 83'!E12,'RallyGully | EOK'!C12,'RallyGully | DOK Dwarka'!C12,'RallyGully | DPSG'!C12,'RallyGully | LCR'!C12,'RallyGully | Gandipath Jaipur'!C12,'RallyGully | Panchsheel'!C12,'RallyGully | Powerplay'!F12,'RallyGully | Commons'!F12) -> 148000 | E43: =sum('RallyGully I Sector 10 Dwarka'!D12,'RallyGully | KLJ 83'!H12,'RallyGully | EOK'!D12,'RallyGully | DOK Dwarka'!D12,'RallyGully | DPSG'!D12,'RallyGully | LCR'!D12,'RallyGully | Gandipath Jaipur'!D12,'RallyGully | Panchsheel'!D12,'RallyGully | Powerplay'!J12,'RallyGully | Commons'!J12+'DOK | 83'!D12+Ambala!B12+Zirakpur!B12) -> 72780 | F43: =sum('RallyGully I Sector 10 Dwarka'!E12,'RallyGully | KLJ 83'!K12,'RallyGully | EOK'!E12,'RallyGully | DOK Dwarka'!E12,'RallyGully | DPSG'!E12,'RallyGully | LCR'!E12,'RallyGully | Gandipath Jaipur'!E12,'RallyGully | Panchsheel'!E12,'RallyGully | Powerplay'!N12,'RallyGully | Commons'!N12+'DOK | 83'!E12+Ambala!C12+Zirakpur!C12) -> 129600 | G43: ='RallyGully I Sector 10 Dwarka'!F12+'RallyGully | KLJ 83'!N12+'RallyGully | EOK'!F12+'RallyGully | DOK Dwarka'!F12+'RallyGully | DPSG'!F12+'RallyGully | Panchsheel'!F12+'RallyGully | LCR'!F12+'RallyGully | Gandipath Jaipur'!F12+'RallyGully | Powerplay'!R12+'RallyGully | Commons'!R12+'DOK | 83'!H12+Ambala!D12+Zirakpur!D12 -> 67600 | H43: ='RallyGully I Sector 10 Dwarka'!G12+'RallyGully | KLJ 83'!Q12+'RallyGully | EOK'!G12+'RallyGully | DOK Dwarka'!G12+'RallyGully | DPSG'!G12+'RallyGully | Panchsheel'!G12+'RallyGully | LCR'!G12+'RallyGully | Powerplay'!V12+'RallyGully | Commons'!V12+'DOK | 83'!I12+'RallyGully | Chd'!B12 -> 128900
B44: Community | C44: =sum(C45:C47) -> 202186 | D44: =sum(D45:D47) -> 207210 | E44: =sum(E45:E47) -> 202254 | F44: =sum(F45:F47) -> 161922 | G44: =sum(G45:G47) -> 299951 | H44: =sum(H45:H47) -> 235548
B45: Pickup games | C45: =sum('RallyGully I Sector 10 Dwarka'!B14,'RallyGully | KLJ 83'!B14,'RallyGully | EOK'!B14,'RallyGully | DOK Dwarka'!B14,'RallyGully | DPSG'!B14,'RallyGully | LCR'!B14,'RallyGully | Gandipath Jaipur'!B14,'RallyGully | Panchsheel'!B14,'RallyGully | Powerplay'!B14,'RallyGully | Commons'!B14) -> 98794 | D45: =sum('RallyGully I Sector 10 Dwarka'!C14,'RallyGully | KLJ 83'!E14,'RallyGully | EOK'!C14,'RallyGully | DOK Dwarka'!C14,'RallyGully | DPSG'!C14,'RallyGully | LCR'!C14,'RallyGully | Gandipath Jaipur'!C14,'RallyGully | Panchsheel'!C14,'RallyGully | Powerplay'!F14,'RallyGully | Commons'!F14) -> 119100 | E45: =sum('RallyGully I Sector 10 Dwarka'!D14,'RallyGully | KLJ 83'!H14,'RallyGully | EOK'!D14,'RallyGully | DOK Dwarka'!D14,'RallyGully | DPSG'!D14,'RallyGully | LCR'!D14,'RallyGully | Gandipath Jaipur'!D14,'RallyGully | Panchsheel'!D14,'RallyGully | Powerplay'!J14,'RallyGully | Commons'!J14+'DOK | 83'!D14+Ambala!B14+Zirakpur!B14) -> 86440 | F45: =sum('RallyGully I Sector 10 Dwarka'!E14,'RallyGully | KLJ 83'!K14,'RallyGully | EOK'!E14,'RallyGully | DOK Dwarka'!E14,'RallyGully | DPSG'!E14,'RallyGully | LCR'!E14,'RallyGully | Gandipath Jaipur'!E14,'RallyGully | Panchsheel'!E14,'RallyGully | Powerplay'!N14,'RallyGully | Commons'!N14+'DOK | 83'!E14+Ambala!C14+Zirakpur!C14) -> 113989 | G45: ='RallyGully I Sector 10 Dwarka'!F14+'RallyGully | KLJ 83'!N14+'RallyGully | EOK'!F14+'RallyGully | DOK Dwarka'!F14+'RallyGully | DPSG'!F14+'RallyGully | Panchsheel'!F14+'RallyGully | LCR'!F14+'RallyGully | Gandipath Jaipur'!F14+'RallyGully | Powerplay'!R14+'RallyGully | Commons'!R14+'DOK | 83'!H14+Ambala!D14+Zirakpur!D14 -> 110675 | H45: ='RallyGully I Sector 10 Dwarka'!G14+'RallyGully | KLJ 83'!Q14+'RallyGully | EOK'!G14+'RallyGully | DOK Dwarka'!G14+'RallyGully | DPSG'!G14+'RallyGully | Panchsheel'!G14+'RallyGully | LCR'!G14+'RallyGully | Powerplay'!V14+'RallyGully | Commons'!V14+'DOK | 83'!I14+'RallyGully | Chd'!B14 -> 129421
B46: Social Events/Tournaments | C46: =sum('RallyGully I Sector 10 Dwarka'!B15,'RallyGully | KLJ 83'!B15,'RallyGully | EOK'!B15,'RallyGully | DOK Dwarka'!B15,'RallyGully | DPSG'!B15,'RallyGully | LCR'!B15,'RallyGully | Gandipath Jaipur'!B15,'RallyGully | Panchsheel'!B15,'RallyGully | Powerplay'!B15,'RallyGully | Commons'!B15) -> 103392 | D46: =sum('RallyGully I Sector 10 Dwarka'!C15,'RallyGully | KLJ 83'!E15,'RallyGully | EOK'!C15,'RallyGully | DOK Dwarka'!C15,'RallyGully | DPSG'!C15,'RallyGully | LCR'!C15,'RallyGully | Gandipath Jaipur'!C15,'RallyGully | Panchsheel'!C15,'RallyGully | Powerplay'!F15,'RallyGully | Commons'!F15) -> 88110 | E46: =sum('RallyGully I Sector 10 Dwarka'!D15,'RallyGully | KLJ 83'!H15,'RallyGully | EOK'!D15,'RallyGully | DOK Dwarka'!D15,'RallyGully | DPSG'!D15,'RallyGully | LCR'!D15,'RallyGully | Gandipath Jaipur'!D15,'RallyGully | Panchsheel'!D15,'RallyGully | Powerplay'!J15,'RallyGully | Commons'!J15+'DOK | 83'!D15+Ambala!B15+Zirakpur!B15) -> 115814 | F46: =sum('RallyGully I Sector 10 Dwarka'!E15,'RallyGully | KLJ 83'!K15,'RallyGully | EOK'!E15,'RallyGully | DOK Dwarka'!E15,'RallyGully | DPSG'!E15,'RallyGully | LCR'!E15,'RallyGully | Gandipath Jaipur'!E15,'RallyGully | Panchsheel'!E15,'RallyGully | Powerplay'!N15,'RallyGully | Commons'!N15+'DOK | 83'!E15+Ambala!C15+Zirakpur!C15) -> 47933 | G46: ='RallyGully I Sector 10 Dwarka'!F15+'RallyGully | KLJ 83'!N15+'RallyGully | EOK'!F15+'RallyGully | DOK Dwarka'!F15+'RallyGully | DPSG'!F15+'RallyGully | Panchsheel'!F15+'RallyGully | LCR'!F15+'RallyGully | Gandipath Jaipur'!F15+'RallyGully | Powerplay'!R15+'RallyGully | Commons'!R15+'DOK | 83'!H15+Ambala!D15+Zirakpur!D15 -> 92923 | H46: ='RallyGully I Sector 10 Dwarka'!G15+'RallyGully | KLJ 83'!Q15+'RallyGully | EOK'!G15+'RallyGully | DOK Dwarka'!G15+'RallyGully | DPSG'!G15+'RallyGully | Panchsheel'!G15+'RallyGully | LCR'!G15+'RallyGully | Powerplay'!V15+'RallyGully | Commons'!V15+'DOK | 83'!I15+'RallyGully | Chd'!B15 -> 24196
B47: Community Partnershps | C47: 0 | D47: 0 | E47: 0 | F47: 0 | G47: ='RallyGully I Sector 10 Dwarka'!F16+'RallyGully | KLJ 83'!N16+'RallyGully | EOK'!F16+'RallyGully | DOK Dwarka'!F16+'RallyGully | DPSG'!F16+'RallyGully | Panchsheel'!F16+'RallyGully | LCR'!F16+'RallyGully | Gandipath Jaipur'!F16+'RallyGully | Powerplay'!R16+'RallyGully | Commons'!R16+'DOK | 83'!H16+Ambala!D16+Zirakpur!D16 -> 96353 | H47: ='RallyGully I Sector 10 Dwarka'!G16+'RallyGully | KLJ 83'!Q16+'RallyGully | EOK'!G16+'RallyGully | DOK Dwarka'!G16+'RallyGully | DPSG'!G16+'RallyGully | Panchsheel'!G16+'RallyGully | LCR'!G16+'RallyGully | Powerplay'!V16+'RallyGully | Commons'!V16+'DOK | 83'!I16+'RallyGully | Chd'!B16 -> 81931
B48: Academy | C48: =sum('RallyGully I Sector 10 Dwarka'!B17,'RallyGully | KLJ 83'!B17,'RallyGully | EOK'!B17,'RallyGully | DOK Dwarka'!B17,'RallyGully | DPSG'!B17,'RallyGully | LCR'!B17,'RallyGully | Gandipath Jaipur'!B17,'RallyGully | Panchsheel'!B17,'RallyGully | Powerplay'!B17,'RallyGully | Commons'!B17) -> 0 | D48: =sum('RallyGully I Sector 10 Dwarka'!C17,'RallyGully | KLJ 83'!E17,'RallyGully | EOK'!C17,'RallyGully | DOK Dwarka'!C17,'RallyGully | DPSG'!C17,'RallyGully | LCR'!C17,'RallyGully | Gandipath Jaipur'!C17,'RallyGully | Panchsheel'!C17,'RallyGully | Powerplay'!F17,'RallyGully | Commons'!F17) -> 98200 | E48: =sum('RallyGully I Sector 10 Dwarka'!D17,'RallyGully | KLJ 83'!H17,'RallyGully | EOK'!D17,'RallyGully | DOK Dwarka'!D17,'RallyGully | DPSG'!D17,'RallyGully | LCR'!D17,'RallyGully | Gandipath Jaipur'!D17,'RallyGully | Panchsheel'!D17,'RallyGully | Powerplay'!J17,'RallyGully | Commons'!J17+'DOK | 83'!D17+Ambala!B17+Zirakpur!B17) -> 90200 | F48: =sum('RallyGully I Sector 10 Dwarka'!E17,'RallyGully | KLJ 83'!K17,'RallyGully | EOK'!E17,'RallyGully | DOK Dwarka'!E17,'RallyGully | DPSG'!E17,'RallyGully | LCR'!E17,'RallyGully | Gandipath Jaipur'!E17,'RallyGully | Panchsheel'!E17,'RallyGully | Powerplay'!N17,'RallyGully | Commons'!N17+'DOK | 83'!E17+Ambala!C17+Zirakpur!C17) -> 106200 | G48: ='RallyGully I Sector 10 Dwarka'!F17+'RallyGully | KLJ 83'!N17+'RallyGully | EOK'!F17+'RallyGully | DOK Dwarka'!F17+'RallyGully | DPSG'!F17+'RallyGully | Panchsheel'!F17+'RallyGully | LCR'!F17+'RallyGully | Gandipath Jaipur'!F17+'RallyGully | Powerplay'!R17+'RallyGully | Commons'!R17+'DOK | 83'!H17+Ambala!D17+Zirakpur!D17 -> 188600 | H48: ='RallyGully I Sector 10 Dwarka'!G17+'RallyGully | KLJ 83'!Q17+'RallyGully | EOK'!G17+'RallyGully | DOK Dwarka'!G17+'RallyGully | DPSG'!G17+'RallyGully | Panchsheel'!G17+'RallyGully | LCR'!G17+'RallyGully | Powerplay'!V17+'RallyGully | Commons'!V17+'DOK | 83'!I17+'RallyGully | Chd'!B17 -> 115320
B49: B2B | C49: =sum(C50:C51) -> 50560 | D49: =sum(D50:D51) -> 98663 | E49: =sum(E50:E51) -> 202766 | F49: =sum(F50:F51) -> 45810 | G49: =sum(G50:G51) -> 131137 | H49: =sum(H50:H51) -> 169615
B50: Corporate events | C50: =sum('RallyGully I Sector 10 Dwarka'!B19,'RallyGully | KLJ 83'!B19,'RallyGully | EOK'!B19,'RallyGully | DOK Dwarka'!B19,'RallyGully | DPSG'!B19,'RallyGully | LCR'!B19,'RallyGully | Gandipath Jaipur'!B19,'RallyGully | Panchsheel'!B19,'RallyGully | Powerplay'!B19,'RallyGully | Commons'!B19) -> 20560 | D50: =sum('RallyGully I Sector 10 Dwarka'!C19,'RallyGully | KLJ 83'!E19,'RallyGully | EOK'!C19,'RallyGully | DOK Dwarka'!C19,'RallyGully | DPSG'!C19,'RallyGully | LCR'!C19,'RallyGully | Gandipath Jaipur'!C19,'RallyGully | Panchsheel'!C19,'RallyGully | Powerplay'!F19,'RallyGully | Commons'!F19) -> 83663 | E50: =sum('RallyGully I Sector 10 Dwarka'!D19,'RallyGully | KLJ 83'!H19,'RallyGully | EOK'!D19,'RallyGully | DOK Dwarka'!D19,'RallyGully | DPSG'!D19,'RallyGully | LCR'!D19,'RallyGully | Gandipath Jaipur'!D19,'RallyGully | Panchsheel'!D19,'RallyGully | Powerplay'!J19,'RallyGully | Commons'!J19+'DOK | 83'!D19+Ambala!B19+Zirakpur!B19) -> 105880 | F50: =sum('RallyGully I Sector 10 Dwarka'!E19,'RallyGully | KLJ 83'!K19,'RallyGully | EOK'!E19,'RallyGully | DOK Dwarka'!E19,'RallyGully | DPSG'!E19,'RallyGully | LCR'!E19,'RallyGully | Gandipath Jaipur'!E19,'RallyGully | Panchsheel'!E19,'RallyGully | Powerplay'!N19,'RallyGully | Commons'!N19+'DOK | 83'!E19+Ambala!C19+Zirakpur!C19) -> 39810 | G50: ='RallyGully I Sector 10 Dwarka'!F19+'RallyGully | KLJ 83'!N19+'RallyGully | EOK'!F19+'RallyGully | DOK Dwarka'!F19+'RallyGully | DPSG'!F19+'RallyGully | Panchsheel'!F19+'RallyGully | LCR'!F19+'RallyGully | Gandipath Jaipur'!F19+'RallyGully | Powerplay'!R19+'RallyGully | Commons'!R19+'DOK | 83'!H19+Ambala!D19+Zirakpur!D19 -> 131137 | H50: ='RallyGully I Sector 10 Dwarka'!G19+'RallyGully | KLJ 83'!Q19+'RallyGully | EOK'!G19+'RallyGully | DOK Dwarka'!G19+'RallyGully | DPSG'!G19+'RallyGully | Panchsheel'!G19+'RallyGully | LCR'!G19+'RallyGully | Powerplay'!V19+'RallyGully | Commons'!V19+'DOK | 83'!I19+'RallyGully | Chd'!B19 -> 132530
B51: All B2B partnerships | C51: =sum('RallyGully I Sector 10 Dwarka'!B20,'RallyGully | KLJ 83'!B20,'RallyGully | EOK'!B20,'RallyGully | DOK Dwarka'!B20,'RallyGully | DPSG'!B20,'RallyGully | LCR'!B20,'RallyGully | Gandipath Jaipur'!B20,'RallyGully | Panchsheel'!B20,'RallyGully | Powerplay'!B20,'RallyGully | Commons'!B20) -> 30000 | D51: =sum('RallyGully I Sector 10 Dwarka'!C20,'RallyGully | KLJ 83'!E20,'RallyGully | EOK'!C20,'RallyGully | DOK Dwarka'!C20,'RallyGully | DPSG'!C20,'RallyGully | LCR'!C20,'RallyGully | Gandipath Jaipur'!C20,'RallyGully | Panchsheel'!C20,'RallyGully | Powerplay'!F20,'RallyGully | Commons'!F20) -> 15000 | E51: =sum('RallyGully I Sector 10 Dwarka'!D20,'RallyGully | KLJ 83'!H20,'RallyGully | EOK'!D20,'RallyGully | DOK Dwarka'!D20,'RallyGully | DPSG'!D20,'RallyGully | LCR'!D20,'RallyGully | Gandipath Jaipur'!D20,'RallyGully | Panchsheel'!D20,'RallyGully | Powerplay'!J20,'RallyGully | Commons'!J20+'DOK | 83'!D20+Ambala!B20+Zirakpur!B20) -> 96886 | F51: =sum('RallyGully I Sector 10 Dwarka'!E20,'RallyGully | KLJ 83'!K20,'RallyGully | EOK'!E20,'RallyGully | DOK Dwarka'!E20,'RallyGully | DPSG'!E20,'RallyGully | LCR'!E20,'RallyGully | Gandipath Jaipur'!E20,'RallyGully | Panchsheel'!E20,'RallyGully | Powerplay'!N20,'RallyGully | Commons'!N20+'DOK | 83'!E20+Ambala!C20+Zirakpur!C20) -> 6000 | G51: ='RallyGully I Sector 10 Dwarka'!F20+'RallyGully | KLJ 83'!N20+'RallyGully | EOK'!F20+'RallyGully | DOK Dwarka'!F20+'RallyGully | DPSG'!F20+'RallyGully | Panchsheel'!F20+'RallyGully | LCR'!F20+'RallyGully | Gandipath Jaipur'!F20+'RallyGully | Powerplay'!R20+'RallyGully | Commons'!R20+'DOK | 83'!H20+Ambala!D20+Zirakpur!D20 -> 0 | H51: ='RallyGully I Sector 10 Dwarka'!G20+'RallyGully | KLJ 83'!Q20+'RallyGully | EOK'!G20+'RallyGully | DOK Dwarka'!G20+'RallyGully | DPSG'!G20+'RallyGully | Panchsheel'!G20+'RallyGully | LCR'!G20+'RallyGully | Powerplay'!V20+'RallyGully | Commons'!V20+'DOK | 83'!I20+'RallyGully | Chd'!B20 -> 37085
B52: Commerce | C52: =sum(C53:C55) -> 87540 | D52: =sum(D53:D55) -> 91720 | E52: =sum(E53:E55) -> 104109 | F52: =sum(F53:F55) -> 88497 | G52: =sum(G53:G55) -> 75430 | H52: =sum(H53:H55) -> 73128
B53: Product rental | C53: =sum('RallyGully I Sector 10 Dwarka'!B22,'RallyGully | KLJ 83'!B22,'RallyGully | EOK'!B22,'RallyGully | DOK Dwarka'!B22,'RallyGully | DPSG'!B22,'RallyGully | LCR'!B22,'RallyGully | Gandipath Jaipur'!B22,'RallyGully | Panchsheel'!B22,'RallyGully | Powerplay'!B22,'RallyGully | Commons'!B22) -> 82310 | D53: =sum('RallyGully I Sector 10 Dwarka'!C22,'RallyGully | KLJ 83'!E22,'RallyGully | EOK'!C22,'RallyGully | DOK Dwarka'!C22,'RallyGully | DPSG'!C22,'RallyGully | LCR'!C22,'RallyGully | Gandipath Jaipur'!C22,'RallyGully | Panchsheel'!C22,'RallyGully | Powerplay'!F22,'RallyGully | Commons'!F22) -> 85820 | E53: =sum('RallyGully I Sector 10 Dwarka'!D22,'RallyGully | KLJ 83'!H22,'RallyGully | EOK'!D22,'RallyGully | DOK Dwarka'!D22,'RallyGully | DPSG'!D22,'RallyGully | LCR'!D22,'RallyGully | Gandipath Jaipur'!D22,'RallyGully | Panchsheel'!D22,'RallyGully | Powerplay'!J22,'RallyGully | Commons'!J22+'DOK | 83'!D22+Ambala!B22+Zirakpur!B22) -> 91315 | F53: =sum('RallyGully I Sector 10 Dwarka'!E22,'RallyGully | KLJ 83'!K22,'RallyGully | EOK'!E22,'RallyGully | DOK Dwarka'!E22,'RallyGully | DPSG'!E22,'RallyGully | LCR'!E22,'RallyGully | Gandipath Jaipur'!E22,'RallyGully | Panchsheel'!E22,'RallyGully | Powerplay'!N22,'RallyGully | Commons'!N22+'DOK | 83'!E22+Ambala!C22+Zirakpur!C22) -> 62937 | G53: ='RallyGully I Sector 10 Dwarka'!F22+'RallyGully | KLJ 83'!N22+'RallyGully | EOK'!F22+'RallyGully | DOK Dwarka'!F22+'RallyGully | DPSG'!F22+'RallyGully | Panchsheel'!F22+'RallyGully | LCR'!F22+'RallyGully | Gandipath Jaipur'!F22+'RallyGully | Powerplay'!R22+'RallyGully | Commons'!R22+'DOK | 83'!H22+Ambala!D22+Zirakpur!D22 -> 50150 | H53: ='RallyGully I Sector 10 Dwarka'!G22+'RallyGully | KLJ 83'!Q22+'RallyGully | EOK'!G22+'RallyGully | DOK Dwarka'!G22+'RallyGully | DPSG'!G22+'RallyGully | Panchsheel'!G22+'RallyGully | LCR'!G22+'RallyGully | Powerplay'!V22+'RallyGully | Commons'!V22+'DOK | 83'!I22+'RallyGully | Chd'!B22 -> 47340
B54: Product sales | C54: =sum('RallyGully I Sector 10 Dwarka'!B23,'RallyGully | KLJ 83'!B23,'RallyGully | EOK'!B23,'RallyGully | DOK Dwarka'!B23,'RallyGully | DPSG'!B23,'RallyGully | LCR'!B23,'RallyGully | Gandipath Jaipur'!B23,'RallyGully | Panchsheel'!B23,'RallyGully | Powerplay'!B23,'RallyGully | Commons'!B23) -> 0 | D54: =sum('RallyGully I Sector 10 Dwarka'!C23,'RallyGully | KLJ 83'!E23,'RallyGully | EOK'!C23,'RallyGully | DOK Dwarka'!C23,'RallyGully | DPSG'!C23,'RallyGully | LCR'!C23,'RallyGully | Gandipath Jaipur'!C23,'RallyGully | Panchsheel'!C23,'RallyGully | Powerplay'!F23,'RallyGully | Commons'!F23) -> 1200 | E54: =sum('RallyGully I Sector 10 Dwarka'!D23,'RallyGully | KLJ 83'!H23,'RallyGully | EOK'!D23,'RallyGully | DOK Dwarka'!D23,'RallyGully | DPSG'!D23,'RallyGully | LCR'!D23,'RallyGully | Gandipath Jaipur'!D23,'RallyGully | Panchsheel'!D23,'RallyGully | Powerplay'!J23,'RallyGully | Commons'!J23+'DOK | 83'!D23+Ambala!B23+Zirakpur!B23) -> 2399 | F54: =sum('RallyGully I Sector 10 Dwarka'!E23,'RallyGully | KLJ 83'!K23,'RallyGully | EOK'!E23,'RallyGully | DOK Dwarka'!E23,'RallyGully | DPSG'!E23,'RallyGully | LCR'!E23,'RallyGully | Gandipath Jaipur'!E23,'RallyGully | Panchsheel'!E23,'RallyGully | Powerplay'!N23,'RallyGully | Commons'!N23+'DOK | 83'!E23+Ambala!C23+Zirakpur!C23) -> 0 | G54: ='RallyGully I Sector 10 Dwarka'!F23+'RallyGully | KLJ 83'!N23+'RallyGully | EOK'!F23+'RallyGully | DOK Dwarka'!F23+'RallyGully | DPSG'!F23+'RallyGully | Panchsheel'!F23+'RallyGully | LCR'!F23+'RallyGully | Gandipath Jaipur'!F23+'RallyGully | Powerplay'!R23+'RallyGully | Commons'!R23+'DOK | 83'!H23+Ambala!D23+Zirakpur!D23 -> 0 | H54: ='RallyGully I Sector 10 Dwarka'!G23+'RallyGully | KLJ 83'!Q23+'RallyGully | EOK'!G23+'RallyGully | DOK Dwarka'!G23+'RallyGully | DPSG'!G23+'RallyGully | Panchsheel'!G23+'RallyGully | LCR'!G23+'RallyGully | Powerplay'!V23+'RallyGully | Commons'!V23+'DOK | 83'!I23+'RallyGully | Chd'!B23 -> 0
B55: F&B | C55: =sum('RallyGully I Sector 10 Dwarka'!B24,'RallyGully | KLJ 83'!B24,'RallyGully | EOK'!B24,'RallyGully | DOK Dwarka'!B24,'RallyGully | DPSG'!B24,'RallyGully | LCR'!B24,'RallyGully | Gandipath Jaipur'!B24,'RallyGully | Panchsheel'!B24,'RallyGully | Powerplay'!B24,'RallyGully | Commons'!B24) -> 5230 | D55: =sum('RallyGully I Sector 10 Dwarka'!C24,'RallyGully | KLJ 83'!E24,'RallyGully | EOK'!C24,'RallyGully | DOK Dwarka'!C24,'RallyGully | DPSG'!C24,'RallyGully | LCR'!C24,'RallyGully | Gandipath Jaipur'!C24,'RallyGully | Panchsheel'!C24,'RallyGully | Powerplay'!F24,'RallyGully | Commons'!F24) -> 4700 | E55: =sum('RallyGully I Sector 10 Dwarka'!D24,'RallyGully | KLJ 83'!H24,'RallyGully | EOK'!D24,'RallyGully | DOK Dwarka'!D24,'RallyGully | DPSG'!D24,'RallyGully | LCR'!D24,'RallyGully | Gandipath Jaipur'!D24,'RallyGully | Panchsheel'!D24,'RallyGully | Powerplay'!J24,'RallyGully | Commons'!J24+'DOK | 83'!D24+Ambala!B24+Zirakpur!B24) -> 10395 | F55: =sum('RallyGully I Sector 10 Dwarka'!E24,'RallyGully | KLJ 83'!K24,'RallyGully | EOK'!E24,'RallyGully | DOK Dwarka'!E24,'RallyGully | DPSG'!E24,'RallyGully | LCR'!E24,'RallyGully | Gandipath Jaipur'!E24,'RallyGully | Panchsheel'!E24,'RallyGully | Powerplay'!N24,'RallyGully | Commons'!N24+'DOK | 83'!E24+Ambala!C24+Zirakpur!C24) -> 25560 | G55: ='RallyGully I Sector 10 Dwarka'!F24+'RallyGully | KLJ 83'!N24+'RallyGully | EOK'!F24+'RallyGully | DOK Dwarka'!F24+'RallyGully | DPSG'!F24+'RallyGully | Panchsheel'!F24+'RallyGully | LCR'!F24+'RallyGully | Gandipath Jaipur'!F24+'RallyGully | Powerplay'!R24+'RallyGully | Commons'!R24+'DOK | 83'!H24+Ambala!D24+Zirakpur!D24 -> 25280 | H55: ='RallyGully I Sector 10 Dwarka'!G24+'RallyGully | KLJ 83'!Q24+'RallyGully | EOK'!G24+'RallyGully | DOK Dwarka'!G24+'RallyGully | DPSG'!G24+'RallyGully | Panchsheel'!G24+'RallyGully | LCR'!G24+'RallyGully | Powerplay'!V24+'RallyGully | Commons'!V24+'DOK | 83'!I24+'RallyGully | Chd'!B24 -> 25788
B56: Other Income | C56: =sum('RallyGully I Sector 10 Dwarka'!B25,'RallyGully | KLJ 83'!B25,'RallyGully | EOK'!B25,'RallyGully | DOK Dwarka'!B25,'RallyGully | DPSG'!B25,'RallyGully | LCR'!B25,'RallyGully | Gandipath Jaipur'!B25,'RallyGully | Panchsheel'!B25,'RallyGully | Powerplay'!B25,'RallyGully | Commons'!B25) -> 256000 | D56: =sum('RallyGully I Sector 10 Dwarka'!C25,'RallyGully | KLJ 83'!E25,'RallyGully | EOK'!C25,'RallyGully | DOK Dwarka'!C25,'RallyGully | DPSG'!C25,'RallyGully | LCR'!C25,'RallyGully | Gandipath Jaipur'!C25,'RallyGully | Panchsheel'!C25,'RallyGully | Powerplay'!F25,'RallyGully | Commons'!F25) -> 256000 | E56: =sum('RallyGully I Sector 10 Dwarka'!D25,'RallyGully | KLJ 83'!H25,'RallyGully | EOK'!D25,'RallyGully | DOK Dwarka'!D25,'RallyGully | DPSG'!D25,'RallyGully | LCR'!D25,'RallyGully | Gandipath Jaipur'!D25,'RallyGully | Panchsheel'!D25,'RallyGully | Powerplay'!J25,'RallyGully | Commons'!J25+'DOK | 83'!D25+Ambala!B25+Zirakpur!B25) -> 256000 | F56: =sum('RallyGully I Sector 10 Dwarka'!E25,'RallyGully | KLJ 83'!K25,'RallyGully | EOK'!E25,'RallyGully | DOK Dwarka'!E25,'RallyGully | DPSG'!E25,'RallyGully | LCR'!E25,'RallyGully | Gandipath Jaipur'!E25,'RallyGully | Panchsheel'!E25,'RallyGully | Powerplay'!N25,'RallyGully | Commons'!N25+'DOK | 83'!E25+Ambala!C25+Zirakpur!C25) -> 253000 | G56: ='RallyGully I Sector 10 Dwarka'!F25+'RallyGully | KLJ 83'!N25+'RallyGully | EOK'!F25+'RallyGully | DOK Dwarka'!F25+'RallyGully | DPSG'!F25+'RallyGully | Panchsheel'!F25+'RallyGully | LCR'!F25+'RallyGully | Gandipath Jaipur'!F25+'RallyGully | Powerplay'!R25+'RallyGully | Commons'!R25+'DOK | 83'!H25+Ambala!D25+Zirakpur!D25 -> 245500 | H56: ='RallyGully I Sector 10 Dwarka'!G25+'RallyGully | KLJ 83'!Q25+'RallyGully | EOK'!G25+'RallyGully | DOK Dwarka'!G25+'RallyGully | DPSG'!G25+'RallyGully | Panchsheel'!G25+'RallyGully | LCR'!G25+'RallyGully | Powerplay'!V25+'RallyGully | Commons'!V25+'DOK | 83'!I25+'RallyGully | Chd'!B25 -> 238000
B57: Total Gross Revenue | C57: =sum(C34,C44,C48,C49,C52,C56) -> 2000499 | D57: =sum(D34,D44,D48,D49,D52,D56) -> 2706094 | E57: =sum(E34,E44,E48,E49,E52,E56) -> 2501621 | F57: =sum(F34,F44,F48,F49,F52,F56) -> 2100970 | G57: =sum(G34,G44,G48,G49,G52,G56) -> 2004701 | H57: =sum(H34,H44,H48,H49,H52,H56) -> 1992183
F58: =G57+G58 -> 3304701 | G58: =1300000 -> 1300000 | H58: =1128700 -> 1128700 | I58: =H58+H57 -> 3120883
B59: Verticle Vise | C59: April | D59: May | E59: June | F59: July | G59: August | H59: Sept | I59: Oct | J59: Nov | K59: Dec
B60: Pay & Play | C60: =C34/$C$57 -> 0.70193137 | D60: =D34/$D$57 -> 0.72218519 | E60: =E34/$E$57 -> 0.65809009 | F60: =F34/$F$57 -> 0.68803505 | G60: =G34/G57 -> 0.53079387 | H60: =H34/$H$57 -> 0.58256295
B61: Online | C61: =C35/$C$57 -> 0.4008005 | D61: =D35/$D$57 -> 0.4882602 | E61: =E35/$E$57 -> 0.38432201 | F61: =E35/$F$57 -> 0.45761148 | G61: =G35/G57 -> 0.33678588 | H61: =H35/$H$57 -> 0.37964032
B62: District | C62: =C36/$C$57 -> 0.12908729 | D62: =D36/$D$57 -> 0.36810436 | E62: =E36/$E$57 -> 0.32575118 | F62: =F36/$F$57 -> 0.33729325 | G62: =G36/G57 -> 0.30946161 | H62: =H36/$H$57 -> 0.34556815
B63: Hudle | C63: =C37/$C$57 -> 0.17590211 | D63: =D37/$D$57 -> 0.061450194 | E63: =E37/$E$57 -> 0.0077038049 | F63: =F37/$F$57 -> 0.012725551 | G63: =G37/$G$57 -> 0.007802161 | H63: =H37/$H$57 -> 0.0050547565
B64: Playo | C64: =C38/$C$57 -> 0.053924546 | D64: =D38/$D$57 -> 0.038281745 | E64: =E38/$E$57 -> 0.033928001 | F64: =F38/$F$57 -> 0.013209613 | G64: =G38/$G$57 -> 0.012972009 | H64: =H38/$H$57 -> 0.022452757
B65: Khelomore | C65: =C39/$C$57 -> 0.023438152 | D65: =D39/$D$57 -> 0.015252611 | E65: =E39/$E$57 -> 0.014061682 | F65: =F39/$F$57 -> 0.0067368882 | G65: =G39/$G$57 -> 0.0059754547 | H65: =H39/$H$57 -> 0.006564658
B66: Zplys | C66: =C40/$C$57 -> 0.018448397 | D66: =D40/$D$57 -> 0.0051712912 | E66: =E40/$E$57 -> 0.0028773343 | F66: =F40/$F$57 -> 0.00027796684 | G66: =G40/$G$57 -> 0.00057464929 | H66: =H40/$H$57 -> 0
B67: Offline | C67: =C41/$C$57 -> 0.30113087 | D67: =D41/$D$57 -> 0.23392499 | E67: =E41/$E$57 -> 0.27376809 | F67: =F41/$F$57 -> 0.31779178 | G67: =G41/$G$57 -> 0.19400798 | H67: =H41/$H$57 -> 0.20292262
B68: Bookings | C68: =C42/$C$57 -> 0.26848901 | D68: =D42/$D$57 -> 0.17923361 | E68: =E42/$E$57 -> 0.24467495 | F68: =F42/$F$57 -> 0.25610599 | G68: =G42/$G$57 -> 0.16028724 | H68: =H42/$H$57 -> 0.13821973
B69: Memberships | C69: =C43/$C$57 -> 0.032641856 | D69: =D43/$D$57 -> 0.054691374 | E69: =E43/$E$57 -> 0.029093136 | F69: =F43/$F$57 -> 0.061685793 | G69: =G43/$G$57 -> 0.033720739 | H69: =H43/$H$57 -> 0.064702891
B70: Community | C70: =C44/$C$57 -> 0.10106778 | D70: =D44/$D$57 -> 0.076571619 | E70: =E44/$E$57 -> 0.080849177 | F70: =F44/$F$57 -> 0.077070115 | G70: =G44/$G$57 -> 0.14962381 | H70: =H44/$H$57 -> 0.11823613
B71: Pickup games | C71: =C45/$C$57 -> 0.049384679 | D71: =D45/$D$57 -> 0.044011775 | E71: =E45/$E$57 -> 0.034553595 | F71: =F45/$F$57 -> 0.054255415 | G71: =G45/$G$57 -> 0.055207734 | H71: =H45/$H$57 -> 0.064964413
B72: Social Events/Tournaments | C72: =C46/$C$57 -> 0.051683105 | D72: =D46/$D$57 -> 0.032559845 | E72: =E46/$E$57 -> 0.046295582 | F72: =F46/$F$57 -> 0.0228147 | G72: =G46/$G$57 -> 0.046352548 | H72: =H46/$H$57 -> 0.012145471
B73: Community Partnerships | C73: 0 | D73: 0 | E73: 0 | F73: 0 | G73: =G47/$G$57 -> 0.048063527 | H73: =H47/$H$57 -> 0.041126242
B74: Academy | C74: =C48/$C$57 -> 0 | D74: =D48/$D$57 -> 0.036288466 | E74: =E48/$E$57 -> 0.036056621 | F74: =F48/$F$57 -> 0.05054808 | G74: =G48/$G$57 -> 0.094078868 | H74: =H48/$H$57 -> 0.057886248
B75: B2B | C75: =C49/$C$57 -> 0.025273694 | D75: =D49/$D$57 -> 0.036459561 | E75: =E49/$E$57 -> 0.081053845 | F75: =F49/$F$57 -> 0.021804214 | G75: =G49/$G$57 -> 0.065414743 | H75: =H49/$H$57 -> 0.085140271
B76: Corporate events | C76: =C50/$C$57 -> 0.010277436 | D76: =D50/$D$57 -> 0.030916517 | E76: =E50/$E$57 -> 0.042324557 | F76: =F50/$F$57 -> 0.018948391 | G76: =G50/$G$57 -> 0.065414743 | H76: =H50/$H$57 -> 0.066525013
B77: All B2B partnerships | C77: =C51/$C$57 -> 0.014996258 | D77: =D51/$D$57 -> 0.0055430447 | E77: =E51/$E$57 -> 0.038729288 | F77: =F51/$F$57 -> 0.0028558237 | G77: =G51/$G$57 -> 0 | H77: =H51/$H$57 -> 0.018615258
B78: Commerce | C78: =C52/$C$57 -> 0.043759082 | D78: =D52/$D$57 -> 0.033893871 | E78: =E52/$E$57 -> 0.041616616 | F78: =F52/$F$57 -> 0.042121972 | G78: =G52/$G$57 -> 0.037626559 | H78: =H52/$H$57 -> 0.036707471
B79: Product rental | C79: =C53/$C$57 -> 0.041144734 | D79: =D53/$D$57 -> 0.031713606 | E79: =E53/$E$57 -> 0.036502332 | F79: =F53/$F$57 -> 0.029956163 | G79: =G53/$G$57 -> 0.025016199 | H79: =H53/$H$57 -> 0.023762877
B80: Product sales | C80: =C54/$C$57 -> 0 | D80: =D54/$D$57 -> 0.00044344358 | E80: =E54/$E$57 -> 0.0009589782 | F80: =F54/$F$57 -> 0 | G80: =G54/$G$57 -> 0 | H80: =H54/$H$57 -> 0
B81: F&B | C81: =C55/$C$57 -> 0.0026143477 | D81: =D55/$D$57 -> 0.0017368207 | E81: =E55/$E$57 -> 0.0041553057 | F81: =F55/$F$57 -> 0.012165809 | G81: =G55/$G$57 -> 0.012610359 | H81: =H55/$H$57 -> 0.012944594
B82: Other Income | C82: =C56/$C$57 -> 0.12796807 | D82: =D56/$D$57 -> 0.094601296 | E82: =E56/$E$57 -> 0.10233365 | F82: =F56/$F$57 -> 0.12042057 | G82: =G56/$G$57 -> 0.12246215 | H82: =H56/$H$57 -> 0.11946694
B83: Total Gross Revenue | C83: =C57/$C$57 -> 1 | D83: =D57/$D$57 -> 1 | E83: =E57/$E$57 -> 1 | F83: =F57/$F$57 -> 1 | G83: =G57/$G$57 -> 1 | H83: =H57/$H$57 -> 1

Sheet RallyGully I Sector 10 Dwarka
B1: Link | C1: Link | D1: Link | E1: Link | F1: Link | G1: Link
A2: Venues | B2: April | C2: May | D2: June | E2: July | F2: August | G2: Sept | H2: Oct | I2: Nov | J2: Dec
A3: Pay & Play | B3: =sum(B4,B10) -> 120359 | C3: =sum(C4,C10) -> 339577 | D3: =sum(D4,D10) -> 186067 | E3: =sum(E4,E10) -> 174333 | F3: =sum(F4,F10) -> 130433 | G3: =sum(G4,G10) -> 180690
A4: Online | B4: =sum(B5:B9) -> 98039 | C4: =sum(C5:C9) -> 267597 | D4: =sum(D5:D9) -> 122537 | E4: =sum(E5:E9) -> 116989 | F4: =sum(F5:F9) -> 100710 | G4: =sum(G5:G9) -> 149821
A5: District | B5: 50900 | C5: 225063 | D5: 122537 | E5: 116989 | F5: 100710 | G5: 149821
A6: Hudle | B6: 39539 | C6: 42134 | D6: 0 | E6: 0 | F6: 0 | G6: 0
A7: Playo | B7: 4400 | C7: 400 | D7: 0 | E7: 0 | F7: 0 | G7: 0
A8: Khelomore | B8: 3200 | C8: 0 | D8: 0 | E8: 0 | F8: 0 | G8: 0
A9: Zplys | B9: 0 | C9: 0 | D9: 0 | E9: 0 | F9: 0 | G9: 0
A10: Offline | B10: =sum(B11:B12) -> 22320 | C10: =sum(C11:C12) -> 71980 | D10: =sum(D11:D12) -> 63530 | E10: =sum(E11:E12) -> 57344 | F10: =sum(F11:F12) -> 29723 | G10: =sum(G11:G12) -> 30869
A11: Bookings | B11: 22320 | C11: 20780 | D11: 63530 | E11: 57344 | F11: 29723 | G11: 30869
A12: Memberships | B12: 0 | C12: 51200 | D12: 0 | E12: 0 | F12: 0 | G12: 0
A13: Community | B13: =sum(B14:B16) -> 95160 | C13: =sum(C14:C16) -> 64700 | D13: =sum(D14:D16) -> 44484 | E13: =sum(E14:E16) -> 69742 | F13: =sum(F14:F16) -> 111860 | G13: =sum(G14:G16) -> 123004
A14: Pickup games | B14: 26200 | C14: 42200 | D14: 38100 | E14: 45000 | F14: 58050 | G14: 61300
A15: Social Events/Tournaments | B15: 68960 | C15: 22500 | D15: 6384 | E15: 24742 | F15: 8500 | G15: 7984
A16: Community Partnerships | B16: 0 | C16: 0 | D16: 0 | E16: 0 | F16: 45310 | G16: 53720
A17: Academy | B17: 0 | C17: 13000 | D17: 6500 | E17: 6500 | F17: 6500 | G17: 6500
A18: B2B | B18: =sum(B19,B20) -> 30000 | C18: =sum(C19,C20) -> 0 | D18: =sum(D19,D20) -> 0 | E18: =sum(E19,E20) -> 0 | F18: =sum(F19,F20) -> 5950 | G18: =sum(G19,G20) -> 0
A19: Corporate events | B19: 0 | C19: 0 | D19: 0 | E19: 0 | F19: 5950 | G19: 0
A20: All B2B partnerships | B20: 30000 | C20: 0 | D20: 0 | E20: 0 | F20: 0 | G20: 0
A21: Commerce | B21: =sum(B22:B24) -> 11360 | C21: =sum(C22:C24) -> 11205 | D21: =sum(D22:D24) -> 8490 | E21: =sum(E22,E24) -> 10195 | F21: =sum(F22,F24) -> 9630 | G21: =sum(G22:G24) -> 11135
A22: Product rental | B22: 9200 | C22: 9000 | D22: 8250 | E22: 9775 | F22: 7175 | G22: 6850
A23: Product sales | B23: 0 | C23: 0 | D23: 0 | E23: 0 | F23: 0 | G23: 0
A24: F&B | B24: 2160 | C24: 2205 | D24: 240 | E24: 420 | F24: 2455 | G24: 4285
A25: Other Income | B25: 0 | C25: 0 | D25: 0 | E25: 0 | F25: 0 | G25: 0
A26: Total Gross Revenue | B26: =B3+B13+B17+B18+B21+B25 -> 256879 | C26: =C3+C13+C17+C18+C21+C25 -> 428482 | D26: =D3+D13+D17+D18+D21+D25 -> 245541 | E26: =E3+E13+E17+E18+E21+E25 -> 260770 | F26: =F3+F13+F17+F18+F21+F25 -> 264373 | G26: =G3+G13+G17+G18+G21+G25 -> 321329
A27: GST | B27: =B26-(B26/1.18) -> 39184.932 | C27: =C26-(C26/1.18) -> 65361.661 | D27: =D26-(D26/1.18) -> 37455.407 | E27: =E26-(E26/1.18) -> 39778.475 | F27: =F26-(F26/1.18) -> 40328.085 | G27: =G26-(G26/1.18) -> 49016.288
A28: Net Revenue Post GST | B28: =B26-B27 -> 217694.07 | C28: =C26-C27 -> 363120.34 | D28: =D26-D27 -> 208085.59 | E28: =E26-E27 -> 220991.53 | F28: =F26-F27 -> 224044.92 | G28: =G26-G27 -> 272312.71
G29: =G26/1.18 -> 272312.71

Sheet RallyGully | KLJ 83
B1: Link | E1: Link | H1: Link | K1: Link | N1: Link | Q1: Link
A2: Venues | B2: April | C2: Pickleball | D2: Turf | E2: May | F2: Pickleball | G2: Turf | H2: June | I2: Pickleball | J2: Turf | K2: July | L2: Pickleball | M2: Turf | N2: August | O2: Pickleball | P2: Turf | Q2: Sept | R2: Pickleball | S2: Turf | T2: Oct | U2: Nov | V2: Dec
A3: Pay & Play | B3: =sum(B4,B10) -> 173128 | C3: =sum(C4,C10) -> 89513 | D3: =sum(D4,D10) -> 82658 | E3: =sum(E4,E10) -> 240943 | F3: =sum(F4,F10) -> 131215 | G3: =sum(G4,G10) -> 109728 | H3: =sum(H4,H10) -> 195280 | I3: =sum(I4,I10) -> 103234 | ... S3: =sum(S4,S10) -> 82794
A4: Online | B4: =sum(B5:B9) -> 48628 | C4: =sum(C5:C9) -> 29193 | D4: =sum(D5:D9) -> 18478 | E4: =sum(E5:E9) -> 133403 | F4: =sum(F5:F9) -> 70875 | G4: =sum(G5:G9) -> 62528 | H4: =sum(H5:H9) -> 74190 | I4: =sum(I5:I9) -> 47504 | ... S4: =sum(S5:S9) -> 34894
A5: District | B5: 19000 | C5: 13700 | D5: 5300 | E5: 131267 | F5: 70237 | G5: 61030 | H5: 74190 | I5: 47504 | J5: 2686 | K5: 78884 | L5: 25642 | M5: 8789 | N5: 61103 | O5: 38123 | P5: 22980 | Q5: 85044 | R5: 50150 | S5: 34894
A6: Hudle | B6: 25628 | C6: 13893 | D6: 10778 | E6: 2136 | F6: 638 | G6: 1498 | H6: 0 | I6: 0 | J6: 0 | K6: 0 | L6: 0 | M6: 0 | N6: 0 | O6: 0 | P6: 0 | Q6: 0 | R6: 0 | S6: 0
A7: Playo | B7: 3200 | C7: 800 | D7: 2400 | E7: 0 | F7: 0 | G7: 0 | H7: 0 | I7: 0 | J7: 0 | K7: 0 | L7: 0 | M7: 0 | N7: 0 | O7: 0 | P7: 0 | Q7: 0 | R7: 0 | S7: 0
A8: Khelomore | B8: 800 | C8: 800 | D8: 0 | E8: 0 | F8: 0 | G8: 0 | H8: 0 | I8: 0 | J8: 0 | K8: 0 | L8: 0 | M8: 0 | N8: 0 | O8: 0 | P8: 0 | Q8: 0 | R8: 0 | S8: 0
A9: Zplys | B9: 0 | C9: 0 | D9: 0 | E9: 0 | F9: 0 | G9: 0 | H9: 0 | I9: 0 | J9: 0 | K9: 0 | L9: 0 | M9: 0 | N9: 0 | O9: 0 | P9: 0 | Q9: 0 | R9: 0 | S9: 0
A10: Offline | B10: =sum(B11:B12) -> 124500 | C10: =sum(C11:C12) -> 60320 | D10: =sum(D11:D12) -> 64180 | E10: =sum(E11:E12) -> 107540 | F10: =sum(F11:F12) -> 60340 | G10: =sum(G11:G12) -> 47200 | H10: =sum(H11:H12) -> 121090 | I10: =sum(I11:I12) -> 55730 | ... S10: =sum(S11:S12) -> 47900
A11: Bookings | B11: 105700 | C11: 50920 | D11: 54780 | E11: 60740 | F11: 22940 | G11: 37800 | H11: 92290 | I11: 46330 | J11: 45960 | K11: 106685 | L11: 60125 | M11: 46560 | N11: 102734 | O11: 55300 | P11: 47434 | Q11: 63020 | R11: 41320 | S11: 21700
A12: Memberships | B12: 18800 | C12: 9400 | D12: 9400 | E12: 46800 | F12: 37400 | G12: 9400 | H12: 28800 | I12: 9400 | J12: 19400 | K12: 54800 | L12: 45400 | M12: 9400 | N12: 42800 | O12: 12000 | P12: 21400 | Q12: 35600 | R12: 9400 | S12: 26200
A13: Community | B13: =sum(B14:B16) -> 0 | C13: =sum(C14:C15) -> 0 | D13: =sum(D14:D15) -> 0 | E13: =sum(E14:E16) -> 2400 | F13: =sum(F14:F15) -> 2400 | G13: =sum(G14:G15) -> 0 | H13: =sum(H14:H16) -> 480 | I13: =sum(I14:I15) -> 480 | J13: =sum(J14:J15) -> 0 | K13: =sum(K14:K16) -> 1270 | L13: =sum(L14:L16) -> 1270 | M13: =sum(M14:M16) -> 0 | N13: =sum(N14:N16) -> 450 | O13: =sum(O14:O16) -> 450 | P13: =sum(P14:P16) -> 0 | Q13: =sum(Q14:Q16) -> 1710 | R13: =sum(R14:R16) -> 1710 | S13: =sum(S14:S16) -> 0
A14: Pickup games | B14: 0 | C14: 0 | D14: 0 | E14: 2400 | F14: 2400 | G14: 0 | H14: 480 | I14: 480 | J14: 0 | K14: 1270 | L14: 1270 | M14: 0 | N14: 450 | O14: 450 | P14: 0 | Q14: 1710 | R14: 1710 | S14: 0
A15: Social Events/Tournaments | B15: 0 | C15: 0 | D15: 0 | E15: 0 | F15: 0 | G15: 0 | H15: 0 | I15: 0 | J15: 0 | K15: 0 | L15: 0 | M15: 0 | N15: 0 | O15: 0 | P15: 0 | Q15: 0 | R15: 0
A16: Community Partnerships | B16: 0 | E16: 0 | H16: 0 | K16: 0 | L16: 0 | M16: 0 | N16: 0 | O16: 0 | P16: 0 | Q16: 0 | R16: 0 | S16: 0
A17: Academy | B17: 0 | C17: 0 | D17: 0 | E17: 0 | F17: 0 | G17: 0 | H17: 0 | I17: 0 | J17: 0 | K17: 0 | L17: 0 | M17: 0 | N17: 0 | O17: 0 | P17: 0 | Q17: 0 | R17: 0 | S17: 0
A18: B2B | B18: =sum(B19,B20) -> 2560 | C18: =sum(C19,C20) -> 0 | D18: =sum(D19,D20) -> 2560 | E18: =sum(E19,E20) -> 0 | F18: =sum(F19,F20) -> 0 | G18: =sum(G19,G20) -> 0 | H18: =sum(H19,H20) -> 0 | I18: =sum(I19,I20) -> 0 | ... S18: =sum(S19,S20) -> 1920
A19: Corporate events | B19: 2560 | C19: 0 | D19: 2560 | E19: 0 | F19: 0 | G19: 0 | H19: 0 | I19: 0 | J19: 0 | K19: 2560 | L19: 0 | M19: 2560 | N19: 2560 | O19: 0 | P19: 2560 | Q19: 1920 | R19: 0 | S19: 1920
A20: All B2B partnerships | B20: 0 | C20: 0 | D20: 0 | E20: 0 | F20: 0 | G20: 0 | H20: 0 | I20: 0 | J20: 0 | K20: 0 | L20: 0 | M20: 0 | N20: 0 | O20: 0 | P20: 0 | Q20: 0 | R20: 0 | S20: 0
A21: Commerce | B21: =sum(B22:B24) -> 8225 | C21: =sum(C22:C24) -> 8225 | D21: =sum(D22:D24) -> 0 | E21: =sum(E22:E24) -> 3925 | F21: =sum(F22:F24) -> 3925 | G21: =sum(G22:G24) -> 0 | H21: =sum(H22:H24) -> 3525 | I21: =sum(I22:I24) -> 3525 | ... S21: =sum(S22:S24) -> 0
A22: Product rental | B22: 8225 | C22: 8225 | D22: 0 | E22: 3925 | F22: 3925 | G22: 0 | H22: 3525 | I22: 3525 | J22: 0 | K22: 1000 | L22: 1000 | M22: 0 | N22: 200 | O22: 200 | P22: 0 | Q22: 175 | R22: 175 | S22: 0
A23: Product sales | B23: 0 | C23: 0 | D23: 0 | E23: 0 | F23: 0 | G23: 0 | H23: 0 | I23: 0 | J23: 0 | K23: 0 | L23: 0 | M23: 0 | N23: 0 | O23: 0 | P23: 0 | Q23: 0 | R23: 0 | S23: 0
A24: F&B | B24: 0 | C24: 0 | D24: 0 | E24: 0 | F24: 0 | G24: 0 | H24: 0 | I24: 0 | J24: 0 | K24: 0 | L24: 0 | M24: 0 | N24: 0 | O24: 0 | P24: 0 | Q24: 0 | R24: 0 | S24: 0
A25: Other Income | B25: 0 | C25: 0 | D25: 0 | E25: 0 | F25: 0 | G25: 0 | H25: 0 | I25: 0 | J25: 0 | K25: 0 | L25: 0 | M25: 0 | N25: 0 | O25: 0 | P25: 0 | Q25: 0 | R25: 0 | S25: 0
A26: Total Gross Revenue | B26: =B3+B13+B17+B18+B21+B25 -> 183913 | C26: =C3+C13+C17+C18+C21+C25 -> 97738 | D26: =D3+D13+D17+D18+D21+D25 -> 85218 | E26: =E3+E13+E17+E18+E21+E25 -> 247268 | F26: =F3+F13+F17+F18+F21+F25 -> 137540 | G26: =G3+G13+G17+G18+G21+G25 -> 109728 | H26: =H4+H10+H13+H17+H18+H21+H25 -> 199285 | I26: =I4+I10+I13+I17+I18+I21+I25 -> 107239 | J26: =J4+J10+J13+J17+J18+J21+J25 -> 68046 | K26: =K4+K10+K13+K17+K18+K21+K25 -> 245199 | L26: =L4+L10+L13+L17+L18+L21+L25 -> 133437 | M26: =M4+M10+M13+M17+M18+M21+M25 -> 67309 | N26: =N4+N10+N13+N17+N18+N21+N25 -> 209847 | O26: =sum(O3+O13+O17+O18+O21+O25) -> 106073 | P26: =sum(P3+P13+P17+P18+P21+P25) -> 94374 | Q26: =Q4+Q10+Q13+Q17+Q18+Q21+Q25 -> 187469 | R26: =R4+R10+R13+R17+R18+R21+R25 -> 102755 | S26: =S4+S10+S13+S17+S18+S21+S25 -> 84714
A27: GST | B27: =B26-(B26/1.18) -> 28054.525 | C27: =C26-(C26/1.18) -> 14909.186 | D27: =D26-(D26/1.18) -> 12999.356 | E27: =E26-(E26/1.18) -> 37718.847 | F27: =F26-(F26/1.18) -> 20980.678 | G27: =G26-(G26/1.18) -> 16738.169 | H27: =H26-(H26/1.18) -> 30399.407 | K27: =K26-(K26/1.18) -> 37403.237 | N27: =N26-(N26/1.18) -> 32010.559 | Q27: =Q26-(Q26/1.18) -> 28596.966
A28: Net Revenue Post GST | B28: =B26-B27 -> 155858.47 | C28: =C26-C27 -> 82828.814 | D28: =D26-D27 -> 72218.644 | E28: =E26-E27 -> 209549.15 | F28: 13785 | G28: =G26-G27 -> 92989.831 | H28: =H26-H27 -> 168885.59 | K28: =K26-K27 -> 207795.76 | N28: =N26-N27 -> 177836.44 | Q28: =Q26-Q27 -> 158872.03

Sheet RallyGully | EOK
B1: Link | C1: Link | D1: Link | E1: July | F1: Link | G1: Link
A2: Venues | B2: April | C2: May | D2: June | E2: July | F2: August | G2: Sept | H2: Oct | I2: Nov | J2: Dec
A3: Pay & Play | B3: =sum(B4,B10) -> 205658 | C3: =sum(C4,C10) -> 209404 | D3: =sum(D4,D10) -> 185901 | E3: =sum(E4,E10) -> 117914 | F3: =sum(F4,F10) -> 122577 | G3: =sum(G4,G10) -> 138806
A4: Online | B4: =sum(B5:B9) -> 150228 | C4: =sum(C5:C9) -> 179124 | D4: =sum(D5:D9) -> 142976 | E4: =sum(E5:E9) -> 96864 | F4: =sum(F5:F9) -> 112960 | G4: =sum(G5:G9) -> 121236
A5: District | B5: 49400 | C5: 164897 | D5: 142976 | E5: 96864 | F5: 112960 | G5: 121236
A6: Hudle | B6: 98428 | C6: 14227 | D6: 0 | E6: 0 | F6: 0 | G6: 0
A7: Playo | B7: 1200 | C7: 0 | D7: 0 | E7: 0 | F7: 0 | G7: 0
A8: Khelomore | B8: 1200 | C8: 0 | D8: 0 | E8: 0 | F8: 0 | G8: 0
A9: Zplys | B9: 0 | C9: 0 | D9: 0 | E9: 0 | F9: 0 | G9: 0
A10: Offline | B10: =sum(B11:B12) -> 55430 | C10: =sum(C11:C12) -> 30280 | D10: =sum(D11:D12) -> 42925 | E10: =sum(E11:E12) -> 21050 | F10: =sum(F11:F12) -> 9617 | G10: =sum(G11:G12) -> 17570
A11: Bookings | B11: 55430 | C11: 30280 | D11: 42925 | E11: 21050 | F11: 9617 | G11: 17570
A12: Memberships | B12: 0 | C12: 0 | D12: 0 | E12: 0 | F12: 0 | G12: 0
A13: Community | B13: =sum(B14:B16) -> 78727 | C13: =sum(C14:C16) -> 92550 | D13: =sum(D14:D16) -> 134920 | E13: =sum(E14:E16) -> 38148 | F13: =sum(F14:F16) -> 28774 | G13: =sum(G14:G16) -> 42490
A14: Pickup games | B14: 60338 | C14: 61500 | D14: 40300 | E14: 34200 | F14: 18280 | G14: 35500
A15: Social Events/Tournaments | B15: 18389 | C15: 31050 | D15: 94620 | E15: 3948 | F15: 10494 | G15: 6990
A16: Community Partnerships | B16: 0 | C16: 0 | D16: 0 | E16: 0 | F16: 0 | G16: 0
A17: Academy | B17: 0 | C17: 38000 | D17: 28500 | E17: 29500 | F17: 48750 | G17: 3500
A18: B2B | B18: =sum(B19,B20) -> 0 | C18: =sum(C19,C20) -> 0 | D18: =sum(D19,D20) -> 20000 | E18: =sum(E19,E20) -> 0 | F18: =sum(F19,F20) -> 0 | G18: =sum(G19,G20) -> 20970
A19: Corporate events | B19: 0 | C19: 0 | D19: 0 | E19: 0 | F19: 0 | G19: 0
A20: All B2B partnerships | B20: 0 | C20: 0 | D20: 20000 | E20: 0 | F20: 0 | G20: 20970
A21: Commerce | B21: =sum(B22:B24) -> 17035 | C21: =sum(C22:C24) -> 10890 | D21: =sum(D22:D24) -> 19879 | E21: =sum(E22:E24) -> 7500 | F21: =sum(F22:F24) -> 8065 | G21: =sum(G22:G24) -> 11760
A22: Product rental | B22: 14350 | C22: 8500 | D22: 12400 | E22: 3450 | F22: 4000 | G22: 5750
A23: Product sales | B23: 0 | C23: 0 | D23: 2399 | E23: 0 | F23: 0 | G23: 0
A24: F&B | B24: 2685 | C24: 2390 | D24: 5080 | E24: 4050 | F24: 4065 | G24: 6010
A25: Other Income | B25: 0 | C25: 0 | D25: 0 | E25: 0 | F25: 0 | G25: 0
A26: Total Gross Revenue | B26: =B3+B13+B17+B18+B21+B25 -> 301420 | C26: =C3+C13+C17+C18+C21+C25 -> 350844 | D26: =D3+D13+D17+D18+D21+D25 -> 389200 | E26: =E3+E13+E17+E18+E21+E25 -> 193062 | F26: =F3+F13+F17+F18+F21+F25 -> 208166 | G26: =G3+G13+G17+G18+G21+G25 -> 217526
A27: GST | B27: =B26-(B26/1.18) -> 45979.322 | C27: =C26-(C26/1.18) -> 53518.576 | D27: =D26-(D26/1.18) -> 59369.492 | E27: =E26-(E26/1.18) -> 29450.136 | F27: =F26-(F26/1.18) -> 31754.136 | G27: =G26-(G26/1.18) -> 33181.932
A28: Net Revenue Post GST | B28: =B26-B27 -> 255440.68 | C28: =C26-C27 -> 297325.42 | D28: =D26-D27 -> 329830.51 | E28: =E26-E27 -> 163611.86 | F28: =F26-F27 -> 176411.86 | G28: =G26-G27 -> 184344.07
G29: =G26/1.18 -> 184344.07

Sheet RallyGully | DOK Dwarka
B1: Link | C1: Link | D1: Link | E1: Link | F1: Link | G1: Link
A2: Venues | B2: April | C2: May | D2: June | E2: July | F2: August | G2: Sept | H2: Oct | I2: Nov | J2: Dec
A3: Pay & Play | B3: =sum(B4,B10) -> 57505 | C3: =sum(C4,C10) -> 98847 | D3: =sum(D4,D10) -> 83272 | E3: =sum(E4,E10) -> 41860 | F3: =sum(F4,F10) -> 41255 | G3: =sum(G4,G10) -> 26638
A4: Online | B4: =sum(B5:B9) -> 39965 | C4: =sum(C5:C9) -> 82967 | D4: =sum(D5:D9) -> 61998 | E4: =sum(E5:E9) -> 31980 | F4: =sum(F5:F9) -> 32924 | G4: =sum(G5:G9) -> 23148
A5: District | B5: 17925 | C5: 78175 | D5: 61998 | E5: 31980 | F5: 32924 | G5: 23148
A6: Hudle | B6: 16440 | C6: 3192 | D6: 0 | E6: 0 | F6: 0 | G6: 0
A7: Playo | B7: 2400 | C7: 1600 | D7: 0 | E7: 0 | F7: 0 | G7: 0
A8: Khelomore | B8: 3200 | C8: 0 | D8: 0 | E8: 0 | F8: 0 | G8: 0
A9: Zplys | B9: 0 | C9: 0 | D9: 0 | E9: 0 | F9: 0 | G9: 0
A10: Offline | B10: =sum(B11:B12) -> 17540 | C10: =sum(C11:C12) -> 15880 | D10: =sum(D11:D12) -> 21274 | E10: =sum(E11:E12) -> 9880 | F10: =sum(F11:F12) -> 8331 | G10: =sum(G11:G12) -> 3490
A11: Bookings | B11: 17540 | C11: 15880 | D11: 21274 | E11: 9880 | F11: 8331 | G11: 3490
A12: Memberships | B12: 0 | C12: 0 | D12: 0 | E12: 0 | F12: 0 | G12: 0
A13: Community | B13: =sum(B14:B16) -> 5900 | C13: =sum(C14:C16) -> 7600 | D13: =sum(D14:D16) -> 6120 | E13: =sum(E14:E16) -> 5800 | F13: =sum(F14:F16) -> 1476 | G13: =sum(G14:G16) -> 4897
A14: Pickup games | B14: 5900 | C14: 7600 | D14: 6120 | E14: 5800 | F14: 1476 | G14: 4897
A15: Social Events/Tournaments | B15: 0 | C15: 0 | D15: 0 | E15: 0 | F15: 0 | G15: 0
A16: Community Partnerships | B16: 0 | C16: 0 | D16: 0 | E16: 0 | F16: 0 | G16: 0
A17: Academy | B17: 0 | C17: 0 | D17: 0 | E17: 18000 | F17: 18000 | G17: 18000
A18: B2B | B18: =sum(B19,B20) -> 0 | C18: =sum(C19,C20) -> 0 | D18: =sum(D19,D20) -> 0 | E18: =sum(E19,E20) -> 0 | F18: =sum(F19,F20) -> 0 | G18: =sum(G19,G20) -> 0
A19: Corporate events | B19: 0 | C19: 0 | D19: 0 | E19: 0 | F19: 0 | G19: 0
A20: All B2B partnerships | B20: 0 | C20: 0 | D20: 0 | E20: 0 | F20: 0 | G20: 0
A21: Commerce | B21: =sum(B22:B24) -> 3950 | C21: =sum(C22:C24) -> 7875 | D21: =sum(D22:D24) -> 3425 | E21: =sum(E22:E24) -> 2100 | F21: =sum(F22:F24) -> 3500 | G21: =sum(G22:G24) -> 3200
A22: Product rental | B22: 3950 | C22: 7875 | D22: 3425 | E22: 2100 | F22: 3500 | G22: 3200
A23: Product sales | B23: 0 | C23: 0 | D23: 0 | E23: 0 | F23: 0 | G23: 0
A24: F&B | B24: 0 | C24: 0 | D24: 0 | E24: 0 | F24: 0 | G24: 0
A25: Other Income | B25: 18000 | C25: 18000 | D25: 18000 | E25: 0 | F25: 0 | G25: 0
A26: Total Gross Revenue | B26: =B3+B13+B17+B18+B21+B25 -> 85355 | C26: =C3+C13+C17+C18+C21+C25 -> 132322 | D26: =D3+D13+D17+D18+D21+D25 -> 110817 | E26: =E3+E13+E17+E18+E21+E25 -> 67760 | F26: =F3+F13+F17+F18+F21+F25 -> 64231 | G26: =G3+G13+G17+G18+G21+G25 -> 52735
A27: GST | B27: =B26-(B26/1.18) -> 13020.254 | C27: =C26-(C26/1.18) -> 20184.712 | D27: =D26-(D26/1.18) -> 16904.288 | E27: =E26-(E26/1.18) -> 10336.271 | F27: =F26-(F26/1.18) -> 9797.9492 | G27: =G26-(G26/1.18) -> 8044.322
A28: Net Revenue Post GST | B28: =B26-B27 -> 72334.746 | C28: =C26-C27 -> 112137.29 | D28: =D26-D27 -> 93912.712 | E28: =E26-E27 -> 57423.729 | F28: =F26-F27 -> 54433.051 | G28: =G26-G27 -> 44690.678

Sheet RallyGully | DPSG
B1: Link | C1: Link | D1: Link | E1: Link | F1: Link | G1: Link
A2: Venues | B2: April | C2: May | D2: June | E2: July | F2: August | G2: Sept | H2: Oct | I2: Nov | J2: Dec
A3: Pay & Play | B3: =sum(B4,B10) -> 84355 | C3: =sum(C4,C10) -> 142228 | D3: =sum(D4,D10) -> 100617 | E3: =sum(E4,E10) -> 57151 | F3: =sum(F4,F10) -> 52819 | G3: =sum(G4,G10) -> 43289
A4: Online | B4: =sum(B5:B9) -> 33095 | C4: =sum(C5:C9) -> 97228 | D4: =sum(D5:D9) -> 39717 | E4: =sum(E5:E9) -> 36361 | F4: =sum(F5:F9) -> 36495 | G4: =sum(G5:G9) -> 32802
A5: District | B5: 21550 | C5: 93238 | D5: 39717 | E5: 36361 | F5: 36495 | G5: 32802
A6: Hudle | B6: 11545 | C6: 3990 | D6: 0 | E6: 0 | F6: 0 | G6: 0
A7: Playo | B7: 0 | C7: 0 | D7: 0 | E7: 0 | F7: 0 | G7: 0
A8: Khelomore | B8: 0 | C8: 0 | D8: 0 | E8: 0 | F8: 0 | G8: 0
A9: Zplys | B9: 0 | C9: 0 | D9: 0 | E9: 0 | F9: 0 | G9: 0
A10: Offline | B10: =sum(B11:B12) -> 51260 | C10: =sum(C11:C12) -> 45000 | D10: =sum(D11:D12) -> 60900 | E10: =sum(E11:E12) -> 20790 | F10: =sum(F11:F12) -> 16324 | G10: =sum(G11:G12) -> 10487
A11: Bookings | B11: 43760 | C11: 45000 | D11: 60900 | E11: 20790 | F11: 16324 | G11: 10487
A12: Memberships | B12: 7500 | C12: 0 | D12: 0 | E12: 0 | F12: 0 | G12: 0
A13: Community | B13: =sum(B14:B16) -> 3600 | C13: =sum(C14:C16) -> 3600 | D13: =sum(D14:D16) -> 1440 | E13: =sum(E14:E16) -> 6080 | F13: =sum(F14:F16) -> 3476 | G13: =sum(G14:G16) -> 1540
A14: Pickup games | B14: 3600 | C14: 3600 | D14: 1440 | E14: 6080 | F14: 3476 | G14: 1540
A15: Social Events/Tournaments | B15: 0 | C15: 0 | D15: 0 | E15: 0 | F15: 0 | G15: 0
A16: Community Partnerships | B16: 0 | C16: 0 | D16: 0 | E16: 0 | F16: 0 | G16: 0
A17: Academy | B17: 0 | C17: 0 | D17: 5000 | E17: 0 | F17: 0 | G17: 0
A18: B2B | B18: =sum(B19,B20) -> 0 | C18: =sum(C19,C20) -> 0 | D18: =sum(D19,D20) -> 0 | E18: =sum(E19,E20) -> 0 | F18: =sum(F19,F20) -> 0 | G18: =sum(G19,G20) -> 0
A19: Corporate events | B19: 0 | C19: 0 | D19: 0 | E19: 0 | F19: 0 | G19: 0
A20: All B2B partnerships | B20: 0 | C20: 0 | D20: 0 | E20: 0 | F20: 0 | G20: 0
A21: Commerce | B21: =sum(B22:B24) -> 7235 | C21: =sum(C22:C24) -> 11205 | D21: =sum(D22:D24) -> 10675 | E21: =sum(E22:E24) -> 4975 | F21: =sum(F22:F24) -> 6320 | G21: =sum(G22:G24) -> 4240
A22: Product rental | B22: 6850 | C22: 11100 | D22: 10290 | E22: 4800 | F22: 6250 | G22: 4240
A23: Product sales | B23: 0 | C23: 0 | D23: 0 | E23: 0 | F23: 0 | G23: 0
A24: F&B | B24: 385 | C24: 105 | D24: 385 | E24: 175 | F24: 70 | G24: 0
A25: Other Income | B25: 0 | C25: 0 | D25: 0 | E25: 0 | F25: 0 | G25: 0
A26: Total Gross Revenue | B26: =B3+B13+B17+B18+B21+B25 -> 95190 | C26: =C3+C13+C17+C18+C21+C25 -> 157033 | D26: =D3+D13+D17+D18+D21+D25 -> 117732 | E26: =E3+E13+E17+E18+E21+E25 -> 68206 | F26: =F3+F13+F17+F18+F21+F25 -> 62615 | G26: =G3+G13+G17+G18+G21+G25 -> 49069
A27: GST | B27: =B26-(B26/1.18) -> 14520.508 | C27: =C26-(C26/1.18) -> 23954.186 | D27: =D26-(D26/1.18) -> 17959.119 | E27: =E26-(E26/1.18) -> 10404.305 | F27: =F26-(F26/1.18) -> 9551.4407 | G27: =G26-(G26/1.18) -> 7485.1017
A28: Net Revenue Post GST | B28: =B26-B27 -> 80669.492 | C28: =C26-C27 -> 133078.81 | D28: =D26-D27 -> 99772.881 | E28: =E26-E27 -> 57801.695 | F28: =F26-F27 -> 53063.559 | G28: =G26-G27 -> 41583.898

Sheet RallyGully | Panchsheel
B1: Link | C1: Link | D1: Link | E1: Link | F1: Link | G1: Link
A2: Venues | B2: April | C2: May | D2: June | E2: July | F2: August | G2: Sept | H2: Oct | I2: Nov | J2: Dec
A3: Pay & Play | B3: =sum(B4,B10) -> 114996 | C3: =sum(C4,C10) -> 109675 | D3: =sum(D4,D10) -> 72234 | E3: =sum(E4,E10) -> 54301 | F3: =sum(F4,F10) -> 34608 | G3: =sum(G4,G10) -> 53046
A4: Online | B4: =sum(B5:B9) -> 107696 | C4: =sum(C5:C9) -> 96675 | D4: =sum(D5:D9) -> 62834 | E4: =sum(E5:E9) -> 24256 | F4: =sum(F5:F9) -> 31608 | G4: =sum(G5:G9) -> 39546
A5: District | B5: 49100 | C5: 71921 | D5: 62834 | E5: 24256 | F5: 31608 | G5: 39546
A6: Hudle | B6: 54696 | C6: 22954 | D6: 0 | E6: 0 | F6: 0 | G6: 0
A7: Playo | B7: 3900 | C7: 1800 | D7: 0 | E7: 0 | F7: 0 | G7: 0
A8: Khelomore | B8: 0 | C8: 0 | D8: 0 | E8: 0 | F8: 0 | G8: 0
A9: Zplys | B9: 0 | C9: 0 | D9: 0 | E9: 0 | F9: 0 | G9: 0
A10: Offline | B10: =sum(B11:B12) -> 7300 | C10: =sum(C11:C12) -> 13000 | D10: =sum(D11:D12) -> 9400 | E10: =sum(E11:E12) -> 30045 | F10: =sum(F11:F12) -> 3000 | G10: =sum(G11:G12) -> 13500
A11: Bookings | B11: 7300 | C11: 13000 | D11: 9400 | E11: 30045 | F11: 3000 | G11: 500
A12: Memberships | B12: 0 | C12: 0 | D12: 0 | E12: 0 | F12: 0 | G12: 13000
A13: Community | B13: =sum(B14:B16) -> 2756 | C13: =sum(C14:C16) -> 1800 | D13: =sum(D14:D16) -> 0 | E13: =sum(E14:E16) -> 0 | F13: =sum(F14:F16) -> 2450 | G13: =sum(G14:G16) -> 1500
A14: Pickup games | B14: 2756 | C14: 1800 | D14: 0 | E14: 0 | F14: 2450 | G14: 1500
A15: Social Events/Tournaments | B15: 0 | C15: 0 | D15: 0 | E15: 0 | F15: 0 | G15: 0
A16: Community Partnerships | B16: 0 | C16: 0 | D16: 0 | E16: 0 | F16: 0 | G16: 0
A17: Academy | B17: 0 | C17: 0 | D17: 0 | E17: 0 | F17: 0 | G17: 0
A18: B2B | B18: =sum(B19,B20) -> 0 | C18: =sum(C19,C20) -> 0 | D18: =sum(D19,D20) -> 0 | E18: =sum(E19,E20) -> 6000 | F18: =sum(F19,F20) -> 0 | G18: =sum(G19,G20) -> 2000
A19: Corporate events | B19: 0 | C19: 0 | D19: 0 | E19: 0 | F19: 0 | G19: 2000
A20: All B2B partnerships | B20: 0 | C20: 0 | D20: 0 | E20: 6000 | F20: 0 | G20: 0
A21: Commerce | B21: =sum(B22:B24) -> 8435 | C21: =sum(C22:C24) -> 7720 | D21: =sum(D22:D24) -> 5500 | E21: =sum(E22:E24) -> 5500 | F21: =sum(F22:F24) -> 1350 | G21: =sum(G22:G24) -> 275
A22: Product rental | B22: 8435 | C22: 7720 | D22: 5500 | E22: 5500 | F22: 1350 | G22: 275
A23: Product sales | B23: 0 | C23: 0 | D23: 0 | E23: 0 | F23: 0 | G23: 0
A24: F&B | B24: 0 | C24: 0 | D24: 0 | E24: 0 | F24: 0 | G24: 0
A25: Other Income | B25: 0 | C25: 0 | D25: 0 | E25: 0 | F25: 0 | G25: 0
A26: Total Gross Revenue | B26: =B3+B13+B17+B18+B21+B25 -> 126187 | C26: =C3+C13+C17+C18+C21+C25 -> 119195 | D26: =D3+D13+D17+D18+D21+D25 -> 77734 | E26: =E3+E13+E17+E18+E21+E25 -> 65801 | F26: =F3+F13+F17+F18+F21+F25 -> 38408 | G26: =G3+G13+G17+G18+G21+G25 -> 56821
A27: GST | B27: =B26-(B26/1.18) -> 19248.864 | C27: =C26-(C26/1.18) -> 18182.288 | D27: =D26-(D26/1.18) -> 11857.729 | E27: =E26-(E26/1.18) -> 10037.441 | F27: =F26-(F26/1.18) -> 5858.8475 | G27: =G26-(G26/1.18) -> 8667.6102
A28: Net Revenue Post GST | B28: =B26-B27 -> 106938.14 | C28: =C26-C27 -> 101012.71 | D28: =D26-D27 -> 65876.271 | E28: =E26-E27 -> 55763.559 | F28: =F26-F27 -> 32549.153 | G28: =G26-G27 -> 48153.39

Sheet RallyGully | LCR
B1: Link | C1: Link | D1: Link | E1: Link | F1: Link | G1: Link
A2: Venues | B2: April | C2: May | D2: June | E2: July | F2: August | G2: Sept | H2: Oct | I2: Nov | J2: Dec
A3: Pay & Play | B3: =sum(B4,B10) -> 179568 | C3: =sum(C4,C10) -> 283572 | D3: =sum(D4,D10) -> 164155 | E3: =sum(E4,E10) -> 74328 | F3: =sum(F4,F10) -> 82414 | G3: =sum(G4,G10) -> 109927
A4: Online | B4: =sum(B5:B9) -> 78287 | C4: =sum(C5:C9) -> 169817 | D4: =sum(D5:D9) -> 109600 | E4: =sum(E5:E9) -> 59528 | F4: =sum(F5:F9) -> 74519 | G4: =sum(G5:G9) -> 86293
A5: District | B5: 0 | C5: 87543 | D5: 45000 | E5: 42153 | F5: 43069 | G5: 52574
A6: Hudle | B6: 13450 | C6: 19250 | D6: 10500 | E6: 3650 | F6: 12250 | G6: 9370
A7: Playo | B7: 38962 | C7: 38749 | D7: 27850 | E7: 9600 | F7: 9175 | G7: 16025
A8: Khelomore | B8: 25875 | C8: 24275 | D8: 26250 | E8: 4125 | F8: 10025 | G8: 8324
A9: Zplys | B9: 0 | C9: 0 | D9: 0 | E9: 0 | F9: 0 | G9: 0
A10: Offline | B10: =sum(B11:B12) -> 101281 | C10: =sum(C11:C12) -> 113755 | D10: =sum(D11:D12) -> 54555 | E10: =sum(E11:E12) -> 14800 | F10: =sum(F11:F12) -> 7895 | G10: =sum(G11:G12) -> 23634
A11: Bookings | B11: 101281 | C11: 113755 | D11: 54555 | E11: 14800 | F11: 7895 | G11: 23634
A12: Memberships | B12: 0 | C12: 0 | D12: 0 | E12: 0 | F12: 0 | G12: 0
A13: Community | B13: =sum(B14:B16) -> 3588 | C13: =sum(C14:C16) -> 0 | D13: =sum(D14:D16) -> 0 | E13: =sum(E14:E16) -> 0 | F13: =sum(F14:F16) -> 0 | G13: =sum(G14:G16) -> 0
A14: Pickup games | B14: 0 | C14: 0 | D14: 0 | E14: 0 | F14: 0 | G14: 0
A15: Social Events/Tournaments | B15: 3588 | C15: 0 | D15: 0 | E15: 0 | F15: 0 | G15: 0
A16: Community Partnerships | B16: 0 | C16: 0 | D16: 0 | E16: 0 | F16: 0 | G16: 0
A17: Academy | B17: 0 | C17: 0 | D17: 0 | E17: 0 | F17: 0 | G17: 0
A18: B2B | B18: =sum(B19,B20) -> 18000 | C18: =sum(C19,C20) -> 0 | D18: =sum(D19,D20) -> 0 | E18: =sum(E19,E20) -> 0 | F18: =sum(F19,F20) -> 0 | G18: =sum(G19,G20) -> 0
A19: Corporate events | B19: 18000 | C19: 0 | D19: 0 | E19: 0 | F19: 0 | G19: 0
A20: All B2B partnerships | B20: 0 | C20: 0 | D20: 0 | E20: 0 | F20: 0 | G20: 0
A21: Commerce | B21: =sum(B22:B24) -> 21525 | C21: =sum(C22:C24) -> 19750 | D21: =sum(D22:D24) -> 19400 | E21: =sum(E22:E24) -> 10150 | F21: =sum(F22:F24) -> 13075 | G21: =sum(G22:G24) -> 13300
A22: Product rental | B22: 21525 | C22: 19750 | D22: 19400 | E22: 10150 | F22: 13075 | G22: 13300
A23: Product sales | B23: 0 | C23: 0 | D23: 0 | E23: 0 | F23: 0 | G23: 0
A24: F&B | B24: 0 | C24: 0 | D24: 0 | E24: 0 | F24: 0 | G24: 0
A25: Other Income | B25: 120000 | C25: 120000 | D25: 120000 | E25: 120000 | F25: 120000 | G25: 120000
A26: Total Gross Revenue | B26: =B3+B13+B17+B18+B21+B25 -> 342681 | C26: =C3+C13+C17+C18+C21+C25 -> 423322 | D26: =D3+D13+D17+D18+D21+D25 -> 303555 | E26: =E3+E13+E17+E18+E21+E25 -> 204478 | F26: =F3+F13+F17+F18+F21+F25 -> 215489 | G26: =G3+G13+G17+G18+G21+G25 -> 243227
A27: GST | B27: =B26-(B26/1.18) -> 52273.373 | C27: =C26-(C26/1.18) -> 64574.542 | D27: =D26-(D26/1.18) -> 46305 | E27: =E26-(E26/1.18) -> 31191.559 | F27: =F26-(F26/1.18) -> 32871.203 | G27: =G26-(G26/1.18) -> 37102.424
A28: Net Revenue Post GST | B28: =B26-B27 -> 290407.63 | C28: =C26-C27 -> 358747.46 | D28: =D26-D27 -> 257250 | E28: =E26-E27 -> 173286.44 | F28: =F26-F27 -> 182617.8 | G28: =G26-G27 -> 206124.58

Sheet RallyGully | Gandipath Jaipur
B1: Link | C1: Link | D1: Link | E1: Link | F1: Link
A2: Venues | B2: April | C2: May | D2: June | E2: July | F2: August
A3: Pay & Play | B3: =sum(B4,B10) -> 46515 | C3: =sum(C4,C10) -> 31460 | D3: =sum(D4,D10) -> 36755 | E3: =sum(E4,E10) -> 34021 | F3: =sum(F4,F10) -> 33197
A4: Online | B4: =sum(B5:B9) -> 37856 | C4: =sum(C5:C9) -> 22560 | D4: =sum(D5:D9) -> 32255 | E4: =sum(E5:E9) -> 31721 | F4: =sum(F5:F9) -> 31057
A5: District | B5: 0 | C5: 7128 | D5: 23861 | E5: 28546 | F5: 29905
A6: Hudle | B6: 950 | C6: 638 | D6: 1196 | E6: 1993 | F6: 0
A7: Playo | B7: 0 | C7: 800 | D7: 0 | E7: 598 | F7: 0
A8: Khelomore | B8: 0 | C8: 0 | D8: 0 | E8: 0 | F8: 0
A9: Zplys | B9: 36906 | C9: 13994 | D9: 7198 | E9: 584 | F9: 1152
A10: Offline | B10: =sum(B11:B12) -> 8659 | C10: =sum(C11:C12) -> 8900 | D10: =sum(D11:D12) -> 4500 | E10: =sum(E11:E12) -> 2300 | F10: =sum(F11:F12) -> 2140
A11: Bookings | B11: 8659 | C11: 8900 | D11: 4500 | E11: 2300 | F11: 2140
A12: Memberships | B12: 0 | C12: 0 | D12: 0 | E12: 0 | F12: 0
A13: Community | B13: =sum(B14:B16) -> 0 | C13: =sum(C14:C16) -> 0 | D13: =sum(D14:D16) -> 0 | E13: =sum(E14:E16) -> 0 | F13: =sum(F14:F16) -> 0
A14: Pickup games | B14: 0 | C14: 0 | D14: 0 | E14: 0 | F14: 0
A15: Social Events/Tournaments | B15: 0 | C15: 0 | D15: 0 | E15: 0 | F15: 0
A16: Community Partnerships | B16: 0 | C16: 0 | D16: 0 | E16: 0 | F16: 0
A17: Academy | B17: 0 | C17: 0 | D17: 0 | E17: 0 | F17: 0
A18: B2B | B18: =sum(B19,B20) -> 0 | C18: =sum(C19,C20) -> 0 | D18: =sum(D19,D20) -> 0 | E18: =sum(E19,E20) -> 0 | F18: =sum(F19,F20) -> 0
A19: Corporate events | B19: 0 | C19: 0 | D19: 0 | E19: 0 | F19: 0
A20: All B2B partnerships | B20: 0 | C20: 0 | D20: 0 | E20: 0 | F20: 0
A21: Commerce | B21: =sum(B22:B24) -> 0 | C21: =sum(C22:C24) -> 0 | D21: =sum(D22:D24) -> 0 | E21: =sum(E22:E24) -> 0 | F21: =sum(F22:F24) -> 0
A22: Product rental | B22: 0 | C22: 0 | D22: 0 | E22: 0 | F22: 0
A23: Product sales | B23: 0 | C23: 0 | D23: 0 | E23: 0 | F23: 0
A24: F&B | B24: 0 | C24: 0 | D24: 0 | E24: 0 | F24: 0
A25: Other Income | B25: 0 | C25: 0 | D25: 0 | E25: 15000 | F25: 7500
A26: Total Gross Revenue | B26: =B3+B13+B17+B18+B21+B25 -> 46515 | C26: =C3+C13+C17+C18+C21+C25 -> 31460 | D26: =D3+D13+D17+D18+D21+D25 -> 36755 | E26: =E3+E13+E17+E18+E21+E25 -> 49021 | F26: =F3+F13+F17+F18+F21+F25 -> 40697
A27: GST | B27: =B26-(B26/1.18) -> 7095.5085 | C27: =C26-(C26/1.18) -> 4798.9831 | D27: =D26-(D26/1.18) -> 5606.6949 | E27: =E26-(E26/1.18) -> 7477.7797 | F27: =F26-(F26/1.18) -> 6208.0169
A28: Net Revenue Post GST | B28: =B26-B27 -> 39419.492 | C28: =C26-C27 -> 26661.017 | D28: =D26-D27 -> 31148.305 | E28: =E26-E27 -> 41543.22 | F28: =F26-F27 -> 34488.983

Sheet RallyGully | Powerplay
B1: Link | F1: Link | J1: Link | N1: Link | R1: Link | V1: Link
A2: Venues | B2: April | C2: Pickleball | D2: Turf | E2: Padel | F2: May | G2: Pickleball | H2: Turf | I2: Padel | J2: June | K2: Pickleball | L2: Turf | M2: Padel | N2: July | O2: Pickleball | P2: Turf | Q2: Padel | R2: August | S2: Pickleball | T2: Turf | U2: Padel | V2: Sept | W2: Pickleball | X2: Turf | Y2: Padel
A3: Pay & Play | B3: =sum(B4,B10) -> 108511 | C3: =sum(C4,C10) -> 53909 | D3: =sum(D4,D10) -> 51089 | E3: =sum(E4,E10) -> 0 | F3: =sum(F4,F10) -> 134927 | G3: =sum(G4,G10) -> 87588 | H3: =sum(H4,H10) -> 50432 | I3: =sum(I4,I10) -> 0 | ... Y3: =sum(Y4,Y10) -> 0
A4: Online | B4: =sum(B5:B9) -> 63243 | C4: =sum(C5:C9) -> 25859 | D4: =sum(D5:D9) -> 33871 | E4: =sum(E5:E9) -> 0 | F4: =sum(F5:F9) -> 96037 | G4: =sum(G5:G9) -> 59638 | H4: =sum(H5:H9) -> 39492 | I4: =sum(I5:I9) -> 0 | ... Y4: =sum(Y5:Y9) -> 0
A5: District | B5: 0 | C5: 0 | D5: 0 | E5: 0 | F5: 9579 | G5: 5584 | H5: 3995 | I5: 0 | J5: 10819 | K5: 10819 | L5: 0 | M5: 0 | N5: 2946 | O5: 0 | P5: =N5-O5 -> 2946 | Q5: 0 | R5: 1943 | S5: 1943 | T5: 0 | U5: 0 | V5: 2990 | W5: 2990 | X5: 0 | Y5: 0
A6: Hudle | B6: 7457 | C6: 6686 | D6: 771 | E6: 0 | F6: 9213 | G6: 9213 | H6: 0 | I6: 0 | J6: 2240 | K6: 2240 | L6: 0 | M6: 0 | N6: 4400 | O6: 4400 | P6: =N6-O6 -> 0 | Q6: 0 | R6: 700 | S6: 700 | T6: 0 | U6: 0 | V6: 700 | W6: 700 | Y6: 0
A7: Playo | B7: 43173 | C7: 8960 | D7: 30700 | E7: 0 | F7: 60245 | G7: 30241 | H7: 33097 | I7: 0 | J7: 57025 | K7: 13120 | L7: 43905 | M7: 0 | N7: 17555 | O7: 3080 | P7: =N7-O7 -> 14475 | Q7: 0 | R7: 16830 | S7: 1580 | T7: 15150 | U7: 0 | V7: 28705 | W7: 7280 | X7: 21425 | Y7: 0
A8: Khelomore | B8: 12613 | C8: 10213 | D8: 2400 | E8: 0 | F8: 17000 | G8: 14600 | H8: 2400 | I8: 0 | J8: 8927 | K8: 7329 | L8: 1598 | M8: 0 | N8: 10029 | O8: 5235 | P8: =N8-O8 -> 4794 | Q8: 0 | R8: 1954 | S8: 1954 | T8: 0 | U8: 0 | V8: 4754 | W8: 0 | X8: 4754 | Y8: 0
A9: Zplys | B9: 0 | C9: 0 | D9: 0 | E9: 0 | F9: 0 | G9: 0 | H9: 0 | I9: 0 | J9: 0 | K9: 0 | L9: 0 | M9: 0 | N9: 0 | O9: 0 | P9: =N9-O9 -> 0 | Q9: 0 | R9: 0 | S9: 0 | T9: 0 | U9: 0 | V9: 0 | W9: 0 | X9: 0 | Y9: 0
A10: Offline | B10: =sum(B11:B12) -> 45268 | C10: =sum(C11:C12) -> 28050 | D10: =sum(D11:D12) -> 17218 | E10: =sum(E11:E12) -> 0 | F10: =sum(F11:F12) -> 38890 | G10: =sum(G11:G12) -> 27950 | H10: =sum(H11:H12) -> 10940 | I10: =sum(I11:I12) -> 0 | ... Y10: =sum(Y11:Y12) -> 0
A11: Bookings | B11: 45268 | C11: 28050 | D11: 17218 | E11: 0 | F11: 38890 | G11: 27950 | H11: 10940 | I11: 0 | J11: 20650 | K11: 11800 | L11: 11300 | M11: 0 | N11: 8890 | O11: 3100 | P11: =N11-O11 -> 5790 | Q11: 0 | R11: 2000 | S11: 1300 | T11: 700 | U11: 0 | V11: 2700 | W11: 1300 | X11: 1400 | Y11: 0
A12: Memberships | B12: 0 | C12: 0 | D12: 0 | E12: 0 | F12: 0 | G12: 0 | H12: 0 | I12: 0 | J12: 0 | K12: 0 | L12: 0 | M12: 0 | N12: 0 | O12: 0 | P12: 0 | Q12: 0 | R12: 0 | S12: 0 | T12: 0 | U12: 0 | V12: 0 | W12: 0 | X12: 0 | Y12: 0
A13: Community | B13: =sum(B14:B16) -> 0 | C13: =sum(C14:C15) -> 0 | D13: =sum(D14:D15) -> 0 | E13: =sum(E14:E15) -> 0 | F13: =sum(F14:F16) -> 0 | G13: =sum(G14:G15) -> 0 | H13: =sum(H14:H15) -> 0 | I13: =sum(I14:I15) -> 0 | J13: =sum(J14:J16) -> 0 | K13: =sum(K14:K16) -> 0 | L13: =sum(L14:L16) -> 0 | M13: =sum(M14:M16) -> 0 | N13: =sum(N14:N16) -> 0 | O13: =sum(O14:O16) -> 0 | P13: =sum(P14:P16) -> 0 | Q13: =sum(Q14:Q16) -> 0 | R13: =sum(R14:R15) -> 0 | S13: =sum(S14:S15) -> 0 | T13: =sum(T14:T15) -> 0 | U13: =sum(U14:U15) -> 0 | V13: =sum(V14:V16) -> 0 | W13: =sum(W14:W16) -> 0 | X13: =sum(X14:X16) -> 0 | Y13: =sum(Y14:Y16) -> 0
A14: Pickup games | B14: 0 | C14: 0 | D14: 0 | E14: 0 | F14: 0 | G14: 0 | H14: 0 | I14: 0 | J14: 0 | K14: 0 | L14: 0 | M14: 0 | N14: 0 | O14: 0 | P14: 0 | Q14: 0 | R14: 0 | S14: 0 | T14: 0 | U14: 0 | V14: 0 | W14: 0 | X14: 0 | Y14: 0
A15: Social Events/Tournaments | B15: 0 | C15: 0 | D15: 0 | E15: 0 | F15: 0 | G15: 0 | H15: 0 | I15: 0 | J15: 0 | K15: 0 | L15: 0 | M15: 0 | N15: 0 | O15: 0 | P15: 0 | Q15: 0 | R15: 0 | S15: 0 | T15: 0 | U15: 0 | V15: 0 | W15: 0 | X15: 0 | Y15: 0
A16: Community Partnerships | B16: 0 | F16: 0 | J16: 0 | K16: 0 | L16: 0 | M16: 0 | N16: 0 | O16: 0 | P16: 0 | Q16: 0 | R16: 0 | S16: 0 | T16: 0 | U16: 0 | V16: 0 | W16: 0 | X16: 0 | Y16: 0
A17: Academy | B17: 0 | C17: 0 | D17: 0 | E17: 0 | F17: 0 | G17: 0 | H17: 0 | I17: 0 | J17: =J15/1.18 -> 0 | K17: =K15/1.18 -> 0 | L17: =L15/1.18 -> 0 | M17: 0 | N17: =N15/1.18 -> 0 | O17: =O15/1.18 -> 0 | P17: =P15/1.18 -> 0 | Q17: 0 | R17: 0 | S17: 0 | T17: 0 | U17: 0 | V17: 0 | W17: 0 | X17: 0 | Y17: 0
A18: B2B | B18: =sum(B19,B20) -> 0 | C18: =sum(C19,C20) -> 0 | D18: =sum(D19,D20) -> 0 | E18: =sum(E19,E20) -> 0 | F18: =sum(F19,F20) -> 0 | G18: =sum(G19,G20) -> 0 | H18: =sum(H19,H20) -> 0 | I18: =sum(I19,I20) -> 0 | ... V18: =sum(V19,V20) -> 2720 | W18: =sum(W19) -> 0 | X18: =sum(X19) -> 2720 | Y18: 0
A19: Corporate events | B19: 0 | C19: 0 | D19: 0 | E19: 0 | F19: 0 | G19: 0 | H19: 0 | I19: 0 | J19: 0 | K19: 0 | L19: 0 | M19: 0 | N19: 0 | O19: 0 | P19: 0 | Q19: 0 | R19: 0 | S19: 0 | T19: 0 | U19: 0 | V19: 2720 | W19: 0 | X19: 2720 | Y19: 0
A20: All B2B partnerships | B20: 0 | C20: 0 | D20: 0 | E20: 0 | F20: 0 | G20: 0 | H20: 0 | I20: 0 | J20: 0 | K20: 0 | L20: 0 | M20: 0 | N20: 0 | O20: 0 | P20: 0 | Q20: 0 | R20: 0 | S20: 0 | T20: 0 | U20: 0 | V20: 0 | W20: =SUM(W21:W24) -> 0 | X20: 0 | Y20: 0
A21: Commerce | B21: =sum(B22:B24) -> 0 | C21: =sum(C22:C24) -> 0 | D21: =sum(D22:D24) -> 0 | E21: =sum(E22:E24) -> 0 | F21: =sum(F22:F24) -> 0 | G21: =sum(G22:G24) -> 0 | H21: =sum(H22:H24) -> 0 | I21: =sum(I22:I24) -> 0 | ... X21: =sum(X22:X24) -> 0 | Y21: 0
A22: Product rental | B22: 0 | C22: 0 | D22: 0 | E22: 0 | F22: 0 | G22: 0 | H22: 0 | I22: 0 | J22: 0 | K22: 0 | L22: 0 | M22: 0 | N22: 0 | O22: 0 | P22: 0 | Q22: 0 | R22: 0 | S22: 0 | T22: 0 | U22: 0 | V22: 0 | W22: 0 | X22: 0 | Y22: 0
A23: Product sales | B23: 0 | C23: 0 | D23: 0 | E23: 0 | F23: 0 | G23: 0 | H23: 0 | I23: 0 | J23: 0 | K23: 0 | L23: 0 | M23: 0 | N23: 0 | O23: 0 | P23: 0 | Q23: 0 | R23: 0 | S23: 0 | T23: 0 | U23: 0 | V23: 0 | W23: 0 | X23: 0 | Y23: 0
A24: F&B | B24: 0 | C24: 0 | D24: 0 | E24: 0 | F24: 0 | G24: 0 | H24: 0 | I24: 0 | J24: 0 | K24: 0 | L24: 0 | M24: 0 | N24: 0 | O24: 0 | P24: 0 | Q24: 0 | R24: 0 | S24: 0 | T24: 0 | U24: 0 | V24: 0 | W24: 0 | X24: 0 | Y24: 0
A25: Other Income | B25: 118000 | C25: 0 | D25: 0 | E25: 118000 | F25: 118000 | G25: 0 | H25: 0 | I25: 118000 | J25: 118000 | K25: 0 | L25: 0 | M25: 118000 | N25: 118000 | O25: 0 | P25: 0 | Q25: 118000 | R25: 118000 | S25: 0 | T25: 0 | U25: 118000 | V25: 118000 | W25: 0 | X25: 0 | Y25: 118000
A26: Total Gross Revenue | B26: =B3+B13+B17+B18+B21+B25 -> 226511 | C26: =C3+C13+C17+C18+C21+C25 -> 53909 | D26: =D3+D13+D17+D18+D21+D25 -> 51089 | E26: =E3+E13+E17+E18+E21+E25 -> 118000 | F26: =F3+F13+F17+F18+F21+F25 -> 252927 | G26: =G3+G13+G17+G18+G21+G25 -> 87588 | J26: =J3+J13+J17+J18+J21+J25 -> 217661 | K26: =K4+K10+K13+K17+K18+K21+K25 -> 45308 | L26: =L4+L10+L13+L17+L18+L21+L25 -> 56803 | M26: =M4+M10+M13+M17+M18+M21+M25 -> 118000 | N26: =N4+N10+N13+N17+N18+N21+N25 -> 161820 | O26: =O4+O10+O13+O17+O18+O21+O25 -> 15815 | P26: =P4+P10+P13+P17+P18+P21+P25 -> 28005 | Q26: =Q4+Q10+Q13+Q17+Q18+Q21+Q25 -> 118000 | R26: =sum(R3+R13+R17+R18+R21+R25) -> 141427 | S26: =S3+S13+S17+S18+S21+S25 -> 7477 | T26: =T3+T13+T17+T18+T21+T25 -> 15850 | U26: =sum(U3+U13+U17+U18+U21+U25) -> 118000 | V26: =V3+V13+V17+V18+V21+V25 -> 160569 | W26: =W3+W13+W17+W18+W21+W25 -> 12270 | X26: =X3+X13+X17+X18+X21+X25 -> 30299 | Y26: =Y3+Y13+Y17+Y18+Y21+Y25 -> 118000
A27: GST | B27: =B26-(B26/1.18) -> 34552.525 | C27: =C26-(C26/1.18) -> 8223.4068 | D27: =D26-(D26/1.18) -> 7793.2373 | E27: =E26-(E26/1.18) -> 18000 | F27: =F26-(F26/1.18) -> 38582.085 | G27: =G26-(G26/1.18) -> 13360.881 | J27: =J26-(J26/1.18) -> 33202.525 | N27: =N26-(N26/1.18) -> 24684.407 | R27: =R26-(R26/1.18) -> 21573.61 | V27: =V26-(V26/1.18) -> 24493.576
A28: Net Revenue Post GST | B28: =B26-B27 -> 191958.47 | C28: =C26-C27 -> 45685.593 | D28: =D26-D27 -> 43295.763 | E28: =E26-E27 -> 100000 | F28: =F26-F27 -> 214344.92 | G28: =G26-G27 -> 74227.119 | J28: =J26-J27 -> 184458.47 | N28: =N26-N27 -> 137135.59 | R28: =R26-R27 -> 119853.39 | V28: =V26-V27 -> 136075.42

Sheet RallyGully | Commons
B1: Link | F1: Link | J1: Link | N1: Link | R1: Link | V1: Link
A2: Venues | B2: April | C2: Pickleball | D2: Turf | E2: Padel | F2: May | G2: Pickleball | H2: Turf | I2: Padel | J2: June | K2: Pickleball | L2: Turf | M2: Padel | N2: July | O2: Pickleball | P2: Turf | Q2: Padel | R2: August | S2: Pickleball | T2: Turf | U2: Padel | V2: Sept | W2: Pickleball | X2: Turf | Y2: Padel
A3: Pay & Play | B3: =sum(B4,B10) -> 313618 | C3: =sum(C4,C10) -> 31257 | D3: =sum(D4,D10) -> 163556 | E3: =sum(E4,E10) -> 84413 | F3: =sum(F4,F10) -> 363668 | G3: =sum(G4,G10) -> 91770 | H3: =sum(H4,H10) -> 206991 | I3: =sum(I4,I10) -> 64907 | ... Y3: =sum(Y4,Y10) -> 96132
A4: Online | B4: =sum(B5:B9) -> 144764 | C4: =sum(C5:C9) -> 23611 | D4: =sum(D5:D9) -> 99368 | E4: =sum(E5:E9) -> 21785 | F4: =sum(F5:F9) -> 175870 | G4: =sum(G5:G9) -> 63403 | H4: =sum(H5:H9) -> 69443 | I4: =sum(I5:I9) -> 43024 | ... Y4: =sum(Y5:Y9) -> 31077
A5: District | B5: 50364 | C5: 9209 | D5: 28168 | E5: 12987 | F5: 127314 | G5: 51713 | H5: 49356 | I5: 26245 | J5: 211794 | K5: 62484 | L5: 120067 | M5: 29243 | N5: 241822 | O5: 43319 | P5: 74903 | Q5: 42027 | R5: 162125 | S5: 45329 | T5: 89029 | U5: 27767 | V5: 152594 | W5: 40494 | X5: 81023 | Y5: 31077
A6: Hudle | B6: 83759 | C6: 11251 | D6: 63710 | E6: 8798 | F6: 48556 | G6: 11690 | H6: 20087 | I6: 16779 | J6: 0 | K6: 0 | L6: 0 | M6: 0 | N6: 0 | O6: 0 | P6: 0 | Q6: 0 | R6: 0 | S6: 0 | T6: 0 | U6: 0 | V6: 0 | W6: 0 | X6: 0 | Y6: 0
A7: Playo | B7: 10641 | C7: 3151 | D7: 7490 | E7: 0 | F7: 0 | G7: 0 | H7: 0 | I7: 0 | J7: 0 | K7: 0 | L7: 0 | M7: 0 | N7: 0 | O7: 0 | P7: 0 | Q7: 0 | R7: 0 | S7: 0 | T7: 0 | U7: 0 | V7: 0 | W7: 0 | X7: 0 | Y7: 0
A8: Khelomore | B8: 0 | C8: 0 | D8: 0 | E8: 0 | F8: 0 | G8: 0 | H8: 0 | I8: 0 | J8: 0 | K8: 0 | L8: 0 | M8: 0 | N8: 0 | O8: 0 | P8: 0 | Q8: 0 | R8: 0 | S8: 0 | T8: 0 | U8: 0 | V8: 0 | W8: 0 | X8: 0 | Y8: 0
A9: Zplys | B9: 0 | C9: 0 | D9: 0 | E9: 0 | F9: 0 | G9: 0 | H9: 0 | I9: 0 | J9: 0 | K9: 0 | L9: 0 | M9: 0 | N9: 0 | O9: 0 | P9: 0 | Q9: 0 | R9: 0 | S9: 0 | T9: 0 | U9: 0 | V9: 0 | W9: 0 | X9: 0 | Y9: 0
A10: Offline | B10: =sum(B11:B12) -> 168854 | C10: =sum(C11:C12) -> 7646 | D10: =sum(D11:D12) -> 64188 | E10: =sum(E11:E12) -> 62628 | F10: =sum(F11:F12) -> 187798 | G10: =sum(G11:G12) -> 28367 | H10: =sum(H11:H12) -> 137548 | I10: =sum(I11:I12) -> 21883 | ... Y10: =sum(Y11:Y12) -> 65055
A11: Bookings | B11: 129854 | C11: 7646 | D11: 25188 | E11: 62628 | F11: 137798 | G11: 28367 | H11: 87548 | I11: 21883 | J11: 184716 | K11: 29701 | L11: 127307 | M11: 27708 | N11: 162172 | O11: 16094 | P11: 111578 | Q11: 34500 | R11: 97294 | S11: 12520 | T11: 28989 | U11: 54115 | V11: 109494 | W11: 31283 | X11: 13156 | Y11: 65055
A12: Memberships | B12: 39000 | C12: 0 | D12: 39000 | E12: 0 | F12: 50000 | G12: 0 | H12: 50000 | I12: 0 | J12: 43980 | K12: 0 | L12: 43980 | M12: 0 | N12: 74800 | O12: 0 | P12: 74800 | Q12: 0 | R12: 24800 | S12: 0 | T12: 24800 | U12: 0 | V12: 74800 | W12: 0 | X12: 74800 | Y12: 0
A13: Community | B13: =sum(B14:B16) -> 12455 | C13: =sum(C14:C16) -> 0 | D13: =sum(D14:D16) -> 15178 | E13: =sum(E14:E16) -> 0 | F13: =sum(F14:F16) -> 34560 | G13: =sum(G14:G16) -> 0 | H13: =sum(H14:H16) -> 34560 | I13: =sum(I14:I16) -> 0 | ... Y13: =sum(Y14:Y16) -> 0
A14: Pickup games | B14: 0 | C14: 0 | D14: 0 | E14: 0 | F14: 0 | G14: 0 | H14: 0 | I14: 0 | J14: 0 | K14: 0 | L14: 0 | M14: 0 | N14: 1639 | O14: 1639 | P14: 0 | Q14: 0 | R14: 1493 | S14: 1493 | T14: 0 | U14: 0 | V14: 2700 | W14: 2700 | X14: 0 | Y14: 0
A15: Social Events/Tournaments | B15: 12455 | C15: 0 | D15: 15178 | E15: 0 | F15: 34560 | G15: 0 | H15: 34560 | I15: 0 | J15: 12426 | K15: 0 | L15: 12426 | M15: 0 | N15: 19243 | O15: 0 | P15: 18493 | Q15: 0 | R15: 13662 | S15: 13662 | T15: 0 | U15: 0 | V15: 9222 | W15: 9222 | X15: 0 | Y15: 0
A16: Community Partnerships | B16: 0 | C16: 0 | D16: 0 | E16: 0 | F16: 0 | G16: 0 | H16: 0 | I16: 0 | J16: 0 | K16: 0 | L16: 0 | M16: 0 | N16: 0 | O16: 0 | P16: 0 | Q16: 0 | R16: 51043 | S16: 0 | T16: 51043 | U16: 0 | V16: 28211 | W16: 0 | X16: 28211 | Y16: 0
A17: Academy | B17: 0 | C17: 0 | D17: 0 | E17: 0 | F17: =H17 -> 47200 | G17: 0 | H17: =40000+(18%*40000) -> 47200 | I17: 0 | J17: =K17+L17 -> 50200 | K17: 3000 | L17: =40000+(18%*40000) -> 47200 | M17: 0 | N17: 52200 | O17: 5000 | P17: =40000+(18%*40000) -> 47200 | Q17: 0 | R17: 115350 | S17: 5000 | T17: =40000+(18%*40000) -> 47200 | U17: 0 | V17: 87320 | W17: 0 | X17: 87320 | Y17: 0
A18: B2B | B18: =sum(B19,B20) -> 0 | C18: =sum(C19,C20) -> 0 | D18: =sum(D19,D20) -> 0 | E18: =sum(E19,E20) -> 0 | F18: =sum(F19,F20) -> 98663 | G18: =sum(G19,G20) -> 41205 | H18: =sum(H19,H20) -> 57460 | I18: =sum(I19,I20) -> 0 | ... Y18: =sum(Y19,Y20) -> 0
A19: Corporate events | B19: 0 | C19: 0 | D19: 0 | E19: 0 | F19: 83663 | G19: 41205 | H19: 42460 | I19: 0 | J19: 105880 | K19: 59340 | L19: 46540 | M19: 0 | N19: 27450 | O19: 0 | P19: 27450 | Q19: 0 | R19: 122627 | S19: 0 | T19: 122627 | U19: 0 | V19: 125890 | W19: 0 | X19: 125890 | Y19: 0
A20: All B2B partnerships | B20: 0 | C20: 0 | D20: 0 | E20: 0 | F20: 15000 | G20: 0 | H20: 15000 | I20: 0 | J20: 76886 | K20: 0 | L20: 76886 | M20: 0 | N20: 0 | O20: 0 | P20: 76886 | Q20: 0 | R20: 0 | S20: 0 | T20: 0 | U20: 0 | V20: 16115 | W20: 0 | X20: 16115 | Y20: 0
A21: Commerce | B21: =sum(B22:B24) -> 9775 | C21: =sum(C22:C24) -> 4150 | D21: =sum(D22:D24) -> 0 | E21: =sum(E22:E24) -> 4100 | F21: =sum(F22:F24) -> 19150 | G21: =sum(G22:G24) -> 12225 | H21: =sum(H22:H24) -> 0 | I21: =sum(I22:I24) -> 6925 | ... Y21: =sum(Y22:Y24) -> 3350
A22: Product rental | B22: 9775 | C22: 4150 | D22: 0 | E22: 4100 | F22: 17950 | G22: 12225 | H22: 0 | I22: 5725 | J22: 20075 | K22: 13950 | L22: 0 | M22: 6550 | N22: 14362 | O22: 9550 | P22: 0 | Q22: 4812 | R22: 11975 | S22: 6700 | T22: 0 | U22: 5275 | V22: 13550 | W22: 10220 | X22: 0 | Y22: 3350
A23: Product sales | B23: 0 | C23: 0 | D23: 0 | E23: 0 | F23: 1200 | G23: 0 | H23: 0 | I23: 1200 | J23: 0 | K23: 0 | L23: 0 | M23: 0 | N23: 0 | O23: 0 | P23: 0 | Q23: 0 | R23: 0 | S23: 0 | T23: 0 | U23: 0 | V23: 0 | W23: 0 | X23: 0 | Y23: 0
A24: F&B | B24: 0 | C24: 0 | D24: 0 | E24: 0 | F24: 0 | G24: 0 | H24: 0 | I24: 0 | J24: 4690 | K24: 0 | L24: 0 | M24: 0 | N24: 20915 | O24: 0 | P24: 0 | Q24: 0 | R24: 18690 | S24: 0 | T24: 0 | U24: 0 | V24: 15493 | W24: 0 | X24: 0 | Y24: 0
A25: Other Income | B25: 0 | C25: 0 | D25: 0 | E25: 0 | F25: 0 | G25: 0 | H25: 0 | I25: 0 | J25: 0 | K25: 0 | L25: 0 | M25: 0 | N25: 0 | O25: 0 | P25: 0 | Q25: 0 | R25: 0 | S25: 0 | T25: 0 | U25: 0 | V25: 0 | W25: 0 | X25: 0 | Y25: 0
A26: Total Gross Revenue | B26: =B3+B13+B17+B18+B21+B25 -> 335848 | C26: =C3+C13+C17+C18+C21+C25 -> 35407 | D26: =D3+D13+D17+D18+D21+D25 -> 178734 | E26: =E3+E13+E17+E18+E21+E25 -> 88513 | F26: =F3+F13+F17+F18+F21+F25 -> 563241 | G26: =G3+G13+G17+G18+G21+G25 -> 145200 | H26: =H3+H13+H17+H18+H21+H25 -> 346211 | I26: =I3+I13+I17+I18+I21+I25 -> 71832 | J26: =J3+J13+J17+J18+J21+J25 -> 710647 | K26: =K4+K10+K13+K17+K18+K21+K25 -> 168475 | L26: =L4+L10+L13+L17+L18+L21+L25 -> 474406 | M26: =M4+M10+M13+M17+M18+M21+M25 -> 63501 | N26: =N3+N13+N17+N18+N21+N25 -> 614603 | O26: =O4+O10+O13+O17+O18+O21+O25 -> 75602 | P26: =P4+P10+P13+P17+P18+P21+P25 -> 431310 | Q26: =Q4+Q10+Q13+Q17+Q18+Q21+Q25 -> 81339 | R26: =R3+R13+R17+R18+R21+R25 -> 619059 | S26: =S4+S10+S13+S17+S18+S21+S25 -> 84704 | T26: =T4+T10+T13+T17+T18+T21+T25 -> 363688 | U26: =U4+U10+U13+U17+U18+U21+U25 -> 87157 | V26: =V3+V13+V17+V18+V21+V25 -> 635389 | W26: =W3+W13+W17+W18+W21+W25 -> 93919 | X26: =X3+X13+X17+X18+X21+X25 -> 426515 | Y26: =Y3+Y13+Y17+Y18+Y21+Y25 -> 99482
A27: GST | B27: =B26-(B26/1.18) -> 51231.051 | C27: =C26-(C26/1.18) -> 5401.0678 | D27: =D26-(D26/1.18) -> 27264.508 | E27: =E26-(E26/1.18) -> 13501.983 | F27: =F26-(F26/1.18) -> 85918.119 | G27: =G26-(G26/1.18) -> 22149.153 | J27: =J26-(J26/1.18) -> 108403.78 | N27: =N26-(N26/1.18) -> 93753 | R27: =R26-(R26/1.18) -> 94432.729 | V27: =V26-(V26/1.18) -> 96923.746
A28: Net Revenue Post GST | B28: =B26-B27 -> 284616.95 | C28: =C26-C27 -> 30005.932 | D28: =D26-D27 -> 151469.49 | E28: =E26-E27 -> 75011.017 | F28: =F26-F27 -> 477322.88 | G28: =G26-G27 -> 123050.85 | J28: =J26-J27 -> 602243.22 | N28: =N26-N27 -> 520850 | R28: =R26-R27 -> 524626.27 | V28: =V26-V27 -> 538465.25

Sheet DOK | 83
D1: Link | E1: Link | F1: Link | G1: Link | H1: Link | I1: Link
A2: Venues | B2: April | C2: May | D2: June | E2: July | F2: June | G2: July | H2: August | I2: Sept | J2: Oct | K2: Turf | L2: Padel | M2: Nov | N2: Dec
A3: Pay & Play | B3: =sum(B4,B10) -> 0 | C3: =sum(C4,C10) -> 0 | D3: =sum(D4,D10) -> 49974 | E3: =sum(E4,E10) -> 62050 | F3: =sum(F4,F10) -> 50154 | G3: =sum(G4,G10) -> 62050 | H3: =sum(H4,H10) -> 29344 | I3: =sum(I4,I10) -> 27776 | J3: =sum(J4,J10) -> 0
A4: Online | B4: =sum(B5:B9) -> 0 | C4: =sum(C5:C9) -> 0 | D4: =sum(D5:D9) -> 19180 | E4: =sum(E5:E9) -> 9450 | F4: =sum(F5:F9) -> 19180 | G4: =sum(G5:G9) -> 9450 | H4: =sum(H5:H9) -> 5294 | I4: =sum(I5:I9) -> 14580
A5: District | B5: 0 | C5: 0 | D5: 19180 | E5: 3450 | F5: 19180 | G5: 3450 | H5: 5294 | I5: 14580
A6: Hudle | B6: 0 | C6: 0 | D6: 0 | E6: 6000 | F6: 0 | G6: 6000 | H6: 0 | I6: 0
A7: Playo | B7: 0 | C7: 0 | D7: 0 | E7: 0 | F7: 0 | G7: 0 | H7: 0 | I7: 0
A8: Khelomore | B8: 0 | C8: 0 | D8: 0 | E8: 0 | F8: 0 | G8: 0 | H8: 0 | I8: 0
A9: Zplys | B9: 0 | C9: 0 | D9: 0 | E9: 0 | F9: 0 | G9: 0 | H9: 0 | I9: 0
A10: Offline | B10: =sum(B11:B12) -> 0 | C10: =sum(C11:C12) -> 0 | D10: =sum(D11:D12) -> 30794 | E10: =sum(E11:E12) -> 52600 | F10: =sum(F11:F12) -> 30974 | G10: =sum(G11:G12) -> 52600 | H10: =sum(H11:H12) -> 24050 | I10: =sum(I11:I12) -> 13196
A11: Bookings | B11: 0 | C11: 0 | D11: 30794 | E11: 52600 | F11: 30974 | G11: 52600 | H11: 24050 | I11: 13196
A12: Memberships | B12: 0 | C12: 0 | D12: 0 | E12: 0 | F12: 0 | G12: 0 | H12: 0 | I12: 0
A13: Community | B13: =sum(B14:B16) -> 0 | C13: =sum(C14:C16) -> 0 | D13: =sum(D14:D16) -> 0 | E13: =sum(E14:E16) -> 20000 | F13: =sum(F14:F16) -> 0 | G13: =sum(G14:G16) -> 20000 | H13: =sum(H14:H16) -> 85267 | I13: =sum(I14:I16) -> 19875
A14: Pickup games | B14: 0 | C14: 0 | D14: 0 | E14: 20000 | F14: 0 | G14: 20000 | H14: 25000 | I14: 19875
A15: Social Events/Tournaments | B15: 0 | C15: 0 | D15: 0 | E15: 0 | F15: 0 | G15: 0 | H15: 60267 | I15: 0
A16: Community Partnerships | B16: 0 | C16: 0 | D16: 0 | E16: 0 | F16: 0 | G16: 0 | H16: 0 | I16: 0
A17: Academy | B17: 0 | C17: 0 | D17: 0 | E17: 0 | F17: 0 | G17: 0 | H17: 0 | I17: 0
A18: B2B | B18: =sum(B19,B20) -> 0 | C18: =sum(C19,C20) -> 0 | D18: =sum(D19,D20) -> 0 | E18: =sum(E19,E20) -> 9800 | F18: =sum(F19,F20) -> 0 | G18: =sum(G19,G20) -> 9800 | H18: =sum(H19,H20) -> 0 | I18: =sum(I19,I20) -> 0
A19: Corporate events | B19: 0 | C19: 0 | D19: 0 | E19: 9800 | F19: 0 | G19: 9800 | H19: 0 | I19: 0
A20: All B2B partnerships | B20: 0 | C20: 0 | D20: 0 | E20: 0 | F20: 0 | G20: 0 | H20: 0 | I20: 0
A21: Commerce | B21: =sum(B22:B24) -> 0 | C21: =sum(C22:C24) -> 0 | D21: =sum(D22:D24) -> 0 | E21: =sum(E22:E24) -> 0 | F21: =sum(F22:F24) -> 0 | G21: =sum(G22:G24) -> 0 | H21: =sum(H22:H24) -> 0 | I21: =sum(I22:I24) -> 0
A22: Product rental | B22: 0 | C22: 0 | D22: 0 | E22: 0 | F22: 0 | G22: 0 | H22: 0 | I22: 0
A23: Product sales | B23: 0 | C23: 0 | D23: 0 | E23: 0 | F23: 0 | G23: 0 | H23: 0 | I23: 0
A24: F&B | B24: 0 | C24: 0 | D24: 0 | E24: 0 | F24: 0 | G24: 0 | H24: 0 | I24: 0
A25: Other Income | B25: 0 | C25: 0 | D25: 0 | E25: 0 | F25: 0 | G25: 0 | H25: 0 | I25: 0
A26: Total Gross Revenue | B26: =B3+B13+B17+B18+B21+B25 -> 0 | C26: =C3+C13+C17+C18+C21+C25 -> 0 | D26: =D3+D13+D17+D18+D21+D25 -> 49974 | E26: =E3+E13+E17+E18+E21+E25 -> 91850 | F26: =F3+F13+F17+F18+F21+F25 -> 50154 | G26: =G3+G13+G17+G18+G21+G25 -> 91850 | H26: =H3+H13+H17+H18+H21+H25 -> 114611 | I26: =I3+I13+I17+I18+I21+I25 -> 47651
A27: GST | B27: =B26-(B26/1.18) -> 0 | C27: =C26-(C26/1.18) -> 0 | D27: =D26-(D26/1.18) -> 7623.1525 | E27: =E26-(E26/1.18) -> 14011.017 | F27: =F26-(F26/1.18) -> 7650.6102 | G27: =G26-(G26/1.18) -> 14011.017 | H27: =H26-(H26/1.18) -> 17483.034 | I27: =I26-(I26/1.18) -> 7268.7966
A28: Net Revenue Post GST | B28: =B26-B27 -> 0 | C28: =C26-C27 -> 0 | D28: =D26-D27 -> 42350.847 | E28: =E26-E27 -> 77838.983 | F28: =F26-F27 -> 42503.39 | G28: =G26-G27 -> 77838.983 | H28: =H26-H27 -> 97127.966 | I28: =I26-I27 -> 40382.203

Sheet RallyGully | Chd
B1: Link
A2: Venues | B2: Sept | C2: Oct | D2: Nov | E2: Dec
A3: Pay & Play | B3: =sum(B4,B10) -> 19999
A4: Online | B4: =sum(B5:B9) -> 14100
A5: District | B5: 14100
A6: Hudle | B6: 0
A7: Playo | B7: 0
A8: Khelomore | B8: 0
A9: Zplys | B9: 0
A10: Offline | B10: =sum(B11:B12) -> 5899
A11: Bookings | B11: 399
A12: Memberships | B12: 5500
A13: Community | B13: =sum(B14:B16) -> 399
A14: Pickup games | B14: 399
A15: Social Events/Tournaments | B15: 0
A16: Community Partnerships | B16: 0
A17: Academy | B17: 0
A18: B2B | B18: =sum(B19,B20) -> 0
A19: Corporate events | B19: 0
A20: All B2B partnerships | B20: 0
A21: Commerce | B21: =sum(B22:B24) -> 0
A22: Product rental | B22: 0
A23: Product sales | B23: 0
A24: F&B | B24: 0
A25: Other Income | B25: 0
A26: Total Gross Revenue | B26: =B3+B13+B17+B18+B21+B25 -> 20398
A27: GST (B) | B27: =B26-(B26/1.18) -> 3111.5593
A28: Net Revenue Post GST | B28: =B26-B27 -> 17286.441

Sheet Ambala
B1: Link | C1: Link | D1: Link
A2: Venues | B2: June | C2: July | D2: August
A3: Pay & Play | B3: =sum(B4,B10) -> 28536 | C3: =sum(C4,C10) -> 61908 | D3: =sum(D4,D10) -> 20911
A4: Online | B4: =sum(B5:B9) -> 5336 | C4: =sum(C5:C9) -> 10693 | D4: =sum(D5:D9) -> 2691
A5: District | B5: 0 | C5: 0 | D5: 0
A6: Hudle | B6: 5336 | C6: 10693 | D6: 2691
A7: Playo | B7: 0 | C7: 0 | D7: 0
A8: Khelomore | B8: 0 | C8: 0 | D8: 0
A9: Zplys | B9: 0 | C9: 0 | D9: 0
A10: Offline | B10: =sum(B11:B12) -> 23200 | C10: =sum(C11:C12) -> 51215 | D10: =sum(D11:D12) -> 18220
A11: Bookings | B11: 23200 | C11: 51215 | D11: 18220
A12: Memberships | B12: 0 | C12: 0 | D12: 0
A13: Community | B13: =sum(B14:B16) -> 0 | C13: =sum(C14:C16) -> 0 | D13: =sum(D14:D16) -> 0
A14: Pickup games | B14: 0 | C14: 0 | D14: 0
A15: Social Events/Tournaments | B15: 0 | C15: 0 | D15: 0
A16: Community Partnerships | B16: 0 | C16: 0 | D16: 0
A17: Academy | B17: 0 | C17: 0 | D17: 0
A18: B2B | B18: =sum(B19,B20) -> 0 | C18: =sum(C19,C20) -> 0 | D18: =sum(D19,D20) -> 0
A19: Corporate events | B19: 0 | C19: 0 | D19: 0
A20: All B2B partnerships | B20: 0 | C20: 0 | D20: 0
A21: Commerce | B21: =sum(B22:B24) -> 8450 | C21: =sum(C22:C24) -> 11350 | D21: =sum(D22:D24) -> 2625
A22: Product rental | B22: 8450 | C22: 11350 | D22: 2625
A23: Product sales | B23: 0 | C23: 0 | D23: 0
A24: F&B | B24: 0 | C24: 0 | D24: 0
A25: Other Income | B25: 0 | C25: 0 | D25: 0
A26: Total Gross Revenue | B26: =B3+B13+B17+B18+B21+B25 -> 36986 | C26: =C3+C13+C17+C18+C21+C25 -> 73258 | D26: =D3+D13+D17+D18+D21+D25 -> 23536
A27: GST | B27: =B26-(B26/1.18) -> 5641.9322 | C27: =C26-(C26/1.18) -> 11174.949 | D27: =D26-(D26/1.18) -> 3590.2373
A28: Net Revenue Post GST | B28: =B26-B27 -> 31344.068 | C28: =C26-C27 -> 62083.051 | D28: =D26-D27 -> 19945.763

Sheet Zirakpur
B1: Link | C1: Link | D1: Link
A2: Venues | B2: June | C2: July | D2: August
A3: Pay & Play | B3: =sum(B4,B10) -> 3350 | C3: =sum(C4,C10) -> 4692 | D3: =sum(D4,D10) -> 2242
A4: Online | B4: =sum(B5:B9) -> 0 | C4: =sum(C5:C9) -> 4392 | D4: =sum(D5:D9) -> 2242
A5: District | B5: 0 | C5: 4392 | D5: 2242
A6: Hudle | B6: 0 | C6: 0 | D6: 0
A7: Playo | B7: 0 | C7: 0 | D7: 0
A8: Khelomore | B8: 0 | C8: 0 | D8: 0
A9: Zplys | B9: 0 | C9: 0 | D9: 0
A10: Offline | B10: =sum(B11:B12) -> 3350 | C10: =sum(C11:C12) -> 300 | D10: =sum(D11:D12) -> 0
A11: Bookings | B11: 3350 | C11: 300 | D11: 0
A12: Memberships | B12: 0 | C12: 0 | D12: 0
A13: Community | B13: =sum(B14:B16) -> 2384 | C13: =sum(C14:C16) -> 0 | D13: =sum(D14:D16) -> 0
A14: Pickup games | B14: 0 | C14: 0 | D14: 0
A15: Social Events/Tournaments | B15: 2384 | C15: 0 | D15: 0
A16: Community Partnerships | B16: 0 | C16: 0 | D16: 0
A17: Academy | B17: 0 | C17: 0 | D17: 0
A18: B2B | B18: =sum(B19,B20) -> 0 | C18: =sum(C19,C20) -> 0 | D18: =sum(D19,D20) -> 0
A19: Corporate events | B19: 0 | C19: 0 | D19: 0
A20: All B2B partnerships | B20: 0 | C20: 0 | D20: 0
A21: Commerce | B21: =sum(B22:B24) -> 0 | C21: =sum(C22:C24) -> 450 | D21: =sum(D22:D24) -> 0
A22: Product rental | B22: 0 | C22: 450 | D22: 0
A23: Product sales | B23: 0 | C23: 0 | D23: 0
A24: F&B | B24: 0 | C24: 0 | D24: 0
A25: Other Income | B25: 0 | C25: 0 | D25: 0
A26: Total Gross Revenue | B26: =B3+B13+B17+B18+B21+B25 -> 5734 | C26: =C3+C13+C17+C18+C21+C25 -> 5142 | D26: =D3+D13+D17+D18+D21+D25 -> 2242
A27: GST | B27: =B26-(B26/1.18) -> 874.67797 | C27: =C26-(C26/1.18) -> 784.37288 | D27: =D26-(D26/1.18) -> 342
A28: Net Revenue Post GST | B28: =B26-B27 -> 4859.322 | C28: =C26-C27 -> 4357.6271 | D28: =D26-D27 -> 1900
