Workbook

Sheet Central Dashboard
L1: Link
A2: Sno. | B2: Venues | C2: July | D2: August | E2: September | F2: October | G2: November | H2: December | I2: January | J2: February | K2: March | L2: April (26-27)
A3: 1 | B3: RallyGully I Sector 10 Dwarka | C3: ='RallyGully I Sector 10 Dwarka'!C24 -> 103615 | D3: ='RallyGully I Sector 10 Dwarka'!D24 -> 298839 | E3: ='RallyGully I Sector 10 Dwarka'!E24 -> 245054 | F3: ='RallyGully I Sector 10 Dwarka'!F24 -> 200720 | G3: ='RallyGully I Sector 10 Dwarka'!G24 -> 168129 | H3: ='RallyGully I Sector 10 Dwarka'!H24 -> 206326 | I3: ='RallyGully I Sector 10 Dwarka'!I24 -> 301217 | J3: ='RallyGully I Sector 10 Dwarka'!J24 -> 263730 | K3: ='RallyGully I Sector 10 Dwarka'!K24 -> 251120
A4: 2 | B4: RallyGully I Sector 83 Gurgaon | C4: 0 | D4: ='RallyGully I Sector 83 Gurgaon'!D24 -> 37420 | E4: ='RallyGully I Sector 83 Gurgaon'!E24 -> 154961 | F4: 90075 | G4: ='RallyGully I Sector 83 Gurgaon'!G24 -> 151276 | H4: ='RallyGully I Sector 83 Gurgaon'!H24 -> 175700 | I4: ='RallyGully I Sector 83 Gurgaon'!I24 -> 169521 | J4: ='RallyGully I Sector 83 Gurgaon'!J24 -> 210880 | K4: ='RallyGully I Sector 83 Gurgaon'!K24 -> 226770
A5: 3 | B5: RallyGully I East of Kailash | C5: 0 | D5: 0 | E5: ='RallyGully I East of Kailash'!E24 -> 78858.8 | F5: ='RallyGully I East of Kailash'!F24 -> 183432.6 | G5: ='RallyGully I East of Kailash'!G24 -> 144284 | H5: ='RallyGully I East of Kailash'!H24 -> 123338 | I5: ='RallyGully I East of Kailash'!I24 -> 279567 | J5: ='RallyGully I East of Kailash'!J24 -> 365154 | K5: ='RallyGully I East of Kailash'!K24 -> 281064
A6: 4 | B6: RallyGully I Sector 19 Dwarka Drive Kick | C6: 0 | D6: 0 | E6: 0 | F6: ='RallyGully I Sector 19 Dwarka'!F24 -> 71245 | G6: ='RallyGully I Sector 19 Dwarka'!$G$24 -> 78029 | H6: ='RallyGully I Sector 19 Dwarka'!H24 -> 50925 | I6: ='RallyGully I Sector 19 Dwarka'!I24 -> 125214 | J6: ='RallyGully I Sector 19 Dwarka'!J24 -> 86460 | K6: ='RallyGully I Sector 19 Dwarka'!K24 -> 104875
A7: 5 | B7: RallyGully | DPSG | C7: 0 | D7: 0 | E7: 0 | F7: 0 | G7: 0 | H7: ='RallyGully | DPSG'!H24 -> 21637 | I7: ='RallyGully | DPSG'!I24 -> 49820 | J7: ='RallyGully | DPSG'!J24 -> 113460 | K7: ='RallyGully | DPSG'!K24 -> 179380
A8: 6 | B8: RallyGully I Panchsheel | C8: 0 | D8: 0 | E8: 0 | F8: 0 | G8: 0 | H8: 0 | I8: ='RallyGully | Panchsheel'!I24 -> 78588 | J8: ='RallyGully | Panchsheel'!J24 -> 88970 | K8: ='RallyGully | Panchsheel'!K24 -> 141013
A9: 7 | B9: RallyGully | LCR Pune | C9: 0 | D9: 0 | E9: 0 | F9: 0 | G9: ='RallyGully | LCR Pune'!G24 -> 40125 | H9: ='RallyGully | LCR Pune'!H24 -> 171603 | I9: ='RallyGully | LCR Pune'!I24 -> 399500 | J9: ='RallyGully | LCR Pune'!J24 -> 450865 | K9: ='RallyGully | LCR Pune'!K24 -> 415235
A10: 8 | B10: RallyGully I Gandhipath | C10: 0 | D10: 0 | E10: 0 | F10: 0 | G10: 0 | H10: ='RallyGully | Gandipath'!H24 -> 4900 | I10: ='RallyGully | Gandipath'!I24 -> 98125 | J10: ='RallyGully | Gandipath'!J24 -> 74878 | K10: ='RallyGully | Gandipath'!K24 -> 139155
A11: 9 | B11: Powerplay Park | C11: 0 | D11: 0 | E11: 0 | F11: 0 | G11: 0 | H11: 0 | I11: 0 | J11: ='Powerplay Park, Pune'!J24 -> 59161 | K11: ='Powerplay Park, Pune'!K24 -> 186760
A12: 10 | B12: Commons | RallyGully x Delhi Padel Collective | C12: 0 | D12: 0 | E12: 0 | F12: 0 | G12: 0 | H12: 0 | I12: 0 | J12: 0 | K12: ='Commons, Noida'!K24 -> 136660
B13: Total Gross Revenue | C13: =SUM(C3:C10) -> 103615 | D13: =SUM(D3:D10) -> 336259 | E13: =SUM(E3:E10) -> 478873.8 | F13: =SUM(F3:F10) -> 545472.6 | G13: =SUM(G3:G10) -> 581843 | H13: =SUM(H3:H12) -> 754429 | I13: =SUM(I3:I12) -> 1501552 | J13: =SUM(J3:J12) -> 1713558 | K13: =SUM(K3:K12) -> 2062032
B14: Net Revenue (Post Commissions) | E14: ='RallyGully I Sector 10 Dwarka'!E25+'RallyGully I Sector 83 Gurgaon'!E25+'RallyGully I East of Kailash'!E25+'RallyGully I Sector 19 Dwarka'!E25+'RallyGully | LCR Pune'!E25+'RallyGully | DPSG'!E25+'RallyGully | Gandipath'!E25+'RallyGully | Panchsheel'!E25+'Powerplay Park, Pune'!E25+'Commons, Noida'!E25 -> 383752.5 | F14: ='RallyGully I Sector 10 Dwarka'!F25+'RallyGully I Sector 83 Gurgaon'!F25+'RallyGully I East of Kailash'!F25+'RallyGully I Sector 19 Dwarka'!F25+'RallyGully | LCR Pune'!F25+'RallyGully | DPSG'!F25+'RallyGully | Gandipath'!F25+'RallyGully | Panchsheel'!F25+'Powerplay Park, Pune'!F25+'Commons, Noida'!F25 -> 472432 | G14: ='RallyGully I Sector 10 Dwarka'!G25+'RallyGully I Sector 83 Gurgaon'!G25+'RallyGully I East of Kailash'!G25+'RallyGully I Sector 19 Dwarka'!G25+'RallyGully | LCR Pune'!G25+'RallyGully | DPSG'!G25+'RallyGully | Gandipath'!G25+'RallyGully | Panchsheel'!G25+'Powerplay Park, Pune'!G25+'Commons, Noida'!G25 -> 550598.68 | H14: ='RallyGully I Sector 10 Dwarka'!H25+'RallyGully I Sector 83 Gurgaon'!H25+'RallyGully I East of Kailash'!H25+'RallyGully I Sector 19 Dwarka'!H25+'RallyGully | LCR Pune'!H25+'RallyGully | DPSG'!H25+'RallyGully | Gandipath'!H25+'RallyGully | Panchsheel'!H25+'Powerplay Park, Pune'!H25+'Commons, Noida'!H25 -> 724015.27 | I14: ='RallyGully I Sector 10 Dwarka'!I25+'RallyGully I Sector 83 Gurgaon'!I25+'RallyGully I East of Kailash'!I25+'RallyGully I Sector 19 Dwarka'!I25+'RallyGully | LCR Pune'!I25+'RallyGully | DPSG'!I25+'RallyGully | Gandipath'!I25+'RallyGully | Panchsheel'!I25+'Powerplay Park, Pune'!I25+'Commons, Noida'!I25 -> 1447146.4 | J14: ='RallyGully I Sector 10 Dwarka'!J25+'RallyGully I Sector 83 Gurgaon'!J25+'RallyGully I East of Kailash'!J25+'RallyGully I Sector 19 Dwarka'!J25+'RallyGully | LCR Pune'!J25+'RallyGully | DPSG'!J25+'RallyGully | Gandipath'!J25+'RallyGully | Panchsheel'!J25+'Powerplay Park, Pune'!J25+'Commons, Noida'!J25 -> 1640747 | K14: ='RallyGully I Sector 10 Dwarka'!K25+'RallyGully I Sector 83 Gurgaon'!K25+'RallyGully I East of Kailash'!K25+'RallyGully I Sector 19 Dwarka'!K25+'RallyGully | LCR Pune'!K25+'RallyGully | DPSG'!K25+'RallyGully | Gandipath'!K25+'RallyGully | Panchsheel'!K25+'Powerplay Park, Pune'!K25+'Commons, Noida'!K25 -> 1942531.6
B17: Verticle Vise | C17: July | D17: August | E17: September | F17: October | G17: November | H17: December | I17: January | J17: February | K17: March
A19: 1 | B19: Offline | C19: =SUM('RallyGully I Sector 10 Dwarka'!C3+'RallyGully I Sector 83 Gurgaon'!C3+'RallyGully I East of Kailash'!C3+'RallyGully I Sector 19 Dwarka'!C3+'RallyGully | LCR Pune'!C3+'RallyGully | DPSG'!C3+'RallyGully | Gandipath'!C3+'RallyGully | Panchsheel'!C3) -> 4835 | D19: =SUM('RallyGully I Sector 10 Dwarka'!D3+'RallyGully I Sector 83 Gurgaon'!D3+'RallyGully I East of Kailash'!D3+'RallyGully I Sector 19 Dwarka'!D3+'RallyGully | LCR Pune'!D3+'RallyGully | DPSG'!D3+'RallyGully | Gandipath'!D3+'RallyGully | Panchsheel'!D3) -> 51040 | E19: =SUM('RallyGully I Sector 10 Dwarka'!E3+'RallyGully I Sector 83 Gurgaon'!E3+'RallyGully I East of Kailash'!E3+'RallyGully I Sector 19 Dwarka'!E3+'RallyGully | LCR Pune'!E3+'RallyGully | DPSG'!E3+'RallyGully | Gandipath'!E3+'RallyGully | Panchsheel'!E3) -> 139520 | F19: =SUM('RallyGully I Sector 10 Dwarka'!F3+'RallyGully I Sector 83 Gurgaon'!F3+'RallyGully I East of Kailash'!F3+'RallyGully I Sector 19 Dwarka'!F3+'RallyGully | LCR Pune'!F3+'RallyGully | DPSG'!F3+'RallyGully | Gandipath'!F3+'RallyGully | Panchsheel'!F3) -> 73240 | G19: =SUM('RallyGully I Sector 10 Dwarka'!G3+'RallyGully I Sector 83 Gurgaon'!G3+'RallyGully I East of Kailash'!G3+'RallyGully I Sector 19 Dwarka'!G3+'RallyGully | LCR Pune'!G3+'RallyGully | DPSG'!G3+'RallyGully | Gandipath'!G3+'RallyGully | Panchsheel'!G3) -> 175494 | H19: =SUM('RallyGully I Sector 10 Dwarka'!H3+'RallyGully I Sector 83 Gurgaon'!H3+'RallyGully I East of Kailash'!H3+'RallyGully I Sector 19 Dwarka'!H3+'RallyGully | LCR Pune'!H3+'RallyGully | DPSG'!H3+'RallyGully | Gandipath'!H3+'RallyGully | Panchsheel'!H3) -> 269512 | I19: =SUM('RallyGully I Sector 10 Dwarka'!I3+'RallyGully I Sector 83 Gurgaon'!I3+'RallyGully I East of Kailash'!I3+'RallyGully I Sector 19 Dwarka'!I3+'RallyGully | LCR Pune'!I3+'RallyGully | DPSG'!I3+'RallyGully | Gandipath'!I3+'RallyGully | Panchsheel'!I3) -> 481369 | J19: =SUM('RallyGully I Sector 10 Dwarka'!J3+'RallyGully I Sector 83 Gurgaon'!J3+'RallyGully I East of Kailash'!J3+'RallyGully I Sector 19 Dwarka'!J3+'RallyGully | LCR Pune'!J3+'RallyGully | DPSG'!J3+'RallyGully | Gandipath'!J3+'RallyGully | Panchsheel'!J3+'Powerplay Park, Pune'!J3+'Commons, Noida'!J3) -> 515675 | K19: =SUM('RallyGully I Sector 10 Dwarka'!K3+'RallyGully I Sector 83 Gurgaon'!K3+'RallyGully I East of Kailash'!K3+'RallyGully I Sector 19 Dwarka'!K3+'RallyGully | LCR Pune'!K3+'RallyGully | DPSG'!K3+'RallyGully | Gandipath'!K3+'RallyGully | Panchsheel'!K3+'Powerplay Park, Pune'!K3+'Commons, Noida'!K3) -> 528815
A20: 1.1 | B20: Rentals | C20: =SUM('RallyGully I Sector 10 Dwarka'!C4+'RallyGully I Sector 83 Gurgaon'!C4+'RallyGully I East of Kailash'!C4+'RallyGully I Sector 19 Dwarka'!C4+'RallyGully | LCR Pune'!C4+'RallyGully | DPSG'!C4+'RallyGully | Gandipath'!C4+'RallyGully | Panchsheel'!C4) -> 4475 | D20: =SUM('RallyGully I Sector 10 Dwarka'!D4+'RallyGully I Sector 83 Gurgaon'!D4+'RallyGully I East of Kailash'!D4+'RallyGully I Sector 19 Dwarka'!D4+'RallyGully | LCR Pune'!D4+'RallyGully | DPSG'!D4+'RallyGully | Gandipath'!D4+'RallyGully | Panchsheel'!D4) -> 15580 | E20: =SUM('RallyGully I Sector 10 Dwarka'!E4+'RallyGully I Sector 83 Gurgaon'!E4+'RallyGully I East of Kailash'!E4+'RallyGully I Sector 19 Dwarka'!E4+'RallyGully | LCR Pune'!E4+'RallyGully | DPSG'!E4+'RallyGully | Gandipath'!E4+'RallyGully | Panchsheel'!E4) -> 22280 | F20: =SUM('RallyGully I Sector 10 Dwarka'!F4+'RallyGully I Sector 83 Gurgaon'!F4+'RallyGully I East of Kailash'!F4+'RallyGully I Sector 19 Dwarka'!F4+'RallyGully | LCR Pune'!F4+'RallyGully | DPSG'!F4+'RallyGully | Gandipath'!F4+'RallyGully | Panchsheel'!F4) -> 24840 | G20: =SUM('RallyGully I Sector 10 Dwarka'!G4+'RallyGully I Sector 83 Gurgaon'!G4+'RallyGully I East of Kailash'!G4+'RallyGully I Sector 19 Dwarka'!G4+'RallyGully | LCR Pune'!G4+'RallyGully | DPSG'!G4+'RallyGully | Gandipath'!G4+'RallyGully | Panchsheel'!G4) -> 27820 | H20: =SUM('RallyGully I Sector 10 Dwarka'!H4+'RallyGully I Sector 83 Gurgaon'!H4+'RallyGully I East of Kailash'!H4+'RallyGully I Sector 19 Dwarka'!H4+'RallyGully | LCR Pune'!H4+'RallyGully | DPSG'!H4+'RallyGully | Gandipath'!H4+'RallyGully | Panchsheel'!H4) -> 60775 | I20: =SUM('RallyGully I Sector 10 Dwarka'!I4+'RallyGully I Sector 83 Gurgaon'!I4+'RallyGully I East of Kailash'!I4+'RallyGully I Sector 19 Dwarka'!I4+'RallyGully | LCR Pune'!I4+'RallyGully | DPSG'!I4+'RallyGully | Gandipath'!I4+'RallyGully | Panchsheel'!I4) -> 91339 | J20: =SUM('RallyGully I Sector 10 Dwarka'!J4+'RallyGully I Sector 83 Gurgaon'!J4+'RallyGully I East of Kailash'!J4+'RallyGully I Sector 19 Dwarka'!J4+'RallyGully | LCR Pune'!J4+'RallyGully | DPSG'!J4+'RallyGully | Gandipath'!J4+'RallyGully | Panchsheel'!J4) -> 94325 | K20: =SUM('RallyGully I Sector 10 Dwarka'!K4+'RallyGully I Sector 83 Gurgaon'!K4+'RallyGully I East of Kailash'!K4+'RallyGully I Sector 19 Dwarka'!K4+'RallyGully | LCR Pune'!K4+'RallyGully | DPSG'!K4+'RallyGully | Gandipath'!K4+'RallyGully | Panchsheel'!K4+'Powerplay Park, Pune'!K4+'Commons, Noida'!K4) -> 82830
A21: 1.2 | B21: F&B | C21: =SUM('RallyGully I Sector 10 Dwarka'!C5+'RallyGully I Sector 83 Gurgaon'!C5+'RallyGully I East of Kailash'!C5+'RallyGully I Sector 19 Dwarka'!C5+'RallyGully | LCR Pune'!C5+'RallyGully | DPSG'!C5+'RallyGully | Gandipath'!C5+'RallyGully | Panchsheel'!C5) -> 360 | D21: =SUM('RallyGully I Sector 10 Dwarka'!D5+'RallyGully I Sector 83 Gurgaon'!D5+'RallyGully I East of Kailash'!D5+'RallyGully I Sector 19 Dwarka'!D5+'RallyGully | LCR Pune'!D5+'RallyGully | DPSG'!D5+'RallyGully | Gandipath'!D5+'RallyGully | Panchsheel'!D5) -> 1920 | E21: =SUM('RallyGully I Sector 10 Dwarka'!E5+'RallyGully I Sector 83 Gurgaon'!E5+'RallyGully I East of Kailash'!E5+'RallyGully I Sector 19 Dwarka'!E5+'RallyGully | LCR Pune'!E5+'RallyGully | DPSG'!E5+'RallyGully | Gandipath'!E5+'RallyGully | Panchsheel'!E5) -> 4400 | F21: =SUM('RallyGully I Sector 10 Dwarka'!F5+'RallyGully I Sector 83 Gurgaon'!F5+'RallyGully I East of Kailash'!F5+'RallyGully I Sector 19 Dwarka'!F5+'RallyGully | LCR Pune'!F5+'RallyGully | DPSG'!F5+'RallyGully | Gandipath'!F5+'RallyGully | Panchsheel'!F5) -> 2490 | G21: =SUM('RallyGully I Sector 10 Dwarka'!G5+'RallyGully I Sector 83 Gurgaon'!G5+'RallyGully I East of Kailash'!G5+'RallyGully I Sector 19 Dwarka'!G5+'RallyGully | LCR Pune'!G5+'RallyGully | DPSG'!G5+'RallyGully | Gandipath'!G5+'RallyGully | Panchsheel'!G5) -> 1890 | H21: =SUM('RallyGully I Sector 10 Dwarka'!H5+'RallyGully I Sector 83 Gurgaon'!H5+'RallyGully I East of Kailash'!H5+'RallyGully I Sector 19 Dwarka'!H5+'RallyGully | LCR Pune'!H5+'RallyGully | DPSG'!H5+'RallyGully | Gandipath'!H5+'RallyGully | Panchsheel'!H5) -> 5260 | I21: =SUM('RallyGully I Sector 10 Dwarka'!I5+'RallyGully I Sector 83 Gurgaon'!I5+'RallyGully I East of Kailash'!I5+'RallyGully I Sector 19 Dwarka'!I5+'RallyGully | LCR Pune'!I5+'RallyGully | DPSG'!I5+'RallyGully | Gandipath'!I5+'RallyGully | Panchsheel'!I5) -> 4055 | J21: =SUM('RallyGully I Sector 10 Dwarka'!J5+'RallyGully I Sector 83 Gurgaon'!J5+'RallyGully I East of Kailash'!J5+'RallyGully I Sector 19 Dwarka'!J5+'RallyGully | LCR Pune'!J5+'RallyGully | DPSG'!J5+'RallyGully | Gandipath'!J5+'RallyGully | Panchsheel'!J5) -> 5445 | K21: =SUM('RallyGully I Sector 10 Dwarka'!K5+'RallyGully I Sector 83 Gurgaon'!K5+'RallyGully I East of Kailash'!K5+'RallyGully I Sector 19 Dwarka'!K5+'RallyGully | LCR Pune'!K5+'RallyGully | DPSG'!K5+'RallyGully | Gandipath'!K5+'RallyGully | Panchsheel'!K5+'Powerplay Park, Pune'!K5+'Commons, Noida'!K5) -> 3825
A22: 1.3 | B22: Product Sales | C22: =SUM('RallyGully I Sector 10 Dwarka'!C6+'RallyGully I Sector 83 Gurgaon'!C6+'RallyGully I East of Kailash'!C6+'RallyGully I Sector 19 Dwarka'!C6+'RallyGully | LCR Pune'!C6+'RallyGully | DPSG'!C6+'RallyGully | Gandipath'!C6+'RallyGully | Panchsheel'!C6) -> 0 | D22: =SUM('RallyGully I Sector 10 Dwarka'!D6+'RallyGully I Sector 83 Gurgaon'!D6+'RallyGully I East of Kailash'!D6+'RallyGully I Sector 19 Dwarka'!D6+'RallyGully | LCR Pune'!D6+'RallyGully | DPSG'!D6+'RallyGully | Gandipath'!D6+'RallyGully | Panchsheel'!D6) -> 0 | E22: =SUM('RallyGully I Sector 10 Dwarka'!E6+'RallyGully I Sector 83 Gurgaon'!E6+'RallyGully I East of Kailash'!E6+'RallyGully I Sector 19 Dwarka'!E6+'RallyGully | LCR Pune'!E6+'RallyGully | DPSG'!E6+'RallyGully | Gandipath'!E6+'RallyGully | Panchsheel'!E6) -> 12050 | F22: =SUM('RallyGully I Sector 10 Dwarka'!F6+'RallyGully I Sector 83 Gurgaon'!F6+'RallyGully I East of Kailash'!F6+'RallyGully I Sector 19 Dwarka'!F6+'RallyGully | LCR Pune'!F6+'RallyGully | DPSG'!F6+'RallyGully | Gandipath'!F6+'RallyGully | Panchsheel'!F6) -> 0 | G22: =SUM('RallyGully I Sector 10 Dwarka'!G6+'RallyGully I Sector 83 Gurgaon'!G6+'RallyGully I East of Kailash'!G6+'RallyGully I Sector 19 Dwarka'!G6+'RallyGully | LCR Pune'!G6+'RallyGully | DPSG'!G6+'RallyGully | Gandipath'!G6+'RallyGully | Panchsheel'!G6) -> 0 | H22: =SUM('RallyGully I Sector 10 Dwarka'!H6+'RallyGully I Sector 83 Gurgaon'!H6+'RallyGully I East of Kailash'!H6+'RallyGully I Sector 19 Dwarka'!H6+'RallyGully | LCR Pune'!H6+'RallyGully | DPSG'!H6+'RallyGully | Gandipath'!H6+'RallyGully | Panchsheel'!H6) -> 0 | I22: =SUM('RallyGully I Sector 10 Dwarka'!I6+'RallyGully I Sector 83 Gurgaon'!I6+'RallyGully I East of Kailash'!I6+'RallyGully I Sector 19 Dwarka'!I6+'RallyGully | LCR Pune'!I6+'RallyGully | DPSG'!I6+'RallyGully | Gandipath'!I6+'RallyGully | Panchsheel'!I6) -> 18000 | J22: =SUM('RallyGully I Sector 10 Dwarka'!J6+'RallyGully I Sector 83 Gurgaon'!J6+'RallyGully I East of Kailash'!J6+'RallyGully I Sector 19 Dwarka'!J6+'RallyGully | LCR Pune'!J6+'RallyGully | DPSG'!J6+'RallyGully | Gandipath'!J6+'RallyGully | Panchsheel'!J6) -> 0 | K22: =SUM('RallyGully I Sector 10 Dwarka'!K6+'RallyGully I Sector 83 Gurgaon'!K6+'RallyGully I East of Kailash'!K6+'RallyGully I Sector 19 Dwarka'!K6+'RallyGully | LCR Pune'!K6+'RallyGully | DPSG'!K6+'RallyGully | Gandipath'!K6+'RallyGully | Panchsheel'!K6+'Powerplay Park, Pune'!K6+'Commons, Noida'!K6) -> 0
A23: 1.4 | B23: Bookings | C23: =SUM('RallyGully I Sector 10 Dwarka'!C7+'RallyGully I Sector 83 Gurgaon'!C7+'RallyGully I East of Kailash'!C7+'RallyGully I Sector 19 Dwarka'!C7+'RallyGully | LCR Pune'!C7+'RallyGully | DPSG'!C7+'RallyGully | Gandipath'!C7+'RallyGully | Panchsheel'!C7) -> 0 | D23: =SUM('RallyGully I Sector 10 Dwarka'!D7+'RallyGully I Sector 83 Gurgaon'!D7+'RallyGully I East of Kailash'!D7+'RallyGully I Sector 19 Dwarka'!D7+'RallyGully | LCR Pune'!D7+'RallyGully | DPSG'!D7+'RallyGully | Gandipath'!D7+'RallyGully | Panchsheel'!D7) -> 33540 | E23: =SUM('RallyGully I Sector 10 Dwarka'!E7+'RallyGully I Sector 83 Gurgaon'!E7+'RallyGully I East of Kailash'!E7+'RallyGully I Sector 19 Dwarka'!E7+'RallyGully | LCR Pune'!E7+'RallyGully | DPSG'!E7+'RallyGully | Gandipath'!E7+'RallyGully | Panchsheel'!E7) -> 100790 | F23: =SUM('RallyGully I Sector 10 Dwarka'!F7+'RallyGully I Sector 83 Gurgaon'!F7+'RallyGully I East of Kailash'!F7+'RallyGully I Sector 19 Dwarka'!F7+'RallyGully | LCR Pune'!F7+'RallyGully | DPSG'!F7+'RallyGully | Gandipath'!F7+'RallyGully | Panchsheel'!F7) -> 40710 | G23: =SUM('RallyGully I Sector 10 Dwarka'!G7+'RallyGully I Sector 83 Gurgaon'!G7+'RallyGully I East of Kailash'!G7+'RallyGully I Sector 19 Dwarka'!G7+'RallyGully | LCR Pune'!G7+'RallyGully | DPSG'!G7+'RallyGully | Gandipath'!G7+'RallyGully | Panchsheel'!G7) -> 145784 | H23: =SUM('RallyGully I Sector 10 Dwarka'!H7+'RallyGully I Sector 83 Gurgaon'!H7+'RallyGully I East of Kailash'!H7+'RallyGully I Sector 19 Dwarka'!H7+'RallyGully | LCR Pune'!H7+'RallyGully | DPSG'!H7+'RallyGully | Gandipath'!H7+'RallyGully | Panchsheel'!H7) -> 203477 | I23: =SUM('RallyGully I Sector 10 Dwarka'!I7+'RallyGully I Sector 83 Gurgaon'!I7+'RallyGully I East of Kailash'!I7+'RallyGully I Sector 19 Dwarka'!I7+'RallyGully | LCR Pune'!I7+'RallyGully | DPSG'!I7+'RallyGully | Gandipath'!I7+'RallyGully | Panchsheel'!I7) -> 367975 | J23: =SUM('RallyGully I Sector 10 Dwarka'!J7+'RallyGully I Sector 83 Gurgaon'!J7+'RallyGully I East of Kailash'!J7+'RallyGully I Sector 19 Dwarka'!J7+'RallyGully | LCR Pune'!J7+'RallyGully | DPSG'!J7+'RallyGully | Gandipath'!J7+'RallyGully | Panchsheel'!J7) -> 415905 | K23: =SUM('RallyGully I Sector 10 Dwarka'!K7+'RallyGully I Sector 83 Gurgaon'!K7+'RallyGully I East of Kailash'!K7+'RallyGully I Sector 19 Dwarka'!K7+'RallyGully | LCR Pune'!K7+'RallyGully | DPSG'!K7+'RallyGully | Gandipath'!K7+'RallyGully | Panchsheel'!K7+'Powerplay Park, Pune'!K7+'Commons, Noida'!K7) -> 442160
A24: 2 | B24: Online: Third Party Platform | C24: =SUM('RallyGully I Sector 10 Dwarka'!C8+'RallyGully I Sector 83 Gurgaon'!C8+'RallyGully I East of Kailash'!C8+'RallyGully I Sector 19 Dwarka'!C8+'RallyGully | LCR Pune'!C8+'RallyGully | DPSG'!C8+'RallyGully | Gandipath'!C8+'RallyGully | Panchsheel'!C8) -> 88280 | D24: =SUM('RallyGully I Sector 10 Dwarka'!D8+'RallyGully I Sector 83 Gurgaon'!D8+'RallyGully I East of Kailash'!D8+'RallyGully I Sector 19 Dwarka'!D8+'RallyGully | LCR Pune'!D8+'RallyGully | DPSG'!D8+'RallyGully | Gandipath'!D8+'RallyGully | Panchsheel'!D8) -> 220132 | E24: =SUM('RallyGully I Sector 10 Dwarka'!E8+'RallyGully I Sector 83 Gurgaon'!E8+'RallyGully I East of Kailash'!E8+'RallyGully I Sector 19 Dwarka'!E8+'RallyGully | LCR Pune'!E8+'RallyGully | DPSG'!E8+'RallyGully | Gandipath'!E8+'RallyGully | Panchsheel'!E8) -> 282863.8 | F24: =SUM('RallyGully I Sector 10 Dwarka'!F8+'RallyGully I Sector 83 Gurgaon'!F8+'RallyGully I East of Kailash'!F8+'RallyGully I Sector 19 Dwarka'!F8+'RallyGully | LCR Pune'!F8+'RallyGully | DPSG'!F8+'RallyGully | Gandipath'!F8+'RallyGully | Panchsheel'!F8) -> 299312.6 | G24: =SUM('RallyGully I Sector 10 Dwarka'!G8+'RallyGully I Sector 83 Gurgaon'!G8+'RallyGully I East of Kailash'!G8+'RallyGully I Sector 19 Dwarka'!G8+'RallyGully | LCR Pune'!G8+'RallyGully | DPSG'!G8+'RallyGully | Gandipath'!G8+'RallyGully | Panchsheel'!G8) -> 262229 | H24: =SUM('RallyGully I Sector 10 Dwarka'!H8+'RallyGully I Sector 83 Gurgaon'!H8+'RallyGully I East of Kailash'!H8+'RallyGully I Sector 19 Dwarka'!H8+'RallyGully | LCR Pune'!H8+'RallyGully | DPSG'!H8+'RallyGully | Gandipath'!H8+'RallyGully | Panchsheel'!H8) -> 281135 | I24: =SUM('RallyGully I Sector 10 Dwarka'!I8+'RallyGully I Sector 83 Gurgaon'!I8+'RallyGully I East of Kailash'!I8+'RallyGully I Sector 19 Dwarka'!I8+'RallyGully | LCR Pune'!I8+'RallyGully | DPSG'!I8+'RallyGully | Gandipath'!I8+'RallyGully | Panchsheel'!I8) -> 520434 | J24: =SUM('RallyGully I Sector 10 Dwarka'!J8+'RallyGully I Sector 83 Gurgaon'!J8+'RallyGully I East of Kailash'!J8+'RallyGully I Sector 19 Dwarka'!J8+'RallyGully | LCR Pune'!J8+'RallyGully | DPSG'!J8+'RallyGully | Gandipath'!J8+'RallyGully | Panchsheel'!J8+'Powerplay Park, Pune'!J8+'Commons, Noida'!J8) -> 603109 | K24: =SUM('RallyGully I Sector 10 Dwarka'!K8+'RallyGully I Sector 83 Gurgaon'!K8+'RallyGully I East of Kailash'!K8+'RallyGully I Sector 19 Dwarka'!K8+'RallyGully | LCR Pune'!K8+'RallyGully | DPSG'!K8+'RallyGully | Gandipath'!K8+'RallyGully | Panchsheel'!K8+'Powerplay Park, Pune'!K8+'Commons, Noida'!K8) -> 861713
A25: 2.1 | B25: Hudle | C25: =SUM('RallyGully I Sector 10 Dwarka'!C9+'RallyGully I Sector 83 Gurgaon'!C9+'RallyGully I East of Kailash'!C9+'RallyGully I Sector 19 Dwarka'!C9+'RallyGully | LCR Pune'!C9+'RallyGully | DPSG'!C9+'RallyGully | Gandipath'!C9+'RallyGully | Panchsheel'!C9) -> 73440 | D25: =SUM('RallyGully I Sector 10 Dwarka'!D9+'RallyGully I Sector 83 Gurgaon'!D9+'RallyGully I East of Kailash'!D9+'RallyGully I Sector 19 Dwarka'!D9+'RallyGully | LCR Pune'!D9+'RallyGully | DPSG'!D9+'RallyGully | Gandipath'!D9+'RallyGully | Panchsheel'!D9) -> 162660 | E25: =SUM('RallyGully I Sector 10 Dwarka'!E9+'RallyGully I Sector 83 Gurgaon'!E9+'RallyGully I East of Kailash'!E9+'RallyGully I Sector 19 Dwarka'!E9+'RallyGully | LCR Pune'!E9+'RallyGully | DPSG'!E9+'RallyGully | Gandipath'!E9+'RallyGully | Panchsheel'!E9) -> 244051 | F25: =SUM('RallyGully I Sector 10 Dwarka'!F9+'RallyGully I Sector 83 Gurgaon'!F9+'RallyGully I East of Kailash'!F9+'RallyGully I Sector 19 Dwarka'!F9+'RallyGully | LCR Pune'!F9+'RallyGully | DPSG'!F9+'RallyGully | Gandipath'!F9+'RallyGully | Panchsheel'!F9) -> 257545 | G25: =SUM('RallyGully I Sector 10 Dwarka'!G9+'RallyGully I Sector 83 Gurgaon'!G9+'RallyGully I East of Kailash'!G9+'RallyGully I Sector 19 Dwarka'!G9+'RallyGully | LCR Pune'!G9+'RallyGully | DPSG'!G9+'RallyGully | Gandipath'!G9+'RallyGully | Panchsheel'!G9) -> 201485 | H25: =SUM('RallyGully I Sector 10 Dwarka'!H9+'RallyGully I Sector 83 Gurgaon'!H9+'RallyGully I East of Kailash'!H9+'RallyGully I Sector 19 Dwarka'!H9+'RallyGully | LCR Pune'!H9+'RallyGully | DPSG'!H9+'RallyGully | Gandipath'!H9+'RallyGully | Panchsheel'!H9) -> 173633 | I25: =SUM('RallyGully I Sector 10 Dwarka'!I9+'RallyGully I Sector 83 Gurgaon'!I9+'RallyGully I East of Kailash'!I9+'RallyGully I Sector 19 Dwarka'!I9+'RallyGully | LCR Pune'!I9+'RallyGully | DPSG'!I9+'RallyGully | Gandipath'!I9+'RallyGully | Panchsheel'!I9) -> 263500 | J25: =SUM('RallyGully I Sector 10 Dwarka'!J9+'RallyGully I Sector 83 Gurgaon'!J9+'RallyGully I East of Kailash'!J9+'RallyGully I Sector 19 Dwarka'!J9+'RallyGully | LCR Pune'!J9+'RallyGully | DPSG'!J9+'RallyGully | Gandipath'!J9+'RallyGully | Panchsheel'!J9+'Powerplay Park, Pune'!J9+'Commons, Noida'!J9) -> 263802 | K25: =SUM('RallyGully I Sector 10 Dwarka'!K9+'RallyGully I Sector 83 Gurgaon'!K9+'RallyGully I East of Kailash'!K9+'RallyGully I Sector 19 Dwarka'!K9+'RallyGully | LCR Pune'!K9+'RallyGully | DPSG'!K9+'RallyGully | Gandipath'!K9+'RallyGully | Panchsheel'!K9+'Powerplay Park, Pune'!K9+'Commons, Noida'!K9) -> 377943
A26: 2.2 | B26: Playo | C26: =SUM('RallyGully I Sector 10 Dwarka'!C10+'RallyGully I Sector 83 Gurgaon'!C10+'RallyGully I East of Kailash'!C10+'RallyGully I Sector 19 Dwarka'!C10+'RallyGully | LCR Pune'!C10+'RallyGully | DPSG'!C10+'RallyGully | Gandipath'!C10+'RallyGully | Panchsheel'!C10) -> 14840 | D26: =SUM('RallyGully I Sector 10 Dwarka'!D10+'RallyGully I Sector 83 Gurgaon'!D10+'RallyGully I East of Kailash'!D10+'RallyGully I Sector 19 Dwarka'!D10+'RallyGully | LCR Pune'!D10+'RallyGully | DPSG'!D10+'RallyGully | Gandipath'!D10+'RallyGully | Panchsheel'!D10) -> 46790 | E26: =SUM('RallyGully I Sector 10 Dwarka'!E10+'RallyGully I Sector 83 Gurgaon'!E10+'RallyGully I East of Kailash'!E10+'RallyGully I Sector 19 Dwarka'!E10+'RallyGully | LCR Pune'!E10+'RallyGully | DPSG'!E10+'RallyGully | Gandipath'!E10+'RallyGully | Panchsheel'!E10) -> 32658.8 | F26: =SUM('RallyGully I Sector 10 Dwarka'!F10+'RallyGully I Sector 83 Gurgaon'!F10+'RallyGully I East of Kailash'!F10+'RallyGully I Sector 19 Dwarka'!F10+'RallyGully | LCR Pune'!F10+'RallyGully | DPSG'!F10+'RallyGully | Gandipath'!F10+'RallyGully | Panchsheel'!F10) -> 30067.6 | G26: =SUM('RallyGully I Sector 10 Dwarka'!G10+'RallyGully I Sector 83 Gurgaon'!G10+'RallyGully I East of Kailash'!G10+'RallyGully I Sector 19 Dwarka'!G10+'RallyGully | LCR Pune'!G10+'RallyGully | DPSG'!G10+'RallyGully | Gandipath'!G10+'RallyGully | Panchsheel'!G10) -> 27305 | H26: =SUM('RallyGully I Sector 10 Dwarka'!H10+'RallyGully I Sector 83 Gurgaon'!H10+'RallyGully I East of Kailash'!H10+'RallyGully I Sector 19 Dwarka'!H10+'RallyGully | LCR Pune'!H10+'RallyGully | DPSG'!H10+'RallyGully | Gandipath'!H10+'RallyGully | Panchsheel'!H10) -> 45577 | I26: =SUM('RallyGully I Sector 10 Dwarka'!I10+'RallyGully I Sector 83 Gurgaon'!I10+'RallyGully I East of Kailash'!I10+'RallyGully I Sector 19 Dwarka'!I10+'RallyGully | LCR Pune'!I10+'RallyGully | DPSG'!I10+'RallyGully | Gandipath'!I10+'RallyGully | Panchsheel'!I10) -> 93017 | J26: =SUM('RallyGully I Sector 10 Dwarka'!J10+'RallyGully I Sector 83 Gurgaon'!J10+'RallyGully I East of Kailash'!J10+'RallyGully I Sector 19 Dwarka'!J10+'RallyGully | LCR Pune'!J10+'RallyGully | DPSG'!J10+'RallyGully | Gandipath'!J10+'RallyGully | Panchsheel'!J10+'Powerplay Park, Pune'!J10+'Commons, Noida'!J10) -> 87503 | K26: =SUM('RallyGully I Sector 10 Dwarka'!K10+'RallyGully I Sector 83 Gurgaon'!K10+'RallyGully I East of Kailash'!K10+'RallyGully I Sector 19 Dwarka'!K10+'RallyGully | LCR Pune'!K10+'RallyGully | DPSG'!K10+'RallyGully | Gandipath'!K10+'RallyGully | Panchsheel'!K10+'Powerplay Park, Pune'!K10+'Commons, Noida'!K10) -> 123355
A27: 2.3 | B27: District | C27: =SUM('RallyGully I Sector 10 Dwarka'!C11+'RallyGully I Sector 83 Gurgaon'!C11+'RallyGully I East of Kailash'!C11+'RallyGully I Sector 19 Dwarka'!C11+'RallyGully | LCR Pune'!C11+'RallyGully | DPSG'!C11+'RallyGully | Gandipath'!C11+'RallyGully | Panchsheel'!C11) -> 0 | D27: =SUM('RallyGully I Sector 10 Dwarka'!D11+'RallyGully I Sector 83 Gurgaon'!D11+'RallyGully I East of Kailash'!D11+'RallyGully I Sector 19 Dwarka'!D11+'RallyGully | LCR Pune'!D11+'RallyGully | DPSG'!D11+'RallyGully | Gandipath'!D11+'RallyGully | Panchsheel'!D11) -> 0 | E27: =SUM('RallyGully I Sector 10 Dwarka'!E11+'RallyGully I Sector 83 Gurgaon'!E11+'RallyGully I East of Kailash'!E11+'RallyGully I Sector 19 Dwarka'!E11+'RallyGully | LCR Pune'!E11+'RallyGully | DPSG'!E11+'RallyGully | Gandipath'!E11+'RallyGully | Panchsheel'!E11) -> 0 | F27: =SUM('RallyGully I Sector 10 Dwarka'!F11+'RallyGully I Sector 83 Gurgaon'!F11+'RallyGully I East of Kailash'!F11+'RallyGully I Sector 19 Dwarka'!F11+'RallyGully | LCR Pune'!F11+'RallyGully | DPSG'!F11+'RallyGully | Gandipath'!F11+'RallyGully | Panchsheel'!F11) -> 1200 | G27: =SUM('RallyGully I Sector 10 Dwarka'!G11+'RallyGully I Sector 83 Gurgaon'!G11+'RallyGully I East of Kailash'!G11+'RallyGully I Sector 19 Dwarka'!G11+'RallyGully | LCR Pune'!G11+'RallyGully | DPSG'!G11+'RallyGully | Gandipath'!G11+'RallyGully | Panchsheel'!G11) -> 3106 | H27: =SUM('RallyGully I Sector 10 Dwarka'!H11+'RallyGully I Sector 83 Gurgaon'!H11+'RallyGully I East of Kailash'!H11+'RallyGully I Sector 19 Dwarka'!H11+'RallyGully | LCR Pune'!H11+'RallyGully | DPSG'!H11+'RallyGully | Gandipath'!H11+'RallyGully | Panchsheel'!H11) -> 18150 | I27: =SUM('RallyGully I Sector 10 Dwarka'!I11+'RallyGully I Sector 83 Gurgaon'!I11+'RallyGully I East of Kailash'!I11+'RallyGully I Sector 19 Dwarka'!I11+'RallyGully | LCR Pune'!I11+'RallyGully | DPSG'!I11+'RallyGully | Gandipath'!I11+'RallyGully | Panchsheel'!I11) -> 101150 | J27: =SUM('RallyGully I Sector 10 Dwarka'!J11+'RallyGully I Sector 83 Gurgaon'!J11+'RallyGully I East of Kailash'!J11+'RallyGully I Sector 19 Dwarka'!J11+'RallyGully | LCR Pune'!J11+'RallyGully | DPSG'!J11+'RallyGully | Gandipath'!J11+'RallyGully | Panchsheel'!J11+'Powerplay Park, Pune'!J11+'Commons, Noida'!J11) -> 163600 | K27: =SUM('RallyGully I Sector 10 Dwarka'!K11+'RallyGully I Sector 83 Gurgaon'!K11+'RallyGully I East of Kailash'!K11+'RallyGully I Sector 19 Dwarka'!K11+'RallyGully | LCR Pune'!K11+'RallyGully | DPSG'!K11+'RallyGully | Gandipath'!K11+'RallyGully | Panchsheel'!K11+'Powerplay Park, Pune'!K11+'Commons, Noida'!K11) -> 209600
A28: 2.4 | B28: Khelomore | C28: =SUM('RallyGully I Sector 10 Dwarka'!C12+'RallyGully I Sector 83 Gurgaon'!C12+'RallyGully I East of Kailash'!C12+'RallyGully I Sector 19 Dwarka'!C12+'RallyGully | LCR Pune'!C12+'RallyGully | DPSG'!C12+'RallyGully | Gandipath'!C12+'RallyGully | Panchsheel'!C12) -> 0 | D28: =SUM('RallyGully I Sector 10 Dwarka'!D12+'RallyGully I Sector 83 Gurgaon'!D12+'RallyGully I East of Kailash'!D12+'RallyGully I Sector 19 Dwarka'!D12+'RallyGully | LCR Pune'!D12+'RallyGully | DPSG'!D12+'RallyGully | Gandipath'!D12+'RallyGully | Panchsheel'!D12) -> 10682 | E28: =SUM('RallyGully I Sector 10 Dwarka'!E12+'RallyGully I Sector 83 Gurgaon'!E12+'RallyGully I East of Kailash'!E12+'RallyGully I Sector 19 Dwarka'!E12+'RallyGully | LCR Pune'!E12+'RallyGully | DPSG'!E12+'RallyGully | Gandipath'!E12+'RallyGully | Panchsheel'!E12) -> 6154 | F28: =SUM('RallyGully I Sector 10 Dwarka'!F12+'RallyGully I Sector 83 Gurgaon'!F12+'RallyGully I East of Kailash'!F12+'RallyGully I Sector 19 Dwarka'!F12+'RallyGully | LCR Pune'!F12+'RallyGully | DPSG'!F12+'RallyGully | Gandipath'!F12+'RallyGully | Panchsheel'!F12) -> 10500 | G28: =SUM('RallyGully I Sector 10 Dwarka'!G12+'RallyGully I Sector 83 Gurgaon'!G12+'RallyGully I East of Kailash'!G12+'RallyGully I Sector 19 Dwarka'!G12+'RallyGully | LCR Pune'!G12+'RallyGully | DPSG'!G12+'RallyGully | Gandipath'!G12+'RallyGully | Panchsheel'!G12) -> 30333 | H28: =SUM('RallyGully I Sector 10 Dwarka'!H12+'RallyGully I Sector 83 Gurgaon'!H12+'RallyGully I East of Kailash'!H12+'RallyGully I Sector 19 Dwarka'!H12+'RallyGully | LCR Pune'!H12+'RallyGully | DPSG'!H12+'RallyGully | Gandipath'!H12+'RallyGully | Panchsheel'!H12) -> 42525 | I28: =SUM('RallyGully I Sector 10 Dwarka'!I12+'RallyGully I Sector 83 Gurgaon'!I12+'RallyGully I East of Kailash'!I12+'RallyGully I Sector 19 Dwarka'!I12+'RallyGully | LCR Pune'!I12+'RallyGully | DPSG'!I12+'RallyGully | Gandipath'!I12+'RallyGully | Panchsheel'!I12) -> 37394 | J28: =SUM('RallyGully I Sector 10 Dwarka'!J12+'RallyGully I Sector 83 Gurgaon'!J12+'RallyGully I East of Kailash'!J12+'RallyGully I Sector 19 Dwarka'!J12+'RallyGully | LCR Pune'!J12+'RallyGully | DPSG'!J12+'RallyGully | Gandipath'!J12+'RallyGully | Panchsheel'!J12+'Powerplay Park, Pune'!J12+'Commons, Noida'!J12) -> 47546 | K28: =SUM('RallyGully I Sector 10 Dwarka'!K12+'RallyGully I Sector 83 Gurgaon'!K12+'RallyGully I East of Kailash'!K12+'RallyGully I Sector 19 Dwarka'!K12+'RallyGully | LCR Pune'!K12+'RallyGully | DPSG'!K12+'RallyGully | Gandipath'!K12+'RallyGully | Panchsheel'!K12+'Powerplay Park, Pune'!K12+'Commons, Noida'!K12) -> 55690
A29: 2.5 | B29: Zplys | C29: =SUM('RallyGully I Sector 10 Dwarka'!C13+'RallyGully I Sector 83 Gurgaon'!C13+'RallyGully I East of Kailash'!C13+'RallyGully I Sector 19 Dwarka'!C13+'RallyGully | LCR Pune'!C13+'RallyGully | DPSG'!C13+'RallyGully | Gandipath'!C13+'RallyGully | Panchsheel'!C13) -> 0 | D29: =SUM('RallyGully I Sector 10 Dwarka'!D13+'RallyGully I Sector 83 Gurgaon'!D13+'RallyGully I East of Kailash'!D13+'RallyGully I Sector 19 Dwarka'!D13+'RallyGully | LCR Pune'!D13+'RallyGully | DPSG'!D13+'RallyGully | Gandipath'!D13+'RallyGully | Panchsheel'!D13) -> 0 | E29: =SUM('RallyGully I Sector 10 Dwarka'!E13+'RallyGully I Sector 83 Gurgaon'!E13+'RallyGully I East of Kailash'!E13+'RallyGully I Sector 19 Dwarka'!E13+'RallyGully | LCR Pune'!E13+'RallyGully | DPSG'!E13+'RallyGully | Gandipath'!E13+'RallyGully | Panchsheel'!E13) -> 0 | F29: =SUM('RallyGully I Sector 10 Dwarka'!F13+'RallyGully I Sector 83 Gurgaon'!F13+'RallyGully I East of Kailash'!F13+'RallyGully I Sector 19 Dwarka'!F13+'RallyGully | LCR Pune'!F13+'RallyGully | DPSG'!F13+'RallyGully | Gandipath'!F13+'RallyGully | Panchsheel'!F13) -> 0 | G29: =SUM('RallyGully I Sector 10 Dwarka'!G13+'RallyGully I Sector 83 Gurgaon'!G13+'RallyGully I East of Kailash'!G13+'RallyGully I Sector 19 Dwarka'!G13+'RallyGully | LCR Pune'!G13+'RallyGully | DPSG'!G13+'RallyGully | Gandipath'!G13+'RallyGully | Panchsheel'!G13) -> 0 | H29: =SUM('RallyGully I Sector 10 Dwarka'!H13+'RallyGully I Sector 83 Gurgaon'!H13+'RallyGully I East of Kailash'!H13+'RallyGully I Sector 19 Dwarka'!H13+'RallyGully | LCR Pune'!H13+'RallyGully | DPSG'!H13+'RallyGully | Gandipath'!H13+'RallyGully | Panchsheel'!H13) -> 1250 | I29: =SUM('RallyGully I Sector 10 Dwarka'!I13+'RallyGully I Sector 83 Gurgaon'!I13+'RallyGully I East of Kailash'!I13+'RallyGully I Sector 19 Dwarka'!I13+'RallyGully | LCR Pune'!I13+'RallyGully | DPSG'!I13+'RallyGully | Gandipath'!I13+'RallyGully | Panchsheel'!I13) -> 25373 | J29: =SUM('RallyGully I Sector 10 Dwarka'!J13+'RallyGully I Sector 83 Gurgaon'!J13+'RallyGully I East of Kailash'!J13+'RallyGully I Sector 19 Dwarka'!J13+'RallyGully | LCR Pune'!J13+'RallyGully | DPSG'!J13+'RallyGully | Gandipath'!J13+'RallyGully | Panchsheel'!J13+'Powerplay Park, Pune'!J13+'Commons, Noida'!J13) -> 40658 | K29: =SUM('RallyGully I Sector 10 Dwarka'!K13+'RallyGully I Sector 83 Gurgaon'!K13+'RallyGully I East of Kailash'!K13+'RallyGully I Sector 19 Dwarka'!K13+'RallyGully | LCR Pune'!K13+'RallyGully | DPSG'!K13+'RallyGully | Gandipath'!K13+'RallyGully | Panchsheel'!K13+'Powerplay Park, Pune'!K13+'Commons, Noida'!K13) -> 95125
A30: 3 | B30: Community | C30: =SUM('RallyGully I Sector 10 Dwarka'!C14+'RallyGully I Sector 83 Gurgaon'!C14+'RallyGully I East of Kailash'!C14+'RallyGully I Sector 19 Dwarka'!C14+'RallyGully | LCR Pune'!C14+'RallyGully | DPSG'!C14+'RallyGully | Gandipath'!C14+'RallyGully | Panchsheel'!C14) -> 10500 | D30: =SUM('RallyGully I Sector 10 Dwarka'!D14+'RallyGully I Sector 83 Gurgaon'!D14+'RallyGully I East of Kailash'!D14+'RallyGully I Sector 19 Dwarka'!D14+'RallyGully | LCR Pune'!D14+'RallyGully | DPSG'!D14+'RallyGully | Gandipath'!D14+'RallyGully | Panchsheel'!D14) -> 15087 | E30: =SUM('RallyGully I Sector 10 Dwarka'!E14+'RallyGully I Sector 83 Gurgaon'!E14+'RallyGully I East of Kailash'!E14+'RallyGully I Sector 19 Dwarka'!E14+'RallyGully | LCR Pune'!E14+'RallyGully | DPSG'!E14+'RallyGully | Gandipath'!E14+'RallyGully | Panchsheel'!E14) -> 29490 | F30: =SUM('RallyGully I Sector 10 Dwarka'!F14+'RallyGully I Sector 83 Gurgaon'!F14+'RallyGully I East of Kailash'!F14+'RallyGully I Sector 19 Dwarka'!F14+'RallyGully | LCR Pune'!F14+'RallyGully | DPSG'!F14+'RallyGully | Gandipath'!F14+'RallyGully | Panchsheel'!F14) -> 40340 | G30: =SUM('RallyGully I Sector 10 Dwarka'!G14+'RallyGully I Sector 83 Gurgaon'!G14+'RallyGully I East of Kailash'!G14+'RallyGully I Sector 19 Dwarka'!G14+'RallyGully | LCR Pune'!G14+'RallyGully | DPSG'!G14+'RallyGully | Gandipath'!G14+'RallyGully | Panchsheel'!G14) -> 40260 | H30: =SUM('RallyGully I Sector 10 Dwarka'!H14+'RallyGully I Sector 83 Gurgaon'!H14+'RallyGully I East of Kailash'!H14+'RallyGully I Sector 19 Dwarka'!H14+'RallyGully | LCR Pune'!H14+'RallyGully | DPSG'!H14+'RallyGully | Gandipath'!H14+'RallyGully | Panchsheel'!H14) -> 31109 | I30: =SUM('RallyGully I Sector 10 Dwarka'!I14+'RallyGully I Sector 83 Gurgaon'!I14+'RallyGully I East of Kailash'!I14+'RallyGully I Sector 19 Dwarka'!I14+'RallyGully | LCR Pune'!I14+'RallyGully | DPSG'!I14+'RallyGully | Gandipath'!I14+'RallyGully | Panchsheel'!I14) -> 131439 | J30: =SUM('RallyGully I Sector 10 Dwarka'!J14+'RallyGully I Sector 83 Gurgaon'!J14+'RallyGully I East of Kailash'!J14+'RallyGully I Sector 19 Dwarka'!J14+'RallyGully | LCR Pune'!J14+'RallyGully | DPSG'!J14+'RallyGully | Gandipath'!J14+'RallyGully | Panchsheel'!J14+'Powerplay Park, Pune'!J14+'Commons, Noida'!J14) -> 176514 | K30: =SUM('RallyGully I Sector 10 Dwarka'!K14+'RallyGully I Sector 83 Gurgaon'!K14+'RallyGully I East of Kailash'!K14+'RallyGully I Sector 19 Dwarka'!K14+'RallyGully | LCR Pune'!K14+'RallyGully | DPSG'!K14+'RallyGully | Gandipath'!K14+'RallyGully | Panchsheel'!K14+'Powerplay Park, Pune'!K14+'Commons, Noida'!K14) -> 256304
A31: 3.1 | B31: Courtly (Organized by RallyGully) | C31: =SUM('RallyGully I Sector 10 Dwarka'!C15+'RallyGully I Sector 83 Gurgaon'!C15+'RallyGully I East of Kailash'!C15+'RallyGully I Sector 19 Dwarka'!C15+'RallyGully | LCR Pune'!C15+'RallyGully | DPSG'!C15+'RallyGully | Gandipath'!C15+'RallyGully | Panchsheel'!C15) -> 0 | D31: =SUM('RallyGully I Sector 10 Dwarka'!D15+'RallyGully I Sector 83 Gurgaon'!D15+'RallyGully I East of Kailash'!D15+'RallyGully I Sector 19 Dwarka'!D15+'RallyGully | LCR Pune'!D15+'RallyGully | DPSG'!D15+'RallyGully | Gandipath'!D15+'RallyGully | Panchsheel'!D15) -> 0 | E31: =SUM('RallyGully I Sector 10 Dwarka'!E15+'RallyGully I Sector 83 Gurgaon'!E15+'RallyGully I East of Kailash'!E15+'RallyGully I Sector 19 Dwarka'!E15+'RallyGully | LCR Pune'!E15+'RallyGully | DPSG'!E15+'RallyGully | Gandipath'!E15+'RallyGully | Panchsheel'!E15) -> 0 | F31: =SUM('RallyGully I Sector 10 Dwarka'!F15+'RallyGully I Sector 83 Gurgaon'!F15+'RallyGully I East of Kailash'!F15+'RallyGully I Sector 19 Dwarka'!F15+'RallyGully | LCR Pune'!F15+'RallyGully | DPSG'!F15+'RallyGully | Gandipath'!F15+'RallyGully | Panchsheel'!F15) -> 0 | G31: =SUM('RallyGully I Sector 10 Dwarka'!G15+'RallyGully I Sector 83 Gurgaon'!G15+'RallyGully I East of Kailash'!G15+'RallyGully I Sector 19 Dwarka'!G15+'RallyGully | LCR Pune'!G15+'RallyGully | DPSG'!G15+'RallyGully | Gandipath'!G15+'RallyGully | Panchsheel'!G15) -> 8500 | H31: =SUM('RallyGully I Sector 10 Dwarka'!H15+'RallyGully I Sector 83 Gurgaon'!H15+'RallyGully I East of Kailash'!H15+'RallyGully I Sector 19 Dwarka'!H15+'RallyGully | LCR Pune'!H15+'RallyGully | DPSG'!H15+'RallyGully | Gandipath'!H15+'RallyGully | Panchsheel'!H15) -> 0 | I31: =SUM('RallyGully I Sector 10 Dwarka'!I15+'RallyGully I Sector 83 Gurgaon'!I15+'RallyGully I East of Kailash'!I15+'RallyGully I Sector 19 Dwarka'!I15+'RallyGully | LCR Pune'!I15+'RallyGully | DPSG'!I15+'RallyGully | Gandipath'!I15+'RallyGully | Panchsheel'!I15) -> 38300 | J31: =SUM('RallyGully I Sector 10 Dwarka'!J15+'RallyGully I Sector 83 Gurgaon'!J15+'RallyGully I East of Kailash'!J15+'RallyGully I Sector 19 Dwarka'!J15+'RallyGully | LCR Pune'!J15+'RallyGully | DPSG'!J15+'RallyGully | Gandipath'!J15+'RallyGully | Panchsheel'!J15) -> 55200 | K31: =SUM('RallyGully I Sector 10 Dwarka'!K15+'RallyGully I Sector 83 Gurgaon'!K15+'RallyGully I East of Kailash'!K15+'RallyGully I Sector 19 Dwarka'!K15+'RallyGully | LCR Pune'!K15+'RallyGully | DPSG'!K15+'RallyGully | Gandipath'!K15+'RallyGully | Panchsheel'!K15+'Powerplay Park, Pune'!K15+'Commons, Noida'!K15) -> 93300
A32: 3.2 | B32: Sportomic (Organized by RallyGully) | C32: =SUM('RallyGully I Sector 10 Dwarka'!C16+'RallyGully I Sector 83 Gurgaon'!C16+'RallyGully I East of Kailash'!C16+'RallyGully I Sector 19 Dwarka'!C16+'RallyGully | LCR Pune'!C16+'RallyGully | DPSG'!C16+'RallyGully | Gandipath'!C16+'RallyGully | Panchsheel'!C16) -> 0 | D32: =SUM('RallyGully I Sector 10 Dwarka'!D16+'RallyGully I Sector 83 Gurgaon'!D16+'RallyGully I East of Kailash'!D16+'RallyGully I Sector 19 Dwarka'!D16+'RallyGully | LCR Pune'!D16+'RallyGully | DPSG'!D16+'RallyGully | Gandipath'!D16+'RallyGully | Panchsheel'!D16) -> 0 | E32: =SUM('RallyGully I Sector 10 Dwarka'!E16+'RallyGully I Sector 83 Gurgaon'!E16+'RallyGully I East of Kailash'!E16+'RallyGully I Sector 19 Dwarka'!E16+'RallyGully | LCR Pune'!E16+'RallyGully | DPSG'!E16+'RallyGully | Gandipath'!E16+'RallyGully | Panchsheel'!E16) -> 0 | F32: =SUM('RallyGully I Sector 10 Dwarka'!F16+'RallyGully I Sector 83 Gurgaon'!F16+'RallyGully I East of Kailash'!F16+'RallyGully I Sector 19 Dwarka'!F16+'RallyGully | LCR Pune'!F16+'RallyGully | DPSG'!F16+'RallyGully | Gandipath'!F16+'RallyGully | Panchsheel'!F16) -> 0 | G32: =SUM('RallyGully I Sector 10 Dwarka'!G16+'RallyGully I Sector 83 Gurgaon'!G16+'RallyGully I East of Kailash'!G16+'RallyGully I Sector 19 Dwarka'!G16+'RallyGully | LCR Pune'!G16+'RallyGully | DPSG'!G16+'RallyGully | Gandipath'!G16+'RallyGully | Panchsheel'!G16) -> 0 | H32: =SUM('RallyGully I Sector 10 Dwarka'!H16+'RallyGully I Sector 83 Gurgaon'!H16+'RallyGully I East of Kailash'!H16+'RallyGully I Sector 19 Dwarka'!H16+'RallyGully | LCR Pune'!H16+'RallyGully | DPSG'!H16+'RallyGully | Gandipath'!H16+'RallyGully | Panchsheel'!H16) -> 23290 | I32: =SUM('RallyGully I Sector 10 Dwarka'!I16+'RallyGully I Sector 83 Gurgaon'!I16+'RallyGully I East of Kailash'!I16+'RallyGully I Sector 19 Dwarka'!I16+'RallyGully | LCR Pune'!I16+'RallyGully | DPSG'!I16+'RallyGully | Gandipath'!I16+'RallyGully | Panchsheel'!I16) -> 13650 | J32: =SUM('RallyGully I Sector 10 Dwarka'!J16+'RallyGully I Sector 83 Gurgaon'!J16+'RallyGully I East of Kailash'!J16+'RallyGully I Sector 19 Dwarka'!J16+'RallyGully | LCR Pune'!J16+'RallyGully | DPSG'!J16+'RallyGully | Gandipath'!J16+'RallyGully | Panchsheel'!J16) -> 42360 | K32: =SUM('RallyGully I Sector 10 Dwarka'!K16+'RallyGully I Sector 83 Gurgaon'!K16+'RallyGully I East of Kailash'!K16+'RallyGully I Sector 19 Dwarka'!K16+'RallyGully | LCR Pune'!K16+'RallyGully | DPSG'!K16+'RallyGully | Gandipath'!K16+'RallyGully | Panchsheel'!K16+'Powerplay Park, Pune'!K16+'Commons, Noida'!K16) -> 29390
A33: 3.3 | B33: Rallygully Community games | C33: =SUM('RallyGully I Sector 10 Dwarka'!C17+'RallyGully I Sector 83 Gurgaon'!C17+'RallyGully I East of Kailash'!C17+'RallyGully I Sector 19 Dwarka'!C17+'RallyGully | LCR Pune'!C17+'RallyGully | DPSG'!C17+'RallyGully | Gandipath'!C17+'RallyGully | Panchsheel'!C17) -> 10500 | D33: =SUM('RallyGully I Sector 10 Dwarka'!D17+'RallyGully I Sector 83 Gurgaon'!D17+'RallyGully I East of Kailash'!D17+'RallyGully I Sector 19 Dwarka'!D17+'RallyGully | LCR Pune'!D17+'RallyGully | DPSG'!D17+'RallyGully | Gandipath'!D17+'RallyGully | Panchsheel'!D17) -> 15087 | E33: =SUM('RallyGully I Sector 10 Dwarka'!E17+'RallyGully I Sector 83 Gurgaon'!E17+'RallyGully I East of Kailash'!E17+'RallyGully I Sector 19 Dwarka'!E17+'RallyGully | LCR Pune'!E17+'RallyGully | DPSG'!E17+'RallyGully | Gandipath'!E17+'RallyGully | Panchsheel'!E17) -> 19900 | F33: =SUM('RallyGully I Sector 10 Dwarka'!F17+'RallyGully I Sector 83 Gurgaon'!F17+'RallyGully I East of Kailash'!F17+'RallyGully I Sector 19 Dwarka'!F17+'RallyGully | LCR Pune'!F17+'RallyGully | DPSG'!F17+'RallyGully | Gandipath'!F17+'RallyGully | Panchsheel'!F17) -> 28350 | G33: =SUM('RallyGully I Sector 10 Dwarka'!G17+'RallyGully I Sector 83 Gurgaon'!G17+'RallyGully I East of Kailash'!G17+'RallyGully I Sector 19 Dwarka'!G17+'RallyGully | LCR Pune'!G17+'RallyGully | DPSG'!G17+'RallyGully | Gandipath'!G17+'RallyGully | Panchsheel'!G17) -> 20780 | H33: =SUM('RallyGully I Sector 10 Dwarka'!H17+'RallyGully I Sector 83 Gurgaon'!H17+'RallyGully I East of Kailash'!H17+'RallyGully I Sector 19 Dwarka'!H17+'RallyGully | LCR Pune'!H17+'RallyGully | DPSG'!H17+'RallyGully | Gandipath'!H17+'RallyGully | Panchsheel'!H17) -> 2510 | I33: =SUM('RallyGully I Sector 10 Dwarka'!I17+'RallyGully I Sector 83 Gurgaon'!I17+'RallyGully I East of Kailash'!I17+'RallyGully I Sector 19 Dwarka'!I17+'RallyGully | LCR Pune'!I17+'RallyGully | DPSG'!I17+'RallyGully | Gandipath'!I17+'RallyGully | Panchsheel'!I17) -> 79489 | J33: =SUM('RallyGully I Sector 10 Dwarka'!J17+'RallyGully I Sector 83 Gurgaon'!J17+'RallyGully I East of Kailash'!J17+'RallyGully I Sector 19 Dwarka'!J17+'RallyGully | LCR Pune'!J17+'RallyGully | DPSG'!J17+'RallyGully | Gandipath'!J17+'RallyGully | Panchsheel'!J17) -> 63275 | K33: =SUM('RallyGully I Sector 10 Dwarka'!K17+'RallyGully I Sector 83 Gurgaon'!K17+'RallyGully I East of Kailash'!K17+'RallyGully I Sector 19 Dwarka'!K17+'RallyGully | LCR Pune'!K17+'RallyGully | DPSG'!K17+'RallyGully | Gandipath'!K17+'RallyGully | Panchsheel'!K17+'Powerplay Park, Pune'!K17+'Commons, Noida'!K17) -> 125670
A34: 3.4 | B34: Misfits Community | C34: =SUM('RallyGully I Sector 10 Dwarka'!C18+'RallyGully I Sector 83 Gurgaon'!C18+'RallyGully I East of Kailash'!C18+'RallyGully I Sector 19 Dwarka'!C18+'RallyGully | LCR Pune'!C18+'RallyGully | DPSG'!C18+'RallyGully | Gandipath'!C18+'RallyGully | Panchsheel'!C18) -> 0 | D34: =SUM('RallyGully I Sector 10 Dwarka'!D18+'RallyGully I Sector 83 Gurgaon'!D18+'RallyGully I East of Kailash'!D18+'RallyGully I Sector 19 Dwarka'!D18+'RallyGully | LCR Pune'!D18+'RallyGully | DPSG'!D18+'RallyGully | Gandipath'!D18+'RallyGully | Panchsheel'!D18) -> 0 | E34: =SUM('RallyGully I Sector 10 Dwarka'!E18+'RallyGully I Sector 83 Gurgaon'!E18+'RallyGully I East of Kailash'!E18+'RallyGully I Sector 19 Dwarka'!E18+'RallyGully | LCR Pune'!E18+'RallyGully | DPSG'!E18+'RallyGully | Gandipath'!E18+'RallyGully | Panchsheel'!E18) -> 9590 | F34: =SUM('RallyGully I Sector 10 Dwarka'!F18+'RallyGully I Sector 83 Gurgaon'!F18+'RallyGully I East of Kailash'!F18+'RallyGully I Sector 19 Dwarka'!F18+'RallyGully | LCR Pune'!F18+'RallyGully | DPSG'!F18+'RallyGully | Gandipath'!F18+'RallyGully | Panchsheel'!F18) -> 11990 | G34: =SUM('RallyGully I Sector 10 Dwarka'!G18+'RallyGully I Sector 83 Gurgaon'!G18+'RallyGully I East of Kailash'!G18+'RallyGully I Sector 19 Dwarka'!G18+'RallyGully | LCR Pune'!G18+'RallyGully | DPSG'!G18+'RallyGully | Gandipath'!G18+'RallyGully | Panchsheel'!G18) -> 10980 | H34: =SUM('RallyGully I Sector 10 Dwarka'!H18+'RallyGully I Sector 83 Gurgaon'!H18+'RallyGully I East of Kailash'!H18+'RallyGully I Sector 19 Dwarka'!H18+'RallyGully | LCR Pune'!H18+'RallyGully | DPSG'!H18+'RallyGully | Gandipath'!H18+'RallyGully | Panchsheel'!H18) -> 5309 | I34: =SUM('RallyGully I Sector 10 Dwarka'!I18+'RallyGully I Sector 83 Gurgaon'!I18+'RallyGully I East of Kailash'!I18+'RallyGully I Sector 19 Dwarka'!I18+'RallyGully | LCR Pune'!I18+'RallyGully | DPSG'!I18+'RallyGully | Gandipath'!I18+'RallyGully | Panchsheel'!I18) -> 0 | J34: =SUM('RallyGully I Sector 10 Dwarka'!J18+'RallyGully I Sector 83 Gurgaon'!J18+'RallyGully I East of Kailash'!J18+'RallyGully I Sector 19 Dwarka'!J18+'RallyGully | LCR Pune'!J18+'RallyGully | DPSG'!J18+'RallyGully | Gandipath'!J18+'RallyGully | Panchsheel'!J18) -> 15679 | K34: =SUM('RallyGully I Sector 10 Dwarka'!K18+'RallyGully I Sector 83 Gurgaon'!K18+'RallyGully I East of Kailash'!K18+'RallyGully I Sector 19 Dwarka'!K18+'RallyGully | LCR Pune'!K18+'RallyGully | DPSG'!K18+'RallyGully | Gandipath'!K18+'RallyGully | Panchsheel'!K18+'Powerplay Park, Pune'!K18+'Commons, Noida'!K18) -> 7944
A35: 4 | B35: Memberships | C35: =SUM('RallyGully I Sector 10 Dwarka'!C19+'RallyGully I Sector 83 Gurgaon'!C19+'RallyGully I East of Kailash'!C19+'RallyGully I Sector 19 Dwarka'!C19+'RallyGully | LCR Pune'!C19+'RallyGully | DPSG'!C19+'RallyGully | Gandipath'!C19+'RallyGully | Panchsheel'!C19) -> 0 | D35: =SUM('RallyGully I Sector 10 Dwarka'!D19+'RallyGully I Sector 83 Gurgaon'!D19+'RallyGully I East of Kailash'!D19+'RallyGully I Sector 19 Dwarka'!D19+'RallyGully | LCR Pune'!D19+'RallyGully | DPSG'!D19+'RallyGully | Gandipath'!D19+'RallyGully | Panchsheel'!D19) -> 50000 | E35: =SUM('RallyGully I Sector 10 Dwarka'!E19+'RallyGully I Sector 83 Gurgaon'!E19+'RallyGully I East of Kailash'!E19+'RallyGully I Sector 19 Dwarka'!E19+'RallyGully | LCR Pune'!E19+'RallyGully | DPSG'!E19+'RallyGully | Gandipath'!E19+'RallyGully | Panchsheel'!E19) -> 27000 | F35: =SUM('RallyGully I Sector 10 Dwarka'!F19+'RallyGully I Sector 83 Gurgaon'!F19+'RallyGully I East of Kailash'!F19+'RallyGully I Sector 19 Dwarka'!F19+'RallyGully | LCR Pune'!F19+'RallyGully | DPSG'!F19+'RallyGully | Gandipath'!F19+'RallyGully | Panchsheel'!F19) -> 91300 | G35: =SUM('RallyGully I Sector 10 Dwarka'!G19+'RallyGully I Sector 83 Gurgaon'!G19+'RallyGully I East of Kailash'!G19+'RallyGully I Sector 19 Dwarka'!G19+'RallyGully | LCR Pune'!G19+'RallyGully | DPSG'!G19+'RallyGully | Gandipath'!G19+'RallyGully | Panchsheel'!G19) -> 74380 | H35: =SUM('RallyGully I Sector 10 Dwarka'!H19+'RallyGully I Sector 83 Gurgaon'!H19+'RallyGully I East of Kailash'!H19+'RallyGully I Sector 19 Dwarka'!H19+'RallyGully | LCR Pune'!H19+'RallyGully | DPSG'!H19+'RallyGully | Gandipath'!H19+'RallyGully | Panchsheel'!H19) -> 99380 | I35: =SUM('RallyGully I Sector 10 Dwarka'!I19+'RallyGully I Sector 83 Gurgaon'!I19+'RallyGully I East of Kailash'!I19+'RallyGully I Sector 19 Dwarka'!I19+'RallyGully | LCR Pune'!I19+'RallyGully | DPSG'!I19+'RallyGully | Gandipath'!I19+'RallyGully | Panchsheel'!I19) -> 79480 | J35: =SUM('RallyGully I Sector 10 Dwarka'!J19+'RallyGully I Sector 83 Gurgaon'!J19+'RallyGully I East of Kailash'!J19+'RallyGully I Sector 19 Dwarka'!J19+'RallyGully | LCR Pune'!J19+'RallyGully | DPSG'!J19+'RallyGully | Gandipath'!J19+'RallyGully | Panchsheel'!J19+'Powerplay Park, Pune'!J19+'Commons, Noida'!J19) -> 141880 | K35: =SUM('RallyGully I Sector 10 Dwarka'!K19+'RallyGully I Sector 83 Gurgaon'!K19+'RallyGully I East of Kailash'!K19+'RallyGully I Sector 19 Dwarka'!K19+'RallyGully | LCR Pune'!K19+'RallyGully | DPSG'!K19+'RallyGully | Gandipath'!K19+'RallyGully | Panchsheel'!K19+'Powerplay Park, Pune'!K19+'Commons, Noida'!K19) -> 109180
A36: 5 | B36: Coaching | C36: =SUM('RallyGully I Sector 10 Dwarka'!C20+'RallyGully I Sector 83 Gurgaon'!C20+'RallyGully I East of Kailash'!C20+'RallyGully I Sector 19 Dwarka'!C20+'RallyGully | LCR Pune'!C20+'RallyGully | DPSG'!C20+'RallyGully | Gandipath'!C20+'RallyGully | Panchsheel'!C20) -> 0 | D36: =SUM('RallyGully I Sector 10 Dwarka'!D20+'RallyGully I Sector 83 Gurgaon'!D20+'RallyGully I East of Kailash'!D20+'RallyGully I Sector 19 Dwarka'!D20+'RallyGully | LCR Pune'!D20+'RallyGully | DPSG'!D20+'RallyGully | Gandipath'!D20+'RallyGully | Panchsheel'!D20) -> 0 | E36: =SUM('RallyGully I Sector 10 Dwarka'!E20+'RallyGully I Sector 83 Gurgaon'!E20+'RallyGully I East of Kailash'!E20+'RallyGully I Sector 19 Dwarka'!E20+'RallyGully | LCR Pune'!E20+'RallyGully | DPSG'!E20+'RallyGully | Gandipath'!E20+'RallyGully | Panchsheel'!E20) -> 0 | F36: =SUM('RallyGully I Sector 10 Dwarka'!F20+'RallyGully I Sector 83 Gurgaon'!F20+'RallyGully I East of Kailash'!F20+'RallyGully I Sector 19 Dwarka'!F20+'RallyGully | LCR Pune'!F20+'RallyGully | DPSG'!F20+'RallyGully | Gandipath'!F20+'RallyGully | Panchsheel'!F20) -> 0 | G36: =SUM('RallyGully I Sector 10 Dwarka'!G20+'RallyGully I Sector 83 Gurgaon'!G20+'RallyGully I East of Kailash'!G20+'RallyGully I Sector 19 Dwarka'!G20+'RallyGully | LCR Pune'!G20+'RallyGully | DPSG'!G20+'RallyGully | Gandipath'!G20+'RallyGully | Panchsheel'!G20) -> 0 | H36: =SUM('RallyGully I Sector 10 Dwarka'!H20+'RallyGully I Sector 83 Gurgaon'!H20+'RallyGully I East of Kailash'!H20+'RallyGully I Sector 19 Dwarka'!H20+'RallyGully | LCR Pune'!H20+'RallyGully | DPSG'!H20+'RallyGully | Gandipath'!H20+'RallyGully | Panchsheel'!H20) -> 0 | I36: =SUM('RallyGully I Sector 10 Dwarka'!I20+'RallyGully I Sector 83 Gurgaon'!I20+'RallyGully I East of Kailash'!I20+'RallyGully I Sector 19 Dwarka'!I20+'RallyGully | LCR Pune'!I20+'RallyGully | DPSG'!I20+'RallyGully | Gandipath'!I20+'RallyGully | Panchsheel'!I20) -> 98000 | J36: =SUM('RallyGully I Sector 10 Dwarka'!J20+'RallyGully I Sector 83 Gurgaon'!J20+'RallyGully I East of Kailash'!J20+'RallyGully I Sector 19 Dwarka'!J20+'RallyGully | LCR Pune'!J20+'RallyGully | DPSG'!J20+'RallyGully | Gandipath'!J20+'RallyGully | Panchsheel'!J20+'Powerplay Park, Pune'!J20+'Commons, Noida'!J20) -> 37500 | K36: =SUM('RallyGully I Sector 10 Dwarka'!K20+'RallyGully I Sector 83 Gurgaon'!K20+'RallyGully I East of Kailash'!K20+'RallyGully I Sector 19 Dwarka'!K20+'RallyGully | LCR Pune'!K20+'RallyGully | DPSG'!K20+'RallyGully | Gandipath'!K20+'RallyGully | Panchsheel'!K20+'Powerplay Park, Pune'!K20+'Commons, Noida'!K20) -> 11500
A37: 6 | B37: Corporate Events | C37: =SUM('RallyGully I Sector 10 Dwarka'!C21+'RallyGully I Sector 83 Gurgaon'!C21+'RallyGully I East of Kailash'!C21+'RallyGully I Sector 19 Dwarka'!C21+'RallyGully | LCR Pune'!C21+'RallyGully | DPSG'!C21+'RallyGully | Gandipath'!C21+'RallyGully | Panchsheel'!C21) -> 0 | D37: =SUM('RallyGully I Sector 10 Dwarka'!D21+'RallyGully I Sector 83 Gurgaon'!D21+'RallyGully I East of Kailash'!D21+'RallyGully I Sector 19 Dwarka'!D21+'RallyGully | LCR Pune'!D21+'RallyGully | DPSG'!D21+'RallyGully | Gandipath'!D21+'RallyGully | Panchsheel'!D21) -> 0 | E37: =SUM('RallyGully I Sector 10 Dwarka'!E21+'RallyGully I Sector 83 Gurgaon'!E21+'RallyGully I East of Kailash'!E21+'RallyGully I Sector 19 Dwarka'!E21+'RallyGully | LCR Pune'!E21+'RallyGully | DPSG'!E21+'RallyGully | Gandipath'!E21+'RallyGully | Panchsheel'!E21) -> 0 | F37: =SUM('RallyGully I Sector 10 Dwarka'!F21+'RallyGully I Sector 83 Gurgaon'!F21+'RallyGully I East of Kailash'!F21+'RallyGully I Sector 19 Dwarka'!F21+'RallyGully | LCR Pune'!F21+'RallyGully | DPSG'!F21+'RallyGully | Gandipath'!F21+'RallyGully | Panchsheel'!F21) -> 5400 | G37: =SUM('RallyGully I Sector 10 Dwarka'!G21+'RallyGully I Sector 83 Gurgaon'!G21+'RallyGully I East of Kailash'!G21+'RallyGully I Sector 19 Dwarka'!G21+'RallyGully | LCR Pune'!G21+'RallyGully | DPSG'!G21+'RallyGully | Gandipath'!G21+'RallyGully | Panchsheel'!G21) -> 0 | H37: =SUM('RallyGully I Sector 10 Dwarka'!H21+'RallyGully I Sector 83 Gurgaon'!H21+'RallyGully I East of Kailash'!H21+'RallyGully I Sector 19 Dwarka'!H21+'RallyGully | LCR Pune'!H21+'RallyGully | DPSG'!H21+'RallyGully | Gandipath'!H21+'RallyGully | Panchsheel'!H21) -> 20680 | I37: =SUM('RallyGully I Sector 10 Dwarka'!I21+'RallyGully I Sector 83 Gurgaon'!I21+'RallyGully I East of Kailash'!I21+'RallyGully I Sector 19 Dwarka'!I21+'RallyGully | LCR Pune'!I21+'RallyGully | DPSG'!I21+'RallyGully | Gandipath'!I21+'RallyGully | Panchsheel'!I21) -> 28730 | J37: =SUM('RallyGully I Sector 10 Dwarka'!J21+'RallyGully I Sector 83 Gurgaon'!J21+'RallyGully I East of Kailash'!J21+'RallyGully I Sector 19 Dwarka'!J21+'RallyGully | LCR Pune'!J21+'RallyGully | DPSG'!J21+'RallyGully | Gandipath'!J21+'RallyGully | Panchsheel'!J21+'Powerplay Park, Pune'!J21+'Commons, Noida'!J21) -> 11880 | K37: =SUM('RallyGully I Sector 10 Dwarka'!K21+'RallyGully I Sector 83 Gurgaon'!K21+'RallyGully I East of Kailash'!K21+'RallyGully I Sector 19 Dwarka'!K21+'RallyGully | LCR Pune'!K21+'RallyGully | DPSG'!K21+'RallyGully | Gandipath'!K21+'RallyGully | Panchsheel'!K21+'Powerplay Park, Pune'!K21+'Commons, Noida'!K21) -> 10520
A38: 7 | B38: Brand Activation | C38: =SUM('RallyGully I Sector 10 Dwarka'!C22+'RallyGully I Sector 83 Gurgaon'!C22+'RallyGully I East of Kailash'!C22+'RallyGully I Sector 19 Dwarka'!C22+'RallyGully | LCR Pune'!C22+'RallyGully | DPSG'!C22+'RallyGully | Gandipath'!C22+'RallyGully | Panchsheel'!C22) -> 0 | D38: =SUM('RallyGully I Sector 10 Dwarka'!D22+'RallyGully I Sector 83 Gurgaon'!D22+'RallyGully I East of Kailash'!D22+'RallyGully I Sector 19 Dwarka'!D22+'RallyGully | LCR Pune'!D22+'RallyGully | DPSG'!D22+'RallyGully | Gandipath'!D22+'RallyGully | Panchsheel'!D22) -> 0 | E38: =SUM('RallyGully I Sector 10 Dwarka'!E22+'RallyGully I Sector 83 Gurgaon'!E22+'RallyGully I East of Kailash'!E22+'RallyGully I Sector 19 Dwarka'!E22+'RallyGully | LCR Pune'!E22+'RallyGully | DPSG'!E22+'RallyGully | Gandipath'!E22+'RallyGully | Panchsheel'!E22) -> 0 | F38: =SUM('RallyGully I Sector 10 Dwarka'!F22+'RallyGully I Sector 83 Gurgaon'!F22+'RallyGully I East of Kailash'!F22+'RallyGully I Sector 19 Dwarka'!F22+'RallyGully | LCR Pune'!F22+'RallyGully | DPSG'!F22+'RallyGully | Gandipath'!F22+'RallyGully | Panchsheel'!F22) -> 15000 | G38: =SUM('RallyGully I Sector 10 Dwarka'!G22+'RallyGully I Sector 83 Gurgaon'!G22+'RallyGully I East of Kailash'!G22+'RallyGully I Sector 19 Dwarka'!G22+'RallyGully | LCR Pune'!G22+'RallyGully | DPSG'!G22+'RallyGully | Gandipath'!G22+'RallyGully | Panchsheel'!G22) -> 4480 | H38: =SUM('RallyGully I Sector 10 Dwarka'!H22+'RallyGully I Sector 83 Gurgaon'!H22+'RallyGully I East of Kailash'!H22+'RallyGully I Sector 19 Dwarka'!H22+'RallyGully | LCR Pune'!H22+'RallyGully | DPSG'!H22+'RallyGully | Gandipath'!H22+'RallyGully | Panchsheel'!H22) -> 23313 | I38: =SUM('RallyGully I Sector 10 Dwarka'!I22+'RallyGully I Sector 83 Gurgaon'!I22+'RallyGully I East of Kailash'!I22+'RallyGully I Sector 19 Dwarka'!I22+'RallyGully | LCR Pune'!I22+'RallyGully | DPSG'!I22+'RallyGully | Gandipath'!I22+'RallyGully | Panchsheel'!I22) -> 24100 | J38: =SUM('RallyGully I Sector 10 Dwarka'!J22+'RallyGully I Sector 83 Gurgaon'!J22+'RallyGully I East of Kailash'!J22+'RallyGully I Sector 19 Dwarka'!J22+'RallyGully | LCR Pune'!J22+'RallyGully | DPSG'!J22+'RallyGully | Gandipath'!J22+'RallyGully | Panchsheel'!J22+'Powerplay Park, Pune'!J22+'Commons, Noida'!J22) -> 30000 | K38: =SUM('RallyGully I Sector 10 Dwarka'!K22+'RallyGully I Sector 83 Gurgaon'!K22+'RallyGully I East of Kailash'!K22+'RallyGully I Sector 19 Dwarka'!K22+'RallyGully | LCR Pune'!K22+'RallyGully | DPSG'!K22+'RallyGully | Gandipath'!K22+'RallyGully | Panchsheel'!K22+'Powerplay Park, Pune'!K22+'Commons, Noida'!K22) -> 28000
A39: 8 | B39: Other Income | C39: =SUM('RallyGully I Sector 10 Dwarka'!C23+'RallyGully I Sector 83 Gurgaon'!C23+'RallyGully I East of Kailash'!C23+'RallyGully I Sector 19 Dwarka'!C23+'RallyGully | LCR Pune'!C23+'RallyGully | DPSG'!C23+'RallyGully | Gandipath'!C23+'RallyGully | Panchsheel'!C23) -> 0 | D39: =SUM('RallyGully I Sector 10 Dwarka'!D23+'RallyGully I Sector 83 Gurgaon'!D23+'RallyGully I East of Kailash'!D23+'RallyGully I Sector 19 Dwarka'!D23+'RallyGully | LCR Pune'!D23+'RallyGully | DPSG'!D23+'RallyGully | Gandipath'!D23+'RallyGully | Panchsheel'!D23) -> 0 | E39: =SUM('RallyGully I Sector 10 Dwarka'!E23+'RallyGully I Sector 83 Gurgaon'!E23+'RallyGully I East of Kailash'!E23+'RallyGully I Sector 19 Dwarka'!E23+'RallyGully | LCR Pune'!E23+'RallyGully | DPSG'!E23+'RallyGully | Gandipath'!E23+'RallyGully | Panchsheel'!E23) -> 0 | F39: =SUM('RallyGully I Sector 10 Dwarka'!F23+'RallyGully I Sector 83 Gurgaon'!F23+'RallyGully I East of Kailash'!F23+'RallyGully I Sector 19 Dwarka'!F23+'RallyGully | LCR Pune'!F23+'RallyGully | DPSG'!F23+'RallyGully | Gandipath'!F23+'RallyGully | Panchsheel'!F23) -> 18000 | G39: =SUM('RallyGully I Sector 10 Dwarka'!G23+'RallyGully I Sector 83 Gurgaon'!G23+'RallyGully I East of Kailash'!G23+'RallyGully I Sector 19 Dwarka'!G23+'RallyGully | LCR Pune'!G23+'RallyGully | DPSG'!G23+'RallyGully | Gandipath'!G23+'RallyGully | Panchsheel'!G23) -> 25000 | H39: =SUM('RallyGully I Sector 10 Dwarka'!H23+'RallyGully I Sector 83 Gurgaon'!H23+'RallyGully I East of Kailash'!H23+'RallyGully I Sector 19 Dwarka'!H23+'RallyGully | LCR Pune'!H23+'RallyGully | DPSG'!H23+'RallyGully | Gandipath'!H23+'RallyGully | Panchsheel'!H23) -> 29300 | I39: =SUM('RallyGully I Sector 10 Dwarka'!I23+'RallyGully I Sector 83 Gurgaon'!I23+'RallyGully I East of Kailash'!I23+'RallyGully I Sector 19 Dwarka'!I23+'RallyGully | LCR Pune'!I23+'RallyGully | DPSG'!I23+'RallyGully | Gandipath'!I23+'RallyGully | Panchsheel'!I23) -> 138000 | J39: =SUM('RallyGully I Sector 10 Dwarka'!J23+'RallyGully I Sector 83 Gurgaon'!J23+'RallyGully I East of Kailash'!J23+'RallyGully I Sector 19 Dwarka'!J23+'RallyGully | LCR Pune'!J23+'RallyGully | DPSG'!J23+'RallyGully | Gandipath'!J23+'RallyGully | Panchsheel'!J23+'Powerplay Park, Pune'!J23+'Commons, Noida'!J23) -> 197000 | K39: =SUM('RallyGully I Sector 10 Dwarka'!K23+'RallyGully I Sector 83 Gurgaon'!K23+'RallyGully I East of Kailash'!K23+'RallyGully I Sector 19 Dwarka'!K23+'RallyGully | LCR Pune'!K23+'RallyGully | DPSG'!K23+'RallyGully | Gandipath'!K23+'RallyGully | Panchsheel'!K23+'Powerplay Park, Pune'!K23+'Commons, Noida'!K23) -> 256000
B40: Total Gross Revenue | C40: =sum(C19+C24+C30+C35+C36+C37+C38+C39) -> 103615 | D40: =sum(D19+D24+D30+D35+D36+D37+D38+D39) -> 336259 | E40: =sum(E19+E24+E30+E35+E36+E37+E38+E39) -> 478873.8 | F40: =sum(F19+F24+F30+F35+F36+F37+F38+F39) -> 542592.6 | G40: =sum(G19+G24+G30+G35+G36+G37+G38+G39) -> 581843 | H40: =sum(H19+H24+H30+H35+H36+H37+H38+H39) -> 754429 | I40: =sum(I19+I24+I30+I35+I36+I37+I38+I39) -> 1501552 | J40: =sum(J19+J24+J30+J35+J36+J37+J38+J39) -> 1713558 | K40: =sum(K19+K24+K30+K35+K36+K37+K38+K39) -> 2062032
B42: Verticle Vise | C42: July | D42: August | E42: September | F42: October | G42: November | H42: December | I42: January | J42: February | K42: March
A43: 1 | B43: Offline | C43: =C19/C40 -> 0.046663128 | D43: =D19/D40 -> 0.15178776 | E43: =E19/E40 -> 0.29135025 | F43: =F19/F40 -> 0.13498157 | G43: =G19/G40 -> 0.30161745 | H43: =H19/H40 -> 0.35723971 | I43: =I19/I40 -> 0.32058097 | J43: =J19/J40 -> 0.30093816 | K43: =K19/K40 -> 0.25645334
A44: 1.1 | B44: Rentals | C44: =C20/C40 -> 0.043188728 | D44: =D20/D40 -> 0.046333332 | E44: =E20/E40 -> 0.046525828 | F44: =F20/F40 -> 0.045780204 | G44: =G20/G40 -> 0.047813585 | H44: =H20/H40 -> 0.080557614 | I44: =I20/I40 -> 0.060829728 | J44: =J20/J40 -> 0.055046284 | K44: =K20/K40 -> 0.040169115
A45: 1.2 | B45: F&B | C45: =C21/C40 -> 0.0034744004 | D45: =D21/D40 -> 0.0057098843 | E45: =E21/E40 -> 0.0091882245 | F45: =F21/F40 -> 0.0045890784 | G45: =G21/G40 -> 0.0032482989 | H45: =H21/H40 -> 0.0069721604 | I45: =I21/I40 -> 0.0027005392 | J45: =J21/J40 -> 0.0031775989 | K45: =K21/K40 -> 0.0018549664
A46: 1.3 | B46: Product Sales | C46: =C22/C40 -> 0 | D46: =D22/D40 -> 0 | E46: =E22/E40 -> 0.025163206 | F46: =F22/F40 -> 0 | G46: =G22/G40 -> 0 | H46: =H22/H40 -> 0 | I46: =I22/I40 -> 0.011987597 | J46: =J22/J40 -> 0 | K46: =K22/K40 -> 0
A47: 1.4 | B47: Bookings | C47: =C23/C40 -> 0 | D47: =D23/D40 -> 0.099744542 | E47: =E23/E40 -> 0.21047299 | F47: =F23/F40 -> 0.075028668 | G47: =G23/G40 -> 0.25055556 | H47: =H23/H40 -> 0.26970994 | I47: =I23/I40 -> 0.24506311 | J47: =J23/J40 -> 0.24271428 | K47: =K23/$K$40 -> 0.21442926
A48: 2 | B48: Online: Third Party Platform | C48: =C24/$C$40 -> 0.85200019 | D48: =D24/$D$40 -> 0.65465014 | E48: =E24/$E$40 -> 0.59068548 | F48: =F24/$F$40 -> 0.55163414 | G48: =G24/$G$40 -> 0.45068687 | H48: =H24/$H$40 -> 0.37264607 | I48: =I24/$I$40 -> 0.34659739 | J48: =J24/$J$40 -> 0.35196299 | K48: =K24/$K$40 -> 0.41789507
A49: 2.1 | B49: Hudle | C49: =C25/$C$40 -> 0.70877769 | D49: =D25/$D$40 -> 0.48373426 | E49: =E25/$E$40 -> 0.50963532 | F49: =F25/$F$40 -> 0.47465631 | G49: =G25/$G$40 -> 0.34628757 | H49: =H25/$H$40 -> 0.23015155 | I49: =I25/$I$40 -> 0.1754851 | J49: =J25/$J$40 -> 0.15394985 | K49: =K25/$K$40 -> 0.18328668
A50: 2.2 | B50: Playo | C50: =C26/$C$40 -> 0.14322251 | D50: =D26/$D$40 -> 0.13914869 | E50: =E26/$E$40 -> 0.068199179 | F50: =F26/$F$40 -> 0.055414689 | G50: =G26/$G$40 -> 0.046928467 | H50: =H26/$H$40 -> 0.060412577 | I50: =I26/$I$40 -> 0.061947239 | J50: =J26/$J$40 -> 0.051065094 | K50: =K26/$K$40 -> 0.059822059
A51: 2.3 | B51: District | C51: =C27/$C$40 -> 0 | D51: =D27/$D$40 -> 0 | E51: =E27/$E$40 -> 0 | F51: =F27/$F$40 -> 0.0022116041 | G51: =G27/$G$40 -> 0.0053382098 | H51: =H27/$H$40 -> 0.02405793 | I51: =I27/$I$40 -> 0.067363634 | J51: =J27/$J$40 -> 0.095473862 | K51: =K27/$K$40 -> 0.10164731
A52: 2.4 | B52: Khelomore | C52: =C28/$C$40 -> 0 | D52: =D28/$D$40 -> 0.031767179 | E52: =E28/$E$40 -> 0.012850985 | F52: =F28/$F$40 -> 0.019351536 | G52: =G28/$G$40 -> 0.05213262 | H52: =H28/$H$40 -> 0.056367133 | I52: =I28/$I$40 -> 0.024903566 | J52: =J28/$J$40 -> 0.027746945 | K52: =K28/$K$40 -> 0.02700734
A53: 2.5 | B53: Zplys | C53: =C29/$C$40 -> 0 | D53: =D29/$D$40 -> 0 | E53: =E29/$E$40 -> 0 | F53: =F29/$F$40 -> 0 | G53: =G29/$G$40 -> 0 | H53: =H29/$H$40 -> 0.0016568822 | I53: =I29/$I$40 -> 0.01689785 | J53: =J29/$J$40 -> 0.023727239 | K53: =K29/$K$40 -> 0.04613168
A54: 3 | B54: Community | C54: =C30/$C$40 -> 0.10133668 | D54: =D30/$D$40 -> 0.044867201 | E54: =E30/$E$40 -> 0.061581987 | F54: =F30/$F$40 -> 0.074346757 | G54: =G30/$G$40 -> 0.069193923 | H54: =H30/$H$40 -> 0.041235159 | I54: =I30/$I$40 -> 0.08753543 | J54: =J30/$J$40 -> 0.10301023 | K54: =K30/$K$40 -> 0.12429681
A55: 3.1 | B55: Courtly (Organized by RallyGully) | C55: =C31/$C$40 -> 0 | D55: =D31/$D$40 -> 0 | E55: =E31/$E$40 -> 0 | F55: =F31/$F$40 -> 0 | G55: =G31/$G$40 -> 0.014608752 | H55: =H31/$H$40 -> 0 | I55: =I31/$I$40 -> 0.025506942 | J55: =J31/$J$40 -> 0.032213675 | K55: =K31/$K$40 -> 0.045246631
A56: 3.2 | B56: Sportomic (Organized by RallyGully) | C56: =C32/$C$40 -> 0 | D56: =D32/$D$40 -> 0 | E56: =E32/$E$40 -> 0 | F56: =F32/$F$40 -> 0 | G56: =G32/$G$40 -> 0 | H56: =H32/$H$40 -> 0.03087103 | I56: =I32/$I$40 -> 0.0090905943 | J56: =J32/$J$40 -> 0.024720494 | K56: =K32/$K$40 -> 0.014252931
A57: 3.3 | B57: Rallygully Community games | C57: =C33/$C$40 -> 0.10133668 | D57: =D33/$D$40 -> 0.044867201 | E57: =E33/$E$40 -> 0.041555834 | F57: =F33/$F$40 -> 0.052249146 | G57: =G33/$G$40 -> 0.035714102 | H57: =H33/$H$40 -> 0.0033270195 | I57: =I33/$I$40 -> 0.052937894 | J57: =J33/$J$40 -> 0.036926092 | K57: =K33/$K$40 -> 0.060944738
A58: 3.4 | B58: Misfits Community | C58: =C34/$C$40 -> 0 | D58: =D34/$D$40 -> 0 | E58: =E34/$E$40 -> 0.020026153 | F58: =F34/$F$40 -> 0.022097611 | G58: =G34/$G$40 -> 0.01887107 | H58: =H34/$H$40 -> 0.0070371102 | I58: =I34/$I$40 -> 0 | J58: =J34/$J$40 -> 0.0091499675 | K58: =K34/$K$40 -> 0.0038525105
A59: 4 | B59: Memberships | C59: =C35/$C$40 -> 0 | D59: =D35/$D$40 -> 0.1486949 | E59: =E35/$E$40 -> 0.056382287 | F59: =F35/$F$40 -> 0.16826621 | G59: =G35/$G$40 -> 0.12783517 | H59: =H35/$H$40 -> 0.13172876 | I59: =I35/$I$40 -> 0.0529319 | J59: =J35/$J$40 -> 0.082798481 | K59: =K35/$K$40 -> 0.052947772
... A63: 8 | B63: Other Income | C63: =C39/$C$40 -> 0 | D63: =D39/$D$40 -> 0 | E63: =E39/$E$40 -> 0 | F63: =F39/$F$40 -> 0.033174061 | G63: =G39/$G$40 -> 0.042966917 | H63: =H39/$H$40 -> 0.038837319 | I63: =I39/$I$40 -> 0.091904909 | J63: =J39/$J$40 -> 0.11496547 | K63: =K39/$K$40 -> 0.12414938
B64: Total Gross Revenue | C64: =C43+C48+C54+C59+C60+C61+C62+C63 -> 1 | D64: =D43+D48+D54+D59+D60+D61+D62+D63 -> 1 | E64: =E43+E48+E54+E59+E60+E61+E62+E63 -> 1 | F64: =F43+F48+F54+F59+F60+F61+F62+F63 -> 1 | G64: =G43+G48+G54+G59+G60+G61+G62+G63 -> 1 | H64: =H43+H48+H54+H59+H60+H61+H62+H63 -> 1 | I64: =I43+I48+I54+I59+I60+I61+I62+I63 -> 1 | J64: =J43+J48+J54+J59+J60+J61+J62+J63 -> 1 | K64: =K43+K48+K54+K59+K60+K61+K62+K63 -> 1

Sheet RallyGully I Sector 10 Dwarka
B1: Venue Sheet | F1: Link | G1: Link | H1: Link | I1: Link | J1: Link | K1: Link
B2: Metrics | C2: July | D2: August | E2: September | F2: October | G2: November | H2: December | I2: January | J2: February | K2: March | L2: TOTAL
B3: Offline | C3: =SUM(C4,C5,C6, C7) -> 4835 | D3: =SUM(D4,D5,D6, D7) -> 20820 | E3: =SUM(E4,E5,E6, E7) -> 28070 | F3: =SUM(F4,F5,F6, F7) -> 13235 | G3: =SUM(G4,G5,G6, G7) -> 21000 | H3: =SUM(H4,H5,H6,, H7) -> 47970 | I3: =SUM(I4,I5,I6,, I7) -> 59637 | J3: =SUM(J4,J5,J6,, J7) -> 36605 | K3: =SUM(K4,K5,K6,, K7) -> 37660 | L3: =SUM(C3:K3) -> 269832 | M3: =L3/1.18 -> 228671.19
B4: Rentals | C4: 4475 | D4: 13380 | E4: 10110 | F4: 6425 | G4: 4790 | H4: 15775 | I4: 15709 | J4: 12630 | K4: 11075 | L4: =SUM(C4:K4) -> 94369 | M4: =L4/1.18 -> 79973.729
B5: F&B | C5: 360 | D5: 1920 | E5: 4400 | F5: 2490 | G5: 1890 | H5: 4800 | I5: 3710 | J5: 3615 | K5: 2625 | L5: =SUM(C5:K5) -> 25810 | M5: =L5/1.18 -> 21872.881
B6: Product Sales | C6: 0 | D6: 0 | E6: 7550 | F6: 0 | G6: 0 | H6: 0 | I6: 0 | J6: 0 | K6: 0 | L6: =SUM(C6:K6) -> 7550 | M6: =L6/1.18 -> 6398.3051
B7: Bookings | C7: 0 | D7: 5520 | E7: 6010 | F7: 4320 | G7: 14320 | H7: 27395 | I7: 40218 | J7: 20360 | K7: 23960 | L7: =SUM(C7:K7) -> 142103 | M7: =L7/1.18 -> 120426.27
B8: Online: Third Party Platform | C8: =sum(C9:C13) -> 88280 | D8: =sum(D9:D13) -> 212932 | E8: =sum(E9:E13) -> 188454 | F8: =sum(F9:F13) -> 118535 | G8: =sum(G9:G13) -> 96029 | H8: =sum(H9:H13) -> 97326 | I8: =sum(I9:I13) -> 130380 | J8: =sum(J9:J13) -> 106075 | K8: =sum(K9:K13) -> 167600 | L8: =SUM(C8:K8) -> 1205611 | M8: =L8/1.18 -> 1021704.2
B9: Hudle | C9: 73440 | D9: 160060 | E9: 160060 | F9: 96165 | G9: 65915 | H9: 66215 | I9: 76022 | J9: 53245 | K9: 100520 | L9: =SUM(C9:K9) -> 851642
B10: Playo | C10: 14840 | D10: 44490 | E10: 24400 | F10: 17870 | G10: 11080 | H10: 5361 | I10: 20344 | J10: 14830 | K10: 24855 | L10: =SUM(C10:K10) -> 178070
B11: District | C11: 0 | D11: 0 | E11: 0 | F11: 0 | G11: 0 | H11: 8950 | I11: 24400 | J11: 35200 | K11: 41425 | L11: =SUM(C11:K11) -> 109975
B12: Khelomore | C12: 0 | D12: 8382 | E12: 3994 | F12: 4500 | G12: 19034 | H12: 16800 | I12: 9614 | J12: 2800 | K12: 800 | L12: =SUM(C12:K12) -> 65924
B13: Zplys | C13: 0 | D13: 0 | E13: 0 | F13: 0 | G13: 0 | H13: 0 | I13: 0 | J13: 0 | K13: 0 | L13: =SUM(C13:K13) -> 0
B14: Community | C14: =sum(C17:C18) -> 10500 | D14: =sum(D17:D18) -> 15087 | E14: =sum(E17:E18) -> 28530 | F14: =sum(F17:F18) -> 13550 | G14: =sum(G17:G18) -> 1100 | H14: =SUM(H16:H18) -> 6030 | I14: =SUM(I15:I18) -> 67200 | J14: =SUM(J15:J18) -> 54550 | K14: =SUM(K15:K18) -> 34360 | L14: =SUM(C14:K14) -> 230907 | M14: =L14/1.18 -> 195683.9
B15: Courtly (Organized by RallyGully) | C15: 0 | D15: 0 | E15: 0 | F15: 0 | G15: 0 | H15: 0 | I15: 38300 | J15: 0 | K15: 0 | L15: =SUM(C15:K15) -> 38300
B16: Sportomic (Organized by RallyGully) | C16: 0 | D16: 0 | E16: 0 | F16: 0 | G16: 0 | H16: 6030 | I16: 13650 | J16: 34100 | K16: 11800 | L16: =SUM(C16:K16) -> 65580
B17: Rallygully Community games | C17: 10500 | D17: 15087 | E17: 19900 | F17: 11830 | G17: 1100 | H17: 0 | I17: 15250 | J17: 20450 | K17: 22560 | L17: =SUM(C17:K17) -> 116677
B18: Misfits Community | C18: 0 | D18: 0 | E18: 8630 | F18: 1720 | G18: 0 | H18: 0 | I18: 0 | J18: 0 | K18: 0 | L18: =SUM(C18:K18) -> 10350
B19: Memberships | C19: 0 | D19: 50000 | E19: 0 | F19: 50000 | G19: 50000 | H19: 55000 | I19: 0 | J19: 50000 | K19: 0 | L19: =SUM(C19:K19) -> 255000 | M19: =L19/1.18 -> 216101.69
B20: Coaching | C20: 0 | D20: 0 | E20: 0 | F20: 0 | G20: 0 | H20: 0 | I20: 44000 | J20: =16500 -> 16500 | K20: =6500+5000 -> 11500 | L20: =SUM(C20:K20) -> 72000 | M20: =L20/1.18 -> 61016.949
B21: Corporate Events | C21: 0 | D21: 0 | E21: 0 | F21: 5400 | G21: 0 | H21: 0 | I21: 0 | J21: 0 | K21: 0 | L21: =SUM(C21:K21) -> 5400 | M21: =L21/1.18 -> 4576.2712
B22: Brand Activation | C22: 0 | D22: 0 | E22: 0 | F22: 0 | G22: 0 | H22: 0 | I22: 0 | J22: 0 | K22: 0 | L22: =SUM(C22:K22) -> 0 | M22: =L22/1.18 -> 0
B23: Other Income | C23: 0 | D23: 0 | E23: 0 | F23: 0 | G23: 0 | H23: 0 | I23: 0 | J23: 0 | K23: 0 | L23: =SUM(C23:K23) -> 0 | M23: =L23/1.18 -> 0
B24: Total Gross Revenue | C24: =SUM(C3,C8,C14,C19,C20,C21,C22,C23) -> 103615 | D24: =SUM(D3,D8,D14,D19,D20,D21,D22,D23) -> 298839 | E24: =SUM(E3,E8,E14,E19,E20,E21,E22,E23) -> 245054 | F24: =SUM(F3,F8,F14,F19,F20,F21,F22,F23) -> 200720 | G24: =SUM(G3,G8,G14,G19,G20,G21,G22,G23) -> 168129 | H24: =SUM(H3,H8,H14,H19,H20,H21,H22,H23) -> 206326 | I24: =SUM(I3,I8,I14,I19,I20,I21,I22,I23) -> 301217 | J24: =SUM(J3,J8,J14,J19,J20,J21,J22,J23) -> 263730 | K24: =SUM(K3,K8,K14,K19,K20,K21,K22,K23) -> 251120 | L24: =sum(L3,L8,L14,L19,L20,L21,L22,L23) -> 2038750 | M24: =L24/1.18 -> 1727754.2
B25: Total Net Revenue (Post Commissions) | C25: 87758.59 | D25: 275765 | E25: 171043 | F25: 160536 | G25: 153608.68 | H25: 195900.27 | I25: 286550 | J25: 237720.94 | K25: 226823.45
B26: Total Revenue post GST | C26: =C25/1.18 -> 74371.686 | D26: =D25/1.18 -> 233699.15 | E26: =E25/1.18 -> 144951.69 | F26: =F25/1.18 -> 136047.46 | G26: =G25/1.18 -> 130176.85 | H26: =H25/1.18 -> 166017.18 | I26: =I25/1.18 -> 242838.98 | J26: =J25/1.18 -> 201458.42 | K26: =K25/1.18 -> 192223.26
B27: Note
B28: Venue Operational from 13th July

Sheet RallyGully I Sector 83 Gurgaon
B1: Venue Sheet | F1: Link | G1: Link | H1: Link | I1: Link | J1: Link | K1: Link
B2: Metrics | C2: July | D2: August | E2: September | F2: October | G2: November | H2: December | I2: January | J2: February | K2: March | L2: TOTAL
B3: Offline | C3: =SUM(C4,C5,C6, C7) -> 0 | D3: =SUM(D4,D5,D6, D7) -> 30220 | E3: =SUM(E4,E5,E6, E7) -> 105260 | F3: =SUM(F4,F5,F6, F7) -> 36030 | G3: =SUM(G4,G5,G6, G7) -> 92435 | H3: =SUM(H4,H5,H6,H7) -> 79990 | I3: =SUM(I4,I5,I6,I7) -> 97445 | J3: =SUM(J4,J5,J6,J7) -> 120420 | K3: =SUM(K4,K5,K6,K7) -> 110460 | L3: =SUM(C3:K3) -> 672260
B4: Rentals | C4: 0 | D4: 2200 | E4: 7820 | F4: 6330 | G4: 6595 | H4: 7725 | I4: 8155 | J4: 10250 | K4: 12700 | L4: =SUM(C4:K4) -> 61775
B5: F&B | C5: 0 | D5: 0 | E5: 0 | F5: 0 | G5: 0 | H5: 0 | I5: 0 | J5: 0 | K5: 0 | L5: =SUM(C5:K5) -> 0
B6: Product Sales | C6: 0 | D6: 0 | E6: 4500 | F6: 0 | G6: 0 | H6: 0 | I6: 0 | J6: 0 | K6: 0 | L6: =SUM(C6:K6) -> 4500
B7: Bookings | C7: 0 | D7: 28020 | E7: 92940 | F7: 29700 | G7: 85840 | H7: 72265 | I7: 89290 | J7: 110170 | K7: 97760 | L7: =SUM(C7:K7) -> 605985
B8: Online: Third Party Platform | C8: =SUM(C9:C13) -> 0 | D8: =SUM(D9:D13) -> 7200 | E8: =SUM(E9:E13) -> 21741 | F8: =SUM(F9:F13) -> 19085 | G8: =SUM(G9:G13) -> 20021 | H8: =SUM(H9:H13) -> 39150 | I8: =SUM(I9:I13) -> 47466 | J8: =SUM(J9:J13) -> 41060 | K8: =SUM(K9:K13) -> 45510 | L8: =SUM(C8:K8) -> 241233
B9: Hudle | C9: 0 | D9: 2600 | E9: 16121 | F9: 13485 | G9: 18445 | H9: 34800 | I9: 25407 | J9: 21460 | K9: 28110 | L9: =SUM(C9:K9) -> 160428
B10: Playo | C10: 0 | D10: 2300 | E10: 5620 | F10: 5000 | G10: 800 | H10: 2050 | I10: 4460 | J10: 3200 | K10: 5000 | L10: =SUM(C10:K10) -> 28430
B11: District | C11: 0 | D11: 0 | E11: 0 | F11: 0 | G11: 776 | H11: 2300 | I11: 17200 | J11: 16400 | K11: 12400 | L11: =SUM(C11:K11) -> 49076
B12: Khelomore | C12: 0 | D12: 2300 | E12: 0 | F12: 600 | G12: 0 | H12: 0 | I12: 399 | J12: 0 | K12: 0 | L12: =SUM(C12:K12) -> 3299
B13: Zplys | C13: 0 | D13: 0 | E13: 0 | F13: 0 | G13: 0 | H13: 0 | I13: 0 | J13: 0 | K13: 0 | L13: =SUM(C13:K13) -> 0
B14: Community | C14: =sum(C17:C18) -> 0 | D14: =sum(D17:D18) -> 0 | E14: =sum(E17:E18) -> 960 | F14: =sum(F17:F18) -> 6080 | G14: =sum(G15:G18) -> 9960 | H14: =sum(H16:H18) -> 1500 | I14: =sum(I16:I18) -> 3000 | J14: =sum(J16:J18) -> 0 | K14: =sum(K16:K18) -> 2400 | L14: =SUM(C14:K14) -> 23900
B15: Courtly (Organized by RallyGully) | C15: 0 | D15: 0 | E15: 0 | F15: 0 | G15: 2000 | H15: 0 | I15: 0 | J15: 0 | K15: 0 | L15: =SUM(C15:K15) -> 2000
B16: Sportomic (Organized by RallyGully) | C16: 0 | D16: 0 | E16: 0 | F16: 0 | G16: 0 | H16: 320 | I16: 0 | J16: 0 | K16: 0 | L16: =SUM(C16:K16) -> 320
B17: Rallygully Community games | C17: 0 | D17: 0 | E17: 0 | F17: 3250 | G17: 3320 | H17: 360 | I17: 3000 | J17: 0 | K17: 600 | L17: =SUM(C17:K17) -> 10530
B18: Misfits Community | C18: 0 | D18: 0 | E18: 960 | F18: 2830 | G18: 4640 | H18: 820 | I18: 0 | J18: 0 | K18: 1800 | L18: =SUM(C18:K18) -> 11050
B19: Memberships | C19: 0 | D19: 0 | E19: 27000 | F19: 26000 | G19: 24380 | H19: 34380 | I19: 18880 | J19: 43880 | K19: 62880 | L19: =SUM(C19:K19) -> 237400
B20: Coaching | C20: 0 | D20: 0 | E20: 0 | F20: 0 | G20: 0 | H20: 0 | I20: 0 | J20: 0 | K20: 0 | L20: =SUM(C20:K20) -> 0
B21: Corporate Events | C21: 0 | D21: 0 | E21: 0 | F21: 0 | G21: 0 | H21: 20680 | I21: 2730 | J21: 5520 | K21: 5520 | L21: =SUM(C21:K21) -> 34450
B22: Brand Activation | C22: 0 | D22: 0 | E22: 0 | F22: 0 | G22: 4480 | H22: 0 | I22: 0 | J22: 0 | K22: 0 | L22: =SUM(C22:K22) -> 4480
B23: Other Income | C23: 0 | D23: 0 | E23: 0 | F23: 0 | G23: 0 | H23: 0 | I23: 0 | J23: 0 | K23: 0 | L23: =SUM(C23:K23) -> 0
B24: Total Gross Revenue | C24: =sum(C3,C8,C19,C21,C22,C23,C14, C20) -> 0 | D24: =sum(D3,D8,D19,D21,D22,D23,D14, D20) -> 37420 | E24: =sum(E3,E8,E19,E21,E22,E23,E14, E20) -> 154961 | F24: =sum(F3,F8,F19,F21,F22,F23,F14, F20) -> 87195 | G24: =sum(G3,G8,G19,G21,G22,G23,G14, G20) -> 151276 | H24: =sum(H3,H8,H19,H21,H22,H23,H14, H20) -> 175700 | I24: =sum(I3,I8,I19,I21,I22,I23,I14, I20) -> 169521 | J24: =sum(J3,J8,J19,J21,J22,J23,J14, J20) -> 210880 | K24: =sum(K3,K8,K19,K21,K22,K23,K14, K20) -> 226770 | L24: =sum(L3,L8,L14,L19,L20,L21,L22,L23) -> 1213723
B25: Total Net Revenue (Post Commissions) | C25: 0 | D25: 36852 | E25: 143412.5 | F25: 84073 | G25: 147818 | H25: 170690 | I25: 165384 | J25: 207434.28 | K25: 220596.66 | L25: =SUM(C25:K25) -> 1176260.4
B26: Total Revenue post GST | C26: =C25/1.18 -> 0 | D26: =D25/1.18 -> 31230.508 | E26: =E25/1.18 -> 121536.02 | F26: =F25/1.18 -> 71248.305 | G26: =G25/1.18 -> 125269.49 | H26: =H25/1.18 -> 144652.54 | I26: =I25/1.18 -> 140155.93 | J26: =J25/1.18 -> 175791.76 | K26: =K25/1.18 -> 186946.32 | L26: =SUM(C26:K26) -> 996830.88
B27: Note
B28: Venue Operational from 4th Aug

Sheet RallyGully I East of Kailash
B1: Venue Sheet | F1: Link | G1: Link | H1: Link | I1: Link | J1: Link | K1: Link
B2: Metrics | C2: July | D2: August | E2: September | F2: October | G2: November | H2: December | I2: January | J2: February | K2: March | L2: TOTAL
B3: Offline | C3: =SUM(C4,C5,C6,C18, C7) -> 0 | D3: =SUM(D4,D5,D6,D18, D7) -> 0 | E3: =SUM(E4,E5,E6,E18, E7) -> 6190 | F3: =SUM(F4,F5,F6,F18, F7) -> 15260 | G3: =SUM(G4,G5,G6, G7) -> 24530 | H3: =SUM(H4,H5,H6,H7) -> 23250 | I3: =SUM(I4,I5,I6,I7) -> 31691 | J3: =SUM(J4,J5,J6,J7) -> 53390 | K3: =SUM(K4,K5,K6,K7) -> 38330 | L3: =SUM(C3:K3) -> 192641
B4: Rentals | C4: 0 | D4: 0 | E4: 4350 | F4: 6550 | G4: 6750 | H4: 6150 | I4: 10650 | J4: 17940 | K4: 10550 | L4: =SUM(C4:K4) -> 62940 | N4: Pay & Play Revenue
B5: F&B | C5: 0 | D5: 0 | E5: 0 | F5: 0 | G5: 0 | H5: 460 | I5: 205 | J5: 1830 | K5: 1200 | L5: =SUM(C5:K5) -> 3695 | N5: Community Revenue
B6: Product Sales | C6: 0 | D6: 0 | E6: 0 | F6: 0 | G6: 0 | H6: 0 | I6: 0 | J6: 0 | K6: 0 | L6: =SUM(C6:K6) -> 0 | N6: Academy Revenue
B7: Bookings | C7: 0 | D7: 0 | E7: 1840 | F7: 3510 | G7: 17780 | H7: 16640 | I7: 20836 | J7: 33620 | K7: 26580 | L7: =SUM(C7:K7) -> 120806 | N7: B2B: Corporate and Brand Partnerships
B8: Online: Third Party Platform | C8: 0 | D8: =SUM(D9:D13) -> 0 | E8: =SUM(E9:E13) -> 72668.8 | F8: =SUM(F9:F13) -> 127472.6 | G8: =SUM(G9:G13) -> 99954 | H8: =SUM(H9:H13) -> 54376 | I8: =SUM(I9:I13) -> 96047 | J8: =SUM(J9:J13) -> 113165 | K8: =SUM(K9:K13) -> 156968 | L8: =SUM(C8:K8) -> 720651.4 | N8: Commerce
B9: Hudle | C9: 0 | D9: 0 | E9: 67870 | F9: 115555 | G9: 87600 | H9: 38450 | I9: 66479 | J9: 70765 | K9: 97168 | L9: =SUM(C9:K9) -> 543887
B10: Playo | C10: 0 | D10: 0 | E10: 2638.8 | F10: 5917.6 | G10: 6600 | H10: 6326 | I10: 3168 | J10: 5200 | K10: 7250 | L10: =SUM(C10:K10) -> 37100.4
B11: District | C11: 0 | D11: 0 | E11: 0 | F11: 1200 | G11: 2330 | H11: 6000 | I11: 26400 | J11: 37200 | K11: 51350 | L11: =SUM(C11:K11) -> 124480
B12: Khelomore | C12: 0 | D12: 0 | E12: 2160 | F12: 4800 | G12: 3424 | H12: 3600 | I12: 0 | J12: 0 | K12: 1200 | L12: =SUM(C12:K12) -> 15184
B13: Zplys | C13: 0 | D13: 0 | E13: 0 | F13: 0 | G13: 0 | H13: 0 | I13: 0 | J13: 0 | K13: 0 | L13: =SUM(C13:K13) -> 0
B14: Community | C14: =sum(C15:C18) -> 0 | D14: =sum(D15:D18) -> 0 | E14: =sum(E15:E18) -> 0 | F14: =sum(F15:F18) -> 10400 | G14: =sum(G15:G18) -> 12800 | H14: =SUM(H16,H17,H18) -> 12399 | I14: =SUM(I16,I17,I18) -> 43729 | J14: =SUM(J16,J17,J18,J15) -> 103699 | K14: =SUM(K16,K17,K18,K15) -> 42466 | L14: =SUM(C14:K14) -> 225493
B15: Courtly (Organized by RallyGully) | C15: 0 | D15: 0 | E15: 0 | F15: 0 | G15: 3500 | H15: 0 | I15: 0 | J15: 55200 | K15: 0 | L15: =SUM(C15:K15) -> 58700
B16: Sportomic (Organized by RallyGully) | C16: 0 | D16: 0 | E16: 0 | F16: 0 | G16: 0 | H16: 8100 | I16: 0 | J16: 6900 | K16: 17590 | L16: =SUM(C16:K16) -> 32590
B17: Rallygully Community games | C17: 0 | D17: 0 | E17: 0 | F17: 5200 | G17: 3600 | H17: 450 | I17: 43729 | J17: 35380 | K17: 23280 | L17: =SUM(C17:K17) -> 111639
B18: Misfits Community | C18: 0 | D18: 0 | E18: 0 | F18: 5200 | G18: 5700 | H18: 3849 | I18: 0 | J18: 6219 | K18: 1596 | L18: =SUM(C18:K18) -> 22564
B19: Memberships | C19: 0 | D19: 0 | E19: 0 | F19: 15300 | G19: 0 | H19: 10000 | I19: 27000 | J19: 40000 | K19: 38300 | L19: =SUM(C19:K19) -> 130600
B20: Coaching | C20: 0 | D20: 0 | E20: 0 | F20: 0 | G20: 0 | H20: 0 | I20: 54000 | J20: =15000+6000 -> 21000 | K20: 0 | L20: =SUM(C20:K20) -> 75000
B21: Corporate Events | C21: 0 | D21: 0 | E21: 0 | F21: 0 | G21: 0 | H21: 0 | I21: 3000 | J21: 3900 | K21: 5000 | L21: =SUM(C21:K21) -> 11900
B22: Brand Activation | C22: 0 | D22: 0 | E22: 0 | F22: 15000 | G22: 0 | H22: 23313 | I22: 24100 | J22: 30000 | K22: 0 | L22: =SUM(C22:K22) -> 92413
B23: Other Income | C23: 0 | D23: 0 | E23: 0 | F23: 0 | G23: 7000 | H23: 0 | I23: 0 | J23: 0 | K23: 0 | L23: =SUM(C23:K23) -> 7000
B24: Total Gross Revenue | C24: =sum(C3,C8,C19,C21,C22,C23,C14, C20) -> 0 | D24: =sum(D3,D8,D19,D21,D22,D23,D14, D20) -> 0 | E24: =sum(E3,E8,E19,E21,E22,E23,E14, E20) -> 78858.8 | F24: =sum(F3,F8,F19,F21,F22,F23,F14, F20) -> 183432.6 | G24: =sum(G3,G8,G19,G21,G22,G23,G14, G20) -> 144284 | H24: =sum(H3,H8,H19,H21,H22,H23,H14, H20) -> 123338 | I24: =sum(I3,I8,I14,I19,I20,I21,I22,I23) -> 279567 | J24: =sum(J3,J8,J14,J19,J20,J21,J22,J23) -> 365154 | K24: =sum(K3,K8,K14,K19,K20,K21,K22,K23) -> 281064 | L24: =sum(L3,L8,L14,L19,L20,L21,L22,L23) -> 1455698.4
B25: Total Net Revenue (Post Commissions) | C25: 0 | D25: 0 | E25: 69297 | F25: 161389 | G25: 136408 | H25: 117393 | I25: 264290 | J25: 354855.96 | K25: 227496.86 | L25: =SUM(C25:K25) -> 1331129.8
B26: Total Revenue post GST | C26: =C25/1.18 -> 0 | D26: =D25/1.18 -> 0 | E26: =E25/1.18 -> 58726.271 | F26: =F25/1.18 -> 136770.34 | G26: =G25/1.18 -> 115600 | H26: =H25/1.18 -> 99485.593 | I26: =I25/1.18 -> 223974.58 | J26: =J25/1.18 -> 300725.39 | K26: =K25/1.18 -> 192793.95 | L26: =SUM(C26:K26) -> 1128076.1
B27: Note
B28: Venue Operational from 17th Sep

Sheet RallyGully I Sector 19 Dwarka
B1: Venue Sheet | F1: Link | G1: Link | H1: Link | I1: Link | J1: Link | K1: Link
B2: Metrics | C2: July | D2: August | E2: September | F2: October | G2: November | H2: December | I2: January | J2: February | K2: March | L2: TOTAL
B3: Offline | C3: =SUM(C4,C5,C6,C7) -> 0 | D3: =SUM(D4,D5,D6,D7) -> 0 | E3: =SUM(E4,E5,E6,E7) -> 0 | F3: =SUM(F4,F5,F6,F7) -> 8715 | G3: =SUM(G4,G5,G6,G7) -> 13304 | H3: =SUM(H4,H5,H6,H7) -> 11535 | I3: =SUM(I4,I5,I6,I7) -> 59801 | J3: =SUM(J4,J5,J6,J7) -> 40880 | K3: =SUM(K4,K5,K6,K7) -> 34510 | L3: =SUM(C3:K3) -> 168745 | M3: =L3/1.18 -> 143004.24
B4: Rentals | C4: 0 | D4: 0 | E4: 0 | F4: 5535 | G4: 3460 | H4: 3775 | I4: 12375 | J4: 5880 | K4: 6230 | L4: =SUM(C4:K4) -> 37255
B5: F&B | C5: 0 | D5: 0 | E5: 0 | F5: 0 | G5: 0 | H5: 0 | I5: 140 | J5: 0 | K5: 0 | L5: =SUM(C5:K5) -> 140
B6: Product Sales | C6: 0 | D6: 0 | E6: 0 | F6: 0 | G6: 0 | H6: 0 | I6: 0 | J6: 0 | K6: 0 | L6: =SUM(C6:K6) -> 0 | M6: =L6/1.18 -> 0
B7: Bookings | C7: 0 | D7: 0 | E7: 0 | F7: 3180 | G7: 9844 | H7: 7760 | I7: 47286 | J7: 35000 | K7: 28280 | L7: =SUM(C7:K7) -> 131350
B8: Online: Third Party Platform | C8: =SUM(C9:C13) -> 0 | D8: 0 | E8: =SUM(E9:E13) -> 0 | F8: =SUM(F9:F13) -> 34220 | G8: =SUM(G9:G13) -> 30325 | H8: =SUM(H9:H13) -> 15050 | I8: =SUM(I9:I13) -> 25763 | J8: =SUM(J9:J13) -> 20980 | K8: =SUM(K9:K13) -> 50065 | L8: =SUM(C8:K8) -> 176403 | M8: =L8/1.18 -> 149494.07
B9: Hudle | C9: 0 | D9: 0 | E9: 0 | F9: 32340 | G9: 29525 | H9: 14650 | I9: 16146 | J9: 13940 | K9: 26070 | L9: =SUM(C9:K9) -> 132671
B10: Playo | C10: 0 | D10: 0 | E10: 0 | F10: 1280 | G10: 800 | H10: 400 | I10: 2077 | J10: 2240 | K10: 1520 | L10: =SUM(C10:K10) -> 8317
B11: District | C11: 0 | D11: 0 | E11: 0 | F11: 0 | G11: 0 | H11: 0 | I11: 6400 | J11: 2800 | K11: 18175 | L11: =SUM(C11:K11) -> 27375
B12: Khelomore | C12: 0 | D12: 0 | E12: 0 | F12: 600 | G12: 0 | H12: 0 | I12: 1140 | J12: 2000 | K12: 4300 | L12: =SUM(C12:K12) -> 8040
B13: Zplys | C13: 0 | D13: 0 | E13: 0 | F13: 0 | G13: 0 | H13: 0 | I13: 0 | J13: 0 | K13: 0 | L13: =SUM(C13:K13) -> 0
B14: Community | C14: =sum(C17:C18) -> 0 | D14: =sum(D17:D18) -> 0 | E14: =sum(E17:E18) -> 0 | F14: =sum(F17:F18) -> 10310 | G14: =sum(G15:G18) -> 16400 | H14: =SUM(H16,H17,H18) -> 6340 | I14: =SUM(I16,I17,I18) -> 12050 | J14: =SUM(J16,J17,J18) -> 6600 | K14: =SUM(K16,K17,K18) -> 2300 | L14: =SUM(C14:K14) -> 54000 | M14: =L14/1.18 -> 45762.712
B15: Courtly (Organized by RallyGully) | C15: 0 | D15: 0 | E15: 0 | F15: 0 | G15: 3000 | H15: 0 | I15: 0 | J15: 0 | K15: 0 | L15: =SUM(C15:K15) -> 3000
B16: Sportomic (Organized by RallyGully) | C16: 0 | D16: 0 | E16: 0 | F16: 0 | G16: 0 | H16: 4800 | I16: 0 | J16: 1000 | K16: 0 | L16: =SUM(C16:K16) -> 5800
B17: Rallygully Community games | C17: 0 | D17: 0 | E17: 0 | F17: 8070 | G17: 12760 | H17: 900 | I17: 12050 | J17: 5600 | K17: 2300 | L17: =SUM(C17:K17) -> 41680
B18: Misfits Community | C18: 0 | D18: 0 | E18: 0 | F18: 2240 | G18: 640 | H18: 640 | I18: 0 | J18: 0 | K18: 0 | L18: =SUM(C18:K18) -> 3520
B19: Memberships | C19: 0 | D19: 0 | E19: 0 | F19: 0 | G19: 0 | H19: 0 | I19: 9600 | J19: 0 | K19: 0 | L19: =SUM(C19:K19) -> 9600 | M19: =L19/1.18 -> 8135.5932
B20: Coaching | C20: 0 | D20: 0 | E20: 0 | F20: 0 | G20: 0 | H20: 0 | I20: 0 | J20: 0 | K20: 0 | L20: =SUM(C20:K20) -> 0 | M20: =L20/1.18 -> 0
B21: Corporate Events | C21: 0 | D21: 0 | E21: 0 | F21: 0 | G21: 0 | H21: 0 | I21: 0 | J21: 0 | K21: 0 | L21: =SUM(C21:K21) -> 0 | M21: =L21/1.18 -> 0
B22: Brand Activation | C22: 0 | D22: 0 | E22: 0 | F22: 0 | G22: 0 | H22: 0 | I22: 0 | J22: 0 | K22: 0 | L22: =SUM(C22:K22) -> 0 | M22: =L22/1.18 -> 0
B23: Other Income | C23: 0 | D23: 0 | E23: 0 | F23: 18000 | G23: 18000 | H23: 18000 | I23: 18000 | J23: 18000 | K23: 18000 | L23: =SUM(C23:K23) -> 108000 | M23: =L23/1.18 -> 91525.424
B24: Total Gross Revenue | C24: =sum(C3,C8,C14,C19,C20,C21,C22,C23) -> 0 | D24: =sum(D3,D8,D14,D19,D20,D21,D22,D23) -> 0 | E24: =sum(E3,E8,E14,E19,E20,E21,E22,E23) -> 0 | F24: =sum(F3,F8,F14,F19,F20,F21,F22,F23) -> 71245 | G24: =sum(G3,G8,G14,G19,G20,G21,G22,G23) -> 78029 | H24: =sum(H3,H8,H14,H19,H20,H21,H22,H23) -> 50925 | I24: =sum(I3,I8,I14,I19,I20,I21,I22,I23) -> 125214 | J24: =sum(J3,J8,J14,J19,J20,J21,J22,J23) -> 86460 | ... L24: =sum(L3,L8,L14,L19,L20,L21,L22,L23) -> 516748
B25: Total Net Revenue (Post Commissions) | C25: 0 | D25: 0 | E25: 0 | F25: 66434 | G25: 73886 | H25: 48807 | I25: 122701 | J25: 84275.68 | K25: 100503.36 | L25: =SUM(C25:K25) -> 496607.04
B26: Total Revenue post GST | C26: =C25/1.18 -> 0 | D26: =D25/1.18 -> 0 | E26: =E25/1.18 -> 0 | F26: =F25/1.18 -> 56300 | G26: =G25/1.18 -> 62615.254 | H26: =((H25-H23)/1.18)+H23 -> 44107.627 | I26: =((I25-I23)/1.18)+I23 -> 106729.66 | J26: =((J25-J23)/1.18)+J23 -> 74165.831 | K26: =((K25-K23)/1.18)+K23 -> 87918.102 | L26: =SUM(C26:K26) -> 431836.47
B27: Note
B28: Venue Operational from 28th Sep

Sheet RallyGully | DPSG
B1: Venue Sheet | H1: Link | I1: Link | J1: Link | K1: Link
B2: Metrics | C2: July | D2: August | E2: September | F2: October | G2: November | H2: December | I2: January | J2: February | K2: March | L2: TOTAL
B3: Offline | C3: =SUM(C4,C5,C6,C7) -> 0 | D3: =SUM(D4,D5,D6,D7) -> 0 | E3: =SUM(E4,E5,E6,E7) -> 0 | F3: =SUM(F4,F5,F6,F7) -> 0 | G3: =SUM(G4,G5,G6,G7) -> 0 | H3: =SUM(H4,H5,H6,H7) -> 10137 | I3: =SUM(I4,I5,I6,I7) -> 8850 | J3: =SUM(J4,J5,J6,J7) -> 37220 | K3: =SUM(K4,K5,K6,K7) -> 68265 | L3: =SUM(C3:K3) -> 124472 | M3: =L3/1.18 -> 105484.75
B4: Rentals | C4: 0 | D4: 0 | E4: 0 | F4: 0 | G4: 0 | H4: 3850 | I4: 7950 | J4: 11750 | K4: 9275 | L4: =SUM(C4:K4) -> 32825
B5: F&B | C5: 0 | D5: 0 | E5: 0 | F5: 0 | G5: 0 | H5: 0 | I5: 0 | J5: 0 | K5: 0 | L5: =SUM(C5:K5) -> 0
B6: Product Sales | C6: 0 | D6: 0 | E6: 0 | F6: 0 | G6: 0 | H6: 0 | I6: 0 | J6: 0 | K6: 0 | L6: =SUM(C6:K6) -> 0
B7: Bookings | C7: 0 | D7: 0 | E7: 0 | F7: 0 | G7: 0 | H7: 6287 | I7: 900 | J7: 25470 | K7: 58990 | L7: =SUM(C7:K7) -> 91647
B8: Online: Third Party Platform | C8: =SUM(C9:C13) -> 0 | D8: =SUM(D9:D13) -> 0 | E8: =SUM(E9:E13) -> 0 | F8: =SUM(F9:F13) -> 0 | G8: =SUM(G9:G13) -> 0 | H8: =SUM(H9:H13) -> 7600 | I8: =SUM(I9:I13) -> 40370 | J8: =SUM(J9:J13) -> 73780 | K8: =SUM(K9:K13) -> 44755 | L8: =SUM(C8:K8) -> 166505 | M8: =L8/1.18 -> 141105.93
B9: Hudle | C9: 0 | D9: 0 | E9: 0 | F9: 0 | G9: 0 | H9: 3100 | I9: 17570 | J9: 14380 | K9: 5505 | L9: =SUM(C9:K9) -> 40555
B10: Playo | C10: 0 | D10: 0 | E10: 0 | F10: 0 | G10: 0 | H10: 3600 | I10: 1450 | J10: 1800 | K10: 900 | L10: =SUM(C10:K10) -> 7750
B11: District | C11: 0 | D11: 0 | E11: 0 | F11: 0 | G11: 0 | H11: 900 | I11: 21350 | J11: 57600 | K11: 38350 | L11: =SUM(C11:K11) -> 118200
B12: Khelomore | C12: 0 | D12: 0 | E12: 0 | F12: 0 | G12: 0 | H12: 0 | I12: 0 | J12: 0 | K12: 0 | L12: =SUM(C12:K12) -> 0
B13: Zplys | C13: 0 | D13: 0 | E13: 0 | F13: 0 | G13: 0 | H13: 0 | I13: 0 | J13: 0 | K13: 0 | L13: =SUM(C13:K13) -> 0
B14: Community | C14: =SUM(C16,C15, C17,C18) -> 0 | D14: =SUM(D16,D15, D17,D18) -> 0 | E14: =SUM(E16,E15, E17,E18) -> 0 | F14: =SUM(F16,F15, F17,F18) -> 0 | G14: =SUM(G16,G15, G17,G18) -> 0 | H14: =SUM(H16,H15, H17,H18) -> 3900 | I14: =SUM(I16,I15, I17,I18) -> 600 | J14: =SUM(J16,J15, J17,J18) -> 0 | K14: =SUM(K16,K15, K17,K18) -> 56360 | L14: =SUM(C14:K14) -> 60860 | M14: =L14/1.18 -> 51576.271
B15: Courtly (Organized by RallyGully) | C15: 0 | D15: 0 | E15: 0 | F15: 0 | G15: 0 | H15: 0 | I15: 0 | J15: 0 | K15: 40480 | L15: =SUM(C15:K15) -> 40480
B16: Sportomic (Organized by RallyGully) | C16: 0 | D16: 0 | E16: 0 | F16: 0 | G16: 0 | H16: 3100 | I16: 0 | J16: 0 | K16: 0 | L16: =SUM(C16:K16) -> 3100
B17: Rallygully Community games | C17: 0 | D17: 0 | E17: 0 | F17: 0 | G17: 0 | H17: 800 | I17: 600 | J17: 0 | K17: 15880 | L17: =SUM(C17:K17) -> 17280
B18: Misfits Community | C18: 0 | D18: 0 | E18: 0 | F18: 0 | G18: 0 | H18: 0 | I18: 0 | J18: 0 | K18: 0 | L18: =SUM(C18:K18) -> 0
B19: Memberships | C19: 0 | D19: 0 | E19: 0 | F19: 0 | G19: 0 | H19: 0 | I19: 0 | J19: 0 | K19: 0 | L19: =SUM(C19:K19) -> 0 | M19: =L19/1.18 -> 0
B20: Coaching | C20: 0 | D20: 0 | E20: 0 | F20: 0 | G20: 0 | H20: 0 | I20: 0 | J20: 0 | K20: 0 | L20: =SUM(C20:K20) -> 0 | M20: =L20/1.18 -> 0
B21: Corporate Events | C21: 0 | D21: 0 | E21: 0 | F21: 0 | G21: 0 | H21: 0 | I21: 0 | J21: 2460 | K21: 0 | L21: =SUM(C21:K21) -> 2460 | M21: =L21/1.18 -> 2084.7458
B22: Brand Activation | C22: 0 | D22: 0 | E22: 0 | F22: 0 | G22: 0 | H22: 0 | I22: 0 | J22: 0 | K22: 10000 | L22: =SUM(C22:K22) -> 10000 | M22: =L22/1.18 -> 8474.5763
B23: Other Income | C23: 0 | D23: 0 | E23: 0 | F23: 0 | G23: 0 | H23: 0 | I23: 0 | J23: 0 | K23: 0 | L23: =SUM(C23:K23) -> 0 | M23: =L23/1.18 -> 0
B24: Total Gross Revenue | C24: =sum(C3,C8,C14,C19,C20,C21,C22,C23) -> 0 | D24: =sum(D3,D8,D14,D19,D20,D21,D22,D23) -> 0 | E24: =sum(E3,E8,E14,E19,E20,E21,E22,E23) -> 0 | F24: =sum(F3,F8,F14,F19,F20,F21,F22,F23) -> 0 | G24: =sum(G3,G8,G14,G19,G20,G21,G22,G23) -> 0 | H24: =sum(H3,H8,H14,H19,H20,H21,H22,H23) -> 21637 | I24: =sum(I3,I8,I14,I19,I20,I21,I22,I23) -> 49820 | J24: =sum(J3,J8,J14,J19,J20,J21,J22,J23) -> 113460 | ... L24: =sum(L3,L8,L14,L19,L20,L21,L22,L23) -> 364297 | M24: =L24/1.18 -> 308726.27
B25: Total Net Revenue (Post Commissions) | C25: 0 | D25: 0 | E25: 0 | F25: 0 | G25: 0 | H25: 20915 | I25: 45663 | J25: 110603.09 | K25: 176378.48 | L25: =SUM(C25:K25) -> 353559.57
B26: Total Revenue post GST | C26: =C25/1.18 -> 0 | D26: =D25/1.18 -> 0 | E26: =E25/1.18 -> 0 | F26: =F25/1.18 -> 0 | G26: =G25/1.18 -> 0 | H26: =H25/1.18 -> 17724.576 | I26: =I25/1.18 -> 38697.458 | J26: =J25/1.18 -> 93731.432 | K26: =K25/1.18 -> 149473.29 | L26: =SUM(C26:K26) -> 299626.75
B27: Note
B28: Venue Operational from 13th Dec

Sheet RallyGully | Panchsheel
B1: Venue Sheet | I1: Link | J1: Link | K1: Link
B2: Metrics | C2: July | D2: August | E2: September | F2: October | G2: November | H2: December | I2: January | J2: February | K2: March | L2: TOTAL
B3: Offline | C3: =SUM(C4,C5,C6,C7) -> 0 | D3: =SUM(D4,D5,D6,D7) -> 0 | E3: =SUM(E4,E5,E6,E7) -> 0 | F3: =SUM(F4,F5,F6,F7) -> 0 | G3: =SUM(G4,G5,G6,G7) -> 0 | H3: =SUM(H4,H5,H6,H7) -> 0 | I3: =SUM(I4,I5,I6,I7) -> 30252 | J3: =SUM(J4,J5,J6,J7) -> 16510 | K3: =SUM(K4,K5,K6,K7) -> 26050 | L3: =SUM(C3:K3) -> 72812 | M3: =L3/1.18 -> 61705.085
B4: Rentals | C4: 0 | D4: 0 | E4: 0 | F4: 0 | G4: 0 | H4: 0 | I4: 3700 | J4: 4600 | K4: 7050 | L4: =SUM(C4:K4) -> 15350
B5: F&B | C5: 0 | D5: 0 | E5: 0 | F5: 0 | G5: 0 | H5: 0 | I5: 0 | J5: 0 | K5: 0 | L5: =SUM(C5:K5) -> 0
B6: Product Sales | C6: 0 | D6: 0 | E6: 0 | F6: 0 | G6: 0 | H6: 0 | I6: 0 | J6: 0 | K6: 0 | L6: =SUM(C6:K6) -> 0 | M6: =L6/1.18 -> 0
B7: Bookings | C7: 0 | D7: 0 | E7: 0 | F7: 0 | G7: 0 | H7: 0 | I7: 26552 | J7: 11910 | K7: 19000 | L7: =SUM(C7:K7) -> 57462
B8: Online: Third Party Platform | C8: =SUM(C9:C13) -> 0 | D8: =SUM(D9:D13) -> 0 | E8: =SUM(E9:E13) -> 0 | F8: =SUM(F9:F13) -> 0 | G8: =SUM(G9:G13) -> 0 | H8: =SUM(H9:H13) -> 0 | I8: =SUM(I9:I13) -> 48336 | J8: =SUM(J9:J13) -> 63000 | K8: =SUM(K9:K13) -> 110415 | L8: =SUM(C8:K8) -> 221751 | M8: =L8/1.18 -> 187924.58
B9: Hudle | C9: 0 | D9: 0 | E9: 0 | F9: 0 | G9: 0 | H9: 0 | I9: 40056 | J9: 48600 | K9: 62515 | L9: =SUM(C9:K9) -> 151171
B10: Playo | C10: 0 | D10: 0 | E10: 0 | F10: 0 | G10: 0 | H10: 0 | I10: 2880 | J10: 0 | K10: 0 | L10: =SUM(C10:K10) -> 2880
B11: District | C11: 0 | D11: 0 | E11: 0 | F11: 0 | G11: 0 | H11: 0 | I11: 5400 | J11: 14400 | K11: 47900 | L11: =SUM(C11:K11) -> 67700
B12: Khelomore | C12: 0 | D12: 0 | E12: 0 | F12: 0 | G12: 0 | H12: 0 | I12: 0 | J12: 0 | K12: 0 | L12: =SUM(C12:K12) -> 0
B13: Zplys | C13: 0 | D13: 0 | E13: 0 | F13: 0 | G13: 0 | H13: 0 | I13: 0 | J13: 0 | K13: 0 | L13: =SUM(C13:K13) -> 0
B14: Community | C14: =SUM(C16,C15, C17,C18) -> 0 | D14: =SUM(D16,D15, D17,D18) -> 0 | E14: =SUM(E16,E15, E17,E18) -> 0 | F14: =SUM(F16,F15, F17,F18) -> 0 | G14: =SUM(G16,G15, G17,G18) -> 0 | H14: =SUM(H16,H15, H17,H18) -> 0 | I14: =SUM(I16,I15, I17,I18) -> 0 | J14: =SUM(J16,J15, J17,J18) -> 9460 | K14: =SUM(K16,K15, K17,K18) -> 4548 | L14: =SUM(C14:K14) -> 14008 | M14: =L14/1.18 -> 11871.186
B15: Courtly (Organized by RallyGully) | C15: 0 | D15: 0 | E15: 0 | F15: 0 | G15: 0 | H15: 0 | I15: 0 | J15: 0 | K15: 0 | L15: =SUM(C15:K15) -> 0
B16: Sportomic (Organized by RallyGully) | C16: 0 | D16: 0 | E16: 0 | F16: 0 | G16: 0 | H16: 0 | I16: 0 | J16: 0 | K16: 0 | L16: =SUM(C16:K16) -> 0
B17: Rallygully Community games | C17: 0 | D17: 0 | E17: 0 | F17: 0 | G17: 0 | H17: 0 | I17: 0 | J17: 0 | K17: 0 | L17: =SUM(C17:K17) -> 0
B18: Misfits Community | C18: 0 | D18: 0 | E18: 0 | F18: 0 | G18: 0 | H18: 0 | I18: 0 | J18: 9460 | K18: 4548 | L18: =SUM(C18:K18) -> 14008
B19: Memberships | C19: 0 | D19: 0 | E19: 0 | F19: 0 | G19: 0 | H19: 0 | I19: 0 | J19: 0 | K19: 0 | L19: =SUM(C19:K19) -> 0 | M19: =L19/1.18 -> 0
B20: Coaching | C20: 0 | D20: 0 | E20: 0 | F20: 0 | G20: 0 | H20: 0 | I20: 0 | J20: 0 | K20: 0 | L20: =SUM(C20:K20) -> 0 | M20: =L20/1.18 -> 0
B21: Corporate Events | C21: 0 | D21: 0 | E21: 0 | F21: 0 | G21: 0 | H21: 0 | I21: 0 | J21: 0 | K21: 0 | L21: =SUM(C21:K21) -> 0 | M21: =L21/1.18 -> 0
B22: Brand Activation | C22: 0 | D22: 0 | E22: 0 | F22: 0 | G22: 0 | H22: 0 | I22: 0 | J22: 0 | K22: 0 | L22: =SUM(C22:K22) -> 0 | M22: =L22/1.18 -> 0
B23: Other Income | C23: 0 | D23: 0 | E23: 0 | F23: 0 | G23: 0 | H23: 0 | I23: 0 | J23: 0 | K23: 0 | L23: =SUM(C23:K23) -> 0 | M23: =L23/1.18 -> 0
B24: Total Gross Revenue | C24: =sum(C3,C8,C14,C19,C20,C21,C22,C23) -> 0 | D24: =sum(D3,D8,D14,D19,D20,D21,D22,D23) -> 0 | E24: =sum(E3,E8,E14,E19,E20,E21,E22,E23) -> 0 | F24: =sum(F3,F8,F14,F19,F20,F21,F22,F23) -> 0 | G24: =sum(G3,G8,G14,G19,G20,G21,G22,G23) -> 0 | H24: =sum(H3,H8,H14,H19,H20,H21,H22,H23) -> 0 | I24: =sum(I3,I8,I14,I19,I20,I21,I22,I23) -> 78588 | J24: =sum(J3,J8,J14,J19,J20,J21,J22,J23) -> 88970 | ... M24: =sum(M3,M8,M14,M19,M20,M21,M22,M23) -> 261500.85
B25: Total Net Revenue (Post Commissions) | C25: 0 | D25: 0 | E25: 0 | F25: 0 | G25: 0 | H25: 0 | I25: 72955 | J25: 80551.94 | K25: 130500.87 | L25: =SUM(C25:K25) -> 284007.81
B26: Total Revenue post GST | C26: 0 | D26: 0 | E26: 0 | F26: 0 | G26: 0 | H26: 0 | I26: =I25/1.18 -> 61826.271 | J26: =J25/1.18 -> 68264.356 | K26: =K25/1.18 -> 110593.96 | L26: =SUM(C26:K26) -> 240684.58
B27: Note
B28: Venue Operational from 15th Jan

Sheet RallyGully | LCR Pune
B1: Venue Sheet | G1: Link | H1: Link | I1: Link | J1: Link | K1: Link
B2: Metrics | C2: July | D2: August | E2: September | F2: October | G2: November | H2: December | I2: January | J2: February | K2: March | L2: TOTAL
B3: Offline | C3: =SUM(C4,C5,C6,C7) -> 0 | D3: =SUM(D4,D5,D6,D7) -> 0 | E3: =SUM(E4,E5,E6,E7) -> 0 | F3: =SUM(F4,F5,F6,F7) -> 0 | G3: =SUM(G4,G5,G6,G7) -> 24225 | H3: =SUM(H4,H5,H6,H7) -> 94530 | I3: =SUM(I4,I5,I6,I7) -> 152203 | J3: =SUM(J4,J5,J6,J7) -> 191125 | K3: =SUM(K4,K5,K6,K7) -> 156605 | L3: =SUM(C3:K3) -> 618688 | M3: =L3/1.18 -> 524311.86
B4: Rentals | C4: 0 | D4: 0 | E4: 0 | F4: 0 | G4: 6225 | H4: 23500 | I4: 32800 | J4: 31275 | K4: 25350 | L4: =SUM(C4:K4) -> 119150
B5: F&B | C5: 0 | D5: 0 | E5: 0 | F5: 0 | G5: 0 | H5: 0 | I5: 0 | J5: 0 | K5: 0 | L5: =SUM(C5:K5) -> 0
B6: Product Sales | C6: 0 | D6: 0 | E6: 0 | F6: 0 | G6: 0 | H6: 0 | I6: 0 | J6: 0 | K6: 0 | L6: =SUM(C6:K6) -> 0 | M6: =L6/1.18 -> 0
B7: Bookings | C7: 0 | D7: 0 | E7: 0 | F7: 0 | G7: 18000 | H7: 71030 | I7: 119403 | J7: 159850 | K7: 131255 | L7: =SUM(C7:K7) -> 499538
B8: Online: Third Party Platform | C8: =SUM(C9:C13) -> 0 | D8: =SUM(D9:D13) -> 0 | E8: =SUM(E9:E13) -> 0 | F8: =SUM(F9:F13) -> 0 | G8: =SUM(G9:G13) -> 15900 | H8: =SUM(H9:H13) -> 64833 | I8: =SUM(I9:I13) -> 99437 | J8: =SUM(J9:J13) -> 137535 | K8: =SUM(K9:K13) -> 138630 | L8: =SUM(C8:K8) -> 456335 | M8: =L8/1.18 -> 386724.58
B9: Hudle | C9: 0 | D9: 0 | E9: 0 | F9: 0 | G9: 0 | H9: 14868 | I9: 18140 | J9: 38157 | K9: 40905 | L9: =SUM(C9:K9) -> 112070
B10: Playo | C10: 0 | D10: 0 | E10: 0 | F10: 0 | G10: 8025 | H10: 27840 | I10: 55478 | J10: 57993 | K10: 55350 | L10: =SUM(C10:K10) -> 204686
B11: District | C11: 0 | D11: 0 | E11: 0 | F11: 0 | G11: 0 | H11: 0 | I11: 0 | J11: 0 | K11: 0 | L11: =SUM(C11:K11) -> 0
B12: Khelomore | C12: 0 | D12: 0 | E12: 0 | F12: 0 | G12: 7875 | H12: 22125 | I12: 25819 | J12: 41385 | K12: 42375 | L12: =SUM(C12:K12) -> 139579
B13: Zplys | C13: 0 | D13: 0 | E13: 0 | F13: 0 | G13: 0 | H13: 0 | I13: 0 | J13: 0 | K13: 0 | L13: =SUM(C13:K13) -> 0
B14: Community | C14: =sum(C15:C18) -> 0 | D14: =sum(D15:D18) -> 0 | E14: =sum(E15:E18) -> 0 | F14: =sum(F15:F18) -> 0 | G14: =sum(G15:G18) -> 0 | H14: =SUM(H16,H15, H17,H18) -> 940 | I14: =SUM(I16,I15, I17,I18) -> 4860 | J14: =SUM(J16,J15, J17,J18) -> 2205 | K14: =SUM(K16,K15, K17,K18) -> 0 | L14: =SUM(C14:K14) -> 8005 | M14: =L14/1.18 -> 6783.8983
B15: Courtly (Organized by RallyGully) | C15: 0 | D15: 0 | E15: 0 | F15: 0 | G15: 0 | H15: 0 | I15: 0 | J15: 0 | K15: 0 | L15: =SUM(C15:K15) -> 0
B16: Sportomic (Organized by RallyGully) | C16: 0 | D16: 0 | E16: 0 | F16: 0 | G16: 0 | H16: 940 | I16: 0 | J16: 360 | K16: 0 | L16: =SUM(C16:K16) -> 1300
B17: Rallygully Community games | C17: 0 | D17: 0 | E17: 0 | F17: 0 | G17: 0 | H17: 0 | I17: 4860 | J17: 1845 | K17: 0 | L17: =SUM(C17:K17) -> 6705
B18: Misfits Community | C18: 0 | D18: 0 | E18: 0 | F18: 0 | G18: 0 | H18: 0 | I18: 0 | J18: 0 | K18: 0 | L18: =SUM(C18:K18) -> 0
B19: Memberships | C19: 0 | D19: 0 | E19: 0 | F19: 0 | G19: 0 | H19: 0 | I19: 0 | J19: 0 | K19: 0 | L19: =SUM(C19:K19) -> 0 | M19: =L19/1.18 -> 0
B20: Coaching | C20: 0 | D20: 0 | E20: 0 | F20: 0 | G20: 0 | H20: 0 | I20: 0 | J20: 0 | K20: 0 | L20: =SUM(C20:K20) -> 0 | M20: =L20/1.18 -> 0
B21: Corporate Events | C21: 0 | D21: 0 | E21: 0 | F21: 0 | G21: 0 | H21: 0 | I21: 23000 | J21: 0 | K21: 0 | L21: =SUM(C21:K21) -> 23000 | M21: =L21/1.18 -> 19491.525
B22: Brand Activation | C22: 0 | D22: 0 | E22: 0 | F22: 0 | G22: 0 | H22: 0 | I22: 0 | J22: 0 | K22: 0 | L22: =SUM(C22:K22) -> 0 | M22: =L22/1.18 -> 0
B23: Other Income | C23: 0 | D23: 0 | E23: 0 | F23: 0 | G23: 0 | H23: 11300 | I23: 120000 | J23: 120000 | K23: 120000 | L23: =SUM(C23:K23) -> 371300 | M23: =L23/1.18 -> 314661.02
B24: Total Gross Revenue | C24: =sum(C3,C8,C14,C19,C20,C21,C22,C23) -> 0 | D24: =sum(D3,D8,D14,D19,D20,D21,D22,D23) -> 0 | E24: =sum(E3,E8,E14,E19,E20,E21,E22,E23) -> 0 | F24: =sum(F3,F8,F14,F19,F20,F21,F22,F23) -> 0 | G24: =sum(G3,G8,G14,G19,G20,G21,G22,G23) -> 40125 | H24: =sum(H3,H8,H14,H19,H20,H21,H22,H23) -> 171603 | I24: =sum(I3,I8,I14,I19,I20,I21,I22,I23) -> 399500 | J24: =sum(J3,J8,J14,J19,J20,J21,J22,J23) -> 450865 | ... L24: =sum(L3,L8,L14,L19,L20,L21,L22,L23) -> 1477328
B25: Total Net Revenue (Post Commissions) | C25: =C24/1.18 -> 0 | D25: =D24/1.18 -> 0 | E25: =E24/1.18 -> 0 | F25: =F24/1.18 -> 0 | G25: 38878 | H25: 165616 | I25: 392285.41 | J25: 440045.64 | K25: 404133.28 | L25: =SUM(C25:K25) -> 1440958.3
B26: Total Revenue post GST | C26: =C25/1.18 -> 0 | D26: =D25/1.18 -> 0 | E26: =E25/1.18 -> 0 | F26: =F25/1.18 -> 0 | G26: =G25/1.18 -> 32947.458 | H26: =H25/1.18 -> 140352.54 | I26: =I25/1.18 -> 332445.26 | J26: =J25/1.18 -> 372920.03 | K26: =K25/1.18 -> 342485.83 | L26: =SUM(C26:K26) -> 1221151.1
B27: Note
B28: Venue Operational from 20th Nov

Sheet RallyGully | Gandipath
B1: Venue Sheet | H1: Link | I1: Link | J1: Link | K1: Link
B2: Metrics | C2: July | D2: August | E2: September | F2: October | G2: November | H2: December | I2: January | J2: February | K2: March | L2: TOTAL
B3: Offline | C3: 0 | D3: 0 | E3: 0 | F3: =SUM(F4,F5,F6,F7) -> 0 | G3: =SUM(G4,G5,G6,G7) -> 0 | H3: =SUM(H4,H5,H6,H7) -> 2100 | I3: =SUM(I4,I5,I6,I7) -> 41490 | J3: =SUM(J4,J5,J6,J7) -> 19525 | K3: =SUM(K4,K5,K6,K7) -> 24650 | L3: =SUM(C3:K3) -> 87765 | M3: =L3/1.18 -> 74377.119
B4: Rentals | C4: 0 | D4: 0 | E4: 0 | F4: 0 | G4: 0 | H4: 0 | I4: 0 | J4: 0 | K4: 0 | L4: =SUM(C4:K4) -> 0
B5: F&B | C5: 0 | D5: 0 | E5: 0 | F5: 0 | G5: 0 | H5: 0 | I5: 0 | J5: 0 | K5: 0 | L5: =SUM(C5:K5) -> 0
B6: Product Sales | C6: 0 | D6: 0 | E6: 0 | F6: 0 | G6: 0 | H6: 0 | I6: 18000 | J6: 0 | K6: 0 | L6: =SUM(C6:K6) -> 18000 | M6: =L6/1.18 -> 15254.237
B7: Bookings | C7: 0 | D7: 0 | E7: 0 | F7: 0 | G7: 0 | H7: 2100 | I7: 23490 | J7: 19525 | K7: 24650 | L7: =SUM(C7:K7) -> 69765
B8: Online: Third Party Platform | C8: =SUM(C9:C13) -> 0 | D8: =SUM(D9:D13) -> 0 | E8: =SUM(E9:E13) -> 0 | F8: =SUM(F9:F13) -> 0 | G8: =SUM(G9:G13) -> 0 | H8: =SUM(H9:H13) -> 2800 | I8: =SUM(I9:I13) -> 32635 | J8: =SUM(J9:J13) -> 47353 | K8: =SUM(K9:K13) -> 102905 | L8: =SUM(C8:K8) -> 185693 | M8: =L8/1.18 -> 157366.95
B9: Hudle | C9: 0 | D9: 0 | E9: 0 | F9: 0 | G9: 0 | H9: 1550 | I9: 3680 | J9: 3255 | K9: 5060 | L9: =SUM(C9:K9) -> 13545
B10: Playo | C10: 0 | D10: 0 | E10: 0 | F10: 0 | G10: 0 | H10: 0 | I10: 3160 | J10: 2240 | K10: 2720 | L10: =SUM(C10:K10) -> 8120
B11: District | C11: 0 | D11: 0 | E11: 0 | F11: 0 | G11: 0 | H11: 0 | I11: 0 | J11: 0 | K11: 0 | L11: =SUM(C11:K11) -> 0
B12: Khelomore | C12: 0 | D12: 0 | E12: 0 | F12: 0 | G12: 0 | H12: 0 | I12: 422 | J12: 1200 | K12: 0 | L12: =SUM(C12:K12) -> 1622
B13: Zplys | C13: 0 | D13: 0 | E13: 0 | F13: 0 | G13: 0 | H13: 1250 | I13: 25373 | J13: 40658 | K13: 95125 | L13: =SUM(C13:K13) -> 162406
B14: Community | C14: =SUM(C16,C15, C17,C18) -> 0 | D14: =SUM(D16,D15, D17,D18) -> 0 | E14: =SUM(E16,E15, E17,E18) -> 0 | F14: =SUM(F16,F15, F17,F18) -> 0 | G14: =SUM(G16,G15, G17,G18) -> 0 | H14: =SUM(H16,H15, H17,H18) -> 0 | I14: =SUM(I16,I15, I17,I18) -> 0 | J14: =SUM(J16,J15, J17,J18) -> 0 | K14: =SUM(K16,K15, K17,K18) -> 3600 | L14: =SUM(C14:K14) -> 3600 | M14: =L14/1.18 -> 3050.8475
B15: Courtly (Organized by RallyGully) | C15: 0 | D15: 0 | E15: 0 | F15: 0 | G15: 0 | H15: 0 | I15: 0 | J15: 0 | K15: 0 | L15: =SUM(C15:K15) -> 0
B16: Sportomic (Organized by RallyGully) | C16: 0 | D16: 0 | E16: 0 | F16: 0 | G16: 0 | H16: 0 | I16: 0 | J16: 0 | K16: 0 | L16: =SUM(C16:K16) -> 0
B17: Rallygully Community games | C17: 0 | D17: 0 | E17: 0 | F17: 0 | G17: 0 | H17: 0 | I17: 0 | J17: 0 | K17: 3600 | L17: =SUM(C17:K17) -> 3600
B18: Misfits Community | C18: 0 | D18: 0 | E18: 0 | F18: 0 | G18: 0 | H18: 0 | I18: 0 | J18: 0 | K18: 0 | L18: =SUM(C18:K18) -> 0
B19: Memberships | C19: 0 | D19: 0 | E19: 0 | F19: 0 | G19: 0 | H19: 0 | I19: 24000 | J19: 8000 | K19: 8000 | L19: =SUM(C19:K19) -> 40000 | M19: =L19/1.18 -> 33898.305
B20: Coaching | C20: 0 | D20: 0 | E20: 0 | F20: 0 | G20: 0 | H20: 0 | I20: 0 | J20: 0 | K20: 0 | L20: =SUM(C20:K20) -> 0 | M20: =L20/1.18 -> 0
B21: Corporate Events | C21: 0 | D21: 0 | E21: 0 | F21: 0 | G21: 0 | H21: 0 | I21: 0 | J21: 0 | K21: 0 | L21: =SUM(C21:K21) -> 0 | M21: =L21/1.18 -> 0
B22: Brand Activation | C22: 0 | D22: 0 | E22: 0 | F22: 0 | G22: 0 | H22: 0 | I22: 0 | J22: 0 | K22: 0 | L22: =SUM(C22:K22) -> 0 | M22: =L22/1.18 -> 0
B23: Other Income | C23: 0 | D23: 0 | E23: 0 | F23: 0 | G23: 0 | H23: 0 | I23: 0 | J23: 0 | K23: 0 | L23: =SUM(C23:K23) -> 0 | M23: =L23/1.18 -> 0
B24: Total Gross Revenue | C24: =sum(C3,C8,C14,C19,C20,C21,C22,C23) -> 0 | D24: =sum(D3,D8,D14,D19,D20,D21,D22,D23) -> 0 | E24: =sum(E3,E8,E14,E19,E20,E21,E22,E23) -> 0 | F24: =sum(F3,F8,F14,F19,F20,F21,F22,F23) -> 0 | G24: =sum(G3,G8,G14,G19,G20,G21,G22,G23) -> 0 | H24: =sum(H3,H8,H14,H19,H20,H21,H22,H23) -> 4900 | I24: =sum(I3,I8,I14,I19,I20,I21,I22,I23) -> 98125 | J24: =sum(J3,J8,J14,J19,J20,J21,J22,J23) -> 74878 | ... L24: =sum(L3,L8,L14,L19,L20,L21,L22,L23) -> 317058
B25: Total Net Revenue (Post Commissions) | C25: 0 | D25: 0 | E25: 0 | F25: 0 | G25: 0 | H25: 4694 | I25: 97318 | J25: 66106.48 | K25: 138225.08 | L25: =SUM(C25:K25) -> 306343.56
B26: Total Revenue post GST | C26: 0 | D26: 0 | E26: 0 | F26: 0 | G26: 0 | H26: =H25/1.18 -> 3977.9661 | I26: =(I25-I6)/1.18 + 17148 -> 84366.644 | J26: =(J25-J19)/1.18 + J19 -> 57242.78 | K26: =(K25-K19)/1.18 + K19 -> 118360.24 | L26: =SUM(C26:K26) -> 263947.63
B27: Note
B28: Venue Operational from 23rd Dec

Sheet Powerplay Park, Pune
B1: Venue Sheet | J1: Link | K1: Link
B2: Metrics | C2: July | D2: August | E2: September | F2: October | G2: November | H2: December | I2: January | J2: February | K2: March | L2: TOTAL
B3: Offline | C3: =SUM(C4,C5,C6,C7) -> 0 | D3: =SUM(D4,D5,D6,D7) -> 0 | E3: =SUM(E4,E5,E6,E7) -> 0 | F3: =SUM(F4,F5,F6,F7) -> 0 | G3: =SUM(G4,G5,G6,G7) -> 0 | H3: =SUM(H4,H5,H6,H7) -> 0 | I3: 0 | J3: =SUM(J4,J5,J6,J7) -> 0 | K3: =SUM(K4,K5,K6,K7) -> 29635 | L3: =SUM(C3:K3) -> 29635 | M3: =L3/1.18 -> 25114.407
B4: Rentals | C4: 0 | D4: 0 | E4: 0 | F4: 0 | G4: 0 | H4: 0 | I4: 0 | J4: 0 | K4: 0 | L4: =SUM(C4:K4) -> 0
B5: F&B | C5: 0 | D5: 0 | E5: 0 | F5: 0 | G5: 0 | H5: 0 | I5: =SUM(I6,I7,I8,I9) -> 0 | J5: 0 | K5: 0 | L5: =SUM(C5:K5) -> 0
B6: Product Sales | C6: 0 | D6: 0 | E6: 0 | F6: 0 | G6: 0 | H6: 0 | I6: 0 | J6: 0 | K6: 0 | L6: =SUM(C6:K6) -> 0
B7: Bookings | C7: 0 | D7: 0 | E7: 0 | F7: 0 | G7: 0 | H7: 0 | I7: 0 | J7: 0 | K7: 29635 | L7: =SUM(C7:K7) -> 29635
B8: Online: Third Party Platform | C8: =SUM(C9:C13) -> 0 | D8: =SUM(D9:D13) -> 0 | E8: =SUM(E9:E13) -> 0 | F8: =SUM(F9:F13) -> 0 | G8: =SUM(G9:G13) -> 0 | H8: =SUM(H9:H13) -> 0 | I8: 0 | J8: =SUM(J9:J13) -> 161 | K8: =SUM(K9:K13) -> 39125 | L8: =SUM(C8:K8) -> 39286 | M8: =L8/1.18 -> 33293.22
B9: Hudle | C9: 0 | D9: 0 | E9: 0 | F9: 0 | G9: 0 | H9: 0 | I9: 0 | J9: 0 | K9: 6350 | L9: =SUM(C9:K9) -> 6350
B10: Playo | C10: 0 | D10: 0 | E10: 0 | F10: 0 | G10: 0 | H10: 0 | I10: =SUM(I11:I15) -> 0 | J10: 0 | K10: 25760 | L10: =SUM(C10:K10) -> 25760
B11: District | C11: 0 | D11: 0 | E11: 0 | F11: 0 | G11: 0 | H11: 0 | I11: 0 | J11: 0 | K11: 0 | L11: =SUM(C11:K11) -> 0
B12: Khelomore | C12: 0 | D12: 0 | E12: 0 | F12: 0 | G12: 0 | H12: 0 | I12: 0 | J12: 161 | K12: 7015 | L12: =SUM(C12:K12) -> 7176
B13: Zplys | C13: 0 | D13: 0 | E13: 0 | F13: 0 | G13: 0 | H13: 0 | I13: 0 | J13: 0 | K13: 0 | L13: =SUM(C13:K13) -> 0
B14: Community | C14: =SUM(C16,C15, C17,C18) -> 0 | D14: =SUM(D16,D15, D17,D18) -> 0 | E14: =SUM(E16,E15, E17,E18) -> 0 | F14: =SUM(F16,F15, F17,F18) -> 0 | G14: =SUM(G16,G15, G17,G18) -> 0 | H14: =SUM(H16,H15, H17,H18) -> 0 | I14: 0 | J14: =SUM(J16,J15, J17,J18) -> 0 | K14: =SUM(K16,K15, K17,K18) -> 0 | L14: =SUM(C14:K14) -> 0 | M14: =L14/1.18 -> 0
B15: Courtly (Organized by RallyGully) | C15: 0 | D15: 0 | E15: 0 | F15: 0 | G15: 0 | H15: 0 | I15: 0 | J15: 0 | K15: 0 | L15: =SUM(C15:K15) -> 0
B16: Sportomic (Organized by RallyGully) | C16: 0 | D16: 0 | E16: 0 | F16: 0 | G16: 0 | H16: 0 | I16: =SUM(I18,I17, I19,I20) -> 0 | J16: 0 | K16: 0 | L16: =SUM(C16:K16) -> 0
B17: Rallygully Community games | C17: 0 | D17: 0 | E17: 0 | F17: 0 | G17: 0 | H17: 0 | I17: 0 | J17: 0 | K17: 0 | L17: =SUM(C17:K17) -> 0
B18: Misfits Community | C18: 0 | D18: 0 | E18: 0 | F18: 0 | G18: 0 | H18: 0 | I18: 0 | J18: 0 | K18: 0 | L18: =SUM(C18:K18) -> 0
B19: Memberships | C19: 0 | D19: 0 | E19: 0 | F19: 0 | G19: 0 | H19: 0 | I19: 0 | J19: 0 | K19: 0 | L19: =SUM(C19:K19) -> 0 | M19: =L19/1.18 -> 0
B20: Coaching | C20: 0 | D20: 0 | E20: 0 | F20: 0 | G20: 0 | H20: 0 | I20: 0 | J20: 0 | K20: 0 | L20: =SUM(C20:K20) -> 0 | M20: =L20/1.18 -> 0
B21: Corporate Events | C21: 0 | D21: 0 | E21: 0 | F21: 0 | G21: 0 | H21: 0 | I21: 0 | J21: 0 | K21: 0 | L21: =SUM(C21:K21) -> 0 | M21: =L21/1.18 -> 0
B22: Brand Activation | C22: 0 | D22: 0 | E22: 0 | F22: 0 | G22: 0 | H22: 0 | I22: 0 | J22: 0 | K22: 0 | L22: =SUM(C22:K22) -> 0 | M22: =L22/1.18 -> 0
B23: Other Income | C23: 0 | D23: 0 | E23: 0 | F23: 0 | G23: 0 | H23: 0 | I23: 0 | J23: 59000 | K23: 118000 | L23: =SUM(C23:K23) -> 177000 | M23: =L23/1.18 -> 150000
B24: Total Gross Revenue | C24: =sum(C3,C8,C14,C19,C20,C21,C22,C23) -> 0 | D24: =sum(D3,D8,D14,D19,D20,D21,D22,D23) -> 0 | E24: =sum(E3,E8,E14,E19,E20,E21,E22,E23) -> 0 | F24: =sum(F3,F8,F14,F19,F20,F21,F22,F23) -> 0 | G24: =sum(G3,G8,G14,G19,G20,G21,G22,G23) -> 0 | H24: =sum(H3,H8,H14,H19,H20,H21,H22,H23) -> 0 | I24: =sum(I3,I8,I14,I19,I20,I21,I22,I23) -> 0 | J24: =sum(J3,J8,J14,J19,J20,J21,J22,J23) -> 59161 | ... L24: =sum(L3,L8,L14,L19,L20,L21,L22,L23) -> 245921 | M24: =L24/1.18 -> 208407.63
B25: Total Net Revenue (Post Commissions) | C25: 0 | D25: 0 | E25: 0 | F25: 0 | G25: 0 | H25: 0 | I25: 0 | J25: 59152.95 | K25: 183544.37 | L25: =SUM(C25:K25) -> 242697.32
B26: Total Revenue post GST | C26: 0 | D26: 0 | E26: 0 | F26: 0 | G26: 0 | H26: 0 | I26: =I25/1.18 -> 0 | J26: =J25/1.18 -> 50129.619 | K26: =K25/1.18 -> 155546.08 | L26: =SUM(C26:K26) -> 205675.69
B27: Note
B28: Venue Operational from 24th Feb

Sheet Commons, Noida
B1: Venue Sheet | K1: Link
B2: Metrics | C2: July | D2: August | E2: September | F2: October | G2: November | H2: December | I2: January | J2: February | K2: March | L2: TOTAL
B3: Offline | C3: =SUM(C4,C5,C6,C7) -> 0 | D3: =SUM(D4,D5,D6,D7) -> 0 | E3: =SUM(E4,E5,E6,E7) -> 0 | F3: =SUM(F4,F5,F6,F7) -> 0 | G3: =SUM(G4,G5,G6,G7) -> 0 | H3: =SUM(H4,H5,H6,H7) -> 0 | I3: 0 | J3: 0 | K3: =SUM(K4,K5,K6,K7) -> 2650 | L3: =SUM(C3:K3) -> 2650 | M3: =L3/1.18 -> 2245.7627
B4: Rentals | C4: 0 | D4: 0 | E4: 0 | F4: 0 | G4: 0 | H4: 0 | I4: 0 | J4: 0 | K4: 600 | L4: =SUM(C4:K4) -> 600
B5: F&B | C5: 0 | D5: 0 | E5: 0 | F5: 0 | G5: 0 | H5: 0 | I5: =SUM(I6,I7,I8,I9) -> 0 | J5: =SUM(J6,J7,J8,J9) -> 0 | K5: 0 | L5: =SUM(C5:K5) -> 0
B6: Product Sales | C6: 0 | D6: 0 | E6: 0 | F6: 0 | G6: 0 | H6: 0 | I6: 0 | J6: 0 | K6: 0 | L6: =SUM(C6:K6) -> 0
B7: Bookings | C7: 0 | D7: 0 | E7: 0 | F7: 0 | G7: 0 | H7: 0 | I7: 0 | J7: 0 | K7: 2050 | L7: =SUM(C7:K7) -> 2050
B8: Online: Third Party Platform | C8: =SUM(C9:C13) -> 0 | D8: =SUM(D9:D13) -> 0 | E8: =SUM(E9:E13) -> 0 | F8: =SUM(F9:F13) -> 0 | G8: =SUM(G9:G13) -> 0 | H8: =SUM(H9:H13) -> 0 | I8: 0 | J8: 0 | K8: =SUM(K9:K13) -> 5740 | L8: =SUM(C8:K8) -> 5740 | M8: =L8/1.18 -> 4864.4068
B9: Hudle | C9: 0 | D9: 0 | E9: 0 | F9: 0 | G9: 0 | H9: 0 | I9: 0 | J9: 0 | K9: 5740 | L9: =SUM(C9:K9) -> 5740
B10: Playo | C10: 0 | D10: 0 | E10: 0 | F10: 0 | G10: 0 | H10: 0 | I10: =SUM(I11:I15) -> 0 | J10: =SUM(J11:J15) -> 0 | K10: 0 | L10: =SUM(C10:K10) -> 0
B11: District | C11: 0 | D11: 0 | E11: 0 | F11: 0 | G11: 0 | H11: 0 | I11: 0 | J11: 0 | K11: 0 | L11: =SUM(C11:K11) -> 0
B12: Khelomore | C12: 0 | D12: 0 | E12: 0 | F12: 0 | G12: 0 | H12: 0 | I12: 0 | J12: 0 | K12: 0 | L12: =SUM(C12:K12) -> 0
B13: Zplys | C13: 0 | D13: 0 | E13: 0 | F13: 0 | G13: 0 | H13: 0 | I13: 0 | J13: 0 | K13: 0 | L13: =SUM(C13:K13) -> 0
B14: Community | C14: =SUM(C16,C15, C17,C18) -> 0 | D14: =SUM(D16,D15, D17,D18) -> 0 | E14: =SUM(E16,E15, E17,E18) -> 0 | F14: =SUM(F16,F15, F17,F18) -> 0 | G14: =SUM(G16,G15, G17,G18) -> 0 | H14: =SUM(H16,H15, H17,H18) -> 0 | I14: 0 | J14: 0 | K14: =SUM(K16,K15, K17,K18) -> 110270 | L14: =SUM(C14:K14) -> 110270 | M14: =L14/1.18 -> 93449.153
B15: Courtly (Organized by RallyGully) | C15: 0 | D15: 0 | E15: 0 | F15: 0 | G15: 0 | H15: 0 | I15: 0 | J15: 0 | K15: 52820 | L15: =SUM(C15:K15) -> 52820
B16: Sportomic (Organized by RallyGully) | C16: 0 | D16: 0 | E16: 0 | F16: 0 | G16: 0 | H16: 0 | I16: =SUM(I18,I17, I19,I20) -> 0 | J16: =SUM(J18,J17, J19,J20) -> 0 | K16: 0 | L16: =SUM(C16:K16) -> 0
B17: Rallygully Community games | C17: 0 | D17: 0 | E17: 0 | F17: 0 | G17: 0 | H17: 0 | I17: 0 | J17: 0 | K17: 57450 | L17: =SUM(C17:K17) -> 57450
B18: Misfits Community | C18: 0 | D18: 0 | E18: 0 | F18: 0 | G18: 0 | H18: 0 | I18: 0 | J18: 0 | K18: 0 | L18: =SUM(C18:K18) -> 0
B19: Memberships | C19: 0 | D19: 0 | E19: 0 | F19: 0 | G19: 0 | H19: 0 | I19: 0 | J19: 0 | K19: 0 | L19: =SUM(C19:K19) -> 0 | M19: =L19/1.18 -> 0
B20: Coaching | C20: 0 | D20: 0 | E20: 0 | F20: 0 | G20: 0 | H20: 0 | I20: 0 | J20: 0 | K20: 0 | L20: =SUM(C20:K20) -> 0 | M20: =L20/1.18 -> 0
B21: Corporate Events | C21: 0 | D21: 0 | E21: 0 | F21: 0 | G21: 0 | H21: 0 | I21: 0 | J21: 0 | K21: 0 | L21: =SUM(C21:K21) -> 0 | M21: =L21/1.18 -> 0
B22: Brand Activation | C22: 0 | D22: 0 | E22: 0 | F22: 0 | G22: 0 | H22: 0 | I22: 0 | J22: 0 | K22: 18000 | L22: =SUM(C22:K22) -> 18000 | M22: =L22/1.18 -> 15254.237
B23: Other Income | C23: 0 | D23: 0 | E23: 0 | F23: 0 | G23: 0 | H23: 0 | I23: 0 | J23: 0 | K23: 0 | L23: =SUM(C23:K23) -> 0 | M23: =L23/1.18 -> 0
B24: Total Gross Revenue | C24: =sum(C3,C8,C14,C19,C20,C21,C22,C23) -> 0 | D24: =sum(D3,D8,D14,D19,D20,D21,D22,D23) -> 0 | E24: =sum(E3,E8,E14,E19,E20,E21,E22,E23) -> 0 | F24: =sum(F3,F8,F14,F19,F20,F21,F22,F23) -> 0 | G24: =sum(G3,G8,G14,G19,G20,G21,G22,G23) -> 0 | H24: =sum(H3,H8,H14,H19,H20,H21,H22,H23) -> 0 | I24: =sum(I3,I8,I14,I19,I20,I21,I22,I23) -> 0 | J24: =sum(J3,J8,J14,J19,J20,J21,J22,J23) -> 0 | ... L24: =sum(L3,L8,L14,L19,L20,L21,L22,L23) -> 136660 | M24: =L24/1.18 -> 115813.56
B25: Total Net Revenue (Post Commissions) | C25: 0 | D25: 0 | E25: 0 | F25: 0 | G25: 0 | H25: 0 | I25: 0 | J25: 0 | K25: 134329.16 | L25: =SUM(C25:K25) -> 134329.16
B26: Total Revenue post GST | C26: 0 | D26: 0 | E26: 0 | F26: 0 | G26: 0 | H26: 0 | I26: =I25/1.18 -> 0 | J26: =J25/1.18 -> 0 | K26: =K25/1.18 -> 113838.27 | L26: =SUM(C26:K26) -> 113838.27
B27: Note
B28: Venue Operational from 28th March

Sheet Jan Target
A1: January Projections
A2: Sno. | B2: Venues | C2: No. of Courts | D2: Pay & Play | E2: Coaching | F2: Community | G2: B2B Events | H2: Brand/Corporate Partnerships | I2: Total | K2: Kids | M2: Adults
A3: 1 | B3: RallyGully I Sector 10 Dwarka | C3: 4 | D3: 250000 | E3: =12*5000+8000*12 -> 156000 | F3: 75000 | H3: =5000*C3 -> 20000 | I3: =SUM(D3:H3) -> 501000 | K3: 12 | L3: 1 | M3: 12 | N3: 1
A4: 2 | B4: RallyGully I Sector 83 Gurgaon | C4: 4 | D4: 200000 | E4: =5000*6 -> 30000 | F4: 45000 | G4: =30000*4 -> 120000 | H4: =5000*C4 -> 20000 | I4: =SUM(D4:H4) -> 415000 | K4: 6 | M4: 0
A5: 3 | B5: RallyGully I East of Kailash | C5: 3 | D5: 250000 | E5: =12*5000+8000*12 -> 156000 | F5: 90000 | G5: =30000*2 -> 60000 | H5: =5000*C5 -> 15000 | I5: =SUM(D5:H5) -> 571000 | K5: 12 | L5: 6 | M5: 12 | N5: 5
A6: 4 | B6: RallyGully I Sector 19 Dwarka | C6: 3 | D6: 125000 | E6: =12*5000+8000*6 -> 108000 | F6: 45000 | H6: =5000*C6 -> 15000 | I6: =SUM(D6:H6) -> 293000 | K6: 12 | M6: 6
A7: 5 | B7: RallyGully | LCR Pune | C7: 4 | D7: 200000 | E7: =7000*6 -> 42000 | F7: 45000 | G7: =30000*2 -> 60000 | H7: =5000*C7 -> 20000 | I7: =SUM(D7:H7) -> 367000 | K7: 0 | M7: 6
A8: 6 | B8: RallyGully | DPSG | C8: 4 | D8: 150000 | E8: =5000*12+8000*6 -> 108000 | F8: 30000 | H8: =5000*C8 -> 20000 | I8: =SUM(D8:H8) -> 308000 | K8: 12 | M8: 6
A9: 7 | B9: RallyGully | Gandhipath | C9: 3 | D9: 150000 | E9: =4000*6 -> 24000 | F9: 30000 | H9: =5000*C9 -> 15000 | I9: =SUM(D9:H9) -> 219000 | K9: 6 | M9: 0
A10: 8 | B10: RallyGully | Pancheel Park | C10: 5 | D10: 200000 | E10: =5000*12+8000*6 -> 108000 | F10: 60000 | G10: =30000*2 -> 60000 | H10: =5000*C10 -> 25000 | I10: =SUM(D10:H10) -> 453000 | K10: 12 | M10: 6
B11: Total | C11: =SUM(C3:C10) -> 30 | D11: =SUM(D3:D10) -> 1525000 | E11: =SUM(E3:E10) -> 732000 | F11: =SUM(F3:F10) -> 420000 | G11: =SUM(G3:G10) -> 300000 | H11: =SUM(H3:H10) -> 150000 | I11: =SUM(D11:H11) -> 3127000 | K11: =SUM(K3:K10) -> 72 | L11: =SUM(L3:L10) -> 7 | M11: =SUM(M3:M10) -> 48 | N11: =SUM(N3:N10) -> 6
A12: 9 | B12: RallyGully | Capital Cyberscape | C12: 4
A13: 10 | B13: RallyGully | Baner Pune | C13: 5
C14: =SUM(C11:C13) -> 39

Sheet Copy of Central Dashboard
A1: Sno. | B1: Venues | C1: July | D1: August | E1: September | F1: October | G1: November | H1: December | I1: January | J1: February | K1: March
A2: 1 | B2: RallyGully I Sector 10 Dwarka | C2: ='RallyGully I Sector 10 Dwarka'!C24 -> 103615 | D2: ='RallyGully I Sector 10 Dwarka'!D24 -> 298839 | E2: ='RallyGully I Sector 10 Dwarka'!E24 -> 245054 | F2: ='RallyGully I Sector 10 Dwarka'!F24 -> 200720 | G2: ='RallyGully I Sector 10 Dwarka'!G24 -> 168129 | H2: ='RallyGully I Sector 10 Dwarka'!H24 -> 206326 | I2: ='RallyGully I Sector 10 Dwarka'!I24 -> 301217 | J2: ='RallyGully I Sector 10 Dwarka'!J24 -> 263730 | K2: ='RallyGully I Sector 10 Dwarka'!K24 -> 251120
A3: 2 | B3: RallyGully I Sector 83 Gurgaon | C3: 0 | D3: ='RallyGully I Sector 83 Gurgaon'!D24 -> 37420 | E3: ='RallyGully I Sector 83 Gurgaon'!E24 -> 154961 | F3: 90075 | G3: ='RallyGully I Sector 83 Gurgaon'!G24 -> 151276 | H3: ='RallyGully I Sector 83 Gurgaon'!H24 -> 175700 | I3: ='RallyGully I Sector 83 Gurgaon'!I24 -> 169521 | J3: ='RallyGully I Sector 83 Gurgaon'!J24 -> 210880 | K3: ='RallyGully I Sector 83 Gurgaon'!K24 -> 226770
A4: 3 | B4: RallyGully I East of Kailash | C4: 0 | D4: 0 | E4: ='RallyGully I East of Kailash'!E24 -> 78858.8 | F4: ='RallyGully I East of Kailash'!F24 -> 183432.6 | G4: ='RallyGully I East of Kailash'!G24 -> 144284 | H4: ='RallyGully I East of Kailash'!H24 -> 123338 | I4: ='RallyGully I East of Kailash'!I24 -> 279567 | J4: ='RallyGully I East of Kailash'!J24 -> 365154 | K4: ='RallyGully I East of Kailash'!K24 -> 281064
A5: 4 | B5: RallyGully I Sector 19 Dwarka | C5: 0 | D5: 0 | E5: 0 | F5: ='RallyGully I Sector 19 Dwarka'!F24 -> 71245 | G5: ='RallyGully I Sector 19 Dwarka'!$G$24 -> 78029 | H5: ='RallyGully I Sector 19 Dwarka'!H24 -> 50925 | I5: ='RallyGully I Sector 19 Dwarka'!I24 -> 125214 | J5: ='RallyGully I Sector 19 Dwarka'!J24 -> 86460 | K5: ='RallyGully I Sector 19 Dwarka'!K24 -> 104875
A6: 5 | B6: RallyGully | LCR Pune | C6: 0 | D6: 0 | E6: 0 | F6: 0 | G6: ='RallyGully | LCR Pune'!G24 -> 40125 | H6: ='RallyGully | LCR Pune'!H24 -> 171603 | I6: ='RallyGully | LCR Pune'!I24 -> 399500 | J6: ='RallyGully | LCR Pune'!J24 -> 450865 | K6: ='RallyGully | LCR Pune'!K24 -> 415235
A7: 6 | B7: RallyGully | DPSG | C7: 0 | D7: 0 | E7: 0 | F7: 0 | G7: 0 | H7: ='RallyGully | DPSG'!H24 -> 21637 | I7: ='RallyGully | DPSG'!I24 -> 49820 | J7: ='RallyGully | DPSG'!J24 -> 113460 | K7: ='RallyGully | DPSG'!K24 -> 179380
A8: 7 | B8: RallyGully I Gandhipath | C8: 0 | D8: 0 | E8: 0 | F8: 0 | G8: 0 | H8: ='RallyGully | Gandipath'!H24 -> 4900 | I8: ='RallyGully | Gandipath'!I24 -> 98125 | J8: ='RallyGully | Gandipath'!J24 -> 74878 | K8: ='RallyGully | Gandipath'!K24 -> 139155
A9: 8 | B9: RallyGully I Panchsheel | C9: 0 | D9: 0 | E9: 0 | F9: 0 | G9: 0 | H9: 0 | I9: ='RallyGully | Panchsheel'!I24 -> 78588 | J9: ='RallyGully | Panchsheel'!J24 -> 88970 | K9: ='RallyGully | Panchsheel'!K24 -> 141013
A10: 9 | B10: Powerplay Park | C10: 0 | D10: 0 | E10: 0 | F10: 0 | G10: 0 | H10: 0 | I10: 0 | J10: ='Powerplay Park, Pune'!J24 -> 59161 | K10: ='Powerplay Park, Pune'!K24 -> 186760
A11: 10 | B11: Commons | RallyGully x Delhi Padel Collective | C11: 0 | D11: 0 | E11: 0 | F11: 0 | G11: 0 | H11: 0 | I11: 0 | J11: 0 | K11: ='Commons, Noida'!K24 -> 136660
B12: Total Gross Revenue | C12: =SUM(C2:C9) -> 103615 | D12: =SUM(D2:D9) -> 336259 | E12: =SUM(E2:E9) -> 478873.8 | F12: =SUM(F2:F9) -> 545472.6 | G12: =SUM(G2:G9) -> 581843 | H12: =SUM(H2:H11) -> 754429 | I12: =SUM(I2:I11) -> 1501552 | J12: =SUM(J2:J11) -> 1713558 | K12: =SUM(K2:K11) -> 2062032
B14: Verticle Vise | C14: July | D14: August | E14: September | F14: October | G14: November | H14: December | I14: January | J14: February | K14: March
A15: 1 | B15: Offline | C15: =SUM('RallyGully I Sector 10 Dwarka'!C3+'RallyGully I Sector 83 Gurgaon'!C3+'RallyGully I East of Kailash'!C3+'RallyGully I Sector 19 Dwarka'!C3+'RallyGully | LCR Pune'!C3+'RallyGully | DPSG'!C3+'RallyGully | Gandipath'!C3+'RallyGully | Panchsheel'!C3) -> 4835 | D15: =SUM('RallyGully I Sector 10 Dwarka'!D3+'RallyGully I Sector 83 Gurgaon'!D3+'RallyGully I East of Kailash'!D3+'RallyGully I Sector 19 Dwarka'!D3+'RallyGully | LCR Pune'!D3+'RallyGully | DPSG'!D3+'RallyGully | Gandipath'!D3+'RallyGully | Panchsheel'!D3) -> 51040 | E15: =SUM('RallyGully I Sector 10 Dwarka'!E3+'RallyGully I Sector 83 Gurgaon'!E3+'RallyGully I East of Kailash'!E3+'RallyGully I Sector 19 Dwarka'!E3+'RallyGully | LCR Pune'!E3+'RallyGully | DPSG'!E3+'RallyGully | Gandipath'!E3+'RallyGully | Panchsheel'!E3) -> 139520 | F15: =SUM('RallyGully I Sector 10 Dwarka'!F3+'RallyGully I Sector 83 Gurgaon'!F3+'RallyGully I East of Kailash'!F3+'RallyGully I Sector 19 Dwarka'!F3+'RallyGully | LCR Pune'!F3+'RallyGully | DPSG'!F3+'RallyGully | Gandipath'!F3+'RallyGully | Panchsheel'!F3) -> 73240 | G15: =SUM('RallyGully I Sector 10 Dwarka'!G3+'RallyGully I Sector 83 Gurgaon'!G3+'RallyGully I East of Kailash'!G3+'RallyGully I Sector 19 Dwarka'!G3+'RallyGully | LCR Pune'!G3+'RallyGully | DPSG'!G3+'RallyGully | Gandipath'!G3+'RallyGully | Panchsheel'!G3) -> 175494 | H15: =SUM('RallyGully I Sector 10 Dwarka'!H3+'RallyGully I Sector 83 Gurgaon'!H3+'RallyGully I East of Kailash'!H3+'RallyGully I Sector 19 Dwarka'!H3+'RallyGully | LCR Pune'!H3+'RallyGully | DPSG'!H3+'RallyGully | Gandipath'!H3+'RallyGully | Panchsheel'!H3) -> 269512 | I15: =SUM('RallyGully I Sector 10 Dwarka'!I3+'RallyGully I Sector 83 Gurgaon'!I3+'RallyGully I East of Kailash'!I3+'RallyGully I Sector 19 Dwarka'!I3+'RallyGully | LCR Pune'!I3+'RallyGully | DPSG'!I3+'RallyGully | Gandipath'!I3+'RallyGully | Panchsheel'!I3) -> 481369 | J15: =SUM('RallyGully I Sector 10 Dwarka'!J3+'RallyGully I Sector 83 Gurgaon'!J3+'RallyGully I East of Kailash'!J3+'RallyGully I Sector 19 Dwarka'!J3+'RallyGully | LCR Pune'!J3+'RallyGully | DPSG'!J3+'RallyGully | Gandipath'!J3+'RallyGully | Panchsheel'!J3+'Powerplay Park, Pune'!J3+'Commons, Noida'!J3) -> 515675 | K15: =SUM('RallyGully I Sector 10 Dwarka'!K3+'RallyGully I Sector 83 Gurgaon'!K3+'RallyGully I East of Kailash'!K3+'RallyGully I Sector 19 Dwarka'!K3+'RallyGully | LCR Pune'!K3+'RallyGully | DPSG'!K3+'RallyGully | Gandipath'!K3+'RallyGully | Panchsheel'!K3+'Powerplay Park, Pune'!K3+'Commons, Noida'!K3) -> 528815
A16: 1.1 | B16: Rentals | C16: =SUM('RallyGully I Sector 10 Dwarka'!C4+'RallyGully I Sector 83 Gurgaon'!C4+'RallyGully I East of Kailash'!C4+'RallyGully I Sector 19 Dwarka'!C4+'RallyGully | LCR Pune'!C4+'RallyGully | DPSG'!C4+'RallyGully | Gandipath'!C4+'RallyGully | Panchsheel'!C4) -> 4475 | D16: =SUM('RallyGully I Sector 10 Dwarka'!D4+'RallyGully I Sector 83 Gurgaon'!D4+'RallyGully I East of Kailash'!D4+'RallyGully I Sector 19 Dwarka'!D4+'RallyGully | LCR Pune'!D4+'RallyGully | DPSG'!D4+'RallyGully | Gandipath'!D4+'RallyGully | Panchsheel'!D4) -> 15580 | E16: =SUM('RallyGully I Sector 10 Dwarka'!E4+'RallyGully I Sector 83 Gurgaon'!E4+'RallyGully I East of Kailash'!E4+'RallyGully I Sector 19 Dwarka'!E4+'RallyGully | LCR Pune'!E4+'RallyGully | DPSG'!E4+'RallyGully | Gandipath'!E4+'RallyGully | Panchsheel'!E4) -> 22280 | F16: =SUM('RallyGully I Sector 10 Dwarka'!F4+'RallyGully I Sector 83 Gurgaon'!F4+'RallyGully I East of Kailash'!F4+'RallyGully I Sector 19 Dwarka'!F4+'RallyGully | LCR Pune'!F4+'RallyGully | DPSG'!F4+'RallyGully | Gandipath'!F4+'RallyGully | Panchsheel'!F4) -> 24840 | G16: =SUM('RallyGully I Sector 10 Dwarka'!G4+'RallyGully I Sector 83 Gurgaon'!G4+'RallyGully I East of Kailash'!G4+'RallyGully I Sector 19 Dwarka'!G4+'RallyGully | LCR Pune'!G4+'RallyGully | DPSG'!G4+'RallyGully | Gandipath'!G4+'RallyGully | Panchsheel'!G4) -> 27820 | H16: =SUM('RallyGully I Sector 10 Dwarka'!H4+'RallyGully I Sector 83 Gurgaon'!H4+'RallyGully I East of Kailash'!H4+'RallyGully I Sector 19 Dwarka'!H4+'RallyGully | LCR Pune'!H4+'RallyGully | DPSG'!H4+'RallyGully | Gandipath'!H4+'RallyGully | Panchsheel'!H4) -> 60775 | I16: =SUM('RallyGully I Sector 10 Dwarka'!I4+'RallyGully I Sector 83 Gurgaon'!I4+'RallyGully I East of Kailash'!I4+'RallyGully I Sector 19 Dwarka'!I4+'RallyGully | LCR Pune'!I4+'RallyGully | DPSG'!I4+'RallyGully | Gandipath'!I4+'RallyGully | Panchsheel'!I4) -> 91339 | J16: =SUM('RallyGully I Sector 10 Dwarka'!J4+'RallyGully I Sector 83 Gurgaon'!J4+'RallyGully I East of Kailash'!J4+'RallyGully I Sector 19 Dwarka'!J4+'RallyGully | LCR Pune'!J4+'RallyGully | DPSG'!J4+'RallyGully | Gandipath'!J4+'RallyGully | Panchsheel'!J4) -> 94325 | K16: =SUM('RallyGully I Sector 10 Dwarka'!K4+'RallyGully I Sector 83 Gurgaon'!K4+'RallyGully I East of Kailash'!K4+'RallyGully I Sector 19 Dwarka'!K4+'RallyGully | LCR Pune'!K4+'RallyGully | DPSG'!K4+'RallyGully | Gandipath'!K4+'RallyGully | Panchsheel'!K4) -> 82230
A17: 1.2 | B17: F&B | C17: =SUM('RallyGully I Sector 10 Dwarka'!C5+'RallyGully I Sector 83 Gurgaon'!C5+'RallyGully I East of Kailash'!C5+'RallyGully I Sector 19 Dwarka'!C5+'RallyGully | LCR Pune'!C5+'RallyGully | DPSG'!C5+'RallyGully | Gandipath'!C5+'RallyGully | Panchsheel'!C5) -> 360 | D17: =SUM('RallyGully I Sector 10 Dwarka'!D5+'RallyGully I Sector 83 Gurgaon'!D5+'RallyGully I East of Kailash'!D5+'RallyGully I Sector 19 Dwarka'!D5+'RallyGully | LCR Pune'!D5+'RallyGully | DPSG'!D5+'RallyGully | Gandipath'!D5+'RallyGully | Panchsheel'!D5) -> 1920 | E17: =SUM('RallyGully I Sector 10 Dwarka'!E5+'RallyGully I Sector 83 Gurgaon'!E5+'RallyGully I East of Kailash'!E5+'RallyGully I Sector 19 Dwarka'!E5+'RallyGully | LCR Pune'!E5+'RallyGully | DPSG'!E5+'RallyGully | Gandipath'!E5+'RallyGully | Panchsheel'!E5) -> 4400 | F17: =SUM('RallyGully I Sector 10 Dwarka'!F5+'RallyGully I Sector 83 Gurgaon'!F5+'RallyGully I East of Kailash'!F5+'RallyGully I Sector 19 Dwarka'!F5+'RallyGully | LCR Pune'!F5+'RallyGully | DPSG'!F5+'RallyGully | Gandipath'!F5+'RallyGully | Panchsheel'!F5) -> 2490 | G17: =SUM('RallyGully I Sector 10 Dwarka'!G5+'RallyGully I Sector 83 Gurgaon'!G5+'RallyGully I East of Kailash'!G5+'RallyGully I Sector 19 Dwarka'!G5+'RallyGully | LCR Pune'!G5+'RallyGully | DPSG'!G5+'RallyGully | Gandipath'!G5+'RallyGully | Panchsheel'!G5) -> 1890 | H17: =SUM('RallyGully I Sector 10 Dwarka'!H5+'RallyGully I Sector 83 Gurgaon'!H5+'RallyGully I East of Kailash'!H5+'RallyGully I Sector 19 Dwarka'!H5+'RallyGully | LCR Pune'!H5+'RallyGully | DPSG'!H5+'RallyGully | Gandipath'!H5+'RallyGully | Panchsheel'!H5) -> 5260 | I17: =SUM('RallyGully I Sector 10 Dwarka'!I5+'RallyGully I Sector 83 Gurgaon'!I5+'RallyGully I East of Kailash'!I5+'RallyGully I Sector 19 Dwarka'!I5+'RallyGully | LCR Pune'!I5+'RallyGully | DPSG'!I5+'RallyGully | Gandipath'!I5+'RallyGully | Panchsheel'!I5) -> 4055 | J17: =SUM('RallyGully I Sector 10 Dwarka'!J5+'RallyGully I Sector 83 Gurgaon'!J5+'RallyGully I East of Kailash'!J5+'RallyGully I Sector 19 Dwarka'!J5+'RallyGully | LCR Pune'!J5+'RallyGully | DPSG'!J5+'RallyGully | Gandipath'!J5+'RallyGully | Panchsheel'!J5) -> 5445 | K17: =SUM('RallyGully I Sector 10 Dwarka'!K5+'RallyGully I Sector 83 Gurgaon'!K5+'RallyGully I East of Kailash'!K5+'RallyGully I Sector 19 Dwarka'!K5+'RallyGully | LCR Pune'!K5+'RallyGully | DPSG'!K5+'RallyGully | Gandipath'!K5+'RallyGully | Panchsheel'!K5) -> 3825
A18: 1.3 | B18: Product Sales | C18: =SUM('RallyGully I Sector 10 Dwarka'!C6+'RallyGully I Sector 83 Gurgaon'!C6+'RallyGully I East of Kailash'!C6+'RallyGully I Sector 19 Dwarka'!C6+'RallyGully | LCR Pune'!C6+'RallyGully | DPSG'!C6+'RallyGully | Gandipath'!C6+'RallyGully | Panchsheel'!C6) -> 0 | D18: =SUM('RallyGully I Sector 10 Dwarka'!D6+'RallyGully I Sector 83 Gurgaon'!D6+'RallyGully I East of Kailash'!D6+'RallyGully I Sector 19 Dwarka'!D6+'RallyGully | LCR Pune'!D6+'RallyGully | DPSG'!D6+'RallyGully | Gandipath'!D6+'RallyGully | Panchsheel'!D6) -> 0 | E18: =SUM('RallyGully I Sector 10 Dwarka'!E6+'RallyGully I Sector 83 Gurgaon'!E6+'RallyGully I East of Kailash'!E6+'RallyGully I Sector 19 Dwarka'!E6+'RallyGully | LCR Pune'!E6+'RallyGully | DPSG'!E6+'RallyGully | Gandipath'!E6+'RallyGully | Panchsheel'!E6) -> 12050 | F18: =SUM('RallyGully I Sector 10 Dwarka'!F6+'RallyGully I Sector 83 Gurgaon'!F6+'RallyGully I East of Kailash'!F6+'RallyGully I Sector 19 Dwarka'!F6+'RallyGully | LCR Pune'!F6+'RallyGully | DPSG'!F6+'RallyGully | Gandipath'!F6+'RallyGully | Panchsheel'!F6) -> 0 | G18: =SUM('RallyGully I Sector 10 Dwarka'!G6+'RallyGully I Sector 83 Gurgaon'!G6+'RallyGully I East of Kailash'!G6+'RallyGully I Sector 19 Dwarka'!G6+'RallyGully | LCR Pune'!G6+'RallyGully | DPSG'!G6+'RallyGully | Gandipath'!G6+'RallyGully | Panchsheel'!G6) -> 0 | H18: =SUM('RallyGully I Sector 10 Dwarka'!H6+'RallyGully I Sector 83 Gurgaon'!H6+'RallyGully I East of Kailash'!H6+'RallyGully I Sector 19 Dwarka'!H6+'RallyGully | LCR Pune'!H6+'RallyGully | DPSG'!H6+'RallyGully | Gandipath'!H6+'RallyGully | Panchsheel'!H6) -> 0 | I18: =SUM('RallyGully I Sector 10 Dwarka'!I6+'RallyGully I Sector 83 Gurgaon'!I6+'RallyGully I East of Kailash'!I6+'RallyGully I Sector 19 Dwarka'!I6+'RallyGully | LCR Pune'!I6+'RallyGully | DPSG'!I6+'RallyGully | Gandipath'!I6+'RallyGully | Panchsheel'!I6) -> 18000 | J18: =SUM('RallyGully I Sector 10 Dwarka'!J6+'RallyGully I Sector 83 Gurgaon'!J6+'RallyGully I East of Kailash'!J6+'RallyGully I Sector 19 Dwarka'!J6+'RallyGully | LCR Pune'!J6+'RallyGully | DPSG'!J6+'RallyGully | Gandipath'!J6+'RallyGully | Panchsheel'!J6) -> 0 | K18: =SUM('RallyGully I Sector 10 Dwarka'!K6+'RallyGully I Sector 83 Gurgaon'!K6+'RallyGully I East of Kailash'!K6+'RallyGully I Sector 19 Dwarka'!K6+'RallyGully | LCR Pune'!K6+'RallyGully | DPSG'!K6+'RallyGully | Gandipath'!K6+'RallyGully | Panchsheel'!K6) -> 0
A19: 1.4 | B19: Bookings | C19: =SUM('RallyGully I Sector 10 Dwarka'!C7+'RallyGully I Sector 83 Gurgaon'!C7+'RallyGully I East of Kailash'!C7+'RallyGully I Sector 19 Dwarka'!C7+'RallyGully | LCR Pune'!C7+'RallyGully | DPSG'!C7+'RallyGully | Gandipath'!C7+'RallyGully | Panchsheel'!C7) -> 0 | D19: =SUM('RallyGully I Sector 10 Dwarka'!D7+'RallyGully I Sector 83 Gurgaon'!D7+'RallyGully I East of Kailash'!D7+'RallyGully I Sector 19 Dwarka'!D7+'RallyGully | LCR Pune'!D7+'RallyGully | DPSG'!D7+'RallyGully | Gandipath'!D7+'RallyGully | Panchsheel'!D7) -> 33540 | E19: =SUM('RallyGully I Sector 10 Dwarka'!E7+'RallyGully I Sector 83 Gurgaon'!E7+'RallyGully I East of Kailash'!E7+'RallyGully I Sector 19 Dwarka'!E7+'RallyGully | LCR Pune'!E7+'RallyGully | DPSG'!E7+'RallyGully | Gandipath'!E7+'RallyGully | Panchsheel'!E7) -> 100790 | F19: =SUM('RallyGully I Sector 10 Dwarka'!F7+'RallyGully I Sector 83 Gurgaon'!F7+'RallyGully I East of Kailash'!F7+'RallyGully I Sector 19 Dwarka'!F7+'RallyGully | LCR Pune'!F7+'RallyGully | DPSG'!F7+'RallyGully | Gandipath'!F7+'RallyGully | Panchsheel'!F7) -> 40710 | G19: =SUM('RallyGully I Sector 10 Dwarka'!G7+'RallyGully I Sector 83 Gurgaon'!G7+'RallyGully I East of Kailash'!G7+'RallyGully I Sector 19 Dwarka'!G7+'RallyGully | LCR Pune'!G7+'RallyGully | DPSG'!G7+'RallyGully | Gandipath'!G7+'RallyGully | Panchsheel'!G7) -> 145784 | H19: =SUM('RallyGully I Sector 10 Dwarka'!H7+'RallyGully I Sector 83 Gurgaon'!H7+'RallyGully I East of Kailash'!H7+'RallyGully I Sector 19 Dwarka'!H7+'RallyGully | LCR Pune'!H7+'RallyGully | DPSG'!H7+'RallyGully | Gandipath'!H7+'RallyGully | Panchsheel'!H7) -> 203477 | I19: =SUM('RallyGully I Sector 10 Dwarka'!I7+'RallyGully I Sector 83 Gurgaon'!I7+'RallyGully I East of Kailash'!I7+'RallyGully I Sector 19 Dwarka'!I7+'RallyGully | LCR Pune'!I7+'RallyGully | DPSG'!I7+'RallyGully | Gandipath'!I7+'RallyGully | Panchsheel'!I7) -> 367975 | J19: =SUM('RallyGully I Sector 10 Dwarka'!J7+'RallyGully I Sector 83 Gurgaon'!J7+'RallyGully I East of Kailash'!J7+'RallyGully I Sector 19 Dwarka'!J7+'RallyGully | LCR Pune'!J7+'RallyGully | DPSG'!J7+'RallyGully | Gandipath'!J7+'RallyGully | Panchsheel'!J7) -> 415905 | K19: =SUM('RallyGully I Sector 10 Dwarka'!K7+'RallyGully I Sector 83 Gurgaon'!K7+'RallyGully I East of Kailash'!K7+'RallyGully I Sector 19 Dwarka'!K7+'RallyGully | LCR Pune'!K7+'RallyGully | DPSG'!K7+'RallyGully | Gandipath'!K7+'RallyGully | Panchsheel'!K7) -> 410475
A20: 2 | B20: Online: Third Party Platform | C20: =SUM('RallyGully I Sector 10 Dwarka'!C8+'RallyGully I Sector 83 Gurgaon'!C8+'RallyGully I East of Kailash'!C8+'RallyGully I Sector 19 Dwarka'!C8+'RallyGully | LCR Pune'!C8+'RallyGully | DPSG'!C8+'RallyGully | Gandipath'!C8+'RallyGully | Panchsheel'!C8) -> 88280 | D20: =SUM('RallyGully I Sector 10 Dwarka'!D8+'RallyGully I Sector 83 Gurgaon'!D8+'RallyGully I East of Kailash'!D8+'RallyGully I Sector 19 Dwarka'!D8+'RallyGully | LCR Pune'!D8+'RallyGully | DPSG'!D8+'RallyGully | Gandipath'!D8+'RallyGully | Panchsheel'!D8) -> 220132 | E20: =SUM('RallyGully I Sector 10 Dwarka'!E8+'RallyGully I Sector 83 Gurgaon'!E8+'RallyGully I East of Kailash'!E8+'RallyGully I Sector 19 Dwarka'!E8+'RallyGully | LCR Pune'!E8+'RallyGully | DPSG'!E8+'RallyGully | Gandipath'!E8+'RallyGully | Panchsheel'!E8) -> 282863.8 | F20: =SUM('RallyGully I Sector 10 Dwarka'!F8+'RallyGully I Sector 83 Gurgaon'!F8+'RallyGully I East of Kailash'!F8+'RallyGully I Sector 19 Dwarka'!F8+'RallyGully | LCR Pune'!F8+'RallyGully | DPSG'!F8+'RallyGully | Gandipath'!F8+'RallyGully | Panchsheel'!F8) -> 299312.6 | G20: =SUM('RallyGully I Sector 10 Dwarka'!G8+'RallyGully I Sector 83 Gurgaon'!G8+'RallyGully I East of Kailash'!G8+'RallyGully I Sector 19 Dwarka'!G8+'RallyGully | LCR Pune'!G8+'RallyGully | DPSG'!G8+'RallyGully | Gandipath'!G8+'RallyGully | Panchsheel'!G8) -> 262229 | H20: =SUM('RallyGully I Sector 10 Dwarka'!H8+'RallyGully I Sector 83 Gurgaon'!H8+'RallyGully I East of Kailash'!H8+'RallyGully I Sector 19 Dwarka'!H8+'RallyGully | LCR Pune'!H8+'RallyGully | DPSG'!H8+'RallyGully | Gandipath'!H8+'RallyGully | Panchsheel'!H8) -> 281135 | I20: =SUM('RallyGully I Sector 10 Dwarka'!I8+'RallyGully I Sector 83 Gurgaon'!I8+'RallyGully I East of Kailash'!I8+'RallyGully I Sector 19 Dwarka'!I8+'RallyGully | LCR Pune'!I8+'RallyGully | DPSG'!I8+'RallyGully | Gandipath'!I8+'RallyGully | Panchsheel'!I8) -> 520434 | J20: =SUM('RallyGully I Sector 10 Dwarka'!J8+'RallyGully I Sector 83 Gurgaon'!J8+'RallyGully I East of Kailash'!J8+'RallyGully I Sector 19 Dwarka'!J8+'RallyGully | LCR Pune'!J8+'RallyGully | DPSG'!J8+'RallyGully | Gandipath'!J8+'RallyGully | Panchsheel'!J8+'Powerplay Park, Pune'!J8+'Commons, Noida'!J8) -> 603109 | K20: =SUM('RallyGully I Sector 10 Dwarka'!K8+'RallyGully I Sector 83 Gurgaon'!K8+'RallyGully I East of Kailash'!K8+'RallyGully I Sector 19 Dwarka'!K8+'RallyGully | LCR Pune'!K8+'RallyGully | DPSG'!K8+'RallyGully | Gandipath'!K8+'RallyGully | Panchsheel'!K8+'Powerplay Park, Pune'!K8+'Commons, Noida'!K8) -> 861713
A21: 2.1 | B21: Hudle | C21: =SUM('RallyGully I Sector 10 Dwarka'!C9+'RallyGully I Sector 83 Gurgaon'!C9+'RallyGully I East of Kailash'!C9+'RallyGully I Sector 19 Dwarka'!C9+'RallyGully | LCR Pune'!C9+'RallyGully | DPSG'!C9+'RallyGully | Gandipath'!C9+'RallyGully | Panchsheel'!C9) -> 73440 | D21: =SUM('RallyGully I Sector 10 Dwarka'!D9+'RallyGully I Sector 83 Gurgaon'!D9+'RallyGully I East of Kailash'!D9+'RallyGully I Sector 19 Dwarka'!D9+'RallyGully | LCR Pune'!D9+'RallyGully | DPSG'!D9+'RallyGully | Gandipath'!D9+'RallyGully | Panchsheel'!D9) -> 162660 | E21: =SUM('RallyGully I Sector 10 Dwarka'!E9+'RallyGully I Sector 83 Gurgaon'!E9+'RallyGully I East of Kailash'!E9+'RallyGully I Sector 19 Dwarka'!E9+'RallyGully | LCR Pune'!E9+'RallyGully | DPSG'!E9+'RallyGully | Gandipath'!E9+'RallyGully | Panchsheel'!E9) -> 244051 | F21: =SUM('RallyGully I Sector 10 Dwarka'!F9+'RallyGully I Sector 83 Gurgaon'!F9+'RallyGully I East of Kailash'!F9+'RallyGully I Sector 19 Dwarka'!F9+'RallyGully | LCR Pune'!F9+'RallyGully | DPSG'!F9+'RallyGully | Gandipath'!F9+'RallyGully | Panchsheel'!F9) -> 257545 | G21: =SUM('RallyGully I Sector 10 Dwarka'!G9+'RallyGully I Sector 83 Gurgaon'!G9+'RallyGully I East of Kailash'!G9+'RallyGully I Sector 19 Dwarka'!G9+'RallyGully | LCR Pune'!G9+'RallyGully | DPSG'!G9+'RallyGully | Gandipath'!G9+'RallyGully | Panchsheel'!G9) -> 201485 | H21: =SUM('RallyGully I Sector 10 Dwarka'!H9+'RallyGully I Sector 83 Gurgaon'!H9+'RallyGully I East of Kailash'!H9+'RallyGully I Sector 19 Dwarka'!H9+'RallyGully | LCR Pune'!H9+'RallyGully | DPSG'!H9+'RallyGully | Gandipath'!H9+'RallyGully | Panchsheel'!H9) -> 173633 | I21: =SUM('RallyGully I Sector 10 Dwarka'!I9+'RallyGully I Sector 83 Gurgaon'!I9+'RallyGully I East of Kailash'!I9+'RallyGully I Sector 19 Dwarka'!I9+'RallyGully | LCR Pune'!I9+'RallyGully | DPSG'!I9+'RallyGully | Gandipath'!I9+'RallyGully | Panchsheel'!I9) -> 263500 | J21: =SUM('RallyGully I Sector 10 Dwarka'!J9+'RallyGully I Sector 83 Gurgaon'!J9+'RallyGully I East of Kailash'!J9+'RallyGully I Sector 19 Dwarka'!J9+'RallyGully | LCR Pune'!J9+'RallyGully | DPSG'!J9+'RallyGully | Gandipath'!J9+'RallyGully | Panchsheel'!J9+'Powerplay Park, Pune'!J9+'Commons, Noida'!J9) -> 263802 | K21: =SUM('RallyGully I Sector 10 Dwarka'!K9+'RallyGully I Sector 83 Gurgaon'!K9+'RallyGully I East of Kailash'!K9+'RallyGully I Sector 19 Dwarka'!K9+'RallyGully | LCR Pune'!K9+'RallyGully | DPSG'!K9+'RallyGully | Gandipath'!K9+'RallyGully | Panchsheel'!K9+'Powerplay Park, Pune'!K9+'Commons, Noida'!K9) -> 377943
A22: 2.2 | B22: Playo | C22: =SUM('RallyGully I Sector 10 Dwarka'!C10+'RallyGully I Sector 83 Gurgaon'!C10+'RallyGully I East of Kailash'!C10+'RallyGully I Sector 19 Dwarka'!C10+'RallyGully | LCR Pune'!C10+'RallyGully | DPSG'!C10+'RallyGully | Gandipath'!C10+'RallyGully | Panchsheel'!C10) -> 14840 | D22: =SUM('RallyGully I Sector 10 Dwarka'!D10+'RallyGully I Sector 83 Gurgaon'!D10+'RallyGully I East of Kailash'!D10+'RallyGully I Sector 19 Dwarka'!D10+'RallyGully | LCR Pune'!D10+'RallyGully | DPSG'!D10+'RallyGully | Gandipath'!D10+'RallyGully | Panchsheel'!D10) -> 46790 | E22: =SUM('RallyGully I Sector 10 Dwarka'!E10+'RallyGully I Sector 83 Gurgaon'!E10+'RallyGully I East of Kailash'!E10+'RallyGully I Sector 19 Dwarka'!E10+'RallyGully | LCR Pune'!E10+'RallyGully | DPSG'!E10+'RallyGully | Gandipath'!E10+'RallyGully | Panchsheel'!E10) -> 32658.8 | F22: =SUM('RallyGully I Sector 10 Dwarka'!F10+'RallyGully I Sector 83 Gurgaon'!F10+'RallyGully I East of Kailash'!F10+'RallyGully I Sector 19 Dwarka'!F10+'RallyGully | LCR Pune'!F10+'RallyGully | DPSG'!F10+'RallyGully | Gandipath'!F10+'RallyGully | Panchsheel'!F10) -> 30067.6 | G22: =SUM('RallyGully I Sector 10 Dwarka'!G10+'RallyGully I Sector 83 Gurgaon'!G10+'RallyGully I East of Kailash'!G10+'RallyGully I Sector 19 Dwarka'!G10+'RallyGully | LCR Pune'!G10+'RallyGully | DPSG'!G10+'RallyGully | Gandipath'!G10+'RallyGully | Panchsheel'!G10) -> 27305 | H22: =SUM('RallyGully I Sector 10 Dwarka'!H10+'RallyGully I Sector 83 Gurgaon'!H10+'RallyGully I East of Kailash'!H10+'RallyGully I Sector 19 Dwarka'!H10+'RallyGully | LCR Pune'!H10+'RallyGully | DPSG'!H10+'RallyGully | Gandipath'!H10+'RallyGully | Panchsheel'!H10) -> 45577 | I22: =SUM('RallyGully I Sector 10 Dwarka'!I10+'RallyGully I Sector 83 Gurgaon'!I10+'RallyGully I East of Kailash'!I10+'RallyGully I Sector 19 Dwarka'!I10+'RallyGully | LCR Pune'!I10+'RallyGully | DPSG'!I10+'RallyGully | Gandipath'!I10+'RallyGully | Panchsheel'!I10) -> 93017 | J22: =SUM('RallyGully I Sector 10 Dwarka'!J10+'RallyGully I Sector 83 Gurgaon'!J10+'RallyGully I East of Kailash'!J10+'RallyGully I Sector 19 Dwarka'!J10+'RallyGully | LCR Pune'!J10+'RallyGully | DPSG'!J10+'RallyGully | Gandipath'!J10+'RallyGully | Panchsheel'!J10+'Powerplay Park, Pune'!J10+'Commons, Noida'!J10) -> 87503 | K22: =SUM('RallyGully I Sector 10 Dwarka'!K10+'RallyGully I Sector 83 Gurgaon'!K10+'RallyGully I East of Kailash'!K10+'RallyGully I Sector 19 Dwarka'!K10+'RallyGully | LCR Pune'!K10+'RallyGully | DPSG'!K10+'RallyGully | Gandipath'!K10+'RallyGully | Panchsheel'!K10+'Powerplay Park, Pune'!K10+'Commons, Noida'!K10) -> 123355
A23: 2.3 | B23: District | C23: =SUM('RallyGully I Sector 10 Dwarka'!C11+'RallyGully I Sector 83 Gurgaon'!C11+'RallyGully I East of Kailash'!C11+'RallyGully I Sector 19 Dwarka'!C11+'RallyGully | LCR Pune'!C11+'RallyGully | DPSG'!C11+'RallyGully | Gandipath'!C11+'RallyGully | Panchsheel'!C11) -> 0 | D23: =SUM('RallyGully I Sector 10 Dwarka'!D11+'RallyGully I Sector 83 Gurgaon'!D11+'RallyGully I East of Kailash'!D11+'RallyGully I Sector 19 Dwarka'!D11+'RallyGully | LCR Pune'!D11+'RallyGully | DPSG'!D11+'RallyGully | Gandipath'!D11+'RallyGully | Panchsheel'!D11) -> 0 | E23: =SUM('RallyGully I Sector 10 Dwarka'!E11+'RallyGully I Sector 83 Gurgaon'!E11+'RallyGully I East of Kailash'!E11+'RallyGully I Sector 19 Dwarka'!E11+'RallyGully | LCR Pune'!E11+'RallyGully | DPSG'!E11+'RallyGully | Gandipath'!E11+'RallyGully | Panchsheel'!E11) -> 0 | F23: =SUM('RallyGully I Sector 10 Dwarka'!F11+'RallyGully I Sector 83 Gurgaon'!F11+'RallyGully I East of Kailash'!F11+'RallyGully I Sector 19 Dwarka'!F11+'RallyGully | LCR Pune'!F11+'RallyGully | DPSG'!F11+'RallyGully | Gandipath'!F11+'RallyGully | Panchsheel'!F11) -> 1200 | G23: =SUM('RallyGully I Sector 10 Dwarka'!G11+'RallyGully I Sector 83 Gurgaon'!G11+'RallyGully I East of Kailash'!G11+'RallyGully I Sector 19 Dwarka'!G11+'RallyGully | LCR Pune'!G11+'RallyGully | DPSG'!G11+'RallyGully | Gandipath'!G11+'RallyGully | Panchsheel'!G11) -> 3106 | H23: =SUM('RallyGully I Sector 10 Dwarka'!H11+'RallyGully I Sector 83 Gurgaon'!H11+'RallyGully I East of Kailash'!H11+'RallyGully I Sector 19 Dwarka'!H11+'RallyGully | LCR Pune'!H11+'RallyGully | DPSG'!H11+'RallyGully | Gandipath'!H11+'RallyGully | Panchsheel'!H11) -> 18150 | I23: =SUM('RallyGully I Sector 10 Dwarka'!I11+'RallyGully I Sector 83 Gurgaon'!I11+'RallyGully I East of Kailash'!I11+'RallyGully I Sector 19 Dwarka'!I11+'RallyGully | LCR Pune'!I11+'RallyGully | DPSG'!I11+'RallyGully | Gandipath'!I11+'RallyGully | Panchsheel'!I11) -> 101150 | J23: =SUM('RallyGully I Sector 10 Dwarka'!J11+'RallyGully I Sector 83 Gurgaon'!J11+'RallyGully I East of Kailash'!J11+'RallyGully I Sector 19 Dwarka'!J11+'RallyGully | LCR Pune'!J11+'RallyGully | DPSG'!J11+'RallyGully | Gandipath'!J11+'RallyGully | Panchsheel'!J11+'Powerplay Park, Pune'!J11+'Commons, Noida'!J11) -> 163600 | K23: =SUM('RallyGully I Sector 10 Dwarka'!K11+'RallyGully I Sector 83 Gurgaon'!K11+'RallyGully I East of Kailash'!K11+'RallyGully I Sector 19 Dwarka'!K11+'RallyGully | LCR Pune'!K11+'RallyGully | DPSG'!K11+'RallyGully | Gandipath'!K11+'RallyGully | Panchsheel'!K11+'Powerplay Park, Pune'!K11+'Commons, Noida'!K11) -> 209600
A24: 2.4 | B24: Khelomore | C24: =SUM('RallyGully I Sector 10 Dwarka'!C12+'RallyGully I Sector 83 Gurgaon'!C12+'RallyGully I East of Kailash'!C12+'RallyGully I Sector 19 Dwarka'!C12+'RallyGully | LCR Pune'!C12+'RallyGully | DPSG'!C12+'RallyGully | Gandipath'!C12+'RallyGully | Panchsheel'!C12) -> 0 | D24: =SUM('RallyGully I Sector 10 Dwarka'!D12+'RallyGully I Sector 83 Gurgaon'!D12+'RallyGully I East of Kailash'!D12+'RallyGully I Sector 19 Dwarka'!D12+'RallyGully | LCR Pune'!D12+'RallyGully | DPSG'!D12+'RallyGully | Gandipath'!D12+'RallyGully | Panchsheel'!D12) -> 10682 | E24: =SUM('RallyGully I Sector 10 Dwarka'!E12+'RallyGully I Sector 83 Gurgaon'!E12+'RallyGully I East of Kailash'!E12+'RallyGully I Sector 19 Dwarka'!E12+'RallyGully | LCR Pune'!E12+'RallyGully | DPSG'!E12+'RallyGully | Gandipath'!E12+'RallyGully | Panchsheel'!E12) -> 6154 | F24: =SUM('RallyGully I Sector 10 Dwarka'!F12+'RallyGully I Sector 83 Gurgaon'!F12+'RallyGully I East of Kailash'!F12+'RallyGully I Sector 19 Dwarka'!F12+'RallyGully | LCR Pune'!F12+'RallyGully | DPSG'!F12+'RallyGully | Gandipath'!F12+'RallyGully | Panchsheel'!F12) -> 10500 | G24: =SUM('RallyGully I Sector 10 Dwarka'!G12+'RallyGully I Sector 83 Gurgaon'!G12+'RallyGully I East of Kailash'!G12+'RallyGully I Sector 19 Dwarka'!G12+'RallyGully | LCR Pune'!G12+'RallyGully | DPSG'!G12+'RallyGully | Gandipath'!G12+'RallyGully | Panchsheel'!G12) -> 30333 | H24: =SUM('RallyGully I Sector 10 Dwarka'!H12+'RallyGully I Sector 83 Gurgaon'!H12+'RallyGully I East of Kailash'!H12+'RallyGully I Sector 19 Dwarka'!H12+'RallyGully | LCR Pune'!H12+'RallyGully | DPSG'!H12+'RallyGully | Gandipath'!H12+'RallyGully | Panchsheel'!H12) -> 42525 | I24: =SUM('RallyGully I Sector 10 Dwarka'!I12+'RallyGully I Sector 83 Gurgaon'!I12+'RallyGully I East of Kailash'!I12+'RallyGully I Sector 19 Dwarka'!I12+'RallyGully | LCR Pune'!I12+'RallyGully | DPSG'!I12+'RallyGully | Gandipath'!I12+'RallyGully | Panchsheel'!I12) -> 37394 | J24: =SUM('RallyGully I Sector 10 Dwarka'!J12+'RallyGully I Sector 83 Gurgaon'!J12+'RallyGully I East of Kailash'!J12+'RallyGully I Sector 19 Dwarka'!J12+'RallyGully | LCR Pune'!J12+'RallyGully | DPSG'!J12+'RallyGully | Gandipath'!J12+'RallyGully | Panchsheel'!J12+'Powerplay Park, Pune'!J12+'Commons, Noida'!J12) -> 47546 | K24: =SUM('RallyGully I Sector 10 Dwarka'!K12+'RallyGully I Sector 83 Gurgaon'!K12+'RallyGully I East of Kailash'!K12+'RallyGully I Sector 19 Dwarka'!K12+'RallyGully | LCR Pune'!K12+'RallyGully | DPSG'!K12+'RallyGully | Gandipath'!K12+'RallyGully | Panchsheel'!K12+'Powerplay Park, Pune'!K12+'Commons, Noida'!K12) -> 55690
A25: 2.5 | B25: Zplys | C25: =SUM('RallyGully I Sector 10 Dwarka'!C13+'RallyGully I Sector 83 Gurgaon'!C13+'RallyGully I East of Kailash'!C13+'RallyGully I Sector 19 Dwarka'!C13+'RallyGully | LCR Pune'!C13+'RallyGully | DPSG'!C13+'RallyGully | Gandipath'!C13+'RallyGully | Panchsheel'!C13) -> 0 | D25: =SUM('RallyGully I Sector 10 Dwarka'!D13+'RallyGully I Sector 83 Gurgaon'!D13+'RallyGully I East of Kailash'!D13+'RallyGully I Sector 19 Dwarka'!D13+'RallyGully | LCR Pune'!D13+'RallyGully | DPSG'!D13+'RallyGully | Gandipath'!D13+'RallyGully | Panchsheel'!D13) -> 0 | E25: =SUM('RallyGully I Sector 10 Dwarka'!E13+'RallyGully I Sector 83 Gurgaon'!E13+'RallyGully I East of Kailash'!E13+'RallyGully I Sector 19 Dwarka'!E13+'RallyGully | LCR Pune'!E13+'RallyGully | DPSG'!E13+'RallyGully | Gandipath'!E13+'RallyGully | Panchsheel'!E13) -> 0 | F25: =SUM('RallyGully I Sector 10 Dwarka'!F13+'RallyGully I Sector 83 Gurgaon'!F13+'RallyGully I East of Kailash'!F13+'RallyGully I Sector 19 Dwarka'!F13+'RallyGully | LCR Pune'!F13+'RallyGully | DPSG'!F13+'RallyGully | Gandipath'!F13+'RallyGully | Panchsheel'!F13) -> 0 | G25: =SUM('RallyGully I Sector 10 Dwarka'!G13+'RallyGully I Sector 83 Gurgaon'!G13+'RallyGully I East of Kailash'!G13+'RallyGully I Sector 19 Dwarka'!G13+'RallyGully | LCR Pune'!G13+'RallyGully | DPSG'!G13+'RallyGully | Gandipath'!G13+'RallyGully | Panchsheel'!G13) -> 0 | H25: =SUM('RallyGully I Sector 10 Dwarka'!H13+'RallyGully I Sector 83 Gurgaon'!H13+'RallyGully I East of Kailash'!H13+'RallyGully I Sector 19 Dwarka'!H13+'RallyGully | LCR Pune'!H13+'RallyGully | DPSG'!H13+'RallyGully | Gandipath'!H13+'RallyGully | Panchsheel'!H13) -> 1250 | I25: =SUM('RallyGully I Sector 10 Dwarka'!I13+'RallyGully I Sector 83 Gurgaon'!I13+'RallyGully I East of Kailash'!I13+'RallyGully I Sector 19 Dwarka'!I13+'RallyGully | LCR Pune'!I13+'RallyGully | DPSG'!I13+'RallyGully | Gandipath'!I13+'RallyGully | Panchsheel'!I13) -> 25373 | J25: =SUM('RallyGully I Sector 10 Dwarka'!J13+'RallyGully I Sector 83 Gurgaon'!J13+'RallyGully I East of Kailash'!J13+'RallyGully I Sector 19 Dwarka'!J13+'RallyGully | LCR Pune'!J13+'RallyGully | DPSG'!J13+'RallyGully | Gandipath'!J13+'RallyGully | Panchsheel'!J13+'Powerplay Park, Pune'!J13+'Commons, Noida'!J13) -> 40658 | K25: =SUM('RallyGully I Sector 10 Dwarka'!K13+'RallyGully I Sector 83 Gurgaon'!K13+'RallyGully I East of Kailash'!K13+'RallyGully I Sector 19 Dwarka'!K13+'RallyGully | LCR Pune'!K13+'RallyGully | DPSG'!K13+'RallyGully | Gandipath'!K13+'RallyGully | Panchsheel'!K13+'Powerplay Park, Pune'!K13+'Commons, Noida'!K13) -> 95125
A26: 3 | B26: Community | C26: =SUM('RallyGully I Sector 10 Dwarka'!C14+'RallyGully I Sector 83 Gurgaon'!C14+'RallyGully I East of Kailash'!C14+'RallyGully I Sector 19 Dwarka'!C14+'RallyGully | LCR Pune'!C14+'RallyGully | DPSG'!C14+'RallyGully | Gandipath'!C14+'RallyGully | Panchsheel'!C14) -> 10500 | D26: =SUM('RallyGully I Sector 10 Dwarka'!D14+'RallyGully I Sector 83 Gurgaon'!D14+'RallyGully I East of Kailash'!D14+'RallyGully I Sector 19 Dwarka'!D14+'RallyGully | LCR Pune'!D14+'RallyGully | DPSG'!D14+'RallyGully | Gandipath'!D14+'RallyGully | Panchsheel'!D14) -> 15087 | E26: =SUM('RallyGully I Sector 10 Dwarka'!E14+'RallyGully I Sector 83 Gurgaon'!E14+'RallyGully I East of Kailash'!E14+'RallyGully I Sector 19 Dwarka'!E14+'RallyGully | LCR Pune'!E14+'RallyGully | DPSG'!E14+'RallyGully | Gandipath'!E14+'RallyGully | Panchsheel'!E14) -> 29490 | F26: =SUM('RallyGully I Sector 10 Dwarka'!F14+'RallyGully I Sector 83 Gurgaon'!F14+'RallyGully I East of Kailash'!F14+'RallyGully I Sector 19 Dwarka'!F14+'RallyGully | LCR Pune'!F14+'RallyGully | DPSG'!F14+'RallyGully | Gandipath'!F14+'RallyGully | Panchsheel'!F14) -> 40340 | G26: =SUM('RallyGully I Sector 10 Dwarka'!G14+'RallyGully I Sector 83 Gurgaon'!G14+'RallyGully I East of Kailash'!G14+'RallyGully I Sector 19 Dwarka'!G14+'RallyGully | LCR Pune'!G14+'RallyGully | DPSG'!G14+'RallyGully | Gandipath'!G14+'RallyGully | Panchsheel'!G14) -> 40260 | H26: =SUM('RallyGully I Sector 10 Dwarka'!H14+'RallyGully I Sector 83 Gurgaon'!H14+'RallyGully I East of Kailash'!H14+'RallyGully I Sector 19 Dwarka'!H14+'RallyGully | LCR Pune'!H14+'RallyGully | DPSG'!H14+'RallyGully | Gandipath'!H14+'RallyGully | Panchsheel'!H14) -> 31109 | I26: =SUM('RallyGully I Sector 10 Dwarka'!I14+'RallyGully I Sector 83 Gurgaon'!I14+'RallyGully I East of Kailash'!I14+'RallyGully I Sector 19 Dwarka'!I14+'RallyGully | LCR Pune'!I14+'RallyGully | DPSG'!I14+'RallyGully | Gandipath'!I14+'RallyGully | Panchsheel'!I14) -> 131439 | J26: =SUM('RallyGully I Sector 10 Dwarka'!J14+'RallyGully I Sector 83 Gurgaon'!J14+'RallyGully I East of Kailash'!J14+'RallyGully I Sector 19 Dwarka'!J14+'RallyGully | LCR Pune'!J14+'RallyGully | DPSG'!J14+'RallyGully | Gandipath'!J14+'RallyGully | Panchsheel'!J14+'Powerplay Park, Pune'!J14+'Commons, Noida'!J14) -> 176514 | K26: =SUM('RallyGully I Sector 10 Dwarka'!K14+'RallyGully I Sector 83 Gurgaon'!K14+'RallyGully I East of Kailash'!K14+'RallyGully I Sector 19 Dwarka'!K14+'RallyGully | LCR Pune'!K14+'RallyGully | DPSG'!K14+'RallyGully | Gandipath'!K14+'RallyGully | Panchsheel'!K14+'Powerplay Park, Pune'!K14+'Commons, Noida'!K14) -> 256304
A27: 3.1 | B27: Courtly (Organized by RallyGully) | C27: =SUM('RallyGully I Sector 10 Dwarka'!C15+'RallyGully I Sector 83 Gurgaon'!C15+'RallyGully I East of Kailash'!C15+'RallyGully I Sector 19 Dwarka'!C15+'RallyGully | LCR Pune'!C15+'RallyGully | DPSG'!C15+'RallyGully | Gandipath'!C15+'RallyGully | Panchsheel'!C15) -> 0 | D27: =SUM('RallyGully I Sector 10 Dwarka'!D15+'RallyGully I Sector 83 Gurgaon'!D15+'RallyGully I East of Kailash'!D15+'RallyGully I Sector 19 Dwarka'!D15+'RallyGully | LCR Pune'!D15+'RallyGully | DPSG'!D15+'RallyGully | Gandipath'!D15+'RallyGully | Panchsheel'!D15) -> 0 | E27: =SUM('RallyGully I Sector 10 Dwarka'!E15+'RallyGully I Sector 83 Gurgaon'!E15+'RallyGully I East of Kailash'!E15+'RallyGully I Sector 19 Dwarka'!E15+'RallyGully | LCR Pune'!E15+'RallyGully | DPSG'!E15+'RallyGully | Gandipath'!E15+'RallyGully | Panchsheel'!E15) -> 0 | F27: =SUM('RallyGully I Sector 10 Dwarka'!F15+'RallyGully I Sector 83 Gurgaon'!F15+'RallyGully I East of Kailash'!F15+'RallyGully I Sector 19 Dwarka'!F15+'RallyGully | LCR Pune'!F15+'RallyGully | DPSG'!F15+'RallyGully | Gandipath'!F15+'RallyGully | Panchsheel'!F15) -> 0 | G27: =SUM('RallyGully I Sector 10 Dwarka'!G15+'RallyGully I Sector 83 Gurgaon'!G15+'RallyGully I East of Kailash'!G15+'RallyGully I Sector 19 Dwarka'!G15+'RallyGully | LCR Pune'!G15+'RallyGully | DPSG'!G15+'RallyGully | Gandipath'!G15+'RallyGully | Panchsheel'!G15) -> 8500 | H27: =SUM('RallyGully I Sector 10 Dwarka'!H15+'RallyGully I Sector 83 Gurgaon'!H15+'RallyGully I East of Kailash'!H15+'RallyGully I Sector 19 Dwarka'!H15+'RallyGully | LCR Pune'!H15+'RallyGully | DPSG'!H15+'RallyGully | Gandipath'!H15+'RallyGully | Panchsheel'!H15) -> 0 | I27: =SUM('RallyGully I Sector 10 Dwarka'!I15+'RallyGully I Sector 83 Gurgaon'!I15+'RallyGully I East of Kailash'!I15+'RallyGully I Sector 19 Dwarka'!I15+'RallyGully | LCR Pune'!I15+'RallyGully | DPSG'!I15+'RallyGully | Gandipath'!I15+'RallyGully | Panchsheel'!I15) -> 38300 | J27: =SUM('RallyGully I Sector 10 Dwarka'!J15+'RallyGully I Sector 83 Gurgaon'!J15+'RallyGully I East of Kailash'!J15+'RallyGully I Sector 19 Dwarka'!J15+'RallyGully | LCR Pune'!J15+'RallyGully | DPSG'!J15+'RallyGully | Gandipath'!J15+'RallyGully | Panchsheel'!J15) -> 55200
A28: 3.2 | B28: Sportomic (Organized by RallyGully) | C28: =SUM('RallyGully I Sector 10 Dwarka'!C16+'RallyGully I Sector 83 Gurgaon'!C16+'RallyGully I East of Kailash'!C16+'RallyGully I Sector 19 Dwarka'!C16+'RallyGully | LCR Pune'!C16+'RallyGully | DPSG'!C16+'RallyGully | Gandipath'!C16+'RallyGully | Panchsheel'!C16) -> 0 | D28: =SUM('RallyGully I Sector 10 Dwarka'!D16+'RallyGully I Sector 83 Gurgaon'!D16+'RallyGully I East of Kailash'!D16+'RallyGully I Sector 19 Dwarka'!D16+'RallyGully | LCR Pune'!D16+'RallyGully | DPSG'!D16+'RallyGully | Gandipath'!D16+'RallyGully | Panchsheel'!D16) -> 0 | E28: =SUM('RallyGully I Sector 10 Dwarka'!E16+'RallyGully I Sector 83 Gurgaon'!E16+'RallyGully I East of Kailash'!E16+'RallyGully I Sector 19 Dwarka'!E16+'RallyGully | LCR Pune'!E16+'RallyGully | DPSG'!E16+'RallyGully | Gandipath'!E16+'RallyGully | Panchsheel'!E16) -> 0 | F28: =SUM('RallyGully I Sector 10 Dwarka'!F16+'RallyGully I Sector 83 Gurgaon'!F16+'RallyGully I East of Kailash'!F16+'RallyGully I Sector 19 Dwarka'!F16+'RallyGully | LCR Pune'!F16+'RallyGully | DPSG'!F16+'RallyGully | Gandipath'!F16+'RallyGully | Panchsheel'!F16) -> 0 | G28: =SUM('RallyGully I Sector 10 Dwarka'!G16+'RallyGully I Sector 83 Gurgaon'!G16+'RallyGully I East of Kailash'!G16+'RallyGully I Sector 19 Dwarka'!G16+'RallyGully | LCR Pune'!G16+'RallyGully | DPSG'!G16+'RallyGully | Gandipath'!G16+'RallyGully | Panchsheel'!G16) -> 0 | H28: =SUM('RallyGully I Sector 10 Dwarka'!H16+'RallyGully I Sector 83 Gurgaon'!H16+'RallyGully I East of Kailash'!H16+'RallyGully I Sector 19 Dwarka'!H16+'RallyGully | LCR Pune'!H16+'RallyGully | DPSG'!H16+'RallyGully | Gandipath'!H16+'RallyGully | Panchsheel'!H16) -> 23290 | I28: =SUM('RallyGully I Sector 10 Dwarka'!I16+'RallyGully I Sector 83 Gurgaon'!I16+'RallyGully I East of Kailash'!I16+'RallyGully I Sector 19 Dwarka'!I16+'RallyGully | LCR Pune'!I16+'RallyGully | DPSG'!I16+'RallyGully | Gandipath'!I16+'RallyGully | Panchsheel'!I16) -> 13650 | J28: =SUM('RallyGully I Sector 10 Dwarka'!J16+'RallyGully I Sector 83 Gurgaon'!J16+'RallyGully I East of Kailash'!J16+'RallyGully I Sector 19 Dwarka'!J16+'RallyGully | LCR Pune'!J16+'RallyGully | DPSG'!J16+'RallyGully | Gandipath'!J16+'RallyGully | Panchsheel'!J16) -> 42360
A29: 3.3 | B29: Rallygully Community games | C29: =SUM('RallyGully I Sector 10 Dwarka'!C17+'RallyGully I Sector 83 Gurgaon'!C17+'RallyGully I East of Kailash'!C17+'RallyGully I Sector 19 Dwarka'!C17+'RallyGully | LCR Pune'!C17+'RallyGully | DPSG'!C17+'RallyGully | Gandipath'!C17+'RallyGully | Panchsheel'!C17) -> 10500 | D29: =SUM('RallyGully I Sector 10 Dwarka'!D17+'RallyGully I Sector 83 Gurgaon'!D17+'RallyGully I East of Kailash'!D17+'RallyGully I Sector 19 Dwarka'!D17+'RallyGully | LCR Pune'!D17+'RallyGully | DPSG'!D17+'RallyGully | Gandipath'!D17+'RallyGully | Panchsheel'!D17) -> 15087 | E29: =SUM('RallyGully I Sector 10 Dwarka'!E17+'RallyGully I Sector 83 Gurgaon'!E17+'RallyGully I East of Kailash'!E17+'RallyGully I Sector 19 Dwarka'!E17+'RallyGully | LCR Pune'!E17+'RallyGully | DPSG'!E17+'RallyGully | Gandipath'!E17+'RallyGully | Panchsheel'!E17) -> 19900 | F29: =SUM('RallyGully I Sector 10 Dwarka'!F17+'RallyGully I Sector 83 Gurgaon'!F17+'RallyGully I East of Kailash'!F17+'RallyGully I Sector 19 Dwarka'!F17+'RallyGully | LCR Pune'!F17+'RallyGully | DPSG'!F17+'RallyGully | Gandipath'!F17+'RallyGully | Panchsheel'!F17) -> 28350 | G29: =SUM('RallyGully I Sector 10 Dwarka'!G17+'RallyGully I Sector 83 Gurgaon'!G17+'RallyGully I East of Kailash'!G17+'RallyGully I Sector 19 Dwarka'!G17+'RallyGully | LCR Pune'!G17+'RallyGully | DPSG'!G17+'RallyGully | Gandipath'!G17+'RallyGully | Panchsheel'!G17) -> 20780 | H29: =SUM('RallyGully I Sector 10 Dwarka'!H17+'RallyGully I Sector 83 Gurgaon'!H17+'RallyGully I East of Kailash'!H17+'RallyGully I Sector 19 Dwarka'!H17+'RallyGully | LCR Pune'!H17+'RallyGully | DPSG'!H17+'RallyGully | Gandipath'!H17+'RallyGully | Panchsheel'!H17) -> 2510 | I29: =SUM('RallyGully I Sector 10 Dwarka'!I17+'RallyGully I Sector 83 Gurgaon'!I17+'RallyGully I East of Kailash'!I17+'RallyGully I Sector 19 Dwarka'!I17+'RallyGully | LCR Pune'!I17+'RallyGully | DPSG'!I17+'RallyGully | Gandipath'!I17+'RallyGully | Panchsheel'!I17) -> 79489 | J29: =SUM('RallyGully I Sector 10 Dwarka'!J17+'RallyGully I Sector 83 Gurgaon'!J17+'RallyGully I East of Kailash'!J17+'RallyGully I Sector 19 Dwarka'!J17+'RallyGully | LCR Pune'!J17+'RallyGully | DPSG'!J17+'RallyGully | Gandipath'!J17+'RallyGully | Panchsheel'!J17) -> 63275
A30: 3.4 | B30: Misfits Community | C30: =SUM('RallyGully I Sector 10 Dwarka'!C18+'RallyGully I Sector 83 Gurgaon'!C18+'RallyGully I East of Kailash'!C18+'RallyGully I Sector 19 Dwarka'!C18+'RallyGully | LCR Pune'!C18+'RallyGully | DPSG'!C18+'RallyGully | Gandipath'!C18+'RallyGully | Panchsheel'!C18) -> 0 | D30: =SUM('RallyGully I Sector 10 Dwarka'!D18+'RallyGully I Sector 83 Gurgaon'!D18+'RallyGully I East of Kailash'!D18+'RallyGully I Sector 19 Dwarka'!D18+'RallyGully | LCR Pune'!D18+'RallyGully | DPSG'!D18+'RallyGully | Gandipath'!D18+'RallyGully | Panchsheel'!D18) -> 0 | E30: =SUM('RallyGully I Sector 10 Dwarka'!E18+'RallyGully I Sector 83 Gurgaon'!E18+'RallyGully I East of Kailash'!E18+'RallyGully I Sector 19 Dwarka'!E18+'RallyGully | LCR Pune'!E18+'RallyGully | DPSG'!E18+'RallyGully | Gandipath'!E18+'RallyGully | Panchsheel'!E18) -> 9590 | F30: =SUM('RallyGully I Sector 10 Dwarka'!F18+'RallyGully I Sector 83 Gurgaon'!F18+'RallyGully I East of Kailash'!F18+'RallyGully I Sector 19 Dwarka'!F18+'RallyGully | LCR Pune'!F18+'RallyGully | DPSG'!F18+'RallyGully | Gandipath'!F18+'RallyGully | Panchsheel'!F18) -> 11990 | G30: =SUM('RallyGully I Sector 10 Dwarka'!G18+'RallyGully I Sector 83 Gurgaon'!G18+'RallyGully I East of Kailash'!G18+'RallyGully I Sector 19 Dwarka'!G18+'RallyGully | LCR Pune'!G18+'RallyGully | DPSG'!G18+'RallyGully | Gandipath'!G18+'RallyGully | Panchsheel'!G18) -> 10980 | H30: =SUM('RallyGully I Sector 10 Dwarka'!H18+'RallyGully I Sector 83 Gurgaon'!H18+'RallyGully I East of Kailash'!H18+'RallyGully I Sector 19 Dwarka'!H18+'RallyGully | LCR Pune'!H18+'RallyGully | DPSG'!H18+'RallyGully | Gandipath'!H18+'RallyGully | Panchsheel'!H18) -> 5309 | I30: =SUM('RallyGully I Sector 10 Dwarka'!I18+'RallyGully I Sector 83 Gurgaon'!I18+'RallyGully I East of Kailash'!I18+'RallyGully I Sector 19 Dwarka'!I18+'RallyGully | LCR Pune'!I18+'RallyGully | DPSG'!I18+'RallyGully | Gandipath'!I18+'RallyGully | Panchsheel'!I18) -> 0 | J30: =SUM('RallyGully I Sector 10 Dwarka'!J18+'RallyGully I Sector 83 Gurgaon'!J18+'RallyGully I East of Kailash'!J18+'RallyGully I Sector 19 Dwarka'!J18+'RallyGully | LCR Pune'!J18+'RallyGully | DPSG'!J18+'RallyGully | Gandipath'!J18+'RallyGully | Panchsheel'!J18) -> 15679
A31: 4 | B31: Memberships | C31: =SUM('RallyGully I Sector 10 Dwarka'!C19+'RallyGully I Sector 83 Gurgaon'!C19+'RallyGully I East of Kailash'!C19+'RallyGully I Sector 19 Dwarka'!C19+'RallyGully | LCR Pune'!C19+'RallyGully | DPSG'!C19+'RallyGully | Gandipath'!C19+'RallyGully | Panchsheel'!C19) -> 0 | D31: =SUM('RallyGully I Sector 10 Dwarka'!D19+'RallyGully I Sector 83 Gurgaon'!D19+'RallyGully I East of Kailash'!D19+'RallyGully I Sector 19 Dwarka'!D19+'RallyGully | LCR Pune'!D19+'RallyGully | DPSG'!D19+'RallyGully | Gandipath'!D19+'RallyGully | Panchsheel'!D19) -> 50000 | E31: =SUM('RallyGully I Sector 10 Dwarka'!E19+'RallyGully I Sector 83 Gurgaon'!E19+'RallyGully I East of Kailash'!E19+'RallyGully I Sector 19 Dwarka'!E19+'RallyGully | LCR Pune'!E19+'RallyGully | DPSG'!E19+'RallyGully | Gandipath'!E19+'RallyGully | Panchsheel'!E19) -> 27000 | F31: =SUM('RallyGully I Sector 10 Dwarka'!F19+'RallyGully I Sector 83 Gurgaon'!F19+'RallyGully I East of Kailash'!F19+'RallyGully I Sector 19 Dwarka'!F19+'RallyGully | LCR Pune'!F19+'RallyGully | DPSG'!F19+'RallyGully | Gandipath'!F19+'RallyGully | Panchsheel'!F19) -> 91300 | G31: =SUM('RallyGully I Sector 10 Dwarka'!G19+'RallyGully I Sector 83 Gurgaon'!G19+'RallyGully I East of Kailash'!G19+'RallyGully I Sector 19 Dwarka'!G19+'RallyGully | LCR Pune'!G19+'RallyGully | DPSG'!G19+'RallyGully | Gandipath'!G19+'RallyGully | Panchsheel'!G19) -> 74380 | H31: =SUM('RallyGully I Sector 10 Dwarka'!H19+'RallyGully I Sector 83 Gurgaon'!H19+'RallyGully I East of Kailash'!H19+'RallyGully I Sector 19 Dwarka'!H19+'RallyGully | LCR Pune'!H19+'RallyGully | DPSG'!H19+'RallyGully | Gandipath'!H19+'RallyGully | Panchsheel'!H19) -> 99380 | I31: =SUM('RallyGully I Sector 10 Dwarka'!I19+'RallyGully I Sector 83 Gurgaon'!I19+'RallyGully I East of Kailash'!I19+'RallyGully I Sector 19 Dwarka'!I19+'RallyGully | LCR Pune'!I19+'RallyGully | DPSG'!I19+'RallyGully | Gandipath'!I19+'RallyGully | Panchsheel'!I19) -> 79480 | J31: =SUM('RallyGully I Sector 10 Dwarka'!J19+'RallyGully I Sector 83 Gurgaon'!J19+'RallyGully I East of Kailash'!J19+'RallyGully I Sector 19 Dwarka'!J19+'RallyGully | LCR Pune'!J19+'RallyGully | DPSG'!J19+'RallyGully | Gandipath'!J19+'RallyGully | Panchsheel'!J19+'Powerplay Park, Pune'!J19+'Commons, Noida'!J19) -> 141880 | K31: =SUM('RallyGully I Sector 10 Dwarka'!K19+'RallyGully I Sector 83 Gurgaon'!K19+'RallyGully I East of Kailash'!K19+'RallyGully I Sector 19 Dwarka'!K19+'RallyGully | LCR Pune'!K19+'RallyGully | DPSG'!K19+'RallyGully | Gandipath'!K19+'RallyGully | Panchsheel'!K19+'Powerplay Park, Pune'!K19+'Commons, Noida'!K19) -> 109180
A32: 5 | B32: Coaching | C32: =SUM('RallyGully I Sector 10 Dwarka'!C20+'RallyGully I Sector 83 Gurgaon'!C20+'RallyGully I East of Kailash'!C20+'RallyGully I Sector 19 Dwarka'!C20+'RallyGully | LCR Pune'!C20+'RallyGully | DPSG'!C20+'RallyGully | Gandipath'!C20+'RallyGully | Panchsheel'!C20) -> 0 | D32: =SUM('RallyGully I Sector 10 Dwarka'!D20+'RallyGully I Sector 83 Gurgaon'!D20+'RallyGully I East of Kailash'!D20+'RallyGully I Sector 19 Dwarka'!D20+'RallyGully | LCR Pune'!D20+'RallyGully | DPSG'!D20+'RallyGully | Gandipath'!D20+'RallyGully | Panchsheel'!D20) -> 0 | E32: =SUM('RallyGully I Sector 10 Dwarka'!E20+'RallyGully I Sector 83 Gurgaon'!E20+'RallyGully I East of Kailash'!E20+'RallyGully I Sector 19 Dwarka'!E20+'RallyGully | LCR Pune'!E20+'RallyGully | DPSG'!E20+'RallyGully | Gandipath'!E20+'RallyGully | Panchsheel'!E20) -> 0 | F32: =SUM('RallyGully I Sector 10 Dwarka'!F20+'RallyGully I Sector 83 Gurgaon'!F20+'RallyGully I East of Kailash'!F20+'RallyGully I Sector 19 Dwarka'!F20+'RallyGully | LCR Pune'!F20+'RallyGully | DPSG'!F20+'RallyGully | Gandipath'!F20+'RallyGully | Panchsheel'!F20) -> 0 | G32: =SUM('RallyGully I Sector 10 Dwarka'!G20+'RallyGully I Sector 83 Gurgaon'!G20+'RallyGully I East of Kailash'!G20+'RallyGully I Sector 19 Dwarka'!G20+'RallyGully | LCR Pune'!G20+'RallyGully | DPSG'!G20+'RallyGully | Gandipath'!G20+'RallyGully | Panchsheel'!G20) -> 0 | H32: =SUM('RallyGully I Sector 10 Dwarka'!H20+'RallyGully I Sector 83 Gurgaon'!H20+'RallyGully I East of Kailash'!H20+'RallyGully I Sector 19 Dwarka'!H20+'RallyGully | LCR Pune'!H20+'RallyGully | DPSG'!H20+'RallyGully | Gandipath'!H20+'RallyGully | Panchsheel'!H20) -> 0 | I32: =SUM('RallyGully I Sector 10 Dwarka'!I20+'RallyGully I Sector 83 Gurgaon'!I20+'RallyGully I East of Kailash'!I20+'RallyGully I Sector 19 Dwarka'!I20+'RallyGully | LCR Pune'!I20+'RallyGully | DPSG'!I20+'RallyGully | Gandipath'!I20+'RallyGully | Panchsheel'!I20) -> 98000 | J32: =SUM('RallyGully I Sector 10 Dwarka'!J20+'RallyGully I Sector 83 Gurgaon'!J20+'RallyGully I East of Kailash'!J20+'RallyGully I Sector 19 Dwarka'!J20+'RallyGully | LCR Pune'!J20+'RallyGully | DPSG'!J20+'RallyGully | Gandipath'!J20+'RallyGully | Panchsheel'!J20+'Powerplay Park, Pune'!J20+'Commons, Noida'!J20) -> 37500 | K32: =SUM('RallyGully I Sector 10 Dwarka'!K20+'RallyGully I Sector 83 Gurgaon'!K20+'RallyGully I East of Kailash'!K20+'RallyGully I Sector 19 Dwarka'!K20+'RallyGully | LCR Pune'!K20+'RallyGully | DPSG'!K20+'RallyGully | Gandipath'!K20+'RallyGully | Panchsheel'!K20+'Powerplay Park, Pune'!K20+'Commons, Noida'!K20) -> 11500
A33: 6 | B33: Corporate Events | C33: =SUM('RallyGully I Sector 10 Dwarka'!C21+'RallyGully I Sector 83 Gurgaon'!C21+'RallyGully I East of Kailash'!C21+'RallyGully I Sector 19 Dwarka'!C21+'RallyGully | LCR Pune'!C21+'RallyGully | DPSG'!C21+'RallyGully | Gandipath'!C21+'RallyGully | Panchsheel'!C21) -> 0 | D33: =SUM('RallyGully I Sector 10 Dwarka'!D21+'RallyGully I Sector 83 Gurgaon'!D21+'RallyGully I East of Kailash'!D21+'RallyGully I Sector 19 Dwarka'!D21+'RallyGully | LCR Pune'!D21+'RallyGully | DPSG'!D21+'RallyGully | Gandipath'!D21+'RallyGully | Panchsheel'!D21) -> 0 | E33: =SUM('RallyGully I Sector 10 Dwarka'!E21+'RallyGully I Sector 83 Gurgaon'!E21+'RallyGully I East of Kailash'!E21+'RallyGully I Sector 19 Dwarka'!E21+'RallyGully | LCR Pune'!E21+'RallyGully | DPSG'!E21+'RallyGully | Gandipath'!E21+'RallyGully | Panchsheel'!E21) -> 0 | F33: =SUM('RallyGully I Sector 10 Dwarka'!F21+'RallyGully I Sector 83 Gurgaon'!F21+'RallyGully I East of Kailash'!F21+'RallyGully I Sector 19 Dwarka'!F21+'RallyGully | LCR Pune'!F21+'RallyGully | DPSG'!F21+'RallyGully | Gandipath'!F21+'RallyGully | Panchsheel'!F21) -> 5400 | G33: =SUM('RallyGully I Sector 10 Dwarka'!G21+'RallyGully I Sector 83 Gurgaon'!G21+'RallyGully I East of Kailash'!G21+'RallyGully I Sector 19 Dwarka'!G21+'RallyGully | LCR Pune'!G21+'RallyGully | DPSG'!G21+'RallyGully | Gandipath'!G21+'RallyGully | Panchsheel'!G21) -> 0 | H33: =SUM('RallyGully I Sector 10 Dwarka'!H21+'RallyGully I Sector 83 Gurgaon'!H21+'RallyGully I East of Kailash'!H21+'RallyGully I Sector 19 Dwarka'!H21+'RallyGully | LCR Pune'!H21+'RallyGully | DPSG'!H21+'RallyGully | Gandipath'!H21+'RallyGully | Panchsheel'!H21) -> 20680 | I33: =SUM('RallyGully I Sector 10 Dwarka'!I21+'RallyGully I Sector 83 Gurgaon'!I21+'RallyGully I East of Kailash'!I21+'RallyGully I Sector 19 Dwarka'!I21+'RallyGully | LCR Pune'!I21+'RallyGully | DPSG'!I21+'RallyGully | Gandipath'!I21+'RallyGully | Panchsheel'!I21) -> 28730 | J33: =SUM('RallyGully I Sector 10 Dwarka'!J21+'RallyGully I Sector 83 Gurgaon'!J21+'RallyGully I East of Kailash'!J21+'RallyGully I Sector 19 Dwarka'!J21+'RallyGully | LCR Pune'!J21+'RallyGully | DPSG'!J21+'RallyGully | Gandipath'!J21+'RallyGully | Panchsheel'!J21+'Powerplay Park, Pune'!J21+'Commons, Noida'!J21) -> 11880 | K33: =SUM('RallyGully I Sector 10 Dwarka'!K21+'RallyGully I Sector 83 Gurgaon'!K21+'RallyGully I East of Kailash'!K21+'RallyGully I Sector 19 Dwarka'!K21+'RallyGully | LCR Pune'!K21+'RallyGully | DPSG'!K21+'RallyGully | Gandipath'!K21+'RallyGully | Panchsheel'!K21+'Powerplay Park, Pune'!K21+'Commons, Noida'!K21) -> 10520
A34: 7 | B34: Brand Activation | C34: =SUM('RallyGully I Sector 10 Dwarka'!C22+'RallyGully I Sector 83 Gurgaon'!C22+'RallyGully I East of Kailash'!C22+'RallyGully I Sector 19 Dwarka'!C22+'RallyGully | LCR Pune'!C22+'RallyGully | DPSG'!C22+'RallyGully | Gandipath'!C22+'RallyGully | Panchsheel'!C22) -> 0 | D34: =SUM('RallyGully I Sector 10 Dwarka'!D22+'RallyGully I Sector 83 Gurgaon'!D22+'RallyGully I East of Kailash'!D22+'RallyGully I Sector 19 Dwarka'!D22+'RallyGully | LCR Pune'!D22+'RallyGully | DPSG'!D22+'RallyGully | Gandipath'!D22+'RallyGully | Panchsheel'!D22) -> 0 | E34: =SUM('RallyGully I Sector 10 Dwarka'!E22+'RallyGully I Sector 83 Gurgaon'!E22+'RallyGully I East of Kailash'!E22+'RallyGully I Sector 19 Dwarka'!E22+'RallyGully | LCR Pune'!E22+'RallyGully | DPSG'!E22+'RallyGully | Gandipath'!E22+'RallyGully | Panchsheel'!E22) -> 0 | F34: =SUM('RallyGully I Sector 10 Dwarka'!F22+'RallyGully I Sector 83 Gurgaon'!F22+'RallyGully I East of Kailash'!F22+'RallyGully I Sector 19 Dwarka'!F22+'RallyGully | LCR Pune'!F22+'RallyGully | DPSG'!F22+'RallyGully | Gandipath'!F22+'RallyGully | Panchsheel'!F22) -> 15000 | G34: =SUM('RallyGully I Sector 10 Dwarka'!G22+'RallyGully I Sector 83 Gurgaon'!G22+'RallyGully I East of Kailash'!G22+'RallyGully I Sector 19 Dwarka'!G22+'RallyGully | LCR Pune'!G22+'RallyGully | DPSG'!G22+'RallyGully | Gandipath'!G22+'RallyGully | Panchsheel'!G22) -> 4480 | H34: =SUM('RallyGully I Sector 10 Dwarka'!H22+'RallyGully I Sector 83 Gurgaon'!H22+'RallyGully I East of Kailash'!H22+'RallyGully I Sector 19 Dwarka'!H22+'RallyGully | LCR Pune'!H22+'RallyGully | DPSG'!H22+'RallyGully | Gandipath'!H22+'RallyGully | Panchsheel'!H22) -> 23313 | I34: =SUM('RallyGully I Sector 10 Dwarka'!I22+'RallyGully I Sector 83 Gurgaon'!I22+'RallyGully I East of Kailash'!I22+'RallyGully I Sector 19 Dwarka'!I22+'RallyGully | LCR Pune'!I22+'RallyGully | DPSG'!I22+'RallyGully | Gandipath'!I22+'RallyGully | Panchsheel'!I22) -> 24100 | J34: =SUM('RallyGully I Sector 10 Dwarka'!J22+'RallyGully I Sector 83 Gurgaon'!J22+'RallyGully I East of Kailash'!J22+'RallyGully I Sector 19 Dwarka'!J22+'RallyGully | LCR Pune'!J22+'RallyGully | DPSG'!J22+'RallyGully | Gandipath'!J22+'RallyGully | Panchsheel'!J22+'Powerplay Park, Pune'!J22+'Commons, Noida'!J22) -> 30000 | K34: =SUM('RallyGully I Sector 10 Dwarka'!K22+'RallyGully I Sector 83 Gurgaon'!K22+'RallyGully I East of Kailash'!K22+'RallyGully I Sector 19 Dwarka'!K22+'RallyGully | LCR Pune'!K22+'RallyGully | DPSG'!K22+'RallyGully | Gandipath'!K22+'RallyGully | Panchsheel'!K22+'Powerplay Park, Pune'!K22+'Commons, Noida'!K22) -> 28000
A35: 8 | B35: Other Income | C35: =SUM('RallyGully I Sector 10 Dwarka'!C23+'RallyGully I Sector 83 Gurgaon'!C23+'RallyGully I East of Kailash'!C23+'RallyGully I Sector 19 Dwarka'!C23+'RallyGully | LCR Pune'!C23+'RallyGully | DPSG'!C23+'RallyGully | Gandipath'!C23+'RallyGully | Panchsheel'!C23) -> 0 | D35: =SUM('RallyGully I Sector 10 Dwarka'!D23+'RallyGully I Sector 83 Gurgaon'!D23+'RallyGully I East of Kailash'!D23+'RallyGully I Sector 19 Dwarka'!D23+'RallyGully | LCR Pune'!D23+'RallyGully | DPSG'!D23+'RallyGully | Gandipath'!D23+'RallyGully | Panchsheel'!D23) -> 0 | E35: =SUM('RallyGully I Sector 10 Dwarka'!E23+'RallyGully I Sector 83 Gurgaon'!E23+'RallyGully I East of Kailash'!E23+'RallyGully I Sector 19 Dwarka'!E23+'RallyGully | LCR Pune'!E23+'RallyGully | DPSG'!E23+'RallyGully | Gandipath'!E23+'RallyGully | Panchsheel'!E23) -> 0 | F35: =SUM('RallyGully I Sector 10 Dwarka'!F23+'RallyGully I Sector 83 Gurgaon'!F23+'RallyGully I East of Kailash'!F23+'RallyGully I Sector 19 Dwarka'!F23+'RallyGully | LCR Pune'!F23+'RallyGully | DPSG'!F23+'RallyGully | Gandipath'!F23+'RallyGully | Panchsheel'!F23) -> 18000 | G35: =SUM('RallyGully I Sector 10 Dwarka'!G23+'RallyGully I Sector 83 Gurgaon'!G23+'RallyGully I East of Kailash'!G23+'RallyGully I Sector 19 Dwarka'!G23+'RallyGully | LCR Pune'!G23+'RallyGully | DPSG'!G23+'RallyGully | Gandipath'!G23+'RallyGully | Panchsheel'!G23) -> 25000 | H35: =SUM('RallyGully I Sector 10 Dwarka'!H23+'RallyGully I Sector 83 Gurgaon'!H23+'RallyGully I East of Kailash'!H23+'RallyGully I Sector 19 Dwarka'!H23+'RallyGully | LCR Pune'!H23+'RallyGully | DPSG'!H23+'RallyGully | Gandipath'!H23+'RallyGully | Panchsheel'!H23) -> 29300 | I35: =SUM('RallyGully I Sector 10 Dwarka'!I23+'RallyGully I Sector 83 Gurgaon'!I23+'RallyGully I East of Kailash'!I23+'RallyGully I Sector 19 Dwarka'!I23+'RallyGully | LCR Pune'!I23+'RallyGully | DPSG'!I23+'RallyGully | Gandipath'!I23+'RallyGully | Panchsheel'!I23) -> 138000 | J35: =SUM('RallyGully I Sector 10 Dwarka'!J23+'RallyGully I Sector 83 Gurgaon'!J23+'RallyGully I East of Kailash'!J23+'RallyGully I Sector 19 Dwarka'!J23+'RallyGully | LCR Pune'!J23+'RallyGully | DPSG'!J23+'RallyGully | Gandipath'!J23+'RallyGully | Panchsheel'!J23+'Powerplay Park, Pune'!J23+'Commons, Noida'!J23) -> 197000 | K35: =SUM('RallyGully I Sector 10 Dwarka'!K23+'RallyGully I Sector 83 Gurgaon'!K23+'RallyGully I East of Kailash'!K23+'RallyGully I Sector 19 Dwarka'!K23+'RallyGully | LCR Pune'!K23+'RallyGully | DPSG'!K23+'RallyGully | Gandipath'!K23+'RallyGully | Panchsheel'!K23+'Powerplay Park, Pune'!K23+'Commons, Noida'!K23) -> 256000
B36: Total Gross Revenue | C36: =sum(C15+C20+C26+C31+C32+C33+C34+C35) -> 103615 | D36: =sum(D15+D20+D26+D31+D32+D33+D34+D35) -> 336259 | E36: =sum(E15+E20+E26+E31+E32+E33+E34+E35) -> 478873.8 | F36: =sum(F15+F20+F26+F31+F32+F33+F34+F35) -> 542592.6 | G36: =sum(G15+G20+G26+G31+G32+G33+G34+G35) -> 581843 | H36: =sum(H15+H20+H26+H31+H32+H33+H34+H35) -> 754429 | I36: =sum(I15+I20+I26+I31+I32+I33+I34+I35) -> 1501552 | J36: =sum(J15+J20+J26+J31+J32+J33+J34+J35) -> 1713558 | K36: =sum(K15+K20+K26+K31+K32+K33+K34+K35) -> 2062032
B38: Verticle Vise | C38: July | D38: August | E38: September | F38: October | G38: November | H38: December | I38: January | J38: February | K38: March
A39: 1 | B39: Offline | C39: =C15/$C$36 -> 0.046663128 | D39: =D15/$D$36 -> 0.15178776 | E39: =E15/$E$36 -> 0.29135025 | F39: =F15/$F$36 -> 0.13498157 | G39: =G15/$G$36 -> 0.30161745 | H39: =H15/$H$36 -> 0.35723971 | I39: =I15/$I$36 -> 0.32058097 | J39: =J15/$J$36 -> 0.30093816 | K39: =K15/$K$36 -> 0.25645334
A40: 1.1 | B40: Rentals | C40: =C16/$C$36 -> 0.043188728 | D40: =D16/$D$36 -> 0.046333332 | E40: =E16/$E$36 -> 0.046525828 | F40: =F16/$F$36 -> 0.045780204 | G40: =G16/$G$36 -> 0.047813585 | H40: =H16/$H$36 -> 0.080557614 | I40: =I16/$I$36 -> 0.060829728 | J40: =J16/$J$36 -> 0.055046284 | K40: =K16/$K$36 -> 0.03987814
A41: 1.2 | B41: F&B | C41: =C17/$C$36 -> 0.0034744004 | D41: =D17/$D$36 -> 0.0057098843 | E41: =E17/$E$36 -> 0.0091882245 | F41: =F17/$F$36 -> 0.0045890784 | G41: =G17/$G$36 -> 0.0032482989 | H41: =H17/$H$36 -> 0.0069721604 | I41: =I17/$I$36 -> 0.0027005392 | J41: =J17/$J$36 -> 0.0031775989 | K41: =K17/$K$36 -> 0.0018549664
A42: 1.3 | B42: Product Sales | C42: =C18/$C$36 -> 0 | D42: =D18/$D$36 -> 0 | E42: =E18/$E$36 -> 0.025163206 | F42: =F18/$F$36 -> 0 | G42: =G18/$G$36 -> 0 | H42: =H18/$H$36 -> 0 | I42: =I18/$I$36 -> 0.011987597 | J42: =J18/$J$36 -> 0 | K42: =K18/$K$36 -> 0
A43: 1.4 | B43: Bookings | C43: =C19/$C$36 -> 0 | D43: =D19/$D$36 -> 0.099744542 | E43: =E19/$E$36 -> 0.21047299 | F43: =F19/$F$36 -> 0.075028668 | G43: =G19/$G$36 -> 0.25055556 | H43: =H19/$H$36 -> 0.26970994 | I43: =I19/$I$36 -> 0.24506311 | J43: =J19/$J$36 -> 0.24271428 | K43: =K19/$K$36 -> 0.19906335
A44: 2 | B44: Online: Third Party Platform | C44: =C20/$C$36 -> 0.85200019 | D44: =D20/$D$36 -> 0.65465014 | E44: =E20/$E$36 -> 0.59068548 | F44: =F20/$F$36 -> 0.55163414 | G44: =G20/$G$36 -> 0.45068687 | H44: =H20/$H$36 -> 0.37264607 | I44: =I20/$I$36 -> 0.34659739 | J44: =J20/$J$36 -> 0.35196299 | K44: =K20/$J$36 -> 0.50287939
A45: 2.1 | B45: Hudle | C45: =C21/$C$36 -> 0.70877769 | D45: =D21/$D$36 -> 0.48373426 | E45: =E21/$E$36 -> 0.50963532 | F45: =F21/$F$36 -> 0.47465631 | G45: =G21/$G$36 -> 0.34628757 | H45: =H21/$H$36 -> 0.23015155 | I45: =I21/$I$36 -> 0.1754851 | J45: =J21/$J$36 -> 0.15394985 | K45: =K21/$J$36 -> 0.22056038
A46: 2.2 | B46: Playo | C46: =C22/$C$36 -> 0.14322251 | D46: =D22/$D$36 -> 0.13914869 | E46: =E22/$E$36 -> 0.068199179 | F46: =F22/$F$36 -> 0.055414689 | G46: =G22/$G$36 -> 0.046928467 | H46: =H22/$H$36 -> 0.060412577 | I46: =I22/$I$36 -> 0.061947239 | J46: =J22/$J$36 -> 0.051065094 | K46: =K22/$J$36 -> 0.071987642
A47: 2.3 | B47: District | C47: =C23/$C$36 -> 0 | D47: =D23/$D$36 -> 0 | E47: =E23/$E$36 -> 0 | F47: =F23/$F$36 -> 0.0022116041 | G47: =G23/$G$36 -> 0.0053382098 | H47: =H23/$H$36 -> 0.02405793 | I47: =I23/$I$36 -> 0.067363634 | J47: =J23/$J$36 -> 0.095473862 | K47: =K23/$J$36 -> 0.12231859
A48: 2.4 | B48: Khelomore | C48: =C24/$C$36 -> 0 | D48: =D24/$D$36 -> 0.031767179 | E48: =E24/$E$36 -> 0.012850985 | F48: =F24/$F$36 -> 0.019351536 | G48: =G24/$G$36 -> 0.05213262 | H48: =H24/$H$36 -> 0.056367133 | I48: =I24/$I$36 -> 0.024903566 | J48: =J24/$J$36 -> 0.027746945 | K48: =K24/$J$36 -> 0.032499629
A49: 2.5 | B49: Zplys | C49: =C25/$C$36 -> 0 | D49: =D25/$D$36 -> 0 | E49: =E25/$E$36 -> 0 | F49: =F25/$F$36 -> 0 | G49: =G25/$G$36 -> 0 | H49: =H25/$H$36 -> 0.0016568822 | I49: =I25/$I$36 -> 0.01689785 | J49: =J25/$J$36 -> 0.023727239 | K49: =K25/$J$36 -> 0.055513149
A50: 3 | B50: Community | C50: =C26/$C$36 -> 0.10133668 | D50: =D26/$D$36 -> 0.044867201 | E50: =E26/$E$36 -> 0.061581987 | F50: =F26/$F$36 -> 0.074346757 | G50: =G26/$G$36 -> 0.069193923 | H50: =H26/$H$36 -> 0.041235159 | I50: =I26/$I$36 -> 0.08753543 | J50: =J26/$J$36 -> 0.10301023 | K50: =K26/$J$36 -> 0.14957416
A51: 3.1 | B51: Courtly (Organized by RallyGully) | C51: =C27/$C$36 -> 0 | D51: =D27/$D$36 -> 0 | E51: =E27/$E$36 -> 0 | F51: =F27/$F$36 -> 0 | G51: =G27/$G$36 -> 0.014608752 | H51: =H27/$H$36 -> 0 | I51: =I27/$I$36 -> 0.025506942 | J51: =J27/$J$36 -> 0.032213675 | K51: =K27/$J$36 -> 0
A52: 3.2 | B52: Sportomic (Organized by RallyGully) | C52: =C28/$C$36 -> 0 | D52: =D28/$D$36 -> 0 | E52: =E28/$E$36 -> 0 | F52: =F28/$F$36 -> 0 | G52: =G28/$G$36 -> 0 | H52: =H28/$H$36 -> 0.03087103 | I52: =I28/$I$36 -> 0.0090905943 | J52: =J28/$J$36 -> 0.024720494 | K52: =K28/$J$36 -> 0
A53: 3.3 | B53: Rallygully Community games | C53: =C29/$C$36 -> 0.10133668 | D53: =D29/$D$36 -> 0.044867201 | E53: =E29/$E$36 -> 0.041555834 | F53: =F29/$F$36 -> 0.052249146 | G53: =G29/$G$36 -> 0.035714102 | H53: =H29/$H$36 -> 0.0033270195 | I53: =I29/$I$36 -> 0.052937894 | J53: =J29/$J$36 -> 0.036926092 | K53: =K29/$J$36 -> 0
A54: 3.4 | B54: Misfits Community | C54: =C30/$C$36 -> 0 | D54: =D30/$D$36 -> 0 | E54: =E30/$E$36 -> 0.020026153 | F54: =F30/$F$36 -> 0.022097611 | G54: =G30/$G$36 -> 0.01887107 | H54: =H30/$H$36 -> 0.0070371102 | I54: =I30/$I$36 -> 0 | J54: =J30/$J$36 -> 0.0091499675 | K54: =K30/$J$36 -> 0
A55: 4 | B55: Memberships | C55: =C31/$C$36 -> 0 | D55: =D31/$D$36 -> 0.1486949 | E55: =E31/$E$36 -> 0.056382287 | F55: =F31/$F$36 -> 0.16826621 | G55: =G31/$G$36 -> 0.12783517 | H55: =H31/$H$36 -> 0.13172876 | I55: =I31/$I$36 -> 0.0529319 | J55: =J31/$J$36 -> 0.082798481 | K55: =K31/$J$36 -> 0.063715381
... A59: 8 | B59: Other Income | C59: =C35/$C$36 -> 0 | D59: =D35/$D$36 -> 0 | E59: =E35/$E$36 -> 0 | F59: =F35/$F$36 -> 0.033174061 | G59: =G35/$G$36 -> 0.042966917 | H59: =H35/$H$36 -> 0.038837319 | I59: =I35/$I$36 -> 0.091904909 | J59: =J35/$J$36 -> 0.11496547 | K59: =K35/$J$36 -> 0.14939675
B60: Total Gross Revenue | C60: =C39+C44+C50+C55+C56+C57+C58+C59 -> 1 | D60: =D39+D44+D50+D55+D56+D57+D58+D59 -> 1 | E60: =E39+E44+E50+E55+E56+E57+E58+E59 -> 1 | F60: =F39+F44+F50+F55+F56+F57+F58+F59 -> 1 | G60: =G39+G44+G50+G55+G56+G57+G58+G59 -> 1 | H60: =H39+H44+H50+H55+H56+H57+H58+H59 -> 1 | I60: =I39+I44+I50+I55+I56+I57+I58+I59 -> 1 | J60: =J39+J44+J50+J55+J56+J57+J58+J59 -> 1
