Workbook

Sheet Summary
B2: 1 - 31 July
B3: Particulars | C3: Amount
C4: Pickleball
B5: Pay & Play | C5: =sum(C6,C12) -> 62050
B6: Online | C6: =sum(C7:C11) -> 9450
B7: District | C7: =District!C4 -> 3450
B8: Hudle | C8: =Hudle!C3 -> 6000
B9: Playo | C9: 0
B10: Khelomore | C10: 0
B11: Zplys | C11: 0
B12: Offline | C12: =sum(C13:C14) -> 52600
B13: Bookings | C13: ='Offline & RG Community'!D33 -> 52600
B14: Memberships | C14: 0
B15: Community | C15: =sum(C16:C17) -> 20000
B16: Pickup games | C16: ='Offline & RG Community'!E33 -> 20000
B17: Social Events/Tournaments | C17: 0
B18: Academy | C18: 0
B19: Events & Partnership | C19: =sum(C20,C21) -> 9800
B20: Corporate events | C20: =B2B!E4 -> 9800
B21: All B2B partnerships | C21: 0
B22: Commerce | C22: =sum(C23:C25) -> 0
B23: Product rental | C23: 0
B24: Product sales | C24: 0
B25: F&B | C25: 0
B26: Other Income | C26: 0
B27: Total Gross Revenue | C27: =C6+C12+C15+C18+C19+C22+C26 -> 91850
B28: Total Net Revenue (Post Commissions) | C28: ='Offline & RG Community'!H33+District!F4+B2B!E4+Hudle!E3 -> 89995.5
B29: Total Revenue post GST | C29: =(C27/1.18)-(C27-C28) -> 75984.483
B31: Expenses
B32: VM Salary
B33: Support Staff
B34: Marketing, Branding & Community
B35: Balls
B37: Net Profit | C37: =C29-(sum(C32:C35)) -> 75984.483

Sheet Offline & RG Community
A1: Date | B1: Day | C1: Offline booking hours | D1: Booking Revenue (Turf) | E1: Community Revenue | F1: Total Revenue | G1: Payment Gateway | H1: Net Revenue
A2: 46204 | B2: Wednesday | C2: 1 | D2: 1200 | E2: 0 | F2: =sum(D2:E2) -> 1200 | G2: =F2*1.75% -> 21 | H2: =F2-G2 -> 1179
A3: 46205 | B3: Thursday | C3: 2 | D3: 2400 | E3: 0 | F3: =sum(D3:E3) -> 2400 | G3: =F3*1.75% -> 42 | H3: =F3-G3 -> 2358
A4: 46206 | B4: Friday | C4: 3 | D4: 3900 | E4: 0 | F4: =sum(D4:E4) -> 3900 | G4: =F4*1.75% -> 68.25 | H4: =F4-G4 -> 3831.75
A5: 46207 | B5: Saturday | C5: 3 | D5: 3500 | E5: 0 | F5: =sum(D5:E5) -> 3500 | G5: =F5*1.75% -> 61.25 | H5: =F5-G5 -> 3438.75
A6: 46208 | B6: Sunday | C6: 2 | D6: 5000 | E6: 0 | F6: =sum(D6:E6) -> 5000 | G6: =F6*1.75% -> 87.5 | H6: =F6-G6 -> 4912.5
A7: 46209 | B7: Monday | C7: 0 | D7: 0 | E7: 0 | F7: =sum(D7:E7) -> 0 | G7: =F7*1.75% -> 0 | H7: =F7-G7 -> 0
A8: 46210 | B8: Tuesday | C8: 1 | D8: 1600 | E8: 0 | F8: =sum(D8:E8) -> 1600 | G8: =F8*1.75% -> 28 | H8: =F8-G8 -> 1572
A9: 46211 | B9: Wednesday | C9: 1 | D9: 1500 | E9: 0 | F9: =sum(D9:E9) -> 1500 | G9: =F9*1.75% -> 26.25 | H9: =F9-G9 -> 1473.75
A10: 46212 | B10: Thursday | C10: 1 | D10: 1200 | E10: 0 | F10: =sum(D10:E10) -> 1200 | G10: =F10*1.75% -> 21 | H10: =F10-G10 -> 1179
A11: 46213 | B11: Friday | C11: 2 | D11: 2200 | E11: 0 | F11: =sum(D11:E11) -> 2200 | G11: =F11*1.75% -> 38.5 | H11: =F11-G11 -> 2161.5
A12: 46214 | B12: Saturday | C12: 1 | D12: 1600 | E12: 0 | F12: =sum(D12:E12) -> 1600 | G12: =F12*1.75% -> 28 | H12: =F12-G12 -> 1572
A13: 46215 | B13: Sunday | C13: 10.5 | D13: 6500 | E13: 0 | F13: =sum(D13:E13) -> 6500 | G13: =F13*1.75% -> 113.75 | H13: =F13-G13 -> 6386.25
... A32: 46234 | B32: Friday | C32: 2 | D32: 2400 | E32: 1500 | F32: =sum(D32:E32) -> 3900 | G32: =F32*1.75% -> 68.25 | H32: =F32-G32 -> 3831.75
A33: Total | D33: =SUM(D1:D32) -> 52600 | E33: =SUM(E1:E32) -> 20000 | F33: =SUM(F1:F32) -> 72600 | G33: =SUM(G1:G32) -> 1270.5 | H33: =SUM(H1:H32) -> 71329.5

Sheet District
A1: Link | B1: Date | C1: Paid to District | D1: Commissions (₹) | E1: GST on Commission | F1: Net Revenue | G1: TCS | H1: TDS | I1: Final Amount (₹)
B2: 1 - 31 July | C2: 3450 | D2: 241 | E2: 43 | F2: =C2-D2-E2 -> 3166 | G2: 17 | H2: 3 | I2: =F2-G2-H2 -> 3146
B4: Total | C4: =SUM(C2:C3) -> 3450 | F4: =SUM(F2:F3) -> 3166 | I4: =SUM(I2:I3) -> 3146

Sheet Hudle
A1: Link | B1: Date | C1: Paid to Hudle | D1: Commisions (Including GST) | E1: Net Revenue | F1: TDS | G1: TCS | H1: Amount
B2: 1 - 31 July | C2: 6000 | D2: 300 | E2: =C2-D2 -> 5700 | F2: 5 | G2: 0 | H2: =E2-F2 -> 5695
B3: Total | C3: =SUM(C2) -> 6000 | E3: =SUM(E2) -> 5700 | H3: =SUM(H2) -> 5695

Sheet B2B
A1: Date | B1: Brand | C1: Type | D1: Deliverables | E1: Amt
A2: July | B2: Clash Sports | C2: Football Tournament | D2: 12 hours of turf | E2: 6000
A3: July | B3: Clash Sports | C3: Football Tournament | D3: Energy Drinks | E3: 3800
A4: Total | E4: =SUM(E2,E3) -> 9800
