Workbook

Sheet Summary
B2: 1 - 31 Aug
B3: Particulars | C3: Amount
C4: Pickleball
B5: Pay & Play | C5: =sum(C6,C12) -> 130433
B6: Online | C6: =sum(C7:C11) -> 100710
B7: District | C7: =District!C4 -> 100710
B8: Hudle | C8: 0
B9: Playo | C9: 0
B10: Khelomore | C10: 0
B11: Zplys | C11: 0
B12: Offline | C12: =sum(C13:C14) -> 29723
B13: Bookings | C13: ='Offline & RG Community'!D33 -> 29723
B14: Memberships | C14: 0
B15: Community | C15: =sum(C16:C18) -> 111860
B16: Pickup games | C16: ='Offline & RG Community'!F33 -> 58050
B17: Social Events/Tournaments | C17: ='Social EventsTournaments'!D4 -> 8500
B18: Community Partnerships | C18: ='Offline & RG Community'!E33 -> 45310
B19: Academy | C19: =Academy!C2 -> 6500
B20: B2B | C20: =sum(C21,C22) -> 5950
B21: Corporate events | C21: ='Corporate Events'!E4 -> 5950
B22: All B2B partnerships | C22: 0
B23: Commerce | C23: =sum(C24:C26) -> 9630
B24: Product rental | C24: ='Offline & RG Community'!G33 -> 7175
B25: Product sales | C25: 0
B26: F&B | C26: ='F&B'!B33 -> 2455
B27: Other Income | C27: 0
B28: Total Gross Revenue | C28: =C5+C15+C19+C20+C23+C27 -> 264373
B29: GST (B) | C29: =C28-(C28/1.18) -> 40328.085
B30: Commissions, Payment gateway & Event Expense(C) | C30: ='Offline & RG Community'!I33+'F&B'!C33+'F&B'!E33+District!D4+District!E4+'Social EventsTournaments'!E4+'Social EventsTournaments'!F4+'Social EventsTournaments'!G4+Academy!D2+'Corporate Events'!F4 -> 13784.878
B31: Net Revenue (A-B-C) | C31: =C28-C29-C30 -> 210260.04

Sheet Offline & RG Community
A1: Date | B1: Day | C1: Offline booking hours | D1: Booking Revenue | E1: Community Partnership | F1: Community Revenue | G1: Paddle Rental | H1: Total Revenue | I1: Payment Gateway | J1: Net Revenue
A2: 46235 | B2: Saturday | C2: 2.5 | D2: 1740 | E2: 0 | F2: 1000 | G2: 150 | H2: =sum(D2:G2) -> 2890 | I2: =H2*1.75% -> 50.575 | J2: =H2-I2 -> 2839.425
A3: 46236 | B3: Sunday | C3: 0.5 | D3: 400 | E3: 0 | F3: 3050 | G3: 150 | H3: =sum(D3:G3) -> 3600 | I3: =H3*1.75% -> 63 | J3: =H3-I3 -> 3537
A4: 46237 | B4: Monday | C4: 3 | D4: 2080 | E4: 0 | F4: 2600 | G4: 150 | H4: =sum(D4:G4) -> 4830 | I4: =H4*1.75% -> 84.525 | J4: =H4-I4 -> 4745.475
A5: 46238 | B5: Tuesday | C5: 1 | D5: 720 | E5: 2040 | F5: 800 | G5: 150 | H5: =sum(D5:G5) -> 3710 | I5: =H5*1.75% -> 64.925 | J5: =H5-I5 -> 3645.075
A6: 46239 | B6: Wednesday | C6: 2.5 | D6: 1919 | E6: 680 | F6: 600 | G6: 925 | H6: =sum(D6:G6) -> 4124 | I6: =H6*1.75% -> 72.17 | J6: =H6-I6 -> 4051.83
A7: 46240 | B7: Thursday | C7: 1 | D7: 720 | E7: 2720 | F7: 2800 | G7: 100 | H7: =sum(D7:G7) -> 6340 | I7: =H7*1.75% -> 110.95 | J7: =H7-I7 -> 6229.05
A8: 46241 | B8: Friday | C8: 0 | D8: 0 | E8: 0 | F8: 0 | G8: 0 | H8: =sum(D8:G8) -> 0 | I8: =H8*1.75% -> 0 | J8: =H8-I8 -> 0
A9: 46242 | B9: Saturday | C9: 3.5 | D9: 2500 | E9: 3150 | F9: 3200 | G9: 700 | H9: =sum(D9:G9) -> 9550 | I9: =H9*1.75% -> 167.125 | J9: =H9-I9 -> 9382.875
A10: 46243 | B10: Sunday | C10: 1 | D10: 720 | E10: 0 | F10: 2800 | G10: 250 | H10: 0 | I10: =H10*1.75% -> 0 | J10: =H10-I10 -> 0
A11: 46244 | B11: Monday | C11: 1.5 | D11: 1120 | E11: 680 | F11: 2800 | G11: 100 | H11: =sum(D11:G11) -> 4700 | I11: =H11*1.75% -> 82.25 | J11: =H11-I11 -> 4617.75
A12: 46245 | B12: Tuesday | C12: 0 | D12: 0 | E12: 680 | F12: 3200 | G12: 200 | H12: =sum(D12:G12) -> 4080 | I12: =H12*1.75% -> 71.4 | J12: =H12-I12 -> 4008.6
A13: 46246 | B13: Wednesday | C13: 1 | D13: 720 | E13: 2380 | F13: 1200 | G13: 0 | H13: =sum(D13:G13) -> 4300 | I13: =H13*1.75% -> 75.25 | J13: =H13-I13 -> 4224.75
A14: 46247 | B14: Thursday | C14: 5.5 | D14: 720 | E14: 1020 | F14: 2000 | G14: 225 | H14: =sum(D14:G14) -> 3965 | I14: =H14*1.75% -> 69.3875 | J14: =H14-I14 -> 3895.6125
A15: 46248 | B15: Friday | C15: 9 | D15: 1727 | E15: 2360 | F15: 2400 | G15: 200 | H15: =sum(D15:G15) -> 6687 | I15: =H15*1.75% -> 117.0225 | J15: =H15-I15 -> 6569.9775
A16: 46249 | B16: Saturday | C16: 7 | D16: 1197 | E16: 1020 | F16: 1960 | G16: 700 | H16: =sum(D16:G16) -> 4877 | I16: =H16*1.75% -> 85.3475 | J16: =H16-I16 -> 4791.6525
A17: 46250 | B17: Sunday | C17: 6 | D17: 0 | E17: 1360 | F17: 2920 | G17: 450 | H17: =sum(D17:G17) -> 4730 | I17: =H17*1.75% -> 82.775 | J17: =H17-I17 -> 4647.225
A18: 46251 | B18: Monday | C18: 6 | D18: 720 | E18: 1360 | F18: 2200 | G18: 150 | H18: =sum(D18:G18) -> 4430 | I18: =H18*1.75% -> 77.525 | J18: =H18-I18 -> 4352.475
A19: 46252 | B19: Tuesday | C19: 4 | D19: 720 | E19: 1360 | F19: 400 | G19: 0 | H19: =sum(D19:G19) -> 2480 | I19: =H19*1.75% -> 43.4 | J19: =H19-I19 -> 2436.6
A20: 46253 | B20: Wednesday | C20: 7 | D20: 1920 | E20: 3060 | F20: 800 | G20: 150 | H20: =sum(D20:G20) -> 5930 | I20: =H20*1.75% -> 103.775 | J20: =H20-I20 -> 5826.225
A21: 46254 | B21: Thursday | C21: 7.5 | D21: 720 | E21: 2380 | F21: 2000 | G21: 150 | H21: =sum(D21:G21) -> 5250 | I21: =H21*1.75% -> 91.875 | J21: =H21-I21 -> 5158.125
A22: 46255 | B22: Friday | C22: 7.5 | D22: 0 | E22: 3060 | F22: 2320 | G22: 350 | H22: =sum(D22:G22) -> 5730 | I22: =H22*1.75% -> 100.275 | J22: =H22-I22 -> 5629.725
... A32: 46265 | B32: Monday | C32: 3 | D32: 0 | E32: 2040 | F32: 1200 | G32: 0 | H32: =sum(D32:G32) -> 3240 | I32: =H32*1.75% -> 56.7 | J32: =H32-I32 -> 3183.3
A33: Total | D33: =SUM(D2:D32) -> 29723 | E33: =SUM(E2:E32) -> 45310 | F33: =SUM(F2:F32) -> 58050 | G33: =SUM(G2:G32) -> 7175 | H33: =SUM(H2:H32) -> 136488 | I33: =SUM(I2:I32) -> 2388.54 | J33: =SUM(J1:J32) -> 134099.46

Sheet F&B
A1: Date | B1: F&B | C1: Paid to brand (75%) | D1: Our Margin (25%) | E1: Payment Gateway | F1: Net Revenue
A2: 46235 | B2: 0 | C2: =B2*75% -> 0 | D2: =B2*25% -> 0 | E2: =B2*1.75% -> 0 | F2: =D2-E2 -> 0
A3: 46236 | B3: 35 | C3: =B3*75% -> 26.25 | D3: =B3*25% -> 8.75 | E3: =B3*1.75% -> 0.6125 | F3: =D3-E3 -> 8.1375
A4: 46237 | B4: 0 | C4: =B4*75% -> 0 | D4: =B4*25% -> 0 | E4: =B4*1.75% -> 0 | F4: =D4-E4 -> 0
A5: 46238 | B5: 0 | C5: =B5*75% -> 0 | D5: =B5*25% -> 0 | E5: =B5*1.75% -> 0 | F5: =D5-E5 -> 0
A6: 46239 | B6: 0 | C6: =B6*75% -> 0 | D6: =B6*25% -> 0 | E6: =B6*1.75% -> 0 | F6: =D6-E6 -> 0
A7: 46240 | B7: 0 | C7: =B7*75% -> 0 | D7: =B7*25% -> 0 | E7: =B7*1.75% -> 0 | F7: =D7-E7 -> 0
A8: 46241 | B8: 0 | C8: =B8*75% -> 0 | D8: =B8*25% -> 0 | E8: =B8*1.75% -> 0 | F8: =D8-E8 -> 0
A9: 46242 | B9: 0 | C9: =B9*75% -> 0 | D9: =B9*25% -> 0 | E9: =B9*1.75% -> 0 | F9: =D9-E9 -> 0
A10: 46243 | B10: 0 | C10: =B10*75% -> 0 | D10: =B10*25% -> 0 | E10: =B10*1.75% -> 0 | F10: =D10-E10 -> 0
A11: 46244 | B11: 0 | C11: =B11*75% -> 0 | D11: =B11*25% -> 0 | E11: =B11*1.75% -> 0 | F11: =D11-E11 -> 0
A12: 46245 | B12: 0 | C12: =B12*75% -> 0 | D12: =B12*25% -> 0 | E12: =B12*1.75% -> 0 | F12: =D12-E12 -> 0
A13: 46246 | B13: 0 | C13: =B13*75% -> 0 | D13: =B13*25% -> 0 | E13: =B13*1.75% -> 0 | F13: =D13-E13 -> 0
... A32: 46265 | B32: 210 | C32: =B32*75% -> 157.5 | D32: =B32*25% -> 52.5 | E32: =B32*1.75% -> 3.675 | F32: =D32-E32 -> 48.825
A33: Total | B33: =SUM(B2:B32) -> 2455 | C33: =SUM(C2:C32) -> 1841.25 | D33: =SUM(D2:D32) -> 613.75 | E33: =SUM(E2:E32) -> 42.9625 | F33: =SUM(F2:F32) -> 570.7875

Sheet District
A1: Link | B1: Date | C1: Paid to District | D1: Commissions (₹) | E1: GST on Commission | F1: Net Revenue | G1: TCS | H1: TDS | I1: Final Amount (₹)
B2: 1 - 31 Aug | C2: 100710 | D2: 7478 | E2: 1345 | F2: =C2-D2-E2 -> 91887 | G2: 534 | H2: 107 | I2: =F2-G2-H2 -> 91246
B4: Total | C4: =SUM(C2:C3) -> 100710 | D4: =SUM(D2:D3) -> 7478 | E4: =SUM(E2:E3) -> 1345 | F4: =SUM(F2:F3) -> 91887 | I4: =SUM(I2:I3) -> 91246

Sheet Social EventsTournaments
A1: Date | B1: Sport | C1: Type | D1: Amt | E1: Post Comission | F1: Payment Gateway | G1: Event Cost | H1: Net Revenue | I1: TDS | J1: Final Amount (₹) | K1: Notes
A2: 46256 | B2: Pickleball | C2: DUPR | D2: 5000 | E2: =D2*5% -> 250 | F2: 0 | G2: 160 | H2: =D2-E2-F2-G2 -> 4590 | I2: =D2*2% -> 100 | J2: =H2-I2 -> 4490 | K2: Courtly
B3: Pickleball | C3: DUPR | D3: 3500 | E3: 0 | F3: =D3*1.75% -> 61.25 | G3: 0 | H3: =D3-E3-F3-G3 -> 3438.75 | I3: 0 | J3: =H3-I3 -> 3438.75 | K3: Offline
A4: Total | D4: =SUM(D2:D3) -> 8500 | E4: =SUM(E2:E3) -> 250 | F4: =SUM(F2:F3) -> 61.25 | G4: =SUM(G2:G3) -> 160 | H4: =SUM(H2:H3) -> 8028.75 | I4: =SUM(I2:I3) -> 100 | J4: =SUM(J2:J3) -> 7928.75

Sheet Corporate Events
A1: Start Month | B1: Partnership Type | C1: Name of Brand/Person | D1: Deliverables | E1: Amount (₹) | F1: Payment Gateway | G1: Net Revenue
A2: Aug | B2: Team Event | C2: Morning Picklebal Tournament | D2: 5 Hours of courts | E2: 3150 | F2: =E2*1.75% -> 55.125 | G2: =E2-F2 -> 3094.875
A3: Aug | B3: Team Event | C3: Decathlon | D3: 4 Hours of courts | E3: 2800 | F3: =E3*1.75% -> 49 | G3: =E3-F3 -> 2751
A4: Total | E4: =SUM(E2:E3) -> 5950 | F4: =SUM(F2:F3) -> 104.125 | G4: =SUM(G2:G3) -> 5845.875

Sheet Academy
A1: Sports | B1: Month | C1: Amt | D1: Payment Gateway | E1: Net Revenue
A2: Pickleball | B2: Aug | C2: 6500 | D2: =C2*1.75% -> 113.75 | E2: =C2-D2 -> 6386.25
