Workbook

Sheet Summary
B2: 1 - 31 July
B3: Particulars | C3: Amount
C4: Pickleball
B5: Pay & Play | C5: =sum(C6,C12) -> 41860
B6: Online | C6: =sum(C7:C11) -> 31980
B7: District | C7: =District!C3 -> 31980
B8: Hudle | C8: 0
B9: Playo | C9: 0
B10: Khelomore | C10: 0
B11: Zplys | C11: 0
B12: Offline | C12: =sum(C13:C14) -> 9880
B13: Bookings | C13: ='Offline & RG Community'!D33 -> 9880
B14: Memberships | C14: 0
B15: Community | C15: =sum(C16:C17) -> 5800
B16: Pickup games | C16: ='Offline & RG Community'!E33 -> 5800
B17: Social Events/Tournaments | C17: 0
B18: Academy | C18: =Academy!E2 -> 18000
B19: Events & Partnership | C19: =sum(C20,C21) -> 0
B20: Corporate events | C20: 0
B21: All B2B partnerships | C21: 0
B22: Commerce | C22: =sum(C23:C25) -> 2100
B23: Product rental | C23: ='Offline & RG Community'!F33 -> 2100
B24: Product sales | C24: 0
B25: F&B | C25: 0
B26: Other Income | C26: 0 | D26: (Note for CA Team: Please note that RallyGully hasn't received the 18000 rental for basketball rental service provided) - GST payment would have to be made by Drive & Kick Team
B27: Total Gross Revenue | C27: =sum(C26+C22+C19+C18+C15+C12+C6) -> 67760
B28: Total Net Revenue (Post Commissions) | C28: ='Offline & RG Community'!J33+District!F3+Academy!E2 -> 65178.85
B29: Total Net Revenue post GST | C29: =C27/1.18-(C27-C28) -> 54842.579
B30: Drive & Kick Share (70%) | C30: =C29*70% -> 38389.805
B31: Drive & Kick Share (Final share after incorporting 18k already received by Drive Kick) | C31: =C30-C18 -> 20389.805
B32: RallyGully's Share (30%) | C32: =C29*30% -> 16452.774

Sheet Offline & RG Community
A1: Date | B1: Day | C1: Offline booking hours | D1: Booking Revenue | E1: Community Revenue | F1: Paddle Rental | G1: F&B | H1: Total Revenue | I1: Payment Gateway | J1: Net Revenue
A2: 46204 | B2: Wednesday | C2: 0 | D2: 0 | E2: 0 | F2: 0 | G2: 0 | H2: =sum(D2:G2) -> 0 | I2: =H2*1.75% -> 0 | J2: =H2-I2 -> 0
A3: 46205 | B3: Thursday | C3: 1 | D3: 720 | E3: 1400 | F3: 250 | G3: 0 | H3: =sum(D3:G3) -> 2370 | I3: =H3*1.75% -> 41.475 | J3: =H3-I3 -> 2328.525
A4: 46206 | B4: Friday | C4: 0 | D4: 0 | E4: 1600 | F4: 200 | G4: 0 | H4: =sum(D4:G4) -> 1800 | I4: =H4*1.75% -> 31.5 | J4: =H4-I4 -> 1768.5
A5: 46207 | B5: Saturday | C5: 2 | D5: 1280 | E5: 1800 | F5: 450 | G5: 0 | H5: =sum(D5:G5) -> 3530 | I5: =H5*1.75% -> 61.775 | J5: =H5-I5 -> 3468.225
A6: 46208 | B6: Sunday | C6: 1 | D6: 720 | E6: 0 | F6: 50 | G6: 0 | H6: =sum(D6:G6) -> 770 | I6: =H6*1.75% -> 13.475 | J6: =H6-I6 -> 756.525
A7: 46209 | B7: Monday | C7: 3 | D7: 1920 | E7: 0 | F7: 0 | G7: 0 | H7: =sum(D7:G7) -> 1920 | I7: =H7*1.75% -> 33.6 | J7: =H7-I7 -> 1886.4
A8: 46210 | B8: Tuesday | C8: 0 | D8: 0 | E8: 0 | F8: 0 | G8: 0 | H8: =sum(D8:G8) -> 0 | I8: =H8*1.75% -> 0 | J8: =H8-I8 -> 0
A9: 46211 | B9: Wednesday | C9: 0 | D9: 0 | E9: 0 | F9: 0 | G9: 0 | H9: =sum(D9:G9) -> 0 | I9: =H9*1.75% -> 0 | J9: =H9-I9 -> 0
A10: 46212 | B10: Thursday | C10: 0 | D10: 0 | E10: 400 | F10: 0 | G10: 0 | H10: =sum(D10:G10) -> 400 | I10: =H10*1.75% -> 7 | J10: =H10-I10 -> 393
A11: 46213 | B11: Friday | C11: 0 | D11: 0 | E11: 0 | F11: 0 | G11: 0 | H11: =sum(D11:G11) -> 0 | I11: =H11*1.75% -> 0 | J11: =H11-I11 -> 0
A12: 46214 | B12: Saturday | C12: 1 | D12: 640 | E12: 0 | F12: 200 | G12: 0 | H12: =sum(D12:G12) -> 840 | I12: =H12*1.75% -> 14.7 | J12: =H12-I12 -> 825.3
A13: 46215 | B13: Sunday | C13: 1 | D13: 640 | E13: 0 | F13: 150 | G13: 0 | H13: =sum(D13:G13) -> 790 | I13: =H13*1.75% -> 13.825 | J13: =H13-I13 -> 776.175
... A32: 46234 | B32: Friday | C32: 0 | D32: 0 | E32: 0 | F32: 0 | G32: 0 | H32: =sum(D32:G32) -> 0 | I32: =H32*1.75% -> 0 | J32: =H32-I32 -> 0
A33: Total | D33: =SUM(D1:D32) -> 9880 | E33: =SUM(E1:E32) -> 5800 | F33: =SUM(F1:F32) -> 2100 | G33: =SUM(G1:G32) -> 0 | H33: =SUM(H1:H32) -> 17780 | I33: =SUM(I1:I32) -> 311.15 | J33: =SUM(J1:J32) -> 17468.85

Sheet District
A1: Link | B1: Date | C1: Paid to District | D1: Commissions (₹) | E1: GST on Commission | F1: Net Revenue | G1: TCS | H1: TDS | I1: Final Amount (₹)
B2: 1 - 31 July | C2: 31980 | D2: 2238 | E2: 32 | F2: =C2-D2-E2 -> 29710 | G2: 160 | H2: 32 | I2: =F2-G2-H2 -> 29518
A3: Total | C3: =SUM(C2) -> 31980 | F3: =SUM(F2) -> 29710 | I3: =SUM(I2) -> 29518

Sheet Academy
A1: Month | B1: Coaching | C1: Sports Type | D1: Type | E1: Amount Collected
A2: July | B2: Basketball Coaching | C2: Basketball | D2: 3 days in week | E2: 18000
