Workbook

Sheet Summary
B2: 1 - 31 Aug
B3: Particulars | C3: Amount
C4: Pickleball
B5: Pay & Play | C5: =sum(C6,C12) -> 52819
B6: Online | C6: =sum(C7:C11) -> 36495
B7: District | C7: =District!C4 -> 36495
B8: Hudle | C8: 0
B9: Playo | C9: 0
B10: Khelomore | C10: 0
B11: Zplys | C11: 0
B12: Offline | C12: =sum(C13:C14) -> 16324
B13: Bookings | C13: ='Offline & RG Community'!D33 -> 16324
B14: Memberships | C14: 0
B15: Community | C15: =sum(C16:C17) -> 3476
B16: Pickup games | C16: ='Offline & RG Community'!E33 -> 3476
B17: Social Events/Tournaments | C17: 0
B18: Academy | C18: 0
B19: Events & Partnership | C19: =sum(C20,C21) -> 0
B20: Corporate events | C20: 0
B21: All B2B partnerships | C21: 0
B22: Commerce | C22: =sum(C23:C25) -> 6320
B23: Product rental | C23: ='Offline & RG Community'!F33 -> 6250
B24: Product sales | C24: 0
B25: F&B | C25: ='F&B'!B33 -> 70
B26: Other Income | C26: 0
B27: Total Gross Revenue (A) | C27: =C6+C12+C15+C18+C19+C22+C26 -> 62615
B28: GST (B) | C28: =C27-(C27/1.18) -> 9551.4407
B29: Commissions (C) | C29: ='Offline & RG Community'!H33+'F&B'!C33+'F&B'!E33+District!D4+District!E4 -> 3522.6
B30: Total Net Revenue post GST | C30: =C27-C28-C29 -> 49540.959

Sheet Offline & RG Community
A1: Date | B1: Day | C1: Offline booking hours | D1: Booking Revenue | E1: Community Revenue | F1: Paddle Rental | G1: Total Revenue | H1: Payment Gateway | I1: Net Revenue
A2: 46235 | B2: Saturday | C2: 1 | D2: 640 | E2: 600 | F2: 300 | G2: =sum(D2:F2) -> 1540 | H2: =G2*1.75% -> 26.95 | I2: =G2-H2 -> 1513.05
A3: 46236 | B3: Sunday | C3: 1 | D3: 640 | E3: 396 | F3: 400 | G3: =sum(D3:F3) -> 1436 | H3: =G3*1.75% -> 25.13 | I3: =G3-H3 -> 1410.87
A4: 46237 | B4: Monday | C4: 2.5 | D4: 1600 | E4: 0 | F4: 250 | G4: =sum(D4:F4) -> 1850 | H4: =G4*1.75% -> 32.375 | I4: =G4-H4 -> 1817.625
A5: 46238 | B5: Tuesday | C5: 0 | D5: 0 | E5: 0 | F5: 0 | G5: =sum(D5:F5) -> 0 | H5: =G5*1.75% -> 0 | I5: =G5-H5 -> 0
A6: 46239 | B6: Wednesday | C6: 1 | D6: 640 | E6: 400 | F6: 0 | G6: =sum(D6:F6) -> 1040 | H6: =G6*1.75% -> 18.2 | I6: =G6-H6 -> 1021.8
A7: 46240 | B7: Thursday | C7: 1.5 | D7: 1057 | E7: 0 | F7: 100 | G7: =sum(D7:F7) -> 1157 | H7: =G7*1.75% -> 20.2475 | I7: =G7-H7 -> 1136.7525
A8: 46241 | B8: Friday | C8: 0 | D8: 0 | E8: 0 | F8: 0 | G8: =sum(D8:F8) -> 0 | H8: =G8*1.75% -> 0 | I8: =G8-H8 -> 0
A9: 46242 | B9: Saturday | C9: 1.5 | D9: 957 | E9: 0 | F9: 300 | G9: =sum(D9:F9) -> 1257 | H9: =G9*1.75% -> 21.9975 | I9: =G9-H9 -> 1235.0025
A10: 46243 | B10: Sunday | C10: 2.5 | D10: 1595 | E10: 800 | F10: 250 | G10: =sum(D10:F10) -> 2645 | H10: =G10*1.75% -> 46.2875 | I10: =G10-H10 -> 2598.7125
A11: 46244 | B11: Monday | C11: 1 | D11: 640 | E11: 0 | F11: 100 | G11: =sum(D11:F11) -> 740 | H11: =G11*1.75% -> 12.95 | I11: =G11-H11 -> 727.05
A12: 46245 | B12: Tuesday | C12: 0 | D12: 0 | E12: 0 | F12: 200 | G12: =sum(D12:F12) -> 200 | H12: =G12*1.75% -> 3.5 | I12: =G12-H12 -> 196.5
A13: 46246 | B13: Wednesday | C13: 0.5 | D13: 319 | E13: 0 | F13: 200 | G13: =sum(D13:F13) -> 519 | H13: =G13*1.75% -> 9.0825 | I13: =G13-H13 -> 509.9175
... A32: 46265 | B32: Monday | C32: 0 | D32: 0 | E32: 0 | F32: 0 | G32: =sum(D32:F32) -> 0 | H32: =G32*1.75% -> 0 | I32: =G32-H32 -> 0
A33: Total | D33: =SUM(D1:D32) -> 16324 | E33: =SUM(E1:E32) -> 3476 | F33: =SUM(F1:F32) -> 6250 | G33: =SUM(G1:G32) -> 26050 | H33: =SUM(H1:H32) -> 455.875 | I33: =SUM(I1:I32) -> 25594.125

Sheet F&B
A1: Date | B1: F&B | C1: Paid to brand (75%) | D1: Blended Margin (25%) | E1: Payment Gateway | F1: Net Revenue
A2: 46235 | B2: 0 | C2: =B2*75% -> 0 | D2: =B2*25% -> 0 | E2: =B2*1.75% -> 0 | F2: =D2-E2 -> 0
A3: 46236 | B3: 35 | C3: =B3*75% -> 26.25 | D3: =B3*25% -> 8.75 | E3: =B3*1.75% -> 0.6125 | F3: =D3-E3 -> 8.1375
A4: 46237 | B4: 35 | C4: =B4*75% -> 26.25 | D4: =B4*25% -> 8.75 | E4: =B4*1.75% -> 0.6125 | F4: =D4-E4 -> 8.1375
A5: 46238 | B5: 0 | C5: =B5*75% -> 0 | D5: =B5*25% -> 0 | E5: =B5*1.75% -> 0 | F5: =D5-E5 -> 0
A6: 46239 | B6: 0 | C6: =B6*75% -> 0 | D6: =B6*25% -> 0 | E6: =B6*1.75% -> 0 | F6: =D6-E6 -> 0
A7: 46240 | B7: 0 | C7: =B7*75% -> 0 | D7: =B7*25% -> 0 | E7: =B7*1.75% -> 0 | F7: =D7-E7 -> 0
A8: 46241 | B8: 0 | C8: =B8*75% -> 0 | D8: =B8*25% -> 0 | E8: =B8*1.75% -> 0 | F8: =D8-E8 -> 0
A9: 46242 | B9: 0 | C9: =B9*75% -> 0 | D9: =B9*25% -> 0 | E9: =B9*1.75% -> 0 | F9: =D9-E9 -> 0
A10: 46243 | B10: 0 | C10: =B10*75% -> 0 | D10: =B10*25% -> 0 | E10: =B10*1.75% -> 0 | F10: =D10-E10 -> 0
A11: 46244 | B11: 0 | C11: =B11*75% -> 0 | D11: =B11*25% -> 0 | E11: =B11*1.75% -> 0 | F11: =D11-E11 -> 0
A12: 46245 | B12: 0 | C12: =B12*75% -> 0 | D12: =B12*25% -> 0 | E12: =B12*1.75% -> 0 | F12: =D12-E12 -> 0
A13: 46246 | B13: 0 | C13: =B13*75% -> 0 | D13: =B13*25% -> 0 | E13: =B13*1.75% -> 0 | F13: =D13-E13 -> 0
... A32: 46265 | B32: 0 | C32: =B32*75% -> 0 | D32: =B32*25% -> 0 | E32: =B32*1.75% -> 0 | F32: =D32-E32 -> 0
A33: Total | B33: =SUM(B2:B32) -> 70 | C33: =SUM(C2:C32) -> 52.5 | D33: =SUM(D2:D32) -> 17.5 | E33: =SUM(E2:E32) -> 1.225 | F33: =SUM(F2:F32) -> 16.275

Sheet District
A1: Link | B1: Date | C1: Paid to District | D1: Commissions (₹) | E1: GST on Commission | F1: Net Revenue | G1: TCS | H1: TDS | I1: Final Amount (₹)
B2: 1 - 31 Aug | C2: 36495 | D2: 2554 | E2: 459 | F2: =C2-D2-E2 -> 33482 | G2: 182 | H2: 36 | I2: =F2-G2-H2 -> 33264
B4: Total | C4: =SUM(C2:C3) -> 36495 | D4: =SUM(D2:D3) -> 2554 | E4: =SUM(E2:E3) -> 459 | F4: =SUM(F2:F3) -> 33482 | I4: =SUM(I2:I3) -> 33264
