Workbook

Sheet Summary
B2: 1 - 31 July
B3: Particulars | C3: Amount
C4: Pickleball
B5: Pay & Play | C5: =sum(C6,C12) -> 173433
B6: Online | C6: =sum(C7:C11) -> 116089
B7: District | C7: =District!C4 -> 116089
B8: Hudle | C8: 0
B9: Playo | C9: 0
B10: Khelomore | C10: 0
B11: Zplys | C11: 0
B12: Offline | C12: =sum(C13:C14) -> 57344
B13: Bookings | C13: ='Offline & RG Community'!D33 -> 57344
B14: Memberships | C14: 0
B15: Community | C15: =sum(C16:C17) -> 69742
B16: Pickup games | C16: ='Offline & RG Community'!E33 -> 45000
B17: Social Events/Tournaments | C17: ='Social EventsTournaments'!D6 -> 24742
B18: Academy | C18: =Academy!C2 -> 6500
B19: Events & Partnership | C19: 0
B20: Corporate events | C20: 0
B21: All B2B partnerships | C21: 0
B22: Commerce | C22: =sum(C23:C25) -> 10195
B23: Product rental | C23: ='Offline & RG Community'!F33 -> 9775
B24: Product sales | C24: 0
B25: F&B | C25: ='Offline & RG Community'!G33 -> 420
B26: Other Income | C26: 0
B27: Total Gross Revenue | C27: =C6+C12+C15+C18+C19+C22+C26 -> 259870
B28: GST (B) | C28: =C27-(C27/1.18) -> 39641.186
B29: Commissions, Payment gateway & Event Expense(C) | C29: ='Offline & RG Community'!I33+District!D2+District!E2+'Social EventsTournaments'!E6+'Social EventsTournaments'!F6+Academy!D2 -> 12879.032
B30: Net Revenue (A-B-C) | C30: =C27-C28-C29 -> 207349.78

Sheet Offline & RG Community
A1: Date | B1: Day | C1: Offline booking hours | D1: Booking Revenue | E1: Community Revenue | F1: Paddle Rental | G1: F&B | H1: Total Revenue | I1: Payment Gateway | J1: Net Revenue
A2: 46204 | B2: Wednesday | C2: 2.5 | D2: 960 | E2: 600 | F2: 0 | G2: 0 | H2: =sum(D2:G2) -> 1560 | I2: =H2*1.75% -> 27.3 | J2: =H2-I2 -> 1532.7
A3: 46205 | B3: Thursday | C3: 2 | D3: 1440 | E3: 0 | F3: 250 | G3: 0 | H3: =sum(D3:G3) -> 1690 | I3: =H3*1.75% -> 29.575 | J3: =H3-I3 -> 1660.425
A4: 46206 | B4: Friday | C4: 5 | D4: 3600 | E4: 0 | F4: 350 | G4: 0 | H4: =sum(D4:G4) -> 3950 | I4: =H4*1.75% -> 69.125 | J4: =H4-I4 -> 3880.875
A5: 46207 | B5: Saturday | C5: 3 | D5: 2160 | E5: 0 | F5: 650 | G5: 0 | H5: =sum(D5:G5) -> 2810 | I5: =H5*1.75% -> 49.175 | J5: =H5-I5 -> 2760.825
A6: 46208 | B6: Sunday | C6: 6 | D6: 2880 | E6: 1600 | F6: 500 | G6: 0 | H6: =sum(D6:G6) -> 4980 | I6: =H6*1.75% -> 87.15 | J6: =H6-I6 -> 4892.85
A7: 46209 | B7: Monday | C7: 1.5 | D7: 1080 | E7: 2200 | F7: 200 | G7: 0 | H7: =sum(D7:G7) -> 3480 | I7: =H7*1.75% -> 60.9 | J7: =H7-I7 -> 3419.1
A8: 46210 | B8: Tuesday | C8: 3 | D8: 2160 | E8: 0 | F8: 300 | G8: 70 | H8: =sum(D8:G8) -> 2530 | I8: =H8*1.75% -> 44.275 | J8: =H8-I8 -> 2485.725
A9: 46211 | B9: Wednesday | C9: 3.5 | D9: 2400 | E9: 2200 | F9: 100 | G9: 0 | H9: =sum(D9:G9) -> 4700 | I9: =H9*1.75% -> 82.25 | J9: =H9-I9 -> 4617.75
A10: 46212 | B10: Thursday | C10: 2 | D10: 1440 | E10: 3000 | F10: 350 | G10: 0 | H10: =sum(D10:G10) -> 4790 | I10: =H10*1.75% -> 83.825 | J10: =H10-I10 -> 4706.175
A11: 46213 | B11: Friday | C11: 0.5 | D11: 460 | E11: 1400 | F11: 625 | G11: 0 | H11: =sum(D11:G11) -> 2485 | I11: =H11*1.75% -> 43.4875 | J11: =H11-I11 -> 2441.5125
A12: 46214 | B12: Saturday | C12: 4 | D12: 2985 | E12: 1400 | F12: 700 | G12: 0 | H12: =sum(D12:G12) -> 5085 | I12: =H12*1.75% -> 88.9875 | J12: =H12-I12 -> 4996.0125
A13: 46215 | B13: Sunday | C13: 0 | D13: 0 | E13: 0 | F13: 200 | G13: 0 | H13: =sum(D13:G13) -> 200 | I13: =H13*1.75% -> 3.5 | J13: =H13-I13 -> 196.5
... A32: 46234 | B32: Friday | C32: 3.5 | D32: 2480 | E32: 2400 | F32: 300 | G32: 0 | H32: =sum(D32:G32) -> 5180 | I32: =H32*1.75% -> 90.65 | J32: =H32-I32 -> 5089.35
A33: Total | D33: =SUM(D1:D32) -> 57344 | E33: =SUM(E1:E32) -> 45000 | F33: =SUM(F1:F32) -> 9775 | G33: =SUM(G1:G32) -> 420 | H33: =SUM(H1:H32) -> 112539 | I33: =SUM(I1:I32) -> 1969.4325 | J33: =SUM(J1:J32) -> 110569.57

Sheet District
A1: Link | B1: Date | C1: Paid to District | D1: Commissions (₹) | E1: GST on Commission | F1: Net Revenue | G1: TCS | H1: TDS | I1: Final Amount (₹)
B2: 1 - 31 July | C2: 116089 | D2: 8126 | E2: 1462 | F2: =C2-D2-E2 -> 106501 | G2: 70 | H2: 116 | I2: =F2-G2-H2 -> 106315
B4: Total | C4: =SUM(C2:C3) -> 116089 | F4: =SUM(F2:F3) -> 106501 | I4: =SUM(I2:I3) -> 106315

Sheet Social EventsTournaments
A1: Date | B1: Sport | C1: Type | D1: Amt | E1: Post Comission | F1: Payment Gateway | G1: Net Revenue | H1: TDS | I1: Final Amount (₹) | J1: Notes
A2: 46215 | B2: Pickleball | C2: DUPR | D2: 10800 | E2: =D2*5% -> 540 | F2: 0 | G2: =D2-E2-F2 -> 10260 | H2: =D2*2% -> 216 | I2: =G2-H2 -> 10044 | J2: Courtly
B3: Pickleball | C3: DUPR | D3: 1200 | E3: =D3*1.75% -> 21 | F3: =D3*1.75% -> 21 | G3: =D3-E3-F3 -> 1158 | H3: 0 | I3: =G3-H3 -> 1158 | J3: Offline
A4: 46222 | B4: Pickleball | C4: DUPR | D4: 11992 | E4: =D4*5% -> 599.6 | F4: =0 -> 0 | G4: =D4-E4-F4 -> 11392.4 | H4: =D4*2% -> 239.84 | I4: =G4-H4 -> 11152.56 | J4: Courtly
B5: Pickleball | C5: DUPR | D5: 750 | E5: =D5*1.75% -> 13.125 | F5: =D5*1.75% -> 13.125 | G5: =D5-E5-F5 -> 723.75 | H5: 0 | I5: =G5-H5 -> 723.75 | J5: Offline
A6: Total | D6: =SUM(D2:D5) -> 24742 | E6: =SUM(E2:E5) -> 1173.725 | F6: =SUM(F2:F5) -> 34.125 | G6: =SUM(G2:G5) -> 23534.15 | H6: =SUM(H2:H5) -> 455.84 | I6: =SUM(I2:I5) -> 23078.31

Sheet Academy
A1: Sports | B1: Month | C1: Amt | D1: Payment Gateway | E1: Net Revenue
A2: Pickleball | B2: July | C2: 6500 | D2: =C2*1.75% -> 113.75 | E2: =C2-D2 -> 6386.25
