Workbook

Sheet Summary
B2: 1 - 30 Sept
B3: Particulars | C3: Amount
C4: Pickleball
B5: Pay & Play | C5: =sum(C6,C12) -> 53046
B6: Online | C6: =sum(C7:C11) -> 39546
B7: District | C7: =District!C4 -> 39546
B8: Hudle | C8: 0
B9: Playo | C9: 0
B10: Khelomore | C10: 0
B11: Zplys | C11: 0
B12: Offline | C12: =sum(C13:C14) -> 13500
B13: Bookings | C13: ='Offline & RG Community'!D32 -> 500
B14: Memberships | C14: =Memberships!E4 -> 13000
B15: Community | C15: =sum(C16:C18) -> 1500
B16: Pickup games | C16: ='Offline & RG Community'!E32 -> 1500
B17: Social Events/Tournaments | C17: 0
B18: Community Partnership | C18: 0
B19: Academy | C19: 0
B20: B2B | C20: =sum(C21,C22) -> 2000
B21: Corporate events | C21: =B2B!E2 -> 2000
B22: All B2B partnerships | C22: 0
B23: Commerce | C23: =sum(C24:C26) -> 275
B24: Product rental | C24: ='Offline & RG Community'!F32 -> 275
B25: Product sales | C25: 0
B26: F&B | C26: 0
B27: Other Income | C27: 0
B28: Total Gross Revenue | C28: =C5+C15+C19+C20+C23+C27 -> 56821
B29: GST | C29: =C28-(C28/1.18) -> 8667.6102
B30: Net Revenue Post GST | C30: =C28-C29 -> 48153.39
B31: Commissions, Payment gateway & Event Expense | C31: ='Offline & RG Community'!H32+District!D4+District!E4+Memberships!F4+B2B!F2 -> 3166.3125
B32: Net Revenue | C32: =C28-C29-C31 -> 44987.077
B33: VM Salary | C33: =1580+11032+10000+2400 -> 25012
B34: Support Staff | C34: 5500
B35: Marketing, Branding & Community | C35: 6000
B36: Balls | C36: 5500
B38: Net Profit | C38: =C30-(sum(C33:C36)) -> 6141.3898

Sheet Offline & RG Community
A1: Date | B1: Day | C1: Offline booking hours | D1: Booking Revenue | E1: Community Revenue | F1: Paddle Rental | G1: Total Revenue | H1: Payment Gateway | I1: Net Revenue
A2: 46266 | B2: Tuesday | C2: 0 | D2: 0 | E2: 0 | F2: 100 | G2: =sum(D2:F2) -> 100 | H2: =G2*1.75% -> 1.75 | I2: =G2-H2 -> 98.25
A3: 46267 | B3: Wednesday | C3: 0 | D3: 0 | E3: 0 | F3: 0 | G3: =sum(D3:F3) -> 0 | H3: =G3*1.75% -> 0 | I3: =G3-H3 -> 0
A4: 46268 | B4: Thursday | C4: 0 | D4: 0 | E4: 0 | F4: 0 | G4: =sum(D4:F4) -> 0 | H4: =G4*1.75% -> 0 | I4: =G4-H4 -> 0
A5: 46269 | B5: Friday | C5: 0 | D5: 0 | E5: 0 | F5: 0 | G5: =sum(D5:F5) -> 0 | H5: =G5*1.75% -> 0 | I5: =G5-H5 -> 0
A6: 46270 | B6: Saturday | C6: 0 | D6: 0 | E6: 0 | F6: 0 | G6: =sum(D6:F6) -> 0 | H6: =G6*1.75% -> 0 | I6: =G6-H6 -> 0
A7: 46271 | B7: Sunday | C7: 0 | D7: 0 | E7: 0 | F7: 0 | G7: =sum(D7:F7) -> 0 | H7: =G7*1.75% -> 0 | I7: =G7-H7 -> 0
A8: 46272 | B8: Monday | C8: 0 | D8: 0 | E8: 0 | F8: 0 | G8: =sum(D8:F8) -> 0 | H8: =G8*1.75% -> 0 | I8: =G8-H8 -> 0
A9: 46273 | B9: Tuesday | C9: 0 | D9: 0 | E9: 0 | F9: 0 | G9: =sum(D9:F9) -> 0 | H9: =G9*1.75% -> 0 | I9: =G9-H9 -> 0
A10: 46274 | B10: Wednesday | C10: 0 | D10: 0 | E10: 0 | F10: 25 | G10: =sum(D10:F10) -> 25 | H10: =G10*1.75% -> 0.4375 | I10: =G10-H10 -> 24.5625
A11: 46275 | B11: Thursday | C11: 0 | D11: 0 | E11: 0 | F11: 0 | G11: =sum(D11:F11) -> 0 | H11: =G11*1.75% -> 0 | I11: =G11-H11 -> 0
A12: 46276 | B12: Friday | C12: 0 | D12: 0 | E12: 0 | F12: 0 | G12: =sum(D12:F12) -> 0 | H12: =G12*1.75% -> 0 | I12: =G12-H12 -> 0
A13: 46277 | B13: Saturday | C13: 0 | D13: 0 | E13: 0 | F13: 0 | G13: =sum(D13:F13) -> 0 | H13: =G13*1.75% -> 0 | I13: =G13-H13 -> 0
... A24: 46288 | B24: Wednesday | C24: 0 | D24: 0 | E24: 0 | F24: 150 | G24: =sum(D24:F24) -> 150 | H24: =G24*1.75% -> 2.625 | I24: =G24-H24 -> 147.375
A25: 46289 | B25: Thursday | C25: Venue Closed | G25: =sum(D25:F25) -> 0 | H25: =G25*1.75% -> 0 | I25: =G25-H25 -> 0
A26: 46290 | B26: Friday | G26: =sum(D26:F26) -> 0 | H26: =G26*1.75% -> 0 | I26: =G26-H26 -> 0
A27: 46291 | B27: Saturday | G27: =sum(D27:F27) -> 0 | H27: =G27*1.75% -> 0 | I27: =G27-H27 -> 0
A28: 46292 | B28: Sunday | C28: 0.5 | D28: 500 | E28: 0 | F28: 0 | G28: =sum(D28:F28) -> 500 | H28: =G28*1.75% -> 8.75 | I28: =G28-H28 -> 491.25
A29: 46293 | B29: Monday | C29: 0 | D29: 0 | E29: 0 | F29: 0 | G29: =sum(D29:F29) -> 0 | H29: =G29*1.75% -> 0 | I29: =G29-H29 -> 0
A30: 46294 | B30: Tuesday | C30: 0 | D30: 0 | E30: 0 | F30: 0 | G30: =sum(D30:F30) -> 0 | H30: =G30*1.75% -> 0 | I30: =G30-H30 -> 0
A31: 46295 | B31: Wednesday | C31: 0 | D31: 0 | E31: 0 | F31: 0 | G31: =sum(D31:F31) -> 0 | H31: =G31*1.75% -> 0 | I31: =G31-H31 -> 0
A32: Total | D32: =SUM(D2:D31) -> 500 | E32: =SUM(E2:E31) -> 1500 | F32: =SUM(F2:F31) -> 275 | G32: =SUM(G2:G31) -> 2275 | H32: =SUM(H2:H31) -> 39.8125 | I32: =SUM(I2:I31) -> 2235.1875

Sheet District
A1: Link | B1: Date | C1: Paid to District | D1: Commissions (₹) | E1: GST on Commission | F1: Net Revenue | G1: TCS | H1: TDS | I1: Final Amount (₹)
B2: 1 - 30 Sept | C2: 39546 | D2: 2427 | E2: 437 | F2: =C2-D2-E2 -> 36682 | G2: 197 | H2: 40 | I2: =F2-G2-H2 -> 36445
B4: Total | C4: =SUM(C2:C3) -> 39546 | D4: =SUM(D2:D3) -> 2427 | E4: =SUM(E2:E3) -> 437 | F4: =SUM(F2:F3) -> 36682 | I4: =SUM(I2:I3) -> 36445

Sheet Memberships
A1: Month | B1: Member Name | C1: Sports Type | D1: Credits Issued | E1: Amount Collected | F1: Payment Gateway | G1: Net Revenue
A2: September | B2: Koshik | C2: Pickleball | D2: 10 Hours | E2: 5500 | F2: =E2*1.75% -> 96.25 | G2: =E2-F2 -> 5403.75
A3: September | B3: Utkarsh | C3: Pickleball | D3: 15 Hours | E3: 7500 | F3: =E3*1.75% -> 131.25 | G3: =E3-F3 -> 7368.75
A4: Total | E4: =SUM(E2,E3) -> 13000 | F4: =SUM(F2,F3) -> 227.5 | G4: =SUM(G2,G3) -> 12772.5

Sheet B2B
A1: Start Month | B1: Partnership Type | C1: Name of Brand/Person | D1: Deliverables | E1: Amount (₹) | F1: Payment Gateway | G1: Net Revenue
A2: Sept | B2: Event Booking | C2: Founder mixer event | D2: 2 Hours of Courts | E2: 2000 | F2: =E2*1.75% -> 35 | G2: =E2-F2 -> 1965
