Workbook

Sheet Summary
B2: Date: 1 - 28 Feb
B3: Particulars | C3: Amount
B4: Offline | C4: =SUM(C5,C6,C7,C8) -> 120420
B5: Rentals | C5: ='Offline & RG Community'!G30 -> 10250
B6: F&B | C6: 0
B7: Product Sales | C7: =0 -> 0
B8: Bookings | C8: ='Offline & RG Community'!E30 -> 110170
B9: Online: Third Party Platform | C9: =SUM(C10:C14) -> 41060
B10: Hudle | C10: =Hudle!C5 -> 21460
B11: Playo | C11: =Playo!C4 -> 3200
B12: District | C12: =District!C4 -> 16400
B13: Khelomore | C13: 0
B14: Zplys | C14: 0
B15: Community | C15: =sum(C16:C19) -> 0
B16: Courtly (Organized by RallyGully) | C16: 0
B17: Sportomic (Organized by RallyGully) | C17: 0
B18: Rallygully Community games | C18: ='Offline & RG Community'!F30 -> 0
B19: Misfits Community | C19: 0
B20: Memberships | C20: =Membership!E5 -> 43880
B21: Coaching | C21: 0
B22: Corporate Events | C22: ='Corporate Events'!F3 -> 5520
B23: Brand Activation | C23: 0
B24: Other Income | C24: 0
B25: Total Gross Revenue | C25: =sum(C23,C24,C22, C20,C15,C9,C4) -> 210880
B26: Total Net Revenue (Post Commissions) | C26: ='Offline & RG Community'!H30+Hudle!E5+Playo!F4+District!F4+Membership!E5+'Corporate Events'!F3 -> 207434.28
B27: Total Revenue post GST | C27: =C26/1.18 -> 175791.76

Sheet Offline & RG Community
A1: Date | B1: Day | C1: Offline booking hours | D1: Discount Given | E1: Booking Revenue | F1: Community Revenue | G1: Paddle Rental | H1: Total Revenue
A2: 46054 | B2: Sunday | C2: 4.5 | D2: 30% and 20% | E2: 5560 | F2: 0 | G2: 300 | H2: =E2+F2+G2 -> 5860
A3: 46055 | B3: Monday | C3: 1.5 | D3: 30% and 20% | E3: 960 | F3: 0 | G3: 200 | H3: =E3+F3+G3 -> 1160
A4: 46056 | B4: Tuesday | C4: 2.5 | D4: 30% and 20% | E4: 5800 | F4: 0 | G4: 200 | H4: =E4+F4+G4 -> 6000
A5: 46057 | B5: Wednesday | C5: 2 | D5: 30% and 20% | E5: 1280 | F5: 0 | G5: 150 | H5: =E5+F5+G5 -> 1430
A6: 46058 | B6: Thursday | C6: 7 | D6: 30% and 20% | E6: 5180 | F6: 0 | G6: 700 | H6: =E6+F6+G6 -> 5880
A7: 46059 | B7: Friday | C7: 5 | D7: 30% and 20% | E7: 3200 | F7: 0 | G7: 250 | H7: =E7+F7+G7 -> 3450
A8: 46060 | B8: Saturday | C8: 5 | D8: 30% and 20% | E8: 4480 | F8: 0 | G8: 550 | H8: =E8+F8+G8 -> 5030
A9: 46061 | B9: Sunday | C9: 8.5 | D9: 30% and 20% | E9: 6920 | F9: 0 | G9: 800 | H9: =E9+F9+G9 -> 7720
A10: 46062 | B10: Monday | C10: 4.5 | D10: 30% and 20% | E10: 4800 | F10: 0 | G10: 250 | H10: =E10+F10+G10 -> 5050
A11: 46063 | B11: Tuesday | C11: 5.5 | D11: 30% and 20% | E11: 3520 | F11: 0 | G11: 500 | H11: =E11+F11+G11 -> 4020
A12: 46064 | B12: Wednesday | C12: 4.5 | D12: 30% and 20% | E12: 3520 | F12: 0 | G12: 400 | H12: =E12+F12+G12 -> 3920
A13: 46065 | B13: Thursday | C13: 7 | D13: 30% and 20% | E13: 6770 | F13: 0 | G13: 700 | H13: =E13+F13+G13 -> 7470
... A29: 46081 | B29: Saturday | C29: 7.5 | D29: 30% and 20% | E29: 6360 | F29: 0 | G29: 500 | H29: =E29+F29+G29 -> 6860
A30: Total | C30: =SUM(C2:C29) -> 135 | E30: =SUM(E2:E29) -> 110170 | F30: =SUM(F2:F29) -> 0 | G30: =SUM(G2:G29) -> 10250 | H30: =SUM(H2:H29) -> 120420

Sheet Hudle
A1: Link | B1: Date | C1: Paid to Hudle | D1: Commisions (Including GST) | E1: Net Revenue | F1: TDS | G1: TCS | H1: Amount
B2: 46054 | C2: 1950 | D2: 260 | E2: =C2-D2 -> 1690 | F2: 1.69 | G2: 8.47 | H2: 1729.83
B3: 12 - 15 Feb | C3: 6480 | D3: 842.5 | E3: =C3-D3 -> 5637.5 | F3: 5.49 | G3: 27.45 | H3: 5604.66
B4: 16 - 28 Feb | C4: 13030 | D4: 1695.2 | E4: =C4-D4 -> 11334.8 | F4: 11.051 | G4: 55.25 | H4: 11278.51
B5: Total | C5: =SUM(C2:C4) -> 21460 | E5: =SUM(E2:E4) -> 18662.3 | H5: =SUM(H2:H4) -> 18613

Sheet Playo
A1: Link | B1: Date | C1: Paid to Playo (₹) | D1: Commissions (₹) | E1: GST (₹) | F1: Net Revenue | G1: TDS (₹) | H1: TCS (₹) | I1: Final Amount (₹)
B2: 46061 | C2: 800 | D2: 56 | E2: 10.08 | F2: =C2-D2-E2 -> 733.92 | G2: 0.8 | H2: 4 | I2: 729.12
B3: 46071 | C3: 2400 | D3: 168 | E3: 30.24 | F3: =C3-D3-E3 -> 2201.76 | G3: 0.34 | H3: 1.8 | I3: 2199
B4: Total | C4: =SUM(C2:C3) -> 3200 | F4: =SUM(F2:F3) -> 2935.68 | I4: =SUM(I2:I3) -> 2928.12

Sheet District
A1: Link | B1: Date | C1: Paid to District | D1: Commissions (₹) | E1: GST on Commission | F1: Net Revenue | G1: TCS | H1: TDS | I1: Final Amount (₹)
B2: 1 - 15 Feb | C2: 4400 | D2: 84.8 | E2: 15.26 | F2: =C2-D2-E2 -> 4299.94 | G2: 21.2 | H2: 4.24 | I2: 4114.5
B3: 16 - 28 Feb | C3: 12000 | D3: 241.6 | E3: 42.04 | F3: =C3-D3-E3 -> 11716.36 | G3: 59.4 | H3: 11.68 | I3: 11344.28
B4: Total | C4: =SUM(C2:C3) -> 16400 | F4: =SUM(F2:F3) -> 16016.3 | I4: =SUM(I2:I3) -> 15458.78

Sheet Membership
A1: Member Name | B1: Sports Type | C1: Membership Type | D1: Start Date | E1: Amount Collected
A2: Indian School of hospitality | B2: Pickle & Box | C2: Collab | D2: 46054 | E2: 18880
A3: Shivam | B3: Box Cricket | C3: Collab | D3: 46070 | E3: 10000
A4: Ritesh | B4: Pickleball | C4: Pro Pack (30) | D4: 46071 | E4: 15000
A5: Total | E5: =SUM(E2:E4) -> 43880

Sheet Corporate Events
A1: Date | B1: Name | C1: Type | D1: Sports Type | E1: Deliverables | F1: Amount Collected
A2: Feb | B2: DONALDSON INDIA FILTER SYSTEMS PVT LTD | C2: Team Event | D2: Pickleball | E2: 4 hours of Courts | F2: 5520
A3: Total | F3: 5520
