Workbook

Sheet Summary
B2: Date: 1 - 31 Jan
B3: Particulars | C3: Amount
B4: Offline | C4: =SUM(C5,C6,C7,C8) -> 59801
B5: Rentals | C5: ='Offline & RG Community'!G33 -> 12375
B6: F&B | C6: ='Offline & RG Community'!H33 -> 140
B7: Product Sales | C7: 0
B8: Bookings | C8: ='Offline & RG Community'!E33 -> 47286
B9: Online: Third Party Platform | C9: =SUM(C10:C14) -> 25762.56
B10: Hudle | C10: =Hudle!C7 -> 16146
B11: Playo | C11: =Playo!C6 -> 2076.56
B12: District | C12: =District!C5 -> 6400
B13: Khelomore | C13: =Khelomore!C4 -> 1140
B14: Zplys | C14: 0
B15: Community | C15: =SUM(C17,C18,C19) -> 12050
B16: Courtly (Organized by RallyGully) | C16: 0
B17: Sportomic (Organized by RallyGully) | C17: 0
B18: Rallygully Community games | C18: ='Offline & RG Community'!F33 -> 12050
B19: Misfits Community | C19: 0
B20: Memberships | C20: =Memberships!E4 -> 9600
B21: Coaching | C21: 0
B22: Corporate Events | C22: 0
B23: Brand Activation | C23: 0
B24: Other Income | C24: ='Other Income'!E2 -> 18000 | D24: (Note for CA Team: Please note that RallyGully hasn't received the 18000 rental for basketball rental service provided) - GST payment would have to be made by Drive & Kick Team
B25: Total Gross Revenue | C25: =sum(C4,C9,C15,C20,C22,C23,C24) -> 125213.56
B26: Total Net Revenue (Post Commissions) | C26: ='Offline & RG Community'!I33+Hudle!E7+Playo!F6+Khelomore!E4+District!F5+Memberships!E4+'Other Income'!E2 -> 122701.8
B27: Total Revenue post GST | C27: =((C26-C24)/1.18)+C24 -> 106730.34
B28: Drive & Kick Share (70%) | C28: =C27*70% -> 74711.237
B29: Drive & Kick Share (Final share after incorporting 18k already received by Drive Kick) | C29: =C28-C24 -> 56711.237
B30: RallyGully's Share (30%) | C30: =C27*30% -> 32019.102

Sheet Offline & RG Community
A1: Date | B1: Day | C1: Offline booking hours | D1: Discount Given | E1: Booking Revenue | F1: Community Revenue | G1: Paddle Rental | H1: F&B | I1: Total Revenue
A2: 46023 | B2: Thursday | C2: 2 | D2: 20% and 10% | E2: 1360 | F2: 0 | G2: 500 | H2: 0 | I2: =SUM(E2:H2) -> 1860
A3: 46024 | B3: Friday | C3: 1.5 | D3: 20% and 10% | E3: 1000 | F3: 0 | G3: 150 | H3: 0 | I3: =SUM(E3:H3) -> 1150
A4: 46025 | B4: Saturday | C4: 3 | D4: 20% and 10% | E4: 2080 | F4: 0 | G4: 500 | H4: 0 | I4: =SUM(E4:H4) -> 2580
A5: 46026 | B5: Sunday | C5: 3 | D5: 20% and 10% | E5: 1360 | F5: 5600 | G5: 1025 | H5: 0 | I5: =SUM(E5:H5) -> 7985
A6: 46027 | B6: Monday | C6: 1 | D6: 20% and 10% | E6: 640 | F6: 0 | G6: 300 | H6: 0 | I6: =SUM(E6:H6) -> 940
A7: 46028 | B7: Tuesday | C7: 3.5 | D7: 20% and 10% | E7: 2920 | F7: 0 | G7: 800 | H7: 35 | I7: =SUM(E7:H7) -> 3755
A8: 46029 | B8: Wednesday | C8: 2 | D8: 20% and 10% | E8: 1280 | F8: 0 | G8: 150 | H8: 35 | I8: =SUM(E8:H8) -> 1465
A9: 46030 | B9: Thursday | C9: 1 | D9: 20% and 10% | E9: 640 | F9: 0 | G9: 100 | H9: 0 | I9: =SUM(E9:H9) -> 740
A10: 46031 | B10: Friday | C10: 1 | D10: 20% and 10% | E10: 640 | F10: 0 | G10: 100 | H10: 0 | I10: =SUM(E10:H10) -> 740
A11: 46032 | B11: Saturday | C11: 2 | D11: 20% and 10% | E11: 1280 | F11: 0 | G11: 600 | H11: 0 | I11: =SUM(E11:H11) -> 1880
A12: 46033 | B12: Sunday | C12: 3 | D12: 20% and 10% | E12: 1920 | F12: 0 | G12: 200 | H12: 0 | I12: =SUM(E12:H12) -> 2120
A13: 46034 | B13: Monday | C13: 2.5 | D13: 20% and 10% | E13: 1600 | F13: 0 | G13: 200 | H13: 0 | I13: =SUM(E13:H13) -> 1800
... A32: 46053 | B32: Saturday | C32: 2 | D32: 20% and 10% | E32: 1360 | F32: 0 | G32: 400 | H32: 0 | I32: =SUM(E32:H32) -> 1760
A33: Total | C33: =SUM(C2:C32) -> 75 | E33: =SUM(E2:E32) -> 47286 | F33: =SUM(F2:F32) -> 12050 | G33: =SUM(G2:G32) -> 12375 | H33: =SUM(H2:H32) -> 140 | I33: =SUM(I2:I32) -> 71851

Sheet Hudle
A1: Link | B1: Date | C1: Paid to Hudle | D1: Commisions (Including GST) | E1: Net Revenue | F1: TDS | G1: TCS | H1: Amount
B2: 1 - 5 Jan | C2: 1895 | D2: 249.6 | E2: =C2 - D2 -> 1645.4 | F2: 1.62 | G2: 8.13 | H2: 1660.64
B3: 6 - 12 Jan | C3: 4480 | D3: 582.4 | E3: =C3 - D3 -> 3897.6 | F3: 3.79 | G3: 18.98 | H3: 3874.83
B4: 13 - 19 Jan | C4: 2720 | D4: 353.6 | E4: =C4 - D4 -> 2366.4 | F4: 2.3 | G4: 11.52 | H4: 23.59
B5: 19 - 26 Jan | C5: 3776 | D5: 490.88 | E5: =C5 - D5 -> 3285.12 | F5: 3.2 | G5: 16 | H5: 3265.92
B6: 27 - 31 Jan | C6: 3275 | D6: 429 | E6: =C6 - D6 -> 2846 | F6: 2.79 | G6: 13.98 | H6: 2854.22
C7: =SUM(C2:C6) -> 16146 | E7: =SUM(E2:E6) -> 14040.52 | H7: =SUM(H2:H6) -> 11679.2

Sheet Playo
A1: Link | B1: Date | C1: Paid to Playo (₹) | D1: Commissions (₹) | E1: GST (₹) | F1: Net Revenue | G1: TDS (₹) | H1: TCS (₹) | I1: Final Amount (₹)
B2: 1 - 18 Jan | C2: 364.56 | D2: 28 | E2: 5.04 | F2: =C2 -D2-E2 -> 331.52 | G2: 0.4 | H2: 2 | I2: 364.56
B3: 19 - 25 Jan | C3: 400 | D3: 28 | E3: 5.04 | F3: =C3 -D3-E3 -> 366.96 | G3: 0.4 | H3: 2 | I3: 364.56
B4: 26 - 31 Jan | C4: 1312 | D4: 112 | E4: 20.16 | F4: =C4 -D4-E4 -> 1179.84 | G4: 1.31 | H4: 5.65 | I4: 171.91
C6: =SUM(C2:C4) -> 2076.56 | F6: =SUM(F2:F4) -> 1878.32 | I6: =SUM(I2:I4) -> 901.03

Sheet District
A1: Link | B1: Date | C1: Paid to District | D1: Commissions (₹) | E1: GST on Commission | F1: Net Revenue | G1: TCS | H1: TDS | I1: Final Amount (₹)
B2: 1 - 12 Jan | C2: 1600 | D2: =C2*2% -> 32 | E2: =D2*18% -> 5.76 | F2: =C2-D2-E2 -> 1562.24 | G2: =C2*0.5% -> 8 | H2: =D2*0.1% -> 0.032 | I2: =F2-G2-H2 -> 1554.208
B3: 13 - 19 Jan | C3: 2400 | D3: =C3*2% -> 48 | E3: =D3*18% -> 8.64 | F3: =C3-D3-E3 -> 2343.36 | G3: =C3*0.5% -> 12 | H3: =D3*0.1% -> 0.048 | I3: =F3-G3-H3 -> 2331.312
B4: 20 - 31 Jan | C4: 2400 | D4: =C4*2% -> 48 | E4: =D4*18% -> 8.64 | F4: =C4-D4-E4 -> 2343.36 | G4: =C4*0.5% -> 12 | H4: =D4*0.1% -> 0.048 | I4: =F4-G4-H4 -> 2331.312
B5: Total | C5: =SUM(C2:C4) -> 6400 | F5: =SUM(F2:F4) -> 6248.96 | I5: =SUM(I2:I4) -> 6216.832

Sheet Khelomore
A1: Link | B1: Date | C1: Paid to Khelomore (₹) | D1: Commissions (₹) | E1: Final Amount (₹)
B2: 1 - 25 Jan | C2: 1140 | D2: =C2*5% -> 57 | E2: =C2-D2 -> 1083
C4: =SUM(C2:C3) -> 1140 | D4: =SUM(D2:D3) -> 57 | E4: =SUM(E2:E3) -> 1083

Sheet Misfits
A1: Link | B1: Date | C1: Paid to Misfits (₹) | D1: Post Comission (20%) | E1: TDS | F1: Final Amount (₹)
B2: 1 - 31 Jan | C2: 0

Sheet Sportomic
A1: Link | B1: Date | C1: Paid to Sportomic (₹)
B2: 1 - 31 Jan | C2: 0

Sheet Memberships
A1: Member Name | B1: Sports Type | C1: Membership Type | D1: Start Date | E1: Amount Collected
A2: Vipin | B2: Pickleball | C2: Rally Pack (15) | D2: 46024 | E2: 9600
A4: Total | E4: =SUM(E2) -> 9600

Sheet Other Income
A1: Month | B1: Coaching | C1: Sports Type | D1: Type | E1: Amount Collected
A2: Jan | B2: Basketball Coaching | C2: Basketball | D2: 3 days in week | E2: 18000
