Workbook

Sheet Summary
B2: 1 - 31 July
B3: Particulars | C3: Amount
C4: Pickleball
B5: Pay & Play | C5: =sum(C6,C12) -> 56151
B6: Online | C6: =sum(C7:C11) -> 35361
B7: District | C7: =District!C4 -> 35361
B8: Hudle | C8: 0
B9: Playo | C9: 0
B10: Khelomore | C10: 0
B11: Zplys | C11: 0
B12: Offline | C12: =sum(C13:C14) -> 20790
B13: Bookings | C13: ='Offline & RG Community'!D33 -> 20790
B14: Memberships | C14: 0
B15: Community | C15: =sum(C16:C17) -> 6080
B16: Pickup games | C16: ='Offline & RG Community'!E33+'Offline & RG Community'!B37 -> 6080
B17: Social Events/Tournaments | C17: 0
B18: Academy | C18: 0
B19: Events & Partnership | C19: =sum(C20,C21) -> 0
B20: Corporate events | C20: 0
B21: All B2B partnerships | C21: 0
B22: Commerce | C22: =sum(C23:C25) -> 4975
B23: Product rental | C23: ='Offline & RG Community'!F33 -> 4800
B24: Product sales | C24: 0
B25: F&B | C25: ='Offline & RG Community'!G33 -> 175
B26: Other Income | C26: 0
B27: Total Gross Revenue (A) | C27: =C6+C12+C15+C18+C19+C22+C26 -> 67206
B28: GST (B) | C28: =C27-(C27/1.18) -> 10251.763
B29: Commissions (C) | C29: ='Offline & RG Community'!I33+'Offline & RG Community'!C37+District!D2+District!E2 -> 3236.9875
B30: Total Revenue post GST | C30: =C27-C28-C29 -> 53717.25

Sheet Offline & RG Community
A1: Date | B1: Day | C1: Offline booking hours | D1: Booking Revenue | E1: Community Revenue | F1: Paddle Rental | G1: F&B | H1: Total Revenue | I1: Payment Gateway | J1: Net Revenue
A2: 46204 | B2: Wednesday | C2: 1 | D2: 0 | E2: 1080 | F2: 0 | G2: 0 | H2: =sum(D2:G2) -> 1080 | I2: =H2*1.75% -> 18.9 | J2: =H2-I2 -> 1061.1
A3: 46205 | B3: Thursday | C3: 3.5 | D3: 2520 | E3: 0 | F3: 0 | G3: 0 | H3: =sum(D3:G3) -> 2520 | I3: =H3*1.75% -> 44.1 | J3: =H3-I3 -> 2475.9
A4: 46206 | B4: Friday | C4: 1 | D4: 920 | E4: 0 | F4: 200 | G4: 0 | H4: =sum(D4:G4) -> 1120 | I4: =H4*1.75% -> 19.6 | J4: =H4-I4 -> 1100.4
A5: 46207 | B5: Saturday | C5: 1 | D5: 720 | E5: 0 | F5: 300 | G5: 0 | H5: =sum(D5:G5) -> 1020 | I5: =H5*1.75% -> 17.85 | J5: =H5-I5 -> 1002.15
A6: 46208 | B6: Sunday | C6: 0 | D6: 0 | E6: 0 | F6: 0 | G6: 0 | H6: =sum(D6:G6) -> 0 | I6: =H6*1.75% -> 0 | J6: =H6-I6 -> 0
A7: 46209 | B7: Monday | C7: 1 | D7: 720 | E7: 0 | F7: 150 | G7: 0 | H7: =sum(D7:G7) -> 870 | I7: =H7*1.75% -> 15.225 | J7: =H7-I7 -> 854.775
A8: 46210 | B8: Tuesday | C8: 0 | D8: 0 | E8: 0 | F8: 0 | G8: 0 | H8: =sum(D8:G8) -> 0 | I8: =H8*1.75% -> 0 | J8: =H8-I8 -> 0
A9: 46211 | B9: Wednesday | C9: 0 | D9: 0 | E9: 0 | F9: 0 | G9: 0 | H9: =sum(D9:G9) -> 0 | I9: =H9*1.75% -> 0 | J9: =H9-I9 -> 0
A10: 46212 | B10: Thursday | C10: 0 | D10: 0 | E10: 0 | F10: 0 | G10: 35 | H10: =sum(D10:G10) -> 35 | I10: =H10*1.75% -> 0.6125 | J10: =H10-I10 -> 34.3875
A11: 46213 | B11: Friday | C11: 1 | D11: 720 | E11: 480 | F11: 0 | G11: 0 | H11: =sum(D11:G11) -> 1200 | I11: =H11*1.75% -> 21 | J11: =H11-I11 -> 1179
A12: 46214 | B12: Saturday | C12: 0 | D12: 0 | E12: 0 | F12: 200 | G12: 0 | H12: =sum(D12:G12) -> 200 | I12: =H12*1.75% -> 3.5 | J12: =H12-I12 -> 196.5
A13: 46215 | B13: Sunday | C13: 1.5 | D13: 1080 | E13: 1920 | F13: 500 | G13: 0 | H13: =sum(D13:G13) -> 3500 | I13: =H13*1.75% -> 61.25 | J13: =H13-I13 -> 3438.75
... A32: 46234 | B32: Friday | C32: 0 | D32: 0 | E32: 0 | F32: 0 | G32: 0 | H32: =sum(D32:G32) -> 0 | I32: =H32*1.75% -> 0 | J32: =H32-I32 -> 0
A33: Total | D33: =SUM(D1:D32) -> 20790 | E33: =SUM(E1:E32) -> 4120 | F33: =SUM(F1:F32) -> 4800 | G33: =SUM(G1:G32) -> 175 | H33: =SUM(H1:H32) -> 29885 | I33: =SUM(I1:I32) -> 522.9875 | J33: =SUM(J1:J32) -> 29362.013
A35: Misfits
A36: Date | B36: Amount | C36: Commission | D36: Net Revenue
A37: 46204 | B37: 1960 | C37: =B37*10% -> 196 | D37: =B37-C37 -> 1764

Sheet District
A1: Link | B1: Date | C1: Paid to District | D1: Commissions (₹) | E1: GST on Commission | F1: Net Revenue | G1: TCS | H1: TDS | I1: Final Amount (₹)
B2: 1 - 31 July | C2: 35361 | D2: 2475 | E2: 43 | F2: =C2-D2-E2 -> 32843 | G2: 17 | H2: 3 | I2: =F2-G2-H2 -> 32823
B4: Total | C4: =SUM(C2:C3) -> 35361 | F4: =SUM(F2:F3) -> 32843 | I4: =SUM(I2:I3) -> 32823
