Workbook

Sheet Summary
B2: Date: 1 - 31 Mar
B3: Particulars | C3: Amount
B4: Offline | C4: =SUM(C5,C6,C7,C8) -> 110460
B5: Rentals | C5: ='Offline & RG Community'!G33 -> 12700
B6: F&B | C6: 0
B7: Product Sales | C7: =0 -> 0
B8: Bookings | C8: ='Offline & RG Community'!E33 -> 97760
B9: Online: Third Party Platform | C9: =SUM(C10:C14) -> 45510
B10: Hudle | C10: =Hudle!C4 -> 28110
B11: Playo | C11: =Playo!C4 -> 5000
B12: District | C12: =District!C4 -> 12400
B13: Khelomore | C13: 0
B14: Zplys | C14: 0
B15: Community | C15: =sum(C16:C19) -> 2400
B16: Courtly (Organized by RallyGully) | C16: 0
B17: Sportomic (Organized by RallyGully) | C17: 0
B18: Rallygully Community games | C18: ='Offline & RG Community'!F33 -> 600
B19: Misfits Community | C19: =Misfits!C2 -> 1800
B20: Memberships | C20: =Membership!E6 -> 62880
B21: Coaching | C21: 0
B22: Corporate Events | C22: ='Corporate Events'!F3 -> 5520
B23: Brand Activation | C23: 0
B24: Other Income | C24: 0
B25: Total Gross Revenue | C25: =sum(C23,C24,C22,C20,C15,C9,C4) -> 226770
B26: Total Net Revenue (Post Commissions) | C26: ='Offline & RG Community'!H33+Hudle!E4+Playo!F4+District!F4+Membership!E6+'Corporate Events'!F3+Misfits!E2 -> 221956.66
B27: Total Revenue post GST | C27: =C26/1.18 -> 188098.86

Sheet Offline & RG Community
A1: Date | B1: Day | C1: Offline booking hours | D1: Discount Given | E1: Booking Revenue | F1: Community Revenue | G1: Paddle Rental | H1: Total Revenue
A2: 1 Mar | B2: Sunday | C2: 7 | D2: 30% and 20% | E2: 5460 | F2: 0 | G2: 650 | H2: =E2+F2+G2 -> 6110
A3: 2 Mar | B3: Monday | C3: 3 | D3: 30% and 20% | E3: 3200 | F3: 0 | G3: 475 | H3: =E3+F3+G3 -> 3675
A4: 3 Mar | B4: Tuesday | C4: 3.5 | D4: 30% and 20% | E4: 1950 | F4: 0 | G4: 350 | H4: =E4+F4+G4 -> 2300
A5: 4 Mar | B5: Wednesday | C5: 4 | D5: 30% and 20% | E5: 3200 | F5: 0 | G5: 450 | H5: =E5+F5+G5 -> 3650
A6: 5 Mar | B6: Thursday | C6: 2 | D6: 30% and 20% | E6: 1920 | F6: 0 | G6: 100 | H6: =E6+F6+G6 -> 2020
A7: 6 Mar | B7: Friday | C7: 5.5 | D7: 30% and 20% | E7: 3520 | F7: 0 | G7: 550 | H7: =E7+F7+G7 -> 4070
A8: 7 Mar | B8: Saturday | C8: 3.5 | D8: 30% and 20% | E8: 1960 | F8: 600 | G8: 400 | H8: =E8+F8+G8 -> 2960
A9: 8 Mar | B9: Sunday | C9: 2 | D9: 30% and 20% | E9: 1280 | F9: 0 | G9: 200 | H9: =E9+F9+G9 -> 1480
A10: 9 Mar | B10: Monday | C10: 1 | D10: 30% and 20% | E10: 640 | F10: 0 | G10: 300 | H10: =E10+F10+G10 -> 940
A11: 10 Mar | B11: Tuesday | C11: 2.5 | D11: 30% and 20% | E11: 1600 | F11: 0 | G11: 200 | H11: =E11+F11+G11 -> 1800
A12: 11 Mar | B12: Wednesday | C12: 5 | D12: 30% and 20% | E12: 4440 | F12: 0 | G12: 300 | H12: =E12+F12+G12 -> 4740
A13: 12 Mar | B13: Thursday | C13: 8 | D13: 30% and 20% | E13: 7510 | F13: 0 | G13: 300 | H13: =E13+F13+G13 -> 7810
... A32: 31 Mar | B32: Tuesday | C32: 2 | D32: 30% and 20% | E32: 1920 | F32: 0 | G32: 100 | H32: =E32+F32+G32 -> 2020
A33: Total | C33: =SUM(C1:C32) -> 117 | E33: =SUM(E1:E32) -> 97760 | F33: =SUM(F1:F32) -> 600 | G33: =SUM(G1:G32) -> 12700 | H33: =SUM(H1:H32) -> 111060

Sheet Hudle
A1: Link | B1: Date | C1: Paid to Hudle | D1: Commisions (Including GST) | E1: Net Revenue | F1: TDS | G1: TCS | H1: Amount
B2: 1 - 23 Mar | C2: 17920 | D2: 2371.2 | E2: =C2-D2 -> 15548.8 | F2: 15.45 | G2: 77.28 | H2: 15776.04
B3: 23 - 31 Mar | C3: 10190 | D3: 1331.2 | E3: =C3-D3 -> 8858.8 | F3: 8.67 | G3: 43.39 | H3: 8856.76
B4: Total | C4: =SUM(C2:C3) -> 28110 | E4: =SUM(E2:E3) -> 24407.6 | H4: =SUM(H2:H3) -> 24632.8

Sheet Playo
A1: Link | B1: Date | C1: Paid to Playo (₹) | D1: Commissions (₹) | E1: GST (₹) | F1: Net Revenue | G1: TDS (₹) | H1: TCS (₹) | I1: Final Amount (₹)
B2: 1 - 22 Mar | C2: 4200 | D2: 294 | E2: 52.92 | F2: =C2-D2-E2 -> 3853.08 | G2: 14.2 | H2: 2.84 | I2: 2476.04
B3: 23 - 31 Mar | C3: 800 | D3: 56 | E3: 10.08 | F3: =C3-D3-E3 -> 733.92 | G3: 0.8 | H3: 4 | I3: 729.12
B4: Total | C4: =SUM(C2:C3) -> 5000 | F4: =SUM(F2:F3) -> 4587 | I4: =SUM(I2:I3) -> 3205.16

Sheet District
A1: Link | B1: Date | C1: Paid to District | D1: Commissions (₹) | E1: GST on Commission | F1: Net Revenue | G1: TCS | H1: TDS | I1: Final Amount (₹)
B2: 1 - 24 Mar | C2: 9600 | D2: 230.4 | E2: 41.46 | F2: =C2-D2-E2 -> 9328.14 | G2: 45.6 | H2: 9 | I2: 8793.4
B3: 25 - 31 Mar | C3: 2800 | D3: 56 | E3: 10.08 | F3: =C3-D3-E3 -> 2733.92 | G3: 14 | H3: 2.8 | I3: 2717.28
B4: Total | C4: =SUM(C2:C3) -> 12400 | F4: =SUM(F2:F3) -> 12062.06 | I4: =SUM(I2:I3) -> 11510.68

Sheet Misfits
A1: Link | B1: Date | C1: Paid to Misfits (₹) | D1: Comission (20%) | E1: Net Revenue | F1: TDS | G1: Final Amount (₹)
B2: 1 - 31 Mar | C2: 1800 | D2: =C2*20% -> 360 | E2: =C2-D2 -> 1440 | F2: =C2*2% -> 36 | G2: =E2-F2 -> 1404

Sheet Membership
A1: Member Name | B1: Sports Type | C1: Membership Type | D1: Start Date | E1: Amount Collected
A2: Indian School of hospitality | B2: Pickle & Box | C2: Collab | D2: 46082 | E2: 18880
A3: Akshay | B3: Pickleball | C3: Pro Pack (30) | D3: 46086 | E3: 14000
A4: Sumit | B4: Pickleball | C4: Pro Pack (30) | D4: 46094 | E4: 15000
A5: Ritesh | B5: Pickleball | C5: Pro Pack (30) | D5: 46110 | E5: 15000
A6: Total | E6: =SUM(E2:E5) -> 62880

Sheet Corporate Events
A1: Date | B1: Name | C1: Type | D1: Sports Type | E1: Deliverables | F1: Amount Collected
A2: Mar | B2: Bio Gas KLJ | C2: Team Event | D2: Box Turf | E2: 4 hours of Turf | F2: 5120
A3: Total | F3: 5520
