Workbook

Sheet Summary
B2: 1 - 30 Sept
B3: Particulars | C3: Amount
C4: Total | D4: Pickleball | E4: Turf | F4: Padel
B5: Pay & Play | C5: =sum(C6,C12) -> 39849 | D5: =sum(D6,D12) -> 12270 | E5: =sum(E6,E12) -> 27579 | F5: 0
B6: Online | C6: =sum(C7:C11) -> 37149 | D6: =sum(D7:D11) -> 10970 | E6: =sum(E7:E11) -> 26179 | F6: 0
B7: District | C7: =District!C4 -> 2990 | D7: =District!B6 -> 2990 | E7: =District!B7 -> 0 | F7: 0
B8: Hudle | C8: =Hudle!C2 -> 700 | D8: =Hudle!B5 -> 700 | E8: =Hudle!B6 -> 0 | F8: 0
B9: Playo | C9: =Playo!C2 -> 28705 | D9: =Playo!B5 -> 7280 | E9: =Playo!B6 -> 21425 | F9: 0
B10: Khelomore | C10: =Khelomore!B2 -> 4754 | D10: =Khelomore!B6 -> 0 | E10: =Khelomore!B7 -> 4754 | F10: 0
B11: Zplys | C11: 0 | D11: 0 | E11: 0 | F11: 0
B12: Offline | C12: =sum(C13:C14) -> 2700 | D12: =sum(D13:D14) -> 1300 | E12: =sum(E13:E14) -> 1400 | F12: =sum(F13:F14) -> 0
B13: Bookings | C13: ='Offline & RG Community'!D32+'Offline & RG Community'!E32 -> 2700 | D13: ='Offline & RG Community'!D32 -> 1300 | E13: ='Offline & RG Community'!E32 -> 1400 | F13: 0
B14: Memberships | C14: 0 | D14: 0 | E14: 0 | F14: 0
B15: Community | C15: =sum(C16:C18) -> 0 | D15: =sum(D16:D18) -> 0 | E15: =sum(E16:E18) -> 0 | F15: =sum(F16:F18) -> 0
B16: Pickup games | C16: 0 | D16: 0 | E16: 0 | F16: 0
B17: Social Events/Tournaments | C17: 0 | D17: 0 | E17: 0 | F17: 0
B18: Community Partnerships | C18: 0 | D18: 0 | E18: 0 | F18: 0
B19: Academy | C19: 0 | D19: 0 | E19: 0 | F19: 0
B20: B2B | C20: =sum(C21) -> 2720 | D20: =sum(D21) -> 0 | E20: =sum(E21) -> 2720 | F20: 0
B21: Corporate events | C21: =B2B!E2 -> 2720 | D21: 0 | E21: =B2B!E2 -> 2720 | F21: 0
B22: All B2B partnerships | C22: 0 | D22: =SUM(D23:D26) -> 0 | E22: 0 | F22: 0
B23: Commerce | C23: =sum(C24:C26) -> 0 | D23: =sum(D24:D26) -> 0 | E23: =sum(E24:E26) -> 0 | F23: 0
B24: Product rental | C24: 0 | D24: 0 | E24: 0 | F24: 0
B25: Product sales | C25: 0 | D25: 0 | E25: 0 | F25: 0
B26: F&B | C26: 0 | D26: 0 | E26: 0 | F26: 0
B27: Other Income | C27: 118000 | D27: 0 | E27: 0 | F27: 118000
B28: Total Gross Revenue | C28: =C5+C15+C19+C20+C23+C27 -> 160569 | D28: =D5+D15+D19+D20+D23+D27 -> 12270 | E28: =E5+E15+E19+E20+E23+E27 -> 30299 | F28: =F5+F15+F19+F20+F23+F27 -> 118000
B29: GST | C29: =C28-(C28/1.18) -> 24493.576
B30: Net Revenue Post GST | C30: =C28-C29 -> 136075.42
B31: Commissions, Payment gateway & Event Expense | C31: ='Offline & RG Community'!I32+District!E4+District!D4+Hudle!D3+Playo!E3+Playo!D3+Khelomore!C4+B2B!F2 -> 3495.55
B32: Net Revenue | C32: =C28-C29-C31 -> 132579.87

Sheet Offline & RG Community
A1: Date | B1: Day | C1: Offline booking hours | D1: Booking Revenue | E1: Booking Revenue (Turf) | F1: Community Revenue | G1: Paddle Rental | H1: Total Revenue | I1: Payment Gateway | J1: Net Revenue
A2: 46266 | B2: Tuesday | C2: 0 | D2: 0 | E2: 0 | F2: 0 | G2: 0 | H2: =SUM(D2:G2) -> 0 | I2: =H2*1.75% -> 0 | J2: =H2-I2 -> 0
A3: 46267 | B3: Wednesday | C3: 0 | D3: 0 | E3: 0 | F3: 0 | G3: 0 | H3: =SUM(D3:G3) -> 0 | I3: =H3*1.75% -> 0 | J3: =H3-I3 -> 0
A4: 46268 | B4: Thursday | C4: 0 | D4: 0 | E4: 0 | F4: 0 | G4: 0 | H4: =SUM(D4:G4) -> 0 | I4: =H4*1.75% -> 0 | J4: =H4-I4 -> 0
A5: 46269 | B5: Friday | C5: 0 | D5: 0 | E5: 0 | F5: 0 | G5: 0 | H5: =SUM(D5:G5) -> 0 | I5: =H5*1.75% -> 0 | J5: =H5-I5 -> 0
A6: 46270 | B6: Saturday | C6: 0 | D6: 0 | E6: 0 | F6: 0 | G6: 0 | H6: =SUM(D6:G6) -> 0 | I6: =H6*1.75% -> 0 | J6: =H6-I6 -> 0
A7: 46271 | B7: Sunday | C7: 0 | D7: 0 | E7: 0 | F7: 0 | G7: 0 | H7: =SUM(D7:G7) -> 0 | I7: =H7*1.75% -> 0 | J7: =H7-I7 -> 0
A8: 46272 | B8: Monday | C8: 0 | D8: 0 | E8: 0 | F8: 0 | G8: 0 | H8: =SUM(D8:G8) -> 0 | I8: =H8*1.75% -> 0 | J8: =H8-I8 -> 0
A9: 46273 | B9: Tuesday | C9: 0 | D9: 0 | E9: 0 | F9: 0 | G9: 0 | H9: =SUM(D9:G9) -> 0 | I9: =H9*1.75% -> 0 | J9: =H9-I9 -> 0
A10: 46274 | B10: Wednesday | C10: 0 | D10: 0 | E10: 0 | F10: 0 | G10: 0 | H10: =SUM(D10:G10) -> 0 | I10: =H10*1.75% -> 0 | J10: =H10-I10 -> 0
A11: 46275 | B11: Thursday | C11: 1 | D11: 600 | E11: 0 | F11: 0 | G11: 0 | H11: =SUM(D11:G11) -> 600 | I11: =H11*1.75% -> 10.5 | J11: =H11-I11 -> 589.5
A12: 46276 | B12: Friday | C12: 0 | D12: 0 | E12: 0 | F12: 0 | G12: 0 | H12: =SUM(D12:G12) -> 0 | I12: =H12*1.75% -> 0 | J12: =H12-I12 -> 0
A13: 46277 | B13: Saturday | C13: 0 | D13: 0 | E13: 0 | F13: 0 | G13: 0 | H13: =SUM(D13:G13) -> 0 | I13: =H13*1.75% -> 0 | J13: =H13-I13 -> 0
... A31: 46295 | B31: Wednesday | C31: 0 | D31: 0 | E31: 0 | F31: 0 | G31: 0 | H31: =SUM(D31:G31) -> 0 | I31: =H31*1.75% -> 0 | J31: =H31-I31 -> 0
A32: Total | D32: =SUM(D2:D31) -> 1300 | E32: =SUM(E2:E31) -> 1400 | F32: =SUM(F2:F31) -> 0 | G32: =SUM(G2:G31) -> 0 | H32: =SUM(H2:H31) -> 2700 | I32: =SUM(I2:I31) -> 47.25 | J32: =SUM(J2:J31) -> 2652.75

Sheet District
A1: Link | B1: Date | C1: Paid to District | D1: Commissions (₹) | E1: GST on Commission | F1: Net Revenue | G1: TCS | H1: TDS | I1: Final Amount (₹)
B2: 1 - 30 Sept | C2: 2990 | D2: 179 | E2: 32 | F2: =C2-D2-E2 -> 2779 | G2: 14 | H2: 3 | I2: =F2-G2-H2 -> 2762
B4: Total | C4: =SUM(C2:C3) -> 2990 | D4: =SUM(D2:D3) -> 179 | E4: =SUM(E2:E3) -> 32 | F4: =SUM(F2:F3) -> 2779 | I4: =SUM(I2:I3) -> 2762
A6: Pickleball | B6: =C2 -> 2990
A7: Turf | B7: 0

Sheet Hudle
A1: Link | B1: Date | C1: Paid to Hudle | D1: Commisions (Including GST) | E1: Net Revenue | F1: TDS | G1: TCS | H1: Amount
B2: 1 - 30 Sept | C2: 700 | D2: 91 | E2: =C2-D2 -> 609 | F2: 0.5 | G2: 3 | H2: =E2-F2-G2 -> 605.5
B3: Total | C3: =SUM(C2) -> 700 | D3: =SUM(D2) -> 91 | E3: =SUM(E2) -> 609 | H3: =SUM(H2) -> 605.5
A5: Pickleball | B5: =C3-B6-B7 -> 700
A6: Turf | B6: 0

Sheet Playo
A1: Link | B1: Date | C1: Paid to Playo (₹) | D1: Commissions (₹) | E1: GST (₹) | F1: Net Revenue | G1: TDS (₹) | H1: TCS (₹) | I1: Final Amount (₹)
B2: 1 - 30 Sept | C2: 28705 | D2: 2450 | E2: 411 | F2: =C2-D2-E2 -> 25844 | G2: 19 | H2: 0 | I2: =F2-G2 -> 25825
B3: Total | C3: =sum(C2) -> 28705 | D3: =sum(D2) -> 2450 | E3: =sum(E2) -> 411 | F3: =sum(F2) -> 25844 | I3: =sum(I2) -> 25825
A5: Pickleball | B5: 7280
A6: Turf | B6: =C3-B5 -> 21425

Sheet Khelomore
A1: Date | B1: Paid to Khelomore (₹) | C1: Commissions (₹) | D1: Final Amount (₹)
A2: 1 - 30 Sept | B2: 4754 | C2: =B2*5% -> 237.7 | D2: =B2-C2 -> 4516.3
A4: Total | B4: =SUM(B2) -> 4754 | C4: =SUM(C2) -> 237.7 | D4: =SUM(D2) -> 4516.3
A6: Pickleball | B6: 0
A7: Turf | B7: 4754

Sheet B2B
A1: Start Month | B1: Partnership Type | C1: Name of Brand/Person | D1: Deliverables | E1: Amount (₹) | F1: Payment Gateway | G1: Net Revenue
A2: Sept | B2: Event Booking | C2: HOF Pune Event | D2: 2 Hours of turf | E2: 2720 | F2: =E2*1.75% -> 47.6 | G2: =E2-F2 -> 2672.4

Sheet Other Income
A1: Month | B1: Sports Type | C1: Amount Collected
A2: Sept | B2: Padel Operations & Management Fees | C2: 118000
