Workbook

Sheet Summary
B2: 1 - 31 May
B3: Particulars | C3: Amount
C4: Total | D4: Pickleball | E4: Turf | F4: Padel
B5: Pay & Play | C5: =sum(C6,C12) -> 134927 | D5: =sum(D6,D12) -> 87588 | E5: =sum(E6,E12) -> 50432 | F5: 0
B6: Online | C6: =sum(C7:C11) -> 96037 | D6: =sum(D7:D11) -> 59638 | E6: =sum(E7:E11) -> 39492 | F6: 0
B7: District | C7: =District!C4 -> 9579 | D7: =District!B6 -> 5584 | E7: =District!B7 -> 3995 | F7: 0
B8: Hudle | C8: =Hudle!C2 -> 9213 | D8: =Hudle!B5 -> 9213 | E8: =Hudle!B6 -> 0 | F8: 0
B9: Playo | C9: =Playo!C2 -> 60245 | D9: =Playo!B5 -> 30241 | E9: =Playo!B6 -> 33097 | F9: 0
B10: Khelomore | C10: =Khelomore!C2 -> 17000 | D10: =Khelomore!B6 -> 14600 | E10: =Khelomore!B7 -> 2400 | F10: 0
B11: Zplys | C11: 0 | D11: 0 | E11: 0 | F11: 0
B12: Offline | C12: =sum(C13:C14) -> 38890 | D12: =sum(D13:D14) -> 27950 | E12: =sum(E13:E14) -> 10940 | F12: =sum(F13:F14) -> 0
B13: Bookings | C13: ='Offline & RG Community'!E33+'Offline & RG Community'!F33 -> 38890 | D13: ='Offline & RG Community'!E33 -> 27950 | E13: ='Offline & RG Community'!F33 -> 10940 | F13: 0
B14: Memberships | C14: 0 | D14: 0 | E14: 0 | F14: 0
B15: Community | C15: =sum(C16:C17) -> 0 | D15: =sum(D16:D17) -> 0 | E15: =sum(E16:E17) -> 0 | F15: 0
B16: Pickup games | C16: 0 | D16: 0 | E16: 0 | F16: 0
B17: Social Events/Tournaments | C17: 0 | D17: 0 | E17: 0 | F17: 0
B18: Academy | C18: 0 | D18: 0 | E18: 0 | F18: 0
B19: Events & Partnership | C19: =sum(C20) -> 0 | D19: =sum(D20) -> 0 | E19: =sum(E20) -> 0 | F19: 0
B20: Corporate events | C20: 0 | D20: 0 | E20: 0 | F20: 0
B21: All B2B partnerships | C21: 0 | D21: =SUM(D22:D25) -> 0 | E21: 0 | F21: 0
B22: Commerce | C22: =sum(C23:C25) -> 0 | D22: =sum(D23:D25) -> 0 | E22: =sum(E23:E25) -> 0 | F22: 0
B23: Product rental | C23: 0 | D23: 0 | E23: 0 | F23: 0
B24: Product sales | C24: 0 | D24: 0 | E24: 0 | F24: 0
B25: F&B | C25: 0 | D25: 0 | E25: 0 | F25: 0
B26: Other Income | C26: 118000 | D26: 0 | E26: 0 | F26: 118000
B27: Total Gross Revenue | C27: =sum(C5,C15,C18,C19,C22,C26) -> 252927 | D27: =sum(D5,D15,D18,D19,D22,D26) -> 87588 | E27: =sum(E5,E15,E18,E19,E22,E26) -> 50432 | F27: =sum(F5,F15,F18,F19,F22,F26) -> 118000
B28: Total Net Revenue (Post Commissions) | C28: ='Offline & RG Community'!I33+Hudle!E3+District!F4+Playo!F3+Khelomore!E4+'Other Income'!C2 -> 242538.74
B29: Total Revenue post GST | C29: =C28/1.18 -> 205541.31

Sheet Offline & RG Community
A1: Date | B1: Day | C1: Offline booking hours | D1: Discount Given | E1: Pickleball | F1: Turf | G1: Total Revenue | H1: Payment Gateway | I1: Net Revenue
A2: 46143 | B2: Friday | C2: 3.5 | D2: 15% & 20% | E2: 2450 | F2: 0 | G2: =sum(E2:F2) -> 2450 | H2: =G2*2.5%*1.18 -> 72.275 | I2: =G2-H2 -> 2377.725
A3: 46144 | B3: Saturday | C3: 0.5 | D3: 15% & 20% | E3: 350 | F3: 0 | G3: =sum(E3:F3) -> 350 | H3: =G3*2.5%*1.18 -> 10.325 | I3: =G3-H3 -> 339.675
A4: 46145 | B4: Sunday | C4: 2 | D4: 15% & 20% | E4: 1400 | F4: 0 | G4: =sum(E4:F4) -> 1400 | H4: =G4*2.5%*1.18 -> 41.3 | I4: =G4-H4 -> 1358.7
A5: 46146 | B5: Monday | C5: 2 | D5: 15% & 20% | E5: 1400 | F5: 0 | G5: =SUM(E5:F5) -> 1400 | H5: =G5*2.5%*1.18 -> 41.3 | I5: =G5-H5 -> 1358.7
A6: 46147 | B6: Tuesday | C6: 2 | D6: 15% & 20% | E6: 1350 | F6: 0 | G6: =SUM(E6:F6) -> 1350 | H6: =G6*2.5%*1.18 -> 39.825 | I6: =G6-H6 -> 1310.175
A7: 46148 | B7: Wednesday | C7: 0 | D7: 15% & 20% | E7: 0 | F7: 0 | G7: =SUM(F7) -> 0 | H7: =G7*2.5%*1.18 -> 0 | I7: =G7-H7 -> 0
A8: 46149 | B8: Thursday | C8: 0 | D8: 15% & 20% | E8: 0 | F8: 0 | G8: =SUM(E8:F8) -> 0 | H8: =G8*2.5%*1.18 -> 0 | I8: =G8-H8 -> 0
A9: 46150 | B9: Friday | C9: 0 | D9: 15% & 20% | E9: 0 | F9: 0 | G9: 0 | H9: =G9*2.5%*1.18 -> 0 | I9: =G9-H9 -> 0
A10: 46151 | B10: Saturday | C10: 1 | D10: 15% & 20% | E10: 700 | F10: 0 | G10: =SUM(E10:F10) -> 700 | H10: =G10*2.5%*1.18 -> 20.65 | I10: =G10-H10 -> 679.35
A11: 46152 | B11: Sunday | C11: 4.5 | D11: 15% & 20% | E11: 1750 | F11: 3600 | G11: =SUM(E11:F11) -> 5350 | H11: =G11*2.5%*1.18 -> 157.825 | I11: =G11-H11 -> 5192.175
A12: 46153 | B12: Monday | C12: 0 | D12: 15% & 20% | E12: 0 | F12: 0 | G12: =SUM(E12:F12) -> 0 | H12: =G12*2.5%*1.18 -> 0 | I12: =G12-H12 -> 0
A13: 46154 | B13: Tuesday | C13: 2 | D13: 15% & 20% | E13: 1400 | F13: 0 | G13: =SUM(E13:F13) -> 1400 | H13: =G13*2.5%*1.18 -> 41.3 | I13: =G13-H13 -> 1358.7
A14: 46155 | B14: Wednesday | C14: 0.5 | D14: 15% & 20% | E14: 350 | F14: 0 | G14: =SUM(E14:F14) -> 350 | H14: =G14*2.5%*1.18 -> 10.325 | I14: =G14-H14 -> 339.675
A15: 46156 | B15: Thursday | C15: 1.5 | D15: 15% & 20% | E15: 700 | F15: 90 | G15: =SUM(E15:F15) -> 790 | H15: =G15*2.5%*1.18 -> 23.305 | I15: =G15-H15 -> 766.695
A16: 46157 | B16: Friday | C16: 2 | D16: 15% & 20% | E16: 350 | F16: 2250 | G16: =SUM(E16:F16) -> 2600 | H16: =G16*2.5%*1.18 -> 76.7 | I16: =G16-H16 -> 2523.3
A17: 46158 | B17: Saturday | C17: 1 | D17: 15% & 20% | E17: 700 | F17: 0 | G17: =SUM(E17:F17) -> 700 | H17: =G17*2.5%*1.18 -> 20.65 | I17: =G17-H17 -> 679.35
A18: 46159 | B18: Sunday | C18: 2.5 | D18: 15% & 20% | E18: 1750 | F18: 0 | G18: =SUM(E18:F18) -> 1750 | H18: =G18*2.5%*1.18 -> 51.625 | I18: =G18-H18 -> 1698.375
A19: 46160 | B19: Monday | C19: 1 | D19: 15% & 20% | E19: 700 | F19: 0 | G19: =SUM(E19:F19) -> 700 | H19: =G19*2.5%*1.18 -> 20.65 | I19: =G19-H19 -> 679.35
A20: 46161 | B20: Tuesday | C20: 0 | D20: 15% & 20% | E20: 0 | F20: 0 | G20: =SUM(E20:F20) -> 0 | H20: =G20*2.5%*1.18 -> 0 | I20: =G20-H20 -> 0
A21: 46162 | B21: Wednesday | C21: 0 | D21: 15% & 20% | E21: 0 | F21: 0 | G21: =SUM(E21:F21) -> 0 | H21: =G21*2.5%*1.18 -> 0 | I21: =G21-H21 -> 0
... A32: 46173 | B32: Sunday | C32: 2 | D32: 15% & 20% | E32: 700 | F32: 1400 | G32: =SUM(E32:F32) -> 2100 | H32: =G32*2.5%*1.18 -> 61.95 | I32: =G32-H32 -> 2038.05
A33: Total | C33: =SUM(C1:C32) -> 47.5 | E33: =SUM(E1:E32) -> 27950 | F33: =SUM(F1:F32) -> 10940 | G33: =SUM(G1:G32) -> 38890 | H33: =SUM(H1:H32) -> 1147.255 | I33: =SUM(I1:I32) -> 37742.745

Sheet District
A1: Link | B1: Date | C1: Paid to District | D1: Commissions (₹) | E1: GST on Commission | F1: Net Revenue | G1: TCS | H1: TDS | I1: Final Amount (₹)
B2: 1 - 31 May | C2: 9579 | D2: 574 | E2: 103 | F2: =C2-D2-E2 -> 8902 | G2: 48 | H2: 9.6 | I2: =F2-G2-H2 -> 8844.4
B4: Total | C4: =SUM(C2:C3) -> 9579 | F4: =SUM(F2:F3) -> 8902 | I4: =SUM(I2:I3) -> 8844.4
A6: Pickleball | B6: =C4-B7-B8 -> 5584
A7: Turf | B7: 3995

Sheet Hudle
A1: Link | B1: Date | C1: Paid to Hudle | D1: Commisions (Including GST) | E1: Net Revenue | F1: TDS | G1: TCS | H1: Amount
B2: 1 - 31 May | C2: 9213 | D2: 1197 | E2: =C2-D2 -> 8016 | F2: 7.8 | G2: 39 | H2: 7969
B3: Total | C3: =SUM(C2) -> 9213 | E3: =SUM(E2) -> 8016 | H3: =SUM(H2) -> 7969
A5: Pickleball | B5: =C3-B6-B7 -> 9213
A6: Turf | B6: 0

Sheet Playo
A1: Link | B1: Date | C1: Paid to Playo (₹) | D1: Commissions (₹) | E1: GST (₹) | F1: Net Revenue | G1: TDS (₹) | H1: TCS (₹) | I1: Final Amount (₹)
B2: 1 - 31 May | C2: 60245 | D2: 5523 | E2: 994 | F2: =C2-D2-E2 -> 53728 | G2: 38 | H2: 0 | I2: 53690
B3: Total | C3: =sum(C2) -> 60245 | F3: =sum(F2) -> 53728 | I3: =sum(I2) -> 53690
A5: Pickleball | B5: 30241
A6: Turf | B6: =30700+2397 -> 33097

Sheet Khelomore
A1: Link | B1: Date | C1: Paid to Khelomore (₹) | D1: Commissions (₹) | E1: Final Amount (₹)
B2: 1 - 31 May | C2: 17000 | D2: =C2*5% -> 850 | E2: =C2-D2 -> 16150
B4: Total | C4: =SUM(C2) -> 17000 | E4: =SUM(E2) -> 16150
A6: Pickleball | B6: =C4-B7-B8 -> 14600
A7: Turf | B7: 2400

Sheet Other Income
A1: Month | B1: Sports Type | C1: Amount Collected
A2: May | B2: Padel Operations & Management Fees | C2: 118000
