Workbook

Sheet Summary
B2: 1 - 30 Sept
B3: Particulars | C3: Amount
C4: Pickleball
B5: Pay & Play | C5: =sum(C6,C12) -> 19999
B6: Online | C6: =sum(C7:C11) -> 14100
B7: District | C7: =District!C4 -> 14100
B8: Hudle | C8: 0
B9: Playo | C9: 0
B10: Khelomore | C10: 0
B11: Zplys | C11: 0
B12: Offline | C12: =sum(C13:C14) -> 5899
B13: Bookings | C13: ='Offline & RG Community'!D25 -> 399
B14: Memberships | C14: =Memberships!E2 -> 5500
B15: Community | C15: =sum(C16:C18) -> 399
B16: Pickup games | C16: ='Offline & RG Community'!E25 -> 399
B17: Social Events/Tournaments | C17: 0
B18: Community Partnership | C18: 0
B19: Academy | C19: 0
B20: B2B | C20: =sum(C21,C22) -> 0
B21: Corporate events | C21: 0
B22: All B2B partnerships | C22: 0
B23: Commerce | C23: =sum(C24:C26) -> 0
B24: Product rental | C24: ='Offline & RG Community'!F25 -> 0
B25: Product sales | C25: 0
B26: F&B | C26: 0
B27: Other Income | C27: 0
B28: Total Gross Revenue | C28: =C5+C15+C19+C20+C23+C27 -> 20398
B29: GST | C29: =C28-(C28/1.18) -> 3111.5593
B30: Net Revenue Post GST | C30: =C28-C29 -> 17286.441
B31: Commissions, Payment gateway & Event Expense | C31: ='Offline & RG Community'!I25+District!D4+District!E4+Memberships!F2 -> 1094.25
B32: Net Revenue | C32: =C28-C29-C31 -> 16192.191

Sheet Offline & RG Community
A1: Date | B1: Day | C1: Offline booking hours | D1: Discount Given | E1: Booking Revenue | F1: Community Revenue | G1: Paddle Rental | H1: Total Revenue | I1: Payment Gateway | J1: Net Revenue
A2: 46273 | B2: Tuesday | C2: 0 | D2: 0 | E2: 0 | F2: 0 | G2: 0 | H2: 0 | I2: =G2*1.75% -> 0 | J2: =G2-I2 -> 0
A3: 46274 | B3: Wednesday | C3: 0 | D3: 0 | E3: 0 | F3: 0 | G3: 0 | H3: 0 | I3: =G3*1.75% -> 0 | J3: =G3-I3 -> 0
A4: 46275 | B4: Thursday | C4: 0 | D4: 0 | E4: 0 | F4: 0 | G4: 0 | H4: 0 | I4: =G4*1.75% -> 0 | J4: =G4-I4 -> 0
A5: 46276 | B5: Friday | C5: 0 | D5: 0 | E5: 0 | F5: 0 | G5: 0 | H5: 0 | I5: =G5*1.75% -> 0 | J5: =G5-I5 -> 0
A6: 46277 | B6: Saturday | C6: 0 | D6: 0 | E6: 0 | F6: 0 | G6: 0 | H6: 0 | I6: =G6*1.75% -> 0 | J6: =G6-I6 -> 0
A7: 46278 | B7: Sunday | C7: 0 | D7: 0 | E7: 0 | F7: 0 | G7: 0 | H7: 0 | I7: =G7*1.75% -> 0 | J7: =G7-I7 -> 0
A8: 46279 | B8: Monday | C8: 0 | D8: 0 | E8: 0 | F8: 0 | G8: 0 | H8: 0 | I8: =G8*1.75% -> 0 | J8: =G8-I8 -> 0
A9: 46280 | B9: Tuesday | C9: 0 | D9: 0 | E9: 0 | F9: 0 | G9: 0 | H9: 0 | I9: =G9*1.75% -> 0 | J9: =G9-I9 -> 0
A10: 46281 | B10: Wednesday | C10: 0 | D10: 0 | E10: 0 | F10: 0 | G10: 0 | H10: 0 | I10: =G10*1.75% -> 0 | J10: =G10-I10 -> 0
A11: 46282 | B11: Thursday | C11: 0 | D11: 0 | E11: 0 | F11: 0 | G11: 0 | H11: 0 | I11: =G11*1.75% -> 0 | J11: =G11-I11 -> 0
A12: 46283 | B12: Friday | C12: 0 | D12: 0 | E12: 0 | F12: 0 | G12: 0 | H12: 0 | I12: =G12*1.75% -> 0 | J12: =G12-I12 -> 0
A13: 46284 | B13: Saturday | C13: 0 | D13: 0 | E13: 0 | F13: 0 | G13: 0 | H13: 0 | I13: =G13*1.75% -> 0 | J13: =G13-I13 -> 0
... A24: 46295 | B24: Wednesday | C24: 0 | D24: 0 | E24: 0 | F24: 0 | G24: 0 | H24: 0 | I24: =G24*1.75% -> 0 | J24: =G24-I24 -> 0
A25: Total | D25: =SUM(D2:D24) -> 399 | E25: =SUM(E2:E24) -> 399 | F25: =SUM(F2:F24) -> 0 | G25: =SUM(G2:G24) -> 0 | H25: =SUM(H2:H24) -> 399 | I25: =SUM(I2:I24) -> 0 | J25: =SUM(J2:J24) -> 0

Sheet District
A1: Link | B1: Date | C1: Paid to District | D1: Commissions (₹) | E1: GST on Commission | F1: Net Revenue | G1: TCS | H1: TDS | I1: Final Amount (₹)
B2: 1 - 30 Sept | C2: 14100 | D2: 846 | E2: 152 | F2: =C2-D2-E2 -> 13102 | G2: 68 | H2: 13 | I2: =F2-G2-H2 -> 13021
B4: Total | C4: =SUM(C2:C3) -> 14100 | D4: =SUM(D2:D3) -> 846 | E4: =SUM(E2:E3) -> 152 | F4: =SUM(F2:F3) -> 13102 | I4: =SUM(I2:I3) -> 13021

Sheet Memberships
A1: Month | B1: Member Name | C1: Sports Type | D1: Credits Issued | E1: Amount Collected | F1: Payment Gateway | G1: Net Revenue
A2: September | B2: Tanu | C2: Pickleball | D2: 10 Hours | E2: 5500 | F2: =E2*1.75% -> 96.25 | G2: =E2-F2 -> 5403.75
