Workbook

Sheet Summary
B2: 1 - 30 Sept
B3: Particulars | C3: Amount
C4: Total | D4: Pickleball | E4: Turf
B5: Pay & Play | C5: =sum(C6,C12) -> 183664 | D5: =sum(D6,D12) -> 100870 | E5: =sum(E6,E12) -> 82794
B6: Online | C6: =sum(C7:C11) -> 85044 | D6: =sum(D7:D11) -> 50150 | E6: =sum(E7:E11) -> 34894
B7: District | C7: =District!C3 -> 85044 | D7: =District!B5 -> 50150 | E7: =District!B6 -> 34894
B8: Hudle | C8: 0 | D8: 0 | E8: 0
B9: Playo | C9: 0 | D9: 0 | E9: 0
B10: Khelomore | C10: 0 | D10: 0 | E10: 0
B11: Zplys | C11: 0 | D11: 0 | E11: 0
B12: Offline | C12: =sum(C13:C14) -> 98620 | D12: =sum(D13:D14) -> 50720 | E12: =sum(E13:E14) -> 47900
B13: Bookings | C13: ='Offline & RG Community'!D32+'Offline & RG Community'!E32 -> 63020 | D13: ='Offline & RG Community'!D32 -> 41320 | E13: ='Offline & RG Community'!E32 -> 21700
B14: Memberships | C14: =Memberships!D4 -> 35600 | D14: =Memberships!D3/2 -> 9400 | E14: =Memberships!D3/2+Memberships!D2 -> 26200
B15: Community | C15: =sum(C16:C18) -> 1710 | D15: =sum(D16:D18) -> 1710 | E15: =sum(E16:E18) -> 0
B16: Pickup games | C16: ='Offline & RG Community'!F32 -> 1710 | D16: ='Offline & RG Community'!F32 -> 1710 | E16: 0
B17: Social Events/Tournaments | C17: 0 | D17: 0 | E17: 0
B18: Community Partnerships | C18: 0 | D18: 0 | E18: 0
B19: Academy | C19: 0 | D19: 0 | E19: 0
B20: Events & Partnership | C20: =sum(C21,C22) -> 1920 | D20: =sum(D21,D22) -> 0 | E20: =sum(E21,E22) -> 1920
B21: Corporate events | C21: ='Corporate Events'!E2 -> 1920 | D21: 0 | E21: ='Corporate Events'!E2 -> 1920
B22: All B2B partnerships | C22: 0 | D22: 0 | E22: 0
B23: Commerce | C23: =sum(C24:C26) -> 175 | D23: =sum(D24:D26) -> 175 | E23: =sum(E24:E26) -> 0
B24: Product rental | C24: ='Offline & RG Community'!G32 -> 175 | D24: ='Offline & RG Community'!G32 -> 175 | E24: 0
B25: Product sales | C25: 0 | D25: 0 | E25: 0
B26: F&B | C26: 0 | D26: 0 | E26: 0
B27: Other Income | C27: 0 | D27: 0 | E27: 0
B28: Total Gross Revenue | C28: =C6+C12+C15+C19+C20+C23+C27 -> 187469 | D28: =D6+D12+D15+D19+D20+D23+D27 -> 102755 | E28: =E6+E12+E15+E19+E20+E23+E27 -> 84714
B29: GST (B) | C29: =C28-(C28/1.18) -> 28596.966
B30: Net Revenue Post GST | C30: =C28-C29 -> 158872.03
B31: Commissions, Payment gateway & Event Expense(C) | C31: ='Offline & RG Community'!I32+District!E3+District!D3+Memberships!E4+'Corporate Events'!F2 -> 7499.4375
B32: Net Revenue (A-B-C) | C32: =C28-C29-C31 -> 151372.6

Sheet Offline & RG Community
A1: Date | B1: Day | C1: Offline booking hours | D1: Booking Revenue | E1: Booking Revenue (Turf) | F1: Community Revenue | G1: Paddle Rental | H1: Total Revenue | I1: Payment Gateway | J1: Net Revenue
A2: 46266 | B2: Tuesday | C2: 6.5 | D2: 2325 | E2: 3600 | F2: 0 | G2: 0 | H2: =sum(D2:G2) -> 5925 | I2: =H2*1.75% -> 103.6875 | J2: =H2-I2 -> 5821.3125
A3: 46267 | B3: Wednesday | C3: 2 | D3: 1400 | E3: 0 | F3: 0 | G3: 0 | H3: =sum(D3:G3) -> 1400 | I3: =H3*1.75% -> 24.5 | J3: =H3-I3 -> 1375.5
A4: 46268 | B4: Thursday | C4: 5 | D4: 700 | E4: 4800 | F4: 0 | G4: 0 | H4: =sum(D4:G4) -> 5500 | I4: =H4*1.75% -> 96.25 | J4: =H4-I4 -> 5403.75
A5: 46269 | B5: Friday | C5: 0 | D5: 0 | E5: 0 | F5: 0 | G5: 0 | H5: =sum(D5:G5) -> 0 | I5: =H5*1.75% -> 0 | J5: =H5-I5 -> 0
A6: 46270 | B6: Saturday | C6: 7 | D6: 2600 | E6: 3600 | F6: 0 | G6: 0 | H6: =sum(D6:G6) -> 6200 | I6: =H6*1.75% -> 108.5 | J6: =H6-I6 -> 6091.5
A7: 46271 | B7: Sunday | C7: 3.5 | D7: 2950 | E7: 0 | F7: 0 | G7: 0 | H7: =sum(D7:G7) -> 2950 | I7: =H7*1.75% -> 51.625 | J7: =H7-I7 -> 2898.375
A8: 46272 | B8: Monday | C8: 0.5 | D8: 325 | E8: 0 | F8: 0 | G8: 0 | H8: =sum(D8:G8) -> 325 | I8: =H8*1.75% -> 5.6875 | J8: =H8-I8 -> 319.3125
A9: 46273 | B9: Tuesday | C9: 2 | D9: 975 | E9: 0 | F9: 0 | G9: 0 | H9: =sum(D9:G9) -> 975 | I9: =H9*1.75% -> 17.0625 | J9: =H9-I9 -> 957.9375
A10: 46274 | B10: Wednesday | C10: 1.5 | D10: 975 | E10: 0 | F10: 0 | G10: 0 | H10: =sum(D10:G10) -> 975 | I10: =H10*1.75% -> 17.0625 | J10: =H10-I10 -> 957.9375
A11: 46275 | B11: Thursday | C11: 2.5 | D11: 1625 | E11: 0 | F11: 0 | G11: 0 | H11: =sum(D11:G11) -> 1625 | I11: =H11*1.75% -> 28.4375 | J11: =H11-I11 -> 1596.5625
A12: 46276 | B12: Friday | C12: 1 | D12: 1200 | E12: 0 | F12: 0 | G12: 0 | H12: =sum(D12:G12) -> 1200 | I12: =H12*1.75% -> 21 | J12: =H12-I12 -> 1179
A13: 46277 | B13: Saturday | C13: 8.5 | D13: 3575 | E13: 4800 | F13: 0 | G13: 0 | H13: =sum(D13:G13) -> 8375 | I13: =H13*1.75% -> 146.5625 | J13: =H13-I13 -> 8228.4375
... A15: 46279 | B15: Monday | C15: 1 | D15: 650 | E15: 0 | F15: 0 | G15: 0 | H15: =sum(D15:G15) -> 650 | I15: =H15*1.75% -> 11.375 | J15: =H15-I15 -> 638.625
A16: 46280 | B16: Tuesday | C16: 0 | D16: 0 | E16: 0 | F16: 0 | G16: 0 | H16: =sum(D16:G16) -> 0 | I16: =H16*1.75% -> 0 | J16: =H16-I16 -> 0 | K16: Report Not received
A17: 46281 | B17: Wednesday | C17: 1.5 | D17: 1025 | E17: 0 | F17: 640 | G17: 0 | H17: =sum(D17:G17) -> 1665 | I17: =H17*1.75% -> 29.1375 | J17: =H17-I17 -> 1635.8625
A18: 46282 | B18: Thursday | C18: 4 | D18: 2750 | E18: 0 | F18: 0 | G18: 0 | H18: =sum(D18:G18) -> 2750 | I18: =H18*1.75% -> 48.125 | J18: =H18-I18 -> 2701.875
A19: 46283 | B19: Friday | C19: 1 | D19: 650 | E19: 0 | F19: 0 | G19: 0 | H19: =sum(D19:G19) -> 650 | I19: =H19*1.75% -> 11.375 | J19: =H19-I19 -> 638.625
A20: 46284 | B20: Saturday | C20: 2.5 | D20: 1725 | E20: 0 | F20: 0 | G20: 0 | H20: =sum(D20:G20) -> 1725 | I20: =H20*1.75% -> 30.1875 | J20: =H20-I20 -> 1694.8125
A21: 46285 | B21: Sunday | C21: 1 | D21: 700 | E21: 0 | F21: 320 | G21: 0 | H21: =sum(D21:G21) -> 1020 | I21: =H21*1.75% -> 17.85 | J21: =H21-I21 -> 1002.15
A22: 46286 | B22: Monday | C22: 1 | D22: 650 | E22: 0 | F22: 0 | G22: 0 | H22: =sum(D22:G22) -> 650 | I22: =H22*1.75% -> 11.375 | J22: =H22-I22 -> 638.625
A23: 46287 | B23: Tuesday | C23: 1.5 | D23: 975 | E23: 0 | F23: 0 | G23: 0 | H23: =sum(D23:G23) -> 975 | I23: =H23*1.75% -> 17.0625 | J23: =H23-I23 -> 957.9375
A24: 46288 | B24: Wednesday | C24: 3.5 | D24: 2425 | E24: 0 | F24: 750 | G24: 0 | H24: =sum(D24:G24) -> 3175 | I24: =H24*1.75% -> 55.5625 | J24: =H24-I24 -> 3119.4375
A25: 46289 | B25: Thursday | C25: 3 | D25: 1950 | E25: 0 | F25: 0 | G25: 175 | H25: =sum(D25:G25) -> 2125 | I25: =H25*1.75% -> 37.1875 | J25: =H25-I25 -> 2087.8125
A26: 46290 | B26: Friday | C26: 0.5 | D26: 375 | E26: 0 | F26: 0 | G26: 0 | H26: =sum(D26:G26) -> 375 | I26: =H26*1.75% -> 6.5625 | J26: =H26-I26 -> 368.4375
A27: 46291 | B27: Saturday | C27: 4.5 | D27: 2975 | E27: 0 | F27: 0 | G27: 0 | H27: =sum(D27:G27) -> 2975 | I27: =H27*1.75% -> 52.0625 | J27: =H27-I27 -> 2922.9375
A28: 46292 | B28: Sunday | C28: 0 | D28: 0 | E28: 0 | F28: 0 | G28: 0 | H28: =sum(D28:G28) -> 0 | I28: =H28*1.75% -> 0 | J28: =H28-I28 -> 0
... A31: 46295 | B31: Wednesday | C31: 5.5 | D31: 2275 | E31: 1300 | F31: 0 | G31: 0 | H31: =sum(D31:G31) -> 3575 | I31: =H31*1.75% -> 62.5625 | J31: =H31-I31 -> 3512.4375
A32: Total | D32: =SUM(D2:D31) -> 41320 | E32: =SUM(E2:E31) -> 21700 | F32: =SUM(F2:F31) -> 1710 | G32: =SUM(G2:G31) -> 175 | H32: =SUM(H2:H31) -> 64905 | I32: =SUM(I2:I31) -> 1135.8375 | J32: =SUM(J2:J31) -> 63769.162

Sheet District
A1: Link | B1: Date | C1: Paid to District | D1: Commissions (₹) | E1: GST on Commission | F1: Net Revenue | G1: TCS | H1: TDS | I1: Final Amount (₹)
B2: 1 - 30 Sept | C2: 85044 | D2: 5116 | E2: 920 | F2: =C2-D2-E2 -> 79008 | G2: 300 | H2: 60 | I2: =F2-G2-H2 -> 78648
B3: Total | C3: =SUM(C2) -> 85044 | D3: =SUM(D2) -> 5116 | E3: =SUM(E2) -> 920 | F3: =SUM(F2) -> 79008 | I3: =SUM(I2) -> 78648
A5: Pickleball | B5: 50150
A6: Turf | B6: =C3-B5 -> 34894

Sheet Memberships
A1: Member Name | B1: Sports Type | C1: Membership Type | D1: Amount Collected | E1: Payment Gateway | F1: Net Revenue
A2: Karan | B2: Box Cricket | C2: 12 Hours | D2: 16800 | E2: =D2*1.75% -> 294 | F2: =D2-E2 -> 16506
A3: ISH | B3: Turf and Pickleball | C3: Custom | D3: 18800 | E3: 0 | F3: =D3-E3 -> 18800
A4: Total | D4: =SUM(D2:D3) -> 35600 | E4: =SUM(E2:E3) -> 294 | F4: =SUM(F2:F3) -> 35306

Sheet Corporate Events
A1: Start Month | B1: Partnership Type | C1: Name of Brand/Person | D1: Deliverables | E1: Amount (₹) | F1: Payment Gateway | G1: Net Revenue
A2: 24 Sept | B2: Team Event | C2: Bio Gas KLJ | D2: 1.5 hours of Turf | E2: 1920 | F2: =E2*1.75% -> 33.6 | G2: =E2-F2 -> 1886.4
