Workbook

Sheet Summary
B2: 1 - 30 Sept
B3: Particulars | C3: Amount
C4: Pickleball
B5: Pay & Play | C5: =sum(C6,C12) -> 26638
B6: Online | C6: =sum(C7:C11) -> 23148
B7: District | C7: =District!C3 -> 23148
B8: Hudle | C8: 0
B9: Playo | C9: 0
B10: Khelomore | C10: 0
B11: Zplys | C11: 0
B12: Offline | C12: =sum(C13:C14) -> 3490
B13: Bookings | C13: ='Offline & RG Community'!D32 -> 3490
B14: Memberships | C14: 0
B15: Community | C15: =sum(C16:C18) -> 4897
B16: Pickup games | C16: ='Offline & RG Community'!E32 -> 4897
B17: Social Events/Tournaments | C17: 0
B18: Community Partnership | C18: 0
B19: Academy | C19: =Academy!E2 -> 18000 | D19: (Note for CA Team: Please note that RallyGully hasn't received the 18000 rental for basketball rental service provided) - GST payment would have to be made by Drive & Kick Team
B20: B2B | C20: =sum(C21,C22) -> 0
B21: Corporate events | C21: 0
B22: All B2B partnerships | C22: 0
B23: Commerce | C23: =sum(C24:C26) -> 3200
B24: Product rental | C24: ='Offline & RG Community'!F32 -> 3200
B25: Product sales | C25: 0
B26: F&B | C26: 0
B27: Other Income | C27: 0
B28: Total Gross Revenue | C28: =C5+C15+C19+C20+C23+C27 -> 52735
B29: GST | C29: =C28-(C28/1.18) -> 8044.322
B30: Net Revenue Post GST | C30: =C28-C29 -> 44690.678
B31: Commissions, Payment gateway & Event Expense | C31: ='Offline & RG Community'!H32+District!D3+District!E3 -> 1856.7725
B32: Net Revenue | C32: =C28-C29-C31 -> 42833.905

Sheet Offline & RG Community
A1: Date | B1: Day | C1: Offline booking hours | D1: Booking Revenue | E1: Community Revenue | F1: Paddle Rental | G1: Total Revenue | H1: Payment Gateway | I1: Net Revenue
A2: 46266 | B2: Tuesday | C2: 0.5 | D2: 349 | E2: 0 | F2: 100 | G2: =sum(D2:F2) -> 449 | H2: =G2*1.75% -> 7.8575 | I2: =G2-H2 -> 441.1425
A3: 46267 | B3: Wednesday | C3: 0 | D3: 0 | E3: 0 | F3: 0 | G3: =sum(D3:F3) -> 0 | H3: =G3*1.75% -> 0 | I3: =G3-H3 -> 0
A4: 46268 | B4: Thursday | C4: 0 | D4: 0 | E4: 0 | F4: 0 | G4: =sum(D4:F4) -> 0 | H4: =G4*1.75% -> 0 | I4: =G4-H4 -> 0
A5: 46269 | B5: Friday | C5: 0 | D5: 0 | E5: 0 | F5: 0 | G5: =sum(D5:F5) -> 0 | H5: =G5*1.75% -> 0 | I5: =G5-H5 -> 0
A6: 46270 | B6: Saturday | C6: 0 | D6: 0 | E6: 0 | F6: 0 | G6: =sum(D6:F6) -> 0 | H6: =G6*1.75% -> 0 | I6: =G6-H6 -> 0
A7: 46271 | B7: Sunday | C7: 1 | D7: 698 | E7: 0 | F7: 375 | G7: =sum(D7:F7) -> 1073 | H7: =G7*1.75% -> 18.7775 | I7: =G7-H7 -> 1054.2225
A8: 46272 | B8: Monday | C8: 0 | D8: 0 | E8: 0 | F8: 0 | G8: =sum(D8:F8) -> 0 | H8: =G8*1.75% -> 0 | I8: =G8-H8 -> 0
A9: 46273 | B9: Tuesday | C9: 0 | D9: 0 | E9: 0 | F9: 0 | G9: =sum(D9:F9) -> 0 | H9: =G9*1.75% -> 0 | I9: =G9-H9 -> 0
A10: 46274 | B10: Wednesday | C10: 2 | D10: 1396 | E10: 0 | F10: 375 | G10: =sum(D10:F10) -> 1771 | H10: =G10*1.75% -> 30.9925 | I10: =G10-H10 -> 1740.0075
A11: 46275 | B11: Thursday | C11: 0 | D11: 0 | E11: 0 | F11: 0 | G11: =sum(D11:F11) -> 0 | H11: =G11*1.75% -> 0 | I11: =G11-H11 -> 0
A12: 46276 | B12: Friday | C12: 0 | D12: 0 | E12: 0 | F12: 0 | G12: =sum(D12:F12) -> 0 | H12: =G12*1.75% -> 0 | I12: =G12-H12 -> 0
A13: 46277 | B13: Saturday | C13: 0 | D13: 0 | E13: 0 | F13: 0 | G13: =sum(D13:F13) -> 0 | H13: =G13*1.75% -> 0 | I13: =G13-H13 -> 0
... A31: 46295 | B31: Wednesday | C31: 0 | D31: 0 | E31: 0 | F31: 0 | G31: =sum(D31:F31) -> 0 | H31: =G31*1.75% -> 0 | I31: =G31-H31 -> 0
A32: Total | D32: =SUM(D2:D31) -> 3490 | E32: =SUM(E2:E31) -> 4897 | F32: =SUM(F2:F31) -> 3200 | G32: =SUM(G2:G31) -> 11587 | H32: =SUM(H2:H31) -> 202.7725 | I32: =SUM(I1:I31) -> 11384.228

Sheet District
A1: Link | B1: Date | C1: Paid to District | D1: Commissions (₹) | E1: GST on Commission | F1: Net Revenue | G1: TCS | H1: TDS | I1: Final Amount (₹)
B2: 1 - 30 Sept | C2: 23148 | D2: 1402 | E2: 252 | F2: =C2-D2-E2 -> 21494 | G2: 94 | H2: 19 | I2: =F2-G2-H2 -> 21381
A3: Total | C3: =SUM(C2) -> 23148 | D3: =SUM(D2) -> 1402 | E3: =SUM(E2) -> 252 | F3: =SUM(F2) -> 21494 | I3: =SUM(I2) -> 21381

Sheet Academy
A1: Month | B1: Coaching | C1: Sports Type | D1: Type | E1: Amount Collected
A2: Sept | B2: Basketball Coaching | C2: Basketball | D2: 3 days in week | E2: 18000
