Workbook

Sheet Summary
B2: 1 - 30 Sept
B3: Particulars | C3: Amount
C4: Pickleball
B5: Pay & Play | C5: =sum(C6,C12) -> 180690
B6: Online | C6: =sum(C7:C11) -> 149821
B7: District | C7: =District!C4 -> 149821
B8: Hudle | C8: 0
B9: Playo | C9: 0
B10: Khelomore | C10: 0
B11: Zplys | C11: 0
B12: Offline | C12: =sum(C13:C14) -> 30869
B13: Bookings | C13: ='Offline & RG Community'!D32 -> 30869
B14: Memberships | C14: 0
B15: Community | C15: =sum(C16:C18) -> 123004
B16: Pickup games | C16: ='Offline & RG Community'!F32 -> 61300
B17: Social Events/Tournaments | C17: ='Social EventsTournaments'!D3 -> 7984
B18: Community Partnerships | C18: ='Offline & RG Community'!E32 -> 53720
B19: Academy | C19: =Academy!C2 -> 6500
B20: B2B | C20: =sum(C21,C22) -> 0
B21: Corporate events | C21: 0
B22: All B2B partnerships | C22: 0
B23: Commerce | C23: =sum(C24:C26) -> 11135
B24: Product rental | C24: ='Offline & RG Community'!G32 -> 6850
B25: Product sales | C25: 0
B26: F&B | C26: ='F&B'!B32 -> 4285
B27: Other Income | C27: 0
B28: Total Gross Revenue | C28: =C5+C15+C19+C20+C23+C27 -> 321329
B29: GST | C29: =C28-(C28/1.18) -> 49016.288
B30: Net Revenue Post GST | C30: =C28-C29 -> 272312.71
B31: Commissions, Payment gateway & Event Expense | C31: ='Offline & RG Community'!I32+District!D4+District!E4+'Social EventsTournaments'!F3+Academy!D2+'F&B'!C32+'F&B'!E32 -> 16806.565
B32: Net Revenue | C32: =C28-C29-C31 -> 255506.15

Sheet Offline & RG Community
A1: Date | B1: Day | C1: Offline Booking Hours | D1: Booking Revenue | E1: Community Partnership | F1: Community Revenue | G1: Paddle Rental | H1: Total Revenue | I1: Payment Gateway | J1: Net Revenue
A2: 46266 | B2: Tuesday | C2: 0 | D2: 0 | E2: 0 | F2: 800 | G2: 100 | H2: =sum(D2:G2) -> 900 | I2: =H2*1.75% -> 15.75 | J2: =H2-I2 -> 884.25
A3: 46267 | B3: Wednesday | C3: 3.5 | D3: 1919 | E3: 680 | F3: 3000 | G3: 150 | H3: =sum(D3:G3) -> 5749 | I3: =H3*1.75% -> 100.6075 | J3: =H3-I3 -> 5648.3925
A4: 46268 | B4: Thursday | C4: 5.5 | D4: 2317 | E4: 1020 | F4: 1800 | G4: 300 | H4: =sum(D4:G4) -> 5437 | I4: =H4*1.75% -> 95.1475 | J4: =H4-I4 -> 5341.8525
A5: 46269 | B5: Friday | C5: 0 | D5: 0 | E5: 0 | F5: 0 | G5: 0 | H5: =sum(D5:G5) -> 0 | I5: =H5*1.75% -> 0 | J5: =H5-I5 -> 0
A6: 46270 | B6: Saturday | C6: 9 | D6: 1518 | E6: 4760 | F6: 1600 | G6: 200 | H6: =sum(D6:G6) -> 8078 | I6: =H6*1.75% -> 141.365 | J6: =H6-I6 -> 7936.635
A7: 46271 | B7: Sunday | C7: 5 | D7: 1950 | E7: 1700 | F7: 2400 | G7: 725 | H7: =sum(D7:G7) -> 6775 | I7: =H7*1.75% -> 118.5625 | J7: =H7-I7 -> 6656.4375
A8: 46272 | B8: Monday | C8: 5 | D8: 1920 | E8: 1700 | F8: 2200 | G8: 200 | H8: =sum(D8:G8) -> 6020 | I8: =H8*1.75% -> 105.35 | J8: =H8-I8 -> 5914.65
A9: 46273 | B9: Tuesday | C9: 4 | D9: 798 | E9: 2040 | F9: 2000 | G9: 150 | H9: =sum(D9:G9) -> 4988 | I9: =H9*1.75% -> 87.29 | J9: =H9-I9 -> 4900.71
A10: 46274 | B10: Wednesday | C10: 3 | D10: 0 | E10: 2040 | F10: 800 | G10: 50 | H10: 0 | I10: =H10*1.75% -> 0 | J10: =H10-I10 -> 0
A11: 46275 | B11: Thursday | C11: 2 | D11: 1520 | E11: 0 | F11: 2200 | G11: 100 | H11: =sum(D11:G11) -> 3820 | I11: =H11*1.75% -> 66.85 | J11: =H11-I11 -> 3753.15
A12: 46276 | B12: Friday | C12: 3 | D12: 798 | E12: 1360 | F12: 6800 | G12: 200 | H12: =sum(D12:G12) -> 9158 | I12: =H12*1.75% -> 160.265 | J12: =H12-I12 -> 8997.735
A13: 46277 | B13: Saturday | C13: 5.5 | D13: 2793 | E13: 1360 | F13: 1200 | G13: 500 | H13: =sum(D13:G13) -> 5853 | I13: =H13*1.75% -> 102.4275 | J13: =H13-I13 -> 5750.5725
A14: 46278 | B14: Sunday | C14: 4 | D14: 1450 | E14: 2720 | F14: 2200 | G14: 200 | H14: =sum(D14:G14) -> 6570 | I14: =H14*1.75% -> 114.975 | J14: =H14-I14 -> 6455.025
A15: 46279 | B15: Monday | C15: 4 | D15: 1200 | E15: 2040 | F15: 3200 | G15: 0 | H15: =sum(D15:G15) -> 6440 | I15: =H15*1.75% -> 112.7 | J15: =H15-I15 -> 6327.3
A16: 46280 | B16: Tuesday | C16: 3 | D16: 0 | E16: 2040 | F16: 3000 | G16: 150 | H16: =sum(D16:G16) -> 5190 | I16: =H16*1.75% -> 90.825 | J16: =H16-I16 -> 5099.175
A17: 46281 | B17: Wednesday | C17: 3 | D17: 0 | E17: 2040 | F17: 2200 | G17: 50 | H17: =sum(D17:G17) -> 4290 | I17: =H17*1.75% -> 75.075 | J17: =H17-I17 -> 4214.925
A18: 46282 | B18: Thursday | C18: 5.5 | D18: 1398 | E18: 1700 | F18: 2800 | G18: 150 | H18: =sum(D18:G18) -> 6048 | I18: =H18*1.75% -> 105.84 | J18: =H18-I18 -> 5942.16
A19: 46283 | B19: Friday | C19: 6.5 | D19: 1920 | E19: 2720 | F19: 0 | G19: 600 | H19: =sum(D19:G19) -> 5240 | I19: =H19*1.75% -> 91.7 | J19: =H19-I19 -> 5148.3
A20: 46284 | B20: Saturday | C20: 3 | D20: 400 | E20: 1700 | F20: 2800 | G20: 300 | H20: =sum(D20:G20) -> 5200 | I20: =H20*1.75% -> 91 | J20: =H20-I20 -> 5109
A21: 46285 | B21: Sunday | C21: 4.5 | D21: 798 | E21: 2380 | F21: 1600 | G21: 550 | H21: =sum(D21:G21) -> 5328 | I21: =H21*1.75% -> 93.24 | J21: =H21-I21 -> 5234.76
A22: 46286 | B22: Monday | C22: 3.5 | D22: 0 | E22: 2380 | F22: 2400 | G22: 150 | H22: =sum(D22:G22) -> 4930 | I22: =H22*1.75% -> 86.275 | J22: =H22-I22 -> 4843.725
... A31: 46295 | B31: Wednesday | C31: 8 | D31: 1995 | E31: 3740 | F31: 1400 | G31: 100 | H31: =sum(D31:G31) -> 7235 | I31: =H31*1.75% -> 126.6125 | J31: =H31-I31 -> 7108.3875
A32: Total | D32: =SUM(D2:D31) -> 30869 | E32: =SUM(E2:E31) -> 53720 | F32: =SUM(F2:F31) -> 61300 | G32: =SUM(G2:G31) -> 6850 | H32: =SUM(H2:H31) -> 149849 | I32: =SUM(I2:I31) -> 2622.3575 | J32: =SUM(J1:J31) -> 147226.64

Sheet District
A1: Link | B1: Date | C1: Paid to District | D1: Commissions (₹) | E1: GST on Commission | F1: Net Revenue | G1: TCS | H1: TDS | I1: Final Amount (₹)
B2: 1 - 30 Sept | C2: 149821 | D2: 9019 | E2: 1623 | F2: =C2-D2-E2 -> 139179 | G2: 479 | H2: 96 | I2: =F2-G2-H2 -> 138604
B4: Total | C4: =SUM(C2:C3) -> 149821 | D4: =SUM(D2:D3) -> 9019 | E4: =SUM(E2:E3) -> 1623 | F4: =SUM(F2:F3) -> 139179 | I4: =SUM(I2:I3) -> 138604

Sheet Social EventsTournaments
A1: Date | B1: Sport | C1: Type | D1: Amt | E1: Post Comission | F1: Payment Gateway | G1: Event Cost | H1: Net Revenue | I1: TDS | J1: Final Amount (₹) | K1: Notes
A2: 26 Sept | B2: Pickleball | C2: Double Shuffle | D2: 7984 | E2: 0 | F2: =D2*1.75% -> 139.72 | G2: 0 | H2: =D2-E2-F2-G2 -> 7844.28 | I2: 0 | J2: =H2-I2 -> 7844.28
A3: Total | D3: =SUM(D2) -> 7984 | E3: =SUM(E2) -> 0 | F3: =SUM(F2) -> 139.72 | G3: =SUM(G2) -> 0 | H3: =SUM(H2) -> 7844.28 | I3: =SUM(I2) -> 0 | J3: =SUM(J2) -> 7844.28

Sheet Academy
A1: Sports | B1: Month | C1: Amt | D1: Payment Gateway | E1: Net Revenue
A2: Pickleball | B2: Sept | C2: 6500 | D2: =C2*1.75% -> 113.75 | E2: =C2-D2 -> 6386.25

Sheet F&B
A1: Date | B1: F&B | C1: Paid to brand (75%) | D1: Our Margin (25%) | E1: Payment Gateway | F1: Net Revenue
A2: 46266 | B2: 35 | C2: =B2*75% -> 26.25 | D2: =B2*25% -> 8.75 | E2: =B2*1.75% -> 0.6125 | F2: =D2-E2 -> 8.1375
A3: 46267 | B3: 0 | C3: =B3*75% -> 0 | D3: =B3*25% -> 0 | E3: =B3*1.75% -> 0 | F3: =D3-E3 -> 0
A4: 46268 | B4: 0 | C4: =B4*75% -> 0 | D4: =B4*25% -> 0 | E4: =B4*1.75% -> 0 | F4: =D4-E4 -> 0
A5: 46269 | B5: 0 | C5: =B5*75% -> 0 | D5: =B5*25% -> 0 | E5: =B5*1.75% -> 0 | F5: =D5-E5 -> 0
A6: 46270 | B6: 70 | C6: =B6*75% -> 52.5 | D6: =B6*25% -> 17.5 | E6: =B6*1.75% -> 1.225 | F6: =D6-E6 -> 16.275
A7: 46271 | B7: 105 | C7: =B7*75% -> 78.75 | D7: =B7*25% -> 26.25 | E7: =B7*1.75% -> 1.8375 | F7: =D7-E7 -> 24.4125
A8: 46272 | B8: 350 | C8: =B8*75% -> 262.5 | D8: =B8*25% -> 87.5 | E8: =B8*1.75% -> 6.125 | F8: =D8-E8 -> 81.375
A9: 46273 | B9: 385 | C9: =B9*75% -> 288.75 | D9: =B9*25% -> 96.25 | E9: =B9*1.75% -> 6.7375 | F9: =D9-E9 -> 89.5125
A10: 46274 | B10: 0 | C10: =B10*75% -> 0 | D10: =B10*25% -> 0 | E10: =B10*1.75% -> 0 | F10: =D10-E10 -> 0
A11: 46275 | B11: 335 | C11: =B11*75% -> 251.25 | D11: =B11*25% -> 83.75 | E11: =B11*1.75% -> 5.8625 | F11: =D11-E11 -> 77.8875
A12: 46276 | B12: 0 | C12: =B12*75% -> 0 | D12: =B12*25% -> 0 | E12: =B12*1.75% -> 0 | F12: =D12-E12 -> 0
A13: 46277 | B13: 210 | C13: =B13*75% -> 157.5 | D13: =B13*25% -> 52.5 | E13: =B13*1.75% -> 3.675 | F13: =D13-E13 -> 48.825
... A31: 46295 | B31: 105 | C31: =B31*75% -> 78.75 | D31: =B31*25% -> 26.25 | E31: =B31*1.75% -> 1.8375 | F31: =D31-E31 -> 24.4125
A32: Total | B32: =SUM(B2:B31) -> 4285 | C32: =SUM(C2:C31) -> 3213.75 | D32: =SUM(D2:D31) -> 1071.25 | E32: =SUM(E2:E31) -> 74.9875 | F32: =SUM(F2:F31) -> 996.2625
