Workbook

Sheet Summary
B2: 1 - 31 July
B3: Particulars | C3: Amount
C4: Pickleball
B5: Pay & Play | C5: =sum(C6,C12) -> 117914
B6: Online | C6: =sum(C7:C11) -> 96864
B7: District | C7: =District!C4 -> 96864
B8: Hudle | C8: 0
B9: Playo | C9: 0
B10: Khelomore | C10: 0
B11: Zplys | C11: 0
B12: Offline | C12: =sum(C13:C14) -> 21050
B13: Bookings | C13: ='Offline & RG Community'!D33 -> 21050
B14: Memberships | C14: 0
B15: Community | C15: =sum(C16:C17) -> 38148
B16: Pickup games | C16: ='Offline & RG Community'!E33 -> 34200
B17: Social Events/Tournaments | C17: ='Social EventsTournaments'!D4 -> 3948
B18: Academy | C18: =Academy!C2 -> 29500
B19: Events & Partnership | C19: =sum(C20,C21) -> 0
B20: Corporate events | C20: 0
B21: All B2B partnerships | C21: 0
B22: Commerce | C22: =sum(C23:C25) -> 7500
B23: Product rental | C23: ='Offline & RG Community'!F33 -> 3450
B24: Product sales | C24: 0
B25: F&B | C25: ='Offline & RG Community'!G33 -> 4050
B26: Other Income | C26: 0
B27: Total Gross Revenue | C27: =sum(C26+C22+C19+C18+C15+C12+C6) -> 193062
B28: Total Net Revenue (Post Commissions) | C28: ='Offline & RG Community'!J33+District!F4+'Social EventsTournaments'!G4+Academy!E2 -> 183255.85
B29: Total Net Revenue post GST | C29: =(C27/1.18)-(C27-C28) -> 153805.71
B30: Expenses
B31: Venue Manager + Cleaner | C31: 60164
B32: Marketing, Branding & Community | C32: 15000
B33: Balls Expense | C33: 9500
B34: Branding Revamp | C34: 12595
B35: F&B Inventory Cost | C35: 3024
B36: Total Expenses | C36: =C31+C32+C33+C34+C35 -> 100283
B37: Net Profit (Revenue - Expenses) | C37: =C29-C36 -> 53522.714
B39: School's Profit Share (65%) | C39: =C37*65% -> 34789.764
B40: RallyGully's Profit Share (35%) | C40: =C37*35% -> 18732.95

Sheet Offline & RG Community
A1: Date | B1: Day | C1: Offline booking hours | D1: Booking Revenue | E1: Community Revenue | F1: Paddle Rental | G1: F&B | H1: Total Revenue | I1: Payment Gateway | J1: Net Revenue
A2: 46204 | B2: Wednesday | C2: 2 | D2: 1800 | E2: 900 | F2: 100 | G2: 140 | H2: =sum(D2:G2) -> 2940 | I2: =H2*1.75% -> 51.45 | J2: =H2-I2 -> 2888.55
A3: 46205 | B3: Thursday | C3: 0 | D3: 0 | E3: 1200 | F3: 100 | G3: 35 | H3: =sum(D3:G3) -> 1335 | I3: =H3*1.75% -> 23.3625 | J3: =H3-I3 -> 1311.6375
A4: 46206 | B4: Friday | C4: 1 | D4: 1040 | E4: 2700 | F4: 200 | G4: 490 | H4: =sum(D4:G4) -> 4430 | I4: =H4*1.75% -> 77.525 | J4: =H4-I4 -> 4352.475
A5: 46207 | B5: Saturday | C5: 0 | D5: 0 | E5: 0 | F5: 0 | G5: 0 | H5: =sum(D5:G5) -> 0 | I5: =H5*1.75% -> 0 | J5: =H5-I5 -> 0
A6: 46208 | B6: Sunday | C6: 0 | D6: 0 | E6: 0 | F6: 100 | G6: 0 | H6: =sum(D6:G6) -> 100 | I6: =H6*1.75% -> 1.75 | J6: =H6-I6 -> 98.25
A7: 46209 | B7: Monday | C7: 0 | D7: 0 | E7: 0 | F7: 0 | G7: 125 | H7: =sum(D7:G7) -> 125 | I7: =H7*1.75% -> 2.1875 | J7: =H7-I7 -> 122.8125
A8: 46210 | B8: Tuesday | C8: 0 | D8: 0 | E8: 900 | F8: 50 | G8: 35 | H8: =sum(D8:G8) -> 985 | I8: =H8*1.75% -> 17.2375 | J8: =H8-I8 -> 967.7625
A9: 46211 | B9: Wednesday | C9: 0 | D9: 0 | E9: 0 | F9: 0 | G9: 0 | H9: =sum(D9:G9) -> 0 | I9: =H9*1.75% -> 0 | J9: =H9-I9 -> 0
A10: 46212 | B10: Thursday | C10: 1 | D10: 1200 | E10: 0 | F10: 300 | G10: 320 | H10: =sum(D10:G10) -> 1820 | I10: =H10*1.75% -> 31.85 | J10: =H10-I10 -> 1788.15
A11: 46213 | B11: Friday | C11: 2.5 | D11: 2250 | E11: 2400 | F11: 0 | G11: 105 | H11: =sum(D11:G11) -> 4755 | I11: =H11*1.75% -> 83.2125 | J11: =H11-I11 -> 4671.7875
A12: 46214 | B12: Saturday | C12: 1 | D12: 900 | E12: 0 | F12: 200 | G12: 530 | H12: =sum(D12:G12) -> 1630 | I12: =H12*1.75% -> 28.525 | J12: =H12-I12 -> 1601.475
A13: 46215 | B13: Sunday | C13: 1 | D13: 900 | E13: 0 | F13: 0 | G13: 455 | H13: =sum(D13:G13) -> 1355 | I13: =H13*1.75% -> 23.7125 | J13: =H13-I13 -> 1331.2875
... A32: 46234 | B32: Friday | C32: 2 | D32: 2160 | E32: 2100 | F32: 300 | G32: 40 | H32: =sum(D32:G32) -> 4600 | I32: =H32*1.75% -> 80.5 | J32: =H32-I32 -> 4519.5
A33: Total | D33: =SUM(D1:D32) -> 21050 | E33: =SUM(E1:E32) -> 34200 | F33: =SUM(F1:F32) -> 3450 | G33: =SUM(G1:G32) -> 4050 | H33: =SUM(H1:H32) -> 62750 | I33: =SUM(I1:I32) -> 1098.125 | J33: =SUM(J1:J32) -> 61651.875

Sheet District
A1: Link | B1: Date | C1: Paid to District | D1: Commissions (₹) | E1: GST on Commission | F1: Net Revenue | G1: TCS | H1: TDS | I1: Final Amount (₹)
B2: 1 - 31 July | C2: 96864 | D2: 6780 | E2: 1220 | F2: =C2-D2-E2 -> 88864 | G2: 484 | H2: 97 | I2: =F2-G2-H2 -> 88283
B4: Total | C4: =SUM(C2:C3) -> 96864 | F4: =SUM(F2:F3) -> 88864 | I4: =SUM(I2:I3) -> 88283

Sheet Social EventsTournaments
A1: Date | B1: Sport | C1: Type | D1: Amt | E1: Post Comission | F1: Payment Gateway | G1: Net Revenue | H1: TDS | I1: Final Amount (₹) | J1: Notes
A2: 46204 | B2: Pickleball | C2: DUPR | D2: 1698 | E2: =D2*5% -> 84.9 | F2: 0 | G2: =D2-E2-F2 -> 1613.1 | H2: =D2*2% -> 33.96 | I2: =G2-H2 -> 1579.14 | J2: Courtly
A3: 46204 | B3: Pickleball | C3: DUPR | D3: 2250 | E3: =D3*3% -> 67.5 | F3: =D3*1.75% -> 39.375 | G3: =D3-E3-F3 -> 2143.125 | H3: 0 | I3: =G3-H3 -> 2143.125 | J3: Offline
A4: Total | D4: =SUM(D2:D3) -> 3948 | G4: =SUM(G2:G3) -> 3756.225 | I4: =SUM(I2:I3) -> 3722.265

Sheet Academy
A1: Sports | B1: Month | C1: Amt | D1: Payment Gateway | E1: Net Revenue
A2: Pickleball | B2: July | C2: 29500 | D2: =C2*1.75% -> 516.25 | E2: =C2-D2 -> 28983.75
