Workbook

Sheet Summary
B2: 1 - 31 May
B3: Particulars | C3: Amount
C4: Pickleball
B5: Pay & Play | C5: =sum(C6,C12) -> 142228
B6: Online | C6: =sum(C7:C11) -> 97228
B7: District | C7: =District!C4 -> 93238
B8: Hudle | C8: =Hudle!C4 -> 3990
B9: Playo | C9: 0
B10: Khelomore | C10: 0
B11: Zplys | C11: 0
B12: Offline | C12: =sum(C13:C14) -> 45000
B13: Bookings | C13: ='Offline & RG Community'!E33 -> 45000
B14: Memberships | C14: 0
B15: Community | C15: =sum(C16:C17) -> 3600
B16: Pickup games | C16: ='Offline & RG Community'!F33 -> 3600
B17: Social Events/Tournaments | C17: 0
B18: Academy | C18: 0
B19: Events & Partnership | C19: =sum(C20,C21) -> 0
B20: Corporate events | C20: 0
B21: All B2B partnerships | C21: 0
B22: Commerce | C22: =sum(C23:C25) -> 11205
B23: Product rental | C23: ='Offline & RG Community'!G33 -> 11100
B24: Product sales | C24: 0
B25: F&B | C25: ='Offline & RG Community'!H33 -> 105
B26: Other Income | C26: 0
B27: Total Gross Revenue | C27: =C5+C15+C22+C18+C19+C26 -> 157033
B28: Total Net Revenue (Post Commissions) | C28: ='Offline & RG Community'!K33+Hudle!E4+District!F4 -> 145858.23
B29: Total Revenue post GST | C29: =C28/1.18 -> 123608.67
B30: Investor's Share (40%) | C30: =C29*40% -> 49443.469

Sheet Offline & RG Community
A1: Date | B1: Day | C1: Offline booking hours | D1: Discount | E1: Booking Revenue | F1: Community | G1: Paddle Rental | H1: F&B | I1: Total Revenue | J1: Payment Gateway | K1: Net Revenue
A2: 46143 | B2: Friday | C2: 2 | D2: 10 and 20% | E2: 1800 | F2: 0 | G2: 150 | H2: 0 | I2: =sum(E2:H2) -> 1950 | J2: =I2*2.5%*1.18 -> 57.525 | K2: =I2-J2 -> 1892.475
A3: 46144 | B3: Saturday | C3: 4 | D3: 10 and 20% | E3: 3240 | F3: 0 | G3: 250 | H3: 0 | I3: =sum(E3:H3) -> 3490 | J3: =I3*2.5%*1.18 -> 102.955 | K3: =I3-J3 -> 3387.045
A4: 46145 | B4: Sunday | C4: 3 | D4: 10 and 20% | E4: 2880 | F4: 0 | G4: 150 | H4: 0 | I4: =sum(E4:H4) -> 3030 | J4: =I4*2.5%*1.18 -> 89.385 | K4: =I4-J4 -> 2940.615
A5: 46146 | B5: Monday | C5: 1 | D5: 10 and 20% | E5: 720 | F5: 0 | G5: 200 | H5: 0 | I5: =sum(E5:H5) -> 920 | J5: =I5*2.5%*1.18 -> 27.14 | K5: =I5-J5 -> 892.86
A6: 46147 | B6: Tuesday | C6: 2 | D6: 10 and 20% | E6: 1800 | F6: 800 | G6: 300 | H6: 0 | I6: =sum(E6:H6) -> 2900 | J6: =I6*2.5%*1.18 -> 85.55 | K6: =I6-J6 -> 2814.45
A7: 46148 | B7: Wednesday | C7: 1 | D7: 10 and 20% | E7: 1440 | F7: 800 | G7: 100 | H7: 0 | I7: =sum(E7:H7) -> 2340 | J7: =I7*2.5%*1.18 -> 69.03 | K7: =I7-J7 -> 2270.97
A8: 46149 | B8: Thursday | C8: 0.5 | D8: 10 and 20% | E8: 360 | F8: 0 | G8: 350 | H8: 0 | I8: =sum(E8:H8) -> 710 | J8: =I8*2.5%*1.18 -> 20.945 | K8: =I8-J8 -> 689.055
A9: 46150 | B9: Friday | C9: 2 | D9: 10 and 20% | E9: 1800 | F9: 800 | G9: 500 | H9: 0 | I9: =sum(E9:H9) -> 3100 | J9: =I9*2.5%*1.18 -> 91.45 | K9: =I9-J9 -> 3008.55
A10: 46151 | B10: Saturday | C10: 1 | D10: 10 and 20% | E10: 720 | F10: 600 | G10: 900 | H10: 0 | I10: =sum(E10:H10) -> 2220 | J10: =I10*2.5%*1.18 -> 65.49 | K10: =I10-J10 -> 2154.51
A11: 46152 | B11: Sunday | C11: 3 | D11: 10 and 20% | E11: 2160 | F11: 0 | G11: 550 | H11: 0 | I11: =sum(E11:H11) -> 2710 | J11: =I11*2.5%*1.18 -> 79.945 | K11: =I11-J11 -> 2630.055
A12: 46153 | B12: Monday | C12: 1 | D12: 10 and 20% | E12: 720 | F12: 0 | G12: 350 | H12: 0 | I12: =sum(E12:H12) -> 1070 | J12: =I12*2.5%*1.18 -> 31.565 | K12: =I12-J12 -> 1038.435
A13: 46154 | B13: Tuesday | C13: 1 | D13: 10 and 20% | E13: 720 | F13: 0 | G13: 500 | H13: 0 | I13: =sum(E13:H13) -> 1220 | J13: =I13*2.5%*1.18 -> 35.99 | K13: =I13-J13 -> 1184.01
... A16: 46157 | B16: Friday | C16: 3 | D16: 10 and 20% | E16: 1440 | F16: 600 | G16: 350 | H16: 0 | I16: =sum(E16:H16) -> 2390 | J16: =I16*2.5%*1.18 -> 70.505 | K16: =I16-J16 -> 2319.495
A17: 46158 | B17: Saturday | C17: 3 | D17: 10 and 20% | E17: 2880 | F17: 0 | G17: 600 | H17: 0 | I17: =SUM(E17:H17) -> 3480 | J17: =I17*2.5%*1.18 -> 102.66 | K17: =I17-J17 -> 3377.34
A18: 46159 | B18: Sunday | C18: 0 | D18: 10 and 20% | E18: 0 | F18: 0 | G18: 400 | H18: 0 | I18: =SUM(E18:H18) -> 400 | J18: =I18*2.5%*1.18 -> 11.8 | K18: =I18-J18 -> 388.2
A19: 46160 | B19: Monday | C19: 1 | D19: 10 and 20% | E19: 720 | F19: 0 | G19: 550 | H19: 0 | I19: =SUM(E19:H19) -> 1270 | J19: =I19*2.5%*1.18 -> 37.465 | K19: =I19-J19 -> 1232.535
A20: 46161 | B20: Tuesday | C20: 1 | D20: 10 and 20% | E20: 720 | F20: 0 | G20: 500 | H20: 0 | I20: =SUM(E20:H20) -> 1220 | J20: =I20*2.5%*1.18 -> 35.99 | K20: =I20-J20 -> 1184.01
A21: 46162 | B21: Wednesday | C21: 1 | D21: 10 and 20% | E21: 720 | F21: 0 | G21: 150 | H21: 0 | I21: =SUM(E21:H21) -> 870 | J21: =I21*2.5%*1.18 -> 25.665 | K21: =I21-J21 -> 844.335
A22: 46163 | B22: Thursday | C22: 2 | D22: 10 and 20% | E22: 1440 | F22: 0 | G22: 400 | H22: 0 | I22: =SUM(F22:G22) -> 400 | J22: =I22*2.5%*1.18 -> 11.8 | K22: =I22-J22 -> 388.2
A23: 46164 | B23: Friday | C23: 4 | D23: 10 and 20% | E23: 3600 | F23: 0 | G23: 550 | H23: 0 | I23: =sum(E23:H23) -> 4150 | J23: =I23*2.5%*1.18 -> 122.425 | K23: =I23-J23 -> 4027.575
A24: 46165 | B24: Saturday | C24: 1 | D24: 10 and 20% | E24: 720 | F24: 0 | G24: 100 | H24: 105 | I24: =SUM(E24:H24) -> 925 | J24: =I24*2.5%*1.18 -> 27.2875 | K24: =I24-J24 -> 897.7125
A25: 46166 | B25: Sunday | C25: 1 | D25: 10 and 20% | E25: 720 | F25: 0 | G25: 450 | H25: 0 | I25: =SUM(E25:H25) -> 1170 | J25: =I25*2.5%*1.18 -> 34.515 | K25: =I25-J25 -> 1135.485
A26: 46167 | B26: Monday | C26: 1 | D26: 10 and 20% | E26: 720 | F26: 0 | G26: 300 | H26: 0 | I26: =SUM(E26:H26) -> 1020 | J26: =I26*2.5%*1.18 -> 30.09 | K26: =I26-J26 -> 989.91
A27: 46168 | B27: Tuesday | C27: 2 | D27: 10 and 20% | E27: 1800 | F27: 0 | G27: 250 | H27: 0 | I27: =SUM(E27:H27) -> 2050 | J27: =I27*2.5%*1.18 -> 60.475 | K27: =I27-J27 -> 1989.525
A28: 46169 | B28: Wednesday | C28: 1 | D28: 10 and 20% | E28: 720 | F28: 0 | G28: 100 | H28: 0 | I28: =SUM(E28:H28) -> 820 | J28: =I28*2.5%*1.18 -> 24.19 | K28: =I28-J28 -> 795.81
A29: 46170 | B29: Thursday | C29: 0 | D29: 10 and 20% | E29: 0 | F29: 0 | G29: 600 | H29: 0 | I29: =SUM(E29:H29) -> 600 | J29: =I29*2.5%*1.18 -> 17.7 | K29: =I29-J29 -> 582.3
A30: 46171 | B30: Friday | C30: 4 | D30: 10 and 20% | E30: 5040 | F30: 0 | G30: 450 | H30: 0 | I30: =SUM(E30:H30) -> 5490 | J30: =I30*2.5%*1.18 -> 161.955 | K30: =I30-J30 -> 5328.045
A31: 46172 | B31: Saturday | C31: 3 | D31: 10 and 20% | E31: 2160 | F31: 0 | G31: 450 | H31: 0 | I31: =SUM(E31:H31) -> 2610 | J31: =I31*2.5%*1.18 -> 76.995 | K31: =I31-J31 -> 2533.005
A32: 46173 | B32: Sunday | C32: 4 | D32: 10 and 20% | E32: 3240 | F32: 0 | G32: 550 | H32: 0 | I32: =SUM(E32:H32) -> 3790 | J32: =I32*2.5%*1.18 -> 111.805 | K32: =I32-J32 -> 3678.195
A33: Total | E33: =SUM(E1:E32) -> 45000 | F33: =SUM(F1:F32) -> 3600 | G33: =SUM(G1:G32) -> 11100 | H33: =SUM(H1:H32) -> 105 | I33: =SUM(I1:I32) -> 58365 | J33: =SUM(J1:J32) -> 1721.7675 | K33: =SUM(K1:K32) -> 56643.232

Sheet Hudle
A1: Link | B1: Date | C1: Paid to Hudle | D1: Commisions (Including GST) | E1: Net Revenue | F1: TDS | G1: TCS | H1: Amount
B2: 1 - 31 May | C2: 3990 | D2: 487 | E2: =C2-D2 -> 3503 | F2: 3 | G2: 16 | H2: 3243
B4: Total | C4: =SUM(C2:C3) -> 3990 | E4: =SUM(E2:E3) -> 3503 | H4: =SUM(H2:H3) -> 3243

Sheet District
A1: Link | B1: Date | C1: Paid to District | D1: Commissions (₹) | E1: GST on Commission | F1: Net Revenue | G1: TCS | H1: TDS | I1: Final Amount (₹)
B2: 1 - 31 May | C2: 93238 | D2: 6378 | E2: 1148 | F2: =C2-D2-E2 -> 85712 | G2: 531 | H2: 106 | I2: 85074
B4: Total | C4: =SUM(C2:C3) -> 93238 | F4: =SUM(F2:F3) -> 85712 | I4: =SUM(I2:I3) -> 85074
