Workbook

Sheet Summary
B2: Date: 1 - 31 Jan
B3: Particulars | C3: Amount
B4: Offline | C4: =SUM(C5,C6,C7,, C8) -> 59637
B5: Rentals | C5: ='Offline & RG Community'!G33 -> 15709
B6: F&B | C6: ='Offline & RG Community'!H33 -> 3710
B7: Product Sales | C7: 0
B8: Bookings | C8: ='Offline & RG Community'!E33 -> 40218
B9: Online: Third Party Platform | C9: =SUM(C10:C14) -> 130380
B10: Hudle | C10: =Hudle!C7 -> 76022
B11: Playo | C11: =Playo!C8 -> 20344
B12: District | C12: =District!C5 -> 24400
B13: Khelomore | C13: =Khelomore!C5 -> 9614
B14: Zplys | C14: 0
B15: Community | C15: =SUM(C16:C19) -> 67200
B16: Courtly (Organized by RallyGully) | C16: =Courtly!C2 -> 38300
B17: Sportomic (Organized by RallyGully) | C17: =Sportomic!C2 -> 13650
B18: Rallygully Community games | C18: ='Offline & RG Community'!F33 -> 15250
B19: Misfits Community | C19: =Misfits!C2 -> 0
B20: Memberships | C20: 0
B21: Coaching | C21: =Coaching!D2 -> 44000
B22: Corporate Events | C22: 0
B23: Brand Activation | C23: =0 -> 0
B24: Other Income | C24: 0
B25: Total Gross Revenue | C25: =sum(C4,C9,C20,C22,C23,C24,C15, C21) -> 301217
B26: Total Net Revenue (Post Commissions) | C26: ='Offline & RG Community'!I33+Hudle!E7+Playo!F8+District!F5+Khelomore!E5+Coaching!D2+Sportomic!C2+Courtly!F2 -> 286550.8
B27: Total Revenue post GST | C27: =C26/1.18 -> 242839.66

Sheet Offline & RG Community
A1: Date | B1: Day | C1: Offline booking hours | D1: Discount Given | E1: Booking Revenue | F1: Community Revenue | G1: Paddle Rental | H1: F&B | I1: Total Revenue
A2: 46023 | B2: Thursday | C2: 1 | D2: 0% and 10% | E2: 720 | F2: 0 | G2: 600 | H2: 455 | I2: =SUM(E2:H2) -> 1775
A3: 46024 | B3: Friday | C3: 0.5 | D3: 0% and 10% | E3: 400 | F3: 0 | G3: 350 | H3: 70 | I3: =SUM(E3:H3) -> 820
A4: 46025 | B4: Saturday | C4: 4.5 | D4: 0% and 10% | E4: 3440 | F4: 0 | G4: 700 | H4: 70 | I4: =SUM(E4:H4) -> 4210
A5: 46026 | B5: Sunday | C5: 1.5 | D5: 0% and 10% | E5: 1200 | F5: 0 | G5: 600 | H5: 140 | I5: =SUM(E5:H5) -> 1940
A6: 46027 | B6: Monday | C6: 1 | D6: 0% and 10% | E6: 800 | F6: 0 | G6: 100 | H6: 175 | I6: =SUM(E6:H6) -> 1075
A7: 46028 | B7: Tuesday | C7: 0 | D7: 0% and 10% | E7: 0 | F7: 400 | G7: 300 | H7: 70 | I7: =SUM(E7:H7) -> 770
A8: 46029 | B8: Wednesday | C8: 1 | D8: 0% and 10% | E8: 800 | F8: 0 | G8: 100 | H8: 70 | I8: =SUM(E8:H8) -> 970
A9: 46030 | B9: Thursday | C9: 0 | D9: 0% and 10% | E9: 0 | F9: 0 | G9: 300 | H9: 0 | I9: =SUM(E9:H9) -> 300
A10: 46031 | B10: Friday | C10: 0.5 | D10: 0% and 10% | E10: 400 | F10: 0 | G10: 200 | H10: 205 | I10: =SUM(E10:H10) -> 805
A11: 46032 | B11: Saturday | C11: 4.5 | D11: 0% and 10% | E11: 3520 | F11: 3000 | G11: 700 | H11: 235 | I11: =SUM(E11:H11) -> 7455
A12: 46033 | B12: Sunday | C12: 2 | D12: 0% and 10% | E12: 1050 | F12: 0 | G12: 500 | H12: 210 | I12: =SUM(E12:H12) -> 1760
A13: 46034 | B13: Monday | C13: 0 | D13: 0% and 10% | E13: 0 | F13: 0 | G13: 400 | H13: 245 | I13: =SUM(E13:H13) -> 645
... A32: 46053 | B32: Saturday | C32: 1 | D32: 0% and 10% | E32: 0 | F32: 650 | G32: 550 | H32: 0 | I32: =SUM(E32:H32) -> 1200
A33: Total | C33: =SUM(C2:C32) -> 67.5 | E33: =SUM(E2:E32) -> 40218 | F33: =SUM(F2:F32) -> 15250 | G33: =SUM(G2:G32) -> 15709 | H33: =SUM(H2:H32) -> 3710 | I33: =SUM(I2:I32) -> 74887

Sheet Hudle
A1: Link | B1: Date | C1: Paid to Hudle | D1: Commisions (Including GST) | E1: Net Revenue | F1: TDS | G1: TCS | H1: Amount
B2: 1 - 5 Jan | C2: 9940 | D2: 1435.2 | E2: =C2 - D2 -> 8504.8 | F2: 9.35 | G2: 46.77 | H2: 9548.67
B3: 6 - 12 Jan | C3: 13800 | D3: 1794 | E3: =C3 - D3 -> 12006 | F3: 11.69 | G3: 58.47 | H3: 11935.83
B4: 13 - 19 Jan | C4: 15890 | D4: 2072.2 | E4: =C4 - D4 -> 13817.8 | F4: 13.5 | G4: 67.5 | H4: 13786.73
B5: 20 - 26 Jan | C5: 18272 | D5: 2375.6 | E5: =C5 - D5 -> 15896.4 | F5: 15.48 | G5: 77.42 | H5: 15803.73
B6: 27 - 31 Jan | C6: 18120 | D6: 2355.6 | E6: =C6 - D6 -> 15764.4 | F6: 15.35 | G6: 76.77 | H6: 15672.25
C7: =SUM(C2:C6) -> 76022 | E7: =SUM(E2:E6) -> 65989.4 | H7: =SUM(H2:H6) -> 66747.21

Sheet Playo
A1: Link | B1: Date | C1: Paid to Playo (₹) | D1: Commissions (₹) | E1: GST (₹) | F1: Net Revenue | G1: TDS (₹) | H1: TCS (₹) | I1: Final Amount (₹)
B2: 1 - 13 Jan | C2: 8800 | D2: 616 | E2: 110.88 | F2: =C2 -D2-E2 -> 8073.12 | G2: 8.8 | H2: 44 | I2: 8020.32
B3: 13 - 19 Jan | C3: 2400 | D3: 168 | E3: 30.24 | F3: =C3 -D3-E3 -> 2201.76 | G3: 2.4 | H3: 12 | I3: 2187.36
B4: 20 - 25 Jan | C4: 3720 | D4: 280 | E4: 50.4 | F4: =C4 -D4-E4 -> 3389.6 | G4: 3.72 | H4: 18.6 | I4: 3367.28
B5: 26 - 31 Jan | C5: 5424 | D5: 364 | E5: 65.52 | F5: =C5 -D5-E5 -> 4994.48 | G5: 4.78 | H5: 23.92 | I5: 4325.78
C8: =SUM(C2:C7) -> 20344 | F8: =SUM(F2:F7) -> 18658.96 | I8: =SUM(I2:I6) -> 17900.74

Sheet District
A1: Link | B1: Date | C1: Paid to District | D1: Commissions (₹) | E1: GST on Commission | F1: Net Revenue | G1: TCS | H1: TDS | I1: Final Amount (₹)
B2: 1 - 12 Jan | C2: 12400 | D2: =C2*2% -> 248 | E2: =D2*18% -> 44.64 | F2: =C2-D2-E2 -> 12107.36 | G2: =C2*0.5% -> 62 | H2: =D2*0.1% -> 0.248 | I2: =F2-G2-H2 -> 12045.112
B3: 13 - 19 Jan | C3: 4800 | D3: =C3*2% -> 96 | E3: =D3*18% -> 17.28 | F3: =C3-D3-E3 -> 4686.72 | G3: =C3*0.5% -> 24 | H3: =D3*0.1% -> 0.096 | I3: =F3-G3-H3 -> 4662.624
B4: 20 - 31 Jan | C4: 7200 | D4: =C4*2% -> 144 | E4: =D4*18% -> 25.92 | F4: =C4-D4-E4 -> 7030.08 | G4: =C4*0.5% -> 36 | H4: =D4*0.1% -> 0.144 | I4: =F4-G4-H4 -> 6993.936
B5: Total | C5: =SUM(C2:C4) -> 24400 | F5: =SUM(F2:F4) -> 23824.16 | I5: =SUM(I2:I4) -> 23701.672

Sheet Khelomore
A1: Link | B1: Date | C1: Paid to Khelomore (₹) | D1: Commissions (₹) | E1: Final Amount (₹)
B2: 1 - 13 Jan | C2: 2394 | D2: =C2*5% -> 119.7 | E2: =C2-D2 -> 2274.3
B3: 14 - 25 Jan | C3: 3800 | D3: =C3*5% -> 190 | E3: =C3-D3 -> 3610
B4: 26 - 31 Jan | C4: 3420 | D4: =C4*5% -> 171 | E4: =C4-D4 -> 3249
C5: =SUM(C2:C4) -> 9614 | E5: =SUM(E2:E4) -> 9133.3

Sheet Coaching
A1: Sports Type | B1: Coaching Type | C1: Start Date | D1: Amount Collected
A2: Pickleball | B2: Kids & Adult | C2: Jan | D2: 44000

Sheet Misfits
A1: Link | B1: Date | C1: Paid to Misfits (₹) | D1: Post Comission (20%) | E1: TDS | F1: Final Amount (₹)
B2: 1 - 31 Jan | C2: 0

Sheet Sportomic
A1: Link | B1: Date | C1: Paid to Sportomic (₹)
B2: 1 - 31 Jan | C2: 13650

Sheet Courtly
A1: Link | B1: Date | C1: Paid to Sportomic | D1: Comission | E1: TDS | F1: Final Amt | G1: Notes
B2: 46053 | C2: 38300 | D2: =C2*3% -> 1149 | E2: =(C2-D2)*2% -> 743.02 | F2: =C2-D2-E2 -> 36407.98 | G2: Dwarka Tournament
