Workbook

Sheet Summary
B2: 1 - 31 May
B3: Particulars | C3: Amount
C4: Total | D4: Pickleball | E4: Turf
B5: Pay & Play | C5: =sum(C6,C12) -> 240143 | D5: =sum(D6,D12) -> 131215 | E5: =sum(E6,E12) -> 108928
B6: Online | C6: =sum(C7:C11) -> 133403 | D6: =sum(D7:D11) -> 70875 | E6: =sum(E7:E11) -> 62528
B7: District | C7: =District!C3 -> 131267 | D7: =District!B5 -> 70237 | E7: =District!B6 -> 61030
B8: Hudle | C8: =Hudle!C4 -> 2136 | D8: =Hudle!B6 -> 638 | E8: =Hudle!B7 -> 1498
B9: Playo | C9: 0 | D9: 0 | E9: 0
B10: Khelomore | C10: 0 | D10: 0 | E10: 0
B11: Zplys | C11: 0 | D11: 0 | E11: 0
B12: Offline | C12: =sum(C13:C14) -> 106740 | D12: =sum(D13:D14) -> 60340 | E12: =sum(E13:E14) -> 46400
B13: Bookings | C13: ='Offline & RG Community'!E33+'Offline & RG Community'!F33 -> 59940 | D13: ='Offline & RG Community'!E33 -> 22940 | E13: ='Offline & RG Community'!F33 -> 37000
B14: Memberships | C14: =Memberships!E5 -> 46800 | D14: =Memberships!E2+Memberships!E4+(Memberships!E3/2) -> 37400 | E14: =Memberships!E3/2 -> 9400
B15: Community | C15: =sum(C16:C17) -> 2400 | D15: =sum(D16:D17) -> 2400 | E15: =sum(E16:E17) -> 0
B16: Pickup games | C16: ='Offline & RG Community'!G33 -> 2400 | D16: ='Offline & RG Community'!G33 -> 2400 | E16: 0
B17: Social Events/Tournaments | C17: 0 | D17: 0 | E17: 0
B18: Academy | C18: 0 | D18: 0 | E18: 0
B19: Events & Partnership | C19: =sum(C20,C21) -> 0 | D19: =sum(D20,D21) -> 0 | E19: 0
B20: Corporate events | C20: 0 | D20: 0 | E20: 0
B21: All B2B partnerships | C21: 0 | D21: 0 | E21: 0
B22: Commerce | C22: =sum(C23:C25) -> 3925 | D22: =sum(D23:D25) -> 3925 | E22: =sum(E23:E25) -> 0
B23: Product rental | C23: ='Offline & RG Community'!H33 -> 3925 | D23: ='Offline & RG Community'!H33 -> 3925 | E23: 0
B24: Product sales | C24: 0 | D24: 0 | E24: 0
B25: F&B | C25: 0 | D25: 0 | E25: 0
B26: Other Income | C26: 0 | D26: 0 | E26: 0
B27: Total Gross Revenue | C27: =C6+C12+C15+C18+C19+C22+C26 -> 246468 | D27: =D6+D12+D15+D18+D19+D22+D26 -> 137540 | E27: =E6+E12+E15+E18+E19+E22+E26 -> 108928
B28: Total Net Revenue (Post Commissions) | C28: ='Offline & RG Community'!K33+District!F3+Hudle!E4+Memberships!G5 -> 232567.63
B29: Total Revenue post GST | C29: =C28/1.18 -> 197091.21

Sheet Offline & RG Community
A1: Date | B1: Day | C1: Offline booking hours | D1: Discount Given | E1: Booking Revenue | F1: Booking Revenue (Turf) | G1: Community Revenue | H1: Paddle Rental | I1: Total Revenue | J1: Payment Gateway | K1: Net Revenue
A2: 46143 | B2: Friday | C2: 4.5 | D2: 0 and 10% | E2: 2880 | F2: 0 | G2: 0 | H2: 550 | I2: =sum(E2:H2) -> 3430 | J2: =I2*1.75% -> 60.025 | K2: =I2-J2 -> 3369.975
A3: 46144 | B3: Saturday | C3: 4 | D3: 0 and 10% | E3: =1280+560 -> 1840 | F3: 1800 | G3: 0 | H3: 350 | I3: =sum(E3:H3) -> 3990 | J3: =I3*1.75% -> 69.825 | K3: =I3-J3 -> 3920.175
A4: 46145 | B4: Sunday | C4: 5 | D4: 0 and 10% | E4: 2560 | F4: 1920 | G4: 0 | H4: 200 | I4: =sum(E4:H4) -> 4680 | J4: =I4*1.75% -> 81.9 | K4: =I4-J4 -> 4598.1
A5: 46146 | B5: Monday | C5: 2 | D5: 0 and 10% | E5: 1280 | F5: 0 | G5: 0 | H5: 150 | I5: =sum(E5:H5) -> 1430 | J5: =I5*1.75% -> 25.025 | K5: =I5-J5 -> 1404.975
A6: 46147 | B6: Tuesday | C6: 3 | D6: 0 and 10% | E6: 1920 | F6: 0 | G6: 0 | H6: 175 | I6: =sum(E6:H6) -> 2095 | J6: =I6*1.75% -> 36.6625 | K6: =I6-J6 -> 2058.3375
A7: 46148 | B7: Wednesday | C7: 2.5 | D7: 0 and 10% | E7: 320 | F7: 2560 | G7: 0 | H7: 50 | I7: =sum(E7:H7) -> 2930 | J7: =I7*1.75% -> 51.275 | K7: =I7-J7 -> 2878.725
A8: 46149 | B8: Thursday | C8: 7 | D8: 0 and 10% | E8: 1920 | F8: 4400 | G8: 0 | H8: 150 | I8: =sum(E8:H8) -> 6470 | J8: =I8*1.75% -> 113.225 | K8: =I8-J8 -> 6356.775
A9: 46150 | B9: Friday | C9: 3 | D9: 0 and 10% | E9: 640 | F9: 2560 | G9: 0 | H9: 200 | I9: =sum(E9:H9) -> 3400 | J9: =I9*1.75% -> 59.5 | K9: =I9-J9 -> 3340.5
A10: 46151 | B10: Saturday | C10: 1 | D10: 0 and 10% | E10: 640 | F10: 0 | G10: 0 | H10: 400 | I10: =sum(E10:H10) -> 1040 | J10: =I10*1.75% -> 18.2 | K10: =I10-J10 -> 1021.8
A11: 46152 | B11: Sunday | C11: 5 | D11: 0 and 10% | E11: 960 | F11: 1200 | G11: 800 | H11: 400 | I11: =sum(E11:H11) -> 3360 | J11: =I11*1.75% -> 58.8 | K11: =I11-J11 -> 3301.2
A12: 46153 | B12: Monday | C12: 0 | D12: 0 and 10% | E12: 0 | F12: 0 | G12: 0 | H12: 0 | I12: =sum(E12:H12) -> 0 | J12: =I12*1.75% -> 0 | K12: =I12-J12 -> 0
A13: 46154 | B13: Tuesday | C13: 3 | D13: 0 and 10% | E13: 640 | F13: 1800 | G13: 800 | H13: 0 | I13: =sum(E13:H13) -> 3240 | J13: =I13*1.75% -> 56.7 | K13: =I13-J13 -> 3183.3
A14: 46155 | B14: Wednesday | C14: 2 | D14: 0 and 10% | E14: 1280 | F14: 0 | G14: 0 | H14: 0 | I14: =sum(E14:H14) -> 1280 | J14: =I14*1.75% -> 22.4 | K14: =I14-J14 -> 1257.6
A15: 46156 | B15: Thursday | C15: 0 | D15: 0 and 10% | E15: 0 | F15: 0 | G15: 0 | H15: 0 | I15: =sum(E15:H15) -> 0 | J15: =I15*1.75% -> 0 | K15: =I15-J15 -> 0
A16: 46157 | B16: Friday | C16: 3 | D16: 0 and 10% | E16: 300 | F16: 2400 | G16: 0 | H16: 200 | I16: =SUM(E16:H16) -> 2900 | J16: =I16*1.75% -> 50.75 | K16: =I16-J16 -> 2849.25
A17: 46158 | B17: Saturday | C17: 5.5 | D17: 0 and 10% | E17: 2240 | F17: 5060 | G17: 0 | H17: 350 | I17: =SUM(E17:H17) -> 7650 | J17: =I17*1.75% -> 133.875 | K17: =I17-J17 -> 7516.125
A18: 46159 | B18: Sunday | C18: 0 | D18: 0 and 10% | E18: 0 | F18: 0 | G18: 0 | H18: 0 | I18: =SUM(E18:H18) -> 0 | J18: =I18*1.75% -> 0 | K18: =I18-J18 -> 0
A19: 46160 | B19: Monday | C19: 0.5 | D19: 0 and 10% | E19: 320 | F19: 0 | G19: 0 | H19: 50 | I19: =SUM(E19:H19) -> 370 | J19: =I19*1.75% -> 6.475 | K19: =I19-J19 -> 363.525
A20: 46161 | B20: Tuesday | C20: 1 | D20: 0 and 10% | E20: 0 | F20: 0 | G20: 800 | H20: 0 | I20: =SUM(E20:H20) -> 800 | J20: =I20*1.75% -> 14 | K20: =I20-J20 -> 786
A21: 46162 | B21: Wednesday | C21: 0 | D21: 0 and 10% | E21: 0 | F21: 0 | G21: 0 | H21: 0 | I21: =SUM(E21:H21) -> 0 | J21: =I21*1.75% -> 0 | K21: =I21-J21 -> 0
A22: 46163 | B22: Thursday | C22: 1 | D22: 0 and 10% | E22: 0 | F22: 1800 | G22: 0 | H22: 200 | I22: =sum(E22:H22) -> 2000 | J22: =I22*1.75% -> 35 | K22: =I22-J22 -> 1965
A23: 46164 | B23: Friday | C23: 0 | D23: 0 and 10% | E23: 0 | F23: 0 | G23: 0 | H23: 0 | I23: =SUM(E23:H23) -> 0 | J23: =I23*1.75% -> 0 | K23: =I23-J23 -> 0
A24: 46165 | B24: Saturday | C24: 3 | D24: 0 and 10% | E24: 1280 | F24: 2560 | G24: 0 | H24: 0 | I24: =SUM(E24:H24) -> 3840 | J24: =I24*1.75% -> 67.2 | K24: =I24-J24 -> 3772.8
A25: 46166 | B25: Sunday | C25: 1.5 | D25: 0 and 10% | E25: 960 | F25: 0 | G25: 0 | H25: 450 | I25: =SUM(E25:H25) -> 1410 | J25: =I25*1.75% -> 24.675 | K25: =I25-J25 -> 1385.325
A26: 46167 | B26: Monday | C26: 0 | D26: 0 and 10% | E26: 0 | F26: 0 | G26: 0 | H26: 0 | I26: =SUM(E26:H26) -> 0 | J26: =I26*1.75% -> 0 | K26: =I26-J26 -> 0
A27: 46168 | B27: Tuesday | C27: 0 | D27: 0 and 10% | E27: 0 | F27: 0 | G27: 0 | H27: 0 | I27: =SUM(E27:H27) -> 0 | J27: =I27*1.75% -> 0 | K27: =I27-J27 -> 0
A28: 46169 | B28: Wednesday | C28: 0 | D28: 0 and 10% | E28: 0 | F28: 0 | G28: 0 | H28: 0 | I28: =SUM(E28:H28) -> 0 | J28: =I28*1.75% -> 0 | K28: =I28-J28 -> 0
A29: 46170 | B29: Thursday | C29: 0 | D29: 0 and 10% | E29: 0 | F29: 0 | G29: 0 | H29: 0 | I29: =SUM(E29:H29) -> 0 | J29: =I29*1.75% -> 0 | K29: =I29-J29 -> 0
A30: 46171 | B30: Friday | C30: 2.5 | D30: 0 and 10% | E30: 0 | F30: 4480 | G30: 0 | H30: 0 | I30: =SUM(E30:H30) -> 4480 | J30: =I30*1.75% -> 78.4 | K30: =I30-J30 -> 4401.6
A31: 46172 | B31: Saturday | C31: 5 | D31: 0 and 10% | E31: 640 | F31: 4460 | G31: 0 | H31: 0 | I31: =SUM(E31:H31) -> 5100 | J31: =I31*1.75% -> 89.25 | K31: =I31-J31 -> 5010.75
A32: 46173 | B32: Sunday | C32: 0.5 | D32: 0 and 10% | E32: 320 | F32: 0 | G32: 0 | H32: 50 | I32: =SUM(E32:H32) -> 370 | J32: =I32*1.75% -> 6.475 | K32: =I32-J32 -> 363.525
A33: Total | C33: =SUM(C2:C32) -> 65.5 | E33: =SUM(E2:E32) -> 22940 | F33: =SUM(F2:F32) -> 37000 | G33: =SUM(G2:G32) -> 2400 | H33: =SUM(H2:H32) -> 3925 | I33: =SUM(I2:I32) -> 66265 | J33: =SUM(J2:J32) -> 1159.6375 | K33: =SUM(K2:K32) -> 65105.363

Sheet District
A1: Link | B1: Date | C1: Paid to District | D1: Commissions (₹) | E1: GST on Commission | F1: Net Revenue | G1: TCS | H1: TDS | I1: Final Amount (₹)
B2: 1 - 31 May | C2: 131267 | D2: 10562 | E2: 1901 | F2: =C2-D2-E2 -> 118804 | G2: 880 | H2: 176 | I2: 117746
B3: Total | C3: =SUM(C2) -> 131267 | F3: =SUM(F2) -> 118804 | I3: =SUM(I2) -> 117746
A5: Pickleball | B5: =C3-B6 -> 70237
A6: Turf | B6: 61030

Sheet Hudle
A1: Link | B1: Date | C1: Paid to Hudle | D1: Commisions (Including GST) | E1: Net Revenue | F1: TDS | G1: TCS | H1: Amount
B2: 1 - 31 May | C2: 2136 | D2: 277.73 | E2: =C2-D2 -> 1858.27 | F2: 2 | G2: 9 | H2: 1847
B4: Total | C4: =SUM(C2) -> 2136 | E4: =SUM(E2) -> 1858.27 | H4: =SUM(H2) -> 1847
A6: Pickleball | B6: =C4-B7 -> 638
A7: Turf | B7: 1498

Sheet Memberships
A1: Member Name | B1: Sports Type | C1: Membership Type | D1: Start Date | E1: Amount Collected | F1: Payment Gateway | G1: Net Revenue
A2: Akshay | B2: Pickleball | C2: 30 Slots | D2: May | E2: 14000 | F2: 0 | G2: =E2-F2 -> 14000
A3: ISH | B3: Turf and Pickleball | C3: Custom | D3: May | E3: 18800 | F3: 0 | G3: =E3-F3 -> 18800
A4: Ritesh | B4: Pickleball | C4: 30 Slots | D4: May | E4: 14000 | F4: 0 | G4: =E4-F4 -> 14000
A5: Total | E5: =SUM(E2:E4) -> 46800 | F5: =SUM(F2:F4) -> 0 | G5: =SUM(G2:G4) -> 46800
