Workbook

Sheet Summary
B2: 1 - 30 June
B3: Particulars | C3: Amount
C4: Pickleball
B5: Pay & Play | C5: =sum(C6,C12) -> 185901
B6: Online | C6: =sum(C7:C11) -> 142976
B7: District | C7: =District!C4 -> 142976
B8: Hudle | C8: 0
B9: Playo | C9: 0
B10: Khelomore | C10: 0
B11: Zplys | C11: 0
B12: Offline | C12: =sum(C13:C14) -> 42925
B13: Bookings | C13: ='Offline & RG Community'!E32 -> 42925
B14: Memberships | C14: 0
B15: Community | C15: =sum(C16:C17) -> 134920
B16: Pickup games | C16: ='Offline & RG Community'!F32 -> 40300
B17: Social Events/Tournaments | C17: ='Social EventsTournaments'!B5 -> 94620
B18: Academy | C18: =Academy!C2 -> 28500
B19: Events & Partnership | C19: =sum(C20,C21) -> 20000
B20: Corporate events | C20: 0
B21: All B2B partnerships | C21: =B2B!D5 -> 20000
B22: Commerce | C22: =sum(C23:C25) -> 19879
B23: Product rental | C23: ='Offline & RG Community'!G32 -> 12400
B24: Product sales | C24: =B2B!D3 -> 2399
B25: F&B | C25: ='Offline & RG Community'!H32 -> 5080
B26: Other Income | C26: 0
B27: Total Gross Revenue | C27: =sum(C26+C22+C19+C18+C15+C12+C6) -> 389200
B28: Total Net Revenue (Post Commissions) | C28: ='Offline & RG Community'!K32+District!F4+'Social EventsTournaments'!D5+Academy!E2+B2B!D5+B2B!D3 -> 371359.11
B29: Total Revenue post GST | C29: =C28/1.18 -> 314711.11
B30: Expenses
B31: Venue Manager + Cleaner | C31: 60164
B32: Marketing, Branding & Community | C32: 15000
B33: Balls Expense | C33: 9500
B34: Branding Revamp | C34: 12595
B35: F&B Inventory Cost | C35: 3024
B36: Total Expenses | C36: =C31+C32+C33+C34+C35 -> 100283
B37: Net Profit (Revenue - Expenses) | C37: =C29-C36 -> 214428.11
B39: School's Profit Share (65%) | C39: =C37*65% -> 139378.27
B40: RallyGully's Profit Share (35%) | C40: =C37*35% -> 75049.839

Sheet Offline & RG Community
A1: Date | B1: Day | C1: Offline booking hours | D1: Discount Given | E1: Booking Revenue | F1: Community Revenue | G1: Paddle Rental | H1: F&B | I1: Total Revenue | J1: Payment Gateway | K1: Net Revenue
A2: 46174 | B2: Monday | C2: 1 | D2: 0 and 10% | E2: 1000 | F2: 4200 | G2: 0 | H2: 70 | I2: =sum(E2:H2) -> 5270 | J2: =I2*1.75% -> 92.225 | K2: =I2-J2 -> 5177.775
A3: 46175 | B3: Tuesday | C3: 1 | D3: 0 and 10% | E3: 900 | F3: 0 | G3: 1000 | H3: 105 | I3: =sum(E3:H3) -> 2005 | J3: =I3*1.75% -> 35.0875 | K3: =I3-J3 -> 1969.9125
A4: 46176 | B4: Wednesday | C4: 3 | D4: 0 and 10% | E4: 3240 | F4: 0 | G4: 0 | H4: 0 | I4: =sum(E4:H4) -> 3240 | J4: =I4*1.75% -> 56.7 | K4: =I4-J4 -> 3183.3
A5: 46177 | B5: Thursday | C5: 6 | D5: 0 and 10% | E5: =7560+1350 -> 8910 | F5: 3600 | G5: 400 | H5: 315 | I5: =sum(E5:H5) -> 13225 | J5: =I5*1.75% -> 231.4375 | K5: =I5-J5 -> 12993.562
A6: 46178 | B6: Friday | C6: 0 | D6: 0 and 10% | E6: 0 | F6: 3000 | G6: 300 | H6: 105 | I6: =sum(E6:H6) -> 3405 | J6: =I6*1.75% -> 59.5875 | K6: =I6-J6 -> 3345.4125
A7: 46179 | B7: Saturday | C7: 0.5 | D7: 0 and 10% | E7: 550 | F7: 2400 | G7: 1100 | H7: 105 | I7: =sum(E7:H7) -> 4155 | J7: =I7*1.75% -> 72.7125 | K7: =I7-J7 -> 4082.2875
A8: 46180 | B8: Sunday | C8: 0 | D8: 0 and 10% | E8: 0 | F8: 600 | G8: 400 | H8: 0 | I8: =sum(E8:H8) -> 1000 | J8: =I8*1.75% -> 17.5 | K8: =I8-J8 -> 982.5
A9: 46181 | B9: Monday | C9: 0 | D9: 0 and 10% | E9: 0 | F9: 1800 | G9: 0 | H9: 0 | I9: =sum(E9:H9) -> 1800 | J9: =I9*1.75% -> 31.5 | K9: =I9-J9 -> 1768.5
A10: 46182 | B10: Tuesday | C10: 0 | D10: 0 and 10% | E10: 0 | F10: 0 | G10: 400 | H10: 0 | I10: =sum(E10:H10) -> 400 | J10: =I10*1.75% -> 7 | K10: =I10-J10 -> 393
A11: 46183 | B11: Wednesday | C11: 6.5 | D11: 0 and 10% | E11: 6940 | F11: 0 | G11: 0 | H11: 560 | I11: =sum(E11:H11) -> 7500 | J11: =I11*1.75% -> 131.25 | K11: =I11-J11 -> 7368.75
A12: 46184 | B12: Thursday | C12: 2.5 | D12: 0 and 10% | E12: 2300 | F12: 900 | G12: 100 | H12: 245 | I12: =sum(E12:H12) -> 3545 | J12: =I12*1.75% -> 62.0375 | K12: =I12-J12 -> 3482.9625
A13: 46185 | B13: Friday | C13: 0 | D13: 0 and 10% | E13: 0 | F13: 0 | G13: 2500 | H13: 0 | I13: =sum(E13:H13) -> 2500 | J13: =I13*1.75% -> 43.75 | K13: =I13-J13 -> 2456.25
A14: 46186 | B14: Saturday | C14: 2 | D14: 0 and 10% | E14: 1900 | F14: 0 | G14: 400 | H14: 315 | I14: =sum(E14:H14) -> 2615 | J14: =I14*1.75% -> 45.7625 | K14: =I14-J14 -> 2569.2375
A15: 46187 | B15: Sunday | C15: 1 | D15: 0 and 10% | E15: 900 | F15: 2100 | G15: 800 | H15: 0 | I15: =sum(E15:H15) -> 3800 | J15: =I15*1.75% -> 66.5 | K15: =I15-J15 -> 3733.5
A16: 46188 | B16: Monday | C16: 0 | D16: 0 and 10% | E16: 0 | F16: 0 | G16: 100 | H16: 0 | I16: =SUM(E16:H16) -> 100 | J16: =I16*1.75% -> 1.75 | K16: =I16-J16 -> 98.25
A17: 46189 | B17: Tuesday | C17: 0 | D17: 0 and 10% | E17: 0 | F17: 2400 | G17: 300 | H17: 105 | I17: =SUM(F17:H17) -> 2805 | J17: =I17*1.75% -> 49.0875 | K17: =I17-J17 -> 2755.9125
A18: 46190 | B18: Wednesday | C18: 0 | D18: 0 and 10% | E18: 0 | F18: 0 | G18: 0 | H18: 210 | I18: =SUM(E18:H18) -> 210 | J18: =I18*1.75% -> 3.675 | K18: =I18-J18 -> 206.325
A19: 46191 | B19: Thursday | C19: 6 | D19: 0 and 10% | E19: 6040 | F19: 2400 | G19: 500 | H19: 210 | I19: =SUM(E19:H19) -> 9150 | J19: =I19*1.75% -> 160.125 | K19: =I19-J19 -> 8989.875
A20: 46192 | B20: Friday | C20: 0 | D20: 0 and 10% | E20: 0 | F20: 0 | G20: 100 | H20: 0 | I20: =SUM(E20:H20) -> 100 | J20: =I20*1.75% -> 1.75 | K20: =I20-J20 -> 98.25
A21: 46193 | B21: Saturday | C21: 0 | D21: 0 and 10% | E21: 0 | F21: 0 | G21: 400 | H21: 350 | I21: =SUM(E21:H21) -> 750 | J21: =I21*1.75% -> 13.125 | K21: =I21-J21 -> 736.875
A22: 46194 | B22: Sunday | C22: 0 | D22: 0 and 10% | E22: 0 | F22: 0 | G22: 300 | H22: 600 | I22: =sum(E22:H22) -> 900 | J22: =I22*1.75% -> 15.75 | K22: =I22-J22 -> 884.25
A23: 46195 | B23: Monday | C23: 1 | D23: 0 and 10% | E23: 810 | F23: 2400 | G23: 1100 | H23: 455 | I23: =SUM(E23:H23) -> 4765 | J23: =I23*1.75% -> 83.3875 | K23: =I23-J23 -> 4681.6125
A24: 46196 | B24: Tuesday | C24: 2 | D24: 0 and 10% | E24: =1500+1105 -> 2605 | F24: 2250 | G24: 600 | H24: 70 | I24: =SUM(E24:H24) -> 5525 | J24: =I24*1.75% -> 96.6875 | K24: =I24-J24 -> 5428.3125
A25: 46197 | B25: Wednesday | C25: 1.5 | D25: 0 and 10% | E25: 1350 | F25: 900 | G25: 100 | H25: 0 | I25: =SUM(E25:H25) -> 2350 | J25: =I25*1.75% -> 41.125 | K25: =I25-J25 -> 2308.875
A26: 46198 | B26: Thursday | C26: 3.5 | D26: 0 and 10% | E26: 3580 | F26: 0 | G26: 300 | H26: 140 | I26: =SUM(E26:H26) -> 4020 | J26: =I26*1.75% -> 70.35 | K26: =I26-J26 -> 3949.65
A27: 46199 | B27: Friday | C27: 2 | D27: 0 and 10% | E27: 1900 | F27: 5650 | G27: 200 | H27: 350 | I27: =SUM(E27:H27) -> 8100 | J27: =I27*1.75% -> 141.75 | K27: =I27-J27 -> 7958.25
A28: 46200 | B28: Saturday | C28: 0 | D28: 0 and 10% | E28: 0 | F28: 900 | G28: 0 | H28: 35 | I28: =SUM(E28:H28) -> 935 | J28: =I28*1.75% -> 16.3625 | K28: =I28-J28 -> 918.6375
A29: 46201 | B29: Sunday | C29: 0 | D29: 0 and 10% | E29: 0 | F29: 0 | G29: 800 | H29: 70 | I29: =SUM(E29:H29) -> 870 | J29: =I29*1.75% -> 15.225 | K29: =I29-J29 -> 854.775
A30: 46202 | B30: Monday | C30: 0 | D30: 0 and 10% | E30: 0 | F30: 3600 | G30: 100 | H30: 175 | I30: =SUM(E30:H30) -> 3875 | J30: =I30*1.75% -> 67.8125 | K30: =I30-J30 -> 3807.1875
A31: 46203 | B31: Tuesday | C31: 0 | D31: 0 and 10% | E31: 0 | F31: 1200 | G31: 100 | H31: 490 | I31: =SUM(E31:H31) -> 1790 | J31: =I31*1.75% -> 31.325 | K31: =I31-J31 -> 1758.675
A32: Total | E32: =SUM(E1:E31) -> 42925 | F32: =SUM(F1:F31) -> 40300 | G32: =SUM(G1:G31) -> 12400 | H32: =SUM(H1:H31) -> 5080 | I32: =SUM(I1:I31) -> 100705 | J32: =SUM(J1:J31) -> 1762.3375 | K32: =SUM(K1:K31) -> 98942.663

Sheet District
A1: Link | B1: Date | C1: Paid to District | D1: Commissions (₹) | E1: GST on Commission | F1: Net Revenue | G1: TCS | H1: TDS | I1: Final Amount (₹)
B2: 1 - 30 June | C2: 142976 | D2: 9009 | E2: 1621 | F2: =C2-D2-E2 -> 132346 | G2: 715 | H2: 143 | I2: =F2-G2-H2 -> 131488
B4: Total | C4: =SUM(C2:C3) -> 142976 | F4: =SUM(F2:F3) -> 132346 | I4: =SUM(I2:I3) -> 131488

Sheet Social EventsTournaments
A1: Date | B1: Amt | C1: Post Comission | D1: Net Revenue | E1: TDS | F1: Final Amount (₹) | G1: Notes
A2: June (SDPT) | B2: 78300 | C2: =B2*5% -> 3915 | D2: =B2-C2 -> 74385 | E2: =B2*2% -> 1566 | F2: =D2-E2 -> 72819 | G2: Courtly
A3: June (SDPT) | B3: 2000 | C3: =B3*6% -> 120 | D3: =B3-C3 -> 1880 | E3: 0 | F3: =D3-E3 -> 1880 | G3: District
A4: June (SDPT) | B4: =6120+1800+6400 -> 14320 | C4: =B4*4% -> 572.8 | D4: =B4-C4 -> 13747.2 | E4: 0 | F4: =D4-E4 -> 13747.2 | G4: Offline - QR, POD, Cash & District
A5: Total | B5: =SUM(B2:B4) -> 94620 | D5: =SUM(D2:D4) -> 90012.2 | F5: =SUM(F2:F4) -> 88446.2

Sheet Academy
A1: Sports | B1: Month | C1: Amt | D1: Payment Gateway | E1: Net Revenue
A2: Pickleball | B2: June | C2: 28500 | D2: =C2*2.5%*1.18 -> 840.75 | E2: =C2-D2 -> 27659.25

Sheet B2B
A1: Date | B1: Brand | C1: Type | D1: Amt
A2: June | B2: Savikalpa | C2: Activation | D2: 15000
A3: June | B3: Yaba | C3: Paddle Sales | D3: 2399
A4: June | B4: Eprise | C4: Activation | D4: 5000
A5: Total | D5: =SUM(D2,D4) -> 20000
