Workbook

Sheet Summary
B2: Date: 1 - 31 Mar
B3: Particulars | C3: Amount
B4: Offline | C4: =SUM(C5,C6,C7,C8) -> 36510
B5: Rentals | C5: ='Offline & RG Community'!G33 -> 6230
B6: F&B | C6: ='Offline & RG Community'!H33 -> 0
B7: Product Sales | C7: 0
B8: Bookings | C8: ='Offline & RG Community'!E33 -> 30280
B9: Online: Third Party Platform | C9: =SUM(C10:C14) -> 50065
B10: Hudle | C10: =Hudle!C4 -> 26070
B11: Playo | C11: =Playo!C4 -> 1520
B12: District | C12: =District!C4 -> 18175
B13: Khelomore | C13: =Khelomore!C3 -> 4300
B14: Zplys | C14: 0
B15: Community | C15: =SUM(C17,C18,C19, C16) -> 2300
B16: Courtly (Organized by RallyGully) | C16: 0
B17: Sportomic (Organized by RallyGully) | C17: 0
B18: Rallygully Community games | C18: ='Offline & RG Community'!F33 -> 2300
B19: Misfits Community | C19: 0
B20: Memberships | C20: 0
B21: Coaching | C21: 0
B22: Corporate Events | C22: 0
B23: Brand Activation | C23: 0
B24: Other Income | C24: ='Other Income'!E2 -> 18000 | D24: (Note for CA Team: Please note that RallyGully hasn't received the 18000 rental for basketball rental service provided) - GST payment would have to be made by Drive & Kick Team
B25: Total Gross Revenue | C25: =sum(C4,C9,C15,C20,C22,C23,C24) -> 106875
B26: Total Net Revenue (Post Commissions) | C26: ='Offline & RG Community'!I33+Hudle!E4+Playo!F4+District!F4+Khelomore!E3+'Other Income'!E2 -> 102503.36
B27: Total Revenue post GST | C27: =((C26-C24)/1.18)+C24 -> 89613.017
B28: Drive & Kick Share (70%) | C28: =C27*70% -> 62729.112
B29: Drive & Kick Share (Final share after incorporting 18k already received by Drive Kick) | C29: =C28-C24 -> 44729.112
B30: RallyGully's Share (30%) | C30: =C27*30% -> 26883.905

Sheet Offline & RG Community
A1: Date | B1: Day | C1: Offline booking hours | D1: Discount Given | E1: Booking Revenue | F1: Community Revenue | G1: Paddle Rental | H1: F&B | I1: Total Revenue
A2: 46082 | B2: Sunday | C2: 1 | D2: 20% and 10% | E2: 640 | F2: 0 | G2: 500 | H2: 0 | I2: =SUM(E2:H2) -> 1140
A3: 46083 | B3: Monday | C3: 2 | D3: 20% and 10% | E3: 1280 | F3: 0 | G3: 300 | H3: 0 | I3: =SUM(E3:H3) -> 1580
A4: 46084 | B4: Tuesday | C4: 1 | D4: 20% and 10% | E4: 640 | F4: 0 | G4: 400 | H4: 0 | I4: =SUM(E4:H4) -> 1040
A5: 46085 | B5: Wednesday | C5: 0 | D5: 20% and 10% | E5: 0 | F5: 0 | G5: 200 | H5: 0 | I5: =SUM(E5:H5) -> 200
A6: 46086 | B6: Thursday | C6: 2 | D6: 20% and 10% | E6: 1280 | F6: 0 | G6: 250 | H6: 0 | I6: =SUM(E6:H6) -> 1530
A7: 46087 | B7: Friday | C7: 0 | D7: 20% and 10% | E7: 0 | F7: 0 | G7: 250 | H7: 0 | I7: =SUM(E7:H7) -> 250
A8: 46088 | B8: Saturday | C8: 0.5 | D8: 20% and 10% | E8: 300 | F8: 0 | G8: 500 | H8: 0 | I8: =SUM(E8:H8) -> 800
A9: 46089 | B9: Sunday | C9: 3 | D9: 20% and 10% | E9: 2160 | F9: 1500 | G9: 300 | H9: 0 | I9: =SUM(E9:H9) -> 3960
A10: 46090 | B10: Monday | C10: 3 | D10: 20% and 10% | E10: 1920 | F10: 0 | G10: 230 | H10: 0 | I10: =SUM(E10:H10) -> 2150
A11: 46091 | B11: Tuesday | C11: 1 | D11: 20% and 10% | E11: 640 | F11: 0 | G11: 200 | H11: 0 | I11: =SUM(E11:H11) -> 840
A12: 46092 | B12: Wednesday | C12: 3 | D12: 20% and 10% | E12: 1920 | F12: 0 | G12: 350 | H12: 0 | I12: =SUM(E12:H12) -> 2270
A13: 46093 | B13: Thursday | C13: 2 | D13: 20% and 10% | E13: 1280 | F13: 0 | G13: 100 | H13: 0 | I13: =SUM(E13:H13) -> 1380
... A15: 46095 | B15: Saturday | C15: 3 | D15: 20% and 10% | E15: 2060 | F15: 800 | G15: 400 | H15: 0 | I15: =SUM(E15:H15) -> 3260
A16: 46096 | B16: Sunday | C16: 1.5 | D16: 20% and 10% | E16: =360+720 -> 1080 | F16: 0 | G16: 400 | H16: 0 | I16: =SUM(E16:H16) -> 1480
A17: 46097 | B17: Monday | C17: 1.5 | D17: 20% and 10% | E17: 1120 | F17: 0 | G17: 50 | H17: 0 | I17: =SUM(E17:H17) -> 1170
A18: 46098 | B18: Tuesday | C18: 2 | D18: 20% and 10% | E18: 1360 | F18: 0 | G18: 50 | H18: 0 | I18: =SUM(E18:H18) -> 1410
A19: 46099 | B19: Wednesday | C19: 0 | D19: 20% and 10% | E19: 0 | F19: 0 | G19: 0 | H19: 0 | I19: =SUM(E19:H19) -> 0
A20: 46100 | B20: Thursday | C20: 0 | D20: 20% and 10% | E20: 0 | F20: 0 | G20: 0 | H20: 0 | I20: =SUM(E20:H20) -> 0
A21: 46101 | B21: Friday | C21: 1 | D21: 20% and 10% | E21: 720 | F21: 0 | G21: 50 | H21: 0 | I21: =SUM(E21:H21) -> 770
A22: 46102 | B22: Saturday | C22: 2 | D22: 20% and 10% | E22: 1360 | F22: 0 | G22: 650 | H22: 0 | I22: =SUM(E22:H22) -> 2010
A23: 46103 | B23: Sunday | C23: 1 | D23: 20% and 10% | E23: 640 | F23: 0 | G23: 400 | H23: 0 | I23: =SUM(E23:H23) -> 1040
A24: 46104 | B24: Monday | C24: 3 | D24: 20% and 10% | E24: =1280+640 -> 1920 | F24: 0 | G24: 100 | H24: 0 | I24: =SUM(E24:H24) -> 2020
A25: 46105 | B25: Tuesday | C25: 1 | D25: 20% and 10% | E25: 640 | F25: 0 | G25: 50 | H25: 0 | I25: =SUM(E25:H25) -> 690
A26: 46106 | B26: Wednesday | C26: 3 | D26: 20% and 10% | E26: 2000 | F26: 0 | G26: 150 | H26: 0 | I26: =SUM(E26:H26) -> 2150
A27: 46107 | B27: Thursday | C27: 1.5 | D27: 20% and 10% | E27: =300+640 -> 940 | F27: 0 | G27: 0 | H27: 0 | I27: =SUM(E27:H27) -> 940
A28: 46108 | B28: Friday | C28: 2 | D28: 20% and 10% | E28: 1280 | F28: 0 | G28: 0 | H28: 0 | I28: =SUM(E28:H28) -> 1280
A29: 46109 | B29: Saturday | C29: 2 | D29: 20% and 10% | E29: 1440 | F29: 0 | G29: 150 | H29: 0 | I29: =SUM(E29:H29) -> 1590
A30: 46110 | B30: Sunday | C30: 0.5 | D30: 20% and 10% | E30: 300 | F30: 0 | G30: 200 | H30: 0 | I30: =SUM(E30:H30) -> 500
A31: 46111 | B31: Monday | C31: 1 | D31: 20% and 10% | E31: 640 | F31: 0 | G31: 0 | H31: 0 | I31: =SUM(E31:H31) -> 640
A32: 46112 | B32: Tuesday | C32: 0 | D32: 20% and 10% | E32: 0 | F32: 0 | G32: 0 | H32: 0 | I32: =SUM(E32:H32) -> 0
A33: Total | C33: =SUM(C1:C32) -> 45.5 | E33: =SUM(E1:E32) -> 30280 | F33: =SUM(F1:F32) -> 2300 | G33: =SUM(G1:G32) -> 6230 | H33: =SUM(H1:H32) -> 0 | I33: =SUM(I1:I32) -> 38810

Sheet Hudle
A1: Link | B1: Date | C1: Paid to Hudle | D1: Commisions (Including GST) | E1: Net Revenue | F1: TDS | G1: TCS | H1: Amount
B2: 1 - 23 Mar | C2: 24470 | D2: 3322.8 | E2: =C2-D2 -> 21147.2 | F2: 21.66 | G2: 108.35 | H2: 22107.25
B3: 23 - 31 Mar | C3: 1600 | D3: 187.2 | E3: =C3-D3 -> 1412.8 | F3: 1.22 | G3: 6.1 | H3: 1245.48
B4: Total | C4: =SUM(C2:C3) -> 26070 | E4: =SUM(E2:E3) -> 22560 | H4: =SUM(H2:H3) -> 23352.73

Sheet Playo
A1: Link | B1: Date | C1: Paid to Playo (₹) | D1: Commissions (₹) | E1: GST (₹) | F1: Net Revenue | G1: TDS (₹) | H1: TCS (₹) | I1: Final Amount (₹)
B2: 1 - 15 Mar | C2: 1520 | D2: 112 | E2: 20.16 | F2: =C2-D2-E2 -> 1387.84 | G2: 1.52 | H2: 7.6 | I2: 1378.72
B3: 16 - 31 Mar | F3: =C3-D3-E3 -> 0
B4: Total | C4: =SUM(C2) -> 1520 | F4: =SUM(F2) -> 1387.84 | I4: =SUM(I2) -> 1378.72

Sheet District
A1: Link | B1: Date | C1: Paid to District | D1: Commissions (₹) | E1: GST on Commission | F1: Net Revenue | G1: TCS | H1: TDS | I1: Final Amount (₹)
B2: 1 - 24 Mar | C2: 9775 | D2: 252 | E2: 45.36 | F2: =C2-D2-E2 -> 9477.64 | G2: 51.3 | H2: 10.3 | I2: 9841.44
B3: 25 - 31 Mar | C3: 8400 | D3: 184 | E3: 33.12 | F3: =C3-D3-E3 -> 8182.88 | G3: 46.03 | H3: 9.17 | I3: 8927.68
B4: Total | C4: =SUM(C2:C3) -> 18175 | F4: =SUM(F2:F3) -> 17660.52 | I4: =SUM(I2:I3) -> 18769.12

Sheet Khelomore
A1: Link | B1: Date | C1: Paid to Khelomore (₹) | D1: Commissions (₹) | E1: Final Amount (₹)
B2: 1 - 31 Mar | C2: 4300 | D2: =C2*5% -> 215 | E2: =C2-D2 -> 4085
B3: Total | C3: =SUM(C2) -> 4300 | E3: =SUM(E2) -> 4085

Sheet Other Income
A1: Month | B1: Coaching | C1: Sports Type | D1: Type | E1: Amount Collected
A2: Mar | B2: Basketball Coaching | C2: Basketball | D2: 3 days in week | E2: 18000
