Workbook

Sheet Summary
B2: 1 - 30 June
B3: Particulars | C3: Amount
C4: Pickleball
B5: Pay & Play | C5: =sum(C6,C12) -> 187817
B6: Online | C6: =sum(C7:C11) -> 122537
B7: District | C7: =District!C4 -> 122537
B8: Hudle | C8: 0
B9: Playo | C9: 0
B10: Khelomore | C10: 0
B11: Zplys | C11: 0
B12: Offline | C12: =sum(C13:C14) -> 65280
B13: Bookings | C13: ='Offline & RG Community'!E32 -> 65280
B14: Memberships | C14: 0
B15: Community | C15: =sum(C16:C17) -> 44484
B16: Pickup games | C16: ='Offline & RG Community'!F32 -> 38100
B17: Social Events/Tournaments | C17: ='Social EventsTournaments'!B4 -> 6384
B18: Academy | C18: =Academy!C2 -> 6500
B19: Events & Partnership | C19: 0
B20: Corporate events | C20: 0
B21: All B2B partnerships | C21: 0
B22: Commerce | C22: =sum(C23:C25) -> 8890
B23: Product rental | C23: ='Offline & RG Community'!G32 -> 8650
B24: Product sales | C24: 0
B25: F&B | C25: ='Offline & RG Community'!H32 -> 240
B26: Other Income | C26: 0
B27: Total Gross Revenue | C27: =C6+C12+C15+C18+C19+C22+C26 -> 247691
B28: Total Net Revenue (Post Commissions) | C28: ='Offline & RG Community'!K32+District!F4+'Social EventsTournaments'!D4+Academy!E2 -> 236003.33
B29: Total Revenue post GST | C29: =C28/1.18 -> 200002.82

Sheet Offline & RG Community
A1: Date | B1: Day | C1: Offline booking hours | D1: Discount Given | E1: Booking Revenue | F1: Community Revenue | G1: Paddle Rental | H1: F&B | I1: Total Revenue | J1: Payment Gateway | K1: Net Revenue
A2: 46174 | B2: Monday | C2: 1 | D2: 0 and 10% | E2: 720 | F2: 3200 | G2: 200 | H2: 105 | I2: =sum(E2:H2) -> 4225 | J2: =I2*1.75% -> 73.9375 | K2: =I2-J2 -> 4151.0625
A3: 46175 | B3: Tuesday | C3: 0 | D3: 0 and 10% | E3: 0 | F3: 3800 | G3: 100 | H3: 100 | I3: =sum(E3:H3) -> 4000 | J3: =I3*1.75% -> 70 | K3: =I3-J3 -> 3930
A4: 46176 | B4: Wednesday | C4: 1 | D4: 0 and 10% | E4: 640 | F4: 2400 | G4: 250 | H4: 0 | I4: =sum(E4:H4) -> 3290 | J4: =I4*1.75% -> 57.575 | K4: =I4-J4 -> 3232.425
A5: 46177 | B5: Thursday | C5: 1.5 | D5: 0 and 10% | E5: 1120 | F5: 3000 | G5: 450 | H5: 0 | I5: =sum(E5:H5) -> 4570 | J5: =I5*1.75% -> 79.975 | K5: =I5-J5 -> 4490.025
A6: 46178 | B6: Friday | C6: 3 | D6: 0 and 10% | E6: 4410 | F6: 0 | G6: 0 | H6: 0 | I6: =sum(E6:H6) -> 4410 | J6: =I6*1.75% -> 77.175 | K6: =I6-J6 -> 4332.825
A7: 46179 | B7: Saturday | C7: 10 | D7: 0 and 10% | E7: 6400 | F7: 0 | G7: 300 | H7: 0 | I7: =sum(E7:H7) -> 6700 | J7: =I7*1.75% -> 117.25 | K7: =I7-J7 -> 6582.75
A8: 46180 | B8: Sunday | C8: 5.5 | D8: 0 and 10% | E8: 7560 | F8: 0 | G8: 0 | H8: 0 | I8: =sum(E8:H8) -> 7560 | J8: =I8*1.75% -> 132.3 | K8: =I8-J8 -> 7427.7
A9: 46181 | B9: Monday | C9: 0 | D9: 0 and 10% | E9: 0 | F9: 3000 | G9: 150 | H9: 0 | I9: =sum(E9:H9) -> 3150 | J9: =I9*1.75% -> 55.125 | K9: =I9-J9 -> 3094.875
A10: 46182 | B10: Tuesday | C10: 1.5 | D10: 0 and 10% | E10: 1080 | F10: 0 | G10: 200 | H10: 0 | I10: =sum(E10:H10) -> 1280 | J10: =I10*1.75% -> 22.4 | K10: =I10-J10 -> 1257.6
A11: 46183 | B11: Wednesday | C11: 2.5 | D11: 0 and 10% | E11: 1720 | F11: 0 | G11: 50 | H11: 0 | I11: =sum(E11:H11) -> 1770 | J11: =I11*1.75% -> 30.975 | K11: =I11-J11 -> 1739.025
A12: 46184 | B12: Thursday | C12: 0.5 | D12: 0 and 10% | E12: 360 | F12: 800 | G12: 400 | H12: 0 | I12: =sum(E12:H12) -> 1560 | J12: =I12*1.75% -> 27.3 | K12: =I12-J12 -> 1532.7
A13: 46185 | B13: Friday | C13: 3 | D13: 0 and 10% | E13: 720 | F13: 2400 | G13: 700 | H13: 0 | I13: =sum(E13:H13) -> 3820 | J13: =I13*1.75% -> 66.85 | K13: =I13-J13 -> 3753.15
... A15: 46187 | B15: Sunday | C15: 3.5 | D15: 0 and 10% | E15: 2480 | F15: 0 | G15: 650 | H15: 0 | I15: =sum(E15:H15) -> 3130 | J15: =I15*1.75% -> 54.775 | K15: =I15-J15 -> 3075.225
A16: 46188 | B16: Monday | C16: 4 | D16: 0 and 10% | E16: 2880 | F16: 800 | G16: 200 | H16: 0 | I16: =SUM(E16:H16) -> 3880 | J16: =I16*1.75% -> 67.9 | K16: =I16-J16 -> 3812.1
A17: 46189 | B17: Tuesday | C17: 6 | D17: 0 and 10% | E17: 5030 | F17: 600 | G17: 200 | H17: 0 | I17: =SUM(E17:H17) -> 5830 | J17: =I17*1.75% -> 102.025 | K17: =I17-J17 -> 5727.975
A18: 46190 | B18: Wednesday | C18: 5.5 | D18: 0 and 10% | E18: 3800 | F18: 1600 | G18: 150 | H18: 0 | I18: =SUM(E18:H18) -> 5550 | J18: =I18*1.75% -> 97.125 | K18: =I18-J18 -> 5452.875
A19: 46191 | B19: Thursday | C19: 5 | D19: 0 and 10% | E19: 3520 | F19: 2400 | G19: 550 | H19: 0 | I19: =SUM(E19:H19) -> 6470 | J19: =I19*1.75% -> 113.225 | K19: =I19-J19 -> 6356.775
A20: 46192 | B20: Friday | C20: 1.5 | D20: 0 and 10% | E20: 1080 | F20: 1400 | G20: 250 | H20: 0 | I20: =SUM(E20:H20) -> 2730 | J20: =I20*1.75% -> 47.775 | K20: =I20-J20 -> 2682.225
A21: 46193 | B21: Saturday | C21: 1 | D21: 0 and 10% | E21: 720 | F21: 0 | G21: 100 | H21: 0 | I21: =SUM(E21:H21) -> 820 | J21: =I21*1.75% -> 14.35 | K21: =I21-J21 -> 805.65
A22: 46194 | B22: Sunday | C22: 2 | D22: 0 and 10% | E22: 1860 | F22: 2200 | G22: 450 | H22: 0 | I22: =sum(E22:H22) -> 4510 | J22: =I22*1.75% -> 78.925 | K22: =I22-J22 -> 4431.075
A23: 46195 | B23: Monday | C23: 0 | D23: 0 and 10% | E23: 0 | F23: 1400 | G23: 200 | H23: 0 | I23: =SUM(E23:H23) -> 1600 | J23: =I23*1.75% -> 28 | K23: =I23-J23 -> 1572
A24: 46196 | B24: Tuesday | C24: 2.5 | D24: 0 and 10% | E24: 1740 | F24: 0 | G24: 350 | H24: 0 | I24: =SUM(E24:H24) -> 2090 | J24: =I24*1.75% -> 36.575 | K24: =I24-J24 -> 2053.425
A25: 46197 | B25: Wednesday | C25: 0 | D25: 0 and 10% | E25: 0 | F25: 0 | G25: 100 | H25: 0 | I25: =SUM(E25:H25) -> 100 | J25: =I25*1.75% -> 1.75 | K25: =I25-J25 -> 98.25
A26: 46198 | B26: Thursday | C26: 3.5 | D26: 0 and 10% | E26: 2440 | F26: 1400 | G26: 350 | H26: 0 | I26: =SUM(E26:H26) -> 4190 | J26: =I26*1.75% -> 73.325 | K26: =I26-J26 -> 4116.675
A27: 46199 | B27: Friday | C27: 2.5 | D27: 0 and 10% | E27: 1680 | F27: 700 | G27: 100 | H27: 0 | I27: =SUM(E27:H27) -> 2480 | J27: =I27*1.75% -> 43.4 | K27: =I27-J27 -> 2436.6 | N27: 5.5 | O27: 1.5
A28: 46200 | B28: Saturday | C28: 6.5 | D28: 0 and 10% | E28: 4060 | F28: 0 | G28: 350 | H28: 0 | I28: =SUM(E28:H28) -> 4410 | J28: =I28*1.75% -> 77.175 | K28: =I28-J28 -> 4332.825 | M28: 3200
A29: 46201 | B29: Sunday | C29: 5.5 | D29: 0 and 10% | E29: 3200 | F29: 2400 | G29: 800 | H29: 0 | I29: =SUM(E29:H29) -> 6400 | J29: =I29*1.75% -> 112 | K29: =I29-J29 -> 6288 | M29: 2400
A30: 46202 | B30: Monday | C30: 3 | D30: 0 and 10% | E30: 1660 | F30: 600 | G30: 400 | H30: 0 | I30: =SUM(E30:H30) -> 2660 | J30: =I30*1.75% -> 46.55 | K30: =I30-J30 -> 2613.45 | M30: 400
A31: 46203 | B31: Tuesday | C31: 3 | D31: 0 and 10% | E31: 2000 | F31: 800 | G31: 0 | H31: 0 | I31: =SUM(E31:H31) -> 2800 | J31: =I31*1.75% -> 49 | K31: =I31-J31 -> 2751
A32: Total | C32: =SUM(C1:C31) -> 88 | E32: =SUM(E1:E31) -> 65280 | F32: =SUM(F1:F31) -> 38100 | G32: =SUM(G1:G31) -> 8650 | H32: =SUM(H1:H31) -> 240 | I32: =SUM(I1:I31) -> 112270 | J32: =SUM(J1:J31) -> 1964.725 | K32: =SUM(K1:K31) -> 110305.27
M33: 300
M35: 5 | N35: 3
M36: 1.5

Sheet District
A1: Link | B1: Date | C1: Paid to District | D1: Commissions (₹) | E1: GST on Commission | F1: Net Revenue | G1: TCS | H1: TDS | I1: Final Amount (₹)
B2: 1 - 30 June | C2: 122537 | D2: 7807 | E2: 1405 | F2: =C2-D2-E2 -> 113325 | G2: 613 | H2: 122 | I2: =F2-G2-H2 -> 112590
B4: Total | C4: =SUM(C2:C3) -> 122537 | F4: =SUM(F2:F3) -> 113325 | I4: =SUM(I2:I3) -> 112590

Sheet Social EventsTournaments
A1: Date | B1: Amt | C1: Post Comission | D1: Net Revenue | E1: TDS | F1: Final Amount (₹)
A2: 46193 | B2: 6384 | C2: =B2*5% -> 319.2 | D2: =B2-C2 -> 6064.8 | E2: =B2*2% -> 127.68 | F2: =D2-E2 -> 5937.12
A4: Total | B4: =SUM(B2:B3) -> 6384 | D4: =SUM(D2:D3) -> 6064.8 | F4: =SUM(F2:F3) -> 5937.12

Sheet Academy
A1: Sports | B1: Month | C1: Amt | D1: Payment Gateway | E1: Net Revenue
A2: Pickleball | B2: June | C2: 6500 | D2: =C2*2.5%*1.18 -> 191.75 | E2: =C2-D2 -> 6308.25
