Workbook

Sheet Summary
B2: Date: 1 - 28 Feb
B3: Particulars | C3: Amount
B4: Offline | C4: =SUM(C5,C6,C7,C8) -> 53390
B5: Rentals | C5: ='Offline & RG Community'!G30 -> 17940
B6: F&B | C6: ='Offline & RG Community'!H30 -> 1830
B7: Product Sales | C7: 0
B8: Bookings | C8: ='Offline & RG Community'!E30 -> 33620
B9: Online: Third Party Platform | C9: =SUM(C10:C14) -> 113165
B10: Hudle | C10: =Hudle!C4 -> 70765
B11: Playo | C11: =Playo!C3 -> 5200
B12: District | C12: =District!C4 -> 37200
B13: Khelomore | C13: =Khelomore!E2 -> 0
B14: Zplys | C14: 0
B15: Community | C15: =SUM(C16:C19) -> 103699
B16: Courtly (Organized by RallyGully) | C16: =Courtly!B4 -> 55200
B17: Sportomic (Organized by RallyGully) | C17: =Sportomic!C2 -> 6900
B18: Rallygully Community games | C18: ='Offline & RG Community'!F30 -> 35380
B19: Misfits Community | C19: =Misfits!C2 -> 6219
B20: Memberships | C20: =Memberships!E2 -> 78300
B21: Coaching | C21: =15000+6000 -> 21000
B22: Corporate Events | C22: ='Corporate Events'!C2 -> 3900
B23: Brand Activation | C23: ='Brand Activation'!C5 -> 30000
B24: Other Income | C24: 0
B25: Total Gross Revenue | C25: =sum(C4,C9,C20,C22,C23,C24,C15, C21) -> 403454
B26: Total Net Revenue (Post Commissions) | C26: ='Offline & RG Community'!I30+Hudle!E4+Playo!F3+District!F4+Khelomore!E2+Courtly!D4+Memberships!E2+Coaching!D2+Misfits!E2+Sportomic!C2+'Brand Activation'!E5+'Corporate Events'!C2 -> 383055.96
B27: Total Revenue post GST | C27: =C26/1.18 -> 324623.69
B28: Expenses
B29: Venue Manager + Cleaner | C29: 34100
B30: Marketing, Branding & Community | C30: 15000
B31: Event Expense (Prize money, Setup, Branding) | C31: 70000
B32: Balls | C32: 9500
B33: Total Expenses | C33: =C29+C30+C31+C32 -> 128600
B34: Net Profit (Revenue - Expenses) | C34: =C27-C33 -> 196023.69
B36: School's Profit Share (65%) | C36: =C34*65% -> 127415.4
B37: RallyGully's Profit Share (35%) | C37: =C34*35% -> 68608.293

Sheet Offline & RG Community
A1: Date | B1: Day | C1: Offline booking hours | D1: Discount Given | E1: Booking Revenue | F1: Community Revenue | G1: Paddle Rental | H1: F&B | I1: Total Revenue
A2: 46054 | B2: Sunday | C2: 2 | D2: 10% and 0% | E2: 2980 | F2: 1200 | G2: 600 | H2: 0 | I2: =sum(E2:H2) -> 4780
A3: 46055 | B3: Monday | C3: 1 | D3: 10% and 0% | E3: 1300 | F3: 0 | G3: 500 | H3: 0 | I3: =sum(E3:H3) -> 1800
A4: 46056 | B4: Tuesday | C4: 3 | D4: 10% and 0% | E4: 2900 | F4: 0 | G4: 1300 | H4: 70 | I4: =sum(E4:H4) -> 4270
A5: 46057 | B5: Wednesday | C5: 3.5 | D5: 10% and 0% | E5: 600 | F5: 2100 | G5: 400 | H5: 0 | I5: =sum(E5:H5) -> 3100
A6: 46058 | B6: Thursday | C6: 1 | D6: 10% and 0% | E6: 1200 | F6: 1300 | G6: 600 | H6: 210 | I6: =sum(E6:H6) -> 3310
A7: 46059 | B7: Friday | C7: 0 | D7: 10% and 0% | E7: 0 | F7: 0 | G7: 0 | H7: 500 | I7: =sum(E7:H7) -> 500
A8: 46060 | B8: Saturday | C8: 4 | D8: 10% and 0% | E8: 3000 | F8: 900 | G8: 2300 | H8: 70 | I8: =sum(E8:H8) -> 6270
A9: 46061 | B9: Sunday | C9: 3 | D9: 10% and 0% | E9: 3400 | F9: 0 | G9: 700 | H9: 0 | I9: =sum(E9:H9) -> 4100
A10: 46062 | B10: Monday | C10: 1.5 | D10: 10% and 0% | E10: 300 | F10: 1800 | G10: 850 | H10: 0 | I10: =sum(E10:H10) -> 2950
A11: 46063 | B11: Tuesday | C11: 1 | D11: 10% and 0% | E11: 0 | F11: 900 | G11: 200 | H11: 0 | I11: =sum(E11:H11) -> 1100
A12: 46064 | B12: Wednesday | C12: 0.5 | D12: 10% and 0% | E12: 600 | F12: 900 | G12: 700 | H12: 35 | I12: =sum(E12:H12) -> 2235
A13: 46065 | B13: Thursday | C13: 0 | D13: 10% and 0% | E13: 0 | F13: 0 | G13: 300 | H13: 0 | I13: =sum(E13:H13) -> 300
... A29: 46081 | B29: Saturday | C29: 0 | D29: 10% and 0% | E29: 0 | F29: 6000 | G29: 0 | H29: 0 | I29: =sum(E29:H29) -> 6000
A30: Total | C30: =SUM(C2:C29) -> 51.5 | E30: =SUM(E2:E29) -> 33620 | F30: =SUM(F2:F29) -> 35380 | G30: =SUM(G2:G29) -> 17940 | H30: =SUM(H2:H29) -> 1830 | I30: =SUM(I2:I29) -> 88770

Sheet Hudle
A1: Link | B1: Date | C1: Paid to Hudle | D1: Commisions (Including GST) | E1: Net Revenue | F1: TDS | G1: TCS | H1: Amount
B2: 1 - 23 Feb | C2: 60565 | D2: 8361.6 | E2: =C2-D2 -> 52203.4 | F2: 16.17 | G2: 277.62 | H2: 56669.34
B3: 24 - 28 Feb | C3: 10200 | D3: 1326 | E3: =C3-D3 -> 8874 | F3: 8.64 | G3: 43.22 | H3: 8822.15
B4: Total | C4: =SUM(C2:C3) -> 70765 | E4: =SUM(E2:E3) -> 61077.4 | H4: =SUM(H2:H3) -> 65491.49

Sheet Playo
A1: Link | B1: Date | C1: Paid to Playo (₹) | D1: Commissions (₹) | E1: GST (₹) | F1: Net Revenue | G1: TDS (₹) | H1: TCS (₹) | I1: Final Amount (₹)
B2: 1 - 28 Feb | C2: 5200 | D2: 364 | E2: 65.52 | F2: =C2-D2-E2 -> 4770.48 | G2: 5.2 | H2: 26 | I2: 4739.28
B3: Total | C3: =SUM(C2) -> 5200 | F3: =SUM(F2) -> 4770.48 | I3: =SUM(I2) -> 4739.28

Sheet District
A1: Link | B1: Date | C1: Paid to District | D1: Commissions (₹) | E1: GST on Commission | F1: Net Revenue | G1: TCS | H1: TDS | I1: Final Amount (₹)
B2: 1 - 15 Feb | C2: 22200 | D2: 444 | E2: 79.92 | F2: =C2-D2-E2 -> 21676.08 | G2: 111 | H2: 22.2 | I2: 21542.88
B3: 16 - 28 Feb | C3: 15000 | D3: 300 | E3: 54 | F3: =C3-D3-E3 -> 14646 | G3: 75 | H3: 15 | I3: 14556
B4: Total | C4: =SUM(C2:C3) -> 37200 | F4: =SUM(F2:F3) -> 36322.08 | I4: =SUM(I2:I3) -> 36098.88

Sheet Khelomore
A1: Link | B1: Date | C1: Paid to Khelomore (₹) | D1: Commissions (₹) | E1: Final Amount (₹)
B2: 1 - 28 Feb | C2: 0 | D2: 0 | E2: 0

Sheet Courtly
A1: Date | B1: Paid to Courtly | C1: Post Comission | D1: Net Revenue | E1: TDS | F1: Final Amount (₹)
A2: 46081 | B2: 48000 | C2: =B2*3% -> 1440 | D2: =B2-C2 -> 46560 | E2: =B2*2% -> 960 | F2: =D2-E2 -> 45600
A3: 46081 | B3: 7200 | C3: =B3*10% -> 720 | D3: =B3-C3 -> 6480 | E3: =B3*2% -> 144 | F3: =D3-E3 -> 6336
A4: Total | B4: =SUM(B2:B3) -> 55200 | D4: =SUM(D2:D3) -> 53040 | F4: =SUM(F2:F3) -> 51936

Sheet Misfits
A1: Link | B1: Date | C1: Paid to Misfits (₹) | D1: Comission (20%) | E1: Net Revenue | F1: TDS | G1: Final Amount (₹)
B2: 1 - 28 Feb | C2: 6219 | D2: 1243 | E2: =C2-D2 -> 4976 | F2: 124.38 | G2: =E2-F2 -> 4851.62

Sheet Sportomic
A1: Link | B1: Date | C1: Paid to Sportomic (₹)
B2: 1 - 28 Feb | C2: 6900

Sheet Memberships
A1: Member Name | B1: Sports Type | C1: Membership Type | D1: Start Date | E1: Amount Collected
A2: Offcourt | B2: Pickleball | C2: Grand slam (90) | D2: 46081 | E2: 78300

Sheet Coaching
A1: Sports Type | B1: Coaching Type | C1: Start Date | D1: Amount Collected
A2: Pickleball | B2: Adult | C2: Feb | D2: =15000+6000 -> 21000

Sheet Brand Activation
A1: Date | B1: Brand Name | C1: Amount | D1: Commission | E1: Net Revenue | F1: Type of collab
A2: 46068 | B2: Savikalpa | C2: 15000 | D2: =C2*40% -> 6000 | E2: =C2-D2 -> 9000 | F2: Event Partner
A3: 46080 | B3: Savikalpa | C3: 10000 | D3: 0 | E3: =C3-D3 -> 10000 | F3: Event Partner
A4: 46081 | B4: Smashyn | C4: 5000 | D4: 0 | E4: =C4-D4 -> 5000 | F4: Event Partner
A5: Total | C5: =SUM(C2:C4) -> 30000 | E5: =SUM(E2:E4) -> 24000

Sheet Corporate Events
A1: Date | B1: Brand Name | C1: Amount | D1: Type of collab
A2: 46075 | B2: Courtiside Club | C2: 3900 | D2: Networking Event
