Workbook

Sheet Summary
B2: 1 - 30 Sept
B3: Particulars | C3: Amount
C4: Pickleball
B5: Pay & Play | C5: =sum(C6,C12) -> 43289
B6: Online | C6: =sum(C7:C11) -> 32802
B7: District | C7: =District!C4 -> 32802
B8: Hudle | C8: 0
B9: Playo | C9: 0
B10: Khelomore | C10: 0
B11: Zplys | C11: 0
B12: Offline | C12: =sum(C13:C14) -> 10487
B13: Bookings | C13: ='Offline & RG Community'!D32 -> 10487
B14: Memberships | C14: 0
B15: Community | C15: =sum(C16:C17) -> 1540
B16: Pickup games | C16: ='Offline & RG Community'!E32 -> 1540
B17: Social Events/Tournaments | C17: 0
B18: Academy | C18: 0
B19: B2B | C19: =sum(C20,C21) -> 0
B20: Corporate events | C20: 0
B21: All B2B partnerships | C21: 0
B22: Commerce | C22: =sum(C23:C25) -> 4240
B23: Product rental | C23: ='Offline & RG Community'!F32 -> 4240
B24: Product sales | C24: 0
B25: F&B | C25: 0
B26: Other Income | C26: 0
B27: Total Gross Revenue | C27: =C5+C15+C18+C19+C22+C26 -> 49069
B28: GST | C28: =C27-(C27/1.18) -> 7485.1017
B29: Net Revenue Post GST | C29: =C27-C28 -> 41583.898
B30: Commissions, Payment gateway & Event Expense | C30: ='Offline & RG Community'!H32+District!D4+District!E4 -> 2608.6725
B31: Net Revenue | C31: =C27-C28-C30 -> 38975.226

Sheet Offline & RG Community
A1: Date | B1: Day | C1: Offline booking hours | D1: Booking Revenue | E1: Community Revenue | F1: Paddle Rental | G1: Total Revenue | H1: Payment Gateway | I1: Net Revenue
A2: 46266 | B2: Tuesday | C2: 0 | D2: 0 | E2: 0 | F2: 0 | G2: =sum(D2:F2) -> 0 | H2: =G2*1.75% -> 0 | I2: =G2-H2 -> 0
A3: 46267 | B3: Wednesday | C3: 0 | D3: 0 | E3: 0 | F3: 0 | G3: =sum(D3:F3) -> 0 | H3: =G3*1.75% -> 0 | I3: =G3-H3 -> 0
A4: 46268 | B4: Thursday | C4: 0 | D4: 0 | E4: 0 | F4: 0 | G4: =sum(D4:F4) -> 0 | H4: =G4*1.75% -> 0 | I4: =G4-H4 -> 0
A5: 46269 | B5: Friday | C5: 0 | D5: 0 | E5: 0 | F5: 0 | G5: =sum(D5:F5) -> 0 | H5: =G5*1.75% -> 0 | I5: =G5-H5 -> 0
A6: 46270 | B6: Saturday | C6: 0 | D6: 0 | E6: 0 | F6: 0 | G6: =sum(D6:F6) -> 0 | H6: =G6*1.75% -> 0 | I6: =G6-H6 -> 0
A7: 46271 | B7: Sunday | C7: 0 | D7: 0 | E7: 0 | F7: 50 | G7: =sum(D7:F7) -> 50 | H7: =G7*1.75% -> 0.875 | I7: =G7-H7 -> 49.125
A8: 46272 | B8: Monday | C8: 0 | D8: 0 | E8: 0 | F8: 0 | G8: =sum(D8:F8) -> 0 | H8: =G8*1.75% -> 0 | I8: =G8-H8 -> 0
A9: 46273 | B9: Tuesday | C9: 1 | D9: 638 | E9: 0 | F9: 50 | G9: =sum(D9:F9) -> 688 | H9: =G9*1.75% -> 12.04 | I9: =G9-H9 -> 675.96
A10: 46274 | B10: Wednesday | C10: 0.5 | D10: 319 | E10: 0 | F10: 200 | G10: =sum(D10:F10) -> 519 | H10: =G10*1.75% -> 9.0825 | I10: =G10-H10 -> 509.9175
A11: 46275 | B11: Thursday | C11: 1 | D11: 638 | E11: 0 | F11: 100 | G11: =sum(D11:F11) -> 738 | H11: =G11*1.75% -> 12.915 | I11: =G11-H11 -> 725.085
A12: 46276 | B12: Friday | C12: 0 | D12: 0 | E12: 0 | F12: 0 | G12: =sum(D12:F12) -> 0 | H12: =G12*1.75% -> 0 | I12: =G12-H12 -> 0
A13: 46277 | B13: Saturday | C13: 1.5 | D13: 957 | E13: 0 | F13: 650 | G13: =sum(D13:F13) -> 1607 | H13: =G13*1.75% -> 28.1225 | I13: =G13-H13 -> 1578.8775
... A31: 46295 | B31: Wednesday | C31: 1 | D31: 638 | E31: 0 | F31: 0 | G31: =sum(D31:F31) -> 638 | H31: =G31*1.75% -> 11.165 | I31: =G31-H31 -> 626.835
A32: Total | D32: =SUM(D1:D31) -> 10487 | E32: =SUM(E1:E31) -> 1540 | F32: =SUM(F1:F31) -> 4240 | G32: =SUM(G1:G31) -> 16267 | H32: =SUM(H1:H31) -> 284.6725 | I32: =SUM(I1:I31) -> 15982.327

Sheet District
A1: Link | B1: Date | C1: Paid to District | D1: Commissions (₹) | E1: GST on Commission | F1: Net Revenue | G1: TCS | H1: TDS | I1: Final Amount (₹)
B2: 1 - 30 Sept | C2: 32802 | D2: 1970 | E2: 354 | F2: =C2-D2-E2 -> 30478 | G2: 121 | H2: 24 | I2: =F2-G2-H2 -> 30333
B4: Total | C4: =SUM(C2:C3) -> 32802 | D4: =SUM(D2:D3) -> 1970 | E4: =SUM(E2:E3) -> 354 | F4: =SUM(F2:F3) -> 30478 | I4: =SUM(I2:I3) -> 30333
