Workbook

Sheet Summary
B2: Date: 1 - 31 Jan
B3: Particulars | C3: Amount
B4: Offline | C4: =SUM(C5,C6,C7,C8) -> 30252
B5: Rentals | C5: ='Offline & RG Community'!G26 -> 3700
B6: F&B | C6: 0
B7: Product Sales | C7: 0
B8: Bookings | C8: ='Offline & RG Community'!E26 -> 26552
B9: Online: Third Party Platform | C9: =SUM(C10:C14) -> 48336
B10: Hudle | C10: =Hudle!C6 -> 40056
B11: Playo | C11: =Playo!C4 -> 2880
B12: District | C12: =District!C5 -> 5400
B13: Khelomore | C13: 0
B14: Zplys | C14: 0
B15: Community | C15: =SUM(C17,C16, C18,C19) -> 0
B16: Courtly (Organized by RallyGully) | C16: 0
B17: Sportomic (Organized by RallyGully) | C17: 0
B18: Rallygully Community games | C18: ='Offline & RG Community'!F26 -> 0
B19: Misfits Community | C19: 0
B20: Memberships | C20: 0
B21: Coaching | C21: 0
B22: Corporate Events | C22: 0
B23: Brand Activation | C23: 0
B24: Other Income | C24: 0
B25: Total Gross Revenue | C25: =sum(C4,C9,C20,C22,C23,C24,C15, C21) -> 78588
B26: Total Net Revenue (Post Commissions) | C26: ='Offline & RG Community'!H26 + Hudle!E6+ Playo!F4 + District!F5 -> 72955.92
B27: Total Revenue post GST | C27: =C26/1.18 -> 61827.051
B29: Expenses
B30: VM Salary | C30: 20000
B31: Support Staff | C31: 10000
B32: Marketing, Branding & Community | C32: 10000
B33: Balls | C33: 4500
B35: Net Profit | C35: =C27-(sum(C30:C33)) -> 17327.051

Sheet Offline & RG Community
A1: Date | B1: Day | C1: Offline booking hours | D1: Discount Given | E1: Booking Revenue | F1: Community Revenue | G1: Paddle Rental | H1: Total Revenue
A2: 46030 | B2: Thursday | C2: 0 | D2: 0.2 | E2: 0 | F2: 0 | G2: 0 | H2: =SUM(E2:G2) -> 0
A3: 46031 | B3: Friday | C3: 1.5 | D3: 0.2 | E3: 1560 | F3: 0 | G3: 50 | H3: =SUM(E3:G3) -> 1610
A4: 46032 | B4: Saturday | C4: 4 | D4: 0.2 | E4: 3840 | F4: 0 | G4: 150 | H4: =SUM(E4:G4) -> 3990
A5: 46033 | B5: Sunday | C5: 1.5 | D5: 0.2 | E5: 1500 | F5: 0 | G5: 100 | H5: =SUM(E5:G5) -> 1600
A6: 46034 | B6: Monday | C6: 3 | D6: 0.2 | E6: 2860 | F6: 0 | G6: 150 | H6: =SUM(E6:G6) -> 3010
A7: 46035 | B7: Tuesday | C7: 0 | D7: 0.2 | E7: 0 | F7: 0 | G7: 0 | H7: =SUM(E7:G7) -> 0
A8: 46036 | B8: Wednesday | C8: 0.5 | D8: 0.2 | E8: 500 | F8: 0 | G8: 0 | H8: =SUM(E8:G8) -> 500
A9: 46037 | B9: Thursday | C9: 0 | D9: 0.2 | E9: 0 | F9: 0 | G9: 0 | H9: =SUM(E9:G9) -> 0
A10: 46038 | B10: Friday | C10: 1 | D10: 0.2 | E10: 960 | F10: 0 | G10: 0 | H10: =SUM(E10:G10) -> 960
A11: 46039 | B11: Saturday | C11: 2 | D11: 0.2 | E11: 1920 | F11: 0 | G11: 100 | H11: =SUM(E11:G11) -> 2020
A12: 46040 | B12: Sunday | C12: 2.5 | D12: 0.2 | E12: 2500 | F12: 0 | G12: 450 | H12: =SUM(E12:G12) -> 2950
A13: 46041 | B13: Monday | C13: 2 | D13: 0.2 | E13: 1920 | F13: 0 | G13: 100 | H13: =SUM(E13:G13) -> 2020
... A25: 46053 | B25: Saturday | C25: 0 | D25: 0.2 | E25: 0 | F25: 0 | G25: 300 | H25: =SUM(E25:G25) -> 300
A26: Total | C26: =SUM(C2:C25) -> 27.5 | E26: =SUM(E2:E25) -> 26552 | F26: =SUM(F2:F25) -> 0 | G26: =SUM(G2:G25) -> 3700 | H26: =SUM(H2:H25) -> 30252

Sheet Hudle
A1: Link | B1: Date | C1: Paid to Hudle | D1: Commisions (Including GST) | E1: Net Revenue | F1: TDS | G1: TCS | H1: Amount
B2: 6 - 12 Jan | C2: 6000 | D2: 780 | E2: =C2 - D2 -> 5220 | F2: 5.08 | G2: 25.42 | H2: 5189.5
B3: 13 - 19 Jan | C3: 5760 | D3: 748.8 | E3: =C3 - D3 -> 5011.2 | F3: 4.88 | G3: 24.4 | H3: 4981.8
B4: 19 - 26 Jan | C4: 14496 | D4: 1884.48 | E4: =C4 - D4 -> 12611.52 | F4: 12.28 | G4: 61.42 | H4: 12537.83
B5: 26 - 31 Jan | C5: 13800 | D5: 1794 | E5: =C5 - D5 -> 12006 | F5: 11.69 | G5: 58.47 | H5: 11935.85
C6: =SUM(C2:C5) -> 40056 | E6: =SUM(E2:E5) -> 34848.72 | H6: =SUM(H2:H5) -> 34644.98

Sheet Playo
A1: Link | B1: Date | C1: Paid to Playo (₹) | D1: Commissions (₹) | E1: GST (₹) | F1: Net Revenue | G1: TDS (₹) | H1: TCS (₹) | I1: Final Amount (₹)
B2: 1 - 25 Jan | C2: 960 | D2: 84 | E2: 15.12 | F2: =C2 -D2-E2 -> 860.88 | G2: 0.96 | H2: 4.8 | I2: 855.12
B3: 26 - 31 Jan | C3: 1920 | D3: 168 | E3: 30.24 | F3: =C3 -D3-E3 -> 1721.76 | G3: 1.92 | H3: 9.6 | I3: 1710.24
C4: =SUM(C2,C3) -> 2880 | F4: =SUM(F2,F3) -> 2582.64 | I4: =SUM(I2,I3) -> 2565.36

Sheet District
A1: Link | B1: Date | C1: Paid to District | D1: Commissions (₹) | E1: GST on Commission | F1: Net Revenue | G1: TCS | H1: TDS | I1: Final Amount (₹)
B2: 1 - 12 Jan | C2: 3000 | D2: =C2*2% -> 60 | E2: =D2*18% -> 10.8 | F2: =C2-D2-E2 -> 2929.2 | G2: =C2*0.5% -> 15 | H2: =D2*0.1% -> 0.06 | I2: =F2-G2-H2 -> 2914.14
B3: 13 - 19 Jan | C3: 1800 | D3: =C3*2% -> 36 | E3: =D3*18% -> 6.48 | F3: =C3-D3-E3 -> 1757.52 | G3: =C3*0.5% -> 9 | H3: =D3*0.1% -> 0.036 | I3: =F3-G3-H3 -> 1748.484
B4: 20 - 31 Jan | C4: 600 | D4: =C4*2% -> 12 | E4: =D4*18% -> 2.16 | F4: =C4-D4-E4 -> 585.84 | G4: =C4*0.5% -> 3 | H4: =D4*0.1% -> 0.012 | I4: =F4-G4-H4 -> 582.828
B5: Total | C5: =SUM(C2:C4) -> 5400 | F5: =SUM(F2:F4) -> 5272.56 | I5: =SUM(I2:I4) -> 5245.452

Sheet Khelomore
A1: Link | B1: Date | C1: Paid to Khelomore (₹) | D1: Commissions (₹) | E1: Final Amount (₹)
B2: 1 - 31 Jan | C2: 0
C4: =SUM(C2:C3) -> 0 | D4: =SUM(D2:D3) -> 0 | E4: =SUM(E2:E3) -> 0
