Workbook

Sheet Summary
B2: Date: 1 - 31 Jan
B3: Particulars | C3: Amount
B4: Offline | C4: =SUM(C5,C6,C7,C8) -> 31691
B5: Rentals | C5: ='Offline & RG Community'!G33 -> 10650
B6: F&B | C6: ='Offline & RG Community'!H33 -> 205
B7: Product Sales | C7: 0
B8: Bookings | C8: ='Offline & RG Community'!E33 -> 20836
B9: Online: Third Party Platform | C9: =SUM(C10:C14) -> 96047
B10: Hudle | C10: =Hudle!C7 -> 66479
B11: Playo | C11: =Playo!C6 -> 3168
B12: District | C12: =District!C5 -> 26400
B13: Khelomore | C13: =Khelomore!C4 -> 0
B14: Zplys | C14: 0
B15: Community | C15: =SUM(C17,C18,C19) -> 43728.9
B16: Courtly (Organized by RallyGully) | C16: 0
B17: Sportomic (Organized by RallyGully) | C17: 0
B18: Rallygully Community games | C18: ='Offline & RG Community'!F33 -> 43728.9
B19: Misfits Community | C19: 0
B20: Memberships | C20: =Memberships!E2 -> 27000
B21: Coaching | C21: =Coaching!D2 -> 54000
B22: Corporate Events | C22: ='Corporate Events'!C2 -> 3000
B23: Brand Activation | C23: ='Brand Activation'!C6 -> 24100
B24: Other Income | C24: 0
B25: Total Gross Revenue | C25: =sum(C4,C9,C20,C22,C23,C24,C15, C21) -> 279566.9
B26: Total Net Revenue (Post Commissions) | C26: ='Offline & RG Community'!I33+Hudle!E7+Playo!F6+District!F5+Memberships!E2+Coaching!D2+'Brand Activation'!E6+'Corporate Events'!C2 -> 264290.58
B27: Total Revenue post GST | C27: =C26/1.18 -> 223975.07
B28: Expenses
B29: Venue Manager + Cleaner | C29: 39100
B30: Marketing, Branding & Community | C30: 15000
B31: Total Expenses | C31: =C29+C30 -> 54100
B32: Net Profit (Revenue - Expenses) | C32: =C27-C31 -> 169875.07
B34: School's Profit Share (65%) | C34: =C32*65% -> 110418.79
B35: RallyGully's Profit Share (35%) | C35: =C32*35% -> 59456.274

Sheet Offline & RG Community
A1: Date | B1: Day | C1: Offline booking hours | D1: Discount Given | E1: Booking Revenue | F1: Community Revenue | G1: Paddle Rental | H1: F&B | I1: Total Revenue
A2: 46023 | B2: Thursday | C2: 0 | D2: 0% and 10% | E2: 0 | F2: 0 | G2: 300 | H2: 0 | I2: =SUM(E2:H2) -> 300
A3: 46024 | B3: Friday | C3: 0.5 | D3: 0% and 10% | E3: 600 | F3: 650 | G3: 200 | H3: 0 | I3: =SUM(E3:H3) -> 1450
A4: 46025 | B4: Saturday | C4: 1 | D4: 0% and 10% | E4: 0 | F4: 1200 | G4: 0 | H4: 100 | I4: =SUM(E4:H4) -> 1300
A5: 46026 | B5: Sunday | C5: 0.5 | D5: 0% and 10% | E5: 600 | F5: 0 | G5: 0 | H5: 70 | I5: =SUM(E5:H5) -> 670
A6: 46027 | B6: Monday | C6: 2 | D6: 0% and 10% | E6: 0 | F6: 2900 | G6: 0 | H6: 0 | I6: =SUM(E6:H6) -> 2900
A7: 46028 | B7: Tuesday | C7: 2 | D7: 0% and 10% | E7: 0 | F7: 1850 | G7: 100 | H7: 0 | I7: =SUM(E7:H7) -> 1950
A8: 46029 | B8: Wednesday | C8: 3 | D8: 0% and 10% | E8: 1800 | F8: 2200 | G8: 100 | H8: 35 | I8: =SUM(E8:H8) -> 4135
A9: 46030 | B9: Thursday | C9: 1.5 | D9: 0% and 10% | E9: 2100 | F9: 0 | G9: 500 | H9: 0 | I9: =SUM(E9:H9) -> 2600
A10: 46031 | B10: Friday | C10: 2 | D10: 0% and 10% | E10: 0 | F10: 2400 | G10: 800 | H10: 0 | I10: =SUM(E10:H10) -> 3200
A11: 46032 | B11: Saturday | C11: 2 | D11: 0% and 10% | E11: 0 | F11: 2850 | G11: 200 | H11: 0 | I11: =SUM(E11:H11) -> 3050
A12: 46033 | B12: Sunday | C12: 1.5 | D12: 0% and 10% | E12: 1800 | F12: 0 | G12: 500 | H12: 0 | I12: =SUM(E12:H12) -> 2300
A13: 46034 | B13: Monday | C13: 0 | D13: 0% and 10% | E13: 0 | F13: 2500 | G13: 100 | H13: 0 | I13: =SUM(E13:H13) -> 2600
... A32: 46053 | B32: Saturday | C32: 1.5 | D32: 0% and 10% | E32: 1800 | F32: 7228.9 | G32: 700 | H32: 0 | I32: =SUM(E32:H32) -> 9728.9
A33: Total | C33: =SUM(C2:C32) -> 42 | E33: =SUM(E2:E32) -> 20836 | F33: =SUM(F2:F32) -> 43728.9 | G33: =SUM(G2:G32) -> 10650 | H33: =SUM(H2:H32) -> 205 | I33: =SUM(I2:I32) -> 75419.9

Sheet Hudle
A1: Link | B1: Date | C1: Paid to Hudle | D1: Commisions (Including GST) | E1: Net Revenue | F1: TDS | G1: TCS | H1: Amount
B2: 1 - 5 Jan | C2: 4800 | D2: 624 | E2: =C2 - D2 -> 4176 | F2: 4.06 | G2: 20.33 | H2: 4151.6
B3: 6 - 12 Jan | C3: 14780 | D3: 1921.4 | E3: =C3 - D3 -> 12858.6 | F3: 12.52 | G3: 62.62 | H3: 12783.47
B4: 13 - 19 Jan | C4: 20415 | D4: 2667.6 | E4: =C4 - D4 -> 17747.4 | F4: 17.39 | G4: 86.94 | H4: 17748.09
B5: 20 - 26 Jan | C5: 21684 | D5: 2818.92 | E5: =C5 - D5 -> 18865.08 | F5: 18.37 | G5: 91.88 | H5: 18754.82
B6: 27 - 31 Jan | C6: 4800 | D6: 624 | E6: =C6 - D6 -> 4176 | F6: 4.06 | G6: 20.33 | H6: 4151.6
C7: =SUM(C2:C6) -> 66479 | E7: =SUM(E2:E6) -> 57823.08 | H7: =SUM(H2:H6) -> 57589.58

Sheet Playo
A1: Link | B1: Date | C1: Paid to Playo (₹) | D1: Commissions (₹) | E1: GST (₹) | F1: Net Revenue | G1: TDS (₹) | H1: TCS (₹) | I1: Final Amount (₹)
B2: 1 - 19 Jan | C2: 1080 | D2: 84 | E2: 15.12 | F2: =C2 -D2-E2 -> 980.88 | G2: 1.08 | H2: 5.4 | I2: 974.4
B3: 20 - 25 Jan | C3: 2088 | D3: 168 | E3: 30.24 | F3: =C3 -D3-E3 -> 1889.76 | G3: 2.09 | H3: 10.44 | I3: 1877.23
C6: =SUM(C2:C4) -> 3168 | F6: =SUM(F2:F4) -> 2870.64 | I6: =SUM(I2:I4) -> 2851.63

Sheet District
A1: Link | B1: Date | C1: Paid to District | D1: Commissions (₹) | E1: GST on Commission | F1: Net Revenue | G1: TCS | H1: TDS | I1: Final Amount (₹)
B2: 1 - 12 Jan | C2: 15600 | D2: =C2*2% -> 312 | E2: =D2*18% -> 56.16 | F2: =C2-D2-E2 -> 15231.84 | G2: =C2*0.5% -> 78 | H2: =D2*0.1% -> 0.312 | I2: =F2-G2-H2 -> 15153.528
B3: 13 - 19 Jan | C3: 6000 | D3: =C3*2% -> 120 | E3: =D3*18% -> 21.6 | F3: =C3-D3-E3 -> 5858.4 | G3: =C3*0.5% -> 30 | H3: =D3*0.1% -> 0.12 | I3: =F3-G3-H3 -> 5828.28
B4: 20 - 31 Jan | C4: 4800 | D4: =C4*2% -> 96 | E4: =D4*18% -> 17.28 | F4: =C4-D4-E4 -> 4686.72 | G4: =C4*0.5% -> 24 | H4: =D4*0.1% -> 0.096 | I4: =F4-G4-H4 -> 4662.624
B5: Total | C5: =SUM(C2:C4) -> 26400 | F5: =SUM(F2:F4) -> 25776.96 | I5: =SUM(I2:I4) -> 25644.432

Sheet Khelomore
A1: Link | B1: Date | C1: Paid to Khelomore (₹) | D1: Commissions (₹) | E1: Final Amount (₹)
B2: 1 - 31 Jan | C2: 0
C4: =SUM(C2:C3) -> 0 | D4: =SUM(D2:D3) -> 0 | E4: =SUM(E2:E3) -> 0

Sheet Misfits
A1: Link | B1: Date | C1: Paid to Misfits (₹) | D1: Post Comission (20%) | E1: TDS | F1: Final Amount (₹)
B2: 1 - 31 Jan | C2: 0

Sheet Sportomic
A1: Link | B1: Date | C1: Paid to Sportomic (₹)
B2: 1 - 31 Jan | C2: 0

Sheet Memberships
A1: Member Name | B1: Sports Type | C1: Membership Type | D1: Start Date | E1: Amount Collected
A2: Offcourt | B2: Pickleball | C2: Pro Pack (30) | D2: 46052 | E2: 27000

Sheet Coaching
A1: Sports Type | B1: Coaching Type | C1: Start Date | D1: Amount Collected
A2: Pickleball | B2: Kids & Adult | C2: Jan | D2: 54000

Sheet Brand Activation
A1: Date | B1: Brand Name | C1: Amount | D1: Commission | E1: Net Revenue | F1: Type of collab
A2: 46040 | B2: Savikalpa | C2: 15000 | D2: =C2*30% -> 4500 | E2: =C2-D2 -> 10500 | F2: Event Partner
A3: 46040 | B3: Peeyo | C3: 4000 | D3: =C3*30% -> 1200 | E3: =C3-D3 -> 2800 | F3: Event Partner
A4: 46049 | B4: House of Riya | C4: 3600 | D4: 0 | E4: =C4-D4 -> 3600 | F4: Event Partner
A5: 46049 | B5: Playo | C5: 1500 | D5: 0 | E5: =C5-D5 -> 1500 | F5: Event Partner
A6: Total | C6: =SUM(C2:C5) -> 24100 | E6: =SUM(E2:E5) -> 18400

Sheet Corporate Events
A1: Date | B1: Brand Name | C1: Amount | D1: Type of collab
A2: 46039 | B2: Courtiside Club | C2: 3000 | D2: Networking Event
