Workbook

Sheet Summary
B2: Date: 12th - 31st Dec
B3: Particulars | C3: Amount
B4: Offline | C4: =SUM(C5,C6,C7,C8) -> 10137
B5: Rentals | C5: ='Offline & RG Community'!G21 -> 3850
B6: F&B | C6: 0
B7: Product Sales | C7: 0
B8: Bookings | C8: ='Offline & RG Community'!E21 -> 6287
B9: Online: Third Party Platform | C9: =SUM(C10:C13) -> 7600
B10: Hudle | C10: =Hudle!C6 -> 3100
B11: Playo | C11: =Playo!C3 -> 3600
B12: District | C12: =District!C4 -> 900
B13: Khelomore | C13: 0
B14: Community | C14: =SUM(C16,C15, C17,C18) -> 3900
B15: Courtly (Organized by RallyGully) | C15: 0
B16: Sportomic (Organized by RallyGully) | C16: =Sportomic!C6 -> 3100
B17: Rallygully Community games | C17: ='Offline & RG Community'!F21 -> 800
B18: Misfits Community | C18: =Misfits!C6 -> 0
B19: Memberships | C19: 0
B20: Corporate Events | C20: 0
B21: Brand Activation | C21: 0
B22: Other Income | C22: 0
B23: Total Gross Revenue | C23: =sum(C4,C9,C14,C19,C20,C21,C22) -> 21637
B24: Total Net Revenue (Post Commissions) | C24: ='Offline & RG Community'!H21 +Hudle!E6 +District!F4 +Sportomic!C6 + Playo!F3 -> 20915.44
B25: Total Revenue post GST | C25: =C24/1.18 -> 17724.949
B26: Investor's Share (40%) | C26: =C25*40% -> 7089.9797

Sheet Offline & RG Community
A1: Date | B1: Day | C1: Offline booking hours | D1: Discount Given | E1: Booking Revenue | F1: Community Revenue | G1: Paddle Rental | H1: Total Revenue
A2: 46004 | B2: Saturday | C2: 1 | D2: 0.5 | E2: 450 | F2: 0 | G2: 300 | H2: =sum(E2:G2) -> 750
A3: 46005 | B3: Sunday | C3: 4 | D3: 0.5 | E3: 1800 | F3: 0 | G3: 0 | H3: =sum(E3:G3) -> 1800
A4: 46006 | B4: Monday | C4: 0 | D4: 0.5 | E4: 0 | F4: 0 | G4: 0 | H4: =sum(E4:G4) -> 0
A5: 46007 | B5: Tuesday | C5: 0 | D5: 0.5 | E5: 0 | F5: 0 | G5: 0 | H5: =sum(E5:G5) -> 0
A6: 46008 | B6: Wednesday | C6: 0 | D6: 0.5 | E6: 0 | F6: 0 | G6: 0 | H6: =sum(E6:G6) -> 0
A7: 46009 | B7: Thursday | C7: 0 | D7: 0.5 | E7: 0 | F7: 0 | G7: 0 | H7: =sum(E7:G7) -> 0
A8: 46010 | B8: Friday | C8: 0 | D8: 0.5 | E8: 0 | F8: 0 | G8: 0 | H8: =sum(E8:G8) -> 0
A9: 46011 | B9: Saturday | C9: 0 | D9: 0.5 | E9: 0 | F9: 0 | G9: 0 | H9: =sum(E9:G9) -> 0
A10: 46012 | B10: Sunday | C10: 0 | D10: 0.5 | E10: 0 | F10: 0 | G10: 100 | H10: =sum(E10:G10) -> 100
A11: 46013 | B11: Monday | C11: 0 | D11: 0.5 | E11: 0 | F11: 0 | G11: 0 | H11: =sum(E11:G11) -> 0
A12: 46014 | B12: Tuesday | C12: 2 | D12: 0.5 | E12: 2012 | F12: 450 | G12: 400 | H12: =sum(E12:G12) -> 2862
A13: 46015 | B13: Wednesday | C13: 0 | D13: 0.5 | E13: 0 | F13: 0 | G13: 600 | H13: =sum(E13:G13) -> 600
... A20: 46022 | B20: Wednesday | C20: 0 | D20: 0.5 | E20: 0 | F20: 0 | G20: 0 | H20: =sum(E20:G20) -> 0
A21: Total | C21: =SUM(C2:C20) -> 11.5 | E21: =SUM(E2:E20) -> 6287 | F21: =SUM(F2:F20) -> 800 | G21: =SUM(G2:G20) -> 3850 | H21: =SUM(H2:H20) -> 10937

Sheet Hudle
A1: Link | B1: Date | C1: Paid to Hudle | D1: Commisions (Including GST) | E1: Net Revenue | F1: TDS | G1: TCS | H1: Amount
B2: 1 - 16 Dec | C2: 450 | D2: 58.5 | E2: =C2 - D2 -> 391.5 | F2: 0.3814 | G2: 1.9068 | H2: 389.21
B3: 16 - 23 Dec | C3: 450 | D3: 58.5 | E3: =C3 - D3 -> 391.5 | F3: 0.3814 | G3: 1.9068 | H3: 389.21
B4: 23 - 31 Dec | C4: 2200 | D4: 286 | E4: =C4 - D4 -> 1914 | F4: 1.86 | G4: 9.32 | H4: 1902.81
C6: =SUM(C2:C5) -> 3100 | D6: =SUM(D2:D4) -> 403 | E6: =SUM(E2:E5) -> 2697 | H6: =SUM(H2:H5) -> 2681.23

Sheet Playo
A1: Link | B1: Date | C1: Paid to Playo (₹) | D1: Commissions (₹) | E1: GST (₹) | F1: Net Revenue | G1: TDS (₹) | H1: TCS (₹) | I1: Final Amount (₹)
B2: 1 - 31 Dec | C2: 3600 | D2: 252 | E2: 45.36 | F2: =C2 -D2-E2 -> 3302.64 | G2: 3.6 | H2: 18 | I2: 3281.04
C3: =SUM(C2) -> 3600 | F3: =SUM(F2) -> 3302.64 | I3: =SUM(I2) -> 3281.04

Sheet District
A1: Link | B1: Date | C1: Paid to District | D1: Commissions (₹) | E1: GST on Commission | F1: Net Revenue | G1: TCS | H1: TDS | I1: Final Amount (₹)
B2: 1 - 31 Dec | C2: 900 | D2: 18 | E2: 3.2 | F2: =C2 -D2-E2 -> 878.8 | G2: 0.9 | H2: 4.5 | I2: 877.36
B4: Total | C4: =SUM(C2) -> 900 | F4: =SUM(F2) -> 878.8 | I4: =SUM(I2) -> 877.36

Sheet Khelomore
A1: Link | B1: Date | C1: Paid to Khelomore (₹) | D1: Commissions (₹) | E1: Final Amount (₹)
B2: 1 - 31 Dec | C2: 0
C4: =SUM(C2:C3) -> 0 | D4: =SUM(D2:D3) -> 0 | E4: =SUM(E2:E3) -> 0

Sheet Misfits
A1: Link | B1: Date | C1: Paid to Misfits (₹) | D1: Post Comission (20%) | E1: TDS | F1: Final Amount (₹)
B2: 1 - 31st Dec | C2: 0
C6: =SUM(C2) -> 0

Sheet Sportomic
A1: Link | B1: Date | C1: Paid to Sportomic (₹)
B2: 1 - 31st Dec | C2: 3100
C6: =SUM(C2) -> 3100
