Workbook

Sheet Summary
B2: 1 - 31 Aug
B3: Particulars | C3: Amount
C4: Pickleball
B5: Pay & Play | C5: =sum(C6,C12) -> 41255
B6: Online | C6: =sum(C7:C11) -> 32924
B7: District | C7: =District!C3 -> 32924
B8: Hudle | C8: 0
B9: Playo | C9: 0
B10: Khelomore | C10: 0
B11: Zplys | C11: 0
B12: Offline | C12: =sum(C13:C14) -> 8331
B13: Bookings | C13: ='Offline & RG Community'!D33 -> 8331
B14: Memberships | C14: 0
B15: Community | C15: =sum(C16:C18) -> 1476
B16: Pickup games | C16: ='Offline & RG Community'!E33 -> 1476
B17: Social Events/Tournaments | C17: 0
B18: Community Partnership | C18: 0
B19: Academy | C19: =Academy!E2 -> 18000 | D19: (Note for CA Team: Please note that RallyGully hasn't received the 18000 rental for basketball rental service provided) - GST payment would have to be made by Drive & Kick Team
B20: Events & Partnership | C20: =sum(C21,C22) -> 0
B21: Corporate events | C21: 0
B22: All B2B partnerships | C22: 0
B23: Commerce | C23: =sum(C24:C26) -> 3500
B24: Product rental | C24: ='Offline & RG Community'!F33 -> 3500
B25: Product sales | C25: 0
B26: F&B | C26: 0
B27: Other Income | C27: 0
B28: Total Gross Revenue | C28: =C5+C15+C19+C20+C23+C27 -> 64231
B29: GST (B) | C29: =C28-(C28/1.18) -> 9797.9492 | D29: =(C28-18000)*18% -> 8321.58
B30: Commissions, Payment gateway & Event Expense(C) | C30: ='Offline & RG Community'!I33+District!D2+District!E2 -> 2950.8725 | D30: 2951
B31: Net Revenue (A-B-C) | C31: =C28-C29-C30 -> 51482.178 | D31: =C28-D29-D30 -> 52958.42
B32: Drive & Kick Share (Final share after incorporting 18k already received by Drive Kick) | C32: =C31-C19 -> 33482.178 | D32: =D31*70% -> 37070.894
B33: RallyGully's Share (30%) | C33: =C31*30% -> 15444.654

Sheet Offline & RG Community
A1: Date | B1: Day | C1: Offline booking hours | D1: Booking Revenue | E1: Community Revenue | F1: Paddle Rental | G1: F&B | H1: Total Revenue | I1: Payment Gateway | J1: Net Revenue
A2: 46235 | B2: Saturday | C2: 0.5 | D2: 300 | E2: 0 | F2: 100 | G2: 0 | H2: =sum(D2:G2) -> 400 | I2: =H2*1.75% -> 7 | J2: =H2-I2 -> 393
A3: 46236 | B3: Sunday | C3: 0 | D3: 0 | E3: 396 | F3: 0 | G3: 0 | H3: =sum(D3:G3) -> 396 | I3: =H3*1.75% -> 6.93 | J3: =H3-I3 -> 389.07
A4: 46237 | B4: Monday | C4: 0 | D4: 0 | E4: 0 | F4: 0 | G4: 0 | H4: =sum(D4:G4) -> 0 | I4: =H4*1.75% -> 0 | J4: =H4-I4 -> 0
A5: 46238 | B5: Tuesday | C5: 0 | D5: 0 | E5: 0 | F5: 0 | G5: 0 | H5: =sum(D5:G5) -> 0 | I5: =H5*1.75% -> 0 | J5: =H5-I5 -> 0
A6: 46239 | B6: Wednesday | C6: 0 | D6: 0 | E6: 0 | F6: 0 | G6: 0 | H6: =sum(D6:G6) -> 0 | I6: =H6*1.75% -> 0 | J6: =H6-I6 -> 0
A7: 46240 | B7: Thursday | C7: 0 | D7: 0 | E7: 0 | F7: 0 | G7: 0 | H7: =sum(D7:G7) -> 0 | I7: =H7*1.75% -> 0 | J7: =H7-I7 -> 0
A8: 46241 | B8: Friday | C8: 0 | D8: 0 | E8: 0 | F8: 0 | G8: 0 | H8: =sum(D8:G8) -> 0 | I8: =H8*1.75% -> 0 | J8: =H8-I8 -> 0
A9: 46242 | B9: Saturday | C9: 1.5 | D9: 1047 | E9: 600 | F9: 0 | G9: 0 | H9: =sum(D9:G9) -> 1647 | I9: =H9*1.75% -> 28.8225 | J9: =H9-I9 -> 1618.1775
A10: 46243 | B10: Sunday | C10: 2 | D10: 1400 | E10: 0 | F10: 550 | G10: 0 | H10: =sum(D10:G10) -> 1950 | I10: =H10*1.75% -> 34.125 | J10: =H10-I10 -> 1915.875
A11: 46244 | B11: Monday | C11: 0 | D11: 0 | E11: 0 | F11: 0 | G11: 0 | H11: =sum(D11:G11) -> 0 | I11: =H11*1.75% -> 0 | J11: =H11-I11 -> 0
A12: 46245 | B12: Tuesday | C12: 1.5 | D12: 1047 | E12: 0 | F12: 275 | G12: 0 | H12: =sum(D12:G12) -> 1322 | I12: =H12*1.75% -> 23.135 | J12: =H12-I12 -> 1298.865
A13: 46246 | B13: Wednesday | C13: 0 | D13: 0 | E13: 0 | F13: 0 | G13: 0 | H13: =sum(D13:G13) -> 0 | I13: =H13*1.75% -> 0 | J13: =H13-I13 -> 0
... A32: 46265 | B32: Monday | C32: 0 | D32: 0 | E32: 0 | F32: 0 | G32: 0 | H32: =sum(D32:G32) -> 0 | I32: =H32*1.75% -> 0 | J32: =H32-I32 -> 0
A33: Total | C33: =SUM(C2:C32) -> 13 | D33: =SUM(D2:D32) -> 8331 | E33: =SUM(E2:E32) -> 1476 | F33: =SUM(F2:F32) -> 3500 | G33: =SUM(G2:G32) -> 0 | H33: =SUM(H2:H32) -> 13307 | I33: =SUM(I2:I32) -> 232.8725 | J33: =SUM(J1:J32) -> 13074.128

Sheet District
A1: Link | B1: Date | C1: Paid to District | D1: Commissions (₹) | E1: GST on Commission | F1: Net Revenue | G1: TCS | H1: TDS | I1: Final Amount (₹)
B2: 1 - 31 Aug | C2: 32924 | D2: 2304 | E2: 414 | F2: =C2-D2-E2 -> 30206 | G2: 164 | H2: 33 | I2: =F2-G2-H2 -> 30009
A3: Total | C3: =SUM(C2) -> 32924 | D3: =SUM(D2) -> 2304 | E3: =SUM(E2) -> 414 | F3: =SUM(F2) -> 30206 | I3: =SUM(I2) -> 30009

Sheet Academy
A1: Month | B1: Coaching | C1: Sports Type | D1: Type | E1: Amount Collected
A2: Aug | B2: Basketball Coaching | C2: Basketball | D2: 3 days in week | E2: 18000
