Workbook

Sheet Summary
B2: Date: 1 - 28 Feb
B3: Particulars | C3: Amount
B4: Offline | C4: =SUM(C5,C6,C7,C8) -> 16510
B5: Rentals | C5: ='Offline & RG Community'!G30 -> 4600
B6: F&B | C6: 0
B7: Product Sales | C7: 0
B8: Bookings | C8: ='Offline & RG Community'!E30 -> 11910
B9: Online: Third Party Platform | C9: =SUM(C10:C14) -> 63000
B10: Hudle | C10: =Hudle!C6 -> 48600
B11: Playo | C11: 0
B12: District | C12: =District!C4 -> 14400
B13: Khelomore | C13: 0
B14: Zplys | C14: 0
B15: Community | C15: =SUM(C17,C16,C18,C19) -> 9460
B16: Courtly (Organized by RallyGully) | C16: 0
B17: Sportomic (Organized by RallyGully) | C17: 0
B18: Rallygully Community games | C18: 0
B19: Misfits Community | C19: =Misfits!C2 -> 9460
B20: Memberships | C20: 0
B21: Coaching | C21: 0
B22: Corporate Events | C22: 0
B23: Brand Activation | C23: 0
B24: Other Income | C24: 0
B25: Total Gross Revenue | C25: =sum(C4,C9,C20,C22,C23,C24,C15, C21) -> 88970
B26: Total Net Revenue (Post Commissions) | C26: ='Offline & RG Community'!I30+Hudle!E6+District!F4 + Misfits!E2 -> 80551.94
B27: Total Revenue post GST | C27: =C26/1.18 -> 68264.356
B29: Expenses
B30: VM Salary | C30: 20000
B31: Support Staff | C31: 10000
B32: Marketing, Branding & Community | C32: 10000
B33: Balls | C33: 4500
B35: Net Profit | C35: =C27-(sum(C30:C33)) -> 23764.356

Sheet Offline & RG Community
A1: Date | B1: Day | C1: Offline booking hours | D1: Discount Given | E1: Booking Revenue | F1: Community Revenue | G1: Paddle Rental | H1: F&B | I1: Total Revenue
A2: 46054 | B2: Sunday | C2: 2.5 | D2: 0.2 | E2: 2460 | F2: 0 | G2: 750 | H2: 0 | I2: =SUM(D2:H2) -> 3210.2
A3: 46055 | B3: Monday | C3: 1.5 | D3: 0.2 | E3: 1560 | F3: 0 | G3: 0 | H3: 0 | I3: =SUM(D3:H3) -> 1560.2
A4: 46056 | B4: Tuesday | C4: 0 | D4: 0.2 | E4: 0 | F4: 0 | G4: 150 | H4: 0 | I4: =SUM(D4:H4) -> 150.2
A5: 46057 | B5: Wednesday | C5: 1.5 | D5: 0.2 | E5: 1440 | F5: 0 | G5: 0 | H5: 0 | I5: =SUM(D5:H5) -> 1440.2
A6: 46058 | B6: Thursday | C6: 0 | D6: 0.2 | E6: 0 | F6: 0 | G6: 0 | H6: 0 | I6: =SUM(D6:H6) -> 0.2
A7: 46059 | B7: Friday | C7: 0 | D7: 0.2 | E7: 0 | F7: 0 | G7: 150 | H7: 0 | I7: =SUM(D7:H7) -> 150.2
A8: 46060 | B8: Saturday | C8: 0 | D8: 0.2 | E8: 0 | G8: 250 | H8: 0 | I8: =SUM(D8:H8) -> 250.2
A9: 46061 | B9: Sunday | C9: 1 | D9: 0.2 | E9: 960 | F9: 0 | G9: 650 | H9: 0 | I9: =SUM(D9:H9) -> 1610.2
A10: 46062 | B10: Monday | C10: 0 | D10: 0.2 | E10: 0 | F10: 0 | G10: 100 | H10: 0 | I10: =SUM(D10:H10) -> 100.2
A11: 46063 | B11: Tuesday | C11: 0 | D11: 0.2 | E11: 0 | F11: 0 | G11: 0 | H11: 0 | I11: =SUM(D11:H11) -> 0.2
A12: 46064 | B12: Wednesday | C12: 0 | D12: 0.2 | E12: 0 | F12: 0 | G12: 0 | H12: 0 | I12: =SUM(D12:H12) -> 0.2
A13: 46065 | B13: Thursday | C13: 0 | D13: 0.2 | E13: 0 | F13: 0 | G13: 100 | H13: 0 | I13: =SUM(D13:H13) -> 100.2
A14: 46066 | B14: Friday | C14: 0 | D14: 0.2 | E14: 0 | F14: 0 | G14: 0 | H14: 0 | I14: =SUM(D14:H14) -> 0.2
A15: 46067 | B15: Saturday | C15: 0 | D15: 0.2 | E15: 0 | F15: 0 | G15: 100 | H15: 0 | I15: =SUM(D15:H15) -> 100.2
A16: 46068 | B16: Sunday | C16: 0 | D16: 0.2 | E16: 0 | F16: 0 | G16: 400 | H16: 0 | I16: =SUM(D16:H16) -> 400.2
A17: 46069 | B17: Monday | C17: 0 | D17: 0.2 | E17: 0 | F17: 0 | G17: 200 | H17: 0 | I17: =SUM(D17:H17) -> 200.2
A18: 46070 | B18: Tuesday | C18: 0 | D18: 0.2 | E18: 0 | F18: 0 | G18: 0 | H18: 0 | I18: =SUM(D18:H18) -> 0.2
A19: 46071 | B19: Wednesday | C19: 0 | D19: 0.2 | E19: 0 | F19: 0 | G19: 100 | H19: 0 | I19: =SUM(D19:H19) -> 100.2
A20: 46072 | B20: Thursday | C20: 0 | D20: 0.2 | E20: 0 | F20: 0 | G20: 100 | H20: 0 | I20: =SUM(D20:H20) -> 100.2
... A29: 46081 | B29: Saturday | C29: 1 | D29: 0.2 | E29: 950 | F29: 0 | G29: 450 | H29: 0 | I29: =SUM(D29:H29) -> 1400.2
A30: Total | C30: =SUM(C2:C29) -> 12 | E30: =SUM(E2:E29) -> 11910 | F30: =SUM(F2:F29) -> 0 | G30: =SUM(G2:G29) -> 4600 | H30: =SUM(H2:H29) -> 0 | I30: =SUM(I2:I29) -> 16515.6

Sheet Hudle
A1: Link | B1: Date | C1: Paid to Hudle | D1: Commisions (Including GST) | E1: Net Revenue | F1: TDS | G1: TCS | H1: Amount
B2: 1 - 9 Feb | C2: 15120 | D2: 1965.6 | E2: =C2-D2 -> 13154.4 | F2: 13.83 | G2: 69.15 | H2: 14115.4
B3: 9 - 16 Feb | C3: 11040 | D3: 1435.2 | E3: =C3-D3 -> 9604.8 | F3: 9.35 | G3: 46.77 | H3: 9548.68
B4: 16 - 23 Feb | C4: 15840 | D4: 2059.2 | E4: =C4-D4 -> 13780.8 | F4: 13.42 | G4: 67.11 | H4: 13700.28
B5: 23 - 28 Feb | C5: 6600 | D5: 748.8 | E5: =C5-D5 -> 5851.2 | F5: 4.88 | G5: 24.4 | H5: 4981.92
B6: Total | C6: =SUM(C2:C5) -> 48600 | E6: =SUM(E2:E5) -> 42391.2 | H6: =SUM(H2:H5) -> 42346.28

Sheet District
A1: Link | B1: Date | C1: Paid to District | D1: Commissions (₹) | E1: GST on Commission | F1: Net Revenue | G1: TCS | H1: TDS | I1: Final Amount (₹)
B2: 1 - 15 Feb | C2: 9600 | D2: 177.6 | E2: 31.98 | F2: =C2-D2-E2 -> 9390.42 | G2: 44.4 | H2: 8.88 | I2: 8617.14
B3: 16 - 28 Feb | C3: 4800 | D3: 96 | E3: 17.28 | F3: =C3-D3-E3 -> 4686.72 | G3: 24 | H3: 4.8 | I3: 4657.92
B4: Total | C4: =SUM(C2:C3) -> 14400 | F4: =SUM(F2:F3) -> 14077.14 | I4: =SUM(I2:I3) -> 13275.06

Sheet Misfits
A1: Link | B1: Date | C1: Paid to Misfits (₹) | D1: Comission (20%) | E1: Net Revenue | F1: TDS | G1: Final Amount (₹)
B2: 1 - 28 Feb | C2: 9460 | D2: 1892 | E2: =C2-D2 -> 7568 | F2: 189.2 | G2: =E2-F2 -> 7378.8
