Workbook

Sheet Summary
B2: 1 - 30 April
B3: Particulars | C3: Amount | D3: Amount | E3: Amount | F3: Amount
C4: Pickleball | D4: Turf | E4: Padel | F4: Total | I4: 205676 | J4: =175000*2 -> 350000
B5: Pay & Play | C5: =sum(C6,C12) -> 55025 | D5: =sum(D6,D12) -> 53486 | E5: 0 | F5: =sum(F6,F12) -> 108511 | I5: =F29 -> 185360.2 | J5: 100000
B6: Online | C6: =sum(C7:C11) -> 26975 | D6: =sum(D7:D11) -> 36268 | E6: 0 | F6: =sum(F7:F11) -> 63243 | I6: =I4+I5 -> 391036.2 | J6: =J4+J5 -> 450000
B7: District | C7: 0 | D7: 0 | E7: 0 | F7: 0
B8: Hudle | C8: =Hudle!B9 -> 6686 | D8: =Hudle!B10 -> 771 | E8: 0 | F8: =Hudle!C7 -> 7457
B9: Playo | C9: =Playo!B8 -> 10076 | D9: =Playo!B9 -> 33097 | E9: 0 | F9: =Playo!C6 -> 43173
B10: Khelomore | C10: =Khelomore!B6 -> 10213 | D10: =Khelomore!B7 -> 2400 | E10: 0 | F10: =Khelomore!C4 -> 12613
B11: Zplys | C11: 0 | D11: 0 | E11: 0 | F11: 0
B12: Offline | C12: =sum(C13:C14) -> 28050 | D12: =sum(D13:D14) -> 17218 | E12: 0 | F12: =sum(F13:F14) -> 45268
B13: Bookings | C13: ='Offline & RG Community'!E32 -> 28050 | D13: ='Offline & RG Community'!F32 -> 17218 | E13: 0 | F13: ='Offline & RG Community'!E32+'Offline & RG Community'!F32 -> 45268
B14: Memberships | C14: 0 | D14: 0 | E14: 0 | F14: 0
B15: Community | C15: =sum(C16:C17) -> 0 | D15: =sum(D16:D17) -> 0 | E15: 0 | F15: =sum(F16:F17) -> 0
B16: Pickup games | C16: 0 | D16: 0 | E16: 0 | F16: 0
B17: Social Events/Tournaments | C17: 0 | D17: 0 | E17: 0 | F17: 0
B18: Academy | C18: 0 | D18: 0 | E18: 0 | F18: 0
B19: Events & Partnership | C19: =sum(C20) -> 0 | D19: =sum(D20) -> 0 | E19: 0 | F19: =sum(F20) -> 0
B20: Corporate events | C20: 0 | D20: 0 | E20: 0 | F20: 0
B21: All B2B partnerships | C21: =SUM(C22:C25) -> 0 | D21: 0 | E21: 0 | F21: 0
B22: Commerce | C22: =sum(C23:C25) -> 0 | D22: =sum(D23:D25) -> 0 | E22: 0 | F22: =sum(F23:F25) -> 0
B23: Product rental | C23: 0 | D23: 0 | E23: 0 | F23: 0
B24: Product sales | C24: 0 | D24: 0 | E24: 0 | F24: 0
B25: F&B | C25: 0 | D25: 0 | E25: 0 | F25: 0
B26: Other Income | C26: 0 | D26: 0 | E26: 118000 | F26: ='Other Income'!C2 -> 118000
B27: Total Gross Revenue | C27: =sum(C5,C15,C18,C19,C22,C26) -> 55025 | D27: =sum(D5,D15,D18,D19,D22,D26) -> 53486 | E27: =sum(E5,E15,E18,E19,E22,E26) -> 118000 | F27: =F5+F15+F22+F18+F19+F26 -> 226511
B28: Total Net Revenue (Post Commissions) | F28: ='Offline & RG Community'!I32+Hudle!E7+Playo!F6+Khelomore!E4+'Other Income'!C2 -> 218725.03
B29: Total Revenue post GST | F29: =F28/1.18 -> 185360.2

Sheet Offline & RG Community
A1: Date | B1: Day | C1: Offline booking hours | D1: Discount Given | E1: Pickleball | F1: Turf | G1: Total Revenue | H1: Payment Gateway | I1: Net Revenue
A2: 1 Apr | B2: Wednesday | C2: 1 | D2: 20% and 25% | E2: 700 | F2: 0 | G2: =sum(E2:F2) -> 700 | H2: =G2*2.5%*1.18 -> 20.65 | I2: =G2-H2 -> 679.35
A3: 2 Apr | B3: Thursday | C3: 2 | D3: 20% and 25% | E3: 1750 | F3: 0 | G3: =sum(E3:F3) -> 1750 | H3: =G3*2.5%*1.18 -> 51.625 | I3: =G3-H3 -> 1698.375
A4: 3 Apr | B4: Friday | C4: 4.5 | D4: 20% and 25% | E4: 4650 | F4: 0 | G4: =sum(E4:F4) -> 4650 | H4: =G4*2.5%*1.18 -> 137.175 | I4: =G4-H4 -> 4512.825
A5: 4 Apr | B5: Saturday | C5: 3 | D5: 20% and 25% | E5: 5200 | F5: 0 | G5: =SUM(E5:F5) -> 5200 | H5: =G5*2.5%*1.18 -> 153.4 | I5: =G5-H5 -> 5046.6
A6: 5 Apr | B6: Sunday | C6: 0 | D6: 20% and 25% | E6: 0 | F6: 0 | G6: =SUM(E6:F6) -> 0 | H6: =G6*2.5%*1.18 -> 0 | I6: =G6-H6 -> 0
A7: 6 Apr | B7: Monday | C7: 1 | D7: 20% and 25% | E7: 0 | F7: 1300 | G7: =SUM(F7) -> 1300 | H7: =G7*2.5%*1.18 -> 38.35 | I7: =G7-H7 -> 1261.65
A8: 7 Apr | B8: Tuesday | C8: 0 | D8: 20% and 25% | E8: 0 | F8: 0 | G8: =SUM(E8:F8) -> 0 | H8: =G8*2.5%*1.18 -> 0 | I8: =G8-H8 -> 0
A9: 8 Apr | B9: Wednesday | C9: 0 | D9: 20% and 25% | E9: 0 | F9: 0 | G9: 0 | H9: =G9*2.5%*1.18 -> 0 | I9: =G9-H9 -> 0
A10: 9 Apr | B10: Thursday | C10: 1 | D10: 20% and 25% | E10: 0 | F10: 2250 | G10: =SUM(E10:F10) -> 2250 | H10: =G10*2.5%*1.18 -> 66.375 | I10: =G10-H10 -> 2183.625
A11: 10 Apr | B11: Friday | C11: 1 | D11: 20% and 25% | E11: 700 | F11: 0 | G11: =SUM(E11:F11) -> 700 | H11: =G11*2.5%*1.18 -> 20.65 | I11: =G11-H11 -> 679.35
A12: 11 Apr | B12: Saturday | C12: 0 | D12: 20% and 25% | E12: 0 | F12: 0 | G12: =SUM(E12:F12) -> 0 | H12: =G12*2.5%*1.18 -> 0 | I12: =G12-H12 -> 0
A13: 12 Apr | B13: Sunday | C13: 4.5 | D13: 20% and 25% | E13: 700 | F13: 7580 | G13: =SUM(E13:F13) -> 8280 | H13: =G13*2.5%*1.18 -> 244.26 | I13: =G13-H13 -> 8035.74
A14: 13 Apr | B14: Monday | C14: 1 | D14: 20% and 25% | E14: 700 | F14: 0 | G14: =SUM(E14:F14) -> 700 | H14: =G14*2.5%*1.18 -> 20.65 | I14: =G14-H14 -> 679.35
A15: 14 Apr | B15: Tuesday | C15: 4.5 | D15: 20% and 25% | E15: 2800 | F15: 0 | G15: =SUM(E15:F15) -> 2800 | H15: =G15*2.5%*1.18 -> 82.6 | I15: =G15-H15 -> 2717.4
A16: 15 Apr | B16: Wednesday | C16: 4.5 | D16: 20% and 25% | E16: 350 | F16: 4588 | G16: =SUM(E16:F16) -> 4938 | H16: =G16*2.5%*1.18 -> 145.671 | I16: =G16-H16 -> 4792.329
A17: 16 Apr | B17: Thursday | C17: 0 | D17: 20% and 25% | E17: 0 | F17: 0 | G17: =SUM(E17:F17) -> 0 | H17: =G17*2.5%*1.18 -> 0 | I17: =G17-H17 -> 0
A18: 17 Apr | B18: Friday | C18: 1.5 | D18: 20% and 25% | E18: 700 | F18: 0 | G18: =SUM(E18:F18) -> 700 | H18: =G18*2.5%*1.18 -> 20.65 | I18: =G18-H18 -> 679.35
A19: 18 Apr | B19: Saturday | C19: 0 | D19: 20% and 25% | E19: 0 | F19: 0 | G19: =SUM(E19:F19) -> 0 | H19: =G19*2.5%*1.18 -> 0 | I19: =G19-H19 -> 0
A20: 19 Apr | B20: Sunday | C20: 1 | D20: 20% and 25% | E20: 700 | F20: 0 | G20: =SUM(E20:F20) -> 700 | H20: =G20*2.5%*1.18 -> 20.65 | I20: =G20-H20 -> 679.35
A21: 20 Apr | B21: Monday | C21: 0 | D21: 20% and 25% | E21: 0 | F21: 0 | G21: =SUM(E21:F21) -> 0 | H21: =G21*2.5%*1.18 -> 0 | I21: =G21-H21 -> 0
... A31: 30 Apr | B31: Thursday | C31: 0 | D31: 20% and 25% | E31: 0 | F31: 0 | G31: =SUM(E31:F31) -> 0 | H31: =G31*2.5%*1.18 -> 0 | I31: =G31-H31 -> 0
A32: Total | C32: =SUM(C2:C31) -> 44.5 | E32: =SUM(E2:E31) -> 28050 | F32: =SUM(F2:F31) -> 17218 | G32: =SUM(G2:G31) -> 45268 | H32: =SUM(H2:H31) -> 1335.406 | I32: =SUM(I2:I31) -> 43932.594

Sheet Hudle
A1: Link | B1: Date | C1: Paid to Hudle | D1: Commisions (Including GST) | E1: Net Revenue | F1: TDS | G1: TCS | H1: Amount
B2: 1 - 7 Apr | C2: 1280 | D2: 163.8 | E2: =C2-D2 -> 1116.2 | F2: 1.06 | G2: 5.339 | H2: 1089.74
B3: 7 - 14 Apr | C3: 2800 | D3: 364 | E3: =C3-D3 -> 2436 | F3: 2.37 | G3: 11.86 | H3: 2421.76
B4: 14 - 19 Apr | C4: 2311 | D4: 668 | E4: =C4-D4 -> 1643 | F4: 2 | G4: 9.7 | H4: 1631.6
B5: 19 - 28 Apr | C5: 508 | D5: 27.59 | E5: =C5-D5 -> 480.41 | F5: 1 | G5: 2 | H5: 482
B6: 28 - 30 Apr | C6: 558 | D6: 72 | E6: =C6-D6 -> 486 | F6: 1 | G6: 5 | H6: 966
B7: Total | C7: =SUM(C2:C6) -> 7457 | E7: =SUM(E2:E6) -> 6161.61 | H7: =SUM(H2:H6) -> 6591.1
A9: Pickleball | B9: =C7-B10-B11 -> 6686
A10: Turf | B10: 771

Sheet Playo
A1: Link | B1: Date | C1: Paid to Playo (₹) | D1: Commissions (₹) | E1: GST (₹) | F1: Net Revenue | G1: TDS (₹) | H1: TCS (₹) | I1: Final Amount (₹)
B2: 1 - 12 Apr | C2: 19420 | D2: 1687 | E2: 303.66 | F2: =C2-D2-E2 -> 17429.34 | G2: 8.46 | H2: 0 | I2: 17420.88
B3: 13- 19 Apr | C3: =7700+4620 -> 12320 | D3: 1127 | E3: 202.86 | F3: =C3-D3-E3 -> 10990.14 | G3: 4.62 | H3: 0 | I3: 3285.52
B4: 19 - 26 Apr | C4: 7920 | D4: 700 | E4: 126 | F4: =C4-D4-E4 -> 7094 | G4: 6 | H4: 0 | I4: 5108
B5: 27 - 30 Apr | C5: 3513 | D5: 321 | E5: 57 | F5: =C5-D5-E5 -> 3135 | G5: 1.76 | H5: 0 | I5: 1375
B6: Total | C6: =sum(C2:C5) -> 43173 | F6: =sum(F2:F5) -> 38648.48 | I6: =sum(I2:I5) -> 27189.4
A8: Pickleball | B8: =C6-B9-B10 -> 10076
A9: Turf | B9: =30700+2397 -> 33097

Sheet Khelomore
A1: Link | B1: Date | C1: Paid to Khelomore (₹) | D1: Commissions (₹) | E1: Final Amount (₹)
B2: 1 - 30 Apr | C2: 12613 | D2: =C2*5% -> 630.65 | E2: =C2-D2 -> 11982.35
B4: Total | C4: =SUM(C2) -> 12613 | E4: =SUM(E2) -> 11982.35
A6: Pickleball | B6: =C4-B7-B8 -> 10213
A7: Turf | B7: 2400

Sheet Other Income
A1: Month | B1: Sports Type | C1: Amount Collected
A2: Apr | B2: Padel Operations & Management Fees | C2: 118000
