Workbook

Sheet Summary
B2: Date: 1 - 28 Feb
B3: Particulars | C3: Amount
B4: Offline | C4: =SUM(C5,C6,C7,, C8) -> 0
B5: Rentals | C5: ='Offline & RG Community'!G7 -> 0
B6: F&B | C6: 0
B7: Product Sales | C7: 0
B8: Bookings | C8: ='Offline & RG Community'!E7 -> 0
B9: Online: Third Party Platform | C9: =SUM(C10:C14) -> 161
B10: Hudle | C10: 0
B11: Playo | C11: 0
B12: District | C12: 0
B13: Khelomore | C13: =Khelomore!C3 -> 161
B14: Zplys | C14: 0
B15: Community | C15: =SUM(C16:C19) -> 0
B16: Courtly (Organized by RallyGully) | C16: 0
B17: Sportomic (Organized by RallyGully) | C17: 0
B18: Rallygully Community games | C18: ='Offline & RG Community'!F7 -> 0
B19: Misfits Community | C19: 0
B20: Memberships | C20: 0
B21: Coaching | C21: 0
B22: Corporate Events | C22: 0
B23: Brand Activation | C23: =0 -> 0
B24: Other Income | C24: ='Other Income'!C2 -> 59000
B25: Total Gross Revenue | C25: =sum(C4,C9,C20,C22,C23,C24,C15, C21) -> 59161
B26: Total Net Revenue (Post Commissions) | C26: =Khelomore!E3+'Other Income'!C2 -> 59152.95
B27: Total Revenue post GST | C27: =C26/1.18 -> 50129.619

Sheet Offline & RG Community
A1: Date | B1: Day | C1: Offline booking hours | D1: Discount Given | E1: Booking Revenue | F1: Community Revenue | G1: Paddle Rental | H1: Total Revenue
A2: 24 Feb | B2: Sunday | C2: Free Play | D2: 20% and 25% | H2: =sum(E2:G2) -> 0
A3: 25 Feb | B3: Monday | C3: Free Play | D3: 20% and 25% | H3: =sum(E3:G3) -> 0
A4: 26 Feb | B4: Tuesday | C4: Free Play | D4: 20% and 25% | H4: =sum(E4:G4) -> 0
A5: 27 Feb | B5: Wednesday | C5: Free Play | D5: 20% and 25% | H5: =sum(E5:G5) -> 0
A6: 28 Feb | B6: Thursday | C6: Free Play | D6: 20% and 25% | H6: =sum(E6:G6) -> 0
A7: Total | C7: =SUM(C1:C6) -> 0 | E7: =SUM(E1:E6) -> 0 | F7: =SUM(F1:F6) -> 0 | G7: =SUM(G1:G6) -> 0 | H7: =SUM(H1:H6) -> 0

Sheet Khelomore
A1: Link | B1: Date | C1: Paid to Khelomore (₹) | D1: Commissions (₹) | E1: Final Amount (₹)
B2: 23 - 28 Feb | C2: 161 | D2: =C2*5% -> 8.05 | E2: =C2-D2 -> 152.95
B3: Total | C3: =SUM(C2) -> 161 | E3: =SUM(E2) -> 152.95

Sheet Other Income
A1: Month | B1: Sports Type | C1: Amount Collected
A2: Feb | B2: Padel Operations & Management Fees | C2: 59000
