Workbook

Sheet Summary
B2: 1 - 31 May
B3: Particulars | C3: Amount
C4: Pickleball
B5: Pay & Play | C5: =sum(C6,C12) -> 209404
B6: Online | C6: =sum(C7:C11) -> 179124
B7: District | C7: =District!C4 -> 164897
B8: Hudle | C8: =Hudle!C3 -> 14227
B9: Playo | C9: 0
B10: Khelomore | C10: 0
B11: Zplys | C11: 0
B12: Offline | C12: =sum(C13:C14) -> 30280 | F12: =C13+C16+C23+C25 -> 102670
B13: Bookings | C13: ='Offline & RG Community'!E33 -> 30280
B14: Memberships | C14: 0
B15: Community | C15: =sum(C16:C17) -> 92550
B16: Pickup games | C16: ='Offline & RG Community'!F33 -> 61500
B17: Social Events/Tournaments | C17: =Courtly!B4+Courtly!B6 -> 31050
B18: Academy | C18: =Academy!C2 -> 38000
B19: Events & Partnership | C19: =sum(C20,C21) -> 0
B20: Corporate events | C20: 0
B21: All B2B partnerships | C21: 0
B22: Commerce | C22: =sum(C23:C25) -> 10890
B23: Product rental | C23: ='Offline & RG Community'!G33 -> 8500
B24: Product sales | C24: 0
B25: F&B | C25: ='Offline & RG Community'!H33 -> 2390
B26: Other Income | C26: 0
B27: Total Gross Revenue | C27: =sum(C26+C22+C19+C18+C15+C12+C6) -> 350844
B28: Total Net Revenue (Post Commissions) | C28: ='Offline & RG Community'!K33+District!F4+Hudle!E3+Courtly!D4+Courtly!D6+Academy!F2 -> 330445.82
B29: Total Revenue post GST | C29: =C28/1.18 -> 280038.83
B30: Expenses
B31: Venue Manager + Cleaner | C31: 60164
B32: Marketing, Branding & Community | C32: 15000
B33: Balls Expense | C33: 9500
B34: Branding Revamp | C34: 12595
B35: F&B Inventory Cost | C35: 3024
B36: Total Expenses | C36: =C31+C32+C33+C34+C35 -> 100283
B37: Net Profit (Revenue - Expenses) | C37: =C29-C36 -> 179755.83
B39: School's Profit Share (65%) | C39: =C37*65% -> 116841.29
B40: RallyGully's Profit Share (35%) | C40: =C37*35% -> 62914.542

Sheet Offline & RG Community
A1: Date | B1: Day | C1: Offline booking hours | D1: Discount Given | E1: Booking Revenue | F1: Community Revenue | G1: Paddle Rental | H1: F&B | I1: Total Revenue | J1: Payment Gateway | K1: Net Revenue
A2: 46143 | B2: Friday | C2: 1 | D2: 0 and 10% | E2: 1050 | F2: 2400 | G2: 600 | H2: 140 | I2: =sum(E2:H2) -> 4190 | J2: =I2*2.5%*1.18 -> 123.605 | K2: =I2-J2 -> 4066.395
A3: 46144 | B3: Saturday | C3: 1 | D3: 0 and 10% | E3: 1000 | F3: 2400 | G3: 950 | H3: 105 | I3: =sum(E3:H3) -> 4455 | J3: =I3*1.75% -> 77.9625 | K3: =I3-J3 -> 4377.0375
A4: 46145 | B4: Sunday | C4: 2 | D4: 0 and 10% | E4: 2000 | F4: 4800 | G4: 600 | H4: 140 | I4: =sum(E4:H4) -> 7540 | J4: =I4*1.75% -> 131.95 | K4: =I4-J4 -> 7408.05
A5: 46146 | B5: Monday | C5: 1.5 | D5: 0 and 10% | E5: 1400 | F5: 2400 | G5: 400 | H5: 315 | I5: =sum(E5:H5) -> 4515 | J5: =I5*1.75% -> 79.0125 | K5: =I5-J5 -> 4435.9875
A6: 46147 | B6: Tuesday | C6: 2 | D6: 0 and 10% | E6: 0 | F6: 3000 | G6: 300 | H6: 105 | I6: =sum(E6:H6) -> 3405 | J6: =I6*1.75% -> 59.5875 | K6: =I6-J6 -> 3345.4125
A7: 46148 | B7: Wednesday | C7: 4.5 | D7: 0 and 10% | E7: 7560 | F7: 0 | G7: 100 | H7: 0 | I7: =sum(E7:H7) -> 7660 | J7: =I7*1.75% -> 134.05 | K7: =I7-J7 -> 7525.95
A8: 46149 | B8: Thursday | C8: 4 | D8: 0 and 10% | E8: 3700 | F8: 3900 | G8: 100 | H8: 0 | I8: =sum(E8:H8) -> 7700 | J8: =I8*1.75% -> 134.75 | K8: =I8-J8 -> 7565.25
A9: 46150 | B9: Friday | C9: 1 | D9: 0 and 10% | E9: 1050 | F9: 3000 | G9: 300 | H9: 0 | I9: =sum(E9:H9) -> 4350 | J9: =I9*1.75% -> 76.125 | K9: =I9-J9 -> 4273.875
A10: 46151 | B10: Saturday | C10: 0.5 | D10: 0 and 10% | E10: 500 | F10: 0 | G10: 350 | H10: 0 | I10: =sum(E10:H10) -> 850 | J10: =I10*1.75% -> 14.875 | K10: =I10-J10 -> 835.125
A11: 46152 | B11: Sunday | C11: 1 | D11: 0 and 10% | E11: 1000 | F11: 600 | G11: 0 | H11: 0 | I11: =sum(E11:H11) -> 1600 | J11: =I11*1.75% -> 28 | K11: =I11-J11 -> 1572
A12: 46153 | B12: Monday | C12: 3 | D12: 0 and 10% | E12: 0 | F12: 4200 | G12: 600 | H12: 0 | I12: =sum(E12:H12) -> 4800 | J12: =I12*1.75% -> 84 | K12: =I12-J12 -> 4716
A13: 46154 | B13: Tuesday | C13: 3 | D13: 0 and 10% | E13: 0 | F13: 4200 | G13: 0 | H13: 140 | I13: =sum(E13:H13) -> 4340 | J13: =I13*1.75% -> 75.95 | K13: =I13-J13 -> 4264.05
A14: 46155 | B14: Wednesday | C14: 0 | D14: 0 and 10% | E14: 0 | F14: 0 | G14: 0 | H14: 0 | I14: =sum(E14:H14) -> 0 | J14: =I14*1.75% -> 0 | K14: =I14-J14 -> 0
A15: 46156 | B15: Thursday | C15: 2 | D15: 0 and 10% | E15: 0 | F15: 3000 | G15: 400 | H15: 140 | I15: =sum(E15:H15) -> 3540 | J15: =I15*1.75% -> 61.95 | K15: =I15-J15 -> 3478.05
A16: 46157 | B16: Friday | C16: 2 | D16: 0 and 10% | E16: 1200 | F16: 1200 | G16: 0 | H16: 0 | I16: =SUM(E16:H16) -> 2400 | J16: =I16*1.75% -> 42 | K16: =I16-J16 -> 2358
A17: 46158 | B17: Saturday | C17: 1.5 | D17: 0 and 10% | E17: 1620 | F17: 0 | G17: 300 | H17: 175 | I17: =SUM(F17:H17) -> 475 | J17: =I17*1.75% -> 8.3125 | K17: =I17-J17 -> 466.6875
A18: 46159 | B18: Sunday | C18: 0.5 | D18: 0 and 10% | E18: 600 | F18: 0 | G18: 900 | H18: 0 | I18: =SUM(E18:H18) -> 1500 | J18: =I18*1.75% -> 26.25 | K18: =I18-J18 -> 1473.75
A19: 46160 | B19: Monday | C19: 3 | D19: 0 and 10% | E19: 900 | F19: 3600 | G19: 100 | H19: 315 | I19: =SUM(E19:H19) -> 4915 | J19: =I19*1.75% -> 86.0125 | K19: =I19-J19 -> 4828.9875
A20: 46161 | B20: Tuesday | C20: 2 | D20: 0 and 10% | E20: 0 | F20: 3300 | G20: 400 | H20: 115 | I20: =SUM(E20:H20) -> 3815 | J20: =I20*1.75% -> 66.7625 | K20: =I20-J20 -> 3748.2375
A21: 46162 | B21: Wednesday | C21: 2 | D21: 0 and 10% | E21: 0 | F21: 2400 | G21: 100 | H21: 70 | I21: =SUM(E21:H21) -> 2570 | J21: =I21*1.75% -> 44.975 | K21: =I21-J21 -> 2525.025
A22: 46163 | B22: Thursday | C22: 1 | D22: 0 and 10% | E22: 0 | F22: 900 | G22: 0 | H22: 0 | I22: =sum(E22:H22) -> 900 | J22: =I22*1.75% -> 15.75 | K22: =I22-J22 -> 884.25
A23: 46164 | B23: Friday | C23: 3 | D23: 0 and 10% | E23: 0 | F23: 5700 | G23: 0 | H23: 0 | I23: =SUM(E23:H23) -> 5700 | J23: =I23*1.75% -> 99.75 | K23: =I23-J23 -> 5600.25
A24: 46165 | B24: Saturday | C24: 0.5 | D24: 0 and 10% | E24: 600 | F24: 0 | G24: 1000 | H24: 175 | I24: =SUM(E24:H24) -> 1775 | J24: =I24*1.75% -> 31.0625 | K24: =I24-J24 -> 1743.9375
A25: 46166 | B25: Sunday | C25: 1 | D25: 0 and 10% | E25: 900 | F25: 2400 | G25: 0 | H25: 70 | I25: =SUM(E25:H25) -> 3370 | J25: =I25*1.75% -> 58.975 | K25: =I25-J25 -> 3311.025
A26: 46167 | B26: Monday | C26: 0 | D26: 0 and 10% | E26: 0 | F26: 4200 | G26: 0 | H26: 175 | I26: =SUM(E26:H26) -> 4375 | J26: =I26*1.75% -> 76.5625 | K26: =I26-J26 -> 4298.4375
A27: 46168 | B27: Tuesday | C27: 0 | D27: 0 and 10% | E27: 0 | F27: 900 | G27: 0 | H27: 0 | I27: =SUM(E27:H27) -> 900 | J27: =I27*1.75% -> 15.75 | K27: =I27-J27 -> 884.25
A28: 46169 | B28: Wednesday | C28: 0 | D28: 0 and 10% | E28: 0 | F28: 0 | G28: 0 | H28: 0 | I28: =SUM(E28:H28) -> 0 | J28: =I28*1.75% -> 0 | K28: =I28-J28 -> 0
A29: 46170 | B29: Thursday | C29: 0 | D29: 0 and 10% | E29: 0 | F29: 0 | G29: 100 | H29: 0 | I29: =SUM(E29:H29) -> 100 | J29: =I29*1.75% -> 1.75 | K29: =I29-J29 -> 98.25
A30: 46171 | B30: Friday | C30: 3 | D30: 0 and 10% | E30: 3800 | F30: 0 | G30: 0 | H30: 175 | I30: =SUM(E30:H30) -> 3975 | J30: =I30*1.75% -> 69.5625 | K30: =I30-J30 -> 3905.4375
A31: 46172 | B31: Saturday | C31: 0 | D31: 0 and 10% | E31: 0 | F31: 0 | G31: 0 | H31: 0 | I31: =SUM(E31:H31) -> 0 | J31: =I31*1.75% -> 0 | K31: =I31-J31 -> 0
A32: 46173 | B32: Sunday | C32: 3.5 | D32: 0 and 10% | E32: 1400 | F32: 3000 | G32: 900 | H32: 35 | I32: =SUM(E32:H32) -> 5335 | J32: =I32*1.75% -> 93.3625 | K32: =I32-J32 -> 5241.6375
A33: Total | C33: =SUM(C2:C32) -> 49.5 | E33: =SUM(E2:E32) -> 30280 | F33: =SUM(F2:F32) -> 61500 | G33: =SUM(G2:G32) -> 8500 | H33: =SUM(H2:H32) -> 2390 | I33: =SUM(I2:I32) -> 101050 | J33: =SUM(J2:J32) -> 1818.655 | K33: =SUM(K2:K32) -> 99231.345

Sheet District
A1: Link | B1: Date | C1: Paid to District | D1: Commissions (₹) | E1: GST on Commission | F1: Net Revenue | G1: TCS | H1: TDS | I1: Final Amount (₹)
B2: 1 - 31 May | C2: 164897 | D2: 10736 | E2: 1932 | F2: =C2-D2-E2 -> 152229 | G2: 894 | H2: 178 | I2: 151153
B4: Total | C4: =SUM(C2:C3) -> 164897 | F4: =SUM(F2:F3) -> 152229 | I4: =SUM(I2:I3) -> 151153

Sheet Hudle
A1: Link | B1: Date | C1: Paid to Hudle | D1: Commisions (Including GST) | E1: Net Revenue | F1: TDS | G1: TCS | H1: Amount
B2: 1 - 31 May | C2: 14227 | D2: 1700 | E2: =C2-D2 -> 12527 | F2: 11 | G2: 55 | H2: 11312
B3: Total | C3: =SUM(C2) -> 14227 | E3: =SUM(E2) -> 12527 | H3: =SUM(H2) -> 11312

Sheet Courtly
A1: Date | B1: Paid to Courtly | C1: Post Comission | D1: Net Revenue | E1: TDS | F1: Final Amount (₹)
A2: 16,17 and 23 May | B2: =7595+7304+12152 -> 27051 | C2: =B2*5% -> 1352.55 | D2: =B2-C2 -> 25698.45 | E2: =B2*2% -> 541.02 | F2: =D2-E2 -> 25157.43
A4: Total | B4: =SUM(B2) -> 27051 | D4: =SUM(D2) -> 25698.45 | F4: =SUM(F2) -> 25157.43
A5: Offine DUPR | B5: Amt | C5: Payment Gateway | D5: Net Revenue
A6: 16,17 and 23 May | B6: =1599+2400 -> 3999 | C6: =B6*2.5%*1.18 -> 117.9705 | D6: =B6-C6 -> 3881.0295

Sheet Academy
A1: Sports | B1: Month | C1: Amt | D1: Number of People | E1: Payment Gateway | F1: Net Revenue
A2: Pickleball | B2: May | C2: 38000 | D2: 8 Kids | E2: =C2*2.5%*1.18 -> 1121 | F2: =C2-E2 -> 36879
