Workbook

Sheet Summary
B2: Date: 1 - 31 Jan
B3: Particulars | C3: Amount
B4: Offline | C4: =SUM(C5,C6,C7,C8) -> 97445
B5: Rentals | C5: ='Offline & RG Community'!G33 -> 8155
B6: F&B | C6: 0
B7: Product Sales | C7: =0 -> 0
B8: Bookings | C8: ='Offline & RG Community'!E33 -> 89290
B9: Online: Third Party Platform | C9: =SUM(C10:C13) -> 47466
B10: Hudle | C10: =Hudle!C7 -> 25407
B11: Playo | C11: =Playo!C7 -> 4460
B12: District | C12: =District!C5 -> 17200
B13: Khelomore | C13: =Khelomore!C4 -> 399
B14: Zplys | C14: 0
B15: Community | C15: =sum(C17:C19) -> 3000
B16: Courtly (Organized by RallyGully) | C16: 0
B17: Sportomic (Organized by RallyGully) | C17: =Sportomic!C2 -> 0
B18: Rallygully Community games | C18: ='Offline & RG Community'!F33 -> 3000
B19: Misfits Community | C19: =Misfits!C2 -> 0
B20: Memberships | C20: =Membership!E2 -> 18880
B21: Coaching | C21: 0
B22: Corporate Events | C22: ='Corporate Events'!E2 -> 2730
B23: Brand Activation | C23: 0
B24: Other Income | C24: 0
B25: Total Gross Revenue | C25: =sum(C23,C24,C22, C20,C15,C9,C4) -> 169521
B26: Total Net Revenue (Post Commissions) | C26: ='Offline & RG Community'!H33 + Hudle!E7 +Playo!F7 +District!F5 + Misfits!F3 +Membership!E2+'Corporate Events'!E2+ Khelomore!E4 -> 165384.08
B27: Total Revenue post GST | C27: =C26/1.18 -> 140156

Sheet Offline & RG Community
A1: Date | B1: Day | C1: Offline booking hours | D1: Discount Given | E1: Booking Revenue | F1: Community Revenue | G1: Paddle Rental | H1: Total Revenue
A2: 46023 | B2: Thursday | C2: 3.5 | D2: 30% and 20% | E2: 2240 | F2: 0 | G2: 600 | H2: =sum(E2:G2) -> 2840
A3: 46024 | B3: Friday | C3: 2 | D3: 30% and 20% | E3: 1520 | F3: 0 | G3: 300 | H3: =sum(E3:G3) -> 1820
A4: 46025 | B4: Saturday | C4: 6.5 | D4: 30% and 20% | E4: 5920 | F4: 0 | G4: 350 | H4: =sum(E4:G4) -> 6270
A5: 46026 | B5: Sunday | C5: 5.5 | D5: 30% and 20% | E5: 2880 | F5: 0 | G5: 350 | H5: =sum(E5:G5) -> 3230
A6: 46027 | B6: Monday | C6: 1 | D6: 30% and 20% | E6: 640 | F6: 0 | G6: 0 | H6: =sum(E6:G6) -> 640
A7: 46028 | B7: Tuesday | C7: 1 | D7: 30% and 20% | E7: 1280 | F7: 0 | G7: 0 | H7: =sum(E7:G7) -> 1280
A8: 46029 | B8: Wednesday | C8: 1.5 | D8: 30% and 20% | E8: 2240 | F8: 600 | G8: 50 | H8: =sum(E8:G8) -> 2890
A9: 46030 | B9: Thursday | C9: 1.5 | D9: 30% and 20% | E9: 960 | F9: 800 | G9: 300 | H9: =sum(E9:G9) -> 2060
A10: 46031 | B10: Friday | C10: 0.5 | D10: 30% and 20% | E10: 3180 | F10: 600 | G10: 50 | H10: =sum(E10:G10) -> 3830
A11: 46032 | B11: Saturday | C11: 2.5 | D11: 30% and 20% | E11: 1200 | F11: 0 | G11: 250 | H11: =sum(E11:G11) -> 1450
A12: 46033 | B12: Sunday | C12: 1 | D12: 30% and 20% | E12: 640 | F12: 0 | G12: 150 | H12: =sum(E12:G12) -> 790
A13: 46034 | B13: Monday | C13: 5.5 | D13: 30% and 20% | E13: 4580 | F13: 0 | G13: 0 | H13: =sum(E13:G13) -> 4580
A14: 46035 | B14: Tuesday | C14: 0.5 | D14: 30% and 20% | E14: 320 | F14: 0 | G14: 0 | H14: =sum(E14:G14) -> 320
A15: 46036 | B15: Wednesday | C15: 6 | D15: 30% and 20% | E15: 4650 | G15: 100 | H15: =sum(E15:G15) -> 4750
A16: 46037 | B16: Thursday | C16: 4 | D16: 30% and 20% | E16: 2560 | F16: 0 | G16: 300 | H16: =sum(E16:G16) -> 2860
A17: 46038 | B17: Friday | C17: 3.5 | D17: 30% and 20% | E17: 2240 | F17: 0 | G17: 400 | H17: =sum(E17:G17) -> 2640
A18: 46039 | B18: Saturday | C18: 5 | D18: 30% and 20% | E18: 7360 | F18: 0 | G18: 1150 | H18: =sum(E18:G18) -> 8510
A19: 46040 | B19: Sunday | C19: 4 | D19: 30% and 20% | E19: 3120 | F19: 0 | G19: 450 | H19: =sum(E19:G19) -> 3570
A20: 46041 | B20: Monday | C20: 1.5 | D20: 30% and 20% | E20: 960 | F20: 0 | G20: 400 | H20: =sum(E20:G20) -> 1360
A21: 46042 | B21: Tuesday | C21: 5.5 | D21: 30% and 20% | E21: 3520 | F21: 0 | G21: 30 | H21: =sum(E21:G21) -> 3550
A22: 46043 | B22: Wednesday | C22: 5 | D22: 30% and 20% | E22: 3200 | F22: 0 | G22: 450 | H22: =sum(E22:G22) -> 3650
A23: 46044 | B23: Thursday | C23: 2 | D23: 30% and 20% | E23: 1280 | F23: 0 | G23: 400 | H23: =sum(E23:G23) -> 1680
A24: 46045 | B24: Friday | C24: 0 | D24: 30% and 20% | E24: 0 | F24: 0 | G24: 0 | H24: =sum(E24:G24) -> 0
A25: 46046 | B25: Saturday | C25: 5 | D25: 30% and 20% | E25: 5060 | F25: 0 | G25: 100 | H25: =sum(E25:G25) -> 5160
A26: 46047 | B26: Sunday | C26: 11.5 | D26: 30% and 20% | E26: 10640 | F26: 0 | G26: 750 | H26: =sum(E26:G26) -> 11390
A27: 46048 | B27: Monday | C27: 5 | D27: 30% and 20% | E27: 5140 | F27: 0 | G27: 275 | H27: =sum(E27:G27) -> 5415
... A32: 46053 | B32: Saturday | C32: 6 | D32: 30% and 20% | E32: 5160 | F32: 0 | G32: 550 | H32: =sum(E32:G32) -> 5710
A33: Total | C33: =SUM(C2:C32) -> 108 | E33: =SUM(E2:E32) -> 89290 | F33: =SUM(F2:F32) -> 3000 | G33: =SUM(G2:G32) -> 8155 | H33: =SUM(H2:H32) -> 100445

Sheet Hudle
A1: Link | B1: Date | C1: Paid to Hudle | D1: Commisions (Including GST) | E1: Net Revenue | F1: TDS | G1: TCS | H1: Amount
B2: 1 - 5 Jan | C2: 5760 | D2: 748.8 | E2: =C2 - D2 -> 5011.2 | F2: 4.88 | G2: 24.4 | H2: 4981.9
B3: 6 - 12 Jan | C3: 1335 | D3: 176.8 | E3: =C3 - D3 -> 1158.2 | F3: 1.15 | G3: 5.76 | H3: 1176.28
B4: 13 - 19 Jan | C4: 5905 | D4: 781.3 | E4: =C4 - D4 -> 5123.7 | F4: 5.09 | G4: 25.46 | H4: 5198.6
B5: 20 - 26 Jan | C5: 5847 | D5: 763.36 | E5: =C5 - D5 -> 5083.64 | F5: 4.97 | G5: 24.88 | H5: 5078.8
B6: 27 - 31 Jan | C6: 6560 | D6: 852.8 | E6: =C6 - D6 -> 5707.2 | F6: 5.55 | G6: 27.79 | H6: 5673.85
C7: =SUM(C2:C6) -> 25407 | E7: =SUM(E2:E6) -> 22083.94 | H7: =SUM(H2:H6) -> 22109.43

Sheet Playo
A1: Link | B1: Date | C1: Paid to Playo (₹) | D1: Commissions (₹) | E1: GST (₹) | F1: Net Revenue | G1: TDS (₹) | H1: TCS (₹) | I1: Final Amount (₹)
B2: 1 - 13 Jan | C2: 1600 | D2: 112 | E2: 20.16 | F2: =C2 -D2-E2 -> 1467.84 | G2: 0.24 | H2: 1.2 | I2: 106.4
B3: 13 - 19 Jan | C3: 1500 | D3: 105 | E3: 18.9 | F3: =C3 -D3-E3 -> 1376.1 | G3: 1.5 | H3: 7.5 | I3: 1367.1
B4: 20 - 25 Jan | C4: 560 | D4: 56 | E4: 10.08 | F4: =C4 -D4-E4 -> 493.92 | G4: 0.56 | H4: 2.8 | I4: 490.56
B5: 26 - 31 Jan | C5: 800 | D5: 56 | E5: 10.8 | F5: =C5 -D5-E5 -> 733.2 | G5: 0.8 | H5: 4 | I5: 729.12
B7: Total | C7: =SUM(C2:C5) -> 4460 | F7: =SUM(F2:F6) -> 4071.06 | I7: =SUM(I2:I5) -> 2693.18

Sheet District
A1: Link | B1: Date | C1: Paid to District | D1: Commissions (₹) | E1: GST on Commission | F1: Net Revenue | G1: TCS | H1: TDS | I1: Final Amount (₹)
B2: 1 - 12 Jan | C2: 6800 | D2: =C2*2% -> 136 | E2: =D2*18% -> 24.48 | F2: =C2-D2-E2 -> 6639.52 | G2: =C2*0.5% -> 34 | H2: =D2*0.1% -> 0.136 | I2: =F2-G2-H2 -> 6605.384
B3: 13 - 19 Jan | C3: 4400 | D3: =C3*2% -> 88 | E3: =D3*18% -> 15.84 | F3: =C3-D3-E3 -> 4296.16 | G3: =C3*0.5% -> 22 | H3: =D3*0.1% -> 0.088 | I3: =F3-G3-H3 -> 4274.072
B4: 20 - 31 Jan | C4: 6000 | D4: =C4*2% -> 120 | E4: =D4*18% -> 21.6 | F4: =C4-D4-E4 -> 5858.4 | G4: =C4*0.5% -> 30 | H4: =D4*0.1% -> 0.12 | I4: =F4-G4-H4 -> 5828.28
B5: Total | C5: =SUM(C2:C4) -> 17200 | F5: =SUM(F2:F4) -> 16794.08 | I5: =SUM(I2:I4) -> 16707.736

Sheet Khelomore
A1: Link | B1: Date | C1: Paid to Khelomore (₹) | D1: Commissions (₹) | E1: Final Amount (₹)
B2: 1 - 25 Jan | C2: 399 | D2: =C2*5% -> 19.95 | E2: 380
C4: =SUM(C2:C3) -> 399 | E4: =SUM(E2:E3) -> 380

Sheet Misfits
A1: Link | B1: Date | C1: Paid to Misfits (₹) | D1: Post Comission (20%) | E1: TDS | F1: Final Amount (₹)
B2: 1 - 31 Jan | C2: 0

Sheet Sportomic
A1: Link | B1: Date | C1: Paid to Sportomic (₹)
B2: 1 - 31 Jan | C2: 0

Sheet Membership
A1: Member Name | B1: Sports Type | C1: Membership Type | D1: Start Date | E1: Amount Collected
A2: Indian School of hospitality | B2: Pickle & Box | C2: Collab | D2: 45992 | E2: 18880

Sheet Corporate Events
A1: Date | B1: Type | C1: Sports Type | D1: Deliverables | E1: Amount Collected
A2: 46049 | B2: Bday Event | C2: Pickeball and Box | D2: 3 Hours of courts | E2: 2730
