Workbook

Sheet Summary
B2: Date: 28 - 31 Mar
B3: Particulars | C3: Amount
B4: Offline | C4: =SUM(C5,C6,C7,, C8) -> 2650
B5: Rentals | C5: ='Offline & RG Community'!G6 -> 600
B6: F&B | C6: 0
B7: Product Sales | C7: 0
B8: Bookings | C8: ='Offline & RG Community'!E6 -> 2050
B9: Online: Third Party Platform | C9: =SUM(C10:C14) -> 5740
B10: Hudle | C10: =Hudle!C3 -> 5740
B11: Playo | C11: 0
B12: District | C12: 0
B13: Khelomore | C13: 0
B14: Zplys | C14: 0
B15: Community | C15: =SUM(C16:C19) -> 110270
B16: Courtly (Organized by RallyGully) | C16: =Courtly!B2 -> 52820
B17: Sportomic (Organized by RallyGully) | C17: 0
B18: Rallygully Community games | C18: ='Offline & RG Community'!F6 -> 57450
B19: Misfits Community | C19: 0
B20: Memberships | C20: 0
B21: Coaching | C21: 0
B22: Corporate Events | C22: 0
B23: Brand Activation | C23: ='Brand Activation'!C5 -> 18000
B24: Other Income | C24: 0
B25: Total Gross Revenue | C25: =C15+C9+C4+C23 -> 136660
B26: Total Net Revenue (Post Commissions) | C26: ='Offline & RG Community'!H6+Hudle!E3+Courtly!D3+'Brand Activation'!C5 -> 134329.16
B27: Total Revenue post GST | C27: =C26/1.18 -> 113838.27

Sheet Offline & RG Community
A1: Date | B1: Day | C1: Offline booking hours | D1: Discount Given | E1: Booking Revenue | F1: Community Revenue | G1: Paddle Rental | H1: Total Revenue
A2: 28 Mar | B2: Saturday | C2: Pickleball Event | D2: 20% and 25% | E2: 0 | F2: 23900 | G2: 0 | H2: =sum(E2:G2) -> 23900
A3: 29 Mar | B3: Sunday | C3: Football Event | D3: 20% and 25% | E3: 0 | F3: 33550 | G3: 0 | H3: =sum(E3:G3) -> 33550
A4: 30 Mar | B4: Monday | C4: 1.5 | D4: 20% and 25% | E4: 2050 | F4: 0 | G4: 600 | H4: =sum(E4:G4) -> 2650
A5: 31 Mar | B5: Tuesday | C5: 0 | D5: 20% and 25% | E5: 0 | F5: 0 | G5: 0 | H5: =SUM(E5:G5) -> 0
A6: Total | C6: =SUM(C1:C5) -> 1.5 | E6: =SUM(E1:E5) -> 2050 | F6: =SUM(F1:F5) -> 57450 | G6: =SUM(G1:G5) -> 600 | H6: =SUM(H1:H5) -> 60100

Sheet Hudle
A1: Link | B1: Date | C1: Paid to Hudle | D1: Commisions (Including GST) | E1: Net Revenue | F1: TDS | G1: TCS | H1: Amount
B2: 23 - 31 Mar | C2: 5740 | D2: 746.24 | E2: =C2-D2 -> 4993.76 | F2: 4.86 | G2: 24.32 | H2: 4964.8
B3: Total | C3: =SUM(C2) -> 5740 | E3: =SUM(E2) -> 4993.76 | H3: =SUM(H2) -> 4964.8

Sheet Courtly
A1: Date | B1: Paid to Courtly | C1: Post Comission | D1: Net Revenue | E1: TDS | F1: Final Amount (₹)
A2: 28-29 Mar | B2: 52820 | C2: =B2*3% -> 1584.6 | D2: =B2-C2 -> 51235.4 | E2: =B2*2% -> 1056.4 | F2: =D2-E2 -> 50179
A3: Total | B3: =SUM(B2) -> 52820 | D3: =SUM(D2) -> 51235.4 | F3: =SUM(F2) -> 50179

Sheet Brand Activation
A1: Date | B1: Brand Name | C1: Amount | D1: Type of collab
A2: 28-29 Mar | B2: Truebasics | C2: 15000 | D2: Event Partner
A3: 28-29 Mar | B3: My love Triangle | C3: 2000 | D3: Event Partner
A4: 28-29 Mar | B4: Snackfax | C4: 1000 | D4: Event Partner
A5: Total | C5: =SUM(C2:C4) -> 18000
