Workbook

Sheet Summary
B2: Date: 1 - 28 Feb
B3: Particulars | C3: Amount
B4: Offline | C4: =SUM(C5,C6,C7,, C8) -> 36605
B5: Rentals | C5: ='Offline & RG Community'!G30 -> 12630
B6: F&B | C6: ='Offline & RG Community'!H30 -> 3615
B7: Product Sales | C7: 0
B8: Bookings | C8: ='Offline & RG Community'!E30 -> 20360
B9: Online: Third Party Platform | C9: =SUM(C10:C14) -> 106075
B10: Hudle | C10: =Hudle!C3 -> 53245
B11: Playo | C11: =Playo!C5 -> 14830
B12: District | C12: =District!C4 -> 35200
B13: Khelomore | C13: =Khelomore!C4 -> 2800
B14: Zplys | C14: 0
B15: Community | C15: =SUM(C16:C19) -> 54550
B16: Courtly (Organized by RallyGully) | C16: 0
B17: Sportomic (Organized by RallyGully) | C17: =Sportomic!C2 -> 34100
B18: Rallygully Community games | C18: ='Offline & RG Community'!F30 -> 20450
B19: Misfits Community | C19: 0
B20: Memberships | C20: =Membership!E3 -> 50000
B21: Coaching | C21: =16500 -> 16500
B22: Corporate Events | C22: 0
B23: Brand Activation | C23: =0 -> 0
B24: Other Income | C24: 0
B25: Total Gross Revenue | C25: =sum(C4,C9,C20,C22,C23,C24,C15, C21) -> 263730
B26: Total Net Revenue (Post Commissions) | C26: ='Offline & RG Community'!I30+Hudle!E3+Playo!F5+District!F4+Khelomore!E4+Sportomic!C2+Membership!E3 -> 238070.94
B27: Total Revenue post GST | C27: =C26/1.18 -> 201755.03

Sheet Offline & RG Community
A1: Date | B1: Day | C1: Offline booking hours | D1: Discount Given | E1: Booking Revenue | F1: Community Revenue | G1: Paddle Rental | H1: F&B | I1: Total Revenue
A2: 46054 | B2: Sunday | C2: 0 | D2: 10% and 0% | E2: 0 | F2: 0 | G2: 30 | H2: 0 | I2: =sum(E2:H2) -> 30
A3: 46055 | B3: Monday | C3: 1 | D3: 10% and 0% | E3: 720 | F3: 0 | G3: 350 | H3: 0 | I3: =sum(E3:H3) -> 1070
A4: 46056 | B4: Tuesday | C4: 4 | D4: 10% and 0% | E4: 0 | F4: 3000 | G4: 500 | H4: 0 | I4: =sum(E4:H4) -> 3500
A5: 46057 | B5: Wednesday | C5: 2 | D5: 10% and 0% | E5: 0 | F5: 1400 | G5: 350 | H5: 0 | I5: =sum(E5:H5) -> 1750
A6: 46058 | B6: Thursday | C6: 4.5 | D6: 10% and 0% | E6: 1920 | F6: 1000 | G6: 150 | H6: 0 | I6: =sum(E6:H6) -> 3070
A7: 46059 | B7: Friday | C7: 3.5 | D7: 10% and 0% | E7: 2720 | F7: 0 | G7: 900 | H7: 280 | I7: =sum(E7:H7) -> 3900
A8: 46060 | B8: Saturday | C8: 2.5 | D8: 10% and 0% | E8: 400 | F8: 1200 | G8: 1150 | H8: 420 | I8: =sum(E8:H8) -> 3170
A9: 46061 | B9: Sunday | C9: 0.5 | D9: 10% and 0% | E9: 400 | F9: 0 | G9: 1000 | H9: 280 | I9: =sum(E9:H9) -> 1680
A10: 46062 | B10: Monday | C10: 1.5 | D10: 10% and 0% | E10: 1200 | F10: 0 | G10: 300 | H10: 385 | I10: =sum(E10:H10) -> 1885
A11: 46063 | B11: Tuesday | C11: 0 | D11: 10% and 0% | E11: 0 | F11: 0 | G11: 0 | H11: 70 | I11: =sum(E11:H11) -> 70
A12: 46064 | B12: Wednesday | C12: 0.5 | D12: 10% and 0% | E12: 400 | F12: 0 | G12: 550 | H12: 0 | I12: =sum(E12:H12) -> 950
A13: 46065 | B13: Thursday | C13: 0 | D13: 10% and 0% | E13: 0 | F13: 0 | G13: 100 | H13: 70 | I13: =sum(E13:H13) -> 170
... A29: 46081 | B29: Saturday | C29: 0 | D29: 10% and 0% | E29: 0 | F29: 0 | G29: 1200 | H29: 0 | I29: =sum(E29:H29) -> 1200
A30: Total | C30: =SUM(C2:C29) -> 50 | E30: =SUM(E2:E29) -> 20360 | F30: =SUM(F2:F29) -> 20450 | G30: =SUM(G2:G29) -> 12630 | H30: =SUM(H2:H29) -> 3615 | I30: =SUM(I2:I29) -> 57055

Sheet Hudle
A1: Link | B1: Date | C1: Paid to Hudle | D1: Commisions (Including GST) | E1: Net Revenue | F1: TDS | G1: TCS | H1: Amount
B2: 1 - 28 Feb | C2: 53245 | D2: 6957.6 | E2: =C2-D2 -> 46287.4 | F2: 45.35 | G2: 226.77 | H2: 46290.25
B3: Total | C3: =SUM(C2) -> 53245 | E3: =SUM(E2) -> 46287.4 | H3: =SUM(H2) -> 46290.25

Sheet Playo
A1: Link | B1: Date | C1: Paid to Playo (₹) | D1: Commissions (₹) | E1: GST (₹) | F1: Net Revenue | G1: TDS (₹) | H1: TCS (₹) | I1: Final Amount (₹)
B2: 3 - 6 Feb | C2: 3900 | D2: 273 | E2: 49.14 | F2: =C2-D2-E2 -> 3577.86 | G2: 3.9 | H2: 19.5 | I2: 3554.46
B3: 9 -14 Feb | C3: 4630 | D3: 329 | E3: 59.22 | F3: =C3-D3-E3 -> 4241.78 | G3: 4.63 | H3: 23.15 | I3: 4214
B4: 15 - 28 Feb | C4: 6300 | D4: 441 | E4: 79.38 | F4: =C4-D4-E4 -> 5779.62 | G4: 31.5 | H4: 6.3 | I4: 5741.82
B5: Total | C5: =SUM(C2:C4) -> 14830 | F5: =SUM(F2:F4) -> 13599.26 | I5: =SUM(I2:I4) -> 13510.28

Sheet District
A1: Link | B1: Date | C1: Paid to District | D1: Commissions (₹) | E1: GST on Commission | F1: Net Revenue | G1: TCS | H1: TDS | I1: Final Amount (₹)
B2: 1 - 15 Feb | C2: 19200 | D2: 384 | E2: 69.12 | F2: =C2-D2-E2 -> 18746.88 | G2: 96 | H2: 19.2 | I2: 18631.68
B3: 16 - 28 Feb | C3: 16000 | D3: 320 | E3: 57.6 | F3: =C3-D3-E3 -> 15622.4 | G3: 80 | H3: 13.64 | I3: 15526.4
B4: Total | C4: =SUM(C2:C3) -> 35200 | F4: =SUM(F2:F3) -> 34369.28 | I4: =SUM(I2:I3) -> 34158.08

Sheet Khelomore
A1: Link | B1: Date | C1: Paid to Khelomore (₹) | D1: Commissions (₹) | E1: Final Amount (₹)
B2: 46065 | C2: 1600 | D2: =C2*5% -> 80 | E2: =C2-D2 -> 1520
B3: 46070 | C3: 1200 | D3: =C3*5% -> 60 | E3: =C3-D3 -> 1140
B4: Total | C4: =SUM(C2:C3) -> 2800 | E4: =SUM(E2:E3) -> 2660

Sheet Sportomic
A1: Link | B1: Date | C1: Paid to Sportomic (₹)
B2: 1 - 28 Feb | C2: 34100

Sheet Coaching
A1: Sports Type | B1: Coaching Type | C1: Start Date | D1: Amount Collected
A2: Pickleball | B2: Adult | C2: FEB | D2: =16500 -> 16500

Sheet Membership
A1: Member Name | B1: Sports Type | C1: Membership Type | D1: Start Date | E1: Amount Collected
A2: Sahil | B2: Pickleball | C2: Grand slam (90) | D2: 46077 | E2: 50000
A3: Total | E3: =SUM(E2) -> 50000
