Workbook

Sheet Summary
B2: Date: 1 - 31 Mar
B3: Particulars | C3: Amount
B4: Offline | C4: =SUM(C5,C6,C7,, C8) -> 29635
B5: Rentals | C5: ='Offline & RG Community'!G33 -> 0
B6: F&B | C6: 0
B7: Product Sales | C7: 0
B8: Bookings | C8: ='Offline & RG Community'!E33 -> 29635
B9: Online: Third Party Platform | C9: =SUM(C10:C14) -> 39125
B10: Hudle | C10: =Hudle!C4 -> 6350
B11: Playo | C11: =Playo!C2 -> 25760
B12: District | C12: 0
B13: Khelomore | C13: =Khelomore!C3 -> 7015
B14: Zplys | C14: 0
B15: Community | C15: =SUM(C16:C19) -> 0
B16: Courtly (Organized by RallyGully) | C16: 0
B17: Sportomic (Organized by RallyGully) | C17: 0
B18: Rallygully Community games | C18: ='Offline & RG Community'!F33 -> 0
B19: Misfits Community | C19: 0
B20: Memberships | C20: 0
B21: Coaching | C21: 0
B22: Corporate Events | C22: 0
B23: Brand Activation | C23: =0 -> 0
B24: Other Income | C24: ='Other Income'!C2 -> 118000
B25: Total Gross Revenue | C25: =sum(C4,C9,C20,C22,C23,C24,C15, C21) -> 186760
B26: Total Net Revenue (Post Commissions) | C26: =Khelomore!E3+'Other Income'!C2+'Offline & RG Community'!H33+Playo!F2+Hudle!E4 -> 183544.37
B27: Total Revenue post GST | C27: =C26/1.18 -> 155546.08

Sheet Offline & RG Community
A1: Date | B1: Day | C1: Offline booking hours | D1: Discount Given | E1: Booking Revenue | F1: Community Revenue | G1: Paddle Rental | H1: Total Revenue
A2: 1 Mar | B2: Sunday | C2: 0 | D2: 20% and 25% | E2: 0 | F2: 0 | G2: 0 | H2: =sum(E2:G2) -> 0
A3: 2 Mar | B3: Monday | C3: 0 | D3: 20% and 25% | E3: 0 | F3: 0 | G3: 0 | H3: =sum(E3:G3) -> 0
A4: 3 Mar | B4: Tuesday | C4: 0 | D4: 20% and 25% | E4: 0 | F4: 0 | G4: 0 | H4: =sum(E4:G4) -> 0
A5: 4 Mar | B5: Wednesday | C5: 0 | D5: 20% and 25% | E5: 0 | F5: 0 | G5: 0 | H5: =sum(E5:G5) -> 0
A6: 5 Mar | B6: Thursday | C6: 0 | D6: 20% and 25% | E6: 0 | F6: 0 | G6: 0 | H6: =sum(E6:G6) -> 0
A7: 6 Mar | B7: Friday | D7: 20% and 25% | H7: =sum(E7:G7) -> 0
A8: 7 Mar | B8: Saturday | C8: 2 | D8: 20% and 25% | E8: 2000 | F8: 0 | G8: 0 | H8: =sum(E8:G8) -> 2000
A9: 8 Mar | B9: Sunday | C9: 3 | D9: 20% and 25% | E9: 3095 | F9: 0 | G9: 0 | H9: =sum(E9:G9) -> 3095
A10: 9 Mar | B10: Monday | D10: 20% and 25% | H10: =sum(E10:G10) -> 0
A11: 10 Mar | B11: Tuesday | D11: 20% and 25% | H11: =sum(E11:G11) -> 0
A12: 11 Mar | B12: Wednesday | D12: 20% and 25% | H12: =sum(E12:G12) -> 0
A13: 12 Mar | B13: Thursday | C13: 1 | D13: 20% and 25% | E13: 700 | F13: 0 | G13: 0 | H13: =sum(E13:G13) -> 700
A14: 13 Mar | B14: Friday | D14: 20% and 25% | H14: =sum(E14:G14) -> 0
A15: 14 Mar | B15: Saturday | C15: 2 | D15: 20% and 25% | E15: 1400 | F15: 0 | G15: 0 | H15: =sum(E15:G15) -> 1400
A16: 15 Mar | B16: Sunday | C16: 1 | D16: 20% and 25% | E16: 400 | F16: 0 | G16: 0 | H16: =sum(E16:G16) -> 400
A17: 16 Mar | B17: Monday | D17: 20% and 25% | H17: =sum(E17:G17) -> 0
A18: 17 Mar | B18: Tuesday | D18: 20% and 25% | H18: =sum(E18:G18) -> 0
A19: 18 Mar | B19: Wednesday | D19: 20% and 25% | H19: =sum(E19:G19) -> 0
A20: 19 Mar | B20: Thursday | D20: 20% and 25% | H20: =sum(E20:G20) -> 0
A21: 20 Mar | B21: Friday | D21: 20% and 25% | H21: =sum(E21:G21) -> 0
A22: 21 Mar | B22: Saturday | D22: 20% and 25% | H22: =sum(E22:G22) -> 0
A23: 22 Mar | B23: Sunday | C23: 2 | D23: 20% and 25% | E23: 760 | F23: 0 | G23: 0 | H23: =sum(E23:G23) -> 760
A24: 23 Mar | B24: Monday | C24: 4 | D24: 20% and 25% | E24: 2400 | F24: 0 | G24: 0 | H24: =sum(E24:G24) -> 2400
A25: 24 Mar | B25: Tuesday | D25: 20% and 25% | H25: =sum(E25:G25) -> 0
A26: 25 Mar | B26: Wednesday | D26: 20% and 25% | H26: =sum(E26:G26) -> 0
A27: 26 Mar | B27: Thursday | C27: 4.5 | D27: 20% and 25% | E27: 4030 | F27: 0 | G27: 0 | H27: =sum(E27:G27) -> 4030
A28: 27 Mar | B28: Friday | C28: 3.5 | D28: 20% and 25% | E28: 4300 | F28: 0 | G28: 0 | H28: =sum(E28:G28) -> 4300
A29: 28 Mar | B29: Saturday | C29: 4 | D29: 20% and 25% | E29: 5800 | F29: 0 | G29: 0 | H29: =sum(E29:G29) -> 5800
A30: 29 Mar | B30: Sunday | C30: 1 | D30: 20% and 25% | E30: 1200 | F30: 0 | G30: 0 | H30: =sum(E30:G30) -> 1200
A31: 30 Mar | B31: Monday | C31: 3 | D31: 20% and 25% | E31: 3550 | F31: 0 | G31: 0 | H31: =sum(E31:G31) -> 3550
A32: 31 Mar | B32: Tuesday | D32: 20% and 25% | H32: =SUM(E32:G32) -> 0
A33: Total | C33: =SUM(C1:C32) -> 31 | E33: =SUM(E1:E32) -> 29635 | F33: =SUM(F1:F32) -> 0 | G33: =SUM(G1:G32) -> 0 | H33: =SUM(H1:H32) -> 29635

Sheet Hudle
A1: Link | B1: Date | C1: Paid to Hudle | D1: Commisions (Including GST) | E1: Net Revenue | F1: TDS | G1: TCS | H1: Amount
B2: 1 - 23 Mar | C2: 2850 | D2: 373.1 | E2: =C2-D2 -> 2476.9 | F2: 2.43 | G2: 12.16 | H2: 2482.3
B3: 23 - 31 Mar | C3: 3500 | D3: 364 | E3: =C3-D3 -> 3136 | F3: 2.37 | G3: 11.86 | H3: 2421.76
B4: Total | C4: =SUM(C2:C3) -> 6350 | E4: =SUM(E2:E3) -> 5612.9 | H4: =SUM(H2:H3) -> 4904.06

Sheet Playo
A1: Link | B1: Date | C1: Paid to Playo (₹) | D1: Commissions (₹) | E1: GST (₹) | F1: Net Revenue | G1: TDS (₹) | H1: TCS (₹) | I1: Final Amount (₹)
B2: 1 - 31 Mar | C2: 25760 | D2: =C2*7% -> 1803.2 | E2: =D2*18% -> 324.576 | F2: =C2-D2-E2 -> 23632.224 | G2: =F2*2% -> 472.64448 | H2: 0 | I2: =F2-G2 -> 23159.58

Sheet Khelomore
A1: Link | B1: Date | C1: Paid to Khelomore (₹) | D1: Commissions (₹) | E1: Final Amount (₹)
B2: 1 - 31 Mar | C2: 7015 | D2: =C2*5% -> 350.75 | E2: =C2-D2 -> 6664.25
B3: Total | C3: =SUM(C2) -> 7015 | E3: =SUM(E2) -> 6664.25

Sheet Other Income
A1: Month | B1: Sports Type | C1: Amount Collected
A2: Mar | B2: Padel Operations & Management Fees | C2: 118000
