Workbook

Sheet Summary
B2: Date: 1st - 30th Nov
B3: Particulars | C3: Amount
B4: Offline | C4: =SUM(C5,C6,C7,C8) -> 24530
B5: Rentals | C5: ='Offline & RG Community'!G32 -> 6750
B6: F&B | C6: 0
B7: Product Sales | C7: 0
B8: Bookings | C8: ='Offline & RG Community'!E32 -> 17780
B9: Online: Third Party Platform | C9: =SUM(C10:C13) -> 104113.82
B10: Hudle | C10: =Hudle!C7 -> 91800
B11: Playo | C11: =Playo!C6 -> 6600
B12: District | C12: =District!C2 -> 2329.82
B13: Khelomore | C13: =Khelomore!C4 -> 3384
B14: Community | C14: =SUM(C15,C16,C17) -> 14200
B15: Courtly | C15: =Courtly!C2 -> 3500
B16: Rallygully Community games | C16: ='Offline & RG Community'!F32 -> 7100 | F16: Income : 136,700/-
B17: Misfits Community | C17: =Misfits!C2 -> 3600
B18: Memberships | C18: 0 | F18: Expenses : 45,500/-
B19: Corporate Events | C19: 0
B20: Brand Activation | C20: 0 | F20: Net income : 91,200/- 59,000/- + 32,000/-
B21: Other Income | C21: ='Other Income'!E2 -> 7000
B22: Total Gross Revenue | C22: =sum(C4,C9,C14,C18,C19,C20,C21) -> 149843.82 | F22: 59,000/- + 45,000/- = 104,000/-
B23: Total Net Revenue (Post Commissions) | C23: =sum('Offline & RG Community'!H32,Hudle!E7,Playo!F6,District!C2,Khelomore!E4,Misfits!D2,Courtly!F2,'Other Income'!E2) -> 136368.46
B24: Total Revenue post GST | C24: =C23/1.18 -> 115566.49
B25: Expenses | G25: 45500 | I25: 45543
B26: Venue Manager + Cleaner | C26: 30500
B27: Marketing, Branding & Community | C27: 15000
B28: Total Expenses | C28: =C26+C27 -> 45500 | G28: 45543 | I28: =G31 -> 28457
B29: Net Profit (Revenue - Expenses) | C29: =C24-C28 -> 70066.492 | E29: 45.5 + .74 +5 | G29: 4000 | I29: 4000
G30: =G25+G28+G29 -> 95043
B31: School's Profit Share (65%) | C31: =C29*65% -> 45543.219 | G31: =74000-G28 -> 28457
B32: RallyGully's Profit Share (35%) | C32: =C29*35% -> 24523.272 | G32: =G30+G31 -> 123500

Sheet Offline & RG Community
A1: Date | B1: Day | C1: Offline booking hours | D1: Discount Given | E1: Booking Revenue | F1: Community Revenue | G1: Paddle Rental | H1: Total Revenue
A2: 45962 | B2: Saturday | C2: 0 | D2: 0 | E2: 0 | F2: 0 | G2: 200 | H2: =SUM(E2:G2) -> 200
A3: 45963 | B3: Sunday | C3: 3.5 | D3: 0 | E3: 3760 | F3: 1200 | G3: 600 | H3: =SUM(E3:G3) -> 5560
A4: 45964 | B4: Monday | C4: 0 | D4: 0 | E4: 0 | F4: 0 | G4: 500 | H4: =SUM(E4:G4) -> 500
A5: 45965 | B5: Tuesday | C5: 0 | D5: 0 | E5: 0 | F5: 0 | G5: 400 | H5: =SUM(E5:G5) -> 400
A6: 45966 | B6: Wednesday | C6: 4 | D6: 0 | E6: 600 | F6: 900 | G6: 0 | H6: =SUM(E6:G6) -> 1500
A7: 45967 | B7: Thursday | C7: 1 | D7: 0 | E7: 600 | F7: 0 | G7: 0 | H7: =SUM(E7:G7) -> 600
A8: 45968 | B8: Friday | C8: 0 | D8: 0 | E8: 0 | F8: 0 | G8: 200 | H8: =SUM(E8:G8) -> 200
A9: 45969 | B9: Saturday | C9: 0 | D9: 0 | E9: 0 | F9: 0 | G9: 0 | H9: =SUM(E9:G9) -> 0
A10: 45970 | B10: Sunday | C10: 0 | D10: 0 | E10: 0 | F10: 0 | G10: 400 | H10: =SUM(E10:G10) -> 400
A11: 45971 | B11: Monday | C11: 1 | D11: 0 | E11: 1080 | F11: 0 | G11: 400 | H11: =SUM(E11:G11) -> 1480
A12: 45972 | B12: Tuesday | C12: 1 | D12: 0 | E12: 1080 | F12: 0 | G12: 800 | H12: =SUM(E12:G12) -> 1880
A13: 45973 | B13: Wednesday | C13: 0 | D13: 0 | E13: 0 | F13: 0 | G13: 0 | H13: =SUM(E13:G13) -> 0
... A31: 45991 | B31: Sunday | C31: 1 | D31: 0 | E31: 1200 | F31: 0 | G31: 1050 | H31: =SUM(E31:G31) -> 2250
A32: Total | C32: =SUM(C2:C31) -> 23.5 | E32: =SUM(E2:E31) -> 17780 | F32: =SUM(F2:F31) -> 7100 | G32: =SUM(G2:G31) -> 6750 | H32: =SUM(H2:H31) -> 31630

Sheet Hudle
A1: Link | B1: Date | C1: Paid to Hudle | D1: Commisions (Including GST) | E1: Net Revenue | F1: TDS | G1: TCS | H1: Amount
B2: 1 - 10 Nov | C2: 32100 | D2: 4173 | E2: =C2-D2 -> 27927 | F2: 27.2 | G2: 136 | H2: =E2-F2-G2 -> 27763.8
B3: 11 - 18 Nov | C3: 13700 | D3: 1781 | E3: =C3-D3 -> 11919 | F3: 11.6 | G3: 58 | H3: =E3-F3-G3 -> 11849.4
B4: 18 - 25 Nov | C4: 28000 | D4: 3640 | E4: =C4-D4 -> 24360 | F4: 23.7 | G4: 118.64 | H4: =E4-F4-G4 -> 24217.66
B5: 25 - 30 Nov | C5: 18000 | D5: 2340 | E5: =C5-D5 -> 15660 | F5: 15.25 | G5: 76.27 | H5: =E5-F5-G5 -> 15568.48
C7: =SUM(C2:C6) -> 91800 | E7: =SUM(E2:E6) -> 79866 | H7: =SUM(H2:H6) -> 79399.34

Sheet Playo
A1: Link | B1: Date | C1: Paid to Playo (₹) | D1: Commissions (₹) | E1: GST (₹) | F1: Net Revenue | G1: TDS (₹) | H1: TCS (₹) | I1: Final Amount (₹)
B2: 1 - 30 Nov | C2: 6600 | D2: 462 | E2: 83.16 | F2: =C2-D2-E2 -> 6054.84 | G2: 6.6 | H2: 33 | I2: 6015.23
C6: =SUM(C2:C4) -> 6600 | F6: =SUM(F2:F4) -> 6054.84 | I6: =SUM(I2:I4) -> 6015.23

Sheet District
A1: Link | B1: Date | C1: Paid to District | D1: Commissions (₹) | E1: Final Amount (₹)
B2: 1 - 30 Nov | C2: 2329.82 | D2: 0 | E2: 2329.82

Sheet Khelomore
A1: Link | B1: Date | C1: Paid to Khelomore (₹) | D1: Commissions (₹) | E1: Final Amount (₹)
B2: 1 - 20 Nov | C2: 984 | D2: 49.2 | E2: =C2-D2 -> 934.8
B3: 20 - 30 Nov | C3: 2400 | D3: 122 | E3: =C3-D3 -> 2278
C4: =SUM(C2:C3) -> 3384 | D4: =SUM(D2:D3) -> 171.2 | E4: =SUM(E2:E3) -> 3212.8

Sheet Misfits
A1: Link | B1: Date | C1: Paid to Misfits (₹) | D1: Post Comission (20%) | E1: TDS | F1: Final Amount (₹)
B2: 1 - 30 Nov | C2: 3600 | D2: 2880 | E2: 57.6 | F2: 2822.4

Sheet Courtly
A1: Link | B1: Date | C1: Paid to Courtly (₹) | D1: Comission (3%) | E1: TDS | F1: Final Amount (₹)
B2: 45980 | C2: 3500 | D2: 105 | F2: 3395

Sheet Memberships
A1: Member Name | B1: Sports Type | C1: Membership Type | D1: Start Date | E1: Amount Collected

Sheet Other Income
A1: Coaching | B1: Sports | C1: Type | D1: Start Date | E1: Amount Collected
B2: Pickleball | C2: Adult | D2: 45986 | E2: 7000

Sheet Brand Activation
A1: Date & Day | B1: Brand Name | C1: Amount | D1: Timings | E1: Type of collab
