Workbook

Sheet Summary
B2: 1 - 31 Aug
B3: Particulars | C3: Amount
C4: Pickleball
B5: Pay & Play | C5: =sum(C6,C12) -> 82414
B6: Online | C6: =sum(C7:C11) -> 74519
B7: District | C7: =District!C4 -> 43069
B8: Hudle | C8: =Hudle!C3 -> 12250
B9: Playo | C9: =Playo!C3 -> 9175
B10: Khelomore | C10: =Khelomore!B4 -> 10025
B11: Zplys | C11: 0
B12: Offline | C12: =sum(C13:C14) -> 7895
B13: Bookings | C13: ='Offline & RG Community'!D33 -> 7895
B14: Memberships | C14: 0
B15: Community | C15: =sum(C16:C18) -> 0
B16: Pickup games | C16: =0 -> 0
B17: Social Events/Tournaments | C17: 0
B18: Community Partnerships | C18: 0
B19: Academy | C19: 0
B20: Events & Partnership | C20: =sum(C21,C22) -> 0
B21: Corporate events | C21: 0
B22: All B2B partnerships | C22: 0
B23: Commerce | C23: =sum(C24:C26) -> 13075
B24: Product rental | C24: ='Offline & RG Community'!F33 -> 13075
B25: Product sales | C25: 0
B26: F&B | C26: 0
B27: Other Income | C27: ='Other income'!C2 -> 120000
B28: Total Gross Revenue | C28: =C5+C15+C19+C23+C27 -> 215489
B29: GST (B) | C29: =C28-(C28/1.18) -> 32871.203
B30: Commissions, Payment gateway & Event Expense(C) | C30: ='Offline & RG Community'!H33+District!D4+District!E4+Hudle!D3+Playo!D3+Playo!E3+Khelomore!C4 -> 6829.225
B31: Net Revenue (A-B-C) | C31: =C28-C29-C30 -> 175788.57

Sheet Offline & RG Community
A1: Date | B1: Day | C1: Offline booking hours | D1: Booking Revenue | E1: Community Revenue | F1: Paddle Rental | G1: Total Revenue | H1: Payment Gateway | I1: Net Revenue
A2: 46235 | B2: Saturday | C2: 0 | D2: 0 | E2: 0 | F2: 200 | G2: =sum(D2:F2) -> 200 | H2: =G2*1.75% -> 3.5 | I2: =G2-H2 -> 196.5
A3: 46236 | B3: Sunday | C3: 0 | D3: 0 | E3: 0 | F3: 200 | G3: =sum(D3:F3) -> 200 | H3: =G3*1.75% -> 3.5 | I3: =G3-H3 -> 196.5
A4: 46237 | B4: Monday | C4: 0 | D4: 0 | E4: 0 | F4: 200 | G4: =sum(D4:F4) -> 200 | H4: =G4*1.75% -> 3.5 | I4: =G4-H4 -> 196.5
A5: 46238 | B5: Tuesday | C5: 0 | D5: 0 | E5: 0 | F5: 0 | G5: =sum(D5:F5) -> 0 | H5: =G5*1.75% -> 0 | I5: =G5-H5 -> 0
A6: 46239 | B6: Wednesday | C6: 0 | D6: 0 | E6: 0 | F6: 200 | G6: =sum(D6:F6) -> 200 | H6: =G6*1.75% -> 3.5 | I6: =G6-H6 -> 196.5
A7: 46240 | B7: Thursday | C7: 1 | D7: 698 | E7: 0 | F7: 0 | G7: =sum(D7:F7) -> 698 | H7: =G7*1.75% -> 12.215 | I7: =G7-H7 -> 685.785
A8: 46241 | B8: Friday | C8: 2 | D8: 1396 | E8: 0 | F8: 700 | G8: =sum(D8:F8) -> 2096 | H8: =G8*1.75% -> 36.68 | I8: =G8-H8 -> 2059.32
A9: 46242 | B9: Saturday | C9: 1.5 | D9: 998 | E9: 0 | F9: 325 | G9: =sum(D9:F9) -> 1323 | H9: =G9*1.75% -> 23.1525 | I9: =G9-H9 -> 1299.8475
A10: 46243 | B10: Sunday | C10: 1 | D10: 598 | E10: 0 | F10: 1600 | G10: =sum(D10:F10) -> 2198 | H10: =G10*1.75% -> 38.465 | I10: =G10-H10 -> 2159.535
A11: 46244 | B11: Monday | C11: 0 | D11: 0 | E11: 0 | F11: 0 | G11: =sum(D11:F11) -> 0 | H11: =G11*1.75% -> 0 | I11: =G11-H11 -> 0
A12: 46245 | B12: Tuesday | C12: 0 | D12: 0 | E12: 0 | F12: 0 | G12: =sum(D12:F12) -> 0 | H12: =G12*1.75% -> 0 | I12: =G12-H12 -> 0
A13: 46246 | B13: Wednesday | C13: 1 | D13: 360 | E13: 0 | F13: 150 | G13: =sum(D13:F13) -> 510 | H13: =G13*1.75% -> 8.925 | I13: =G13-H13 -> 501.075
... A32: 46265 | B32: Monday | C32: 0 | D32: 0 | E32: 0 | F32: 400 | G32: =sum(D32:F32) -> 400 | H32: =G32*1.75% -> 7 | I32: =G32-H32 -> 393
A33: Total | D33: =SUM(D1:D32) -> 7895 | E33: =SUM(E1:E32) -> 0 | F33: =SUM(F1:F32) -> 13075 | G33: =SUM(G1:G32) -> 20970 | H33: =SUM(H1:H32) -> 366.975 | I33: =SUM(I1:I32) -> 20603.025

Sheet District
A1: Link | B1: Date | C1: Paid to District | D1: Commissions (₹) | E1: GST on Commission | F1: Net Revenue | G1: TCS | H1: TDS | I1: Final Amount (₹)
B2: 1 - 31 Aug | C2: 43069 | D2: 3014 | E2: 542 | F2: =C2-D2-E2 -> 39513 | G2: 215 | H2: 43 | I2: =F2-G2-H2 -> 39255
B4: Total | C4: =SUM(C2:C3) -> 43069 | D4: =SUM(D2:D3) -> 3014 | E4: =SUM(E2:E3) -> 542 | F4: =SUM(F2:F3) -> 39513 | I4: =SUM(I2:I3) -> 39255

Sheet Hudle
A1: Link | B1: Date | C1: Paid to Hudle | D1: Commisions (Including GST) | E1: Net Revenue | F1: TDS | G1: TCS | H1: Amount
B2: 1 - 31 Aug | C2: 12250 | D2: 1631 | E2: =C2-D2 -> 10619 | F2: 10 | G2: 53 | H2: =E2-F2-G2 -> 10556
B3: Total | C3: =SUM(C2) -> 12250 | D3: =SUM(D2) -> 1631 | E3: =SUM(E2) -> 10619 | H3: =SUM(H2) -> 10556

Sheet Playo
A1: Link | B1: Date | C1: Paid to Playo (₹) | D1: Commissions (₹) | E1: GST (₹) | F1: Net Revenue | G1: TDS (₹) | H1: TCS (₹) | I1: Final Amount (₹)
B2: 1 - 31 Aug | C2: 9175 | D2: 656 | E2: 118 | F2: =C2-D2-E2 -> 8401 | G2: 9 | H2: 0 | I2: =F2-G2-H2 -> 8392
B3: Total | C3: =sum(C2) -> 9175 | D3: =sum(D2) -> 656 | E3: =sum(E2) -> 118 | F3: =sum(F2) -> 8401 | I3: =sum(I2) -> 8392

Sheet Khelomore
A1: Date | B1: Paid to Khelomore (₹) | C1: Commissions (₹) | D1: Final Amount (₹)
A2: 1 - 31 Aug | B2: 10025 | C2: =B2*5% -> 501.25 | D2: =B2-C2 -> 9523.75
A4: Total | B4: =SUM(B2) -> 10025 | C4: =SUM(C2) -> 501.25 | D4: =SUM(D2) -> 9523.75

Sheet Other income
A1: Month | B1: Sports Type | C1: Amount Collected
A2: Aug | B2: Football Management Operations | C2: 120000
