Workbook

Sheet Summary
B2: 1 - 30 April
B3: Particulars | C3: Amount
C4: Pickleball
B5: Pay & Play | C5: =sum(C6,C12) -> 84355
B6: Online | C6: =sum(C7:C11) -> 33095
B7: District | C7: =District!C4 -> 21550
B8: Hudle | C8: =Hudle!C4 -> 11545
B9: Playo | C9: 0
B10: Khelomore | C10: 0
B11: Zplys | C11: 0
B12: Offline | C12: =sum(C13:C14) -> 51260
B13: Bookings | C13: ='Offline & RG Community'!E32 -> 43760
B14: Memberships | C14: =Membership!E2 -> 7500
B15: Community | C15: =sum(C16:C17) -> 3600
B16: Pickup games | C16: ='Offline & RG Community'!F32 -> 3600
B17: Social Events/Tournaments | C17: 0
B18: Academy | C18: 0
B19: Events & Partnership | C19: =sum(C20,C21) -> 0
B20: Corporate events | C20: 0
B21: All B2B partnerships | C21: 0
B22: Commerce | C22: =sum(C23:C25) -> 7235
B23: Product rental | C23: ='Offline & RG Community'!G32 -> 6850
B24: Product sales | C24: 0
B25: F&B | C25: ='Offline & RG Community'!H32 -> 385
B26: Other Income | C26: 0
B27: Total Gross Revenue | C27: =C5+C15+C22+C18+C19+C26 -> 95190
B28: Total Net Revenue (Post Commissions) | C28: ='Offline & RG Community'!K32+Hudle!E4+District!F4+Membership!G2 -> 89173.678
B29: Total Revenue post GST | C29: =C28/1.18 -> 75570.913
B30: Investor's Share (40%) | C30: =C29*40% -> 30228.365

Sheet Offline & RG Community
A1: Date | B1: Day | C1: Offline booking hours | D1: Discount | E1: Booking Revenue | F1: Community | G1: Paddle Rental | H1: F&B | I1: Total Revenue | J1: Payment Gateway | K1: Net Revenue
A2: 1 Apr | B2: Wednesday | C2: 3 | D2: 10 and 20% | E2: 2160 | F2: 0 | G2: 250 | H2: 0 | I2: =sum(E2:H2) -> 2410 | J2: =I2*2.5%*1.18 -> 71.095 | K2: =I2-J2 -> 2338.905
A3: 2 Apr | B3: Thursday | C3: 6.5 | D3: 10 and 20% | E3: 4680 | F3: 0 | G3: 350 | H3: 0 | I3: =sum(E3:H3) -> 5030 | J3: =I3*2.5%*1.18 -> 148.385 | K3: =I3-J3 -> 4881.615
A4: 3 Apr | B4: Friday | C4: 0 | D4: 10 and 20% | E4: 0 | F4: 0 | G4: 0 | H4: 0 | I4: =sum(E4:H4) -> 0 | J4: =I4*2.5%*1.18 -> 0 | K4: =I4-J4 -> 0
A5: 4 Apr | B5: Saturday | C5: 1 | D5: 10 and 20% | E5: 360 | F5: 0 | G5: 100 | H5: 0 | I5: =sum(E5:H5) -> 460 | J5: =I5*2.5%*1.18 -> 13.57 | K5: =I5-J5 -> 446.43
A6: 5 Apr | B6: Sunday | C6: 2.5 | D6: 10 and 20% | E6: 1800 | F6: 0 | G6: 0 | H6: 0 | I6: =sum(E6:H6) -> 1800 | J6: =I6*2.5%*1.18 -> 53.1 | K6: =I6-J6 -> 1746.9
A7: 6 Apr | B7: Monday | C7: 1 | D7: 10 and 20% | E7: 720 | F7: 0 | G7: 100 | H7: 0 | I7: =sum(E7:H7) -> 820 | J7: =I7*2.5%*1.18 -> 24.19 | K7: =I7-J7 -> 795.81
A8: 7 Apr | B8: Tuesday | C8: 1 | D8: 10 and 20% | E8: 720 | F8: 0 | G8: 200 | H8: 0 | I8: =sum(E8:H8) -> 920 | J8: =I8*2.5%*1.18 -> 27.14 | K8: =I8-J8 -> 892.86
A9: 8 Apr | B9: Wednesday | C9: 3.5 | D9: 10 and 20% | E9: 1520 | F9: 0 | G9: 150 | H9: 0 | I9: =sum(E9:H9) -> 1670 | J9: =I9*2.5%*1.18 -> 49.265 | K9: =I9-J9 -> 1620.735
A10: 9 Apr | B10: Thursday | C10: 1 | D10: 10 and 20% | E10: 720 | F10: 600 | G10: 350 | H10: 0 | I10: =sum(E10:H10) -> 1670 | J10: =I10*2.5%*1.18 -> 49.265 | K10: =I10-J10 -> 1620.735
A11: 10 Apr | B11: Friday | C11: 2.5 | D11: 10 and 20% | E11: 1800 | F11: 0 | G11: 100 | H11: 0 | I11: =sum(E11:H11) -> 1900 | J11: =I11*2.5%*1.18 -> 56.05 | K11: =I11-J11 -> 1843.95
A12: 11 Apr | B12: Saturday | C12: 2.5 | D12: 10 and 20% | E12: 1800 | F12: 1400 | G12: 650 | H12: 0 | I12: =sum(E12:H12) -> 3850 | J12: =I12*2.5%*1.18 -> 113.575 | K12: =I12-J12 -> 3736.425
A13: 12 Apr | B13: Sunday | C13: 3.5 | D13: 10 and 20% | E13: 3580 | F13: 600 | G13: 450 | H13: 0 | I13: =sum(E13:H13) -> 4630 | J13: =I13*2.5%*1.18 -> 136.585 | K13: =I13-J13 -> 4493.415
... A16: 15 Apr | B16: Wednesday | C16: 1.5 | D16: 10 and 20% | E16: 1080 | F16: 0 | G16: 200 | H16: 70 | I16: =sum(E16:H16) -> 1350 | J16: =I16*2.5%*1.18 -> 39.825 | K16: =I16-J16 -> 1310.175
A17: 16 Apr | B17: Thursday | C17: 2 | D17: 10 and 20% | E17: 1420 | F17: 200 | G17: 350 | H17: 70 | I17: =SUM(E17:H17) -> 2040 | J17: =I17*2.5%*1.18 -> 60.18 | K17: =I17-J17 -> 1979.82
A18: 17 Apr | B18: Friday | C18: 0 | D18: 10 and 20% | E18: 0 | F18: 0 | G18: 0 | H18: 0 | I18: =SUM(E18:H18) -> 0 | J18: =I18*2.5%*1.18 -> 0 | K18: =I18-J18 -> 0
A19: 18 Apr | B19: Saturday | C19: 0 | D19: 10 and 20% | E19: 0 | F19: 0 | G19: 250 | H19: 0 | I19: =SUM(E19:H19) -> 250 | J19: =I19*2.5%*1.18 -> 7.375 | K19: =I19-J19 -> 242.625
A20: 19 Apr | B20: Sunday | C20: 3 | D20: 10 and 20% | E20: 2160 | F20: 0 | G20: 450 | H20: 0 | I20: =SUM(E20:H20) -> 2610 | J20: =I20*2.5%*1.18 -> 76.995 | K20: =I20-J20 -> 2533.005
A21: 20 Apr | B21: Monday | C21: 2 | D21: 10 and 20% | E21: 1800 | F21: 0 | G21: 150 | H21: 0 | I21: =SUM(E21:H21) -> 1950 | J21: =I21*2.5%*1.18 -> 57.525 | K21: =I21-J21 -> 1892.475
A22: 21 Apr | B22: Tuesday | C22: 2 | D22: 10 and 20% | E22: 1440 | F22: 0 | G22: 150 | H22: 0 | I22: =SUM(F22:G22) -> 150 | J22: =I22*2.5%*1.18 -> 4.425 | K22: =I22-J22 -> 145.575
A23: 22 Apr | B23: Wednesday | C23: 1 | D23: 10 and 20% | E23: 720 | F23: 0 | G23: 50 | H23: 0 | I23: =sum(E23:H23) -> 770 | J23: =I23*2.5%*1.18 -> 22.715 | K23: =I23-J23 -> 747.285
A24: 23 Apr | B24: Thursday | C24: 3 | D24: 10 and 20% | E24: 3600 | F24: 0 | G24: 300 | H24: 35 | I24: =SUM(E24:H24) -> 3935 | J24: =I24*2.5%*1.18 -> 116.0825 | K24: =I24-J24 -> 3818.9175
A25: 24 Apr | B25: Friday | C25: 2 | D25: 10 and 20% | E25: 1520 | F25: 0 | G25: 0 | H25: 70 | I25: =SUM(E25:H25) -> 1590 | J25: =I25*2.5%*1.18 -> 46.905 | K25: =I25-J25 -> 1543.095
A26: 25 Apr | B26: Saturday | C26: 3 | D26: 10 and 20% | E26: 1800 | F26: 0 | G26: 600 | H26: 0 | I26: =SUM(E26:H26) -> 2400 | J26: =I26*2.5%*1.18 -> 70.8 | K26: =I26-J26 -> 2329.2
A27: 26 Apr | B27: Sunday | C27: 3 | D27: 10 and 20% | E27: 1800 | F27: 0 | G27: 350 | H27: 0 | I27: =SUM(E27:H27) -> 2150 | J27: =I27*2.5%*1.18 -> 63.425 | K27: =I27-J27 -> 2086.575
A28: 27 Apr | B28: Monday | C28: 3 | D28: 10 and 20% | E28: 1800 | F28: 0 | G28: 350 | H28: 70 | I28: =SUM(E28:H28) -> 2220 | J28: =I28*2.5%*1.18 -> 65.49 | K28: =I28-J28 -> 2154.51
A29: 28 Apr | B29: Tuesday | C29: 0 | D29: 10 and 20% | E29: 0 | F29: 0 | G29: 150 | H29: 0 | I29: =SUM(E29:H29) -> 150 | J29: =I29*2.5%*1.18 -> 4.425 | K29: =I29-J29 -> 145.575
A30: 29 Apr | B30: Wednesday | C30: 3 | D30: 10 and 20% | E30: 2160 | F30: 0 | G30: 200 | H30: 0 | I30: =SUM(E30:H30) -> 2360 | J30: =I30*2.5%*1.18 -> 69.62 | K30: =I30-J30 -> 2290.38
A31: 30 Apr | B31: Thursday | C31: 0 | D31: 10 and 20% | E31: 0 | F31: 0 | G31: 0 | H31: 0 | I31: =SUM(E31:H31) -> 0 | J31: =I31*2.5%*1.18 -> 0 | K31: =I31-J31 -> 0
A32: Total | C32: =SUM(C2:C31) -> 62.5 | E32: =SUM(E2:E31) -> 43760 | F32: =SUM(F2:F31) -> 3600 | G32: =SUM(G2:G31) -> 6850 | H32: =SUM(H2:H31) -> 385 | I32: =SUM(I2:I31) -> 53155 | J32: =SUM(J2:J31) -> 1568.0725 | K32: =SUM(K2:K31) -> 51586.927

Sheet Hudle
A1: Link | B1: Date | C1: Paid to Hudle | D1: Commisions (Including GST) | E1: Net Revenue | F1: TDS | G1: TCS | H1: Amount
B2: 1-28 Apr | C2: 11545 | D2: 1500 | E2: =C2-D2 -> 10045 | F2: 10 | G2: 49 | H2: 9985
B3: 28-30 Apr | C3: 0 | D3: 0 | E3: =C3-D3 -> 0 | F3: 0 | G3: 0 | H3: 0
B4: Total | C4: =SUM(C2:C3) -> 11545 | E4: =SUM(E2:E3) -> 10045 | H4: =SUM(H2:H3) -> 9985

Sheet District
A1: Link | B1: Date | C1: Paid to District | D1: Commissions (₹) | E1: GST on Commission | F1: Net Revenue | G1: TCS | H1: TDS | I1: Final Amount (₹)
B2: 1 - 30 Apr | C2: 21550 | D2: 1091 | E2: 196 | F2: =C2-D2-E2 -> 20263 | G2: 107 | H2: 21.55 | I2: 20133
B4: Total | C4: =SUM(C2:C3) -> 21550 | F4: =SUM(F2:F3) -> 20263 | I4: =SUM(I2:I3) -> 20133

Sheet Membership
A1: Member Name | B1: Sports Type | C1: Membership Type | D1: Start Date | E1: Amount Collected | F1: Payment Gateway | G1: Net Revenue
A2: Kavish | B2: Pickleball | C2: Rally Pack (15) | D2: 46113 | E2: 7500 | F2: =E2*2.5%*1.18 -> 221.25 | G2: =E2-F2 -> 7278.75
