Workbook

Sheet Summary
B2: Date: 1st - 30th Nov
B3: Particulars | C3: Amount
B4: Offline | C4: =SUM(C5,C6,C7,C8) -> 92435
B5: Rentals | C5: ='Offline & RG Community'!G32 -> 6595
B6: F&B | C6: 0
B7: Product Sales | C7: =0 -> 0
B8: Bookings | C8: ='Offline & RG Community'!E32 -> 85840
B9: Online: Third Party Platform | C9: =SUM(C10:C13) -> 20021.32
B10: Hudle | C10: =Hudle!C7 -> 18445
B11: Playo | C11: =Playo!C7 -> 800
B12: District | C12: =District!C2 -> 776.32
B13: Khelomore | C13: 0
B14: Community | C14: =sum(C15:C17) -> 9960
B15: Courtly | C15: =Courtly!C2 -> 2000
B16: Rallygully Community games | C16: ='Offline & RG Community'!F32 -> 3320
B17: Misfits Community | C17: =Misfits!C2 -> 4640
B18: Memberships | C18: =Membership!E4 -> 24380
B19: Corporate Events | C19: 0
B20: Brand Activation | C20: ='Brand Activation'!C2 -> 4480
B21: Other Income | C21: 0
B22: Total Gross Revenue | C22: =sum(C20,C18,C14,C9,C4) -> 151276.32
B23: Total Net Revenue (Post Commissions) | C23: =sum('Offline & RG Community'!H32,Hudle!E7,Playo!F7,District!C2,Misfits!D2,Courtly!F2,Membership!E4,'Brand Activation'!C2) -> 147817.89
B24: Total Revenue post GST | C24: =C23/1.18 -> 125269.4

Sheet Offline & RG Community
A1: Date | B1: Day | C1: Offline booking hours | D1: Discount Given | E1: Booking Revenue | F1: Community Revenue | G1: Paddle Rental | H1: Total Revenue
A2: 45962 | B2: Saturday | C2: 7.5 | D2: 25% B, 30% P | E2: 5170 | F2: 560 | G2: 600 | H2: =sum(E2:G2) -> 6330
A3: 45963 | B3: Sunday | C3: 6 | D3: 25% B, 30% P | E3: 4600 | F3: 0 | G3: 400 | H3: =sum(E3:G3) -> 5000
A4: 45964 | B4: Monday | C4: 1 | D4: 25% B, 30% P | E4: 560 | F4: 0 | G4: 100 | H4: =sum(E4:G4) -> 660
A5: 45965 | B5: Tuesday | C5: 4.5 | D5: 25% B, 30% P | E5: 2480 | F5: 0 | G5: 500 | H5: =sum(E5:G5) -> 2980
A6: 45966 | B6: Wednesday | C6: 4.5 | D6: 25% B, 30% P | E6: 2400 | F6: 1540 | G6: 0 | H6: =sum(E6:G6) -> 3940
A7: 45967 | B7: Thursday | C7: 0 | D7: 25% B, 30% P | E7: 0 | F7: 0 | G7: 100 | H7: =sum(E7:G7) -> 100
A8: 45968 | B8: Friday | C8: 3.5 | D8: 25% B, 30% P | E8: 2320 | F8: 0 | G8: 300 | H8: =sum(E8:G8) -> 2620
A9: 45969 | B9: Saturday | C9: 4 | D9: 25% B, 30% P | E9: 2450 | F9: 0 | G9: 300 | H9: =sum(E9:G9) -> 2750
A10: 45970 | B10: Sunday | C10: 4 | D10: 25% B, 30% P | E10: 2880 | F10: 0 | G10: 400 | H10: =sum(E10:G10) -> 3280
A11: 45971 | B11: Monday | C11: 3.5 | D11: 25% B, 30% P | E11: 3240 | F11: 0 | G11: 100 | H11: =sum(E11:G11) -> 3340
A12: 45972 | B12: Tuesday | C12: 2.5 | D12: 25% B, 30% P | E12: 1400 | F12: 0 | G12: 100 | H12: =sum(E12:G12) -> 1500
A13: 45973 | B13: Wednesday | C13: 2 | D13: 25% B, 30% P | E13: 1140 | F13: 0 | G13: 300 | H13: =sum(E13:G13) -> 1440
... A21: 45981 | B21: Thursday | C21: 3.5 | D21: 25% B, 30% P | E21: 1960 | F21: 0 | G21: 200 | H21: =sum(E21:G21) -> 2160
A22: 45982 | B22: Friday | C22: 1.5 | D22: 25% B, 30% P | E22: 2040 | F22: 0 | H22: =sum(E22:G22) -> 2040
A23: 45983 | B23: Saturday | C23: 4.5 | D23: 25% B, 30% P | E23: 3210 | F23: 0 | G23: 500 | H23: =sum(E23:G23) -> 3710
A24: 45984 | B24: Sunday | C24: 3 | D24: 25% B, 30% P | E24: 2320 | F24: 200 | G24: 400 | H24: =sum(E24:G24) -> 2920
A25: 45985 | B25: Monday | C25: 2 | D25: 25% B, 30% P | E25: 2400 | F25: 0 | G25: 0 | H25: =sum(E25:G25) -> 2400
A26: 45986 | B26: Tuesday | C26: 5 | D26: 25% B, 30% P | E26: 3370 | F26: 0 | G26: 20 | H26: =sum(E26:G26) -> 3390
A27: 45987 | B27: Wednesday | C27: 2 | D27: 25% B, 30% P | E27: 1120 | F27: 0 | G27: 100 | H27: =sum(E27:G27) -> 1220
A28: 45988 | B28: Thursday | C28: 3 | D28: 25% B, 30% P | E28: 3680 | F28: 0 | G28: 100 | H28: =sum(E28:G28) -> 3780
A29: 45989 | B29: Friday | C29: 2 | D29: 25% B, 30% P | E29: 2920 | F29: 0 | G29: 100 | H29: =sum(E29:G29) -> 3020
A30: 45990 | B30: Saturday | C30: 4 | D30: 25% B, 30% P | E30: 3370 | F30: 0 | G30: 400 | H30: =sum(E30:G30) -> 3770
A31: 45991 | B31: Sunday | C31: 5 | D31: 25% B, 30% P | E31: 2170 | F31: 180 | G31: 300 | H31: =sum(E31:G31) -> 2650
A32: Total | C32: =SUM(C2:C31) -> 115.5 | E32: =SUM(E2:E31) -> 85840 | F32: =SUM(F2:F31) -> 3320 | G32: =SUM(G2:G31) -> 6595 | H32: =SUM(H2:H31) -> 95755

Sheet Hudle
A1: Link | B1: Date | C1: Paid to Hudle | D1: Commisions (Including GST) | E1: Net Revenue | F1: TDS | G1: TCS | H1: Amount
B2: 1 - 10 Nov | C2: 4500 | D2: 585 | E2: =C2-D2 -> 3915 | F2: 3.81 | G2: 19.06 | H2: 3892.11
B3: 11 - 18 Nov | C3: 2560 | D3: 332.8 | E3: =C3-D3 -> 2227.2 | F3: 2.16 | G3: 10.84 | H3: 2214.8
B4: 18 - 25 Nov | C4: 6870 | D4: 899.6 | E4: =C4-D4 -> 5970.4 | F4: 5.8 | G4: 29.3 | H4: 5965.22
B5: 25 - 30 Nov | C5: 4515 | D5: 586.95 | E5: =C5-D5 -> 3928.05 | F5: 3.8 | G5: 19.13 | H5: 3905.09
C7: =SUM(C2:C5) -> 18445 | E7: =SUM(E2:E6) -> 16040.65 | H7: =SUM(H2:H6) -> 15977.22

Sheet Playo
A1: Link | B1: Date | C1: Paid to Playo (₹) | D1: Commissions (₹) | E1: GST (₹) | F1: Net Revenue | G1: TDS (₹) | H1: TCS (₹) | I1: Final Amount (₹)
B2: 1- 30 Nov | C2: 800 | D2: 56 | E2: 10.08 | F2: =C2 - D2-E2 -> 733.92 | G2: 0.8 | H2: 4 | I2: 729.12
F3: =C3 - D3-E3 -> 0
F4: =C4 - D4-E4 -> 0
F5: =C5 - D5-E5 -> 0
C7: =SUM(C2:C5) -> 800 | F7: =SUM(F2:F6) -> 733.92 | I7: =SUM(I2:I5) -> 729.12

Sheet District
A1: Link | B1: Date | C1: Paid to District | D1: Commissions (₹) | E1: Final Amount (₹)
B2: 1 - 30 Nov | C2: 776.32 | D2: 0

Sheet Khelomore
B1: Date | C1: Paid to Khelomore (₹) | D1: Commissions (₹) | E1: Final Amount (₹)
B2: 1 - 30 Nov | C2: 0
C4: =SUM(C2:C3) -> 0 | E4: =SUM(E2:E3) -> 0

Sheet Misfits
A1: Link | B1: Date | C1: Paid to Misfits (₹) | D1: Post Comission (20%) | E1: TDS | F1: Final Amount (₹)
B2: 1 - 30 Nov | C2: 4640 | D2: 3712 | E2: 74.12 | F2: =D2-E2 -> 3637.88

Sheet Courtly
A1: Link | B1: Date | C1: Paid to Courtly (₹) | D1: Comission (3%) | E1: TDS | F1: Final Amount (₹)
B2: 45980 | C2: 2000 | D2: 60 | F2: 1940

Sheet Membership
A1: Member Name | B1: Sports Type | C1: Membership Type | D1: Start Date | E1: Amount Collected
A2: Indian School of hospitality | B2: Pickle & Box | C2: Collab | D2: 45962 | E2: 18880
A3: Akshay | B3: Pickleball | C3: Rally Pack (15) | D3: 45978 | E3: 5500
A4: Total | E4: =SUM(E2:E3) -> 24380

Sheet Brand Activation
A1: Date & Day | B1: Brand Name | C1: Amount | D1: Timings | E1: Type of collab
A2: 20 Nov & Thu | B2: Selfmade | C2: 4480 | D2: 12-4 PM | E2: Brand Shoot
