Workbook

Sheet Summary
B2: 1 - 31 May
C3: Amount
B4: Particulars | C4: Total | D4: Pickleball | E4: Padel | F4: Turf | H4: Razorpay Collection Amount | I4: ='Offline & RG Community'!L34+'Social EventsTournament'!F2+'Social EventsTournament'!F3+'Corporate Events'!H4 -> 191092.32
B5: Pay & Play | C5: =sum(C6,C12) -> 363668 | D5: =sum(D6,D12) -> 91770 | E5: =sum(E6,E12) -> 64907 | F5: =sum(F6,F12) -> 206991 | H5: Cash | I5: =I4-172960 -> 18132.32
B6: Online | C6: =sum(C7:C11) -> 175870 | D6: =sum(D7:D11) -> 63403 | E6: =sum(E7:E11) -> 43024 | F6: =sum(F7:F11) -> 69443
B7: District | C7: =District!C3 -> 127314 | D7: =District!B5 -> 51713 | E7: =District!B7 -> 26245 | F7: =District!B6 -> 49356
B8: Hudle | C8: =Hudle!C5 -> 48556 | D8: =Hudle!B7 -> 11690 | E8: =Hudle!B9 -> 16779 | F8: =Hudle!B8 -> 20087
B9: Playo | C9: 0 | D9: 0 | E9: 0 | F9: 0
B10: Khelomore | C10: 0 | D10: 0 | E10: 0 | F10: 0
B11: Zplys | C11: 0 | D11: 0 | E11: 0 | F11: 0
B12: Offline | C12: =sum(C13:C14) -> 187798 | D12: =sum(D13:D14) -> 28367 | E12: =sum(E13:E14) -> 21883 | F12: =sum(F13:F14) -> 137548
B13: Bookings | C13: ='Offline & RG Community'!E34+'Offline & RG Community'!F34+'Offline & RG Community'!G34 -> 137798 | D13: ='Offline & RG Community'!E34 -> 28367 | E13: ='Offline & RG Community'!F34 -> 21883 | F13: ='Offline & RG Community'!G34 -> 87548
B14: Memberships | C14: =Memberships!E2 -> 50000 | D14: 0 | E14: 0 | F14: =Memberships!E2 -> 50000
B15: Community | C15: =sum(C16:C17) -> 34560 | D15: =sum(D16:D17) -> 0 | E15: =sum(E16:E17) -> 0 | F15: =sum(F16:F17) -> 34560
B16: Pickup games | C16: 0 | D16: 0 | E16: 0 | F16: 0
B17: Social Events/Tournaments | C17: ='Social EventsTournament'!D4 -> 34560 | D17: 0 | E17: 0 | F17: ='Social EventsTournament'!D4 -> 34560
B18: Academy | C18: =Academy!D2 -> 47200 | D18: 0 | E18: 0 | F18: =Academy!D2 -> 47200
B19: Events & Partnership | C19: =sum(C20,C21) -> 98663 | D19: =sum(D20,D21) -> 41202.5 | E19: =sum(E20) -> 0 | F19: =sum(F20,F21) -> 57460.5
B20: Corporate events | C20: ='Corporate Events'!F5 -> 83663 | D20: ='Corporate Events'!F4+'Corporate Events'!F3/2 -> 41202.5 | E20: 0 | F20: ='Corporate Events'!F2+'Corporate Events'!F3/2 -> 42460.5
B21: All B2B partnerships | C21: =B2B!D2 -> 15000 | D21: 0 | E21: 0 | F21: =B2B!D2 -> 15000
B22: Commerce | C22: =sum(C23:C25) -> 19150 | D22: =sum(D23:D25) -> 12225 | E22: =sum(E23:E25) -> 6925 | F22: =sum(F23:F25) -> 0
B23: Product rental | C23: ='Offline & RG Community'!H34+'Offline & RG Community'!I34-1200 -> 17950 | D23: ='Offline & RG Community'!H34 -> 12225 | E23: ='Offline & RG Community'!I34-1200 -> 5725 | F23: 0
B24: Product sales | C24: =600+600 -> 1200 | D24: 0 | E24: 1200 | F24: 0
B25: F&B | C25: 0 | D25: 0 | E25: 0 | F25: 0
B26: Other Income | C26: 0 | D26: 0 | E26: 0 | F26: 0
B27: Total Gross Revenue | C27: =sum(C5,C15,C18,C19,C22) -> 563241 | D27: =D5+D15+D22+D18+D19+D26 -> 145197.5 | E27: =E5+E15+E22+E18+E19+E26 -> 71832 | F27: =F5+F15+F22+F18+F19+F26 -> 346211.5
B28: Total Net Revenue (Post Commissions) | C28: ='Offline & RG Community'!L34+District!F3+Hudle!E5+Memberships!G2+B2B!D2+Academy!D2+'Social EventsTournament'!F4+'Corporate Events'!H5 -> 543571.32
B29: Total Revenue post GST | C29: =C28/1.18 -> 460653.66
B30: SD Vidya School's Share (60%) | C30: =C29*60% -> 276392.2
B31: RG & DPC's Share (40%) | C31: =C29*40% -> 184261.46

Sheet Offline & RG Community
A1: Date | B1: Day | C1: Offline booking hours | D1: Discount Given | F1: Booking Revenue | H1: Paddle Rental | I1: Padel Rental | J1: Total Revenue | K1: Payment Gateway | L1: Net Revenue
E2: Pickleball | F2: Padel | G2: Turf
A3: 46143 | B3: Friday | C3: 3 | D3: 20% and 25% | E3: 399 | F3: 0 | G3: 3999 | H3: 200 | I3: 500 | J3: =sum(E3:I3) -> 5098 | K3: =J3*1.75% -> 89.215 | L3: =J3-K3 -> 5008.785
A4: 46144 | B4: Saturday | C4: 7 | D4: 20% and 25% | E4: 600 | F4: 0 | G4: 10956 | H4: 650 | I4: 0 | J4: =sum(E4:I4) -> 12206 | K4: =J4*1.75% -> 213.605 | L4: =J4-K4 -> 11992.395
A5: 46145 | B5: Sunday | C5: 4.5 | D5: 20% and 25% | E5: 0 | F5: 1452 | G5: 7842 | H5: 300 | I5: 375 | J5: =sum(E5:I5) -> 9969 | K5: =J5*1.75% -> 174.4575 | L5: =J5-K5 -> 9794.5425
A6: 46146 | B6: Monday | C6: 5 | D6: 20% and 25% | E6: 2399 | F6: 2176 | G6: 0 | H6: 100 | I6: 225 | J6: =sum(E6:I6) -> 4900 | K6: =J6*1.75% -> 85.75 | L6: =J6-K6 -> 4814.25
A7: 46147 | B7: Tuesday | C7: 1.5 | D7: 20% and 25% | E7: 400 | F7: 1050 | G7: 0 | H7: 300 | I7: 400 | J7: =sum(E7:I7) -> 2150 | K7: =J7*1.75% -> 37.625 | L7: =J7-K7 -> 2112.375
A8: 46148 | B8: Wednesday | C8: 6 | D8: 20% and 25% | E8: 2496 | F8: 0 | G8: 5697 | H8: 200 | I8: 0 | J8: =sum(E8:I8) -> 8393 | K8: =J8*1.75% -> 146.8775 | L8: =J8-K8 -> 8246.1225
A9: 46149 | B9: Thursday | C9: 4.5 | D9: 20% and 25% | E9: 1800 | F9: 1575 | G9: 0 | H9: 650 | I9: 275 | J9: =sum(E9:I9) -> 4300 | K9: =J9*1.75% -> 75.25 | L9: =J9-K9 -> 4224.75
A10: 46150 | B10: Friday | C10: 7 | D10: 20% and 25% | E10: 3000 | F10: 0 | G10: 5547 | H10: 700 | I10: 0 | J10: =sum(E10:I10) -> 9247 | K10: =J10*1.75% -> 161.8225 | L10: =J10-K10 -> 9085.1775
A11: 46151 | B11: Saturday | C11: 7.5 | D11: 20% and 25% | E11: 1600 | F11: 0 | G11: 10195 | H11: 900 | I11: 200 | J11: =sum(E11:I11) -> 12895 | K11: =J11*1.75% -> 225.6625 | L11: =J11-K11 -> 12669.337
A12: 46152 | B12: Sunday | C12: 6 | D12: 20% and 25% | E12: 2397 | F12: 0 | G12: 3000 | H12: 1050 | I12: 300 | J12: =sum(E12:I12) -> 6747 | K12: =J12*1.75% -> 118.0725 | L12: =J12-K12 -> 6628.9275
A13: 46153 | B13: Monday | C13: 6 | D13: 20% and 25% | E13: 2298 | F13: 2200 | G13: 3230 | H13: =550+600 -> 1150 | I13: 750 | J13: =sum(E13:I13) -> 9628 | K13: =J13*1.75% -> 168.49 | L13: =J13-K13 -> 9459.51
A14: 46154 | B14: Tuesday | C14: 2.5 | D14: 20% and 25% | E14: 1501 | F14: 0 | G14: 0 | H14: 100 | I14: 0 | J14: =sum(E14:I14) -> 1601 | K14: =J14*1.75% -> 28.0175 | L14: =J14-K14 -> 1572.9825
A15: 46155 | B15: Wednesday | C15: 2 | D15: 20% and 25% | E15: 0 | F15: 0 | G15: 3000 | H15: 225 | I15: 300 | J15: =sum(E15:I15) -> 3525 | K15: =J15*1.75% -> 61.6875 | L15: =J15-K15 -> 3463.3125
A16: 46156 | B16: Thursday | C16: 0 | D16: 20% and 25% | E16: 0 | F16: 0 | G16: 0 | H16: 0 | I16: 200 | J16: =sum(E16:I16) -> 200 | K16: =J16*1.75% -> 3.5 | L16: =J16-K16 -> 196.5
A17: 46157 | B17: Friday | C17: 4 | D17: 20% and 25% | E17: 1200 | F17: 0 | G17: 270 | H17: 300 | I17: 100 | J17: =sum(E17:I17) -> 1870 | K17: =J17*1.75% -> 32.725 | L17: =J17-K17 -> 1837.275
A18: 46158 | B18: Saturday | C18: 5 | D18: 20% and 25% | E18: 400 | F18: 0 | G18: 6950 | H18: 0 | I18: 750 | J18: =sum(E18:I18) -> 8100 | K18: =J18*1.75% -> 141.75 | L18: =J18-K18 -> 7958.25
A19: 46159 | B19: Sunday | C19: 0 | D19: 20% and 25% | E19: 0 | F19: 0 | G19: 0 | H19: 150 | I19: 200 | J19: =sum(E19:I19) -> 350 | K19: =J19*1.75% -> 6.125 | L19: =J19-K19 -> 343.875
A20: 46160 | B20: Monday | C20: 2 | D20: 20% and 25% | E20: 0 | F20: 1400 | G20: 3230 | H20: 150 | I20: 0 | J20: =sum(E20:I20) -> 4780 | K20: =J20*1.75% -> 83.65 | L20: =J20-K20 -> 4696.35
A21: 46161 | B21: Tuesday | C21: 4 | D21: 20% and 25% | E21: 1362 | F21: 2075 | G21: 0 | H21: 200 | I21: 400 | J21: =sum(E21:I21) -> 4037 | K21: =J21*1.75% -> 70.6475 | L21: =J21-K21 -> 3966.3525
A22: 46162 | B22: Wednesday | C22: 1.5 | D22: 20% and 25% | E22: 0 | F22: 0 | G22: 2500 | H22: 150 | I22: 300 | J22: =sum(E22:I22) -> 2950 | K22: =J22*1.75% -> 51.625 | L22: =J22-K22 -> 2898.375
A23: 46163 | B23: Thursday | C23: 0 | D23: 20% and 25% | E23: 0 | F23: 0 | G23: 0 | H23: 650 | I23: 75 | J23: =sum(E23:I23) -> 725 | K23: =J23*1.75% -> 12.6875 | L23: =J23-K23 -> 712.3125
A24: 46164 | B24: Friday | C24: 5 | D24: 20% and 25% | E24: 3080 | F24: 0 | G24: 0 | H24: 1250 | I24: 450 | J24: =sum(E24:I24) -> 4780 | K24: =J24*1.75% -> 83.65 | L24: =J24-K24 -> 4696.35
A25: 46165 | B25: Saturday | C25: 4 | D25: 20% and 25% | E25: 945 | F25: 0 | G25: 8190 | H25: 800 | I25: 0 | J25: =sum(E25:I25) -> 9935 | K25: =J25*1.75% -> 173.8625 | L25: =J25-K25 -> 9761.1375
... A30: 46170 | B30: Thursday | C30: 0 | D30: 20% and 25% | E30: 0 | F30: 0 | G30: 0 | H30: 0 | I30: 0 | J30: =sum(E30:I30) -> 0 | K30: =J30*1.75% -> 0 | L30: =J30-K30 -> 0
A31: 46171 | B31: Friday | C31: 8.5 | D31: 20% and 25% | E31: 500 | F31: 4125 | G31: 7695 | H31: 100 | I31: =600+225 -> 825 | J31: =sum(E31:I31) -> 13245 | K31: =J31*1.75% -> 231.7875 | L31: =J31-K31 -> 13013.212
A32: 46172 | B32: Saturday | C32: 3.5 | D32: 20% and 25% | E32: 900 | F32: 0 | G32: 3000 | H32: 750 | I32: 0 | J32: =sum(E32:I32) -> 4650 | K32: =J32*1.75% -> 81.375 | L32: =J32-K32 -> 4568.625
A33: 46173 | B33: Sunday | C33: 0.5 | D33: 20% and 25% | E33: 0 | F33: 800 | G33: 0 | H33: 0 | I33: 300 | J33: =sum(E33:I33) -> 1100 | K33: =J33*1.75% -> 19.25 | L33: =J33-K33 -> 1080.75
A34: Total | C34: =SUM(C2:C33) -> 107 | E34: =SUM(E2:E33) -> 28367 | F34: =SUM(F2:F33) -> 21883 | G34: =SUM(G2:G33) -> 87548 | H34: =SUM(H2:H33) -> 12225 | I34: =SUM(I2:I33) -> 6925 | J34: =SUM(J2:J33) -> 156948 | K34: =SUM(K2:K33) -> 2746.59 | L34: =SUM(L2:L33) -> 154201.41

Sheet District
A1: Link | B1: Date | C1: Paid to District | D1: Commissions (₹) | E1: GST on Commission | F1: Net Revenue | G1: TCS | H1: TDS | I1: Final Amount (₹)
B2: 1 - 31 May | C2: 127314 | D2: 8338 | E2: 1500 | F2: =C2-D2-E2 -> 117476 | G2: 694 | H2: 138 | I2: 116642
B3: Total | C3: =SUM(C2) -> 127314 | F3: =SUM(F2) -> 117476 | I3: =SUM(I2) -> 116642
A5: Pickleball | B5: =C3-B6-B7 -> 51713
A6: Turf | B6: 49356
A7: Padel | B7: 26245

Sheet Hudle
A1: Link | B1: Date | C1: Paid to Hudle | D1: Commisions (Including GST) | E1: Net Revenue | F1: TDS | G1: TCS | H1: Amount
B2: 1 - 5 May | C2: 13777 | D2: 1894 | E2: =C2-D2 -> 11883 | F2: 12 | G2: 61 | H2: 12607
B3: 5 - 12 May | C3: 34779 | D3: 4534 | E3: =C3-D3 -> 30245 | F3: 29 | G3: 147 | H3: 30167
B5: Total | C5: =SUM(C2:C3) -> 48556 | D5: =SUM(D2:D3) -> 6428 | E5: =SUM(E2:E3) -> 42128 | H5: =SUM(H2:H3) -> 42774
A7: Pickleball | B7: =C5-B8-B9 -> 11690
A8: Turf | B8: 20087
A9: Padel | B9: 16779

Sheet Memberships
A1: Member Name | B1: Sports Type | C1: Membership Type | D1: Start Date | E1: Amount Collected | F1: Payment Gateway | G1: Net Revenue
A2: Nikhil | B2: Football | C2: 18 Slots | D2: May | E2: 50000 | F2: 0 | G2: =E2-F2 -> 50000

Sheet B2B
A1: Date | B1: Brand | C1: Type | D1: Amt
A2: May | B2: Savikalpa | C2: Activation | D2: 15000

Sheet Academy
A1: Date | B1: Sport | C1: Type | D1: Amt
A2: May | B2: Football | C2: Academy | D2: 47200

Sheet Social EventsTournament
A1: Date | B1: Sport | C1: Type | D1: Amt | E1: Payment Gateway | F1: Net Revenue
A2: 46166 | B2: Football | C2: Tournament | D2: 32000 | E2: =D2*1.75% -> 560 | F2: =D2-E2 -> 31440
A3: 46159 | B3: Hybrid Social | C3: Mini Hyrox | D3: 2560 | E3: =D3*1.75% -> 44.8 | F3: =D3-E3 -> 2515.2
A4: Total | D4: =SUM(D2:D3) -> 34560 | E4: =SUM(E2:E3) -> 604.8 | F4: =SUM(F2:F3) -> 33955.2

Sheet Corporate Events
A1: Date | B1: Name | C1: Type | D1: Sports Type | E1: Deliverables | F1: Amount Collected | G1: Payment Gateway | H1: Net Revenue
A2: 46159 | B2: Recess Club | C2: Community Event | D2: Turf | E2: 2.5 hours of Turf | F2: 4246 | G2: 0 | H2: =F2-G2 -> 4246
A3: 30 & 31 May | B3: Akribiz | C3: Corporate Event | D3: Turf & Pickleball | E3: 2 Days (6-10 pm) | F3: 76429 | G3: 0 | H3: =F3-G3 -> 76429
A4: 46158 | B4: Fakiha | C4: Bday Event | D4: Pickleball | E4: 2 hours of Courts | F4: 2988 | G4: =F4*1.75% -> 52.29 | H4: =F4-G4 -> 2935.71
A5: Total | F5: =SUM(F2:F4) -> 83663 | G5: =SUM(G2:G4) -> 52.29 | H5: =SUM(H2:H4) -> 83610.71
