Workbook

Sheet Summary
B2: 1 - 31 May
B3: Particulars | C3: Amount
C4: Pickleball
B5: Pay & Play | C5: =sum(C6,C12) -> 283572
B6: Online | C6: =sum(C7:C11) -> 169817
B7: District | C7: =District!C4 -> 87543
B8: Hudle | C8: =Hudle!C3 -> 19250
B9: Playo | C9: =Playo!C3 -> 38749
B10: Khelomore | C10: =Khelomore!C4 -> 24275
B11: Zplys | C11: 0
B12: Offline | C12: =sum(C13:C14) -> 113755
B13: Bookings | C13: ='Offline & RG Community'!E33 -> 113755
B14: Memberships | C14: 0
B15: Community | C15: =sum(C16:C17) -> 0
B16: Pickup games | C16: ='Offline & RG Community'!F33 -> 0
B17: Social Events/Tournaments | C17: 0
B18: Academy | C18: 0
B19: Events & Partnership | C19: =sum(C20,C21) -> 0
B20: Corporate events | C20: 0
B21: All B2B partnerships | C21: 0
B22: Commerce | C22: =sum(C23:C25) -> 19750
B23: Product rental | C23: ='Offline & RG Community'!G33 -> 19750
B24: Product sales | C24: 0
B25: F&B | C25: 0
B26: Other Income | C26: ='Other income'!C2 -> 120000
B27: Total Gross Revenue | C27: =sum(C26+C22+C19+C18+C15+C12+C6) -> 423322
B28: Total Net Revenue (Post Commissions) | C28: ='Offline & RG Community'!J33+District!F4+Hudle!E3+Playo!F3+Khelomore!E4+'Other income'!C2 -> 402966.8
B29: Total Revenue post GST | C29: =C28/1.18 -> 341497.29

Sheet Offline & RG Community
A1: Date | B1: Day | C1: Offline booking hours | D1: Discount Given | E1: Booking Revenue | F1: Community Revenue | G1: Paddle Rental | H1: Total Revenue | I1: Payment Gateway | J1: Net Revenue
A2: 46143 | B2: Friday | C2: 2 | D2: 10 & 15% | E2: 1320 | F2: 0 | G2: 700 | H2: =sum(E2:G2) -> 2020 | I2: =H2*2.5%*1.18 -> 59.59 | J2: =H2-I2 -> 1960.41
A3: 46144 | B3: Saturday | C3: 4 | D3: 10 & 15% | E3: 2550 | F3: 0 | G3: 500 | H3: =sum(E3:G3) -> 3050 | I3: =H3*1.75% -> 53.375 | J3: =H3-I3 -> 2996.625
A4: 46145 | B4: Sunday | C4: 2.5 | D4: 10 & 15% | E4: 1725 | F4: 0 | G4: 650 | H4: =sum(E4:G4) -> 2375 | I4: =H4*1.75% -> 41.5625 | J4: =H4-I4 -> 2333.4375
A5: 46146 | B5: Monday | C5: 4 | D5: 10 & 15% | E5: 2775 | F5: 0 | G5: 150 | H5: =sum(E5:G5) -> 2925 | I5: =H5*1.75% -> 51.1875 | J5: =H5-I5 -> 2873.8125
A6: 46147 | B6: Tuesday | C6: 2.5 | D6: 10 & 15% | E6: 1575 | F6: 0 | G6: 250 | H6: =sum(E6:G6) -> 1825 | I6: =H6*1.75% -> 31.9375 | J6: =H6-I6 -> 1793.0625
A7: 46148 | B7: Wednesday | C7: 5 | D7: 10 & 15% | E7: 3225 | F7: 0 | G7: 300 | H7: =sum(E7:G7) -> 3525 | I7: =H7*1.75% -> 61.6875 | J7: =H7-I7 -> 3463.3125
A8: 46149 | B8: Thursday | C8: 9.5 | D8: 10 & 15% | E8: 6045 | F8: 0 | G8: 1125 | H8: =sum(E8:G8) -> 7170 | I8: =H8*1.75% -> 125.475 | J8: =H8-I8 -> 7044.525
A9: 46150 | B9: Friday | C9: 8 | D9: 10 & 15% | E9: 4950 | F9: 0 | G9: 575 | H9: =sum(E9:G9) -> 5525 | I9: =H9*1.75% -> 96.6875 | J9: =H9-I9 -> 5428.3125
A10: 46151 | B10: Saturday | C10: 6.5 | D10: 10 & 15% | E10: 4350 | F10: 0 | G10: 1350 | H10: =sum(E10:G10) -> 5700 | I10: =H10*1.75% -> 99.75 | J10: =H10-I10 -> 5600.25
A11: 46152 | B11: Sunday | C11: 4.5 | D11: 10 & 15% | E11: 2850 | F11: 0 | G11: 550 | H11: =sum(E11:G11) -> 3400 | I11: =H11*1.75% -> 59.5 | J11: =H11-I11 -> 3340.5
A12: 46153 | B12: Monday | C12: 6.5 | D12: 10 & 15% | E12: 4245 | F12: 0 | G12: 850 | H12: =sum(E12:G12) -> 5095 | I12: =H12*1.75% -> 89.1625 | J12: =H12-I12 -> 5005.8375
A13: 46154 | B13: Tuesday | C13: 8 | D13: 10 & 15% | E13: 5100 | F13: 0 | G13: 600 | H13: =sum(E13:G13) -> 5700 | I13: =H13*1.75% -> 99.75 | J13: =H13-I13 -> 5600.25
A14: 46155 | B14: Wednesday | C14: 8.5 | D14: 10 & 15% | E14: 5470 | F14: 0 | G14: 150 | H14: =sum(E14:G14) -> 5620 | I14: =H14*1.75% -> 98.35 | J14: =H14-I14 -> 5521.65
A15: 46156 | B15: Thursday | C15: 9 | D15: 10 & 15% | E15: 5850 | F15: 0 | G15: 1300 | H15: =sum(E15:G15) -> 7150 | I15: =H15*1.75% -> 125.125 | J15: =H15-I15 -> 7024.875
A16: 46157 | B16: Friday | C16: 7.5 | D16: 10 & 15% | E16: 4740 | F16: 0 | G16: 700 | H16: =SUM(E16:G16) -> 5440 | I16: =H16*1.75% -> 95.2 | J16: =H16-I16 -> 5344.8
A17: 46158 | B17: Saturday | C17: 5 | D17: 10 & 15% | E17: 4350 | F17: 0 | G17: 350 | H17: =SUM(F17:G17) -> 350 | I17: =H17*1.75% -> 6.125 | J17: =H17-I17 -> 343.875
A18: 46159 | B18: Sunday | C18: 4 | D18: 10 & 15% | E18: 2645 | F18: 0 | G18: 500 | H18: =SUM(E18:G18) -> 3145 | I18: =H18*1.75% -> 55.0375 | J18: =H18-I18 -> 3089.9625
A19: 46160 | B19: Monday | C19: 10 | D19: 10 & 15% | E19: 6300 | F19: 0 | G19: 425 | H19: =SUM(E19:G19) -> 6725 | I19: =H19*1.75% -> 117.6875 | J19: =H19-I19 -> 6607.3125
A20: 46161 | B20: Tuesday | C20: 10 | D20: 10 & 15% | E20: 6375 | F20: 0 | G20: 225 | H20: =SUM(E20:G20) -> 6600 | I20: =H20*1.75% -> 115.5 | J20: =H20-I20 -> 6484.5
A21: 46162 | B21: Wednesday | C21: 3 | D21: 10 & 15% | E21: 2045 | F21: 0 | G21: 500 | H21: =SUM(E21:G21) -> 2545 | I21: =H21*1.75% -> 44.5375 | J21: =H21-I21 -> 2500.4625
A22: 46163 | B22: Thursday | C22: 8 | D22: 10 & 15% | E22: 5175 | F22: 0 | G22: 800 | H22: =sum(E22:G22) -> 5975 | I22: =H22*1.75% -> 104.5625 | J22: =H22-I22 -> 5870.4375
A23: 46164 | B23: Friday | C23: 2.5 | D23: 10 & 15% | E23: 1725 | F23: 0 | G23: 100 | H23: =SUM(E23:G23) -> 1825 | I23: =H23*1.75% -> 31.9375 | J23: =H23-I23 -> 1793.0625
A24: 46165 | B24: Saturday | C24: 4 | D24: 10 & 15% | E24: 2775 | F24: 0 | G24: 350 | H24: =SUM(E24:G24) -> 3125 | I24: =H24*1.75% -> 54.6875 | J24: =H24-I24 -> 3070.3125
A25: 46166 | B25: Sunday | C25: 2 | D25: 10 & 15% | E25: 1320 | F25: 0 | G25: 300 | H25: =SUM(E25:G25) -> 1620 | I25: =H25*1.75% -> 28.35 | J25: =H25-I25 -> 1591.65
A26: 46167 | B26: Monday | C26: 3.5 | D26: 10 & 15% | E26: 2425 | F26: 0 | G26: 200 | H26: =SUM(E26:G26) -> 2625 | I26: =H26*1.75% -> 45.9375 | J26: =H26-I26 -> 2579.0625
A27: 46168 | B27: Tuesday | C27: 5 | D27: 10 & 15% | E27: 3075 | F27: 0 | G27: 500 | H27: =SUM(E27:G27) -> 3575 | I27: =H27*1.75% -> 62.5625 | J27: =H27-I27 -> 3512.4375
A28: 46169 | B28: Wednesday | C28: 9 | D28: 10 & 15% | E28: 5795 | F28: 0 | G28: 875 | H28: =SUM(E28:G28) -> 6670 | I28: =H28*1.75% -> 116.725 | J28: =H28-I28 -> 6553.275
A29: 46170 | B29: Thursday | C29: 7 | D29: 10 & 15% | E29: 4620 | F29: 0 | G29: 1350 | H29: =SUM(E29:G29) -> 5970 | I29: =H29*1.75% -> 104.475 | J29: =H29-I29 -> 5865.525
A30: 46171 | B30: Friday | C30: 4 | D30: 10 & 15% | E30: 2700 | F30: 0 | G30: 1475 | H30: =SUM(E30:G30) -> 4175 | I30: =H30*1.75% -> 73.0625 | J30: =H30-I30 -> 4101.9375
A31: 46172 | B31: Saturday | C31: 2.5 | D31: 10 & 15% | E31: 1745 | F31: 0 | G31: 1425 | H31: =SUM(E31:G31) -> 3170 | I31: =H31*1.75% -> 55.475 | J31: =H31-I31 -> 3114.525
A32: 46173 | B32: Sunday | C32: 6 | D32: 10 & 15% | E32: 3915 | F32: 0 | G32: 625 | H32: =SUM(E32:G32) -> 4540 | I32: =H32*1.75% -> 79.45 | J32: =H32-I32 -> 4460.55
A33: Total | C33: =SUM(C2:C32) -> 173.5 | E33: =SUM(E2:E32) -> 113755 | F33: =SUM(F2:F32) -> 0 | G33: =SUM(G2:G32) -> 19750 | H33: =SUM(H2:H32) -> 129155 | I33: =SUM(I2:I32) -> 2284.4525 | J33: =SUM(J2:J32) -> 126870.55

Sheet District
A1: Link | B1: Date | C1: Paid to District | D1: Commissions (₹) | E1: GST on Commission | F1: Net Revenue | G1: TCS | H1: TDS | I1: Final Amount (₹)
B2: 1 - 31 May | C2: 87543 | D2: 5332 | E2: 959 | F2: =C2-D2-E2 -> 81252 | G2: 444 | H2: 88 | I2: 80718
B4: Total | C4: =SUM(C2:C3) -> 87543 | F4: =SUM(F2:F3) -> 81252 | I4: =SUM(I2:I3) -> 80718

Sheet Hudle
A1: Link | B1: Date | C1: Paid to Hudle | D1: Commisions (Including GST) | E1: Net Revenue | F1: TDS | G1: TCS | H1: Amount
B2: 1 - 31 May | C2: 19250 | D2: 2593 | E2: =C2-D2 -> 16657 | F2: 16 | G2: 84 | H2: 17255
B3: Total | C3: =SUM(C2) -> 19250 | E3: =SUM(E2) -> 16657 | H3: =SUM(H2) -> 17255

Sheet Playo
A1: Link | B1: Date | C1: Paid to Playo (₹) | D1: Commissions (₹) | E1: GST (₹) | F1: Net Revenue | G1: TDS (₹) | H1: TCS (₹) | I1: Final Amount (₹)
B2: 1 - 31 May | C2: 38749 | D2: 3071 | E2: 552 | F2: =C2-D2-E2 -> 35126 | G2: 38 | H2: 0 | I2: 35087.14
B3: Total | C3: =sum(C2) -> 38749 | F3: =sum(F2) -> 35126 | I3: =sum(I2) -> 35087.14

Sheet Khelomore
A1: Link | B1: Date | C1: Paid to Khelomore (₹) | D1: Commissions (₹) | E1: Final Amount (₹)
B2: 1 - 31 May | C2: 24275 | D2: =C2*5% -> 1213.75 | E2: =C2-D2 -> 23061.25
B4: Total | C4: =SUM(C2) -> 24275 | E4: =SUM(E2) -> 23061.25

Sheet Other income
A1: Month | B1: Sports Type | C1: Amount Collected
A2: May | B2: Football Management Operations | C2: 120000
