Workbook

Sheet Summary
B2: 1 - 30 June
B3: Particulars | C3: Amount
C4: Pickleball
B5: Pay & Play | C5: =sum(C6,C12) -> 72234
B6: Online | C6: =sum(C7:C11) -> 62834
B7: District | C7: =District!C4 -> 62834
B8: Hudle | C8: 0
B9: Playo | C9: 0
B10: Khelomore | C10: 0
B11: Zplys | C11: 0
B12: Offline | C12: =sum(C13:C14) -> 9400
B13: Bookings | C13: ='Offline & RG Community'!E32 -> 9400
B14: Memberships | C14: 0
B15: Community | C15: =sum(C16:C17) -> 0
B16: Pickup games | C16: ='Offline & RG Community'!F32 -> 0
B17: Social Events/Tournaments | C17: 0
B18: Academy | C18: 0
B19: Events & Partnership | C19: =sum(C20,C21) -> 0
B20: Corporate events | C20: 0
B21: All B2B partnerships | C21: 0
B22: Commerce | C22: =sum(C23:C25) -> 5500
B23: Product rental | C23: ='Offline & RG Community'!G32 -> 5500
B24: Product sales | C24: 0
B25: F&B | C25: 0
B26: Other Income | C26: 0
B27: Total Gross Revenue | C27: =C6+C12+C15+C18+C19+C22+C26 -> 77734
B28: Total Net Revenue (Post Commissions) | C28: ='Offline & RG Community'!K32+District!F4 -> 72883.25
B29: Total Revenue post GST | C29: =C28/1.18 -> 61765.466
B31: Expenses
B32: VM Salary | C32: =1580+11032+10000+2400 -> 25012
B33: Support Staff | C33: 5500
B34: Marketing, Branding & Community | C34: 6000
B35: Balls | C35: 5500
B37: Net Profit | C37: =C29-(sum(C32:C35)) -> 19753.466

Sheet Offline & RG Community
A1: Date | B1: Day | C1: Offline booking hours | D1: Discount Given | E1: Booking Revenue | F1: Community Revenue | G1: Paddle Rental | H1: F&B | I1: Total Revenue | J1: Payment Gateway | K1: Net Revenue
A2: 46174 | B2: Monday | C2: 0.5 | D2: 0 and 10% | E2: 500 | F2: 0 | G2: 150 | H2: 0 | I2: =sum(E2:H2) -> 650 | J2: =I2*1.75% -> 11.375 | K2: =I2-J2 -> 638.625
A3: 46175 | B3: Tuesday | C3: 0.5 | D3: 0 and 10% | E3: 500 | F3: 0 | G3: 200 | H3: 0 | I3: =sum(E3:H3) -> 700 | J3: =I3*1.75% -> 12.25 | K3: =I3-J3 -> 687.75
A4: 46176 | B4: Wednesday | C4: 1 | D4: 0 and 10% | E4: 900 | F4: 0 | G4: 200 | H4: 0 | I4: =sum(E4:H4) -> 1100 | J4: =I4*1.75% -> 19.25 | K4: =I4-J4 -> 1080.75
A5: 46177 | B5: Thursday | C5: 0 | D5: 0 and 10% | E5: 0 | F5: 0 | G5: 550 | H5: 0 | I5: =sum(E5:H5) -> 550 | J5: =I5*1.75% -> 9.625 | K5: =I5-J5 -> 540.375
A6: 46178 | B6: Friday | C6: 0 | D6: 0 and 10% | E6: 0 | F6: 0 | G6: 600 | H6: 0 | I6: =sum(E6:H6) -> 600 | J6: =I6*1.75% -> 10.5 | K6: =I6-J6 -> 589.5
A7: 46179 | B7: Saturday | C7: 0 | D7: 0 and 10% | E7: 0 | F7: 0 | G7: 300 | H7: 0 | I7: =sum(E7:H7) -> 300 | J7: =I7*1.75% -> 5.25 | K7: =I7-J7 -> 294.75
A8: 46180 | B8: Sunday | C8: 0 | D8: 0 and 10% | E8: 0 | F8: 0 | G8: 100 | H8: 0 | I8: =sum(E8:H8) -> 100 | J8: =I8*1.75% -> 1.75 | K8: =I8-J8 -> 98.25
A9: 46181 | B9: Monday | C9: 0 | D9: 0 and 10% | E9: 0 | F9: 0 | G9: 700 | H9: 0 | I9: =sum(E9:H9) -> 700 | J9: =I9*1.75% -> 12.25 | K9: =I9-J9 -> 687.75
A10: 46182 | B10: Tuesday | C10: 1 | D10: 0 and 10% | E10: 900 | F10: 0 | G10: 100 | H10: 0 | I10: =sum(E10:H10) -> 1000 | J10: =I10*1.75% -> 17.5 | K10: =I10-J10 -> 982.5
A11: 46183 | B11: Wednesday | C11: 0 | D11: 0 and 10% | E11: 0 | F11: 0 | G11: 450 | H11: 0 | I11: =sum(E11:H11) -> 450 | J11: =I11*1.75% -> 7.875 | K11: =I11-J11 -> 442.125
A12: 46184 | B12: Thursday | C12: 1 | D12: 0 and 10% | E12: 900 | F12: 0 | G12: 400 | H12: 0 | I12: =sum(E12:H12) -> 1300 | J12: =I12*1.75% -> 22.75 | K12: =I12-J12 -> 1277.25
A13: 46185 | B13: Friday | C13: 0 | D13: 0 and 10% | E13: 0 | F13: 0 | G13: 0 | H13: 0 | I13: =sum(E13:H13) -> 0 | J13: =I13*1.75% -> 0 | K13: =I13-J13 -> 0
... A15: 46187 | B15: Sunday | C15: 0 | D15: 0 and 10% | E15: 0 | F15: 0 | G15: 150 | H15: 0 | I15: =sum(E15:H15) -> 150 | J15: =I15*1.75% -> 2.625 | K15: =I15-J15 -> 147.375
A16: 46188 | B16: Monday | C16: 0.5 | D16: 0 and 10% | E16: 500 | F16: 0 | G16: 300 | H16: 0 | I16: =SUM(E16:H16) -> 800 | J16: =I16*1.75% -> 14 | K16: =I16-J16 -> 786
A17: 46189 | B17: Tuesday | C17: 1.5 | D17: 0 and 10% | E17: 1400 | F17: 0 | G17: 450 | H17: 0 | I17: =SUM(E17:H17) -> 1850 | J17: =I17*1.75% -> 32.375 | K17: =I17-J17 -> 1817.625
A18: 46190 | B18: Wednesday | C18: 0 | D18: 0 and 10% | E18: 0 | F18: 0 | G18: 100 | H18: 0 | I18: =SUM(E18:H18) -> 100 | J18: =I18*1.75% -> 1.75 | K18: =I18-J18 -> 98.25
A19: 46191 | B19: Thursday | C19: 1.5 | D19: 0 and 10% | E19: 1400 | F19: 0 | G19: 500 | H19: 0 | I19: =SUM(E19:H19) -> 1900 | J19: =I19*1.75% -> 33.25 | K19: =I19-J19 -> 1866.75
A20: 46192 | B20: Friday | C20: 0.5 | D20: 0 and 10% | E20: 500 | F20: 0 | G20: 150 | H20: 0 | I20: =SUM(E20:H20) -> 650 | J20: =I20*1.75% -> 11.375 | K20: =I20-J20 -> 638.625
A21: 46193 | B21: Saturday | C21: 0 | D21: 0 and 10% | E21: 0 | F21: 0 | G21: 0 | H21: 0 | I21: =SUM(E21:H21) -> 0 | J21: =I21*1.75% -> 0 | K21: =I21-J21 -> 0
A22: 46194 | B22: Sunday | C22: 1 | D22: 0 and 10% | E22: 1000 | F22: 0 | G22: 0 | H22: 0 | I22: =sum(E22:H22) -> 1000 | J22: =I22*1.75% -> 17.5 | K22: =I22-J22 -> 982.5
A23: 46195 | B23: Monday | C23: 1 | D23: 0 and 10% | E23: 900 | F23: 0 | G23: 100 | H23: 0 | I23: =SUM(E23:H23) -> 1000 | J23: =I23*1.75% -> 17.5 | K23: =I23-J23 -> 982.5
A24: 46196 | B24: Tuesday | C24: 0 | D24: 0 and 10% | E24: 0 | F24: 0 | G24: 0 | H24: 0 | I24: =SUM(E24:H24) -> 0 | J24: =I24*1.75% -> 0 | K24: =I24-J24 -> 0
A25: 46197 | B25: Wednesday | C25: 0 | D25: 0 and 10% | E25: 0 | F25: 0 | G25: 0 | H25: 0 | I25: =SUM(E25:H25) -> 0 | J25: =I25*1.75% -> 0 | K25: =I25-J25 -> 0
A26: 46198 | B26: Thursday | C26: 0 | D26: 0 and 10% | E26: 0 | F26: 0 | G26: 0 | H26: 0 | I26: =SUM(E26:H26) -> 0 | J26: =I26*1.75% -> 0 | K26: =I26-J26 -> 0
A27: 46199 | B27: Friday | C27: 0 | D27: 0 and 10% | E27: 0 | F27: 0 | G27: 0 | H27: 0 | I27: =SUM(E27:H27) -> 0 | J27: =I27*1.75% -> 0 | K27: =I27-J27 -> 0
A28: 46200 | B28: Saturday | C28: 0 | D28: 0 and 10% | E28: 0 | F28: 0 | G28: 0 | H28: 0 | I28: =SUM(E28:H28) -> 0 | J28: =I28*1.75% -> 0 | K28: =I28-J28 -> 0
A29: 46201 | B29: Sunday | C29: 0 | D29: 0 and 10% | E29: 0 | F29: 0 | G29: 0 | H29: 0 | I29: =SUM(E29:H29) -> 0 | J29: =I29*1.75% -> 0 | K29: =I29-J29 -> 0
A30: 46202 | B30: Monday | C30: 0 | D30: 0 and 10% | E30: 0 | F30: 0 | G30: 0 | H30: 0 | I30: =SUM(E30:H30) -> 0 | J30: =I30*1.75% -> 0 | K30: =I30-J30 -> 0
A31: 46203 | B31: Tuesday | C31: 0 | D31: 0 and 10% | E31: 0 | F31: 0 | G31: 0 | H31: 0 | I31: =SUM(E31:H31) -> 0 | J31: =I31*1.75% -> 0 | K31: =I31-J31 -> 0
A32: Total | E32: =SUM(E1:E31) -> 9400 | F32: =SUM(F1:F31) -> 0 | G32: =SUM(G1:G31) -> 5500 | H32: =SUM(H1:H31) -> 0 | I32: =SUM(I1:I31) -> 14900 | J32: =SUM(J1:J31) -> 260.75 | K32: =SUM(K1:K31) -> 14639.25

Sheet District
A1: Link | B1: Date | C1: Paid to District | D1: Commissions (₹) | E1: GST on Commission | F1: Net Revenue | G1: TCS | H1: TDS | I1: Final Amount (₹)
B2: 1 - 30 May | C2: 62834 | D2: 3890 | E2: 700 | F2: =C2-D2-E2 -> 58244 | G2: 314 | H2: 62 | I2: =F2-G2-H2 -> 57868
B4: Total | C4: =SUM(C2:C3) -> 62834 | F4: =SUM(F2:F3) -> 58244 | I4: =SUM(I2:I3) -> 57868
