Workbook

Sheet Summary
B2: Date: 1 - 31 Jan
B3: Particulars | C3: Amount
B4: Offline | C4: =SUM(C5,C6,C7,C8) -> 8850
B5: Rentals | C5: ='Offline & RG Community'!G33 -> 7950
B6: F&B | C6: 0
B7: Product Sales | C7: 0
B8: Bookings | C8: ='Offline & RG Community'!E33 -> 900
B9: Online: Third Party Platform | C9: =SUM(C10:C13) -> 40370
B10: Hudle | C10: =Hudle!C7 -> 17570
B11: Playo | C11: =Playo!C3 -> 1450
B12: District | C12: =District!C5 -> 21350
B13: Khelomore | C13: 0
B14: Community | C14: =SUM(C16,C15, C17,C18) -> 600
B15: Courtly (Organized by RallyGully) | C15: 0
B16: Sportomic (Organized by RallyGully) | C16: 0
B17: Rallygully Community games | C17: ='Offline & RG Community'!F33 -> 600
B18: Misfits Community | C18: 0
B19: Memberships | C19: 0
B20: Corporate Events | C20: 0
B21: Brand Activation | C21: 0
B22: Other Income | C22: =0 -> 0
B23: Total Gross Revenue | C23: =sum(C4,C9,C14,C19,C20,C21,C22) -> 49820
B24: Total Net Revenue (Post Commissions) | C24: ='Offline & RG Community'!H33 + Hudle!E7 + Playo!F3 + District!F5 -> 46834.92
B25: Total Revenue post GST | C25: =C24/1.18 -> 39690.61
B26: Investor's Share (40%) | C26: =C25*40% -> 15876.244

Sheet Offline & RG Community
A1: Date | B1: Day | C1: Offline booking hours | D1: Discount Given | E1: Booking Revenue | F1: Community Revenue | G1: Paddle Rental | H1: Total Revenue
A2: 46023 | B2: Thursday | C2: 0 | D2: 0.2 | E2: 0 | F2: 0 | G2: 600 | H2: =sum(E2:G2) -> 600
A3: 46024 | B3: Friday | C3: 0 | D3: 0.2 | E3: 0 | F3: 0 | G3: 0 | H3: =sum(E3:G3) -> 0
A4: 46025 | B4: Saturday | C4: 0 | D4: 0.2 | E4: 0 | F4: 0 | G4: 100 | H4: =sum(E4:G4) -> 100
A5: 46026 | B5: Sunday | C5: 0 | D5: 0.2 | E5: 0 | F5: 0 | G5: 500 | H5: =sum(E5:G5) -> 500
A6: 46027 | B6: Monday | C6: 0 | D6: 0.2 | E6: 0 | F6: 0 | G6: 500 | H6: =sum(E6:G6) -> 500
A7: 46028 | B7: Tuesday | C7: 0 | D7: 0.2 | E7: 0 | F7: 0 | G7: 600 | H7: =sum(E7:G7) -> 600
A8: 46029 | B8: Wednesday | C8: 0 | D8: 0.2 | E8: 0 | F8: 0 | G8: 300 | H8: =sum(E8:G8) -> 300
A9: 46030 | B9: Thursday | C9: 0 | D9: 0.2 | E9: 0 | F9: 0 | G9: 0 | H9: =sum(E9:G9) -> 0
A10: 46031 | B10: Friday | C10: 0 | D10: 0.2 | E10: 0 | F10: 0 | G10: 200 | H10: =sum(E10:G10) -> 200
A11: 46032 | B11: Saturday | C11: 0 | D11: 0.2 | E11: 0 | F11: 0 | G11: 850 | H11: =sum(E11:G11) -> 850
A12: 46033 | B12: Sunday | C12: 0 | D12: 0.2 | E12: 0 | F12: 0 | G12: 200 | H12: =sum(E12:G12) -> 200
A13: 46034 | B13: Monday | C13: 0 | D13: 0.2 | E13: 0 | F13: 0 | G13: 0 | H13: =sum(E13:G13) -> 0
... A32: 46053 | B32: Saturday | C32: 1 | D32: 0.2 | E32: 450 | F32: 0 | G32: 300 | H32: =sum(E32:G32) -> 750
A33: Total | C33: =SUM(C2:C32) -> 4 | E33: =SUM(E2:E32) -> 900 | F33: =SUM(F2:F32) -> 600 | G33: =SUM(G2:G32) -> 7950 | H33: =SUM(H2:H32) -> 9450

Sheet Hudle
A1: Link | B1: Date | C1: Paid to Hudle | D1: Commisions (Including GST) | E1: Net Revenue | F1: TDS | G1: TCS | H1: Amount
B2: 1 - 5 Jan | C2: 5520 | D2: 685.1 | E2: =C2 - D2 -> 4834.9 | F2: 4.4 | G2: 22.33 | H2: 4558.11
B3: 6 - 12 Jan | C3: 6500 | D3: 845 | E3: =C3 - D3 -> 5655 | F3: 5.5 | G3: 27.54 | H3: 5621.97
B4: 13 - 19 Jan | C4: 450 | D4: 58.6 | E4: =C4 - D4 -> 391.4 | F4: 0.38 | G4: 1.9 | H4: 389.21
B5: 20 - 26 Jan | C5: 2925 | D5: 380.25 | E5: =C5 - D5 -> 2544.75 | F5: 2.47 | G5: 12.39 | H5: 2529.88
B6: 27 - 31 Jan | C6: 2175 | D6: 289.25 | E6: =C6 - D6 -> 1885.75 | F6: 1.88 | G6: 9.42 | H6: 1924.43
C7: =SUM(C2:C6) -> 17570 | E7: =SUM(E2:E6) -> 15311.8 | H7: =SUM(H2:H6) -> 15023.6

Sheet Playo
A1: Link | B1: Date | C1: Paid to Playo (₹) | D1: Commissions (₹) | E1: GST (₹) | F1: Net Revenue | G1: TDS (₹) | H1: TCS (₹) | I1: Final Amount (₹)
B2: 1 - 31 Jan | C2: 1450 | D2: 189 | E2: 34.02 | F2: =C2 -D2-E2 -> 1226.98 | G2: 1.45 | H2: 7.25 | I2: 1218.28
C3: =SUM(C2) -> 1450 | F3: =SUM(F2) -> 1226.98 | I3: =SUM(I2) -> 1218.28

Sheet District
A1: Link | B1: Date | C1: Paid to District | D1: Commissions (₹) | E1: GST on Commission | F1: Net Revenue | G1: TCS | H1: TDS | I1: Final Amount (₹)
B2: 1 - 12 Jan | C2: 3350 | D2: =C2*2% -> 67 | E2: =D2*18% -> 12.06 | F2: =C2-D2-E2 -> 3270.94 | G2: =C2*0.5% -> 16.75 | H2: =D2*0.1% -> 0.067 | I2: =F2-G2-H2 -> 3254.123
B3: 13 - 19 Jan | C3: 4050 | D3: =C3*2% -> 81 | E3: =D3*18% -> 14.58 | F3: =C3-D3-E3 -> 3954.42 | G3: =C3*0.5% -> 20.25 | H3: =D3*0.1% -> 0.081 | I3: =F3-G3-H3 -> 3934.089
B4: 20 - 31 Jan | C4: 13950 | D4: =C4*2% -> 279 | E4: =D4*18% -> 50.22 | F4: =C4-D4-E4 -> 13620.78 | G4: =C4*0.5% -> 69.75 | H4: =D4*0.1% -> 0.279 | I4: =F4-G4-H4 -> 13550.751
B5: Total | C5: =SUM(C2:C4) -> 21350 | F5: =SUM(F2:F4) -> 20846.14 | I5: =SUM(I2:I4) -> 20738.963
