Workbook

Sheet Summary
B2: 1 - 30 June
B3: Particulars | C3: Amount
C4: Pickleball
B5: Pay & Play | C5: =sum(C6,C12) -> 83272
B6: Online | C6: =sum(C7:C11) -> 61998
B7: District | C7: =District!C4 -> 61998
B8: Hudle | C8: 0
B9: Playo | C9: 0
B10: Khelomore | C10: 0
B11: Zplys | C11: 0
B12: Offline | C12: =sum(C13:C14) -> 21274
B13: Bookings | C13: ='Offline & RG Community'!E32 -> 21274
B14: Memberships | C14: 0
B15: Community | C15: =sum(C16:C17) -> 6120
B16: Pickup games | C16: ='Offline & RG Community'!F32 -> 6120
B17: Social Events/Tournaments | C17: 0
B18: Academy | C18: 0
B19: Events & Partnership | C19: =sum(C20,C21) -> 0
B20: Corporate events | C20: 0
B21: All B2B partnerships | C21: 0
B22: Commerce | C22: =sum(C23:C25) -> 3425
B23: Product rental | C23: ='Offline & RG Community'!G32 -> 3425
B24: Product sales | C24: 0
B25: F&B | C25: 0
B26: Other Income | C26: ='Other Income'!E2 -> 18000 | D26: (Note for CA Team: Please note that RallyGully hasn't received the 18000 rental for basketball rental service provided) - GST payment would have to be made by Drive & Kick Team
B27: Total Gross Revenue | C27: =sum(C26+C22+C19+C18+C15+C12+C6) -> 110817
B28: Total Net Revenue (Post Commissions) | C28: ='Offline & RG Community'!K32+District!F4+'Other Income'!E2 -> 105741.67
B29: Total Revenue post GST | C29: =C28/1.18 -> 89611.583
B30: Drive & Kick Share (70%) | C30: =C29*70% -> 62728.108
B31: Drive & Kick Share (Final share after incorporting 18k already received by Drive Kick) | C31: =C30-C26 -> 44728.108
B32: RallyGully's Share (30%) | C32: =C29*30% -> 26883.475

Sheet Offline & RG Community
A1: Date | B1: Day | C1: Offline booking hours | D1: Discount | E1: Booking Revenue | F1: Community Revenue | G1: Paddle Rental | H1: F&B | I1: Total Revenue | J1: Payment Gateway | K1: Net Revenue
A2: 46174 | B2: Monday | C2: 0 | D2: 20 and 10% | E2: 0 | F2: 0 | G2: 0 | H2: 0 | I2: =sum(E2:H2) -> 0 | J2: =I2*1.75% -> 0 | K2: =I2-J2 -> 0
A3: 46175 | B3: Tuesday | C3: 0 | D3: 20 and 10% | E3: 0 | F3: 0 | G3: 0 | H3: 0 | I3: =sum(E3:H3) -> 0 | J3: =I3*1.75% -> 0 | K3: =I3-J3 -> 0
A4: 46176 | B4: Wednesday | C4: 2 | D4: 20 and 10% | E4: 1280 | F4: 0 | G4: 50 | H4: 0 | I4: =sum(E4:H4) -> 1330 | J4: =I4*1.75% -> 23.275 | K4: =I4-J4 -> 1306.725
A5: 46177 | B5: Thursday | C5: 0.5 | D5: 20 and 10% | E5: 360 | F5: 0 | G5: 100 | H5: 0 | I5: =sum(E5:H5) -> 460 | J5: =I5*1.75% -> 8.05 | K5: =I5-J5 -> 451.95
A6: 46178 | B6: Friday | C6: 0 | D6: 20 and 10% | E6: 0 | F6: 0 | G6: 0 | H6: 0 | I6: =sum(E6:H6) -> 0 | J6: =I6*1.75% -> 0 | K6: =I6-J6 -> 0
A7: 46179 | B7: Saturday | C7: 0 | D7: 20 and 10% | E7: 0 | F7: 2800 | G7: 300 | H7: 0 | I7: =sum(E7:H7) -> 3100 | J7: =I7*1.75% -> 54.25 | K7: =I7-J7 -> 3045.75
A8: 46180 | B8: Sunday | C8: 0 | D8: 20 and 10% | E8: 0 | F8: 0 | G8: 250 | H8: 0 | I8: =sum(E8:H8) -> 250 | J8: =I8*1.75% -> 4.375 | K8: =I8-J8 -> 245.625
A9: 46181 | B9: Monday | C9: 2.5 | D9: 20 and 10% | E9: 1720 | F9: 0 | G9: 675 | H9: 0 | I9: =sum(E9:H9) -> 2395 | J9: =I9*1.75% -> 41.9125 | K9: =I9-J9 -> 2353.0875
A10: 46182 | B10: Tuesday | C10: 0 | D10: 20 and 10% | E10: 0 | F10: 0 | G10: 0 | H10: 0 | I10: =sum(E10:H10) -> 0 | J10: =I10*1.75% -> 0 | K10: =I10-J10 -> 0
A11: 46183 | B11: Wednesday | C11: 0 | D11: 20 and 10% | E11: 0 | F11: 600 | G11: 50 | H11: 0 | I11: =sum(E11:H11) -> 650 | J11: =I11*1.75% -> 11.375 | K11: =I11-J11 -> 638.625
A12: 46184 | B12: Thursday | C12: 0 | D12: 20 and 10% | E12: 0 | F12: 0 | G12: 0 | H12: 0 | I12: =sum(E12:H12) -> 0 | J12: =I12*1.75% -> 0 | K12: =I12-J12 -> 0
A13: 46185 | B13: Friday | C13: 0 | D13: 20 and 10% | E13: 0 | F13: 0 | G13: 0 | H13: 0 | I13: =sum(E13:H13) -> 0 | J13: =I13*1.75% -> 0 | K13: =I13-J13 -> 0
A14: 46186 | B14: Saturday | C14: 0.5 | D14: 20 and 10% | E14: 360 | F14: 0 | G14: 0 | H14: 0 | I14: =sum(E14:H14) -> 360 | J14: =I14*1.75% -> 6.3 | K14: =I14-J14 -> 353.7
A15: 46187 | B15: Sunday | C15: 3.5 | D15: 20 and 10% | E15: =360+2320 -> 2680 | F15: 0 | G15: 250 | H15: 0 | I15: =sum(E15:H15) -> 2930 | J15: =I15*1.75% -> 51.275 | K15: =I15-J15 -> 2878.725
A16: 46188 | B16: Monday | C16: 0 | D16: 20 and 10% | E16: 0 | F16: 0 | G16: 0 | H16: 0 | I16: =SUM(E16:H16) -> 0 | J16: =I16*1.75% -> 0 | K16: =I16-J16 -> 0
A17: 46189 | B17: Tuesday | C17: 0 | D17: 20 and 10% | E17: 0 | F17: 0 | G17: 0 | H17: 0 | I17: =SUM(F17:H17) -> 0 | J17: =I17*1.75% -> 0 | K17: =I17-J17 -> 0
A18: 46190 | B18: Wednesday | C18: 0 | D18: 20 and 10% | E18: 0 | F18: 0 | G18: 150 | H18: 0 | I18: =SUM(E18:H18) -> 150 | J18: =I18*1.75% -> 2.625 | K18: =I18-J18 -> 147.375
A19: 46191 | B19: Thursday | C19: 0 | D19: 20 and 10% | E19: 0 | F19: 0 | G19: 200 | H19: 0 | I19: =SUM(E19:H19) -> 200 | J19: =I19*1.75% -> 3.5 | K19: =I19-J19 -> 196.5
A20: 46192 | B20: Friday | C20: 5 | D20: 20 and 10% | E20: 3280 | F20: 0 | G20: 0 | H20: 0 | I20: =SUM(E20:H20) -> 3280 | J20: =I20*1.75% -> 57.4 | K20: =I20-J20 -> 3222.6
A21: 46193 | B21: Saturday | C21: 4 | D21: 20 and 10% | E21: =474+1920 -> 2394 | F21: 0 | G21: 150 | H21: 0 | I21: =SUM(E21:H21) -> 2544 | J21: =I21*1.75% -> 44.52 | K21: =I21-J21 -> 2499.48
A22: 46194 | B22: Sunday | C22: 0 | D22: 20 and 10% | E22: 0 | F22: 0 | G22: 0 | H22: 0 | I22: =sum(E22:H22) -> 0 | J22: =I22*1.75% -> 0 | K22: =I22-J22 -> 0
A23: 46195 | B23: Monday | C23: 5 | D23: 20 and 10% | E23: 3360 | F23: 0 | G23: 0 | H23: 0 | I23: =SUM(E23:H23) -> 3360 | J23: =I23*1.75% -> 58.8 | K23: =I23-J23 -> 3301.2
A24: 46196 | B24: Tuesday | C24: 2 | D24: 20 and 10% | E24: 1280 | F24: 1600 | G24: 100 | H24: 0 | I24: =SUM(E24:H24) -> 2980 | J24: =I24*1.75% -> 52.15 | K24: =I24-J24 -> 2927.85
A25: 46197 | B25: Wednesday | C25: 2 | D25: 20 and 10% | E25: 1280 | F25: 0 | G25: 50 | H25: 0 | I25: =SUM(E25:H25) -> 1330 | J25: =I25*1.75% -> 23.275 | K25: =I25-J25 -> 1306.725
A26: 46198 | B26: Thursday | C26: 5 | D26: 20 and 10% | E26: 3280 | F26: 0 | G26: 0 | H26: 0 | I26: =SUM(E26:H26) -> 3280 | J26: =I26*1.75% -> 57.4 | K26: =I26-J26 -> 3222.6
A27: 46199 | B27: Friday | C27: 0 | D27: 20 and 10% | E27: 0 | F27: 0 | G27: 0 | H27: 0 | I27: =SUM(E27:H27) -> 0 | J27: =I27*1.75% -> 0 | K27: =I27-J27 -> 0
A28: 46200 | B28: Saturday | C28: 0 | D28: 20 and 10% | E28: 0 | F28: 480 | G28: 200 | H28: 0 | I28: =SUM(E28:H28) -> 680 | J28: =I28*1.75% -> 11.9 | K28: =I28-J28 -> 668.1
A29: 46201 | B29: Sunday | C29: 0 | D29: 20 and 10% | E29: 0 | F29: 0 | G29: 700 | H29: 0 | I29: =SUM(E29:H29) -> 700 | J29: =I29*1.75% -> 12.25 | K29: =I29-J29 -> 687.75
A30: 46202 | B30: Monday | C30: 0 | D30: 20 and 10% | E30: 0 | F30: 640 | G30: 200 | H30: 0 | I30: =SUM(E30:H30) -> 840 | J30: =I30*1.75% -> 14.7 | K30: =I30-J30 -> 825.3
A31: 46203 | B31: Tuesday | C31: 0 | D31: 20 and 10% | E31: 0 | F31: 0 | G31: 0 | H31: 0 | I31: =SUM(E31:H31) -> 0 | J31: =I31*1.75% -> 0 | K31: =I31-J31 -> 0
A32: Total | E32: =SUM(E1:E31) -> 21274 | F32: =SUM(F1:F31) -> 6120 | G32: =SUM(G1:G31) -> 3425 | H32: =SUM(H1:H31) -> 0 | I32: =SUM(I1:I31) -> 30819 | J32: =SUM(J1:J31) -> 539.3325 | K32: =SUM(K1:K31) -> 30279.667

Sheet District
A1: Link | B1: Date | C1: Paid to District | D1: Commissions (₹) | E1: GST on Commission | F1: Net Revenue | G1: TCS | H1: TDS | I1: Final Amount (₹)
B2: 1 - 30 June | C2: 61998 | D2: 3844 | E2: 692 | F2: =C2-D2-E2 -> 57462 | G2: 310 | H2: 62 | I2: =F2-G2-H2 -> 57090
B4: Total | C4: =SUM(C2:C3) -> 61998 | F4: =SUM(F2:F3) -> 57462 | I4: =SUM(I2:I3) -> 57090

Sheet Other Income
A1: Month | B1: Coaching | C1: Sports Type | D1: Type | E1: Amount Collected
A2: June | B2: Basketball Coaching | C2: Basketball | D2: 3 days in week | E2: 18000
