Workbook

Sheet Summary
B2: 1 - 31 July
B3: Particulars | C3: Amount
C4: Total | D4: Pickleball | E4: Turf | F4: Padel
B5: Pay & Play | C5: =sum(C6,C12) -> 43820 | D5: =sum(D6,D12) -> 15815 | E5: =sum(E6,E12) -> 28005 | F5: 0
B6: Online | C6: =sum(C7:C11) -> 34930 | D6: =sum(D7:D11) -> 12715 | E6: =sum(E7:E11) -> 22215 | F6: 0
B7: District | C7: =District!C4 -> 2946 | D7: =District!B6 -> 0 | E7: =District!B7 -> 2946 | F7: 0
B8: Hudle | C8: =Hudle!C2 -> 4400 | D8: =Hudle!B5 -> 4400 | E8: =Hudle!B6 -> 0 | F8: 0
B9: Playo | C9: =Playo!C2 -> 17555 | D9: =Playo!B5 -> 3080 | E9: =Playo!B6 -> 14475 | F9: 0
B10: Khelomore | C10: =Khelomore!C2 -> 10029 | D10: =Khelomore!B6 -> 5235 | E10: =Khelomore!B7 -> 4794 | F10: 0
B11: Zplys | C11: 0 | D11: 0 | E11: 0 | F11: 0
B12: Offline | C12: =sum(C13:C14) -> 8890 | D12: =sum(D13:D14) -> 3100 | E12: =sum(E13:E14) -> 5790 | F12: =sum(F13:F14) -> 0
B13: Bookings | C13: ='Offline & RG Community'!D33+'Offline & RG Community'!E33 -> 8890 | D13: ='Offline & RG Community'!D33 -> 3100 | E13: ='Offline & RG Community'!E33 -> 5790 | F13: 0
B14: Memberships | C14: 0 | D14: 0 | E14: 0 | F14: 0
B15: Community | C15: =sum(C16:C17) -> 0 | D15: =sum(D16:D17) -> 0 | E15: =sum(E16:E17) -> 0 | F15: 0
B16: Pickup games | C16: 0 | D16: 0 | E16: 0 | F16: 0
B17: Social Events/Tournaments | C17: 0 | D17: 0 | E17: 0 | F17: 0
B18: Academy | C18: 0 | D18: 0 | E18: 0 | F18: 0
B19: Events & Partnership | C19: =sum(C20) -> 0 | D19: =sum(D20) -> 0 | E19: =sum(E20) -> 0 | F19: 0
B20: Corporate events | C20: 0 | D20: 0 | E20: 0 | F20: 0
B21: All B2B partnerships | C21: 0 | D21: =SUM(D22:D25) -> 0 | E21: 0 | F21: 0
B22: Commerce | C22: =sum(C23:C25) -> 0 | D22: =sum(D23:D25) -> 0 | E22: =sum(E23:E25) -> 0 | F22: 0
B23: Product rental | C23: 0 | D23: 0 | E23: 0 | F23: 0
B24: Product sales | C24: 0 | D24: 0 | E24: 0 | F24: 0
B25: F&B | C25: 0 | D25: 0 | E25: 0 | F25: 0
B26: Other Income | C26: 118000 | D26: 0 | E26: 0 | F26: 118000
B27: Total Gross Revenue | C27: =sum(C5,C15,C18,C19,C22,C26) -> 161820 | D27: =sum(D5,D15,D18,D19,D22,D26) -> 15815 | E27: =sum(E5,E15,E18,E19,E22,E26) -> 28005 | F27: =sum(F5,F15,F18,F19,F22,F26) -> 118000
B28: Total Net Revenue (Post Commissions) | C28: ='Offline & RG Community'!I33+District!F4+Hudle!E3+Playo!F3+Khelomore!E4+'Other Income'!C2 -> 158235.24
B29: Total Revenue post GST | C29: =(C27/1.18)-(C27-C28) -> 133550.83

Sheet Offline & RG Community
A1: Date | B1: Day | C1: Offline booking hours | D1: Pickleball | E1: Turf | F1: Community Revenue | G1: Total Revenue | H1: Payment Gateway | I1: Net Revenue
A2: 46204 | B2: Wednesday | C2: 0 | D2: 0 | E2: 0 | F2: 0 | G2: =SUM(C2:F2) -> 0 | H2: =G2*1.75% -> 0 | I2: =G2-H2 -> 0
A3: 46205 | B3: Thursday | C3: 0 | D3: 0 | E3: 0 | F3: 0 | G3: =SUM(C3:F3) -> 0 | H3: =G3*1.75% -> 0 | I3: =G3-H3 -> 0
A4: 46206 | B4: Friday | C4: 0 | D4: 0 | E4: 0 | F4: 0 | G4: =SUM(C4:F4) -> 0 | H4: =G4*1.75% -> 0 | I4: =G4-H4 -> 0
A5: 46207 | B5: Saturday | C5: 0 | D5: 0 | E5: 0 | F5: 0 | G5: =SUM(C5:F5) -> 0 | H5: =G5*1.75% -> 0 | I5: =G5-H5 -> 0
A6: 46208 | B6: Sunday | C6: 0 | D6: 0 | E6: 0 | F6: 0 | G6: =SUM(C6:F6) -> 0 | H6: =G6*1.75% -> 0 | I6: =G6-H6 -> 0
A7: 46209 | B7: Monday | C7: 0 | D7: 0 | E7: 0 | F7: 0 | G7: =SUM(C7:F7) -> 0 | H7: =G7*1.75% -> 0 | I7: =G7-H7 -> 0
A8: 46210 | B8: Tuesday | C8: 0 | D8: 0 | E8: 0 | F8: 0 | G8: =SUM(C8:F8) -> 0 | H8: =G8*1.75% -> 0 | I8: =G8-H8 -> 0
A9: 46211 | B9: Wednesday | C9: 0 | D9: 0 | E9: 0 | F9: 0 | G9: =SUM(C9:F9) -> 0 | H9: =G9*1.75% -> 0 | I9: =G9-H9 -> 0
A10: 46212 | B10: Thursday | C10: 0 | D10: 0 | E10: 0 | F10: 0 | G10: =SUM(C10:F10) -> 0 | H10: =G10*1.75% -> 0 | I10: =G10-H10 -> 0
A11: 46213 | B11: Friday | C11: 0 | D11: 0 | E11: 0 | F11: 0 | G11: =SUM(C11:F11) -> 0 | H11: =G11*1.75% -> 0 | I11: =G11-H11 -> 0
A12: 46214 | B12: Saturday | C12: 0.5 | D12: 0 | E12: 850 | F12: 0 | G12: =SUM(C12:F12) -> 850.5 | H12: =G12*1.75% -> 14.88375 | I12: =G12-H12 -> 835.61625
A13: 46215 | B13: Sunday | C13: 2 | D13: 0 | E13: 0 | F13: 0 | G13: =SUM(C13:F13) -> 2 | H13: =G13*1.75% -> 0.035 | I13: =G13-H13 -> 1.965
... A15: 46217 | B15: Tuesday | C15: 0.5 | D15: 350 | E15: 0 | F15: 0 | G15: =SUM(C15:F15) -> 350.5 | H15: =G15*1.75% -> 6.13375 | I15: =G15-H15 -> 344.36625
A16: 46218 | B16: Wednesday | C16: 0 | D16: 0 | E16: 0 | F16: 0 | G16: 0 | H16: =G16*1.75% -> 0 | I16: =G16-H16 -> 0
A17: 46219 | B17: Thursday | C17: 2 | D17: 0 | E17: 2840 | F17: 0 | G17: =SUM(C17:F17) -> 2842 | H17: =G17*1.75% -> 49.735 | I17: =G17-H17 -> 2792.265
A18: 46220 | B18: Friday | C18: 1 | D18: 600 | E18: 0 | F18: 0 | G18: =SUM(C18:F18) -> 601 | H18: =G18*1.75% -> 10.5175 | I18: =G18-H18 -> 590.4825
A19: 46221 | B19: Saturday | C19: 3 | D19: 1800 | E19: 0 | F19: 0 | G19: =SUM(C19:F19) -> 1803 | H19: =G19*1.75% -> 31.5525 | I19: =G19-H19 -> 1771.4475
A20: 46222 | B20: Sunday | C20: 0.5 | D20: 350 | E20: 0 | F20: 0 | G20: =SUM(C20:F20) -> 350.5 | H20: =G20*1.75% -> 6.13375 | I20: =G20-H20 -> 344.36625
A21: 46223 | B21: Monday | C21: 0 | D21: 0 | E21: 0 | F21: 0 | G21: =SUM(C21:F21) -> 0 | H21: =G21*1.75% -> 0 | I21: =G21-H21 -> 0
A22: 46224 | B22: Tuesday | C22: 0 | D22: 0 | E22: 0 | F22: 0 | G22: =SUM(C22:F22) -> 0 | H22: =G22*1.75% -> 0 | I22: =G22-H22 -> 0
A23: 46225 | B23: Wednesday | C23: 0 | D23: 0 | E23: 0 | F23: 0 | G23: =SUM(C23:F23) -> 0 | H23: =G23*1.75% -> 0 | I23: =G23-H23 -> 0
A24: 46226 | B24: Thursday | C24: 0 | D24: 0 | E24: 0 | F24: 0 | G24: =SUM(C24:F24) -> 0 | H24: =G24*1.75% -> 0 | I24: =G24-H24 -> 0
A25: 46227 | B25: Friday | C25: 0 | D25: 0 | E25: 0 | F25: 0 | G25: =SUM(C25:F25) -> 0 | H25: =G25*1.75% -> 0 | I25: =G25-H25 -> 0
A26: 46228 | B26: Saturday | C26: 0 | D26: 0 | E26: 0 | F26: 0 | G26: =SUM(C26:F26) -> 0 | H26: =G26*1.75% -> 0 | I26: =G26-H26 -> 0
A27: 46229 | B27: Sunday | C27: 2 | D27: 0 | E27: 0 | F27: 0 | G27: =SUM(C27:F27) -> 2 | H27: =G27*1.75% -> 0.035 | I27: =G27-H27 -> 1.965
A28: 46230 | B28: Monday | C28: 0 | D28: 0 | E28: 0 | F28: 0 | G28: =SUM(C28:F28) -> 0 | H28: =G28*1.75% -> 0 | I28: =G28-H28 -> 0
... A32: 46234 | B32: Friday | C32: 0 | D32: 0 | E32: 0 | F32: 0 | G32: =SUM(C32:F32) -> 0 | H32: =G32*1.75% -> 0 | I32: =G32-H32 -> 0
A33: Total | C33: =SUM(C2:C32) -> 13.5 | D33: =SUM(D1:D32) -> 3100 | E33: =sum(E1:E32) -> 5790 | F33: =SUM(F1:F32) -> 0 | G33: =SUM(G1:G32) -> 8903.5 | H33: =SUM(H1:H32) -> 155.81125 | I33: =SUM(I1:I32) -> 8747.6887

Sheet District
A1: Link | B1: Date | C1: Paid to District | D1: Commissions (₹) | E1: GST on Commission | F1: Net Revenue | G1: TCS | H1: TDS | I1: Final Amount (₹)
B2: 1 - 31 July | C2: 2946 | D2: 206 | E2: 37 | F2: =C2-D2-E2 -> 2703 | G2: 14 | H2: 3 | I2: =F2-G2-H2 -> 2686
B4: Total | C4: =SUM(C2:C3) -> 2946 | F4: =SUM(F2:F3) -> 2703 | I4: =SUM(I2:I3) -> 2686
A6: Pickleball | B6: =C4-B7-B8 -> 0
A7: Turf | B7: 2946

Sheet Hudle
A1: Link | B1: Date | C1: Paid to Hudle | D1: Commisions (Including GST) | E1: Net Revenue | F1: TDS | G1: TCS | H1: Amount
B2: 1 - 31 July | C2: 4400 | D2: 572 | E2: =C2-D2 -> 3828 | F2: 4 | G2: 18 | H2: 3805
B3: Total | C3: =SUM(C2) -> 4400 | E3: =SUM(E2) -> 3828 | H3: =SUM(H2) -> 3805
A5: Pickleball | B5: =C3-B6-B7 -> 4400
A6: Turf | B6: 0

Sheet Playo
A1: Link | B1: Date | C1: Paid to Playo (₹) | D1: Commissions (₹) | E1: GST (₹) | F1: Net Revenue | G1: TDS (₹) | H1: TCS (₹) | I1: Final Amount (₹)
B2: 1 - 31 July | C2: 17555 | D2: 1802 | E2: 324 | F2: =C2-D2-E2 -> 15429 | G2: 13 | H2: 0 | I2: =F2-G2 -> 15416
B3: Total | C3: =sum(C2) -> 17555 | F3: =sum(F2) -> 15429 | I3: =sum(I2) -> 15416
A5: Pickleball | B5: =C3-B6 -> 3080
A6: Turf | B6: 14475

Sheet Khelomore
B1: Date | C1: Paid to Khelomore (₹) | D1: Commissions (₹) | E1: Final Amount (₹)
B2: 1 - 31 July | C2: 10029 | D2: =C2*5% -> 501.45 | E2: =C2-D2 -> 9527.55
B4: Total | C4: =SUM(C2) -> 10029 | E4: =SUM(E2) -> 9527.55
A6: Pickleball | B6: =C4-B7-B8 -> 5235
A7: Turf | B7: 4794

Sheet Other Income
A1: Month | B1: Sports Type | C1: Amount Collected
A2: July | B2: Padel Operations & Management Fees | C2: 118000
