Workbook

Sheet Summary
B2: 1 - 30 June
B3: Particulars | C3: Amount
C4: Total | D4: Pickleball | E4: Turf
B5: Pay & Play | C5: =sum(C6,C12) -> 209687 | D5: =sum(D6,D12) -> 102234 | E5: =sum(E6,E12) -> 107453
B6: Online | C6: =sum(C7:C11) -> 74190 | D6: =sum(D7:D11) -> 47504 | E6: =sum(E7:E11) -> 26686
B7: District | C7: =District!C3 -> 74190 | D7: =District!B5 -> 47504 | E7: =District!B6 -> 26686
B8: Hudle | C8: 0 | D8: 0 | E8: 0
B9: Playo | C9: 0 | D9: 0 | E9: 0
B10: Khelomore | C10: 0 | D10: 0 | E10: 0
B11: Zplys | C11: 0 | D11: 0 | E11: 0
B12: Offline | C12: =sum(C13:C14) -> 135497 | D12: =sum(D13:D14) -> 54730 | E12: =sum(E13:E14) -> 80767
B13: Bookings | C13: ='Offline & RG Community'!E32+'Offline & RG Community'!F32 -> 104697 | D13: ='Offline & RG Community'!E32 -> 45330 | E13: ='Offline & RG Community'!F32 -> 59367
B14: Memberships | C14: =Memberships!E4 -> 30800 | D14: =Memberships!E3/2 -> 9400 | E14: =Memberships!E2+(Memberships!E3/2) -> 21400
B15: Community | C15: =sum(C16:C17) -> 480 | D15: =sum(D16:D17) -> 480 | E15: =sum(E16:E17) -> 0
B16: Pickup games | C16: ='Offline & RG Community'!G32 -> 480 | D16: ='Offline & RG Community'!G32 -> 480 | E16: 0
B17: Social Events/Tournaments | C17: 0 | D17: 0 | E17: 0
B18: Academy | C18: 0 | D18: 0 | E18: 0
B19: Events & Partnership | C19: =sum(C20,C21) -> 0 | D19: =sum(D20,D21) -> 0 | E19: 0
B20: Corporate events | C20: 0 | D20: 0 | E20: 0
B21: All B2B partnerships | C21: 0 | D21: 0 | E21: 0
B22: Commerce | C22: =sum(C23:C25) -> 3325 | D22: =sum(D23:D25) -> 3325 | E22: =sum(E23:E25) -> 0
B23: Product rental | C23: ='Offline & RG Community'!H32 -> 3325 | D23: ='Offline & RG Community'!H32 -> 3325 | E23: 0
B24: Product sales | C24: 0 | D24: 0 | E24: 0
B25: F&B | C25: 0 | D25: 0 | E25: 0
B26: Other Income | C26: 0 | D26: 0 | E26: 0
B27: Total Gross Revenue | C27: =C6+C12+C15+C18+C19+C22+C26 -> 213492 | D27: =D6+D12+D15+D18+D19+D22+D26 -> 106039 | E27: =E6+E12+E15+E18+E19+E22+E26 -> 107453
B28: Total Net Revenue (Post Commissions) | C28: ='Offline & RG Community'!K32+District!F3+Memberships!G4 -> 204751.21
B29: Total Revenue post GST | C29: =C28/1.18 -> 173517.98

Sheet Offline & RG Community
A1: Date | B1: Day | C1: Offline booking hours | D1: Discount | E1: Booking Revenue | F1: Booking Revenue (Turf) | G1: Community Revenue | H1: Paddle Rental | I1: Total Revenue | J1: Payment Gateway | K1: Net Revenue
A2: 46174 | B2: Monday | C2: 2.5 | D2: 20 & 30% | E2: 1600 | F2: 1800 | G2: 0 | H2: 0 | I2: =sum(E2:H2) -> 3400 | J2: =I2*1.75% -> 59.5 | K2: =I2-J2 -> 3340.5
A3: 46175 | B3: Tuesday | C3: 2.5 | D3: 20 & 30% | E3: 1600 | F3: 0 | G3: 0 | H3: 0 | I3: =sum(E3:H3) -> 1600 | J3: =I3*1.75% -> 28 | K3: =I3-J3 -> 1572
A4: 46176 | B4: Wednesday | C4: 0.5 | D4: 20 & 30% | E4: 320 | F4: 0 | G4: 0 | H4: 50 | I4: =sum(E4:H4) -> 370 | J4: =I4*1.75% -> 6.475 | K4: =I4-J4 -> 363.525
A5: 46177 | B5: Thursday | C5: 0 | D5: 20 & 30% | E5: 0 | F5: 0 | G5: 0 | H5: 0 | I5: =sum(E5:H5) -> 0 | J5: =I5*1.75% -> 0 | K5: =I5-J5 -> 0
A6: 46178 | B6: Friday | C6: 5 | D6: 20 & 30% | E6: 3200 | F6: 0 | G6: 0 | H6: 400 | I6: =sum(E6:H6) -> 3600 | J6: =I6*1.75% -> 63 | K6: =I6-J6 -> 3537
A7: 46179 | B7: Saturday | C7: 6 | D7: 20 & 30% | E7: 1280 | F7: 5120 | G7: 0 | H7: 200 | I7: =sum(E7:H7) -> 6600 | J7: =I7*1.75% -> 115.5 | K7: =I7-J7 -> 6484.5
A8: 46180 | B8: Sunday | C8: 3 | D8: 20 & 30% | E8: 1920 | F8: 0 | G8: 0 | H8: 0 | I8: =sum(E8:H8) -> 1920 | J8: =I8*1.75% -> 33.6 | K8: =I8-J8 -> 1886.4
A9: 46181 | B9: Monday | C9: 2.5 | D9: 20 & 30% | E9: 1600 | F9: 0 | G9: 0 | H9: 0 | I9: =sum(E9:H9) -> 1600 | J9: =I9*1.75% -> 28 | K9: =I9-J9 -> 1572
A10: 46182 | B10: Tuesday | C10: 0.5 | D10: 20 & 30% | E10: 320 | F10: 6280 | G10: 0 | H10: 0 | I10: =sum(E10:H10) -> 6600 | J10: =I10*1.75% -> 115.5 | K10: =I10-J10 -> 6484.5
A11: 46183 | B11: Wednesday | C11: 4.5 | D11: 20 & 30% | E11: 2880 | F11: 1480 | G11: 0 | H11: 0 | I11: =sum(E11:H11) -> 4360 | J11: =I11*1.75% -> 76.3 | K11: =I11-J11 -> 4283.7
A12: 46184 | B12: Thursday | C12: 1.5 | D12: 20 & 30% | E12: 320 | F12: 0 | G12: 0 | H12: 100 | I12: =sum(E12:H12) -> 420 | J12: =I12*1.75% -> 7.35 | K12: =I12-J12 -> 412.65
A13: 46185 | B13: Friday | C13: 2.5 | D13: 20 & 30% | E13: =620+1600 -> 2220 | F13: =3840+1280 -> 5120 | G13: 0 | H13: 100 | I13: =sum(E13:H13) -> 7440 | J13: =I13*1.75% -> 130.2 | K13: =I13-J13 -> 7309.8
A14: 46186 | B14: Saturday | C14: 9.5 | D14: 20 & 30% | E14: 6080 | F14: 5120 | G14: 0 | H14: 400 | I14: =sum(E14:H14) -> 11600 | J14: =I14*1.75% -> 203 | K14: =I14-J14 -> 11397
A15: 46187 | B15: Sunday | C15: 2.5 | D15: 20 & 30% | E15: =1280+730 -> 2010 | F15: 3040 | G15: 0 | H15: 200 | I15: =sum(E15:H15) -> 5250 | J15: =I15*1.75% -> 91.875 | K15: =I15-J15 -> 5158.125
A16: 46188 | B16: Monday | C16: 5 | D16: 20 & 30% | E16: =320+790+960 -> 2070 | F16: =1280*2 -> 2560 | G16: 0 | H16: 0 | I16: =SUM(E16:H16) -> 4630 | J16: =I16*1.75% -> 81.025 | K16: =I16-J16 -> 4548.975
A17: 46189 | B17: Tuesday | C17: 4 | D17: 20 & 30% | E17: =740+740 -> 1480 | F17: =1280+1920 -> 3200 | G17: 0 | H17: 300 | I17: =SUM(E17:H17) -> 4980 | J17: =I17*1.75% -> 87.15 | K17: =I17-J17 -> 4892.85
A18: 46190 | B18: Wednesday | C18: 3.5 | D18: 20 & 30% | E18: =E19 -> 0 | F18: 0 | G18: 0 | H18: 250 | I18: =SUM(E18:H18) -> 250 | J18: =I18*1.75% -> 4.375 | K18: =I18-J18 -> 245.625
A19: 46191 | B19: Thursday | C19: 2.5 | D19: 20 & 30% | E19: 0 | F19: 0 | G19: 0 | H19: 0 | I19: =SUM(E19:H19) -> 0 | J19: =I19*1.75% -> 0 | K19: =I19-J19 -> 0
A20: 46192 | B20: Friday | C20: 1 | D20: 20 & 30% | E20: 640 | F20: 0 | G20: 0 | H20: 0 | I20: =SUM(E20:H20) -> 640 | J20: =I20*1.75% -> 11.2 | K20: =I20-J20 -> 628.8
A21: 46193 | B21: Saturday | C21: 5 | D21: 20 & 30% | E21: 1600 | F21: 3200 | G21: 0 | H21: 425 | I21: =SUM(E21:H21) -> 5225 | J21: =I21*1.75% -> 91.4375 | K21: =I21-J21 -> 5133.5625
A22: 46194 | B22: Sunday | C22: 6.5 | D22: 20 & 30% | E22: =1160+560 -> 1720 | F22: =2560+3200+2247 -> 8007 | G22: 0 | H22: 0 | I22: =sum(E22:H22) -> 9727 | J22: =I22*1.75% -> 170.2225 | K22: =I22-J22 -> 9556.7775
A23: 46195 | B23: Monday | C23: 3 | D23: 20 & 30% | E23: 1280 | F23: 1000 | G23: 0 | H23: 100 | I23: =SUM(E23:H23) -> 2380 | J23: =I23*1.75% -> 41.65 | K23: =I23-J23 -> 2338.35
A24: 46196 | B24: Tuesday | C24: 1 | D24: 20 & 30% | E24: 640 | F24: 0 | G24: 0 | H24: 50 | I24: =SUM(E24:H24) -> 690 | J24: =I24*1.75% -> 12.075 | K24: =I24-J24 -> 677.925
A25: 46197 | B25: Wednesday | C25: 1 | D25: 20 & 30% | E25: 640 | F25: 1920 | G25: 0 | H25: 0 | I25: =SUM(E25:H25) -> 2560 | J25: =I25*1.75% -> 44.8 | K25: =I25-J25 -> 2515.2
A26: 46198 | B26: Thursday | C26: 3.5 | D26: 20 & 30% | E26: 1600 | F26: 0 | G26: 480 | H26: 200 | I26: =SUM(E26:H26) -> 2280 | J26: =I26*1.75% -> 39.9 | K26: =I26-J26 -> 2240.1
A27: 46199 | B27: Friday | C27: 2 | D27: 20 & 30% | E27: =640+640+320 -> 1600 | F27: 0 | G27: 0 | H27: 0 | I27: =SUM(E27:H27) -> 1600 | J27: =I27*1.75% -> 28 | K27: =I27-J27 -> 1572
A28: 46200 | B28: Saturday | C28: 5 | D28: 20 & 30% | E28: 3200 | F28: 5120 | G28: 0 | H28: 300 | I28: =SUM(E28:H28) -> 8620 | J28: =I28*1.75% -> 150.85 | K28: =I28-J28 -> 8469.15
A29: 46201 | B29: Sunday | C29: 5 | D29: 20 & 30% | E29: =790+360+1500-100 -> 2550 | F29: =2560*2 -> 5120 | G29: 0 | H29: 200 | I29: =SUM(E29:H29) -> 7870 | J29: =I29*1.75% -> 137.725 | K29: =I29-J29 -> 7732.275
A30: 46202 | B30: Monday | C30: 0 | D30: 20 & 30% | E30: 0 | F30: 0 | G30: 0 | H30: 0 | I30: =SUM(E30:H30) -> 0 | J30: =I30*1.75% -> 0 | K30: =I30-J30 -> 0
A31: 46203 | B31: Tuesday | C31: 1.5 | D31: 20 & 30% | E31: 960 | F31: 1280 | G31: 0 | H31: 50 | I31: =SUM(E31:H31) -> 2290 | J31: =I31*1.75% -> 40.075 | K31: =I31-J31 -> 2249.925
A32: Total | C32: =SUM(C2:C31) -> 92.5 | E32: =sum(E2:E31) -> 45330 | F32: =sum(F2:F31) -> 59367 | G32: =sum(G2:G31) -> 480 | H32: =sum(H2:H31) -> 3325 | I32: =sum(I2:I31) -> 108502 | J32: =sum(J2:J31) -> 1898.785 | K32: =sum(K2:K31) -> 106603.21

Sheet District
A1: Link | B1: Date | C1: Paid to District | D1: Commissions (₹) | E1: GST on Commission | F1: Net Revenue | G1: TCS | H1: TDS | I1: Final Amount (₹)
B2: 1 - 30 June | C2: 74190 | D2: 4877 | E2: 1755 | F2: =C2-D2-E2 -> 67558 | G2: 372 | H2: 74 | I2: =F2-G2-H2 -> 67112
B3: Total | C3: =SUM(C2) -> 74190 | F3: =SUM(F2) -> 67558 | I3: =SUM(I2) -> 67112
A5: Pickleball | B5: =C3-B6 -> 47504
A6: Turf | B6: 26686

Sheet Memberships
A1: Member Name | B1: Sports Type | C1: Membership Type | D1: Start Date | E1: Amount Collected | F1: Payment Gateway | G1: Net Revenue
A2: Sunil | B2: Box Cricket | C2: 10 Hours | D2: 46203 | E2: 12000 | F2: =E2*1.75% -> 210 | G2: =E2-F2 -> 11790
A3: ISH | B3: Turf and Pickleball | C3: Custom | D3: June | E3: 18800 | F3: 0 | G3: =E3-F3 -> 18800
A4: Total | E4: =SUM(E2:E3) -> 30800 | F4: =SUM(F2:F3) -> 210 | G4: =SUM(G2:G3) -> 30590
