Workbook

Sheet Summary
B2: Date: 1st Oct - 31st Oct
B3: Particulars | C3: Amount
B4: Offline | C4: =SUM(C5,C6,C7,C8, C9) -> 15260
B5: Rentals | C5: =sum('Offline & RG Community'!F33) -> 6550
B6: F&B | C6: 0
B7: Product Sales | C7: 0
B8: Rallygully Community games | C8: 5200
B9: Bookings | C9: ='Offline & RG Community'!E33-C8 -> 3510
B10: Online: Third Party Platform | C10: =SUM(C11:C15) -> 132672.6
B11: Hudle | C11: =Hudle!C7 -> 115555
B12: Playo | C12: =Playo!C6 -> 5917.6
B13: District | C13: =District!B2 -> 1200
B14: Khelomore | C14: =Khelomore!C4 -> 4800
B15: Misfits Community | C15: =Misfits!C2 -> 5200
B16: Memberships | C16: =Memberships!E2 -> 15300
B17: Corporate Events | C17: 0
B18: Brand Activation | C18: ='Brand Activation'!C2 -> 15000
B19: Other Income | C19: 0
B20: Total Gross Revenue | C20: =sum(C4,C10,C16,C17,C18,C19) -> 178232.6
B21: Total Net Revenue (Post Commissions) | C21: =sum('Offline & RG Community'!G33,Hudle!E7,Playo!F6,District!F2,Khelomore!E4,Misfits!D2,Memberships!E2,'Brand Activation'!C2) -> 161389.26
B22: Total Revenue post GST | C22: =C21/1.18 -> 136770.56
B23: Expenses
B24: Venue Manager + Cleaner | C24: =5500+25000 -> 30500
B25: Marketing, Branding & Community | C25: 15000
B26: Total | C26: =C24+C25 -> 45500
B27: Net Profit (Revenue- Expense) | C27: =C22-C26 -> 91270.559
B29: School's Profit Share (65%) | C29: =C27*65% -> 59325.864
B30: RallyGully's Profit Share (35%) | C30: =C27*35% -> 31944.696

Sheet Offline & RG Community
A1: Date | B1: Day | C1: Total Offline (Hours) | D1: Discount Given | E1: Revenue | F1: Paddle Rental | G1: Total Revenue
A2: 45931 | B2: Wednesday | C2: 0 | D2: 0 | E2: 0 | F2: 400 | G2: =sum(E2:F2) -> 400
A3: 45932 | B3: Thursday | C3: 0 | D3: 0 | E3: 0 | F3: 400 | G3: =sum(E3:F3) -> 400
A4: 45933 | B4: Friday | C4: 0 | D4: 0 | E4: 0 | F4: 200 | G4: =sum(E4:F4) -> 200
A5: 45934 | B5: Saturday | C5: 0 | D5: 0 | E5: 0 | F5: 200 | G5: =sum(E5:F5) -> 200
A6: 45935 | B6: Sunday | C6: 0 | D6: 0 | E6: 0 | F6: 800 | G6: =sum(E6:F6) -> 800
A7: 45936 | B7: Monday | C7: 0 | D7: 0 | E7: 0 | F7: 0 | G7: =sum(E7:F7) -> 0
A8: 45937 | B8: Tuesday | C8: 0 | D8: 0 | E8: 0 | F8: 200 | G8: =sum(E8:F8) -> 200
A9: 45938 | B9: Wednesday | C9: 0 | D9: 0 | E9: 0 | F9: 0 | G9: =sum(E9:F9) -> 0
A10: 45939 | B10: Thursday | C10: 0 | D10: 0 | E10: 0 | F10: 0 | G10: 0
A11: 45940 | B11: Friday | C11: 0 | D11: 0 | E11: 0 | F11: 0 | G11: 0
A12: 45941 | B12: Saturday | C12: 0 | D12: 0 | E12: 0 | F12: 0 | G12: 0
A13: 45942 | B13: Sunday | C13: 0 | D13: 0 | E13: 0 | F13: 0 | G13: 0
A14: 45943 | B14: Monday | C14: 0 | D14: 0 | E14: 0 | F14: 0 | G14: 0
A15: 45944 | B15: Tuesday | C15: 0 | D15: 0 | E15: 0 | F15: 0 | G15: 0
A16: 45945 | B16: Wednesday | C16: 0 | D16: 0 | E16: 0 | F16: 0 | G16: 0
A17: 45946 | B17: Thursday | C17: 0 | D17: 0 | E17: 0 | F17: 0 | G17: 0
A18: 45947 | B18: Friday | C18: 0 | D18: 0 | E18: 0 | F18: 0 | G18: 0
A19: 45948 | B19: Saturday | C19: 0 | D19: 0 | E19: 0 | F19: 100 | G19: =SUM(E19:F19) -> 100
A20: 45949 | B20: Sunday | C20: 1 | D20: 0 | E20: 250 | F20: 0 | G20: 250
A21: 45950 | B21: Monday | C21: 0 | D21: 0 | E21: 0 | F21: 0 | G21: =SUM(E21:F21) -> 0
A22: 45951 | B22: Tuesday | C22: 0 | D22: 0 | E22: 0 | F22: 600 | G22: =SUM(E22:F22) -> 600
A23: 45952 | B23: Wednesday | C23: 0 | D23: 0 | E23: 0 | F23: 200 | G23: =SUM(E23:F23) -> 200
A24: 45953 | B24: Thursday | C24: 0 | D24: 0 | E24: 0 | F24: 400 | G24: =SUM(E24:F24) -> 400
A25: 45954 | B25: Friday | C25: 1.5 | D25: 0 | E25: 1620 | F25: 200 | G25: =SUM(E25:F25) -> 1820
A26: 45955 | B26: Saturday | C26: 0.5 | D26: 0 | E26: 600 | F26: 600 | G26: =SUM(E26:F26) -> 1200
A27: 45956 | B27: Sunday | C27: 5 | D27: 0 | E27: 3300 | F27: 1200 | G27: =SUM(E27:F27) -> 4500
A28: 45957 | B28: Monday | C28: 1 | D28: 0 | E28: 1200 | F28: 800 | G28: =SUM(E28:F28) -> 2000
A29: 45958 | B29: Tuesday | C29: 0.5 | D29: 0 | E29: 570 | F29: 100 | G29: 670
A30: 45959 | B30: Wednesday | C30: 0 | D30: 0 | E30: 0 | F30: 0 | G30: 0
A31: 45960 | B31: Thursday | C31: 0.5 | D31: 0 | E31: 570 | F31: 0 | G31: 570
A32: 45961 | B32: Friday | C32: 1 | D32: 0 | E32: 600 | F32: 150 | G32: 750
A33: Total | B33: October | C33: =SUM(C2:C32) -> 11 | E33: =SUM(E2:E32) -> 8710 | F33: =SUM(F2:F32) -> 6550 | G33: =SUM(G2:G32) -> 15260

Sheet Hudle
A1: Link | B1: Date | C1: Paid to Hudle | D1: Commisions (Including GST) | E1: Net Revenue | F1: TDS | G1: TCS | H1: Amount
B2: 30 Sep - 7 Oct | C2: 37440 | D2: 4867.2 | E2: =C2-D2 -> 32572.8 | F2: 31.72 | G2: 158.64 | H2: 32375.33
B3: 7 Oct - 14 Oct | C3: 11800 | D3: 1534 | E3: =C3-D3 -> 10266 | F3: 10.0001 | G3: 50.0001 | H3: 10206.02
B4: 14 Oct - 21 Oct | C4: 29965 | D4: 3901.5 | E4: =C4-D4 -> 26063.5 | F4: 25.43 | G4: 127.18 | H4: 25960.49
B5: 21 Oct - 28 Oct | C5: 26200 | D5: 3406 | E5: =C5-D5 -> 22794 | F5: 22.2 | G5: 111.01 | H5: 22660.82
B6: 28 Oct - 31 Oct | C6: 10150 | D6: 1326 | E6: =C6-D6 -> 8824 | F6: 8.64 | G6: 43.22 | H6: 8822.15
C7: =SUM(C2:C6) -> 115555 | E7: =SUM(E2:E6) -> 100520.3 | H7: =SUM(H2:H6) -> 100024.81

Sheet Playo
A1: Link | B1: Date | C1: Paid to Playo (₹) | D1: Commissions (₹) | E1: GST (₹) | F1: Net Revenue | G1: TDS (₹) | H1: TCS (₹) | I1: Final Amount (₹)
B2: 29 Sep - 30 Sep | C2: 1917.6 | D2: 168 | E2: 30.24 | F2: =C2-D2-E2 -> 1719.36 | G2: 1.92 | H2: 9.58 | I2: 1707.86
B3: 1 Oct - 5 Oct | C3: 1200 | D3: 84 | E3: 15.12 | F3: =C3-D3-E3 -> 1100.88 | G3: 1.2 | H3: 6 | I3: 1093.68
B4: 20 Oct - 26 Oct | C4: 2800 | D4: 196 | E4: 35.28 | F4: =C4-D4-E4 -> 2568.72 | G4: 2.8 | H4: 14 | I4: 2551.92
C6: =SUM(C2:C4) -> 5917.6 | F6: =SUM(F2:F4) -> 5388.96 | I6: =SUM(I2:I4) -> 5353.46

Sheet District
A1: Date | B1: Paid to District | C1: Commisions (Including GST) | D1: TDS | E1: TCS | F1: Amount
A2: 45959 | B2: 1200 | C2: 0 | D2: 0 | E2: 0 | F2: 1200

Sheet Khelomore
A1: Link | B1: Date | C1: Paid to Khelomore (₹) | D1: Commissions (₹) | E1: Final Amount (₹)
B2: 1 - 21 Oct | C2: 3600 | D2: 180 | E2: 3420
B3: 22 - 31 Oct | C3: 1200 | D3: 60 | E3: 1140
C4: =SUM(C2:C3) -> 4800 | E4: =SUM(E2:E3) -> 4560

Sheet Misfits
A1: Link | B1: Date | C1: Paid to Misfits (₹) | D1: Post Comission (20%) | E1: TDS | F1: Final Amount (₹)
B2: October | C2: 5200 | D2: =C2 - (C2 * 20%) -> 4160 | E2: 0.02 | F2: =D2 - D2*E2 -> 4076.8

Sheet Memberships
A1: Member Name | B1: Sports Type | C1: Membership Type | D1: Start Date | E1: Amount Collected
A2: Nitin | B2: Pickleball | C2: Rally Pack (15) | D2: 45955 | E2: 15300

Sheet Brand Activation
A1: Date & Day | B1: Brand Name | C1: Amount | D1: Timings | E1: Type of collab
A2: 8 Nov & Saturday | B2: Savikalpa | C2: 15000 | D2: 5-9 PM | E2: On court activation for community game
