Workbook

Sheet Summary
B2: 1 - 30 April
B3: Particulars | C3: Amount
C4: Total | D4: Pickleball | E4: Turf
B5: Pay & Play | C5: =sum(C6,C12) -> 173128 | D5: =sum(D6,D12) -> 90470 | E5: =sum(E6,E12) -> 82658
B6: Online | C6: =sum(C7:C11) -> 48628 | D6: =sum(D7:D11) -> 30150 | E6: =sum(E7:E11) -> 18478
B7: District | C7: =District!C4 -> 19000 | D7: =District!B6 -> 13700 | E7: =District!B7 -> 5300
B8: Hudle | C8: =Hudle!C7 -> 25628 | D8: =Hudle!B9 -> 14850 | E8: =Hudle!B10 -> 10778
B9: Playo | C9: =Playo!C4 -> 3200 | D9: =Playo!B6 -> 800 | E9: =Playo!B7 -> 2400
B10: Khelomore | C10: =Khelomore!C3 -> 800 | D10: =Khelomore!C2 -> 800 | E10: 0
B11: Zplys | C11: 0 | D11: 0 | E11: 0
B12: Offline | C12: =sum(C13:C14) -> 124500 | D12: =sum(D13:D14) -> 60320 | E12: =sum(E13:E14) -> 64180
B13: Bookings | C13: ='Offline & RG Community'!E32+'Offline & RG Community'!F32 -> 105700 | D13: ='Offline & RG Community'!E32 -> 50920 | E13: ='Offline & RG Community'!F32 -> 54780
B14: Memberships | C14: =Memberships!D2 -> 18800 | D14: =Memberships!D2/2 -> 9400 | E14: =Memberships!D2/2 -> 9400
B15: Community | C15: =sum(C16:C17) -> 0 | D15: =sum(D16:D17) -> 0 | E15: =sum(E16:E17) -> 0
B16: Pickup games | C16: 0 | D16: 0 | E16: 0
B17: Social Events/Tournaments | C17: 0 | D17: 0 | E17: 0
B18: Academy | C18: 0 | D18: 0 | E18: 0
B19: Events & Partnership | C19: =sum(C20,C21) -> 2560 | D19: =sum(D20,D21) -> 0 | E19: =sum(E20,E21) -> 2560
B20: Corporate events | C20: ='Corporate Events'!D2 -> 2560 | D20: 0 | E20: ='Corporate Events'!D2 -> 2560
B21: All B2B partnerships | C21: 0 | D21: 0 | E21: 0
B22: Commerce | C22: =sum(C23:C25) -> 8225 | D22: =sum(D23:D25) -> 8225 | E22: =sum(E23:E25) -> 0
B23: Product rental | C23: ='Offline & RG Community'!G32 -> 8225 | D23: ='Offline & RG Community'!G32 -> 8225 | E23: 0
B24: Product sales | C24: 0 | D24: 0 | E24: 0
B25: F&B | C25: 0 | D25: 0 | E25: 0
B26: Other Income | C26: 0 | D26: 0 | E26: 0
B27: Total Gross Revenue | C27: =C6+C12+C15+C18+C19+C22+C26 -> 183913 | D27: =D6+D12+D15+D18+D19+D22+D26 -> 98695 | E27: =E6+E12+E15+E18+E19+E22+E26 -> 85218
B28: Total Net Revenue (Post Commissions) | C28: ='Offline & RG Community'!J32+Hudle!E7+Playo!F4+District!F4+Khelomore!E3+'Corporate Events'!F2+Memberships!D2 -> 175761.69
B29: Total Revenue post GST | C29: =C28/1.18 -> 148950.59

Sheet Offline & RG Community
A1: Date | B1: Day | C1: Offline booking hours | D1: Discount Given | E1: Booking Revenue | F1: Booking Revenue (Turf) | G1: Paddle Rental | H1: Total Revenue | I1: Payment Gateway | J1: Net Revenue
A2: 1 Apr | B2: Wednesday | C2: 4 | D2: 15 and 30% | E2: 1280 | F2: 2560 | G2: 200 | H2: =sum(E2:G2) -> 4040 | I2: =H2*2.5%*1.18 -> 119.18 | J2: =H2-I2 -> 3920.82
A3: 2 Apr | B3: Thursday | C3: 4.5 | D3: 15 and 30% | E3: 1600 | F3: 2400 | G3: 350 | H3: =sum(E3:G3) -> 4350 | I3: =H3*2.5%*1.18 -> 128.325 | J3: =H3-I3 -> 4221.675
A4: 3 Apr | B4: Friday | C4: 4.5 | D4: 15 and 30% | E4: 0 | F4: 5400 | G4: 100 | H4: =sum(E4:G4) -> 5500 | I4: =H4*2.5%*1.18 -> 162.25 | J4: =H4-I4 -> 5337.75
A5: 4 Apr | B5: Saturday | C5: 5 | D5: 15 and 30% | E5: 1280 | F5: 3120 | G5: 550 | H5: =sum(E5:G5) -> 4950 | I5: =H5*2.5%*1.18 -> 146.025 | J5: =H5-I5 -> 4803.975
A6: 5 Apr | B6: Sunday | C6: 8 | D6: 15 and 30% | E6: 1920 | F6: 5900 | G6: 300 | H6: =sum(E6:G6) -> 8120 | I6: =H6*2.5%*1.18 -> 239.54 | J6: =H6-I6 -> 7880.46
A7: 6 Apr | B7: Monday | C7: 3.5 | D7: 15 and 30% | E7: 1600 | F7: 1200 | G7: 350 | H7: =sum(E7:G7) -> 3150 | I7: =H7*2.5%*1.18 -> 92.925 | J7: =H7-I7 -> 3057.075
A8: 7 Apr | B8: Tuesday | C8: 2 | D8: 15 and 30% | E8: 640 | F8: 1200 | G8: 50 | H8: =sum(E8:G8) -> 1890 | I8: =H8*2.5%*1.18 -> 55.755 | J8: =H8-I8 -> 1834.245
A9: 8 Apr | B9: Wednesday | C9: 2.5 | D9: 15 and 30% | E9: 1920 | F9: 0 | G9: 250 | H9: =sum(E9:G9) -> 2170 | I9: =H9*2.5%*1.18 -> 64.015 | J9: =H9-I9 -> 2105.985
A10: 9 Apr | B10: Thursday | C10: 3 | D10: 15 and 30% | E10: 1920 | F10: 0 | G10: 150 | H10: =sum(E10:G10) -> 2070 | I10: =H10*2.5%*1.18 -> 61.065 | J10: =H10-I10 -> 2008.935
A11: 10 Apr | B11: Friday | C11: 6.5 | D11: 15 and 30% | E11: 1280 | F11: 4320 | G11: 450 | H11: =sum(E11:G11) -> 6050 | I11: =H11*2.5%*1.18 -> 178.475 | J11: =H11-I11 -> 5871.525
A12: 11 Apr | B12: Saturday | C12: 7 | D12: 15 and 30% | E12: 3520 | F12: 1920 | G12: 700 | H12: =sum(E12:G12) -> 6140 | I12: =H12*2.5%*1.18 -> 181.13 | J12: =H12-I12 -> 5958.87
A13: 12 Apr | B13: Sunday | C13: 9 | D13: 15 and 30% | E13: 4480 | F13: 2200 | G13: 900 | H13: =sum(E13:G13) -> 7580 | I13: =H13*2.5%*1.18 -> 223.61 | J13: =H13-I13 -> 7356.39
... A16: 15 Apr | B16: Wednesday | C16: 4.5 | D16: 15 and 30% | E16: 1920 | F16: 1800 | G16: 50 | H16: =sum(E16:G16) -> 3770 | I16: =H16*2.5%*1.18 -> 111.215 | J16: =H16-I16 -> 3658.785
A17: 16 Apr | B17: Thursday | C17: 4.5 | D17: 15 and 30% | E17: 1600 | F17: 2560 | G17: 400 | H17: =SUM(E17:G17) -> 4560 | I17: =H17*2.5%*1.18 -> 134.52 | J17: =H17-I17 -> 4425.48
A18: 17 Apr | B18: Friday | C18: 2.5 | D18: 15 and 30% | E18: 960 | F18: 1280 | G18: 150 | H18: =SUM(E18:G18) -> 2390 | I18: =H18*2.5%*1.18 -> 70.505 | J18: =H18-I18 -> 2319.495
A19: 18 Apr | B19: Saturday | C19: 7 | D19: 15 and 30% | E19: 2560 | F19: 3840 | G19: 750 | H19: =SUM(E19:G19) -> 7150 | I19: =H19*2.5%*1.18 -> 210.925 | J19: =H19-I19 -> 6939.075
A20: 19 Apr | B20: Sunday | C20: 5 | D20: 15 and 30% | E20: 3200 | F20: 0 | G20: 350 | H20: =SUM(E20:G20) -> 3550 | I20: =H20*2.5%*1.18 -> 104.725 | J20: =H20-I20 -> 3445.275
A21: 20 Apr | B21: Monday | C21: 2.5 | D21: 15 and 30% | E21: 2240 | F21: 0 | G21: 50 | H21: =SUM(E21:G21) -> 2290 | I21: =H21*2.5%*1.18 -> 67.555 | J21: =H21-I21 -> 2222.445
A22: 21 Apr | B22: Tuesday | C22: 3.5 | D22: 15 and 30% | E22: 2240 | F22: 0 | G22: 350 | H22: =SUM(E22:G22) -> 2590 | I22: =H22*2.5%*1.18 -> 76.405 | J22: =H22-I22 -> 2513.595
A23: 22 Apr | B23: Wednesday | C23: 2.5 | D23: 15 and 30% | E23: 1600 | F23: 0 | G23: 100 | H23: =sum(E23:G23) -> 1700 | I23: =H23*2.5%*1.18 -> 50.15 | J23: =H23-I23 -> 1649.85
A24: 23 Apr | B24: Thursday | C24: 3 | D24: 15 and 30% | E24: 1960 | G24: 100 | H24: =SUM(E24:G24) -> 2060 | I24: =H24*2.5%*1.18 -> 60.77 | J24: =H24-I24 -> 1999.23
A25: 24 Apr | B25: Friday | C25: 5 | D25: 15 and 30% | E25: 2240 | F25: 2560 | G25: 300 | H25: =SUM(E25:G25) -> 5100 | I25: =H25*2.5%*1.18 -> 150.45 | J25: =H25-I25 -> 4949.55
A26: 25 Apr | B26: Saturday | C26: 3 | D26: 15 and 30% | E26: 0 | F26: 5120 | G26: 0 | H26: =SUM(E26:G26) -> 5120 | I26: =H26*2.5%*1.18 -> 151.04 | J26: =H26-I26 -> 4968.96
A27: 26 Apr | B27: Sunday | C27: 1 | D27: 15 and 30% | E27: 640 | F27: 0 | G27: 100 | H27: =SUM(E27:G27) -> 740 | I27: =H27*2.5%*1.18 -> 21.83 | J27: =H27-I27 -> 718.17
A28: 27 Apr | B28: Monday | C28: 2 | D28: 15 and 30% | E28: 320 | F28: 1800 | G28: 0 | H28: =SUM(E28:G28) -> 2120 | I28: =H28*2.5%*1.18 -> 62.54 | J28: =H28-I28 -> 2057.46
A29: 28 Apr | B29: Tuesday | C29: 3 | D29: 15 and 30% | E29: 960 | F29: 2560 | G29: 75 | H29: =SUM(E29:G29) -> 3595 | I29: =H29*2.5%*1.18 -> 106.0525 | J29: =H29-I29 -> 3488.9475
A30: 29 Apr | B30: Wednesday | C30: 3 | D30: 15 and 30% | E30: 1920 | F30: 640 | G30: 200 | H30: =SUM(E30:G30) -> 2760 | I30: =H30*2.5%*1.18 -> 81.42 | J30: =H30-I30 -> 2678.58
A31: 30 Apr | B31: Thursday | D31: 15 and 30% | I31: =H31*2.5%*1.18 -> 0 | J31: =H31-I31 -> 0
A32: Total | C32: =SUM(C2:C31) -> 123.5 | E32: =SUM(E2:E31) -> 50920 | F32: =SUM(F2:F31) -> 54780 | G32: =SUM(G2:G31) -> 8225 | H32: =SUM(H2:H31) -> 113925 | I32: =SUM(I2:I31) -> 3360.7875 | J32: =SUM(J2:J31) -> 110564.21

Sheet Hudle
A1: Link | B1: Date | C1: Paid to Hudle | D1: Commisions (Including GST) | E1: Net Revenue | F1: TDS | G1: TCS | H1: Amount
B2: 1-7 Apr | C2: 6320 | D2: 821 | E2: =C2-D2 -> 5499 | F2: 5.3 | G2: 26.77 | H2: 5466
B3: 7-12 Apr | C3: 7120 | D3: 925 | E3: =C3-D3 -> 6195 | F3: 6 | G3: 30.1 | H3: 6158
B4: 13-19 Apr | C4: 2880 | D4: 374 | E4: =C4-D4 -> 2506 | F4: 2.4 | G4: 12 | H4: 2490
B5: 19 - 28 Apr | C5: 8351 | D5: 1085 | E5: =C5-D5 -> 7266 | F5: 7 | G5: 35 | H5: 7222
B6: 28 - 30 Apr | C6: 957 | D6: 124 | E6: =C6-D6 -> 833 | F6: 0.8 | G6: 4 | H6: 828
B7: Total | C7: =SUM(C2:C6) -> 25628 | E7: =SUM(E2:E6) -> 22299 | H7: =SUM(H2:H6) -> 22164
A9: Pickleball | B9: =C7-B10 -> 14850
A10: Turf | B10: 10778

Sheet Playo
A1: Link | B1: Date | C1: Paid to Playo (₹) | D1: Commissions (₹) | E1: GST (₹) | F1: Net Revenue | G1: TDS (₹) | H1: TCS (₹) | I1: Final Amount (₹)
B2: 1 - 26 Apr | C2: 3200 | D2: 224 | E2: 60 | F2: =C2-D2-E2 -> 2916 | G2: 5.8 | H2: 1 | I2: 888.72
B3: 27 - 30 Apr | F3: =C3-D3-E3 -> 0
B4: Total | C4: =SUM(C2:C3) -> 3200 | F4: =SUM(F2:F3) -> 2916 | I4: =SUM(I2:I3) -> 888.72
A6: Pickleball | B6: 800
A7: Turf | B7: 2400

Sheet District
A1: Link | B1: Date | C1: Paid to District | D1: Commissions (₹) | E1: GST on Commission | F1: Net Revenue | G1: TCS | H1: TDS | I1: Final Amount (₹)
B2: 1 - 30 Apr | C2: 19000 | D2: 900 | E2: 162 | F2: =C2-D2-E2 -> 17938 | G2: 95 | H2: 19 | I2: 17824
B4: Total | C4: =SUM(C2:C3) -> 19000 | F4: =SUM(F2:F3) -> 17938 | I4: =SUM(I2:I3) -> 17824
A6: Pickleball | B6: =C4-B7 -> 13700
A7: Turf | B7: =1500 + 3100 + 700 -> 5300

Sheet Khelomore
A1: Link | B1: Date | C1: Paid to Khelomore (₹) | D1: Commissions (₹) | E1: Final Amount (₹)
B2: 1 - 30th Apr | C2: 800 | D2: =C2*5% -> 40 | E2: =C2-D2 -> 760
B3: Total | C3: =SUM(C2) -> 800 | E3: =SUM(E2) -> 760

Sheet Corporate Events
A1: Name | B1: Date | C1: Sport | D1: Amt | E1: Payment Gateway | F1: Net Revenue | G1: POC
A2: Bio Gas | B2: 46142 | C2: Box turf | D2: 2560 | E2: =D2*2.5%*1.18 -> 75.52 | F2: =D2-E2 -> 2484.48 | G2: Rishi

Sheet Memberships
A1: Name | B1: Date | C1: Sport | D1: Amt
A2: ISH | B2: Apr | C2: Turf and Pickleball | D2: 18800
G32: =SUM(I2:I31) -> 0
