Workbook

Sheet Summary
B2: 1 - 31 Aug
B3: Particulars | C3: Amount
C4: Pickleball
B5: Pay & Play | C5: =sum(C6,C12) -> 121907
B6: Online | C6: =sum(C7:C11) -> 112290
B7: District | C7: =District!C4 -> 112290
B8: Hudle | C8: 0
B9: Playo | C9: 0
B10: Khelomore | C10: 0
B11: Zplys | C11: 0
B12: Offline | C12: =sum(C13:C14) -> 9617
B13: Bookings | C13: ='Offline & RG Community'!D33 -> 9617
B14: Memberships | C14: 0
B15: Community | C15: =sum(C16:C18) -> 28774
B16: Pickup games | C16: ='Offline & RG Community'!E33 -> 18280
B17: Social Events/Tournaments | C17: ='Social EventsTournaments'!D4 -> 10494
B18: Community Partnerships | C18: 0
B19: Academy | C19: =Academy!C2 -> 48750
B20: Events & Partnership | C20: =sum(C21,C22) -> 0
B21: Corporate events | C21: 0
B22: All B2B partnerships | C22: 0
B23: Commerce | C23: =sum(C24:C26) -> 8065
B24: Product rental | C24: ='Offline & RG Community'!F33 -> 4000
B25: Product sales | C25: 0
B26: F&B | C26: ='F&B'!B33 -> 4065
B27: Other Income | C27: 0
B28: Total Gross Revenue | C28: =C5+C15+C19+C20+C23+C27 -> 207496
B29: GST (B) | C29: =C28-(C28/1.18) -> 31651.932
B30: Commissions, Payment gateway & Event Expense(C) | C30: ='Offline & RG Community'!H33+District!D4+District!E4+'Social EventsTournaments'!E4+'Social EventsTournaments'!F4+'Social EventsTournaments'!G4+Academy!D2+'F&B'!C33 -> 14415.022
B31: Net Revenue (A-B-C) | C31: =C28-C29-C30 -> 161429.05
B32: Venue Manager + Cleaner | C32: 60164
B33: Marketing, Branding & Community | C33: 15000
B34: Balls Expense | C34: 9500
B35: Branding Revamp | C35: 12595
B36: F&B Inventory Cost | C36: 3024
B37: Total Expenses | C37: =C32+C33+C34+C35+C36 -> 100283
B38: Net Profit (Revenue - Expenses) | C38: =C31-C37 -> 61146.045
B40: School's Profit Share (65%) | C40: =C38*65% -> 39744.929
B41: RallyGully's Profit Share (35%) | C41: =C38*35% -> 21401.116

Sheet Offline & RG Community
A1: Date | B1: Day | C1: Offline booking hours | D1: Booking Revenue | E1: Community Revenue | F1: Paddle Rental | G1: Total Revenue | H1: Payment Gateway | I1: Net Revenue
A2: 46235 | B2: Saturday | C2: 0 | D2: 0 | E2: 0 | F2: 0 | G2: =SUM(D2:F2) -> 0 | H2: =G2*1.75% -> 0 | I2: =G2-H2 -> 0
A3: 46236 | B3: Sunday | C3: 0 | D3: 0 | E3: 2000 | F3: 500 | G3: =SUM(D3:F3) -> 2500 | H3: =G3*1.75% -> 43.75 | I3: =G3-H3 -> 2456.25
A4: 46237 | B4: Monday | C4: 1.5 | D4: 1800 | E4: 2100 | F4: 300 | G4: =SUM(D4:F4) -> 4200 | H4: =G4*1.75% -> 73.5 | I4: =G4-H4 -> 4126.5
A5: 46238 | B5: Tuesday | C5: 0 | D5: 0 | E5: 0 | F5: 0 | G5: =SUM(D5:F5) -> 0 | H5: =G5*1.75% -> 0 | I5: =G5-H5 -> 0
A6: 46239 | B6: Wednesday | C6: 0 | D6: 0 | E6: 900 | F6: 0 | G6: =SUM(D6:F6) -> 900 | H6: =G6*1.75% -> 15.75 | I6: =G6-H6 -> 884.25
A7: 46240 | B7: Thursday | C7: 0 | D7: 0 | E7: 0 | F7: 0 | G7: =SUM(D7:F7) -> 0 | H7: =G7*1.75% -> 0 | I7: =G7-H7 -> 0
A8: 46241 | B8: Friday | C8: 0 | D8: 0 | E8: 0 | F8: 0 | G8: =SUM(D8:F8) -> 0 | H8: =G8*1.75% -> 0 | I8: =G8-H8 -> 0
A9: 46242 | B9: Saturday | C9: 0 | D9: 0 | E9: 0 | F9: 0 | G9: =SUM(D9:F9) -> 0 | H9: =G9*1.75% -> 0 | I9: =G9-H9 -> 0
A10: 46243 | B10: Sunday | C10: 0 | D10: 0 | E10: 0 | F10: 0 | G10: =SUM(D10:F10) -> 0 | H10: =G10*1.75% -> 0 | I10: =G10-H10 -> 0
A11: 46244 | B11: Monday | C11: 0 | D11: 0 | E11: 1200 | F11: 200 | G11: =SUM(D11:F11) -> 1400 | H11: =G11*1.75% -> 24.5 | I11: =G11-H11 -> 1375.5
A12: 46245 | B12: Tuesday | C12: 0.5 | D12: 500 | E12: 900 | F12: 0 | G12: =SUM(D12:F12) -> 1400 | H12: =G12*1.75% -> 24.5 | I12: =G12-H12 -> 1375.5
A13: 46246 | B13: Wednesday | C13: 1 | D13: 0 | E13: 500 | F13: 200 | G13: =SUM(E13:F13) -> 700 | H13: =G13*1.75% -> 12.25 | I13: =G13-H13 -> 687.75
A14: 46247 | B14: Thursday | C14: 1 | D14: 0 | E14: 600 | F14: 100 | G14: =SUM(E14:F14) -> 700 | H14: =G14*1.75% -> 12.25 | I14: =G14-H14 -> 687.75
A15: 46248 | B15: Friday | C15: 0 | D15: 0 | E15: 0 | F15: 300 | G15: =SUM(E15:F15) -> 300 | H15: =G15*1.75% -> 5.25 | I15: =G15-H15 -> 294.75
A16: 46249 | B16: Saturday | C16: 0 | D16: 0 | E16: 880 | F16: 400 | G16: =SUM(E16:F16) -> 1280 | H16: =G16*1.75% -> 22.4 | I16: =G16-H16 -> 1257.6
A17: 46250 | B17: Sunday | C17: 0 | D17: 0 | E17: 0 | F17: 0 | G17: =SUM(E17:F17) -> 0 | H17: =G17*1.75% -> 0 | I17: =G17-H17 -> 0
A18: 46251 | B18: Monday | C18: 0 | D18: 0 | E18: 2100 | F18: 0 | G18: =SUM(E18:F18) -> 2100 | H18: =G18*1.75% -> 36.75 | I18: =G18-H18 -> 2063.25
A19: 46252 | B19: Tuesday | C19: 1 | D19: 600 | E19: 0 | F19: 0 | G19: =sum(D19:F19) -> 600 | H19: =G19*1.75% -> 10.5 | I19: =G19-H19 -> 589.5
A20: 46253 | B20: Wednesday | C20: 3 | D20: 0 | E20: 2300 | F20: 100 | G20: =sum(D20:F20) -> 2400 | H20: =G20*1.75% -> 42 | I20: =G20-H20 -> 2358
A21: 46254 | B21: Thursday | C21: 3.5 | D21: 2520 | E21: 1200 | F21: 0 | G21: =sum(D21:F21) -> 3720 | H21: =G21*1.75% -> 65.1 | I21: =G21-H21 -> 3654.9
A22: 46255 | B22: Friday | C22: 0 | D22: 0 | E22: 0 | F22: 100 | G22: =sum(D22:F22) -> 100 | H22: =G22*1.75% -> 1.75 | I22: =G22-H22 -> 98.25
A23: 46256 | B23: Saturday | C23: 3.5 | D23: 1797 | E23: 2400 | F23: 700 | G23: =sum(D23:F23) -> 4897 | H23: =G23*1.75% -> 85.6975 | I23: =G23-H23 -> 4811.3025
A24: 46257 | B24: Sunday | C24: 0 | D24: 0 | E24: 0 | F24: 100 | G24: =sum(D24:F24) -> 100 | H24: =G24*1.75% -> 1.75 | I24: =G24-H24 -> 98.25
A25: 46258 | B25: Monday | C25: 0 | D25: 0 | E25: 0 | F25: 0 | G25: =sum(D25:F25) -> 0 | H25: =G25*1.75% -> 0 | I25: =G25-H25 -> 0
A26: 46259 | B26: Tuesday | C26: 0 | D26: 0 | E26: 0 | F26: 0 | G26: =sum(D26:F26) -> 0 | H26: =G26*1.75% -> 0 | I26: =G26-H26 -> 0
A27: 46260 | B27: Wednesday | C27: 1 | D27: 600 | E27: 1200 | F27: 700 | G27: =sum(D27:F27) -> 2500 | H27: =G27*1.75% -> 43.75 | I27: =G27-H27 -> 2456.25
A28: 46261 | B28: Thursday | C28: 2 | D28: 1800 | E28: 0 | F28: 0 | G28: =sum(D28:F28) -> 1800 | H28: =G28*1.75% -> 31.5 | I28: =G28-H28 -> 1768.5
A29: 46262 | B29: Friday | C29: 0 | D29: 0 | E29: 0 | F29: 0 | G29: =sum(D29:F29) -> 0 | H29: =G29*1.75% -> 0 | I29: =G29-H29 -> 0
A30: 46263 | B30: Saturday | C30: 0 | D30: 0 | E30: 0 | F30: 300 | G30: =sum(D30:F30) -> 300 | H30: =G30*1.75% -> 5.25 | I30: =G30-H30 -> 294.75
... A32: 46265 | B32: Monday | C32: 0 | D32: 0 | E32: 0 | F32: 0 | G32: =sum(D32:F32) -> 0 | H32: =G32*1.75% -> 0 | I32: =G32-H32 -> 0
A33: Total | D33: =SUM(D2:D32) -> 9617 | E33: =SUM(E2:E32) -> 18280 | F33: =SUM(F2:F32) -> 4000 | G33: =SUM(G2:G32) -> 31897 | H33: =SUM(H2:H32) -> 558.1975 | I33: =SUM(I2:I32) -> 31338.803

Sheet District
A1: Link | B1: Date | C1: Paid to District | D1: Commissions (₹) | E1: GST on Commission | F1: Net Revenue | G1: TCS | H1: TDS | I1: Final Amount (₹)
B2: 1 - 31 Aug | C2: 112290 | D2: 7860 | E2: 1414 | F2: =C2-D2-E2 -> 103016 | G2: 561 | H2: 112 | I2: =F2-G2-H2 -> 102343
B4: Total | C4: =SUM(C2:C3) -> 112290 | D4: =SUM(D2:D3) -> 7860 | E4: =SUM(E2:E3) -> 1414 | F4: =SUM(F2:F3) -> 103016 | I4: =SUM(I2:I3) -> 102343

Sheet Social EventsTournaments
A1: Date | B1: Sport | C1: Type | D1: Amt | E1: Commission | F1: Event Expenses | G1: Payment Gateway | H1: Net Revenue | I1: TDS | J1: Final Amount (₹) | K1: Notes
A2: 46250 | B2: Pickleball | C2: DUPR | D2: 8994 | E2: =D2*5% -> 449.7 | F2: 160 | G2: 0 | H2: =D2-E2-G2 -> 8544.3 | I2: =D2*2% -> 179.88 | J2: =H2-I2 -> 8364.42 | K2: Courtly
B3: Pickleball | C3: DUPR | D3: 1500 | E3: =D3*3% -> 45 | F3: 0 | G3: =D3*1.75% -> 26.25 | H3: =D3-E3-G3 -> 1428.75 | I3: 0 | J3: =H3-I3 -> 1428.75 | K3: Offline
A4: Total | D4: =SUM(D2:D3) -> 10494 | E4: =SUM(E2:E3) -> 494.7 | F4: =SUM(F2:F3) -> 160 | G4: =SUM(G2:G3) -> 26.25 | H4: =SUM(H2:H3) -> 9973.05 | I4: =SUM(I2:I3) -> 179.88 | J4: =SUM(J2:J3) -> 9793.17

Sheet Academy
A1: Sports | B1: Month | C1: Amt | D1: Payment Gateway | E1: Net Revenue
A2: Pickleball | B2: Aug | C2: 48750 | D2: =C2*1.75% -> 853.125 | E2: =C2-D2 -> 47896.875

Sheet F&B
A1: Date | B1: F&B | C1: Paid to brand (75%) | D1: Blended Margin (25%) | E1: Payment Gateway | F1: Net Revenue
A2: 46235 | B2: 20 | C2: =B2*75% -> 15 | D2: =B2*25% -> 5 | E2: =B2*1.75% -> 0.35 | F2: =D2-E2 -> 4.65
A3: 46236 | B3: 510 | C3: =B3*75% -> 382.5 | D3: =B3*25% -> 127.5 | E3: =B3*1.75% -> 8.925 | F3: =D3-E3 -> 118.575
A4: 46237 | B4: 75 | C4: =B4*75% -> 56.25 | D4: =B4*25% -> 18.75 | E4: =B4*1.75% -> 1.3125 | F4: =D4-E4 -> 17.4375
A5: 46238 | B5: 40 | C5: =B5*75% -> 30 | D5: =B5*25% -> 10 | E5: =B5*1.75% -> 0.7 | F5: =D5-E5 -> 9.3
A6: 46239 | B6: 125 | C6: =B6*75% -> 93.75 | D6: =B6*25% -> 31.25 | E6: =B6*1.75% -> 2.1875 | F6: =D6-E6 -> 29.0625
A7: 46240 | B7: 0 | C7: =B7*75% -> 0 | D7: =B7*25% -> 0 | E7: =B7*1.75% -> 0 | F7: =D7-E7 -> 0
A8: 46241 | B8: 0 | C8: =B8*75% -> 0 | D8: =B8*25% -> 0 | E8: =B8*1.75% -> 0 | F8: =D8-E8 -> 0
A9: 46242 | B9: 0 | C9: =B9*75% -> 0 | D9: =B9*25% -> 0 | E9: =B9*1.75% -> 0 | F9: =D9-E9 -> 0
A10: 46243 | B10: 70 | C10: =B10*75% -> 52.5 | D10: =B10*25% -> 17.5 | E10: =B10*1.75% -> 1.225 | F10: =D10-E10 -> 16.275
A11: 46244 | B11: 270 | C11: =B11*75% -> 202.5 | D11: =B11*25% -> 67.5 | E11: =B11*1.75% -> 4.725 | F11: =D11-E11 -> 62.775
A12: 46245 | B12: 0 | C12: =B12*75% -> 0 | D12: =B12*25% -> 0 | E12: =B12*1.75% -> 0 | F12: =D12-E12 -> 0
A13: 46246 | B13: 765 | C13: =B13*75% -> 573.75 | D13: =B13*25% -> 191.25 | E13: =B13*1.75% -> 13.3875 | F13: =D13-E13 -> 177.8625
... A32: 46265 | B32: 0 | C32: =B32*75% -> 0 | D32: =B32*25% -> 0 | E32: =B32*1.75% -> 0 | F32: =D32-E32 -> 0
A33: Total | B33: =SUM(B2:B32) -> 4065 | C33: =SUM(C2:C32) -> 3048.75 | D33: =SUM(D2:D32) -> 1016.25 | E33: =SUM(E2:E32) -> 71.1375 | F33: =SUM(F2:F32) -> 945.1125
