Workbook

Sheet Summary
B2: 1 - 30 April
B3: Particulars | C3: Amount
C4: Pickleball
B5: Pay & Play | C5: =sum(C6,C12) -> 205658
B6: Online | C6: =sum(C7:C11) -> 150228
B7: District | C7: =District!C4 -> 49400
B8: Hudle | C8: =Hudle!C7 -> 98428
B9: Playo | C9: =Playo!C3 -> 1200
B10: Khelomore | C10: =Khelomore!C3 -> 1200
B11: Zplys | C11: 0
B12: Offline | C12: =sum(C13:C14) -> 55430
B13: Bookings | C13: ='Offline & RG Community'!E32 -> 55430
B14: Memberships | C14: 0
B15: Community | C15: =sum(C16:C17) -> 78727
B16: Pickup games | C16: ='Offline & RG Community'!F32+Sportomic!C2 -> 60338
B17: Social Events/Tournaments | C17: =Courtly!B3 -> 18389
B18: Academy | C18: 0
B19: Events & Partnership | C19: =sum(C20,C21) -> 0
B20: Corporate events | C20: 0
B21: All B2B partnerships | C21: 0
B22: Commerce | C22: =sum(C23:C25) -> 17035
B23: Product rental | C23: ='Offline & RG Community'!G32 -> 14350
B24: Product sales | C24: 0
B25: F&B | C25: ='Offline & RG Community'!H32 -> 2685
B26: Other Income | C26: 0
B27: Total Gross Revenue | C27: =sum(C26+C22+C19+C18+C15+C12+C6) -> 301420
B28: Total Net Revenue (Post Commissions) | C28: ='Offline & RG Community'!K32+Hudle!E7+Playo!F3+District!F4+Khelomore!E3+Sportomic!C2+Courtly!D3 -> 281311.97 | D28: =C27-C28 -> 20108.033
B29: Total Revenue post GST | C29: =C28/1.18 -> 238399.97
B30: Expenses
B31: Venue Manager + Cleaner + Overtime + Incentive | C31: 60164
B32: Marketing, Branding & Community | C32: 15000
B33: Balls Expense | C33: 9500
B34: F&B Inventory Cost | C34: 3024
B35: Total Expenses | C35: =C31+C32+C33+C34 -> 87688
B36: Net Profit (Revenue - Expenses) | C36: =C29-C35 -> 150711.97
B38: School's Profit Share (65%) | C38: =C36*65%-10665 -> 87297.782
B39: RallyGully's Profit Share (35%) | C39: =10665+C36*35% -> 63414.19

Sheet Offline & RG Community
A1: Date | B1: Day | C1: Offline booking hours | D1: Discount Given | E1: Booking Revenue | F1: Community Revenue | G1: Paddle Rental | H1: F&B | I1: Total Revenue | J1: Payment Gateway | K1: Net Revenue
A2: 1 Apr | B2: Wednesday | C2: 5 | D2: 0 and 10% | E2: 900 | F2: 5700 | G2: 300 | H2: 0 | I2: =sum(E2:H2) -> 6900 | J2: =I2*2.5%*1.18 -> 203.55 | K2: =I2-J2 -> 6696.45
A3: 2 Apr | B3: Thursday | C3: 1 | D3: 0 and 10% | E3: 900 | F3: 0 | G3: 400 | H3: 0 | I3: =sum(E3:H3) -> 1300 | J3: =I3*2.5%*1.18 -> 38.35 | K3: =I3-J3 -> 1261.65
A4: 3 Apr | B4: Friday | C4: 1 | D4: 0 and 10% | E4: 900 | F4: 2900 | G4: 900 | H4: 0 | I4: =sum(E4:H4) -> 4700 | J4: =I4*2.5%*1.18 -> 138.65 | K4: =I4-J4 -> 4561.35
A5: 4 Apr | B5: Saturday | C5: 1 | D5: 0 and 10% | E5: 900 | F5: 0 | G5: 550 | H5: 315 | I5: =sum(E5:H5) -> 1765 | J5: =I5*2.5%*1.18 -> 52.0675 | K5: =I5-J5 -> 1712.9325
A6: 5 Apr | B6: Sunday | C6: 5 | D6: 0 and 10% | E6: 5440 | F6: 0 | G6: 1000 | H6: 0 | I6: =sum(E6:H6) -> 6440 | J6: =I6*2.5%*1.18 -> 189.98 | K6: =I6-J6 -> 6250.02
A7: 6 Apr | B7: Monday | C7: 2 | D7: 0 and 10% | E7: 1600 | F7: 0 | G7: 800 | H7: 140 | I7: =sum(E7:H7) -> 2540 | J7: =I7*2.5%*1.18 -> 74.93 | K7: =I7-J7 -> 2465.07
A8: 7 Apr | B8: Tuesday | C8: 1 | D8: 0 and 10% | E8: 0 | F8: 2400 | G8: 300 | H8: 0 | I8: =sum(E8:H8) -> 2700 | J8: =I8*2.5%*1.18 -> 79.65 | K8: =I8-J8 -> 2620.35
A9: 8 Apr | B9: Wednesday | C9: 4 | D9: 0 and 10% | E9: 1800 | F9: 4500 | G9: 100 | H9: 0 | I9: =sum(E9:H9) -> 6400 | J9: =I9*2.5%*1.18 -> 188.8 | K9: =I9-J9 -> 6211.2
A10: 9 Apr | B10: Thursday | C10: 1 | D10: 0 and 10% | E10: 900 | F10: 0 | G10: 600 | H10: 0 | I10: =sum(E10:H10) -> 1500 | J10: =I10*2.5%*1.18 -> 44.25 | K10: =I10-J10 -> 1455.75
A11: 10 Apr | B11: Friday | C11: 2.5 | D11: 0 and 10% | E11: 2400 | F11: 0 | G11: 300 | H11: 0 | I11: =sum(E11:H11) -> 2700 | J11: =I11*2.5%*1.18 -> 79.65 | K11: =I11-J11 -> 2620.35
A12: 11 Apr | B12: Saturday | C12: 3 | D12: 0 and 10% | E12: 2900 | F12: 0 | G12: 650 | H12: 245 | I12: =sum(E12:H12) -> 3795 | J12: =I12*2.5%*1.18 -> 111.9525 | K12: =I12-J12 -> 3683.0475
A13: 12 Apr | B13: Sunday | C13: 2 | D13: 0 and 10% | E13: 2000 | F13: 0 | G13: 900 | H13: 0 | I13: =sum(E13:H13) -> 2900 | J13: =I13*2.5%*1.18 -> 85.55 | K13: =I13-J13 -> 2814.45
... A25: 24 Apr | B25: Friday | C25: 5 | D25: 0 and 10% | E25: 2100 | F25: 4500 | G25: 600 | H25: 70 | I25: =sum(E25:H25) -> 7270 | J25: =I25*2.5%*1.18 -> 214.465 | K25: =I25-J25 -> 7055.535
A26: 25 Apr | B26: Saturday | C26: 0 | D26: 0 and 10% | I26: =sum(E26:H26) -> 0 | J26: =I26*2.5%*1.18 -> 0 | K26: =I26-J26 -> 0
A27: 26 Apr | B27: Sunday | C27: 5 | D27: 0 and 10% | E27: 2200 | F27: 3000 | G27: 250 | H27: 70 | I27: =sum(E27:H27) -> 5520 | J27: =I27*2.5%*1.18 -> 162.84 | K27: =I27-J27 -> 5357.16
A28: 27 Apr | B28: Monday | C28: 2 | D28: 0 and 10% | E28: 900 | F28: 900 | G28: 500 | H28: 135 | I28: =sum(E28:H28) -> 2435 | J28: =I28*2.5%*1.18 -> 71.8325 | K28: =I28-J28 -> 2363.1675
A29: 28 Apr | B29: Tuesday | C29: 6 | D29: 0 and 10% | E29: 3850 | F29: 3300 | G29: 400 | H29: 135 | I29: =sum(E29:H29) -> 7685 | J29: =I29*2.5%*1.18 -> 226.7075 | K29: =I29-J29 -> 7458.2925
A30: 29 Apr | B30: Wednesday | C30: 5 | D30: 0 and 10% | E30: 2160 | F30: 2700 | G30: 300 | H30: 70 | I30: =sum(E30:H30) -> 5230 | J30: =I30*2.5%*1.18 -> 154.285 | K30: =I30-J30 -> 5075.715
A31: 30 Apr | B31: Thursday | C31: 2 | D31: 0 and 10% | E31: 0 | F31: 3300 | G31: 600 | H31: 0 | I31: =sum(E31:H31) -> 3900 | J31: =I31*2.5%*1.18 -> 115.05 | K31: =I31-J31 -> 3784.95
A32: Total | C32: =SUM(C2:C31) -> 83 | E32: =SUM(E2:E31) -> 55430 | F32: =SUM(F2:F31) +C34 -> 51950 | G32: =SUM(G2:G31) -> 14350 | H32: =SUM(H2:H31) -> 2685 | I32: =SUM(I2:I31) +E34 -> 124415 | J32: =SUM(J2:J31) -> 3670.2425 | K32: =SUM(K2:K31) -> 120744.76

Sheet Hudle
A1: Link | B1: Date | C1: Paid to Hudle | D1: Commisions (Including GST) | E1: Net Revenue | F1: TDS | G1: TCS | H1: Amount
B2: 1-7th Apr | C2: 19475 | D2: 2535 | E2: =C2-D2 -> 16940 | F2: 16.5 | G2: 82.62 | H2: 16865.87
B3: 7-12th Apr | C3: 28100 | D3: 3653 | E3: =C3-D3 -> 24447 | F3: 23.8 | G3: 119 | H3: 24304.6
B4: 13-19th Apr | C4: 19800 | D4: 2574 | E4: =C4-D4 -> 17226 | F4: 16.7 | G4: 83.9 | H4: 17125.35
B5: 19-28 Apr | C5: 25765 | D5: 3349 | E5: =C5-D5 -> 22416 | F5: 21 | G5: 109 | H5: 22284
B6: 28-30 Apr | C6: 5288 | D6: 700 | E6: =C6-D6 -> 4588 | F6: 4.5 | G6: 22 | H6: 4498
B7: Total | C7: =SUM(C2:C6) -> 98428 | E7: =SUM(E2:E6) -> 85617 | H7: =SUM(H2:H6) -> 85077.82

Sheet Playo
A1: Link | B1: Date | C1: Paid to Playo (₹) | D1: Commissions (₹) | E1: GST (₹) | F1: Net Revenue | G1: TDS (₹) | H1: TCS (₹) | I1: Final Amount (₹)
B2: 1-30 Apr | C2: 1200 | D2: 84 | E2: 15.12 | F2: =C2-D2-E2 -> 1100.88 | G2: 1.2 | H2: 6 | I2: 1093.6
B3: Total | C3: =SUM(C2) -> 1200 | F3: =SUM(F2) -> 1100.88 | I3: =SUM(I2) -> 1093.6

Sheet District
A1: Link | B1: Date | C1: Paid to District | D1: Commissions (₹) | E1: GST on Commission | F1: Net Revenue | G1: TCS | H1: TDS | I1: Final Amount (₹)
B2: 1 - 30 Apr | C2: 49400 | D2: 2472 | E2: 444 | F2: =C2-D2-E2 -> 46484 | G2: 247 | H2: 49 | I2: 46186
B4: Total | C4: =SUM(C2:C3) -> 49400 | F4: =SUM(F2:F3) -> 46484 | I4: =SUM(I2:I3) -> 46186

Sheet Khelomore
A1: Link | B1: Date | C1: Paid to Khelomore (₹) | D1: Commissions (₹) | E1: Final Amount (₹)
B2: 1 - 30th Apr | C2: 1200 | D2: =C2*5% -> 60 | E2: =C2-D2 -> 1140
B3: Total | C3: =SUM(C2) -> 1200 | E3: =SUM(E2) -> 1140

Sheet Sportomic
A1: Link | B1: Date | C1: Paid to Sportomic (₹)
B2: 1 -30 Apr | C2: 8388

Sheet Courtly
A1: Date | B1: Paid to Courtly | C1: Post Comission | D1: Net Revenue | E1: TDS | F1: Final Amount (₹)
A2: 25th Apr | B2: 18389 | C2: =B2*3% -> 551.67 | D2: =B2-C2 -> 17837.33 | E2: =B2*2% -> 367.78 | F2: =D2-E2 -> 17469.55
A3: Total | B3: =SUM(B2) -> 18389 | D3: =SUM(D2) -> 17837.33 | F3: =SUM(F2) -> 17469.55

Sheet Coaching
A1: Sports Type | B1: Coaching Type | C1: Start Date | D1: Amount Collected
