Workbook

Sheet Summary
B2: 1 - 31 July
B3: Particulars | C3: Amount
C4: Pickleball
B5: Pay & Play | C5: =sum(C6,C12) -> 74328
B6: Online | C6: =sum(C7:C11) -> 59528
B7: District | C7: =District!C4 -> 42153
B8: Hudle | C8: =Hudle!C3 -> 3650
B9: Playo | C9: =Playo!C3 -> 9600
B10: Khelomore | C10: =Khelomore!B4 -> 4125
B11: Zplys | C11: 0
B12: Offline | C12: =sum(C13:C14) -> 14800
B13: Bookings | C13: ='Offline & RG Community'!D33 -> 14800
B14: Memberships | C14: 0
B15: Community | C15: =sum(C16:C17) -> 0
B16: Pickup games | C16: =0 -> 0
B17: Social Events/Tournaments | C17: 0
B18: Academy | C18: 0
B19: Events & Partnership | C19: =sum(C20,C21) -> 0
B20: Corporate events | C20: 0
B21: All B2B partnerships | C21: 0
B22: Commerce | C22: =sum(C23:C25) -> 10150
B23: Product rental | C23: ='Offline & RG Community'!F33 -> 10150
B24: Product sales | C24: 0
B25: F&B | C25: 0
B26: Other Income | C26: ='Other income'!C2 -> 120000
B27: Total Gross Revenue | C27: =sum(C26+C22+C19+C18+C15+C12+C6) -> 204478
B28: Total Net Revenue (Post Commissions) | C28: ='Offline & RG Community'!J33+District!F4+Hudle!E3+Playo!F3+Khelomore!D4+'Other income'!C2 -> 198821.12
B29: Total Revenue post GST | C29: =(C27/1.18)-(C27-C28) -> 167629.57

Sheet Offline & RG Community
A1: Date | B1: Day | C1: Offline booking hours | D1: Booking Revenue | E1: Community Revenue | F1: Paddle Rental | G1: F&B | H1: Total Revenue | I1: Payment Gateway | J1: Net Revenue
A2: 46204 | B2: Wednesday | C2: 0 | D2: 0 | E2: 0 | F2: 0 | G2: 0 | H2: =sum(D2:G2) -> 0 | I2: =H2*1.75% -> 0 | J2: =H2-I2 -> 0
A3: 46205 | B3: Thursday | C3: 0.5 | D3: 350 | E3: 0 | F3: 300 | G3: 0 | H3: =sum(D3:G3) -> 650 | I3: =H3*1.75% -> 11.375 | J3: =H3-I3 -> 638.625
A4: 46206 | B4: Friday | C4: 0 | D4: 0 | E4: 0 | F4: 100 | G4: 0 | H4: =sum(D4:G4) -> 100 | I4: =H4*1.75% -> 1.75 | J4: =H4-I4 -> 98.25
A5: 46207 | B5: Saturday | C5: 0.5 | D5: 350 | E5: 0 | F5: 300 | G5: 0 | H5: =sum(D5:G5) -> 650 | I5: =H5*1.75% -> 11.375 | J5: =H5-I5 -> 638.625
A6: 46208 | B6: Sunday | C6: 0 | D6: 0 | E6: 0 | F6: 0 | G6: 0 | H6: =sum(D6:G6) -> 0 | I6: =H6*1.75% -> 0 | J6: =H6-I6 -> 0
A7: 46209 | B7: Monday | C7: 0 | D7: 0 | E7: 0 | F7: 0 | G7: 0 | H7: =sum(D7:G7) -> 0 | I7: =H7*1.75% -> 0 | J7: =H7-I7 -> 0
A8: 46210 | B8: Tuesday | C8: 0 | D8: 0 | E8: 0 | F8: 0 | G8: 0 | H8: =sum(D8:G8) -> 0 | I8: =H8*1.75% -> 0 | J8: =H8-I8 -> 0
A9: 46211 | B9: Wednesday | C9: 0 | D9: 0 | E9: 0 | F9: 0 | G9: 0 | H9: =sum(D9:G9) -> 0 | I9: =H9*1.75% -> 0 | J9: =H9-I9 -> 0
A10: 46212 | B10: Thursday | C10: 2 | D10: 1300 | E10: 0 | F10: 475 | G10: 0 | H10: =sum(D10:G10) -> 1775 | I10: =H10*1.75% -> 31.0625 | J10: =H10-I10 -> 1743.9375
A11: 46213 | B11: Friday | C11: 7 | D11: 4900 | E11: 0 | F11: 300 | G11: 0 | H11: =sum(D11:G11) -> 5200 | I11: =H11*1.75% -> 91 | J11: =H11-I11 -> 5109
A12: 46214 | B12: Saturday | C12: 0 | D12: 0 | E12: 0 | F12: 300 | G12: 0 | H12: =sum(D12:G12) -> 300 | I12: =H12*1.75% -> 5.25 | J12: =H12-I12 -> 294.75
A13: 46215 | B13: Sunday | C13: 1 | D13: 700 | E13: 0 | F13: 1725 | G13: 0 | H13: =sum(D13:G13) -> 2425 | I13: =H13*1.75% -> 42.4375 | J13: =H13-I13 -> 2382.5625
... A32: 46234 | B32: Friday | C32: 1 | D32: 650 | E32: 0 | F32: 800 | G32: 0 | H32: =sum(D32:G32) -> 1450 | I32: =H32*1.75% -> 25.375 | J32: =H32-I32 -> 1424.625
A33: Total | D33: =SUM(D1:D32) -> 14800 | E33: =SUM(E1:E32) -> 0 | F33: =SUM(F1:F32) -> 10150 | G33: =SUM(G1:G32) -> 0 | H33: =sum(D33:G33) -> 24950 | I33: =SUM(I1:I32) -> 436.625 | J33: =SUM(J1:J32) -> 24513.375

Sheet District
A1: Link | B1: Date | C1: Paid to District | D1: Commissions (₹) | E1: GST on Commission | F1: Net Revenue | G1: TCS | H1: TDS | I1: Final Amount (₹)
B2: 1 - 31 July | C2: 42153 | D2: 2950 | E2: 531 | F2: =C2-D2-E2 -> 38672 | G2: 210 | H2: 42 | I2: =F2-G2-H2 -> 38420
B4: Total | C4: =SUM(C2:C3) -> 42153 | F4: =SUM(F2:F3) -> 38672 | I4: =SUM(I2:I3) -> 38420

Sheet Hudle
A1: Link | B1: Date | C1: Paid to Hudle | D1: Commisions (Including GST) | E1: Net Revenue | F1: TDS | G1: TCS | H1: Amount
B2: 1 - 31 July | C2: 3650 | D2: 481 | E2: =C2-D2 -> 3169 | F2: 3 | G2: 15 | H2: 3200
B3: Total | C3: =SUM(C2) -> 3650 | E3: =SUM(E2) -> 3169 | H3: =SUM(H2) -> 3200

Sheet Playo
A1: Link | B1: Date | C1: Paid to Playo (₹) | D1: Commissions (₹) | E1: GST (₹) | F1: Net Revenue | G1: TDS (₹) | H1: TCS (₹) | I1: Final Amount (₹)
B2: 1 - 31 July | C2: 9600 | D2: 892 | E2: 160 | F2: =C2-D2-E2 -> 8548 | G2: 9.6 | H2: 0 | I2: =F2-G2-H2 -> 8538.4
B3: Total | C3: =sum(C2) -> 9600 | F3: =sum(F2) -> 8548 | I3: =sum(I2) -> 8538.4

Sheet Khelomore
A1: Date | B1: Paid to Khelomore (₹) | C1: Commissions (₹) | D1: Final Amount (₹)
A2: 1 - 31 July | B2: 4125 | C2: =B2*5% -> 206.25 | D2: =B2-C2 -> 3918.75
A4: Total | B4: =SUM(B2) -> 4125 | D4: =SUM(D2) -> 3918.75

Sheet Other income
A1: Month | B1: Sports Type | C1: Amount Collected
A2: July | B2: Football Management Operations | C2: 120000
