Workbook

Sheet Summary
B2: Date: 1st - 31st Dec
B3: Particulars | C3: Amount
B4: Offline | C4: =SUM(C5,C6,C7,C8) -> 11535
B5: Rentals | C5: ='Offline & RG Community'!G33 -> 3775
B6: F&B | C6: 0
B7: Product Sales | C7: 0
B8: Bookings | C8: ='Offline & RG Community'!E33 -> 7760
B9: Online: Third Party Platform | C9: =SUM(C10:C13) -> 15050
B10: Hudle | C10: =Hudle!C7 -> 14650
B11: Playo | C11: =Playo!C6 -> 400
B12: District | C12: =District!C2 -> 0
B13: Khelomore | C13: =Khelomore!C4 -> 0
B14: Community | C14: =SUM(C16,C17,C18) -> 6340
B15: Courtly | C15: 0
B16: Sportomic | C16: =Sportomic!C6 -> 4800
B17: Rallygully Community games | C17: ='Offline & RG Community'!F33 -> 900
B18: Misfits Community | C18: =Misfits!C6 -> 640
B19: Memberships | C19: 0
B20: Corporate Events | C20: 0
B21: Brand Activation | C21: 0
B22: Other Income | C22: ='Other Income'!E2 -> 18000 | D22: (Note for CA Team: Please note that RallyGully hasn't received the 18000 rental for basketball rental service provided) - GST payment would have to be made by Drive & Kick Team
B23: Total Gross Revenue | C23: =sum(C4,C9,C14,C19,C20,C21,C22) -> 50925
B24: Total Net Revenue (Post Commissions) | C24: ='Offline & RG Community'!H33 +Hudle!E7 + Playo!I6 + Misfits!F2 + Sportomic!C6 +'Other Income'!E2 -> 48807.26
B25: Total Revenue post GST | C25: =((C24-C22)/1.18)+C22 -> 44107.847
B26: Drive & Kick Share (70%) | C26: =C25*70% -> 30875.493
B27: Drive & Kick Share (Final share after incorporting 18k already received by Drive Kick) | C27: =C26-C22 -> 12875.493
B28: RallyGully's Share (30%) | C28: =C25*30% -> 13232.354

Sheet Offline & RG Community
A1: Date | B1: Day | C1: Offline booking hours | D1: Discount Given | E1: Booking Revenue | F1: Community Revenue | G1: Paddle Rental | H1: Total Revenue
A2: 45992 | B2: Monday | D2: 20% and 10% | H2: =SUM(E2:G2) -> 0
A3: 45993 | B3: Tuesday | C3: 0 | D3: 20% and 10% | E3: 0 | F3: 0 | G3: 100 | H3: =SUM(E3:G3) -> 100
A4: 45994 | B4: Wednesday | C4: 0.5 | D4: 20% and 10% | E4: 360 | F4: 0 | G4: 200 | H4: =SUM(E4:G4) -> 560
A5: 45995 | B5: Thursday | C5: 0 | D5: 20% and 10% | E5: 0 | F5: 0 | G5: 50 | H5: =SUM(E5:G5) -> 50
A6: 45996 | B6: Friday | C6: 1 | D6: 20% and 10% | E6: 720 | F6: 0 | G6: 100 | H6: =SUM(E6:G6) -> 820
A7: 45997 | B7: Saturday | C7: 0 | D7: 20% and 10% | E7: 0 | F7: 0 | G7: 0 | H7: =SUM(E7:G7) -> 0
A8: 45998 | B8: Sunday | C8: 1 | D8: 20% and 10% | E8: 720 | F8: 0 | G8: 50 | H8: =SUM(E8:G8) -> 770
A9: 45999 | B9: Monday | C9: 0 | D9: 20% and 10% | E9: 0 | F9: 0 | G9: 0 | H9: =SUM(E9:G9) -> 0
A10: 46000 | B10: Tuesday | C10: 0 | D10: 20% and 10% | E10: 0 | F10: 0 | G10: 400 | H10: =SUM(E10:G10) -> 400
A11: 46001 | B11: Wednesday | C11: 0 | D11: 20% and 10% | E11: 0 | F11: 0 | G11: 0 | H11: =SUM(E11:G11) -> 0
A12: 46002 | B12: Thursday | D12: 20% and 10%
A13: 46003 | B13: Friday | D13: 20% and 10%
A14: 46004 | B14: Saturday | D14: 20% and 10%
A15: 46005 | B15: Sunday | D15: 20% and 10%
A16: 46006 | B16: Monday | D16: 20% and 10%
A17: 46007 | B17: Tuesday | D17: 20% and 10%
A18: 46008 | B18: Wednesday | D18: 20% and 10%
A19: 46009 | B19: Thursday | D19: 20% and 10%
A20: 46010 | B20: Friday | D20: 20% and 10%
A21: 46011 | B21: Saturday | D21: 20% and 10% | H21: =SUM(E21:G21) -> 0
A22: 46012 | B22: Sunday | C22: 0 | D22: 20% and 10% | E22: 0 | F22: 0 | G22: 100 | H22: =SUM(E22:G22) -> 100
A23: 46013 | B23: Monday | C23: 2 | D23: 20% and 10% | E23: 2000 | F23: 0 | G23: 450 | H23: =SUM(E23:G23) -> 2450
A24: 46014 | B24: Tuesday | C24: 1 | D24: 20% and 10% | E24: 640 | F24: 0 | G24: 150 | H24: =SUM(E24:G24) -> 790
A25: 46015 | B25: Wednesday | C25: 1 | D25: 20% and 10% | E25: 0 | F25: 900 | G25: 250 | H25: =SUM(E25:G25) -> 1150
A26: 46016 | B26: Thursday | C26: 0 | D26: 20% and 10% | E26: 0 | F26: 0 | G26: 100 | H26: =SUM(E26:G26) -> 100
A27: 46017 | B27: Friday | C27: 0 | D27: 20% and 10% | E27: 0 | F27: 0 | G27: 150 | H27: =SUM(E27:G27) -> 150
A28: 46018 | B28: Saturday | C28: 0.5 | D28: 20% and 10% | E28: 320 | F28: 0 | G28: 225 | H28: =SUM(E28:G28) -> 545
A29: 46019 | B29: Sunday | C29: 0.5 | D29: 20% and 10% | E29: 360 | F29: 0 | G29: 650 | H29: =SUM(E29:G29) -> 1010
A30: 46020 | B30: Monday | C30: 0 | D30: 20% and 10% | E30: 0 | F30: 0 | G30: 200 | H30: =SUM(E30:G30) -> 200
A31: 46021 | B31: Tuesday | C31: 2.5 | D31: 20% and 10% | E31: 1640 | F31: 0 | G31: 500 | H31: =SUM(E31:G31) -> 2140
A32: 46022 | B32: Wednesday | C32: 1.5 | D32: 20% and 10% | E32: 1000 | F32: 0 | G32: 100 | H32: =SUM(E32:G32) -> 1100
A33: Total | C33: =SUM(C2:C32) -> 11.5 | E33: =SUM(E2:E32) -> 7760 | F33: =SUM(F2:F32) -> 900 | G33: =SUM(G2:G32) -> 3775 | H33: =SUM(H2:H32) -> 12435

Sheet Hudle
A1: Link | B1: Date | C1: Paid to Hudle | D1: Commisions (Including GST) | E1: Net Revenue | F1: TDS | G1: TCS | H1: Amount
B2: 1 - 9 Dec | C2: 3180 | D2: 452.4 | E2: =C2-D2 -> 2727.6 | F2: 2.94 | G2: 14.74 | H2: 3000.9
B3: 9 - 16 Dec | C3: 1600 | D3: 208 | E3: =C3-D3 -> 1392 | F3: 1.3559 | G3: 6.7797 | H3: 1383.86
B4: 16 - 23 Dec | C4: 1920 | D4: 249.6 | E4: =C4-D4 -> 1670.4 | F4: 1.67 | G4: 8.13 | H4: 1660.64
B5: 23 - 30 Dec | C5: 7150 | D5: 929.5 | E5: =C5-D5 -> 6220.5 | F5: 6.05 | G5: 30.29 | H5: 6184.15
B6: 30 - 31 Dec | C6: 800 | D6: 106.56 | E6: =C6-D6 -> 693.44 | F6: 0.7 | G6: 3.44 | H6: 689.3
C7: =SUM(C2:C6) -> 14650 | E7: =SUM(E2:E6) -> 12703.94 | H7: =SUM(H2:H6) -> 12918.85

Sheet Playo
A1: Link | B1: Date | C1: Paid to Playo (₹) | D1: Commissions (₹) | E1: GST (₹) | F1: Net Revenue | G1: TDS (₹) | H1: TCS (₹) | I1: Final Amount (₹)
B2: 1 - 31 Dec | C2: 400 | D2: 28 | E2: 5.04 | F2: =C2-D2-E2 -> 366.96 | G2: 0.4 | H2: 2 | I2: 364.56
C6: =SUM(C2:C4) -> 400 | F6: =SUM(F2:F4) -> 366.96 | I6: =SUM(I2:I4) -> 364.56

Sheet Khelomore
A1: Link | B1: Date | C1: Paid to Khelomore (₹) | D1: Commissions (₹) | E1: Final Amount (₹)
B2: 1 - 31 Dec | C2: 0
C4: =SUM(C2:C3) -> 0 | D4: =SUM(D2:D3) -> 0 | E4: =SUM(E2:E3) -> 0

Sheet District
A1: Link | B1: Date | C1: Paid to District | D1: Commissions (₹) | E1: Final Amount (₹)
B2: 1 - 31st Dec | C2: 0

Sheet Misfits
A1: Link | B1: Date | C1: Paid to Misfits (₹) | D1: Post Comission (20%) | E1: TDS | F1: Final Amount (₹)
B2: 1 - 31st Dec | C2: 640 | D2: 128 | E2: 8.24 | F2: =C2-D2-E2 -> 503.76
C6: =SUM(C2) -> 640 | F6: =SUM(F2) -> 503.76

Sheet Sportomic
A1: Link | B1: Date | C1: Paid to Sportomic (₹) | D1: TDS | E1: Final Amount (₹)
B2: 1 - 31st Dec | C2: 4800
C6: =SUM(C2) -> 4800

Sheet Memberships
A1: Member Name | B1: Sports Type | C1: Membership Type | D1: Start Date | E1: Amount Collected

Sheet Brand Activation
A1: Date | B1: Brand Name | C1: Amount | D1: Type of collab

Sheet Other Income
A1: Month | B1: Coaching | C1: Sports Type | D1: Type | E1: Amount Collected
A2: Dec | B2: Basketball Coaching | C2: Basketball | D2: 3 days in week | E2: 18000
