Workbook

Sheet Summary
B2: Date: 1 - 28 Feb
B3: Particulars | C3: Amount
B4: Offline | C4: =SUM(C5,C6,C7,C8) -> 191125
B5: Rentals | C5: ='Offline & RG Community'!G30 -> 31275
B6: F&B | C6: 0
B7: Product Sales | C7: 0
B8: Bookings | C8: ='Offline & RG Community'!E30 -> 159850
B9: Online: Third Party Platform | C9: =SUM(C10:C14) -> 137534.76
B10: Hudle | C10: =Hudle!C3 -> 38157
B11: Playo | C11: =Playo!C3 -> 57992.5
B12: District | C12: 0
B13: Khelomore | C13: =Khelomore!C3 -> 41385.26
B14: Zplys | C14: 0
B15: Community | C15: =sum(C16:C19) -> 2205
B16: Courtly (Organized by RallyGully) | C16: 0
B17: Sportomic (Organized by RallyGully) | C17: =Sportomic!C2 -> 360
B18: Rallygully Community games | C18: ='Offline & RG Community'!F30 -> 1845
B19: Misfits Community | C19: 0
B20: Memberships | C20: 0
B21: Corporate Events | C21: 0
B22: Brand Activation | C22: 0
B23: Other Income | C23: ='Other Income'!C2 -> 120000
B24: Total Gross Revenue | C24: =sum(C4,C9,C15,C20,C21,C22,C23) -> 450864.76
B25: Total Net Revenue (Post Commissions) | C25: ='Offline & RG Community'!H30+Hudle!E3+Playo!F3+Khelomore!E3+'Other Income'!C2 + Sportomic!C2 -> 440225.64
B26: Total Revenue post GST | C26: =C25/1.18 -> 373072.57

Sheet Offline & RG Community
A1: Date | B1: Day | C1: Offline booking hours | D1: Discount Given | E1: Booking Revenue | F1: Community Revenue | G1: Paddle Rental | H1: Total Revenue
A2: 46054 | B2: Sunday | C2: 12.5 | D2: 14% and 10% | E2: 6995 | F2: 1125 | G2: 3200 | H2: =SUM(E2:G2) -> 11320
A3: 46055 | B3: Monday | C3: 3 | D3: 14% and 10% | E3: 2025 | F3: 0 | G3: 1000 | H3: =SUM(E3:G3) -> 3025
A4: 46056 | B4: Tuesday | C4: 6.5 | D4: 14% and 10% | E4: 4850 | F4: 0 | G4: 850 | H4: =SUM(E4:G4) -> 5700
A5: 46057 | B5: Wednesday | C5: 5 | D5: 14% and 10% | E5: 3525 | F5: 0 | G5: 1000 | H5: =SUM(E5:G5) -> 4525
A6: 46058 | B6: Thursday | C6: 3.5 | D6: 14% and 10% | E6: 2400 | F6: 540 | G6: 550 | H6: =SUM(E6:G6) -> 3490
A7: 46059 | B7: Friday | C7: 5.5 | D7: 14% and 10% | E7: 3585 | F7: 0 | G7: 850 | H7: =SUM(E7:G7) -> 4435
A8: 46060 | B8: Saturday | C8: 2.5 | D8: 14% and 10% | E8: 1665 | F8: 0 | G8: 1600 | H8: =SUM(E8:G8) -> 3265
A9: 46061 | B9: Sunday | C9: 9.5 | D9: 14% and 10% | E9: 6305 | F9: 0 | G9: 2275 | H9: =SUM(E9:G9) -> 8580
A10: 46062 | B10: Monday | C10: 6 | D10: 14% and 10% | E10: 4025 | F10: 0 | G10: 800 | H10: =SUM(E10:G10) -> 4825
A11: 46063 | B11: Tuesday | C11: 10 | D11: 14% and 10% | E11: 6955 | F11: 180 | G11: 1000 | H11: =SUM(E11:G11) -> 8135
A12: 46064 | B12: Wednesday | C12: 7.5 | D12: 14% and 10% | E12: 4920 | F12: 0 | G12: 1600 | H12: =SUM(E12:G12) -> 6520
A13: 46065 | B13: Thursday | C13: 11 | D13: 14% and 10% | E13: 7340 | F13: 0 | G13: 1825 | H13: =SUM(E13:G13) -> 9165
... A29: 46081 | B29: Saturday | C29: 16 | D29: 14% and 10% | E29: 10200 | F29: 0 | G29: 600 | H29: =SUM(E29:G29) -> 10800
A30: Total | C30: =SUM(C2:C29) -> 244.5 | E30: =SUM(E2:E29) -> 159850 | F30: =SUM(F2:F29) -> 1845 | G30: =SUM(G2:G29) -> 31275 | H30: =SUM(H2:H29) -> 192970

Sheet Hudle
A1: Link | B1: Date | C1: Paid to Hudle | D1: Commisions (Including GST) | E1: Net Revenue | F1: TDS | G1: TCS | H1: Amount
B2: 1 - 28 Feb | C2: 38157 | D2: 4973.5 | E2: =C2-D2 -> 33183.5 | F2: 32.42 | G2: 162.1 | H2: 33089.6
B3: Total | C3: =SUM(C2) -> 38157 | E3: =SUM(E2) -> 33183.5 | H3: =SUM(H2) -> 33089.6

Sheet Playo
A1: Link | B1: Date | C1: Paid to Playo (₹) | D1: Commissions (₹) | E1: GST (₹) | F1: Net Revenue | G1: TDS (₹) | H1: TCS (₹) | I1: Final Amount (₹)
B2: 1 - 28 Feb | C2: 57992.5 | D2: 3047.75 | E2: 548.61 | F2: =C2-D2-E2 -> 54396.14 | G2: 58.04 | H2: 0 | I2: 54314.96
B3: Total | C3: =SUM(C2) -> 57992.5 | F3: =SUM(F2) -> 54396.14 | I3: =SUM(I2) -> 54314.96

Sheet Khelomore
A1: Link | B1: Date | C1: Paid to Khelomore (₹) | D1: Commissions (₹) | E1: Final Amount (₹)
B2: 1 - 28 Feb | C2: 41385.26 | D2: =C2*5% -> 2069.263 | E2: =C2-D2 -> 39315.997
B3: Total | C3: =SUM(C2) -> 41385.26 | E3: =SUM(E2) -> 39315.997

Sheet Sportomic
A1: Link | B1: Date | C1: Paid to Sportomic (₹)
B2: 1 - 28 Feb | C2: 360

Sheet Other Income
A1: Month | B1: Sports Type | C1: Amount Collected
A2: Feb | B2: Football Management Operations | C2: 120000
