Workbook

Sheet Summary
B2: 1 - 30 Sept
B3: Particulars | C3: Amount
C4: Pickleball
B5: Pay & Play | C5: =sum(C6,C12) -> 138806
B6: Online | C6: =sum(C7:C11) -> 121236
B7: District | C7: =District!C4 -> 121236
B8: Hudle | C8: 0
B9: Playo | C9: 0
B10: Khelomore | C10: 0
B11: Zplys | C11: 0
B12: Offline | C12: =sum(C13:C14) -> 17570
B13: Bookings | C13: ='Offline & RG Community'!D33 -> 17570
B14: Memberships | C14: 0
B15: Community | C15: =sum(C16:C18) -> 42490
B16: Pickup games | C16: ='Offline & RG Community'!E33 -> 35500
B17: Social Events/Tournaments | C17: ='Social EventsTournaments'!D4 -> 6990
B18: Community Partnerships | C18: 0
B19: Academy | C19: =Academy!C2 -> 3500
B20: B2B | C20: =sum(C21,C22) -> 20970
B21: Corporate events | C21: 0
B22: All B2B partnerships | C22: =B2B!E4 -> 20970
B23: Commerce | C23: =sum(C24:C26) -> 11760
B24: Product rental | C24: ='Offline & RG Community'!F33 -> 5750
B25: Product sales | C25: 0
B26: F&B | C26: ='F&B'!B32 -> 6010
B27: Other Income | C27: 0
B28: Total Gross Revenue | C28: =C5+C15+C19+C20+C23+C27 -> 217526
B29: GST | C29: =C28-(C28/1.18) -> 33181.932
B30: Net Revenue Post GST | C30: =C28-C29 -> 184344.07
B31: Commissions, Payment gateway & Event Expense | C31: ='Offline & RG Community'!H33+District!D4+District!E4+'Social EventsTournaments'!E4+Academy!D2+'F&B'!C32+'F&B'!E32 -> 14734.775
B32: Net Revenue | C32: =C28-C29-C31 -> 169609.29
B34: Venue Manager + Cleaner | C34: 60164
B35: Marketing, Branding & Community | C35: 15000
B36: Balls Expense | C36: 9500
B37: Branding Revamp | C37: 12595
B38: F&B Inventory Cost | C38: 3024
B39: Total Expenses | C39: =C34+C35+C36+C37+C38 -> 100283
B40: Net Profit (Revenue - Expenses) | C40: =C32-C39 -> 69326.293
B42: School's Profit Share (65%) | C42: =C40*65% -> 45062.09
B43: RallyGully's Profit Share (35%) | C43: =C40*35% -> 24264.202

Sheet Offline & RG Community
A1: Date | B1: Day | C1: Offline booking hours | D1: Booking Revenue | E1: Community Revenue | F1: Paddle Rental | G1: Total Revenue | H1: Payment Gateway | I1: Net Revenue
A2: 46266 | B2: Tuesday | C2: 1 | D2: 900 | E2: 0 | F2: 400 | G2: =SUM(D2:F2) -> 1300 | H2: =G2*1.75% -> 22.75 | I2: =G2-H2 -> 1277.25
A3: 46267 | B3: Wednesday | C3: 0 | D3: 0 | E3: 0 | F3: 500 | G3: =SUM(D3:F3) -> 500 | H3: =G3*1.75% -> 8.75 | I3: =G3-H3 -> 491.25
A4: 46268 | B4: Thursday | C4: 0 | D4: 0 | E4: 0 | F4: 700 | G4: =SUM(D4:F4) -> 700 | H4: =G4*1.75% -> 12.25 | I4: =G4-H4 -> 687.75
A5: 46269 | B5: Friday | C5: 0 | D5: 0 | E5: 0 | F5: 0 | G5: =SUM(D5:F5) -> 0 | H5: =G5*1.75% -> 0 | I5: =G5-H5 -> 0
A6: 46270 | B6: Saturday | C6: 1 | D6: 1200 | E6: 0 | F6: 0 | G6: =SUM(D6:F6) -> 1200 | H6: =G6*1.75% -> 21 | I6: =G6-H6 -> 1179
A7: 46271 | B7: Sunday | C7: 0 | D7: 0 | E7: 0 | F7: 0 | G7: =SUM(D7:F7) -> 0 | H7: =G7*1.75% -> 0 | I7: =G7-H7 -> 0
A8: 46272 | B8: Monday | C8: 0.5 | D8: 600 | E8: 2400 | F8: 0 | G8: =SUM(D8:F8) -> 3000 | H8: =G8*1.75% -> 52.5 | I8: =G8-H8 -> 2947.5
A9: 46273 | B9: Tuesday | C9: 0 | D9: 0 | E9: 3300 | F9: 350 | G9: =SUM(D9:F9) -> 3650 | H9: =G9*1.75% -> 63.875 | I9: =G9-H9 -> 3586.125
A10: 46274 | B10: Wednesday | C10: 0 | D10: 0 | E10: 2400 | F10: 300 | G10: =SUM(D10:F10) -> 2700 | H10: =G10*1.75% -> 47.25 | I10: =G10-H10 -> 2652.75
A11: 46275 | B11: Thursday | C11: 0 | D11: 0 | E11: 300 | F11: 0 | G11: =SUM(D11:F11) -> 300 | H11: =G11*1.75% -> 5.25 | I11: =G11-H11 -> 294.75
A12: 46276 | B12: Friday | C12: 0 | D12: 0 | E12: 2700 | F12: 400 | G12: =SUM(D12:F12) -> 3100 | H12: =G12*1.75% -> 54.25 | I12: =G12-H12 -> 3045.75
A13: 46277 | B13: Saturday | C13: 0 | D13: 0 | E13: 1200 | F13: 0 | G13: =SUM(D13:F13) -> 1200 | H13: =G13*1.75% -> 21 | I13: =G13-H13 -> 1179
... A32: 46265 | B32: Monday | C32: 0 | D32: 0 | E32: 0 | F32: 0 | G32: =SUM(D32:F32) -> 0 | H32: =G32*1.75% -> 0 | I32: =G32-H32 -> 0
A33: Total | D33: =SUM(D2:D32) -> 17570 | E33: =SUM(E2:E32) -> 35500 | F33: =SUM(F2:F32) -> 5750 | G33: =SUM(G2:G32) -> 58820 | H33: =SUM(H2:H32) -> 1029.35 | I33: =SUM(I2:I32) -> 57790.65

Sheet District
A1: Link | B1: Date | C1: Paid to District | D1: Commissions (₹) | E1: GST on Commission | F1: Net Revenue | G1: TCS | H1: TDS | I1: Final Amount (₹)
B2: 1 - 30 Sept | C2: 121236 | D2: 7358 | E2: 1324 | F2: =C2-D2-E2 -> 112554 | G2: 605 | H2: 121 | I2: =F2-G2-H2 -> 111828
B4: Total | C4: =SUM(C2:C3) -> 121236 | D4: =SUM(D2:D3) -> 7358 | E4: =SUM(E2:E3) -> 1324 | F4: =SUM(F2:F3) -> 112554 | I4: =SUM(I2:I3) -> 111828

Sheet Social EventsTournaments
A1: Date | B1: Sport | C1: Type | D1: Amt | E1: Commission | F1: Event Expenses | G1: Payment Gateway | H1: Net Revenue | I1: TDS | J1: Final Amount (₹)
A2: 30 Sept | B2: Pickleball | C2: DUPR Shuffle | D2: 6990 | E2: =D2*5% -> 349.5 | F2: 0 | G2: 0 | H2: =D2-E2-G2 -> 6640.5 | I2: =D2*2% -> 139.8 | J2: =H2-I2 -> 6500.7
A4: Total | D4: =SUM(D2:D3) -> 6990 | E4: =SUM(E2:E3) -> 349.5 | F4: =SUM(F2:F3) -> 0 | G4: =SUM(G2:G3) -> 0 | H4: =SUM(H2:H3) -> 6640.5 | I4: =SUM(I2:I3) -> 139.8 | J4: =SUM(J2:J3) -> 6500.7

Sheet B2B
A1: Start Month | B1: Partnership Type | C1: Name of Brand | D1: Deliverables | E1: Amount (₹)
A2: Sep | B2: Product Shoot | C2: Savikalpa | D2: 3 Hours of courts | E2: 4800
A3: Sep | B3: Mastercard Corporate Package | C3: Mastercard | D3: 1 Court Daily | E3: 16170
A4: Total | E4: =SUM(E2,E3) -> 20970

Sheet Academy
A1: Sports | B1: Month | C1: Amt | D1: Payment Gateway | E1: Net Revenue
A2: Pickleball | B2: Sept | C2: 3500 | D2: =C2*1.75% -> 61.25 | E2: =C2-D2 -> 3438.75

Sheet F&B
A1: Date | B1: F&B | C1: Paid to brand (75%) | D1: Blended Margin (25%) | E1: Payment Gateway | F1: Net Revenue
A2: 46266 | B2: 0 | C2: =B2*75% -> 0 | D2: =B2*25% -> 0 | E2: =B2*1.75% -> 0 | F2: =D2-E2 -> 0
A3: 46267 | B3: 280 | C3: =B3*75% -> 210 | D3: =B3*25% -> 70 | E3: =B3*1.75% -> 4.9 | F3: =D3-E3 -> 65.1
A4: 46268 | B4: 270 | C4: =B4*75% -> 202.5 | D4: =B4*25% -> 67.5 | E4: =B4*1.75% -> 4.725 | F4: =D4-E4 -> 62.775
A5: 46269 | B5: 0 | C5: =B5*75% -> 0 | D5: =B5*25% -> 0 | E5: =B5*1.75% -> 0 | F5: =D5-E5 -> 0
A6: 46270 | B6: 360 | C6: =B6*75% -> 270 | D6: =B6*25% -> 90 | E6: =B6*1.75% -> 6.3 | F6: =D6-E6 -> 83.7
A7: 46271 | B7: 0 | C7: =B7*75% -> 0 | D7: =B7*25% -> 0 | E7: =B7*1.75% -> 0 | F7: =D7-E7 -> 0
A8: 46272 | B8: 175 | C8: =B8*75% -> 131.25 | D8: =B8*25% -> 43.75 | E8: =B8*1.75% -> 3.0625 | F8: =D8-E8 -> 40.6875
A9: 46273 | B9: 735 | C9: =B9*75% -> 551.25 | D9: =B9*25% -> 183.75 | E9: =B9*1.75% -> 12.8625 | F9: =D9-E9 -> 170.8875
A10: 46274 | B10: 410 | C10: =B10*75% -> 307.5 | D10: =B10*25% -> 102.5 | E10: =B10*1.75% -> 7.175 | F10: =D10-E10 -> 95.325
A11: 46275 | B11: 105 | C11: =B11*75% -> 78.75 | D11: =B11*25% -> 26.25 | E11: =B11*1.75% -> 1.8375 | F11: =D11-E11 -> 24.4125
A12: 46276 | B12: 200 | C12: =B12*75% -> 150 | D12: =B12*25% -> 50 | E12: =B12*1.75% -> 3.5 | F12: =D12-E12 -> 46.5
A13: 46277 | B13: 0 | C13: =B13*75% -> 0 | D13: =B13*25% -> 0 | E13: =B13*1.75% -> 0 | F13: =D13-E13 -> 0
... A31: 46295 | B31: 435 | C31: =B31*75% -> 326.25 | D31: =B31*25% -> 108.75 | E31: =B31*1.75% -> 7.6125 | F31: =D31-E31 -> 101.1375
A32: Total | B32: =SUM(B2:B31) -> 6010 | C32: =SUM(C2:C31) -> 4507.5 | D32: =SUM(D2:D31) -> 1502.5 | E32: =SUM(E2:E31) -> 105.175 | F32: =SUM(F2:F31) -> 1397.325
