Workbook

Sheet Summary
B2: 1 - 31 May
B3: Particulars | C3: Amount
C4: Pickleball
B5: Pay & Play | C5: =sum(C6,C12) -> 98847
B6: Online | C6: =sum(C7:C11) -> 82967
B7: District | C7: =District!C4 -> 78175
B8: Hudle | C8: =Hudle!C4 -> 3192
B9: Playo | C9: =Playo!C3 -> 1600
B10: Khelomore | C10: 0
B11: Zplys | C11: 0
B12: Offline | C12: =sum(C13:C14) -> 15880
B13: Bookings | C13: ='Offline & RG Community'!E33 -> 15880
B14: Memberships | C14: 0
B15: Community | C15: =sum(C16:C17) -> 7600
B16: Pickup games | C16: ='Offline & RG Community'!F33 -> 7600
B17: Social Events/Tournaments | C17: 0
B18: Academy | C18: 0
B19: Events & Partnership | C19: =sum(C20,C21) -> 0
B20: Corporate events | C20: 0
B21: All B2B partnerships | C21: 0
B22: Commerce | C22: =sum(C23:C25) -> 7875
B23: Product rental | C23: ='Offline & RG Community'!G33 -> 7875
B24: Product sales | C24: 0
B25: F&B | C25: 0
B26: Other Income | C26: ='Other Income'!E2 -> 18000 | D26: (Note for CA Team: Please note that RallyGully hasn't received the 18000 rental for basketball rental service provided) - GST payment would have to be made by Drive & Kick Team
B27: Total Gross Revenue | C27: =sum(C26+C22+C19+C18+C15+C12+C6) -> 132322
B28: Total Net Revenue (Post Commissions) | C28: ='Offline & RG Community'!J33+District!F4+Hudle!E4+Playo!F3+'Other Income'!E2 -> 124115.03
B29: Total Revenue post GST | C29: =C28/1.18 -> 105182.23
B30: Drive & Kick Share (70%) | C30: =C29*70% -> 73627.559
B31: Drive & Kick Share (Final share after incorporting 18k already received by Drive Kick) | C31: =C30-C26 -> 55627.559
B32: RallyGully's Share (30%) | C32: =C29*30% -> 31554.668

Sheet Offline & RG Community
A1: Date | B1: Day | C1: Offline booking hours | D1: Discount | E1: Booking Revenue | F1: Community | G1: Paddle Rental | H1: Total Revenue | I1: Payment Gateway | J1: Net Revenue
A2: 46143 | B2: Friday | C2: 0 | D2: 10 and 20% | E2: 0 | F2: 0 | G2: 200 | H2: =sum(E2:G2) -> 200 | I2: =H2*2.5%*1.18 -> 5.9 | J2: =H2-I2 -> 194.1
A3: 46144 | B3: Saturday | C3: 1 | D3: 10 and 20% | E3: 640 | F3: 0 | G3: 0 | H3: =sum(E3:G3) -> 640 | I3: =H3*2.5%*1.18 -> 18.88 | J3: =H3-I3 -> 621.12
A4: 46145 | B4: Sunday | C4: 2 | D4: 10 and 20% | E4: 1280 | F4: 0 | G4: 400 | H4: =sum(E4:G4) -> 1680 | I4: =H4*2.5%*1.18 -> 49.56 | J4: =H4-I4 -> 1630.44
A5: 46146 | B5: Monday | C5: 3 | D5: 10 and 20% | E5: 2000 | F5: 0 | G5: 400 | H5: =sum(E5:G5) -> 2400 | I5: =H5*2.5%*1.18 -> 70.8 | J5: =H5-I5 -> 2329.2
A6: 46147 | B6: Tuesday | C6: 0.1 | D6: 10 and 20% | E6: 100 | F6: 0 | G6: 50 | H6: =sum(E6:G6) -> 150 | I6: =H6*2.5%*1.18 -> 4.425 | J6: =H6-I6 -> 145.575
A7: 46148 | B7: Wednesday | C7: 2 | D7: 10 and 20% | E7: 1280 | F7: 0 | G7: 50 | H7: =sum(E7:G7) -> 1330 | I7: =H7*2.5%*1.18 -> 39.235 | J7: =H7-I7 -> 1290.765
A8: 46149 | B8: Thursday | C8: 1 | D8: 10 and 20% | E8: 720 | F8: 0 | G8: 250 | H8: =sum(E8:G8) -> 970 | I8: =H8*2.5%*1.18 -> 28.615 | J8: =H8-I8 -> 941.385
A9: 46150 | B9: Friday | C9: 0 | D9: 10 and 20% | E9: 0 | F9: 0 | G9: 200 | H9: =sum(E9:G9) -> 200 | I9: =H9*2.5%*1.18 -> 5.9 | J9: =H9-I9 -> 194.1
A10: 46151 | B10: Saturday | C10: 2 | D10: 10 and 20% | E10: 1360 | F10: 2800 | G10: 650 | H10: =sum(E10:G10) -> 4810 | I10: =H10*2.5%*1.18 -> 141.895 | J10: =H10-I10 -> 4668.105
A11: 46152 | B11: Sunday | C11: 1.5 | D11: 10 and 20% | E11: 1060 | F11: 2600 | G11: 750 | H11: =sum(E11:G11) -> 4410 | I11: =H11*2.5%*1.18 -> 130.095 | J11: =H11-I11 -> 4279.905
A12: 46153 | B12: Monday | C12: 0 | D12: 10 and 20% | E12: 0 | F12: 0 | G12: 100 | H12: =sum(E12:G12) -> 100 | I12: =H12*2.5%*1.18 -> 2.95 | J12: =H12-I12 -> 97.05
A13: 46154 | B13: Tuesday | C13: 0 | D13: 10 and 20% | E13: 0 | F13: 0 | G13: 200 | H13: =sum(E13:G13) -> 200 | I13: =H13*2.5%*1.18 -> 5.9 | J13: =H13-I13 -> 194.1
... A16: 46157 | B16: Friday | C16: 2 | D16: 10 and 20% | E16: 1440 | F16: 0 | G16: 300 | H16: =sum(E16:G16) -> 1740 | I16: =H16*2.5%*1.18 -> 51.33 | J16: =H16-I16 -> 1688.67
A17: 46158 | B17: Saturday | C17: 0 | D17: 10 and 20% | E17: 0 | F17: 0 | G17: 75 | H17: =SUM(E17:G17) -> 75 | I17: =H17*2.5%*1.18 -> 2.2125 | J17: =H17-I17 -> 72.7875
A18: 46159 | B18: Sunday | C18: 1.5 | D18: 10 and 20% | E18: 1000 | F18: 0 | G18: 300 | H18: =SUM(E18:G18) -> 1300 | I18: =H18*2.5%*1.18 -> 38.35 | J18: =H18-I18 -> 1261.65
A19: 46160 | B19: Monday | C19: 0 | D19: 10 and 20% | E19: 0 | F19: 0 | G19: 150 | H19: =SUM(E19:G19) -> 150 | I19: =H19*2.5%*1.18 -> 4.425 | J19: =H19-I19 -> 145.575
A20: 46161 | B20: Tuesday | C20: 3 | D20: 10 and 20% | E20: 1920 | F20: 0 | G20: 250 | H20: =SUM(E20:G20) -> 2170 | I20: =H20*2.5%*1.18 -> 64.015 | J20: =H20-I20 -> 2105.985
A21: 46162 | B21: Wednesday | C21: 0 | D21: 10 and 20% | E21: 0 | F21: 0 | G21: 200 | H21: =SUM(E21:G21) -> 200 | I21: =H21*2.5%*1.18 -> 5.9 | J21: =H21-I21 -> 194.1
A22: 46163 | B22: Thursday | C22: 0 | D22: 10 and 20% | E22: 0 | F22: 0 | G22: 175 | H22: =SUM(E22:G22) -> 175 | I22: =H22*2.5%*1.18 -> 5.1625 | J22: =H22-I22 -> 169.8375
A23: 46164 | B23: Friday | C23: 0 | D23: 10 and 20% | E23: 0 | F23: 0 | G23: 0 | H23: =sum(E23:G23) -> 0 | I23: =H23*2.5%*1.18 -> 0 | J23: =H23-I23 -> 0
A24: 46165 | B24: Saturday | C24: 1 | D24: 10 and 20% | E24: 640 | F24: 2200 | G24: 500 | H24: =SUM(E24:G24) -> 3340 | I24: =H24*2.5%*1.18 -> 98.53 | J24: =H24-I24 -> 3241.47
A25: 46166 | B25: Sunday | C25: 2 | D25: 10 and 20% | E25: 1440 | F25: 0 | G25: 950 | H25: =SUM(E25:G25) -> 2390 | I25: =H25*2.5%*1.18 -> 70.505 | J25: =H25-I25 -> 2319.495
A26: 46167 | B26: Monday | C26: 0 | D26: 10 and 20% | E26: 0 | F26: 0 | G26: 200 | H26: =SUM(E26:G26) -> 200 | I26: =H26*2.5%*1.18 -> 5.9 | J26: =H26-I26 -> 194.1
A27: 46168 | B27: Tuesday | C27: 0 | D27: 10 and 20% | E27: 0 | F27: 0 | G27: 350 | H27: =SUM(E27:G27) -> 350 | I27: =H27*2.5%*1.18 -> 10.325 | J27: =H27-I27 -> 339.675
A28: 46169 | B28: Wednesday | C28: 0 | D28: 10 and 20% | E28: 0 | F28: 0 | G28: 250 | H28: =SUM(E28:G28) -> 250 | I28: =H28*2.5%*1.18 -> 7.375 | J28: =H28-I28 -> 242.625
A29: 46170 | B29: Thursday | C29: 0 | D29: 10 and 20% | E29: 0 | F29: 0 | G29: 0 | H29: =SUM(E29:G29) -> 0 | I29: =H29*2.5%*1.18 -> 0 | J29: =H29-I29 -> 0
A30: 46171 | B30: Friday | C30: 0 | D30: 10 and 20% | E30: 0 | F30: 0 | G30: 0 | H30: =SUM(E30:G30) -> 0 | I30: =H30*2.5%*1.18 -> 0 | J30: =H30-I30 -> 0
A31: 46172 | B31: Saturday | C31: 0 | D31: 10 and 20% | E31: 0 | F31: 0 | G31: 250 | H31: =SUM(E31:G31) -> 250 | I31: =H31*2.5%*1.18 -> 7.375 | J31: =H31-I31 -> 242.625
A32: 46173 | B32: Sunday | C32: 1.5 | D32: 10 and 20% | E32: 1000 | F32: 0 | G32: 425 | H32: =SUM(E32:G32) -> 1425 | I32: =H32*2.5%*1.18 -> 42.0375 | J32: =H32-I32 -> 1382.9625
A33: Total | E33: =SUM(E1:E32) -> 15880 | F33: =SUM(F1:F32) -> 7600 | G33: =SUM(G1:G32) -> 7875 | H33: =SUM(H1:H32) -> 31355 | I33: =SUM(I1:I32) -> 924.9725 | J33: =SUM(J1:J32) -> 30430.028

Sheet District
A1: Link | B1: Date | C1: Paid to District | D1: Commissions (₹) | E1: GST on Commission | F1: Net Revenue | G1: TCS | H1: TDS | I1: Final Amount (₹)
B2: 1 - 31 May | C2: 78175 | D2: 5726 | E2: 1030 | F2: =C2-D2-E2 -> 71419 | G2: 477 | H2: 95 | I2: 70845
B4: Total | C4: =SUM(C2:C3) -> 78175 | F4: =SUM(F2:F3) -> 71419 | I4: =SUM(I2:I3) -> 70845

Sheet Hudle
A1: Link | B1: Date | C1: Paid to Hudle | D1: Commisions (Including GST) | E1: Net Revenue | F1: TDS | G1: TCS | H1: Amount
B2: 1 - 31 May | C2: 3192 | D2: 394 | E2: =C2-D2 -> 2798 | F2: 2.5 | G2: 12.8 | H2: 2622
B4: Total | C4: =SUM(C2:C3) -> 3192 | E4: =SUM(E2:E3) -> 2798 | H4: =SUM(H2:H3) -> 2622

Sheet Playo
A1: Link | B1: Date | C1: Paid to Playo (₹) | D1: Commissions (₹) | E1: GST (₹) | F1: Net Revenue | G1: TDS (₹) | H1: TCS (₹) | I1: Final Amount (₹)
B2: 1 - 31 May | C2: 1600 | D2: 112 | E2: 20 | F2: =C2-D2-E2 -> 1468 | G2: 1.6 | H2: 8 | I2: 1458
B3: Total | C3: =SUM(C2) -> 1600 | F3: =SUM(F2) -> 1468 | I3: =SUM(I2) -> 1458

Sheet Other Income
A1: Month | B1: Coaching | C1: Sports Type | D1: Type | E1: Amount Collected
A2: May | B2: Basketball Coaching | C2: Basketball | D2: 3 days in week | E2: 18000
