Workbook

Sheet Summary
B2: Date: 1 - 31 Mar
B3: Particulars | C3: Amount
B4: Offline | C4: =SUM(C5,C6,C7,C8) -> 68755
B5: Rentals | C5: ='Offline & RG Community'!G33 -> 9275
B6: F&B | C6: ='Offline & RG Community'!H33 -> 490
B7: Product Sales | C7: 0
B8: Bookings | C8: ='Offline & RG Community'!E33 -> 58990
B9: Online: Third Party Platform | C9: =SUM(C10:C13) -> 44755
B10: Hudle | C10: =Hudle!C4 -> 5505
B11: Playo | C11: =Playo!C4 -> 900
B12: District | C12: =District!C4 -> 38350
B13: Khelomore | C13: 0
B14: Zplys | C14: 0
B15: Community | C15: =SUM(C17,C16, C18,C19) -> 56360
B16: Courtly (Organized by RallyGully) | C16: =Courtly!B3 -> 40480
B17: Sportomic (Organized by RallyGully) | C17: 0
B18: Rallygully Community games | C18: ='Offline & RG Community'!F33 -> 15880
B19: Misfits Community | C19: 0
B20: Memberships | C20: 0
B21: Corporate Events | C21: 0
B22: Brand Activation | C22: ='Brand Activation'!E4 -> 10000
B23: Other Income | C23: =0 -> 0
B24: Total Gross Revenue | C24: =sum(C4,C9,C15,C20,C21,C22,C23) -> 179870
B25: Total Net Revenue (Post Commissions) | C25: ='Offline & RG Community'!I33+Hudle!E4+Playo!F4+District!F4+Courtly!D3+'Brand Activation'!E4 -> 176378.48
B26: Total Revenue post GST | C26: =C25/1.18 -> 149473.29
B27: Investor's Share (40%) | C27: =C26*40% -> 59789.315

Sheet Offline & RG Community
A1: Date | B1: Day | C1: Offline booking hours | D1: Discount Given | E1: Booking Revenue | F1: Community Revenue | G1: Paddle Rental | H1: F&B | I1: Total Revenue
A2: 1 Mar | B2: Sunday | C2: 2 | D2: 0.2 | E2: 1470 | F2: 0 | G2: 550 | H2: 0 | I2: =E2+F2+G2 -> 2020
A3: 2 Mar | B3: Monday | C3: 1 | D3: 0.2 | E3: 720 | F3: 0 | G3: 200 | H3: 0 | I3: =E3+F3+G3 -> 920
A4: 3 Mar | B4: Tuesday | C4: 2.5 | D4: 0.2 | E4: 1730 | F4: 0 | G4: 500 | H4: 70 | I4: =E4+F4+G4+H4 -> 2300
A5: 4 Mar | B5: Wednesday | C5: 0.5 | D5: 0.2 | E5: 360 | F5: 0 | G5: 550 | H5: 0 | I5: =E5+F5+G5 -> 910
A6: 5 Mar | B6: Thursday | C6: 5 | D6: 0.2 | E6: 3600 | F6: 0 | G6: 200 | H6: 0 | I6: =E6+F6+G6 -> 3800
A7: 6 Mar | B7: Friday | C7: 2.5 | D7: 0.2 | E7: 1800 | F7: 0 | G7: 550 | H7: 105 | I7: =E7+F7+G7+H7 -> 2455
A8: 7 Mar | B8: Saturday | C8: 4.5 | D8: 0.2 | E8: 3240 | F8: 0 | G8: 450 | H8: 0 | I8: =E8+F8+G8 -> 3690
A9: 8 Mar | B9: Sunday | C9: 2 | D9: 0.2 | E9: 1440 | F9: 0 | G9: 275 | H9: 35 | I9: =E9+F9+G9+H9 -> 1750
A10: 9 Mar | B10: Monday | C10: 4 | D10: 0.2 | E10: 3240 | F10: 0 | G10: 400 | H10: 0 | I10: =E10+F10+G10 -> 3640
A11: 10 Mar | B11: Tuesday | C11: 3 | D11: 0.2 | E11: 2160 | F11: 0 | G11: 200 | H11: 0 | I11: =E11+F11+G11 -> 2360
A12: 11 Mar | B12: Wednesday | C12: 2 | D12: 0.2 | E12: 1170 | F12: 0 | G12: 350 | H12: 0 | I12: =E12+F12+G12 -> 1520
A13: 12 Mar | B13: Thursday | C13: 6 | D13: 0.2 | E13: 5760 | F13: 0 | G13: 400 | H13: 0 | I13: =E13+F13+G13 -> 6160
A14: 13 Mar | B14: Friday | C14: 2 | D14: 0.2 | E14: 1440 | F14: 0 | G14: 950 | H14: 105 | I14: =E14+F14+G14+H14 -> 2495
A15: 14 Mar | B15: Saturday | C15: 0 | D15: 0.2 | E15: 0 | F15: 0 | G15: 150 | H15: 0 | I15: =E15+F15+G15 -> 150
A16: 15 Mar | B16: Sunday | C16: 5 | D16: 0.2 | E16: 4240 | F16: 0 | G16: 800 | H16: 0 | I16: =E16+F16+G16 -> 5040
A17: 16 Mar | B17: Monday | C17: 2 | D17: 0.2 | E17: 2160 | F17: 0 | G17: 100 | H17: 0 | I17: =E17+F17+G17 -> 2260
A18: 17 Mar | B18: Tuesday | C18: 3 | D18: 0.2 | E18: 3240 | F18: 0 | G18: 150 | H18: 70 | I18: =E18+F18+G18+H18 -> 3460
A19: 18 Mar | B19: Wednesday | C19: 0 | D19: 0.2 | E19: 0 | F19: 0 | G19: 0 | H19: 0 | I19: =E19+F19+G19 -> 0
A20: 19 Mar | B20: Thursday | C20: 0 | D20: 0.2 | E20: 0 | F20: 0 | G20: 0 | H20: 0 | I20: =E20+F20+G20 -> 0
A21: 20 Mar | B21: Friday | C21: 0 | D21: 0.2 | E21: 0 | F21: 0 | G21: 0 | H21: 0 | I21: =E21+F21+G21 -> 0
A22: 21 Mar | B22: Saturday | C22: 1 | D22: 0.2 | E22: 700 | F22: 15880 | G22: 0 | H22: 105 | I22: =E22+F22+G22+H22 -> 16685
A23: 22 Mar | B23: Sunday | C23: 3 | D23: 0.2 | E23: 1800 | F23: 0 | G23: 650 | H23: 0 | I23: =E23+F23+G23+H23 -> 2450
A24: 23 Mar | B24: Monday | C24: 0 | D24: 0.2 | E24: 0 | F24: 0 | G24: 0 | H24: 0 | I24: =E24+F24+G24 -> 0
A25: 24 Mar | B25: Tuesday | C25: 1 | D25: 0.2 | E25: 720 | F25: 0 | G25: 0 | H25: 0 | I25: =E25+F25+G25 -> 720
A26: 25 Mar | B26: Wednesday | C26: 3 | D26: 0.2 | E26: 3240 | F26: 0 | G26: 150 | H26: 0 | I26: =E26+F26+G26 -> 3390
A27: 26 Mar | B27: Thursday | C27: 3 | D27: 0.2 | E27: 2160 | F27: 0 | G27: 200 | H27: 0 | I27: =E27+F27+G27 -> 2360
A28: 27 Mar | B28: Friday | C28: 0 | D28: 0.2 | E28: 0 | F28: 0 | G28: 100 | H28: 0 | I28: =E28+F28+G28 -> 100
A29: 28 Mar | B29: Saturday | C29: 3 | D29: 0.2 | E29: 3600 | F29: 0 | G29: 300 | H29: 0 | I29: =E29+F29+G29 -> 3900
A30: 29 Mar | B30: Sunday | C30: 3 | D30: 0.2 | E30: 2520 | F30: 0 | G30: 600 | H30: 0 | I30: =E30+F30+G30 -> 3120
A31: 30 Mar | B31: Monday | C31: 2 | D31: 0.2 | E31: 2880 | F31: 0 | G31: 500 | H31: 0 | I31: =E31+F31+G31 -> 3380
A32: 31 Mar | B32: Tuesday | C32: 0 | D32: 0.2 | E32: 3600 | F32: 0 | G32: 0 | H32: 0 | I32: =E32+F32+G32 -> 3600
A33: Total | C33: =SUM(C1:C32) -> 66 | E33: =SUM(E1:E32) -> 58990 | F33: =SUM(F1:F32) -> 15880 | G33: =SUM(G1:G32) -> 9275 | H33: =SUM(H1:H32) -> 490 | I33: =SUM(I1:I32) -> 84635

Sheet Hudle
A1: Link | B1: Date | C1: Paid to Hudle | D1: Commisions (Including GST) | E1: Net Revenue | F1: TDS | G1: TCS | H1: Amount
B2: 1 - 23 Mar | C2: 5505 | D2: 789.1 | E2: =C2-D2 -> 4715.9 | F2: 5.14 | G2: 25.73 | H2: 5250.02
B3: 23 - 31 Mar | C3: 0 | D3: 0 | E3: =C3-D3 -> 0 | F3: 0 | G3: 0 | H3: 0
B4: Total | C4: =SUM(C2:C3) -> 5505 | E4: =SUM(E2:E3) -> 4715.9 | H4: =SUM(H2:H3) -> 5250.02

Sheet Playo
A1: Link | B1: Date | C1: Paid to Playo (₹) | D1: Commissions (₹) | E1: GST (₹) | F1: Net Revenue | G1: TDS (₹) | H1: TCS (₹) | I1: Final Amount (₹)
B2: 1 - 22 Mar | C2: 900 | D2: 63 | E2: 11.34 | F2: =C2-D2-E2 -> 825.66 | G2: 4.5 | H2: 0.9 | I2: 820.26
B3: 23 - 31 Mar | C3: 0 | D3: 0 | E3: 0 | F3: =C3-D3-E3 -> 0 | G3: 0 | H3: 0 | I3: 0
B4: Total | C4: =SUM(C2) -> 900 | F4: =SUM(F2) -> 825.66 | I4: =SUM(I2) -> 820.26

Sheet District
A1: Link | B1: Date | C1: Paid to District | D1: Commissions (₹) | E1: GST on Commission | F1: Net Revenue | G1: TCS | H1: TDS | I1: Final Amount (₹)
B2: 1 - 24 Mar | C2: 28450 | D2: 986 | E2: 177.52 | F2: =C2-D2-E2 -> 27286.48 | G2: 137 | H2: 29.4 | I2: 25654.6
B3: 25 - 31 Mar | C3: 9900 | D3: 212 | E3: 38.16 | F3: =C3-D3-E3 -> 9649.84 | G3: 53 | H3: 10.6 | I3: 10286.24
B4: Total | C4: =SUM(C2:C3) -> 38350 | F4: =SUM(F2:F3) -> 36936.32 | I4: =SUM(I2:I3) -> 35940.84

Sheet Courtly
A1: Date | B1: Paid to Courtly | C1: Post Comission | D1: Net Revenue | E1: TDS | F1: Final Amount (₹)
A2: 46102 | B2: 40480 | C2: =B2*3% -> 1214.4 | D2: =B2-C2 -> 39265.6 | E2: =B2*2% -> 809.6 | F2: =D2-E2 -> 38456
A3: Total | B3: =SUM(B2) -> 40480 | D3: =SUM(D2) -> 39265.6 | F3: =SUM(F2) -> 38456

Sheet Brand Activation
A1: Date | B1: Brand Name | C1: Amount | D1: Commission | E1: Net Revenue | F1: Type of collab
A2: 46102 | B2: Savikalpa | C2: 10000 | D2: 0 | E2: =C2-D2 -> 10000 | F2: Event Partner
A4: Total | C4: =SUM(C2:C3) -> 10000 | E4: =SUM(E2:E3) -> 10000
