Workbook

Sheet Summary
B2: Date: 1st - 30th Nov
B3: Particulars | C3: Amount
B4: Offline | C4: =SUM(C5,C6,C7,, C8) -> 21000
B5: Rentals | C5: ='Offline & RG Community'!G32 -> 4790
B6: F&B | C6: ='Offline & RG Community'!H32 -> 1890
B7: Product Sales | C7: 0
B8: Bookings | C8: ='Offline & RG Community'!E32 -> 14320
B9: Online: Third Party Platform | C9: =sum(C10,C11,C12,C13,) -> 96029
B10: Hudle | C10: =Hudle!C7 -> 65915
B11: Playo | C11: =Playo!C8 -> 11080
B12: District | C12: 0
B13: Khelomore | C13: =Khelomore!C6 -> 19034
B14: Community | C14: =SUM(C15,C16) -> 1100
B15: Rallygully Community games | C15: ='Offline & RG Community'!F32 -> 1100
B16: Misfits Community | C16: 0
B17: Courtly | C17: 0
B18: Memberships | C18: =Memberships!E2 -> 50000
B19: Corporate Events | C19: 0
B20: Brand Activation | C20: =0 -> 0
B21: Other Income | C21: 0
B22: Total Gross Revenue | C22: =sum(C4,C9,C18,C19,C20,C21,C14) -> 168129
B23: Total Net Revenue (Post Commissions) | C23: =SUM('Offline & RG Community'!I32,Hudle!E7,Playo!F8,Khelomore!E6,Misfits!D2,Memberships!E2) -> 153608.68
B24: Total Revenue post GST | C24: =C23/1.18 -> 130176.85

Sheet Offline & RG Community
A1: Date | B1: Day | C1: Offline booking hours | D1: Discount Given | E1: Booking Revenue | F1: Community Revenue | G1: Paddle Rental | H1: Drinks Revenue | I1: Total Revenue
A2: 45962 | B2: Saturday | C2: 0 | D2: 0% and 10% | E2: 0 | F2: 0 | G2: 175 | H2: 150 | I2: =SUM(E2:H2) -> 325
A3: 45963 | B3: Sunday | C3: 0 | D3: 0% and 10% | E3: 0 | F3: 0 | G3: 50 | H3: 60 | I3: =SUM(E3:H3) -> 110
A4: 45964 | B4: Monday | C4: 0 | D4: 0% and 10% | E4: 0 | F4: 0 | G4: 0 | H4: 0 | I4: =SUM(E4:H4) -> 0
A5: 45965 | B5: Tuesday | C5: 1 | D5: 0% and 10% | E5: 720 | F5: 0 | G5: 100 | H5: 30 | I5: =SUM(E5:H5) -> 850
A6: 45966 | B6: Wednesday | C6: 1 | D6: 0% and 10% | E6: 800 | F6: 50 | G6: 180 | H6: 0 | I6: =SUM(E6:H6) -> 1030
A7: 45967 | B7: Thursday | C7: 1 | D7: 0% and 10% | E7: 720 | F7: 250 | G7: 60 | H7: 60 | I7: =SUM(E7:H7) -> 1090
A8: 45968 | B8: Friday | C8: 0 | D8: 0% and 10% | E8: 0 | F8: 0 | G8: 100 | H8: 60 | I8: =SUM(E8:H8) -> 160
A9: 45969 | B9: Saturday | C9: 1 | D9: 0% and 10% | E9: 800 | F9: 800 | G9: 300 | H9: 0 | I9: =SUM(E9:H9) -> 1900
A10: 45970 | B10: Sunday | C10: 0 | D10: 0% and 10% | E10: 0 | F10: 0 | G10: 150 | H10: 210 | I10: =SUM(E10:H10) -> 360
A11: 45971 | B11: Monday | C11: 0 | D11: 0% and 10% | E11: 0 | F11: 0 | G11: 100 | H11: 0 | I11: =SUM(E11:H11) -> 100
A12: 45972 | B12: Tuesday | C12: 0 | D12: 0% and 10% | E12: 0 | F12: 0 | G12: 0 | H12: 120 | I12: =SUM(E12:H12) -> 120
A13: 45973 | B13: Wednesday | C13: 0 | D13: 0% and 10% | E13: 0 | F13: 0 | G13: 100 | H13: 0 | I13: =SUM(E13:H13) -> 100
... A29: 45989 | B29: Friday | C29: 0 | D29: 0% and 10% | E29: 0 | F29: 0 | G29: 350 | H29: 0 | I29: =SUM(E29:H29) -> 350
A30: 45990 | B30: Saturday | C30: 0 | D30: 0% and 10% | I30: Venue Closed
A31: 45991 | B31: Sunday | C31: 0 | D31: 0% and 10% | I31: Venue Closed
A32: Total | C32: =SUM(C2:C31) -> 18.5 | E32: =SUM(E2:E31) -> 14320 | F32: =SUM(F2:F31) -> 1100 | G32: =SUM(G2:G31) -> 4790 | H32: =SUM(H2:H31) -> 1890 | I32: =SUM(I2:I31) -> 22100

Sheet Hudle
A1: Link | B1: Date | C1: Paid to Hudle | D1: Commisions (Including GST) | E1: Net Revenue | F1: TDS | G1: TCS | H1: Amount
B2: 1 - 10 Nov | C2: 29650 | D2: 3854.5 | E2: =C2-D2 -> 25795.5 | F2: 25.12 | G2: 125.6 | H2: 25644.75
B3: 10 - 18 Nov | C3: 14440 | D3: 1877.2 | E3: =C3-D3 -> 12562.8 | F3: 12.23 | G3: 61.18 | H3: 12489.36
B4: 18 - 25 Nov | C4: 11275 | D4: 1469 | E4: =C4-D4 -> 9806 | F4: 9.5 | G4: 47.8 | H4: 9773.53
B5: 25 - 30 Nov | C5: 10550 | D5: 1378 | E5: =C5-D5 -> 9172 | F5: 8.9 | G5: 44.91 | H5: 9168.08
C7: =SUM(C2:C6) -> 65915 | E7: =SUM(E2:E6) -> 57336.3 | H7: =SUM(H2:H6) -> 57075.72

Sheet Playo
A1: Link | B1: Date | C1: Paid to Playo (₹) | D1: Commissions (₹) | E1: GST (₹) | F1: Net Revenue | G1: TDS (₹) | H1: TCS (₹) | I1: Final Amount (₹)
B2: 1 - 10 Nov | C2: 4600 | D2: 322 | E2: 57.96 | F2: =C2 - D2-E2 -> 4220.04 | G2: 4.6 | H2: 23 | I2: 4192.44
B3: 11 -16 Nov | C3: 3600 | D3: 252 | E3: 45.36 | F3: =C3 - D3-E3 -> 3302.64 | G3: 3.6 | H3: 18 | I3: 3281.04
B4: 17 - 23 Nov | C4: 1600 | D4: 112 | E4: 20.6 | F4: =C4 - D4-E4 -> 1467.4 | G4: 1.6 | H4: 8 | I4: 1458.24
B5: 24 - 30 Nov | C5: 1280 | F5: =C5 - D5-E5 -> 1280 | G5: 25.6 | I5: 1254.4
C8: =SUM(C2:C7) -> 11080 | F8: =SUM(F2:F7) -> 10270.08 | I8: =SUM(I2:I6) -> 10186.12

Sheet Khelomore
A1: Link | B1: Date | C1: Paid to Khelomore (₹) | D1: Commissions (₹) | E1: Final Amount (₹)
B2: 1 - 10 Nov | C2: 2134 | D2: 106.7 | E2: 2027.3
B3: 11 - 16 Nov | C3: 6000 | D3: 300 | E3: 5700
B4: 17 - 23 Nov | C4: 6500 | D4: 325 | E4: 6175
B5: 24 - 30 Nov | C5: 4400
C6: =SUM(C2:C5) -> 19034 | E6: =SUM(E2:E4) -> 13902.3

Sheet Misfits
A1: Link | B1: Date | C1: Paid to Misfits (₹) | D1: Post Comission (20%) | E1: TDS | F1: Final Amount (₹)
B2: 1 - 30 NOV | C2: 0

Sheet Corporate Event
A1: Date & Day | B1: Brand Name | C1: Amount | D1: Timings | E1: Type of collab

Sheet Memberships
A1: Member Name | B1: Sports Type | C1: Membership Type | D1: Start Date | E1: Amount Collected
A2: Sahil Gupta | B2: Pickleball | C2: Grand slam (90) | D2: 45971 | E2: 50000
