Workbook

Sheet Summary
B2: 1 - 31 May
B3: Particulars | C3: Amount
C4: Pickleball
B5: Pay & Play | C5: =sum(C6,C12) -> 109675
B6: Online | C6: =sum(C7:C11) -> 96675
B7: District | C7: =District!C4 -> 71921
B8: Hudle | C8: =Hudle!C3 -> 22954
B9: Playo | C9: =Playo!C3 -> 1800
B10: Khelomore | C10: 0
B11: Zplys | C11: 0
B12: Offline | C12: =sum(C13:C14) -> 13000
B13: Bookings | C13: ='Offline & RG Community'!E33 -> 13000
B14: Memberships | C14: 0
B15: Community | C15: =sum(C16:C17) -> 1800
B16: Pickup games | C16: ='Offline & RG Community'!F33 -> 1800
B17: Social Events/Tournaments | C17: 0
B18: Academy | C18: 0
B19: Events & Partnership | C19: =sum(C20,C21) -> 0
B20: Corporate events | C20: 0
B21: All B2B partnerships | C21: 0
B22: Commerce | C22: =sum(C23:C25) -> 7720
B23: Product rental | C23: ='Offline & RG Community'!G33 -> 7720
B24: Product sales | C24: 0
B25: F&B | C25: 0
B26: Other Income | C26: 0
B27: Total Gross Revenue | C27: =C6+C12+C15+C18+C19+C22+C26 -> 119195
B28: Total Net Revenue (Post Commissions) | C28: ='Offline & RG Community'!J33+District!F4+Hudle!E3+Playo!F3 -> 108708.21
B29: Total Revenue post GST | C29: =C28/1.18 -> 92125.602
B31: Expenses
B32: VM Salary | C32: =1580+11032+10000+2400 -> 25012
B33: Support Staff | C33: 5500
B34: Marketing, Branding & Community | C34: 6000
B35: Balls | C35: 5500
B37: Net Profit | C37: =C29-(sum(C32:C35)) -> 50113.602

Sheet Offline & RG Community
A1: Date | B1: Day | C1: Offline booking hours | D1: Discount Given | E1: Booking Revenue | F1: Community Revenue | G1: Paddle Rental | H1: Total Revenue | I1: Payment Gateway | J1: Net Revenue
A2: 46143 | B2: Friday | C2: 0.5 | D2: 0 and 10% | E2: 500 | F2: 0 | G2: 175 | H2: =sum(E2:G2) -> 675 | I2: =H2*2.5%*1.18 -> 19.9125 | J2: =H2-I2 -> 655.0875
A3: 46144 | B3: Saturday | C3: 0 | D3: 0 and 10% | E3: 0 | F3: 0 | G3: 250 | H3: =sum(E3:G3) -> 250 | I3: =H3*2.5%*1.18 -> 7.375 | J3: =H3-I3 -> 242.625
A4: 46145 | B4: Sunday | C4: 1 | D4: 0 and 10% | E4: 900 | F4: 0 | G4: 100 | H4: =sum(E4:G4) -> 1000 | I4: =H4*2.5%*1.18 -> 29.5 | J4: =H4-I4 -> 970.5
A5: 46146 | B5: Monday | C5: 0.5 | D5: 0 and 10% | E5: 500 | F5: 0 | G5: 500 | H5: =sum(E5:G5) -> 1000 | I5: =H5*2.5%*1.18 -> 29.5 | J5: =H5-I5 -> 970.5
A6: 46147 | B6: Tuesday | C6: 1 | D6: 0 and 10% | E6: 500 | F6: 0 | G6: 250 | H6: =sum(E6:G6) -> 750 | I6: =H6*2.5%*1.18 -> 22.125 | J6: =H6-I6 -> 727.875
A7: 46148 | B7: Wednesday | C7: 2 | D7: 0 and 10% | E7: 0 | F7: 1800 | G7: 150 | H7: =sum(E7:G7) -> 1950 | I7: =H7*2.5%*1.18 -> 57.525 | J7: =H7-I7 -> 1892.475
A8: 46149 | B8: Thursday | C8: 0.5 | D8: 0 and 10% | E8: 500 | F8: 0 | G8: 100 | H8: =sum(E8:G8) -> 600 | I8: =H8*2.5%*1.18 -> 17.7 | J8: =H8-I8 -> 582.3
A9: 46150 | B9: Friday | C9: 0 | D9: 0 and 10% | E9: 0 | F9: 0 | G9: 150 | H9: =sum(E9:G9) -> 150 | I9: =H9*2.5%*1.18 -> 4.425 | J9: =H9-I9 -> 145.575
A10: 46151 | B10: Saturday | C10: 4 | D10: 0 and 10% | E10: 3600 | F10: 0 | G10: 250 | H10: =sum(E10:G10) -> 3850 | I10: =H10*2.5%*1.18 -> 113.575 | J10: =H10-I10 -> 3736.425
A11: 46152 | B11: Sunday | C11: 0 | D11: 0 and 10% | E11: 0 | F11: 0 | G11: 0 | H11: =sum(E11:G11) -> 0 | I11: =H11*2.5%*1.18 -> 0 | J11: =H11-I11 -> 0
A12: 46153 | B12: Monday | C12: 0 | D12: 0 and 10% | E12: 0 | F12: 0 | G12: 560 | H12: =sum(E12:G12) -> 560 | I12: =H12*2.5%*1.18 -> 16.52 | J12: =H12-I12 -> 543.48
A13: 46154 | B13: Tuesday | C13: 0 | D13: 0 and 10% | E13: 0 | F13: 0 | G13: 300 | H13: =sum(E13:G13) -> 300 | I13: =H13*2.5%*1.18 -> 8.85 | J13: =H13-I13 -> 291.15
... A15: 46156 | B15: Thursday | C15: 0 | D15: 0 and 10% | E15: 0 | F15: 0 | G15: 600 | H15: =sum(E15:G15) -> 600 | I15: =H15*2.5%*1.18 -> 17.7 | J15: =H15-I15 -> 582.3
A16: 46157 | B16: Friday | C16: 0 | D16: 0 and 10% | E16: 0 | F16: 0 | G16: 0 | H16: =SUM(E16:G16) -> 0 | I16: =H16*2.5%*1.18 -> 0 | J16: =H16-I16 -> 0
A17: 46158 | B17: Saturday | C17: 1 | D17: 0 and 10% | E17: 900 | F17: 0 | G17: 500 | H17: =SUM(F17:G17) -> 500 | I17: =H17*2.5%*1.18 -> 14.75 | J17: =H17-I17 -> 485.25
A18: 46159 | B18: Sunday | C18: 1 | D18: 0 and 10% | E18: 900 | F18: 0 | G18: 500 | H18: =SUM(E18:G18) -> 1400 | I18: =H18*2.5%*1.18 -> 41.3 | J18: =H18-I18 -> 1358.7
A19: 46160 | B19: Monday | C19: 0 | D19: 0 and 10% | E19: 0 | F19: 0 | G19: 325 | H19: =SUM(E19:G19) -> 325 | I19: =H19*2.5%*1.18 -> 9.5875 | J19: =H19-I19 -> 315.4125
A20: 46161 | B20: Tuesday | C20: 0.5 | D20: 0 and 10% | E20: 500 | F20: 0 | G20: 150 | H20: =SUM(E20:G20) -> 650 | I20: =H20*2.5%*1.18 -> 19.175 | J20: =H20-I20 -> 630.825
A21: 46162 | B21: Wednesday | C21: 1 | D21: 0 and 10% | E21: 1000 | F21: 0 | G21: 150 | H21: =SUM(E21:G21) -> 1150 | I21: =H21*2.5%*1.18 -> 33.925 | J21: =H21-I21 -> 1116.075
A22: 46163 | B22: Thursday | C22: 1 | D22: 0 and 10% | E22: 900 | F22: 0 | G22: 200 | H22: =sum(E22:G22) -> 1100 | I22: =H22*2.5%*1.18 -> 32.45 | J22: =H22-I22 -> 1067.55
A23: 46164 | B23: Friday | C23: 0 | D23: 0 and 10% | E23: 0 | F23: 0 | G23: 800 | H23: =SUM(E23:G23) -> 800 | I23: =H23*2.5%*1.18 -> 23.6 | J23: =H23-I23 -> 776.4
A24: 46165 | B24: Saturday | C24: 0 | D24: 0 and 10% | E24: 0 | F24: 0 | G24: 200 | H24: =SUM(E24:G24) -> 200 | I24: =H24*2.5%*1.18 -> 5.9 | J24: =H24-I24 -> 194.1
A25: 46166 | B25: Sunday | C25: 0 | D25: 0 and 10% | E25: 0 | F25: 0 | G25: 200 | H25: =SUM(E25:G25) -> 200 | I25: =H25*2.5%*1.18 -> 5.9 | J25: =H25-I25 -> 194.1
A26: 46167 | B26: Monday | C26: 0.5 | D26: 0 and 10% | E26: 500 | F26: 0 | G26: 250 | H26: =SUM(E26:G26) -> 750 | I26: =H26*2.5%*1.18 -> 22.125 | J26: =H26-I26 -> 727.875
A27: 46168 | B27: Tuesday | C27: 0.5 | D27: 0 and 10% | E27: 500 | F27: 0 | G27: 400 | H27: =SUM(E27:G27) -> 900 | I27: =H27*2.5%*1.18 -> 26.55 | J27: =H27-I27 -> 873.45
A28: 46169 | B28: Wednesday | C28: 0.5 | D28: 0 and 10% | E28: 400 | F28: 0 | G28: 0 | H28: =SUM(E28:G28) -> 400 | I28: =H28*2.5%*1.18 -> 11.8 | J28: =H28-I28 -> 388.2
A29: 46170 | B29: Thursday | C29: 0 | D29: 0 and 10% | E29: 0 | F29: 0 | G29: 0 | H29: =SUM(E29:G29) -> 0 | I29: =H29*2.5%*1.18 -> 0 | J29: =H29-I29 -> 0
A30: 46171 | B30: Friday | C30: 0 | D30: 0 and 10% | E30: 0 | F30: 0 | G30: 300 | H30: =SUM(E30:G30) -> 300 | I30: =H30*2.5%*1.18 -> 8.85 | J30: =H30-I30 -> 291.15
A31: 46172 | B31: Saturday | C31: 0 | D31: 0 and 10% | E31: 900 | F31: 0 | G31: 100 | H31: =SUM(E31:G31) -> 1000 | I31: =H31*2.5%*1.18 -> 29.5 | J31: =H31-I31 -> 970.5
A32: 46173 | B32: Sunday | C32: 0 | D32: 0 and 10% | E32: 0 | F32: 0 | G32: 100 | H32: =SUM(E32:G32) -> 100 | I32: =H32*2.5%*1.18 -> 2.95 | J32: =H32-I32 -> 97.05
A33: Total | C33: =SUM(C2:C32) -> 15.5 | E33: =SUM(E2:E32) -> 13000 | F33: =SUM(F2:F32) -> 1800 | G33: =SUM(G2:G32) -> 7720 | H33: =SUM(H2:H32) -> 21620 | I33: =SUM(I2:I32) -> 637.79 | J33: =SUM(J2:J32) -> 20982.21

Sheet District
A1: Link | B1: Date | C1: Paid to District | D1: Commissions (₹) | E1: GST on Commission | F1: Net Revenue | G1: TCS | H1: TDS | I1: Final Amount (₹)
B2: 1 - 31 May | C2: 71921 | D2: 5015 | E2: 902 | F2: =C2-D2-E2 -> 66004 | G2: 417 | H2: 83 | I2: 65501
B4: Total | C4: =SUM(C2:C3) -> 71921 | F4: =SUM(F2:F3) -> 66004 | I4: =SUM(I2:I3) -> 65501

Sheet Hudle
A1: Link | B1: Date | C1: Paid to Hudle | D1: Commisions (Including GST) | E1: Net Revenue | F1: TDS | G1: TCS | H1: Amount
B2: 1 - 31 May | C2: 22954 | D2: 2867 | E2: =C2-D2 -> 20087 | F2: 18.6 | G2: 93 | H2: 19076
B3: Total | C3: =SUM(C2) -> 22954 | E3: =SUM(E2) -> 20087 | H3: =SUM(H2) -> 19076

Sheet Playo
A1: Link | B1: Date | C1: Paid to Playo (₹) | D1: Commissions (₹) | E1: GST (₹) | F1: Net Revenue | G1: TDS (₹) | H1: TCS (₹) | I1: Final Amount (₹)
B2: 1 - 31 May | C2: 1800 | D2: 140 | E2: 25 | F2: =C2-D2-E2 -> 1635 | G2: 9 | H2: 1.8 | I2: 1624
B3: Total | C3: =SUM(C2) -> 1800 | F3: =SUM(F2) -> 1635 | I3: =SUM(I2) -> 1624
