Workbook

Sheet Summary
B2: Date: 1st Oct - 31st Oct
B3: Particulars | C3: Amount
B4: Offline | C4: =SUM(C5,C6,C7,C8, C9) -> 25065
B5: Rentals | C5: ='Offline & RG Community'!F33 -> 6425
B6: F&B | C6: ='Offline & RG Community'!G33 -> 2490
B7: Product Sales | C7: 0
B8: Rallygully Community games | C8: 5200
B9: Bookings | C9: ='Offline & RG Community'!E33-C8 -> 10950
B10: Online: Third Party Platform | C10: =sum(C11,C12,C13,C14,C15) -> 120255
B11: Hudle | C11: =Hudle!C7 -> 96165
B12: Playo | C12: =Playo!C8 -> 17870
B13: District | C13: 0
B14: Khelomore | C14: =Khelomore!C5 -> 4500
B15: Misfits Community | C15: =Misfits!C2 -> 1720
B16: Memberships | C16: =Memberships!E2 -> 50000
B17: Corporate Events | C17: ='Corporate Event'!C2 -> 5400
B18: Brand Activation | C18: =0 -> 0
B19: Other Income | C19: 0
B20: Total Gross Revenue | C20: =sum(C4,C10,C16,C17,C18,C19) -> 200720
B21: Total Net Revenue (Post Commissions) | C21: =SUM(,Hudle!E7,Playo!F8,Khelomore!E5,Misfits!D2,'Corporate Event'!C2,Memberships!E2,'Offline & RG Community'!H33) -> 185600.92
B22: Total Revenue post GST | C22: =C21/1.18 -> 157288.92

Sheet Offline & RG Community
A1: Date | B1: Day | C1: Total Offline (Hours) | D1: Discount Given | E1: Revenue | F1: Paddle Rental | G1: Energy Drinks | H1: Total Revenue
A2: 45931 | B2: Wednesday | C2: 0 | D2: 0.1 | E2: 0 | F2: 375 | G2: 180 | H2: =sum(E2:F2:G2) -> 555
A3: 45932 | B3: Thursday | C3: 0 | D3: 0.1 | E3: 0 | F3: 0 | G3: 0 | H3: =sum(E3:F3:G3) -> 0
A4: 45933 | B4: Friday | C4: 0 | D4: 0.1 | E4: 0 | F4: 300 | G4: 0 | H4: =sum(E4:F4:G4) -> 300
A5: 45934 | B5: Saturday | C5: 0.5 | D5: 0.1 | E5: 360 | F5: 250 | G5: 0 | H5: =sum(E5:F5:G5) -> 610
A6: 45935 | B6: Sunday | C6: 1 | D6: 0.1 | E6: 600 | F6: 450 | G6: 0 | H6: =sum(E6:F6:G6) -> 1050
A7: 45936 | B7: Monday | C7: 0 | D7: 0.1 | E7: 0 | F7: 0 | G7: 0 | H7: 0
A8: 45937 | B8: Tuesday | C8: 0 | D8: 0.1 | E8: 0 | F8: 0 | G8: 0 | H8: 0
A9: 45938 | B9: Wednesday | C9: 0.5 | D9: 0.1 | E9: 360 | F9: 175 | G9: 0 | H9: =sum(E9:F9:G9) -> 535
A10: 45939 | B10: Thursday | C10: 0 | D10: 0.1 | E10: 0 | F10: 0 | G10: 0 | H10: =sum(E10:F10:G10) -> 0
A11: 45940 | B11: Friday | C11: 5 | D11: 0.1 | E11: 2320 | F11: 300 | G11: 0 | H11: =sum(E11:F11:G11) -> 2620
A12: 45941 | B12: Saturday | C12: 1 | D12: 0.1 | E12: 720 | F12: 350 | G12: 0 | H12: =sum(E12:F12:G12) -> 1070
A13: 45942 | B13: Sunday | C13: 1 | D13: 0.1 | E13: 720 | F13: 150 | G13: 0 | H13: =sum(E13:F13:G13) -> 870
A14: 45943 | B14: Monday | C14: 1.5 | D14: 0.1 | E14: 1080 | F14: 300 | G14: 120 | H14: =sum(E14:F14:G14) -> 1500
A15: 45944 | B15: Tuesday | C15: 2 | D15: 0.1 | E15: 1750 | F15: 275 | G15: 180 | H15: =sum(E15:F15:G15) -> 2205
A16: 45945 | B16: Wednesday | C16: 1 | D16: 0.1 | E16: 720 | F16: 300 | G16: 180 | H16: =sum(E16:F16:G16) -> 1200
A17: 45946 | B17: Thursday | C17: 0.5 | D17: 0.1 | E17: 360 | F17: 550 | G17: 300 | H17: =sum(E17:F17:G17) -> 1210
A18: 45947 | B18: Friday | C18: 0 | D18: 0.1 | E18: 0 | F18: 200 | G18: 120 | H18: =sum(E18:F18:G18) -> 320
A19: 45948 | B19: Saturday | C19: 0 | D19: 0.1 | E19: 0 | F19: 225 | G19: 510 | H19: =sum(E19:F19:G19) -> 735
A20: 45949 | B20: Sunday | C20: 3 | D20: 0.1 | E20: 1000 | F20: 50 | G20: 60 | H20: =sum(E20:F20:G20) -> 1110
... A32: 45961 | B32: Friday | C32: 0 | D32: 0.1 | E32: 0 | F32: 100 | G32: 60 | H32: =sum(E32:F32:G32) -> 160
A33: Total | B33: October | C33: =SUM(C2:C32) -> 27 | E33: =SUM(E2:E32) -> 16150 | F33: =SUM(F2:F32) -> 6425 | G33: =SUM(G2:G32) -> 2490 | H33: =SUM(H2:H32) -> 25065

Sheet Hudle
A1: Link | B1: Date | C1: Paid to Hudle | D1: Commisions (Including GST) | E1: Net Revenue | F1: TDS | G1: TCS | H1: Amount
B2: 30 Sep - 7 Oct | C2: 29430 | D2: 3832.4 | E2: =C2-D2 -> 25597.6 | F2: 24.98 | G2: 124.91 | H2: 25491.97
B3: 7 Oct - 14 Oct | C3: 22255 | D3: 2902.9 | E3: =C3-D3 -> 19352.1 | F3: 18.92 | G3: 94.61 | H3: 19313.57
B4: 14 Oct - 21 Oct | C4: 13395 | D4: 1741.35 | E4: =C4-D4 -> 11653.65 | F4: 11.35 | G4: 56.75 | H4: 11585.56
B5: 21 Oct - 28 Oct | C5: 22635 | D5: 2945.8 | E5: =C5-D5 -> 19689.2 | F5: 19.2 | G5: 96.01 | H5: 19599.02
B6: 29 Oct - 31 Oct | C6: 8450 | D6: 1098.5 | E6: =C6-D6 -> 7351.5 | F6: 7.16 | G6: 35.8 | H6: 7308.54
C7: =SUM(C2:C6) -> 96165 | E7: =SUM(E2:E6) -> 83644.05 | H7: =SUM(H2:H6) -> 83298.66

Sheet Playo
A1: Link | B1: Date | C1: Paid to Playo (₹) | D1: Commissions (₹) | E1: GST (₹) | F1: Net Revenue | G1: TDS (₹) | H1: TCS (₹) | I1: Final Amount (₹)
B2: 29 Sep - 30 Sep | C2: 800 | D2: 84 | E2: 15.12 | F2: =C2 - D2-E2 -> 700.88 | G2: 0.8 | H2: 4 | I2: 696.08
B3: 1 Oct - 5 Oct | C3: 5080 | D3: 616 | E3: 110 | F3: =C3 - D3-E3 -> 4354 | G3: 5.08 | H3: 25.4 | I3: 4322.64
B4: 6 Oct - 12 Oct | C4: 5720 | D4: 560 | E4: 100.8 | F4: =C4 - D4-E4 -> 5059.2 | G4: 5.72 | H4: 28.6 | I4: 5024.88
B5: 13 Oct - 19 Oct | C5: 2040 | D5: 154 | E5: 27.72 | F5: =C5 - D5-E5 -> 1858.28 | G5: 2.04 | H5: 10.2 | I5: 1846.04
B6: 20 - 26 Oct | C6: 3430 | D6: 255.5 | E6: 45.99 | F6: =C6 - D6-E6 -> 3128.51 | G6: 3.43 | H6: 17.15 | I6: 3107.93
B7: 27 - 31 Oct | C7: 800 | D7: 60 | F7: =C7 - D7-E7 -> 740
C8: =SUM(C2:C7) -> 17870 | F8: =SUM(F2:F7) -> 15840.87 | I8: =SUM(I2:I6) -> 14997.57

Sheet Khelomore
A1: Link | B1: Date | C1: Paid to Khelomore (₹) | D1: Commissions (₹) | E1: Final Amount (₹)
B2: 30 Sep - 5 Oct | C2: 800 | D2: 40 | E2: 760
B3: 6 Oct - 19 Oct | C3: 2100 | D3: 105 | E3: 1995
B4: 20 Oct - 31 Oct | C4: 1600 | D4: 80 | E4: 1520
C5: =SUM(C2:C4) -> 4500 | E5: =SUM(E2:E4) -> 4275

Sheet Misfits
A1: Link | B1: Date | C1: Paid to Misfits (₹) | D1: Post Comission (20%) | E1: TDS | F1: Final Amount (₹)
B2: October | C2: 1720 | D2: =C2 - (C2 * 20%) -> 1376 | E2: 0.02 | F2: =D2 - D2*E2 -> 1348.48

Sheet Corporate Event
A1: Date & Day | B1: Brand Name | C1: Amount | D1: Timings | E1: Type of collab
A2: 7 Nov & Friday | B2: Scimplify | C2: 5400 | D2: 5-8 PM | E2: 20 People team bonding session

Sheet Memberships
A1: Member Name | B1: Sports Type | C1: Membership Type | D1: Start Date | E1: Amount Collected
A2: October | B2: Sahil Gupta | C2: Pickleball | D2: Grand Slam (90) | E2: 50000
