Workbook

Sheet Summary
B2: Date: 1 - 28 Feb
B3: Particulars | C3: Amount
B4: Offline | C4: =SUM(C5,C6,C7,C8) -> 37220
B5: Rentals | C5: ='Offline & RG Community'!G30 -> 11750
B6: F&B | C6: 0
B7: Product Sales | C7: 0
B8: Bookings | C8: ='Offline & RG Community'!E30 -> 25470
B9: Online: Third Party Platform | C9: =SUM(C10:C13) -> 73780
B10: Hudle | C10: =Hudle!C6 -> 14380
B11: Playo | C11: =Playo!C4 -> 1800
B12: District | C12: =District!C4 -> 57600
B13: Khelomore | C13: 0
B14: Zplys | C14: 0
B15: Community | C15: =SUM(C17,C16, C18,C19) -> 0
B16: Courtly (Organized by RallyGully) | C16: 0
B17: Sportomic (Organized by RallyGully) | C17: 0
B18: Rallygully Community games | C18: ='Offline & RG Community'!F30 -> 0
B19: Misfits Community | C19: 0
B20: Memberships | C20: 0
B21: Corporate Events | C21: ='Corporate Events'!F2 -> 2460
B22: Brand Activation | C22: 0
B23: Other Income | C23: =0 -> 0
B24: Total Gross Revenue | C24: =sum(C4,C9,C15,C20,C21,C22,C23) -> 113460
B25: Total Net Revenue (Post Commissions) | C25: ='Offline & RG Community'!H30 + Hudle!E6 + Playo!F4 + District!F4 + 'Corporate Events'!F2 -> 110603.09
B26: Total Revenue post GST | C26: =C25/1.18 -> 93731.432
B27: Investor's Share (40%) | C27: =C26*40% -> 37492.573

Sheet Offline & RG Community
A1: Date | B1: Day | C1: Offline booking hours | D1: Discount Given | E1: Booking Revenue | F1: Community Revenue | G1: Paddle Rental | H1: Total Revenue
A2: 46054 | B2: Sunday | C2: 3 | D2: 0.2 | E2: 2160 | F2: 0 | G2: 550 | H2: =E2+F2+G2 -> 2710
A3: 46055 | B3: Monday | C3: 0 | D3: 0.2 | E3: 0 | F3: 0 | G3: 0 | H3: =E3+F3+G3 -> 0
A4: 46056 | B4: Tuesday | C4: 1.5 | D4: 0.2 | E4: 1080 | F4: 0 | G4: 600 | H4: =E4+F4+G4 -> 1680
A5: 46057 | B5: Wednesday | C5: 0.5 | D5: 0.2 | E5: 360 | F5: 0 | G5: 200 | H5: =E5+F5+G5 -> 560
A6: 46058 | B6: Thursday | C6: 0 | D6: 0.2 | E6: 0 | F6: 0 | G6: 0 | H6: =E6+F6+G6 -> 0
A7: 46059 | B7: Friday | C7: 0 | D7: 0.2 | E7: 0 | F7: 0 | G7: 0 | H7: =E7+F7+G7 -> 0
A8: 46060 | B8: Saturday | C8: 2.5 | D8: 0.2 | E8: 1305 | F8: 0 | G8: 525 | H8: =E8+F8+G8 -> 1830
A9: 46061 | B9: Sunday | C9: 1.5 | D9: 0.2 | E9: 945 | F9: 0 | G9: 800 | H9: =E9+F9+G9 -> 1745
A10: 46062 | B10: Monday | C10: 2 | D10: 0.2 | E10: 1440 | F10: 0 | G10: 400 | H10: =E10+F10+G10 -> 1840
A11: 46063 | B11: Tuesday | C11: 1.5 | D11: 0.2 | E11: 1170 | F11: 0 | G11: 250 | H11: =E11+F11+G11 -> 1420
A12: 46064 | B12: Wednesday | C12: 1.5 | D12: 0.2 | E12: 945 | F12: 0 | G12: 250 | H12: =E12+F12+G12 -> 1195
A13: 46065 | B13: Thursday | C13: 0 | D13: 0.2 | E13: 0 | F13: 0 | G13: 0 | H13: =E13+F13+G13 -> 0
... A29: 46081 | B29: Saturday | C29: 2 | D29: 0.2 | E29: 1035 | F29: 0 | G29: 1775 | H29: =E29+F29+G29 -> 2810
A30: Total | C30: =SUM(C2:C29) -> 39.5 | E30: =SUM(E2:E29) -> 25470 | F30: =SUM(F2:F29) -> 0 | G30: =SUM(G2:G29) -> 11750 | H30: =SUM(H2:H29) -> 37220

Sheet Hudle
A1: Link | B1: Date | C1: Paid to Hudle | D1: Commisions (Including GST) | E1: Net Revenue | F1: TDS | G1: TCS | H1: Amount
B2: 1 - 9 Feb | C2: 6760 | D2: 878.8 | E2: =C2-D2 -> 5881.2 | F2: 5.72 | G2: 28.64 | H2: 5846.84
B3: 9 - 16 Feb | C3: 3340 | D3: 434.2 | E3: =C3-D3 -> 2905.8 | F3: 2.83 | G3: 14.15 | H3: 2888.82
B4: 16 - 23 Feb | C4: 2480 | D4: 322.4 | E4: =C4-D4 -> 2157.6 | F4: 2.1 | G4: 10.5 | H4: =E4-F4-G4 -> 2145
B5: 23 - 28 Feb | C5: 1800 | D5: 187.2 | E5: =C5-D5 -> 1612.8 | F5: 1.22 | G5: 6.1 | H5: 1245.48
B6: Total | C6: =SUM(C2:C5) -> 14380 | E6: =SUM(E2:E5) -> 12557.4 | H6: =SUM(H2:H5) -> 12126.14

Sheet Playo
A1: Link | B1: Date | C1: Paid to Playo (₹) | D1: Commissions (₹) | E1: GST (₹) | F1: Net Revenue | G1: TDS (₹) | H1: TCS (₹) | I1: Final Amount (₹)
B2: 46061 | C2: 1350 | D2: 189 | E2: 34.02 | F2: =C2-D2-E2 -> 1126.98 | G2: 1.35 | H2: 6.75 | I2: 1118.88
B3: 46064 | C3: 450 | D3: 63 | E3: 11.34 | F3: =C3-D3-E3 -> 375.66 | G3: 0.45 | H3: 2.25 | I3: 372.96
B4: Total | C4: =SUM(C2:C3) -> 1800 | F4: =SUM(F2:F3) -> 1502.64 | I4: =SUM(I2:I3) -> 1491.84

Sheet District
A1: Link | B1: Date | C1: Paid to District | D1: Commissions (₹) | E1: GST on Commission | F1: Net Revenue | G1: TCS | H1: TDS | I1: Final Amount (₹)
B2: 1 - 15 Feb | C2: 22050 | D2: 256.2 | E2: 46.14 | F2: =C2-D2-E2 -> 21747.66 | G2: 64.16 | H2: 12.95 | I2: =F2-G2-H2 -> 21670.55
B3: 16 - 28 Feb | C3: 35550 | D3: 368.3 | E3: 66.31 | F3: =C3-D3-E3 -> 35115.39 | G3: 92.43 | H3: 18.77 | I3: =F3-G3-H3 -> 35004.19
B4: Total | C4: =SUM(C2:C3) -> 57600 | F4: =SUM(F2:F3) -> 56863.05 | I4: =SUM(I2:I3) -> 56674.74

Sheet Corporate Events
A1: Date | B1: Name | C1: Type | D1: Sports Type | E1: Deliverables | F1: Amount Collected
A2: Feb | B2: Anuj | C2: Team Event | D2: Pickleball | E2: 3 hours of Courts | F2: 2460
