Workbook

Sheet Summary
B2: 1 - 30 April
B3: Particulars | C3: Amount
C4: Pickleball
B5: Pay & Play | C5: =sum(C6,C12) -> 179568
B6: Online | C6: =sum(C7:C11) -> 78287
B7: District | C7: 0
B8: Hudle | C8: =Hudle!C4 -> 13450
B9: Playo | C9: =Playo!C4 -> 38962
B10: Khelomore | C10: =Khelomore!C3 -> 25875
B11: Zplys | C11: 0
B12: Offline | C12: =sum(C13:C14) -> 101281
B13: Bookings | C13: ='Offline & RG Community'!E32 -> 101281
B14: Memberships | C14: 0
B15: Community | C15: =sum(C16:C17) -> 3588
B16: Pickup games | C16: 0
B17: Social Events/Tournaments | C17: =Sportomic!C2 -> 3588
B18: Academy | C18: 0
B19: Events & Partnership | C19: =sum(C20,C21) -> 18000
B20: Corporate events | C20: ='Corporate Events'!D2 -> 18000
B21: All B2B partnerships | C21: 0
B22: Commerce | C22: =sum(C23:C25) -> 21525
B23: Product rental | C23: ='Offline & RG Community'!F32 -> 21525
B24: Product sales | C24: 0
B25: F&B | C25: 0
B26: Other Income | C26: ='Other income'!C2 -> 120000
B27: Total Gross Revenue | C27: =sum(C26+C22+C19+C18+C15+C12+C6) -> 342681
B28: Total Net Revenue (Post Commissions) | C28: ='Offline & RG Community'!I32+Hudle!E4+Playo!F4+Khelomore!E3+Sportomic!C2+'Other income'!C2+'Corporate Events'!F2 -> 327604.8
B29: Total Revenue post GST | C29: =C28/1.18 -> 277631.18

Sheet Offline & RG Community
A1: Date | B1: Day | C1: Offline booking hours | D1: Discount | E1: Booking Revenue | F1: Paddle Rental | G1: Total Revenue | H1: Payment Gateway | I1: Net Revenue
A2: 1 Apr | B2: Wednesday | C2: 4 | D2: 10 and 15% | E2: 2475 | F2: 200 | G2: =sum(E2:F2) -> 2675 | H2: =G2*2.5%*1.18 -> 78.9125 | I2: =G2-H2 -> 2596.0875
A3: 2 Apr | B3: Thursday | C3: 1 | D3: 10 and 15% | E3: 471 | F3: 150 | G3: =sum(E3:F3) -> 621 | H3: =G3*2.5%*1.18 -> 18.3195 | I3: =G3-H3 -> 602.6805
A4: 3 Apr | B4: Friday | C4: 7.5 | D4: 10 and 15% | E4: 4665 | F4: 850 | G4: =sum(E4:F4) -> 5515 | H4: =G4*2.5%*1.18 -> 162.6925 | I4: =G4-H4 -> 5352.3075
A5: 4 Apr | B5: Saturday | C5: 2 | D5: 10 and 15% | E5: 1320 | F5: 700 | G5: =sum(E5:F5) -> 2020 | H5: =G5*2.5%*1.18 -> 59.59 | I5: =G5-H5 -> 1960.41
A6: 5 Apr | B6: Sunday | C6: 8.5 | D6: 10 and 15% | E6: 5485 | F6: 2150 | G6: =sum(E6:F6) -> 7635 | H6: =G6*2.5%*1.18 -> 225.2325 | I6: =G6-H6 -> 7409.7675
A7: 6 Apr | B7: Monday | C7: 6 | D7: 10 and 15% | E7: 3750 | F7: 650 | G7: =sum(E7:F7) -> 4400 | H7: =G7*2.5%*1.18 -> 129.8 | I7: =G7-H7 -> 4270.2
A8: 7 Apr | B8: Tuesday | C8: 4.5 | D8: 10 and 15% | E8: 2825 | F8: 400 | G8: =sum(E8:F8) -> 3225 | H8: =G8*2.5%*1.18 -> 95.1375 | I8: =G8-H8 -> 3129.8625
A9: 8 Apr | B9: Wednesday | C9: 7 | D9: 10 and 15% | E9: 4500 | F9: 675 | G9: =sum(E9:F9) -> 5175 | H9: =G9*2.5%*1.18 -> 152.6625 | I9: =G9-H9 -> 5022.3375
A10: 9 Apr | B10: Thursday | C10: 7 | D10: 10 and 15% | E10: 4550 | F10: 1200 | G10: =sum(E10:F10) -> 5750 | H10: =G10*2.5%*1.18 -> 169.625 | I10: =G10-H10 -> 5580.375
A11: 10 Apr | B11: Friday | C11: 9.5 | D11: 10 and 15% | E11: 6150 | F11: 1250 | G11: =sum(E11:F11) -> 7400 | H11: =G11*2.5%*1.18 -> 218.3 | I11: =G11-H11 -> 7181.7
A12: 11 Apr | B12: Saturday | C12: 1 | D12: 10 and 15% | E12: 645 | F12: 700 | G12: =sum(E12:F12) -> 1345 | H12: =G12*2.5%*1.18 -> 39.6775 | I12: =G12-H12 -> 1305.3225
A13: 12 Apr | B13: Sunday | C13: 8 | D13: 10 and 15% | E13: 5380 | F13: 1150 | G13: =sum(E13:F13) -> 6530 | H13: =G13*2.5%*1.18 -> 192.635 | I13: =G13-H13 -> 6337.365
... A16: 15 Apr | B16: Wednesday | C16: 4 | D16: 10 and 15% | E16: 2475 | F16: 700 | G16: =sum(E16:F16) -> 3175 | H16: =G16*2.5%*1.18 -> 93.6625 | I16: =G16-H16 -> 3081.3375
A17: 16 Apr | B17: Thursday | C17: 8.5 | D17: 10 and 15% | E17: 5250 | F17: 575 | G17: =SUM(E17:F17) -> 5825 | H17: =G17*2.5%*1.18 -> 171.8375 | I17: =G17-H17 -> 5653.1625
A18: 17 Apr | B18: Friday | C18: 3 | D18: 10 and 15% | E18: 2025 | F18: 350 | G18: =SUM(E18:F18) -> 2375 | H18: =G18*2.5%*1.18 -> 70.0625 | I18: =G18-H18 -> 2304.9375
A19: 18 Apr | B19: Saturday | C19: 1.5 | D19: 10 and 15% | E19: 975 | F19: 450 | G19: =SUM(E19:F19) -> 1425 | H19: =G19*2.5%*1.18 -> 42.0375 | I19: =G19-H19 -> 1382.9625
A20: 19 Apr | B20: Sunday | C20: 3 | D20: 10 and 15% | E20: 2040 | F20: 775 | G20: =SUM(E20:F20) -> 2815 | H20: =G20*2.5%*1.18 -> 83.0425 | I20: =G20-H20 -> 2731.9575
A21: 20 Apr | B21: Monday | C21: 7 | D21: 10 and 15% | E21: 4725 | F21: 500 | G21: =SUM(E21:F21) -> 5225 | H21: =G21*2.5%*1.18 -> 154.1375 | I21: =G21-H21 -> 5070.8625
A22: 21 Apr | B22: Tuesday | C22: 7 | D22: 10 and 15% | E22: 4350 | F22: 650 | G22: =SUM(F22) -> 650 | H22: =G22*2.5%*1.18 -> 19.175 | I22: =G22-H22 -> 630.825
A23: 22 Apr | B23: Wednesday | C23: 6.5 | D23: 10 and 15% | E23: 4290 | F23: 650 | G23: =sum(E23:F23) -> 4940 | H23: =G23*2.5%*1.18 -> 145.73 | I23: =G23-H23 -> 4794.27
A24: 23 Apr | B24: Thursday | C24: 8.5 | D24: 10 and 15% | E24: 5250 | F24: 0 | G24: =SUM(E24:F24) -> 5250 | H24: =G24*2.5%*1.18 -> 154.875 | I24: =G24-H24 -> 5095.125
A25: 24 Apr | B25: Friday | C25: 0 | D25: 10 and 15% | E25: 0 | F25: 100 | G25: =SUM(E25:F25) -> 100 | H25: =G25*2.5%*1.18 -> 2.95 | I25: =G25-H25 -> 97.05
A26: 25 Apr | B26: Saturday | C26: 8 | D26: 10 and 15% | E26: 5315 | F26: 2075 | G26: =SUM(E26:F26) -> 7390 | H26: =G26*2.5%*1.18 -> 218.005 | I26: =G26-H26 -> 7171.995
A27: 26 Apr | B27: Sunday | C27: 7 | D27: 10 and 15% | E27: 4545 | F27: 975 | G27: =SUM(E27:F27) -> 5520 | H27: =G27*2.5%*1.18 -> 162.84 | I27: =G27-H27 -> 5357.16
A28: 27 Apr | B28: Monday | C28: 5 | D28: 10 and 15% | E28: 3300 | F28: 425 | G28: =SUM(E28:F28) -> 3725 | H28: =G28*2.5%*1.18 -> 109.8875 | I28: =G28-H28 -> 3615.1125
A29: 28 Apr | B29: Tuesday | C29: 1.5 | D29: 10 and 15% | E29: 975 | F29: 600 | G29: =SUM(E29:F29) -> 1575 | H29: =G29*2.5%*1.18 -> 46.4625 | I29: =G29-H29 -> 1528.5375
A30: 29 Apr | B30: Wednesday | C30: 1.5 | D30: 10 and 15% | E30: 975 | F30: 575 | G30: =SUM(E30:F30) -> 1550 | H30: =G30*2.5%*1.18 -> 45.725 | I30: =G30-H30 -> 1504.275
A31: 30 Apr | B31: Thursday | C31: 6.5 | D31: 10 and 15% | E31: 4325 | F31: 775 | G31: =SUM(E31:F31) -> 5100 | H31: =G31*2.5%*1.18 -> 150.45 | I31: =G31-H31 -> 4949.55
A32: Total | C32: =SUM(C2:C31) -> 157 | E32: =SUM(E2:E31) -> 101281 | F32: =SUM(F2:F31) -> 21525 | G32: =SUM(G2:G31) -> 118456 | H32: =SUM(H2:H31) -> 3494.452 | I32: =SUM(I2:I31) -> 114961.55

Sheet Hudle
A1: Link | B1: Date | C1: Paid to Hudle | D1: Commisions (Including GST) | E1: Net Revenue | F1: TDS | G1: TCS | H1: Amount
B2: 1-28 Apr | C2: 10500 | D2: 1432 | E2: =C2-D2 -> 9068 | F2: 9 | G2: 46 | H2: 9531
B3: 28-30 Apr | C3: 2950 | D3: 383 | E3: =C3-D3 -> 2567 | F3: 2.5 | G3: 12.5 | H3: 2551
B4: Total | C4: =SUM(C2:C3) -> 13450 | E4: =SUM(E2:E3) -> 11635 | H4: =SUM(H2:H3) -> 12082

Sheet Playo
A1: Link | B1: Date | C1: Paid to Playo (₹) | D1: Commissions (₹) | E1: GST (₹) | F1: Net Revenue | G1: TDS (₹) | H1: TCS (₹) | I1: Final Amount (₹)
B2: 1-26 Apr | C2: 32775 | D2: 2572 | E2: 463 | F2: =C2-D2-E2 -> 29740 | G2: 33 | H2: 0 | I2: 29706
B3: 27-30 Apr | C3: 6187 | D3: 472 | E3: 85 | F3: =C3-D3-E3 -> 5630 | G3: 6 | H3: 0 | I3: 5623
B4: Total | C4: =SUM(C2,C3) -> 38962 | F4: =SUM(F2,F3) -> 35370 | I4: =SUM(I2,I3) -> 35329

Sheet Khelomore
A1: Link | B1: Date | C1: Paid to Khelomore (₹) | D1: Commissions (₹) | E1: Final Amount (₹)
B2: 1 - 30th Apr | C2: 25875 | D2: =C2*5% -> 1293.75 | E2: =C2-D2 -> 24581.25
B3: Total | C3: =SUM(C2) -> 25875 | E3: =SUM(E2) -> 24581.25

Sheet Sportomic
A1: Link | B1: Date | C1: Paid to Sportomic (₹)
B2: 1 -30 Apr | C2: 3588

Sheet Other income
A1: Month | B1: Sports Type | C1: Amount Collected
A2: Apr | B2: Football Management Operations | C2: 120000

Sheet Corporate Events
A1: Name | B1: Date | C1: Sport | D1: Amt | E1: Payment Gateway | F1: Net Revenue
A2: Life School | B2: 46119 | C2: Pickleball | D2: 18000 | E2: =D2*2.5%*1.18 -> 531 | F2: =D2-E2 -> 17469
