Workbook

Sheet Summary
B2: 1 - 31 Aug
B3: Particulars | C3: Amount
C4: Total | D4: Pickleball | E4: Turf
B5: Pay & Play | C5: =sum(C6,C12) -> 206637 | D5: =sum(D6,D12) -> 105423 | E5: =sum(E6,E12) -> 91814
B6: Online | C6: =sum(C7:C11) -> 61103 | D6: =sum(D7:D11) -> 38123 | E6: =sum(E7:E11) -> 22980
B7: District | C7: =District!C3 -> 61103 | D7: =District!B5 -> 38123 | E7: =District!B6 -> 22980
B8: Hudle | C8: 0 | D8: 0 | E8: 0
B9: Playo | C9: 0 | D9: 0 | E9: 0
B10: Khelomore | C10: 0 | D10: 0 | E10: 0
B11: Zplys | C11: 0 | D11: 0 | E11: 0
B12: Offline | C12: =sum(C13:C14) -> 145534 | D12: =sum(D13:D14) -> 67300 | E12: =sum(E13:E14) -> 68834
B13: Bookings | C13: ='Offline & RG Community'!D33+'Offline & RG Community'!E33 -> 102734 | D13: ='Offline & RG Community'!D33 -> 55300 | E13: ='Offline & RG Community'!E33 -> 47434
B14: Memberships | C14: =Memberships!D5 -> 42800 | D14: =Memberships!D3 -> 12000 | E14: =Memberships!D4/2+Memberships!D2 -> 21400
B15: Community | C15: =sum(C16:C18) -> 450 | D15: =sum(D16:D18) -> 450 | E15: =sum(E16:E18) -> 0
B16: Pickup games | C16: ='Offline & RG Community'!F33 -> 450 | D16: ='Offline & RG Community'!F33 -> 450 | E16: 0
B17: Social Events/Tournaments | C17: 0 | D17: 0 | E17: 0
B18: Community Partnerships | C18: 0 | D18: 0 | E18: 0
B19: Academy | C19: 0 | D19: 0 | E19: 0
B20: Events & Partnership | C20: =sum(C21,C22) -> 2560 | D20: =sum(D21,D22) -> 0 | E20: =sum(E21,E22) -> 2560
B21: Corporate events | C21: ='Corporate Events'!F2 -> 2560 | D21: 0 | E21: ='Corporate Events'!F2 -> 2560
B22: All B2B partnerships | C22: 0 | D22: 0 | E22: 0
B23: Commerce | C23: =sum(C24:C26) -> 200 | D23: =sum(D24:D26) -> 200 | E23: =sum(E24:E26) -> 0
B24: Product rental | C24: ='Offline & RG Community'!G33 -> 200 | D24: ='Offline & RG Community'!G33 -> 200 | E24: 0
B25: Product sales | C25: 0 | D25: 0 | E25: 0
B26: F&B | C26: 0 | D26: 0 | E26: 0
B27: Other Income | C27: 0 | D27: 0 | E27: 0
B28: Total Gross Revenue | C28: =C6+C12+C15+C19+C20+C23+C27 -> 209847 | D28: =D6+D12+D15+D19+D20+D23+D27 -> 106073 | E28: =E6+E12+E15+E19+E20+E23+E27 -> 94374
B29: GST (B) | C29: =C28-(C28/1.18) -> 32010.559
B30: Commissions, Payment gateway & Event Expense(C) | C30: ='Offline & RG Community'!I33+District!D3+District!E3+Memberships!E5+'Corporate Events'!G2 -> 7359.02
B31: Net Revenue (A-B-C) | C31: =C28-C29-C30 -> 170477.42

Sheet Offline & RG Community
A1: Date | B1: Day | C1: Offline booking hours | D1: Booking Revenue | E1: Booking Revenue (Turf) | F1: Community Revenue | G1: Paddle Rental | H1: Total Revenue | I1: Payment Gateway | J1: Net Revenue
A2: 46235 | B2: Saturday | C2: 7.5 | D2: 4540 | E2: 3400 | F2: 0 | G2: 0 | H2: =sum(D2:G2) -> 7940 | I2: =H2*1.75% -> 138.95 | J2: =H2-I2 -> 7801.05
A3: 46236 | B3: Sunday | C3: 6 | D3: 1825 | E3: 3600 | F3: 0 | G3: 0 | H3: =sum(D3:G3) -> 5425 | I3: =H3*1.75% -> 94.9375 | J3: =H3-I3 -> 5330.0625
A4: 46237 | B4: Monday | C4: 3 | D4: 1925 | E4: 0 | F4: 0 | G4: 0 | H4: =sum(D4:G4) -> 1925 | I4: =H4*1.75% -> 33.6875 | J4: =H4-I4 -> 1891.3125
A5: 46238 | B5: Tuesday | C5: 3 | D5: 1285 | E5: 1200 | F5: 0 | G5: 0 | H5: =sum(D5:G5) -> 2485 | I5: =H5*1.75% -> 43.4875 | J5: =H5-I5 -> 2441.5125
A6: 46239 | B6: Wednesday | C6: 1.5 | D6: 1040 | E6: 0 | F6: 0 | G6: 0 | H6: =sum(D6:G6) -> 1040 | I6: =H6*1.75% -> 18.2 | J6: =H6-I6 -> 1021.8
A7: 46240 | B7: Thursday | C7: 1 | D7: 640 | E7: 0 | F7: 0 | G7: 0 | H7: =sum(D7:G7) -> 640 | I7: =H7*1.75% -> 11.2 | J7: =H7-I7 -> 628.8
A8: 46241 | B8: Friday | C8: 0 | D8: 0 | E8: 0 | F8: 0 | G8: 0 | H8: =sum(D8:G8) -> 0 | I8: =H8*1.75% -> 0 | J8: =H8-I8 -> 0
A9: 46242 | B9: Saturday | C9: 7 | D9: 3230 | E9: 2800 | F9: 0 | G9: 0 | H9: =sum(D9:G9) -> 6030 | I9: =H9*1.75% -> 105.525 | J9: =H9-I9 -> 5924.475
A10: 46243 | B10: Sunday | C10: 6.5 | D10: 3250 | E10: 2396 | F10: 450 | G10: 0 | H10: =sum(D10:G10) -> 6096 | I10: =H10*1.75% -> 106.68 | J10: =H10-I10 -> 5989.32
A11: 46244 | B11: Monday | C11: 1.5 | D11: 1075 | E11: 0 | F11: 0 | G11: 0 | H11: =sum(D11:G11) -> 1075 | I11: =H11*1.75% -> 18.8125 | J11: =H11-I11 -> 1056.1875
A12: 46245 | B12: Tuesday | C12: 6 | D12: 3050 | E12: 3600 | F12: 0 | G12: 0 | H12: =sum(D12:G12) -> 6650 | I12: =H12*1.75% -> 116.375 | J12: =H12-I12 -> 6533.625
A13: 46246 | B13: Wednesday | C13: 3 | D13: 1950 | E13: 0 | F13: 0 | G13: 0 | H13: =sum(D13:G13) -> 1950 | I13: =H13*1.75% -> 34.125 | J13: =H13-I13 -> 1915.875
... A32: 46265 | B32: Monday | C32: 0 | D32: 0 | E32: 0 | F32: 0 | G32: 0 | H32: =sum(D32:G32) -> 0 | I32: =H32*1.75% -> 0 | J32: =H32-I32 -> 0
A33: Total | D33: =SUM(D2:D32) -> 55300 | E33: =SUM(E2:E32) -> 47434 | F33: =SUM(F2:F32) -> 450 | G33: =SUM(G2:G32) -> 200 | H33: =SUM(H2:H32) -> 103384 | I33: =SUM(I2:I32) -> 1809.22 | J33: =SUM(J2:J32) -> 101574.78

Sheet District
A1: Link | B1: Date | C1: Paid to District | D1: Commissions (₹) | E1: GST on Commission | F1: Net Revenue | G1: TCS | H1: TDS | I1: Final Amount (₹)
B2: 1 - 31 Aug | C2: 61103 | D2: 4310 | E2: 775 | F2: =C2-D2-E2 -> 56018 | G2: 308 | H2: 61 | I2: =F2-G2-H2 -> 55649
B3: Total | C3: =SUM(C2) -> 61103 | D3: =SUM(D2) -> 4310 | E3: =SUM(E2) -> 775 | F3: =SUM(F2) -> 56018 | I3: =SUM(I2) -> 55649
A5: Pickleball | B5: 38123
A6: Turf | B6: =C3-B5 -> 22980

Sheet Memberships
A1: Member Name | B1: Sports Type | C1: Membership Type | D1: Amount Collected | E1: Payment Gateway | F1: Net Revenue
A2: Sumit | B2: Box Cricket | C2: 10 Hours | D2: 12000 | E2: =D2*1.75% -> 210 | F2: =D2-E2 -> 11790
A3: Amit | B3: Pickleball | C3: 30 Hours | D3: 12000 | E3: =D3*1.75% -> 210 | F3: =D3-E3 -> 11790
A4: ISH | B4: Turf and Pickleball | C4: Custom | D4: 18800 | E4: 0 | F4: =D4-E4 -> 18800
A5: Total | D5: =SUM(D2:D4) -> 42800 | E5: =SUM(E2:E4) -> 420 | F5: =SUM(F2:F4) -> 42380

Sheet Corporate Events
A1: Start Month | B1: Partnership Type | C1: Name of Brand/Person | D1: Deliverables | E1: Venue | F1: Amount (₹) | G1: Payment Gateway | H1: Net Revenue
A2: July | B2: Team Event | C2: Bio Gas KLJ | D2: 2 hours of Turf | E2: Sec 83 | F2: 2560 | G2: =F2*1.75% -> 44.8 | H2: =F2-G2 -> 2515.2
