Workbook

Sheet Summary
B2: Date: 1st - 31st Dec
B3: Particulars | C3: Amount
B4: Offline | C4: =SUM(C5,C6,C7,C8) -> 79990
B5: Rentals | C5: ='Offline & RG Community'!G33 -> 7725
B6: F&B | C6: 0
B7: Product Sales | C7: =0 -> 0
B8: Bookings | C8: ='Offline & RG Community'!E33 -> 72265
B9: Online: Third Party Platform | C9: =SUM(C10:C13) -> 39150
B10: Hudle | C10: =Hudle!C7 -> 34800
B11: Playo | C11: =Playo!C7 -> 2050
B12: District | C12: =District!C4 -> 2300
B13: Khelomore | C13: =Khelomore!C4 -> 0
B14: Community | C14: =sum(C16:C18) -> 1500
B15: Courtly | C15: 0
B16: Sportomic | C16: =Sportomic!C2 -> 320
B17: Rallygully Community games | C17: ='Offline & RG Community'!F33 -> 360
B18: Misfits Community | C18: =Misfits!C2 -> 820
B19: Memberships | C19: =Membership!E5 -> 29660
B20: Corporate Events | C20: ='Corporate Events'!E4 -> 20680
B21: Brand Activation | C21: 0
B22: Other Income | C22: 0
B23: Total Gross Revenue | C23: =sum(C21,C22,C20, C19,C14,C9,C4) -> 170980
B24: Total Net Revenue (Post Commissions) | C24: ='Offline & RG Community'!H33 + Hudle!E7 +Playo!F7 +District!F4 + Misfits!F3 +Sportomic!D2 +Membership!E5 +'Corporate Events'!E4 -> 165970.3
B25: Total Revenue post GST | C25: =C24/1.18 -> 140652.8

Sheet Offline & RG Community
A1: Date | B1: Day | C1: Offline booking hours | D1: Discount Given | E1: Booking Revenue | F1: Community Revenue | G1: Paddle Rental | H1: Total Revenue
A2: 45992 | B2: Monday | C2: 0 | D2: 25% B, 25% P | E2: 0 | F2: 0 | G2: 0 | H2: =sum(E2:G2) -> 0
A3: 45993 | B3: Tuesday | C3: 1 | D3: 25% B, 25% P | E3: 560 | F3: 0 | G3: 100 | H3: =sum(E3:G3) -> 660
A4: 45994 | B4: Wednesday | C4: 2.5 | D4: 25% B, 25% P | E4: 1400 | F4: 0 | G4: 300 | H4: =sum(E4:G4) -> 1700
A5: 45995 | B5: Thursday | C5: 4 | D5: 25% B, 25% P | E5: 2980 | F5: 0 | G5: 200 | H5: =sum(E5:G5) -> 3180
A6: 45996 | B6: Friday | C6: 4 | D6: 25% B, 25% P | E6: 3000 | F6: 0 | G6: 275 | H6: =sum(E6:G6) -> 3275
A7: 45997 | B7: Saturday | C7: 3.5 | D7: 25% B, 25% P | E7: 3280 | F7: 0 | G7: 450 | H7: =sum(E7:G7) -> 3730
A8: 45998 | B8: Sunday | C8: 0.5 | D8: 25% B, 25% P | E8: 300 | F8: 160 | G8: 200 | H8: =sum(E8:G8) -> 660
A9: 45999 | B9: Monday | C9: 6 | D9: 25% B, 25% P | E9: 2700 | F9: 0 | G9: 350 | H9: =sum(E9:G9) -> 3050
A10: 46000 | B10: Tuesday | C10: 3.5 | D10: 25% B, 25% P | E10: 2100 | F10: 0 | G10: 100 | H10: =sum(E10:G10) -> 2200
A11: 46001 | B11: Wednesday | C11: 0 | D11: 25% B, 25% P | E11: 0 | F11: 0 | G11: 0 | H11: =sum(E11:G11) -> 0
A12: 46002 | B12: Thursday | C12: 4.5 | D12: 25% B, 25% P | E12: 3900 | F12: 0 | G12: 400 | H12: =sum(E12:G12) -> 4300
A13: 46003 | B13: Friday | C13: 3 | D13: 25% B, 25% P | E13: 2600 | F13: 0 | G13: 300 | H13: =sum(E13:G13) -> 2900
... A32: 46022 | B32: Wednesday | C32: 2 | D32: 25% B, 50% P | E32: 1800 | F32: 0 | G32: 150 | H32: =sum(E32:G32) -> 1950
A33: Total | C33: =SUM(C2:C32) -> 105.5 | E33: =SUM(E2:E32) -> 72265 | F33: =SUM(F2:F32) -> 360 | G33: =SUM(G2:G32) -> 7725 | H33: =SUM(H2:H32) -> 80350

Sheet Hudle
A1: Link | B1: Date | C1: Paid to Hudle | D1: Commisions (Including GST) | E1: Net Revenue | F1: TDS | G1: TCS | H1: Amount
B2: 1 - 8 Dec | C2: 7550 | D2: 988 | E2: =C2-D2 -> 6562 | F2: 6.44 | G2: 32.3 | H2: 6573.37
B3: 9 - 16 Dec | C3: 8000 | D3: 1040 | E3: =C3-D3 -> 6960 | F3: 6.77 | G3: 33.8 | H3: 6919.33
B4: 16 - 23 Dec | C4: 6900 | D4: 897 | E4: =C4-D4 -> 6003 | F4: 5.84 | G4: 29.23 | H4: 5967.92
B5: 23 - 31 Dec | C5: 12350 | D5: 1605.5 | E5: =C5-D5 -> 10744.5 | F5: 10.4 | G5: 52.33 | H5: 10681.73
C7: =SUM(C2:C5) -> 34800 | E7: =SUM(E2:E6) -> 30269.5 | H7: =SUM(H2:H6) -> 30142.35

Sheet Playo
A1: Link | B1: Date | C1: Paid to Playo (₹) | D1: Commissions (₹) | E1: GST (₹) | F1: Net Revenue | G1: TDS (₹) | H1: TCS (₹) | I1: Final Amount (₹)
B2: 1 - 15 Dec | C2: 1050 | D2: 98 | E2: 17.64 | F2: =C2-D2-E2 -> 934.36 | G2: 1.05 | H2: 5.25 | I2: 928.06
B3: 15 - 31 Dec | C3: 1000 | D3: 112 | E3: 20.16 | F3: =C3-D3-E3 -> 867.84 | G3: 0.24 | H3: 1.2 | I3: 106.4
C7: =SUM(C2:C5) -> 2050 | F7: =SUM(F2:F6) -> 1802.2 | I7: =SUM(I2:I5) -> 1034.46

Sheet District
A1: Link | B1: Date | C1: Paid to District | D1: Commissions (₹) | E1: GST on Commission | F1: Net Revenue | G1: TCS | H1: TDS | I1: Final Amount (₹)
B2: 1 - 31 Dec | C2: 2300 | D2: 46 | E2: 8.28 | F2: =C2 -D2-E2 -> 2245.72 | G2: 11.5 | H2: 2.3 | I2: 2235.92
B4: Total | C4: =SUM(C2) -> 2300 | F4: =SUM(F2) -> 2245.72 | I4: =SUM(I2) -> 2235.92

Sheet Khelomore
A1: Link | B1: Date | C1: Paid to Khelomore (₹) | D1: Commissions (₹) | E1: Final Amount (₹)
B2: 1 - 31 Dec | C2: 0
C4: =SUM(C2:C3) -> 0 | E4: =SUM(E2:E3) -> 0

Sheet Misfits
A1: Link | B1: Date | C1: Paid to Misfits (₹) | D1: Post Comission (20%) | E1: TDS | F1: Final Amount (₹)
B2: 1 - 31 Dec | C2: 820 | D2: 164 | E2: 13.12 | F2: =C2-D2-E2 -> 642.88
B3: Total | F3: =SUM(F2) -> 642.88

Sheet Sportomic
A1: Link | B1: Date | C1: Paid to Sportomic (₹) | D1: Final Amount (₹)
B2: 45998 | C2: 320 | D2: 320

Sheet Membership
A1: Member Name | B1: Sports Type | C1: Membership Type | D1: Start Date | E1: Amount Collected
A2: Indian School of hospitality | B2: Pickle & Box | C2: Collab | D2: 45992 | E2: 14160
A3: Sunil | B3: Box Cricket | C3: Custom | D3: 46005 | E3: 10000
A4: Arshdeep | B4: Pickleball | C4: Rally Pack (15) | D4: 45996 | E4: 5500
A5: Total | E5: =SUM(E2:E4) -> 29660

Sheet Brand Activation
A1: Date & Day | B1: Brand Name | C1: Amount | D1: Timings | E1: Type of collab

Sheet Corporate Events
A1: Date | B1: Type | C1: Sports Type | D1: Deliverables | E1: Amount Collected
A2: 46001 | B2: Team Event | C2: Pickleball | D2: Reel, Linkedin | E2: 5000
A3: 46011 | B3: Team Event | C3: Box Cricket | D3: Only Space | E3: 15680
A4: Total | E4: =SUM(E2:E3) -> 20680
