Workbook

Sheet Summary
B2: Date: 1st Oct - 31st Oct
B3: Particulars | C3: Amount
B4: Offline | C4: =SUM(C5,C6,C7,C8, C9) -> 39280
B5: Rentals | C5: ='Offline & RG Community'!F33 -> 6330
B6: F&B | C6: 0
B7: Product Sales | C7: 0
B8: Rallygully Community games | C8: 3250
B9: Bookings | C9: ='Offline & RG Community'!E33-C8 -> 29700
B10: Online: Third Party Platform | C10: =SUM(C11:C15) -> 21915
B11: Hudle | C11: =Hudle!C7 -> 13485
B12: Playo | C12: =Playo!C7 -> 5000
B13: District | C13: 0
B14: Khelomore | C14: =Khelomore!C4 -> 600
B15: Misfits Community | C15: =Misfits!C2 -> 2830
B16: Memberships | C16: =Membership!E4 -> 28880
B17: Corporate Events | C17: 0
B18: Brand Activation | C18: 0
B19: Other Income | C19: 0
B20: Total Gross Revenue | C20: =SUM(C4,C10,C16,C17,C18:C19) -> 90075
B21: Total Net Revenue (Post Commissions) | C21: =SUM('Offline & RG Community'!G33,Hudle!E7,Playo!F7,Khelomore!E4,Misfits!D2,Membership!E4) -> 86953.3
B22: Total Revenue post GST | C22: =C21/1.18 -> 73689.237

Sheet Offline & RG Community
A1: Date | B1: Day | C1: Total Offline (Hours) P + B | D1: Discount Given | E1: Revenue (₹) | F1: Paddle Rental | G1: Total (₹)
A2: 45931 | B2: Wednesday | C2: 0 | D2: 25% B, 40% P | E2: 0 | F2: 0 | G2: =sum(E2:F2) -> 0
A3: 45932 | B3: Thursday | C3: 1 | D3: 25% B, 40% P | E3: 480 | F3: 500 | G3: =sum(E3:F3) -> 980
A4: 45933 | B4: Friday | C4: 2 | D4: 25% B, 40% P | E4: 1440 | F4: 350 | G4: =sum(E4:F4) -> 1790
A5: 45934 | B5: Saturday | C5: 0 | D5: 25% B, 40% P | E5: 0 | F5: 500 | G5: =sum(E5:F5) -> 500
A6: 45935 | B6: Sunday | C6: 3 | D6: 25% B, 40% P | E6: 1440 | F6: 400 | G6: =sum(E6:F6) -> 1840
A7: 45936 | B7: Monday | C7: 0.5 | D7: 25% B, 40% P | E7: 240 | F7: 200 | G7: =sum(E7:F7) -> 440
A8: 45937 | B8: Tuesday | C8: 0 | D8: 25% B, 40% P | E8: 0 | F8: 0 | G8: =sum(E8:F8) -> 0
A9: 45938 | B9: Wednesday | C9: 0 | D9: 25% B, 40% P | E9: 0 | F9: 0 | G9: 0
A10: 45939 | B10: Thursday | C10: 0.5 | D10: 25% B, 40% P | E10: 240 | F10: 200 | G10: =sum(E10:F10) -> 440
A11: 45940 | B11: Friday | C11: 2 | D11: 25% B, 30% P | E11: 1120 | F11: 280 | G11: =sum(E11:F11) -> 1400
A12: 45941 | B12: Saturday | C12: 2.5 | D12: 25% B, 30% P | E12: 1410 | F12: 300 | G12: =sum(E12:F12) -> 1710
A13: 45942 | B13: Sunday | C13: 3.75 | D13: 25% B, 30% P | E13: 3000 | G13: =sum(E13:F13) -> 3000
A14: 45943 | B14: Monday | C14: 5 | D14: 25% B, 30% P | E14: 4400 | F14: 400 | G14: =sum(E14:F14) -> 4800
A15: 45944 | B15: Tuesday | C15: 0 | D15: 25% B, 30% P | E15: 0 | F15: 0 | G15: =sum(E15:F15) -> 0
A16: 45945 | B16: Wednesday | C16: 1 | D16: 25% B, 30% P | E16: 560 | F16: 150 | G16: =sum(E16:F16) -> 710
A17: 45946 | B17: Thursday | C17: 1 | D17: 25% B, 30% P | E17: 560 | F17: 150 | G17: =sum(E17:F17) -> 710
A18: 45947 | B18: Friday | C18: 2 | D18: 25% B, 30% P | E18: 1120 | F18: 150 | G18: =sum(E18:F18) -> 1270
A19: 45948 | B19: Saturday | C19: 1 | D19: 25% B, 30% P | E19: 570 | F19: 0 | G19: =sum(E19:F19) -> 570
A20: 45949 | B20: Sunday | C20: 2 | D20: 25% B, 30% P | E20: 1100 | F20: 100 | G20: =sum(E20:F20) -> 1200
A21: 45950 | B21: Monday | C21: 0 | D21: 25% B, 30% P | E21: 0 | F21: 0 | G21: 0
A22: 45951 | B22: Tuesday | C22: 5 | D22: 25% B, 30% P | E22: 4080 | F22: 400 | G22: =sum(E22:F22) -> 4480
A23: 45952 | B23: Wednesday | C23: 2 | D23: 25% B, 30% P | E23: 1760 | F23: 250 | G23: =sum(E23:F23) -> 2010
A24: 45953 | B24: Thursday | C24: 2 | D24: 25% B, 30% P | E24: 1120 | F24: 200 | G24: =sum(E24:F24) -> 1320
A25: 45954 | B25: Friday | C25: 0.5 | D25: 25% B, 30% P | E25: 280 | F25: 100 | G25: =sum(E25:F25) -> 380
A26: 45955 | B26: Saturday | C26: 2 | D26: 25% B, 30% P | E26: 1610 | F26: 0 | G26: =sum(E26:F26) -> 1610
A27: 45956 | B27: Sunday | C27: 1 | D27: 25% B, 30% P | E27: 1200 | F27: 300 | G27: =sum(E27:F27) -> 1500
A28: 45957 | B28: Monday | C28: 1.5 | D28: 25% B, 30% P | E28: 960 | F28: 200 | G28: =sum(E28:F28) -> 1160
A29: 45958 | B29: Tuesday | C29: 0.5 | D29: 25% B, 30% P | E29: 280 | F29: 200 | G29: =sum(E29:F29) -> 480
A30: 45959 | B30: Wednesday | C30: 2 | D30: 25% B, 30% P | E30: 1250 | F30: 100 | G30: =sum(E30:F30) -> 1350
A31: 45960 | B31: Thursday | C31: 2 | D31: 25% B, 30% P | E31: 1120 | F31: 250 | G31: =sum(E31:F31) -> 1370
A32: 45961 | B32: Friday | C32: 3.5 | D32: 25% B, 30% P | E32: 1610 | F32: 650 | G32: =sum(E32:F32) -> 2260
A33: Total | B33: October | C33: =SUM(C2:C32) -> 49.25 | E33: =SUM(E2:E32) -> 32950 | F33: =SUM(F2:F32) -> 6330 | G33: =SUM(G2:G32) -> 39280

Sheet Hudle
A1: Link | B1: Date | C1: Paid to Hudle | D1: Commisions (Including GST) | E1: Net Revenue | F1: TDS | G1: TCS | H1: Amount
B2: 30 Sep - 7 Oct | C2: 3335 | D2: 436.8 | E2: =C2-D2 -> 2898.2 | F2: 2.84 | G2: 14.32 | H2: 2905.84
B3: 7 Oct - 14 Oct | C3: 2000 | D3: 260 | E3: =C3-D3 -> 1740 | F3: 1.69 | G3: 8.47 | H3: 1729.83
B4: 14 Oct - 21 Oct | C4: 960 | D4: 124.8 | E4: =C4-D4 -> 835.2 | F4: 0.81 | G4: 4.06 | H4: 830.32
B5: 21 Oct - 28 Oct | C5: 6630 | D5: 887.9 | E5: =C5-D5 -> 5742.1 | F5: 5.78 | G5: 28.94 | H5: 5907.37
B6: 29 Oct - 31 Oct | C6: 560 | D6: 72.8 | E6: =C6-D6 -> 487.2 | F6: 0.47 | G6: 2.37 | H6: 484.32
C7: =SUM(C2:C6) -> 13485 | E7: =SUM(E2:E6) -> 11702.7 | H7: =SUM(H2:H6) -> 11857.68

Sheet Playo
A1: Link | B1: Date | C1: Paid to Playo (₹) | D1: Commissions (₹) | E1: GST (₹) | F1: Net Revenue | G1: TDS (₹) | H1: TCS (₹) | I1: Final Amount (₹)
B2: 29 Sep - 30 Sep | C2: 1320 | D2: 154 | E2: 27.72 | F2: =C2 - D2-E2 -> 1138.28 | G2: 1.32 | H2: 6.6 | I2: 1130.36
B3: 1 Oct - 5 Oct | C3: 720 | D3: 168 | E3: 30.24 | F3: =C3 - D3-E3 -> 521.76 | G3: 0.2 | H3: 3.6 | I3: 517.44
B4: 6 Oct - 12 Oct | C4: 1280 | D4: 140 | E4: 25.2 | F4: =C4 - D4-E4 -> 1114.8 | G4: 1.28 | H4: 6.4 | I4: 1107.12
B5: 13 Oct - 19 Oct | C5: 1680 | D5: 168 | E5: 30.24 | F5: =C5 - D5-E5 -> 1481.76 | G5: 1.68 | H5: 8.4 | I5: 1471.68
B6: 20 Oct - 26 Oct | C6: 0 | D6: 0 | E6: 0 | H6: 0 | I6: 0
C7: =SUM(C2:C5) -> 5000 | F7: =SUM(F2:F6) -> 4256.6 | I7: =SUM(I2:I5) -> 4226.6

Sheet Khelomore
A1: Link | B1: Date | C1: Paid to Khelomore (₹) | D1: Commissions (₹) | E1: Final Amount (₹)
B2: 13 Oct - 19 Oct | C2: 600 | D2: 30 | E2: 570
C4: =SUM(C2:C3) -> 600 | E4: =SUM(E2:E3) -> 570

Sheet Misfits
A1: Link | B1: Date | C1: Paid to Misfits (₹) | D1: Post Comission (20%) | E1: TDS | F1: Final Amount (₹)
B2: October | C2: 2830 | D2: =C2 - (C2 * 20%) -> 2264 | E2: 0.02 | F2: =D2 - D2*E2 -> 2218.72

Sheet Membership
A1: Member Name | B1: Sports Type | C1: Membership Type | D1: Start Date | E1: Amount Collected
A2: Indian School of hospitality | B2: Pickleball and Box | C2: Collab Deal | D2: 45931 | E2: 18880
A3: Sunil | B3: Box Cricket | C3: 12 Slots | D3: Oct | E3: 10000
E4: =SUM(E2:E3) -> 28880
