Workbook

Sheet Summary
B2: Date: 1st - 31st Dec
B3: Particulars | C3: Amount
B4: Offline | C4: =SUM(C5,C6,C7,C8) -> 23250
B5: Rentals | C5: ='Offline & RG Community'!G33 -> 6150
B6: F&B | C6: ='Offline & RG Community'!H33 -> 460
B7: Product Sales | C7: 0
B8: Bookings | C8: ='Offline & RG Community'!E33 -> 16640
B9: Online: Third Party Platform | C9: =SUM(C10:C13) -> 54376
B10: Hudle | C10: =Hudle!C7 -> 38450
B11: Playo | C11: =Playo!C6 -> 6326
B12: District | C12: =District!C2 -> 6000
B13: Khelomore | C13: =Khelomore!C4 -> 3600
B14: Community | C14: =SUM(C16,C17,C18) -> 12399
B15: Courtly | C15: 0
B16: Sportomic | C16: =Sportomic!C6 -> 8100
B17: Rallygully Community games | C17: ='Offline & RG Community'!F33 -> 450
B18: Misfits Community | C18: =Misfits!C6 -> 3849
B19: Memberships | C19: =Memberships!D2 -> 10000
B20: Corporate Events | C20: 0
B21: Brand Activation | C21: ='Brand Activation'!C5 -> 23313
B22: Other Income | C22: 0
B23: Total Gross Revenue | C23: =sum(C4,C9,C14,C19,C20,C21,C22) -> 123338
B24: Total Net Revenue (Post Commissions) | C24: ='Offline & RG Community'!I33 + Hudle!E7 + Playo!F6 + Khelomore!E4 + District!F4 + Sportomic!C6 + 'Brand Activation'!C5 +Misfits!F6 +Memberships!D2 -> 117393.28
B25: Total Revenue post Taxes | C25: =C24/1.18 -> 99485.831
B26: Expenses
B27: Venue Manager + Cleaner | C27: 34100
B28: Marketing, Branding & Community | C28: 15000
B29: Total Expenses | C29: =C27+C28 -> 49100
B30: Net Profit (Revenue - Expenses) | C30: =C25-C29 -> 50385.831
B32: School's Profit Share (65%) | C32: =C30*65% -> 32750.79
B33: RallyGully's Profit Share (35%) | C33: =C30*35% -> 17635.041

Sheet Offline & RG Community
A1: Date | B1: Day | C1: Offline booking hours | D1: Discount Given | E1: Booking Revenue | F1: Community Revenue | G1: Paddle Rental | H1: F&B | I1: Total Revenue
A2: 45992 | B2: Monday | C2: 0 | D2: 0 | E2: 0 | F2: 0 | G2: 300 | I2: =SUM(E2:G2) -> 300
A3: 45993 | B3: Tuesday | C3: 0 | D3: 0 | E3: 0 | F3: 0 | G3: 200 | I3: =SUM(E3:G3) -> 200
A4: 45994 | B4: Wednesday | C4: 0 | D4: 0 | E4: 0 | F4: 450 | G4: 0 | I4: =SUM(E4:G4) -> 450
A5: 45995 | B5: Thursday | C5: 1 | D5: 0 | E5: 1200 | F5: 0 | G5: 50 | I5: =SUM(E5:G5) -> 1250
A6: 45996 | B6: Friday | C6: 0 | D6: 0 | E6: 0 | F6: 0 | G6: 0 | I6: =SUM(E6:G6) -> 0
A7: 45997 | B7: Saturday | C7: 1 | D7: 0 | E7: 900 | F7: 0 | G7: 300 | I7: =SUM(E7:G7) -> 1200
A8: 45998 | B8: Sunday | C8: 0 | D8: 0 | E8: 0 | F8: 0 | G8: 700 | I8: =SUM(E8:G8) -> 700
A9: 45999 | B9: Monday | C9: 0.5 | D9: 0 | E9: 600 | F9: 0 | G9: 0 | I9: =SUM(E9:G9) -> 600
A10: 46000 | B10: Tuesday | D10: 0 | I10: =SUM(E10:G10) -> 0
A11: 46001 | B11: Wednesday | D11: 0 | I11: =SUM(E11:G11) -> 0
A12: 46002 | B12: Thursday | D12: 0 | I12: =SUM(E12:G12) -> 0
A13: 46003 | B13: Friday | D13: 0 | I13: =SUM(E13:G13) -> 0
A14: 46004 | B14: Saturday | D14: 0 | I14: =SUM(E14:G14) -> 0
A15: 46005 | B15: Sunday | C15: 0 | D15: 0 | E15: 0 | F15: 0 | G15: 800 | H15: 0 | I15: =SUM(E15:H15) -> 800
A16: 46006 | B16: Monday | C16: 1 | D16: 0 | E16: 1200 | F16: 0 | G16: 0 | H16: 0 | I16: =SUM(E16:H16) -> 1200
A17: 46007 | B17: Tuesday | C17: 2 | D17: 0 | E17: 2160 | F17: 0 | G17: 0 | H17: 0 | I17: =SUM(E17:H17) -> 2160
A18: 46008 | B18: Wednesday | C18: 0 | D18: 0 | E18: 0 | F18: 0 | G18: 100 | H18: 0 | I18: =SUM(E18:H18) -> 100
A19: 46009 | B19: Thursday | C19: 1.5 | D19: 0 | E19: 1800 | F19: 0 | G19: 0 | H19: 0 | I19: =SUM(E19:H19) -> 1800
A20: 46010 | B20: Friday | C20: 0 | D20: 0 | E20: 0 | F20: 0 | G20: 400 | H20: 0 | I20: =SUM(E20:H20) -> 400
A21: 46011 | B21: Saturday | C21: 0 | D21: 0 | E21: 0 | F21: 0 | G21: 0 | H21: 0 | I21: =SUM(E21:H21) -> 0
A22: 46012 | B22: Sunday | C22: 1.5 | D22: 0 | E22: 1800 | F22: 0 | G22: 600 | H22: 0 | I22: =SUM(E22:H22) -> 2400
A23: 46013 | B23: Monday | C23: 1.5 | D23: 0 | E23: 1800 | F23: 0 | G23: 100 | H23: 0 | I23: =SUM(E23:H23) -> 1900
A24: 46014 | B24: Tuesday | C24: 1.5 | D24: 0 | E24: 1780 | F24: 0 | G24: 400 | H24: 0 | I24: =SUM(E24:H24) -> 2180
A25: 46015 | B25: Wednesday | C25: 0.5 | D25: 0 | E25: 600 | F25: 0 | G25: 0 | H25: 60 | I25: =SUM(E25:H25) -> 660
A26: 46016 | B26: Thursday | C26: 1.5 | D26: 0 | E26: 1600 | F26: 0 | G26: 0 | H26: 300 | I26: =SUM(E26:H26) -> 1900
... A32: 46022 | B32: Wednesday | C32: 0 | D32: 0 | E32: 0 | F32: 0 | G32: 0 | H32: 0 | I32: =SUM(E32:H32) -> 0
A33: Total | C33: =SUM(C2:C32) -> 14.5 | E33: =SUM(E2:E32) -> 16640 | F33: =SUM(F2:F32) -> 450 | G33: =SUM(G2:G32) -> 6150 | H33: =SUM(H2:H32) -> 460 | I33: =SUM(I2:I32) -> 23700

Sheet Hudle
A1: Link | B1: Date | C1: Paid to Hudle | D1: Commisions (Including GST) | E1: Net Revenue | F1: TDS | G1: TCS | H1: Amount
B2: 1 - 8 Dec | C2: 17400 | D2: 2262 | E2: =C2 - D2 -> 15138 | F2: 14.74 | G2: 73.72 | H2: 15049.55
B3: 9 - 16 Dec | C3: 1200 | D3: 156 | E3: =C3 - D3 -> 1044 | F3: 1.01 | G3: 5.08 | H3: 1037.9
B4: 16 - 23 Dec | C4: 4250 | D4: 559 | E4: =C4 - D4 -> 3691 | F4: 3.64 | G4: 18.22 | H4: 3719.14
B5: 23 - 30 Dec | C5: 15000 | D5: 1950 | E5: =C5 - D5 -> 13050 | F5: 12.7 | G5: 63.55 | H5: 12973.5
B6: 30 - 31 Dec | C6: 600 | D6: 79.92 | E6: =C6 - D6 -> 520.08 | F6: 0.52 | G6: 2.58 | H6: 516.98
C7: =SUM(C2:C6) -> 38450 | E7: =SUM(E2:E6) -> 33443.08 | H7: =SUM(H2:H6) -> 33297.07

Sheet Playo
A1: Link | B1: Date | C1: Paid to Playo (₹) | D1: Commissions (₹) | E1: GST (₹) | F1: Net Revenue | G1: TDS (₹) | H1: TCS (₹) | I1: Final Amount (₹)
B2: 1 - 6 Dec | C2: 1726 | D2: 200.2 | E2: 36.04 | F2: =C2 -D2-E2 -> 1489.76 | G2: 1.72 | H2: 8.63 | I2: 1479.41
B3: 7 - 21 Dec | C3: 4600 | D3: 322 | E3: 57.96 | F3: =C3 -D3-E3 -> 4220.04 | G3: 4.6 | H3: 23 | I3: 4192.44
B4: 22 - 31 Dec | C4: 0
C6: =SUM(C2:C4) -> 6326 | F6: =SUM(F2:F4) -> 5709.8 | I6: =SUM(I2:I4) -> 5671.85

Sheet Khelomore
A1: Link | B1: Date | C1: Paid to Khelomore (₹) | D1: Commissions (₹) | E1: Final Amount (₹)
B2: 1 - 31 Dec | C2: 3600 | D2: 180 | E2: =C2-D2 -> 3420
C4: =SUM(C2:C3) -> 3600 | D4: =SUM(D2:D3) -> 180 | E4: =SUM(E2:E3) -> 3420

Sheet District
A1: Link | B1: Date | C1: Paid to District | D1: Commissions (₹) | E1: GST on Commission | F1: Net Revenue | G1: TCS | H1: TDS | I1: Final Amount (₹)
B2: 1 - 31 Dec | C2: 6000 | D2: 120 | E2: 21.6 | F2: =C2 -D2-E2 -> 5858.4 | G2: 30 | H2: 6 | I2: 5882.4
B4: Total | C4: =SUM(C2) -> 6000 | F4: =SUM(F2) -> 5858.4 | I4: =SUM(I2) -> 5882.4

Sheet Misfits
A1: Link | B1: Date | C1: Paid to Misfits (₹) | D1: Post Comission (20%) | E1: TDS | F1: Final Amount (₹)
B2: 1 - 31st Dec | C2: 3849 | D2: 769.8 | E2: 61.58 | F2: =C2-D2-E2 -> 3017.62
C6: =SUM(C2) -> 3849 | F6: =C6-D6-E6 -> 3849

Sheet Sportomic
A1: Link | B1: Date | C1: Paid to Sportomic (₹) | D1: TDS | E1: Final Amount (₹)
B2: 1 - 31st Dec | C2: 8100
C6: =SUM(C2) -> 8100

Sheet Memberships
A1: Sports Type | B1: Membership Type | C1: Start Date | D1: Amount Collected
A2: Pickleball | B2: Coaching | C2: 46376 | D2: 10000

Sheet Brand Activation
A1: Date | B1: Brand Name | C1: Amount | D1: Type of collab
A2: 46011 | B2: Savikalpa | C2: 15000 | D2: Christmas Event
A3: 46011 | B3: Sweetlifey | C3: 4720 | D3: Christmas Event
A4: 46011 | B4: Ticket Sale | C4: 3593 | D4: Christmas Event
C5: =SUM(C2:C4) -> 23313

Sheet Other Income
A1: Coaching | B1: Sports | C1: Type | D1: Start Date | E1: Amount Collected
