Workbook

Sheet Summary
B2: 1 - 30 April
B3: Particulars | C3: Total | D3: Pickleball | E3: Turf | F3: Padel
B4: Pay & Play | C4: =sum(C5,C11) -> 280714.75 | D4: =sum(D5,D11) -> 32157.75 | E4: =sum(E5,E11) -> 164504 | F4: =sum(F5,F11) -> 84053
B5: Online | C5: =sum(C6:C10) -> 144764.75 | D5: =sum(D6:D10) -> 23611.75 | E5: =sum(E6:E10) -> 99368 | F5: =sum(F6:F10) -> 21785
B6: District | C6: =District!C3 -> 50364 | D6: =District!B5 -> 9209 | E6: =District!B6 -> 28168 | F6: =District!B7 -> 12987
B7: Hudle | C7: =Hudle!C7 -> 83759.25 | D7: =Hudle!B9 -> 11251.25 | E7: =Hudle!B10 -> 63710 | F7: =Hudle!B11 -> 8798
B8: Playo | C8: =Playo!C6 -> 10641.5 | D8: =Playo!B8 -> 3151.5 | E8: =Playo!B9 -> 7490 | F8: 0
B9: Khelomore | C9: 0 | D9: 0 | E9: 0 | F9: 0
B10: Zplys | C10: 0 | D10: 0 | E10: 0 | F10: 0
B11: Offline | C11: =sum(C12:C13) -> 135950 | D11: =sum(D12:D13) -> 8546 | E11: =sum(E12:E13) -> 65136 | F11: =sum(F12:F13) -> 62268
B12: Bookings | C12: =SUM(D12:F12) -> 96950 | D12: ='Offline & RG Community'!E33 -> 8546 | E12: ='Offline & RG Community'!F33 -> 26136 | F12: ='Offline & RG Community'!G33 -> 62268 | H12: =C11+C21+C14 -> 159778
B13: Memberships | C13: 39000 | D13: 0 | E13: =Memberships!E2 -> 39000 | F13: 0
B14: Community | C14: =sum(C15:C16) -> 15178 | D14: =sum(D15:D16) -> 0 | E14: =sum(E15:E16) -> 15178 | F14: =sum(F15:F16) -> 0
B15: Pickup games | C15: ='Offline & RG Community'!H33 -> 0 | D15: 0 | E15: 0 | F15: 0
B16: Social Events/Tournaments | C16: =SUM(D16:F16) -> 15178 | D16: 0 | E16: ='Offline & RG Community'!C38+'Offline & RG Community'!C39 -> 15178 | F16: 0
B17: Academy | C17: 0 | D17: 0 | E17: 0 | F17: 0
B18: Events & Partnership | C18: =sum(C19,C20) -> 0 | D18: =sum(D19) -> 0 | E18: =sum(E19) -> 0 | F18: =sum(F19) -> 0
B19: Corporate events | C19: 0 | D19: 0 | E19: 0 | F19: 0
B20: All B2B partnerships | C20: 0 | D20: 0 | E20: 0 | F20: 0
B21: Commerce | C21: =sum(C22:C24) -> 8650 | D21: =sum(D22:D24) -> 4550 | E21: =sum(E22:E24) -> 0 | F21: =sum(F22:F24) -> 4100
B22: Product rental | C22: ='Offline & RG Community'!I33+'Offline & RG Community'!J33 -> 8650 | D22: ='Offline & RG Community'!I33 -> 4550 | E22: 0 | F22: ='Offline & RG Community'!J33 -> 4100
B23: Product sales | C23: 0 | D23: 0 | E23: 0 | F23: 0
B24: F&B | C24: 0 | D24: 0 | E24: 0 | F24: 0
B25: Other Income | C25: 0 | D25: 0 | E25: 0 | F25: 0
B26: Total Gross Revenue | C26: =C4+C14+C21+C17+C18+C25 -> 304542.75 | D26: =D4+D14+D21+D17+D18+D25 -> 36707.75 | E26: =E4+E14+E21+E17+E18+E25 -> 179682 | F26: =F4+F14+F21+F17+F18+F25 -> 88153
B27: Total Net Revenue (Post Commissions) | C27: ='Offline & RG Community'!M33+'Offline & RG Community'!E40+Hudle!E7+District!F3+Playo!F6+Memberships!G2 -> 280112.88
B28: Total Revenue post GST | C28: =C27/1.18 -> 237383.79
B30: SD VIdya's Share | C30: =C28*60% -> 142430.28
B31: Our Share (RG + Commons) | C31: =C28*40% -> 94953.517

Sheet Offline & RG Community
A1: Date | B1: Day | C1: Offline booking hours | D1: Discount Given | F1: Booking Revenue | H1: Community Revenue | I1: Paddle Rental | J1: Padel Rental | K1: Total Revenue | L1: Payment Gateway | M1: Net Revenue
E2: Pickleball | F2: Padel | G2: Turf
A3: 1 Apr | B3: Wednesday | C3: 2.5 | D3: 20% and 25% | E3: 0 | F3: =1700 -> 1700 | G3: =1998 -> 1998 | H3: 0 | I3: 400 | J3: 200 | K3: =sum(E3:J3) -> 4298 | L3: =K3*2.5%*1.18 -> 126.791 | M3: =K3-L3 -> 4171.209
A4: 2 Apr | B4: Thursday | C4: 1.5 | D4: 20% and 25% | E4: 450 | F4: 1600 | G4: 0 | H4: 0 | I4: 100 | J4: 0 | K4: =sum(E4:J4) -> 2150 | L4: =K4*2.5%*1.18 -> 63.425 | M4: =K4-L4 -> 2086.575
A5: 3 Apr | B5: Friday | C5: 3 | D5: 20% and 25% | E5: 450 | F5: 3200 | G5: 0 | H5: 0 | I5: 450 | J5: 400 | K5: =sum(E5:J5) -> 4500 | L5: =K5*2.5%*1.18 -> 132.75 | M5: =K5-L5 -> 4367.25
A6: 4 Apr | B6: Saturday | C6: 0 | D6: 20% and 25% | E6: 0 | F6: 0 | G6: 0 | H6: 0 | I6: 200 | J6: 0 | K6: =sum(E6:J6) -> 200 | L6: =K6*2.5%*1.18 -> 5.9 | M6: =K6-L6 -> 194.1
A7: 5 Apr | B7: Sunday | C7: 1.5 | D7: 20% and 25% | E7: 900 | F7: 800 | G7: 0 | H7: 0 | I7: 600 | J7: 0 | K7: =sum(E7:J7) -> 2300 | L7: =K7*2.5%*1.18 -> 67.85 | M7: =K7-L7 -> 2232.15
A8: 6 Apr | B8: Monday | C8: 1 | D8: 20% and 25% | E8: 0 | F8: 0 | G8: 1500 | H8: 0 | I8: 0 | J8: 0 | K8: =sum(E8:J8) -> 1500 | L8: =K8*2.5%*1.18 -> 44.25 | M8: =K8-L8 -> 1455.75
A9: 7 Apr | B9: Tuesday | C9: 1.5 | D9: 20% and 25% | E9: 0 | F9: 2175 | G9: 0 | H9: 0 | I9: 0 | J9: 100 | K9: =sum(E9:J9) -> 2275 | L9: =K9*2.5%*1.18 -> 67.1125 | M9: =K9-L9 -> 2207.8875
A10: 8 Apr | B10: Wednesday | C10: 5 | D10: 20% and 25% | E10: =575 -> 575 | F10: 1635 | G10: 6807 | H10: 0 | I10: 100 | J10: 0 | K10: =sum(E10:J10) -> 9117 | L10: =K10*2.5%*1.18 -> 268.9515 | M10: =K10-L10 -> 8848.0485
A11: 9 Apr | B11: Thursday | C11: 0 | D11: 20% and 25% | E11: 0 | F11: 0 | G11: 0 | H11: 0 | I11: 0 | J11: 400 | K11: =sum(E11:J11) -> 400 | L11: =K11*2.5%*1.18 -> 11.8 | M11: =K11-L11 -> 388.2
A12: 10 Apr | B12: Friday | C12: 6 | D12: 20% and 25% | E12: 900 | F12: 1600 | G12: =3000 -> 3000 | H12: 0 | I12: 0 | J12: 0 | K12: =sum(E12:J12) -> 5500 | L12: =K12*2.5%*1.18 -> 162.25 | M12: =K12-L12 -> 5337.75
A13: 11 Apr | B13: Saturday | C13: 2.5 | D13: 20% and 25% | E13: 450 | F13: 1180 | G13: 1900 | H13: 0 | I13: 1100 | J13: 100 | K13: =sum(E13:J13) -> 4730 | L13: =K13*2.5%*1.18 -> 139.535 | M13: =K13-L13 -> 4590.465
A14: 12 Apr | B14: Sunday | C14: 1.5 | D14: 20% and 25% | E14: 1050 | F14: 0 | G14: 0 | H14: 0 | I14: 0 | J14: 0 | K14: =sum(E14:J14) -> 1050 | L14: =K14*2.5%*1.18 -> 30.975 | M14: =K14-L14 -> 1019.025
A15: 13 Apr | B15: Monday | C15: 1.5 | D15: 20% and 25% | E15: 0 | F15: 0 | G15: 3040 | H15: 0 | I15: 0 | J15: 0 | K15: =sum(E15:J15) -> 3040 | L15: =K15*2.5%*1.18 -> 89.68 | M15: =K15-L15 -> 2950.32
A16: 14 Apr | B16: Tuesday | C16: 1 | D16: 20% and 25% | E16: 0 | F16: 0 | G16: 3000 | H16: 0 | I16: 0 | J16: 0 | K16: =sum(E16:J16) -> 3000 | L16: =K16*2.5%*1.18 -> 88.5 | M16: =K16-L16 -> 2911.5
A17: 15 Apr | B17: Wednesday | C17: 2 | D17: 20% and 25% | E17: 0 | F17: 1350 | G17: 3000 | H17: 0 | I17: 0 | J17: 0 | K17: =sum(E17:J17) -> 4350 | L17: =K17*2.5%*1.18 -> 128.325 | M17: =K17-L17 -> 4221.675
A18: 16 Apr | B18: Thursday | C18: 1.5 | D18: 20% and 25% | E18: 0 | F18: 2400 | G18: 0 | H18: 0 | I18: 0 | J18: 600 | K18: =SUM(E18:J18) -> 3000 | L18: =K18*2.5%*1.18 -> 88.5 | M18: =K18-L18 -> 2911.5
A19: 17 Apr | B19: Friday | C19: 1 | D19: 20% and 25% | E19: 0 | F19: 1648 | G19: 0 | H19: 0 | I19: 0 | J19: 0 | K19: =SUM(E19:J19) -> 1648 | L19: =K19*2.5%*1.18 -> 48.616 | M19: =K19-L19 -> 1599.384
A20: 18 Apr | B20: Saturday | C20: 4.5 | D20: 20% and 25% | E20: 450 | F20: 1800 | G20: 4200 | H20: 0 | I20: 400 | J20: 100 | K20: =SUM(E20:J20) -> 6950 | L20: =K20*2.5%*1.18 -> 205.025 | M20: =K20-L20 -> 6744.975
A21: 19 Apr | B21: Sunday | C21: 0 | D21: 20% and 25% | E21: 0 | F21: 0 | G21: 0 | H21: 0 | I21: 0 | J21: 0 | K21: =SUM(E21:J21) -> 0 | L21: =K21*2.5%*1.18 -> 0 | M21: =K21-L21 -> 0
A22: 20 Apr | B22: Monday | C22: 0 | D22: 20% and 25% | E22: 0 | F22: 0 | G22: 0 | H22: 0 | I22: 0 | J22: 0 | K22: =SUM(E22:J22) -> 0 | L22: =K22*2.5%*1.18 -> 0 | M22: =K22-L22 -> 0
A23: 21 Apr | B23: Tuesday | C23: 2.5 | D23: 20% and 25% | E23: =675 -> 675 | F23: 0 | G23: 4230 | H23: 0 | I23: 0 | J23: 300 | K23: =SUM(E23:J23) -> 5205 | L23: =K23*2.5%*1.18 -> 153.5475 | M23: =K23-L23 -> 5051.4525
A24: 22 Apr | B24: Wednesday | C24: 1.5 | D24: 20% and 25% | E24: 0 | F24: 0 | G24: 2318 | H24: 0 | I24: 0 | J24: 500 | K24: =sum(E24:J24) -> 2818 | L24: =K24*2.5%*1.18 -> 83.131 | M24: =K24-L24 -> 2734.869
A25: 23 Apr | B25: Thursday | C25: 2.5 | D25: 20% and 25% | E25: 0 | F25: 1448 | G25: 4845 | H25: 0 | I25: 0 | J25: 350 | K25: =SUM(E25:J25) -> 6643 | L25: =K25*2.5%*1.18 -> 195.9685 | M25: =K25-L25 -> 6447.0315
A26: 24 Apr | B26: Friday | C26: 3.5 | D26: 20% and 25% | E26: 450 | F26: 1400 | G26: 3200 | H26: 0 | I26: 200 | J26: 400 | K26: =SUM(E26:J26) -> 5650 | L26: =K26*2.5%*1.18 -> 166.675 | M26: =K26-L26 -> 5483.325
A27: 25 Apr | B27: Saturday | C27: 3.5 | D27: 20% and 25% | E27: 1197 | F27: 0 | G27: 4495 | H27: 0 | I27: 0 | J27: 150 | K27: =SUM(E27:J27) -> 5842 | L27: =K27*2.5%*1.18 -> 172.339 | M27: =K27-L27 -> 5669.661
A28: 26 Apr | B28: Sunday | C28: 3.5 | D28: 20% and 25% | E28: 0 | F28: 800 | G28: 5998 | H28: 0 | I28: 200 | J28: 100 | K28: =SUM(E28:J28) -> 7098 | L28: =K28*2.5%*1.18 -> 209.391 | M28: =K28-L28 -> 6888.609
A29: 27 Apr | B29: Monday | C29: 0 | D29: 20% and 25% | E29: 0 | F29: 0 | G29: 0 | H29: 0 | I29: 0 | J29: 0 | K29: =SUM(E29:J29) -> 0 | L29: =K29*2.5%*1.18 -> 0 | M29: =K29-L29 -> 0
A30: 28 Apr | B30: Tuesday | C30: 3.5 | D30: 20% and 25% | E30: 999 | F30: 1400 | G30: 3040 | H30: 0 | I30: 400 | J30: 400 | K30: =SUM(E30:J30) -> 6239 | L30: =K30*2.5%*1.18 -> 184.0505 | M30: =K30-L30 -> 6054.9495
A31: 29 Apr | B31: Wednesday | C31: 1 | D31: 20% and 25% | E31: 0 | F31: 0 | G31: 5697 | H31: 0 | I31: 400 | J31: 0 | K31: =SUM(G31:J31) -> 6097 | L31: =K31*2.5%*1.18 -> 179.8615 | M31: =K31-L31 -> 5917.1385
A32: 30 Apr | B32: Thursday | C32: 0 | D32: 20% and 25% | E32: 0 | F32: 0 | G32: 0 | H32: 0 | I32: 0 | J32: 0 | K32: =SUM(E32:J32) -> 0 | L32: =K32*2.5%*1.18 -> 0 | M32: =K32-L32 -> 0
A33: Total | C33: =SUM(C3:C32) -> 59 | E33: =SUM(E3:E32) -> 8546 | F33: =SUM(F3:F32) -> 26136 | G33: =SUM(G3:G32) -> 62268 | H33: =SUM(H3:H32) -> 0 | I33: =SUM(I3:I32) -> 4550 | J33: =SUM(J3:J32) -> 4100 | K33: =SUM(K3:K32) -> 105600 | L33: =SUM(L3:L32) -> 3115.2 | M33: =SUM(M3:M32) -> 102484.8
A36: Community Event
A37: Date | B37: Day | C37: Amt | D37: Commission | E37: Net Amt | F37: Type of Event
A38: 46123 | B38: Sunday | C38: 8928 | D38: =C38*19.3% -> 1723.104 | E38: =C38-D38 -> 7204.896 | F38: Run+Pickle
A39: 46137 | B39: Sunday | C39: 6250 | D39: =C39*60% -> 3750 | E39: =C39-D39 -> 2500 | F39: Recess Club
C40: =SUM(C38:C39) -> 15178 | E40: =SUM(E38:E39) -> 9704.896

Sheet Hudle
A1: Link | B1: Date | C1: Paid to Hudle | D1: Commisions (Including GST) | E1: Net Revenue | F1: TDS | G1: TCS | H1: Amount
B2: 1 - 7 Apr | C2: 23018 | D2: 2992.35 | E2: =C2-D2 -> 20025.65 | F2: 19.5 | G2: 97.53 | H2: 19908.64
B3: 7 - 14 Apr | C3: 16765.5 | D3: 2179.52 | E3: =C3-D3 -> 14585.98 | F3: 14.2 | G3: 71.04 | H3: 14500.74
B4: 15 - 21 Apr | C4: 20063.25 | D4: 2608.23 | E4: =C4-D4 -> 17455.02 | F4: 17 | G4: 85.01 | H4: 17353.01
B5: 21- 28 Apr | C5: 20223.5 | D5: 2629 | E5: =C5-D5 -> 17594.5 | F5: 17 | G5: 85.6 | H5: 17187
B6: 28 - 30 Apr | C6: 3689 | D6: 479 | E6: =C6-D6 -> 3210 | F6: 3 | G6: 15 | H6: 2921
B7: Total | C7: =SUM(C2:C6) -> 83759.25 | E7: =SUM(E2:E6) -> 72871.15 | H7: =SUM(H2:H6) -> 71870.39
A9: Pickleball | B9: =C7-B10-B11 -> 11251.25
A10: Turf | B10: 63710
A11: Padel | B11: 8798

Sheet District
A1: Link | B1: Date | C1: Paid to District | D1: Commissions (₹) | E1: GST on Commission | F1: Net Revenue | G1: TCS | H1: TDS | I1: Final Amount (₹)
B2: 1 - 30 Apr | C2: 50364 | D2: 2272 | E2: 409 | F2: =C2-D2-E2 -> 47683 | G2: 1046 | H2: 249 | I2: 46324
B3: Total | C3: =SUM(C2) -> 50364 | F3: =SUM(F2) -> 47683 | I3: =SUM(I2) -> 46324
A5: Pickleball | B5: =C3-B6-B7 -> 9209
A6: Turf | B6: =2747+2897+1748+899+1998+2697+3896+5893+1898+1498+1997 -> 28168
A7: Padel | B7: =1998+2997+2997+1998+2997 -> 12987

Sheet Playo
A1: Link | B1: Date | C1: Paid to Playo (₹) | D1: Commissions (₹) | E1: GST (₹) | F1: Net Revenue | G1: TDS (₹) | H1: TCS (₹) | I1: Final Amount (₹)
B2: 1 - 5 Apr | C2: 675 | D2: 63 | E2: 11.4 | F2: =C2-D2-E2 -> 600.6 | G2: 0.68 | H2: 3.38 | I2: 596.6
B3: 6 - 12 Apr | C3: 4722.5 | D3: 398.79 | E3: 71.78 | F3: =C3-D3-E3 -> 4251.93 | G3: 3.07 | H3: 15.38 | I3: 2585.37
B4: 13 - 30 Apr | C4: 5244 | D4: 489 | E4: 88 | F4: =C4-D4-E4 -> 4667 | G4: 1.4 | H4: 7 | I4: 812.8
B6: Total | C6: =sum(C2:C4) -> 10641.5 | F6: =sum(F2:F4) -> 9519.53 | I6: =sum(I2:I4) -> 3994.77
A8: Pickleball | B8: =C6-B9-B10 -> 3151.5
A9: Turf | B9: 7490
A10: Padel | B10: 0

Sheet Memberships
A1: Member Name | B1: Sports Type | C1: Membership Type | D1: Start Date | E1: Amount Collected | F1: Payment Gateway | G1: Net Revenue
A2: Nikhil | B2: Football | C2: Rally Pack (15) | D2: 46113 | E2: 39000 | F2: =E2*2.5%*1.18 -> 1150.5 | G2: =E2-F2 -> 37849.5
